Workbook

Sheet 연간
A1: 쿠쿠레브어드바이저즈 Model
A2: 모를 땐 보수적으로 | B2: (단위: 백만엔) | C2: 8월 결산 · 일본 기준 · 2026.4Q = 2026년 8월 결산기 4분기 | Y2: (추정: 파란 글씨 = 직접 입력)
A3: 항목 | B3: 참고 | C3: 2024.1Q | D3: 2024.2Q | E3: 2024.3Q | F3: 2024.4Q | G3: 2025.1Q | H3: 2025.2Q | I3: 2025.3Q | J3: 2025.4Q | K3: 2026.1Q | L3: 2026.2Q | M3: 2026.3Q | N3: 2026.4Q | O3: 2017 | P3: 2018 | Q3: 2019 | R3: 2020 | S3: 2021 | T3: 2022 | U3: 2023 | V3: 2024 | W3: 2025 | X3: 2026 | Y3: 2027(MW) | Z3: 2028(MW) | AA3: 2029(MW) | AB3: 2030(MW) | AC3: 2031(MW)
A4: 매출액 | B4: MW 직접 입력 | F4: 219.337 | G4: 681.93 | H4: 972.877 | I4: 314.592 | J4: 585.647 | K4: 730.585 | L4: 178.465 | M4: 2226.174 | N4: 3885.273 | V4: 1269.627 | W4: 2555.046 | X4: 7020.497 | Y4: =IF(COUNT(Y7)=0,"",SUM(Y7)) | Z4: =IF(COUNT(Z7)=0,"",SUM(Z7)) | AA4: =IF(COUNT(AA7)=0,"",SUM(AA7)) | AB4: =IF(COUNT(AB7)=0,"",SUM(AB7)) | AC4: =IF(COUNT(AC7)=0,"",SUM(AC7))
A5: YoY | G5: =IF(OR(G4="",C4=""),"",IFERROR(G4/C4-1,"")) | H5: =IF(OR(H4="",D4=""),"",IFERROR(H4/D4-1,"")) | I5: =IF(OR(I4="",E4=""),"",IFERROR(I4/E4-1,"")) | J5: =IF(OR(J4="",F4=""),"",IFERROR(J4/F4-1,"")) | K5: =IF(OR(K4="",G4=""),"",IFERROR(K4/G4-1,"")) | L5: =IF(OR(L4="",H4=""),"",IFERROR(L4/H4-1,"")) | M5: =IF(OR(M4="",I4=""),"",IFERROR(M4/I4-1,"")) | N5: =IF(OR(N4="",J4=""),"",IFERROR(N4/J4-1,"")) | P5: =IF(OR(P4="",O4=""),"",IFERROR(P4/O4-1,"")) | Q5: =IF(OR(Q4="",P4=""),"",IFERROR(Q4/P4-1,"")) | R5: =IF(OR(R4="",Q4=""),"",IFERROR(R4/Q4-1,"")) | S5: =IF(OR(S4="",R4=""),"",IFERROR(S4/R4-1,"")) | T5: =IF(OR(T4="",S4=""),"",IFERROR(T4/S4-1,"")) | U5: =IF(OR(U4="",T4=""),"",IFERROR(U4/T4-1,"")) | V5: =IF(OR(V4="",U4=""),"",IFERROR(V4/U4-1,"")) | W5: =IF(OR(W4="",V4=""),"",IFERROR(W4/V4-1,"")) | ... AC5: =IF(OR(AC4="",AB4=""),"",IFERROR(AC4/AB4-1,""))
A6: 제품별 매출 분류 | B6: 사업보고서 매출실적
A7: (제품별 매출 미공시 — 직접 입력)
A8: 비중 | C8: =IF(OR(C7="",C4=""),"",IFERROR(C7/C4,"")) | D8: =IF(OR(D7="",D4=""),"",IFERROR(D7/D4,"")) | E8: =IF(OR(E7="",E4=""),"",IFERROR(E7/E4,"")) | F8: =IF(OR(F7="",F4=""),"",IFERROR(F7/F4,"")) | G8: =IF(OR(G7="",G4=""),"",IFERROR(G7/G4,"")) | H8: =IF(OR(H7="",H4=""),"",IFERROR(H7/H4,"")) | I8: =IF(OR(I7="",I4=""),"",IFERROR(I7/I4,"")) | J8: =IF(OR(J7="",J4=""),"",IFERROR(J7/J4,"")) | ... AC8: =IF(OR(AC7="",AC4=""),"",IFERROR(AC7/AC4,""))
A9: YoY | G9: =IF(OR(G7="",C7=""),"",IFERROR(G7/C7-1,"")) | H9: =IF(OR(H7="",D7=""),"",IFERROR(H7/D7-1,"")) | I9: =IF(OR(I7="",E7=""),"",IFERROR(I7/E7-1,"")) | J9: =IF(OR(J7="",F7=""),"",IFERROR(J7/F7-1,"")) | K9: =IF(OR(K7="",G7=""),"",IFERROR(K7/G7-1,"")) | L9: =IF(OR(L7="",H7=""),"",IFERROR(L7/H7-1,"")) | M9: =IF(OR(M7="",I7=""),"",IFERROR(M7/I7-1,"")) | N9: =IF(OR(N7="",J7=""),"",IFERROR(N7/J7-1,"")) | P9: =IF(OR(P7="",O7=""),"",IFERROR(P7/O7-1,"")) | Q9: =IF(OR(Q7="",P7=""),"",IFERROR(Q7/P7-1,"")) | R9: =IF(OR(R7="",Q7=""),"",IFERROR(R7/Q7-1,"")) | S9: =IF(OR(S7="",R7=""),"",IFERROR(S7/R7-1,"")) | T9: =IF(OR(T7="",S7=""),"",IFERROR(T7/S7-1,"")) | U9: =IF(OR(U7="",T7=""),"",IFERROR(U7/T7-1,"")) | V9: =IF(OR(V7="",U7=""),"",IFERROR(V7/U7-1,"")) | W9: =IF(OR(W7="",V7=""),"",IFERROR(W7/V7-1,"")) | ... AC9: =IF(OR(AC7="",AB7=""),"",IFERROR(AC7/AB7-1,""))
A10: 매출원가
A11: 전체 매출원가 | F11: 93.727 | G11: 255.855 | H11: 627.894 | I11: 179.79 | J11: 372.086 | K11: 331.295 | L11: 103.926 | M11: 1597.534 | N11: 3171.325 | V11: 420.184 | W11: 1435.625 | X11: 5204.08
A12: YoY | G12: =IF(OR(G11="",C11=""),"",IF(C11<=0,"",IFERROR(G11/C11-1,""))) | H12: =IF(OR(H11="",D11=""),"",IF(D11<=0,"",IFERROR(H11/D11-1,""))) | I12: =IF(OR(I11="",E11=""),"",IF(E11<=0,"",IFERROR(I11/E11-1,""))) | J12: =IF(OR(J11="",F11=""),"",IF(F11<=0,"",IFERROR(J11/F11-1,""))) | K12: =IF(OR(K11="",G11=""),"",IF(G11<=0,"",IFERROR(K11/G11-1,""))) | L12: =IF(OR(L11="",H11=""),"",IF(H11<=0,"",IFERROR(L11/H11-1,""))) | M12: =IF(OR(M11="",I11=""),"",IF(I11<=0,"",IFERROR(M11/I11-1,""))) | N12: =IF(OR(N11="",J11=""),"",IF(J11<=0,"",IFERROR(N11/J11-1,""))) | P12: =IF(OR(P11="",O11=""),"",IF(O11<=0,"",IFERROR(P11/O11-1,""))) | Q12: =IF(OR(Q11="",P11=""),"",IF(P11<=0,"",IFERROR(Q11/P11-1,""))) | R12: =IF(OR(R11="",Q11=""),"",IF(Q11<=0,"",IFERROR(R11/Q11-1,""))) | S12: =IF(OR(S11="",R11=""),"",IF(R11<=0,"",IFERROR(S11/R11-1,""))) | T12: =IF(OR(T11="",S11=""),"",IF(S11<=0,"",IFERROR(T11/S11-1,""))) | U12: =IF(OR(U11="",T11=""),"",IF(T11<=0,"",IFERROR(U11/T11-1,""))) | V12: =IF(OR(V11="",U11=""),"",IF(U11<=0,"",IFERROR(V11/U11-1,""))) | W12: =IF(OR(W11="",V11=""),"",IF(V11<=0,"",IFERROR(W11/V11-1,""))) | ... AC12: =IF(OR(AC11="",AB11=""),"",IF(AB11<=0,"",IFERROR(AC11/AB11-1,"")))
A13: 매출총이익 | C13: =IF(OR(C4="",C11=""),"",IFERROR(C4-C11,"")) | D13: =IF(OR(D4="",D11=""),"",IFERROR(D4-D11,"")) | E13: =IF(OR(E4="",E11=""),"",IFERROR(E4-E11,"")) | F13: =IF(OR(F4="",F11=""),"",IFERROR(F4-F11,"")) | G13: =IF(OR(G4="",G11=""),"",IFERROR(G4-G11,"")) | H13: =IF(OR(H4="",H11=""),"",IFERROR(H4-H11,"")) | I13: =IF(OR(I4="",I11=""),"",IFERROR(I4-I11,"")) | J13: =IF(OR(J4="",J11=""),"",IFERROR(J4-J11,"")) | ... X13: =IF(OR(X4="",X11=""),"",IFERROR(X4-X11,""))
A14: GPM | C14: =IF(OR(C13="",C4=""),"",IFERROR(C13/C4,"")) | D14: =IF(OR(D13="",D4=""),"",IFERROR(D13/D4,"")) | E14: =IF(OR(E13="",E4=""),"",IFERROR(E13/E4,"")) | F14: =IF(OR(F13="",F4=""),"",IFERROR(F13/F4,"")) | G14: =IF(OR(G13="",G4=""),"",IFERROR(G13/G4,"")) | H14: =IF(OR(H13="",H4=""),"",IFERROR(H13/H4,"")) | I14: =IF(OR(I13="",I4=""),"",IFERROR(I13/I4,"")) | J14: =IF(OR(J13="",J4=""),"",IFERROR(J13/J4,"")) | ... AC14: =IF(OR(AC13="",AC4=""),"",IFERROR(AC13/AC4,""))
A15: YoY | G15: =IF(OR(G13="",C13=""),"",IF(C13<=0,"",IFERROR(G13/C13-1,""))) | H15: =IF(OR(H13="",D13=""),"",IF(D13<=0,"",IFERROR(H13/D13-1,""))) | I15: =IF(OR(I13="",E13=""),"",IF(E13<=0,"",IFERROR(I13/E13-1,""))) | J15: =IF(OR(J13="",F13=""),"",IF(F13<=0,"",IFERROR(J13/F13-1,""))) | K15: =IF(OR(K13="",G13=""),"",IF(G13<=0,"",IFERROR(K13/G13-1,""))) | L15: =IF(OR(L13="",H13=""),"",IF(H13<=0,"",IFERROR(L13/H13-1,""))) | M15: =IF(OR(M13="",I13=""),"",IF(I13<=0,"",IFERROR(M13/I13-1,""))) | N15: =IF(OR(N13="",J13=""),"",IF(J13<=0,"",IFERROR(N13/J13-1,""))) | P15: =IF(OR(P13="",O13=""),"",IF(O13<=0,"",IFERROR(P13/O13-1,""))) | Q15: =IF(OR(Q13="",P13=""),"",IF(P13<=0,"",IFERROR(Q13/P13-1,""))) | R15: =IF(OR(R13="",Q13=""),"",IF(Q13<=0,"",IFERROR(R13/Q13-1,""))) | S15: =IF(OR(S13="",R13=""),"",IF(R13<=0,"",IFERROR(S13/R13-1,""))) | T15: =IF(OR(T13="",S13=""),"",IF(S13<=0,"",IFERROR(T13/S13-1,""))) | U15: =IF(OR(U13="",T13=""),"",IF(T13<=0,"",IFERROR(U13/T13-1,""))) | V15: =IF(OR(V13="",U13=""),"",IF(U13<=0,"",IFERROR(V13/U13-1,""))) | W15: =IF(OR(W13="",V13=""),"",IF(V13<=0,"",IFERROR(W13/V13-1,""))) | ... AC15: =IF(OR(AC13="",AB13=""),"",IF(AB13<=0,"",IFERROR(AC13/AB13-1,"")))
A16: 판매관리비
A17: 전체 판관비 | F17: 135.333 | G17: 118.964 | H17: 124.32 | I17: 124.284 | J17: 138.854 | K17: 155.948 | L17: 159.973 | M17: 177.053 | N17: 179.065 | V17: 428.488 | W17: 506.422 | X17: 672.039
A18: YoY | G18: =IF(OR(G17="",C17=""),"",IF(C17<=0,"",IFERROR(G17/C17-1,""))) | H18: =IF(OR(H17="",D17=""),"",IF(D17<=0,"",IFERROR(H17/D17-1,""))) | I18: =IF(OR(I17="",E17=""),"",IF(E17<=0,"",IFERROR(I17/E17-1,""))) | J18: =IF(OR(J17="",F17=""),"",IF(F17<=0,"",IFERROR(J17/F17-1,""))) | K18: =IF(OR(K17="",G17=""),"",IF(G17<=0,"",IFERROR(K17/G17-1,""))) | L18: =IF(OR(L17="",H17=""),"",IF(H17<=0,"",IFERROR(L17/H17-1,""))) | M18: =IF(OR(M17="",I17=""),"",IF(I17<=0,"",IFERROR(M17/I17-1,""))) | N18: =IF(OR(N17="",J17=""),"",IF(J17<=0,"",IFERROR(N17/J17-1,""))) | P18: =IF(OR(P17="",O17=""),"",IF(O17<=0,"",IFERROR(P17/O17-1,""))) | Q18: =IF(OR(Q17="",P17=""),"",IF(P17<=0,"",IFERROR(Q17/P17-1,""))) | R18: =IF(OR(R17="",Q17=""),"",IF(Q17<=0,"",IFERROR(R17/Q17-1,""))) | S18: =IF(OR(S17="",R17=""),"",IF(R17<=0,"",IFERROR(S17/R17-1,""))) | T18: =IF(OR(T17="",S17=""),"",IF(S17<=0,"",IFERROR(T17/S17-1,""))) | U18: =IF(OR(U17="",T17=""),"",IF(T17<=0,"",IFERROR(U17/T17-1,""))) | V18: =IF(OR(V17="",U17=""),"",IF(U17<=0,"",IFERROR(V17/U17-1,""))) | W18: =IF(OR(W17="",V17=""),"",IF(V17<=0,"",IFERROR(W17/V17-1,""))) | ... AC18: =IF(OR(AC17="",AB17=""),"",IF(AB17<=0,"",IFERROR(AC17/AB17-1,"")))
A19: 영업이익 | B19: MW = 매출 × OPM | F19: -9.723 | G19: 307.11 | H19: 220.662 | I19: 10.52 | J19: 74.706 | K19: 243.341 | L19: -85.434 | M19: 451.587 | N19: 534.882 | V19: 420.954 | W19: 612.998 | X19: 1144.376 | Y19: =IF(OR(Y4="",Y20=""),"",IFERROR(Y4*Y20,"")) | Z19: =IF(OR(Z4="",Z20=""),"",IFERROR(Z4*Z20,"")) | AA19: =IF(OR(AA4="",AA20=""),"",IFERROR(AA4*AA20,"")) | AB19: =IF(OR(AB4="",AB20=""),"",IFERROR(AB4*AB20,"")) | AC19: =IF(OR(AC4="",AC20=""),"",IFERROR(AC4*AC20,""))
A20: OPM | B20: MW 입력 | C20: =IF(OR(C19="",C4=""),"",IFERROR(C19/C4,"")) | D20: =IF(OR(D19="",D4=""),"",IFERROR(D19/D4,"")) | E20: =IF(OR(E19="",E4=""),"",IFERROR(E19/E4,"")) | F20: =IF(OR(F19="",F4=""),"",IFERROR(F19/F4,"")) | G20: =IF(OR(G19="",G4=""),"",IFERROR(G19/G4,"")) | H20: =IF(OR(H19="",H4=""),"",IFERROR(H19/H4,"")) | I20: =IF(OR(I19="",I4=""),"",IFERROR(I19/I4,"")) | J20: =IF(OR(J19="",J4=""),"",IFERROR(J19/J4,"")) | ... X20: =IF(OR(X19="",X4=""),"",IFERROR(X19/X4,""))
A21: 증가율 | G21: =IF(OR(G19="",C19=""),"",IFERROR(G19/C19-1,"")) | H21: =IF(OR(H19="",D19=""),"",IFERROR(H19/D19-1,"")) | I21: =IF(OR(I19="",E19=""),"",IFERROR(I19/E19-1,"")) | J21: =IF(OR(J19="",F19=""),"",IFERROR(J19/F19-1,"")) | K21: =IF(OR(K19="",G19=""),"",IFERROR(K19/G19-1,"")) | L21: =IF(OR(L19="",H19=""),"",IFERROR(L19/H19-1,"")) | M21: =IF(OR(M19="",I19=""),"",IFERROR(M19/I19-1,"")) | N21: =IF(OR(N19="",J19=""),"",IFERROR(N19/J19-1,"")) | P21: =IF(OR(P19="",O19=""),"",IFERROR(P19/O19-1,"")) | Q21: =IF(OR(Q19="",P19=""),"",IFERROR(Q19/P19-1,"")) | R21: =IF(OR(R19="",Q19=""),"",IFERROR(R19/Q19-1,"")) | S21: =IF(OR(S19="",R19=""),"",IFERROR(S19/R19-1,"")) | T21: =IF(OR(T19="",S19=""),"",IFERROR(T19/S19-1,"")) | U21: =IF(OR(U19="",T19=""),"",IFERROR(U19/T19-1,"")) | V21: =IF(OR(V19="",U19=""),"",IFERROR(V19/U19-1,"")) | W21: =IF(OR(W19="",V19=""),"",IFERROR(W19/V19-1,"")) | ... AC21: =IF(OR(AC19="",AB19=""),"",IFERROR(AC19/AB19-1,""))
A22: 비용의 성격별 분류 | B22: 참고 데이터
A23: 총 판관비 | O23: =IF(O17="","",O17) | P23: =IF(P17="","",P17) | Q23: =IF(Q17="","",Q17) | R23: =IF(R17="","",R17) | S23: =IF(S17="","",S17) | T23: =IF(T17="","",T17) | U23: =IF(U17="","",U17) | V23: =IF(V17="","",V17) | ... X23: =IF(X17="","",X17)
A24: 급여 | B24: 고정비
A25: % of Sales | O25: =IF(OR(O24="",O4=""),"",IFERROR(O24/O4,"")) | P25: =IF(OR(P24="",P4=""),"",IFERROR(P24/P4,"")) | Q25: =IF(OR(Q24="",Q4=""),"",IFERROR(Q24/Q4,"")) | R25: =IF(OR(R24="",R4=""),"",IFERROR(R24/R4,"")) | S25: =IF(OR(S24="",S4=""),"",IFERROR(S24/S4,"")) | T25: =IF(OR(T24="",T4=""),"",IFERROR(T24/T4,"")) | U25: =IF(OR(U24="",U4=""),"",IFERROR(U24/U4,"")) | V25: =IF(OR(V24="",V4=""),"",IFERROR(V24/V4,"")) | ... X25: =IF(OR(X24="",X4=""),"",IFERROR(X24/X4,""))
A26: 감가상각비 | B26: 고정비
A27: % of Sales | O27: =IF(OR(O26="",O4=""),"",IFERROR(O26/O4,"")) | P27: =IF(OR(P26="",P4=""),"",IFERROR(P26/P4,"")) | Q27: =IF(OR(Q26="",Q4=""),"",IFERROR(Q26/Q4,"")) | R27: =IF(OR(R26="",R4=""),"",IFERROR(R26/R4,"")) | S27: =IF(OR(S26="",S4=""),"",IFERROR(S26/S4,"")) | T27: =IF(OR(T26="",T4=""),"",IFERROR(T26/T4,"")) | U27: =IF(OR(U26="",U4=""),"",IFERROR(U26/U4,"")) | V27: =IF(OR(V26="",V4=""),"",IFERROR(V26/V4,"")) | ... X27: =IF(OR(X26="",X4=""),"",IFERROR(X26/X4,""))
A28: 지급수수료 | B28: 고정비
A29: % of Sales | O29: =IF(OR(O28="",O4=""),"",IFERROR(O28/O4,"")) | P29: =IF(OR(P28="",P4=""),"",IFERROR(P28/P4,"")) | Q29: =IF(OR(Q28="",Q4=""),"",IFERROR(Q28/Q4,"")) | R29: =IF(OR(R28="",R4=""),"",IFERROR(R28/R4,"")) | S29: =IF(OR(S28="",S4=""),"",IFERROR(S28/S4,"")) | T29: =IF(OR(T28="",T4=""),"",IFERROR(T28/T4,"")) | U29: =IF(OR(U28="",U4=""),"",IFERROR(U28/U4,"")) | V29: =IF(OR(V28="",V4=""),"",IFERROR(V28/V4,"")) | ... X29: =IF(OR(X28="",X4=""),"",IFERROR(X28/X4,""))
A30: 연구개발비 | B30: 변동비
A31: % of Sales | O31: =IF(OR(O30="",O4=""),"",IFERROR(O30/O4,"")) | P31: =IF(OR(P30="",P4=""),"",IFERROR(P30/P4,"")) | Q31: =IF(OR(Q30="",Q4=""),"",IFERROR(Q30/Q4,"")) | R31: =IF(OR(R30="",R4=""),"",IFERROR(R30/R4,"")) | S31: =IF(OR(S30="",S4=""),"",IFERROR(S30/S4,"")) | T31: =IF(OR(T30="",T4=""),"",IFERROR(T30/T4,"")) | U31: =IF(OR(U30="",U4=""),"",IFERROR(U30/U4,"")) | V31: =IF(OR(V30="",V4=""),"",IFERROR(V30/V4,"")) | ... X31: =IF(OR(X30="",X4=""),"",IFERROR(X30/X4,""))
A32: 기타비용 | B32: 변동비 | O32: =IF(OR(O23="",O24="",O26="",O28="",O30=""),"",IFERROR(O23-O24-O26-O28-O30,"")) | P32: =IF(OR(P23="",P24="",P26="",P28="",P30=""),"",IFERROR(P23-P24-P26-P28-P30,"")) | Q32: =IF(OR(Q23="",Q24="",Q26="",Q28="",Q30=""),"",IFERROR(Q23-Q24-Q26-Q28-Q30,"")) | R32: =IF(OR(R23="",R24="",R26="",R28="",R30=""),"",IFERROR(R23-R24-R26-R28-R30,"")) | S32: =IF(OR(S23="",S24="",S26="",S28="",S30=""),"",IFERROR(S23-S24-S26-S28-S30,"")) | T32: =IF(OR(T23="",T24="",T26="",T28="",T30=""),"",IFERROR(T23-T24-T26-T28-T30,"")) | U32: =IF(OR(U23="",U24="",U26="",U28="",U30=""),"",IFERROR(U23-U24-U26-U28-U30,"")) | V32: =IF(OR(V23="",V24="",V26="",V28="",V30=""),"",IFERROR(V23-V24-V26-V28-V30,"")) | ... X32: =IF(OR(X23="",X24="",X26="",X28="",X30=""),"",IFERROR(X23-X24-X26-X28-X30,""))
A33: % of Sales | O33: =IF(OR(O32="",O4=""),"",IFERROR(O32/O4,"")) | P33: =IF(OR(P32="",P4=""),"",IFERROR(P32/P4,"")) | Q33: =IF(OR(Q32="",Q4=""),"",IFERROR(Q32/Q4,"")) | R33: =IF(OR(R32="",R4=""),"",IFERROR(R32/R4,"")) | S33: =IF(OR(S32="",S4=""),"",IFERROR(S32/S4,"")) | T33: =IF(OR(T32="",T4=""),"",IFERROR(T32/T4,"")) | U33: =IF(OR(U32="",U4=""),"",IFERROR(U32/U4,"")) | V33: =IF(OR(V32="",V4=""),"",IFERROR(V32/V4,"")) | ... X33: =IF(OR(X32="",X4=""),"",IFERROR(X32/X4,""))
A34: 당기순이익 추정
A35: 특별이익 | F35: 0 | G35: 0 | H35: 0 | I35: 0 | J35: 23.736 | K35: 1.08 | L35: 0 | M35: 0 | N35: 0 | V35: 29.3 | W35: 23.736 | X35: 1.08 | Y35: =IF(OR(Y4="",Y36=""),"",IFERROR(Y4*Y36,"")) | Z35: =IF(OR(Z4="",Z36=""),"",IFERROR(Z4*Z36,"")) | AA35: =IF(OR(AA4="",AA36=""),"",IFERROR(AA4*AA36,"")) | AB35: =IF(OR(AB4="",AB36=""),"",IFERROR(AB4*AB36,"")) | AC35: =IF(OR(AC4="",AC36=""),"",IFERROR(AC4*AC36,""))
A36: % of Sales | B36: MW = 최근 3년 평균 | C36: =IF(OR(C35="",C4=""),"",IFERROR(C35/C4,"")) | D36: =IF(OR(D35="",D4=""),"",IFERROR(D35/D4,"")) | E36: =IF(OR(E35="",E4=""),"",IFERROR(E35/E4,"")) | F36: =IF(OR(F35="",F4=""),"",IFERROR(F35/F4,"")) | G36: =IF(OR(G35="",G4=""),"",IFERROR(G35/G4,"")) | H36: =IF(OR(H35="",H4=""),"",IFERROR(H35/H4,"")) | I36: =IF(OR(I35="",I4=""),"",IFERROR(I35/I4,"")) | J36: =IF(OR(J35="",J4=""),"",IFERROR(J35/J4,"")) | ... X36: =IF(OR(X35="",X4=""),"",IFERROR(X35/X4,"")) | Y36: =IFERROR(AVERAGE(V36,W36,X36),"") | Z36: =Y36 | AA36: =Z36 | AB36: =AA36 | AC36: =AB36
A37: 특별손실 | F37: 0 | J37: 0 | V37: 16.939 | W37: 0 | Y37: =IF(OR(Y4="",Y38=""),"",IFERROR(Y4*Y38,"")) | Z37: =IF(OR(Z4="",Z38=""),"",IFERROR(Z4*Z38,"")) | AA37: =IF(OR(AA4="",AA38=""),"",IFERROR(AA4*AA38,"")) | AB37: =IF(OR(AB4="",AB38=""),"",IFERROR(AB4*AB38,"")) | AC37: =IF(OR(AC4="",AC38=""),"",IFERROR(AC4*AC38,""))
A38: % of Sales | C38: =IF(OR(C37="",C4=""),"",IFERROR(C37/C4,"")) | D38: =IF(OR(D37="",D4=""),"",IFERROR(D37/D4,"")) | E38: =IF(OR(E37="",E4=""),"",IFERROR(E37/E4,"")) | F38: =IF(OR(F37="",F4=""),"",IFERROR(F37/F4,"")) | G38: =IF(OR(G37="",G4=""),"",IFERROR(G37/G4,"")) | H38: =IF(OR(H37="",H4=""),"",IFERROR(H37/H4,"")) | I38: =IF(OR(I37="",I4=""),"",IFERROR(I37/I4,"")) | J38: =IF(OR(J37="",J4=""),"",IFERROR(J37/J4,"")) | ... X38: =IF(OR(X37="",X4=""),"",IFERROR(X37/X4,"")) | Y38: =IFERROR(AVERAGE(V38,W38,X38),"") | Z38: =Y38 | AA38: =Z38 | AB38: =AA38 | AC38: =AB38
A39: 영업외수익 | F39: -0.169 | G39: 0.514 | H39: 0.63 | I39: 0.31 | J39: 2.3 | K39: 0.696 | L39: 3.092 | M39: 0.789 | N39: 4.24 | V39: 0.992 | W39: 3.754 | X39: 8.817 | Y39: =IF(OR(Y4="",Y40=""),"",IFERROR(Y4*Y40,"")) | Z39: =IF(OR(Z4="",Z40=""),"",IFERROR(Z4*Z40,"")) | AA39: =IF(OR(AA4="",AA40=""),"",IFERROR(AA4*AA40,"")) | AB39: =IF(OR(AB4="",AB40=""),"",IFERROR(AB4*AB40,"")) | AC39: =IF(OR(AC4="",AC40=""),"",IFERROR(AC4*AC40,""))
A40: % of Sales | C40: =IF(OR(C39="",C4=""),"",IFERROR(C39/C4,"")) | D40: =IF(OR(D39="",D4=""),"",IFERROR(D39/D4,"")) | E40: =IF(OR(E39="",E4=""),"",IFERROR(E39/E4,"")) | F40: =IF(OR(F39="",F4=""),"",IFERROR(F39/F4,"")) | G40: =IF(OR(G39="",G4=""),"",IFERROR(G39/G4,"")) | H40: =IF(OR(H39="",H4=""),"",IFERROR(H39/H4,"")) | I40: =IF(OR(I39="",I4=""),"",IFERROR(I39/I4,"")) | J40: =IF(OR(J39="",J4=""),"",IFERROR(J39/J4,"")) | ... X40: =IF(OR(X39="",X4=""),"",IFERROR(X39/X4,"")) | Y40: =IFERROR(AVERAGE(V40,W40,X40),"") | Z40: =Y40 | AA40: =Z40 | AB40: =AA40 | AC40: =AB40
A41: 영업외비용 | F41: 3.03 | G41: 16.354 | H41: 1.303 | I41: 0.12 | J41: 0.375 | K41: 41.408 | L41: 13.506 | M41: 28.194 | N41: 12.438 | V41: 5.537 | W41: 18.152 | X41: 95.546 | Y41: =IF(OR(Y4="",Y42=""),"",IFERROR(Y4*Y42,"")) | Z41: =IF(OR(Z4="",Z42=""),"",IFERROR(Z4*Z42,"")) | AA41: =IF(OR(AA4="",AA42=""),"",IFERROR(AA4*AA42,"")) | AB41: =IF(OR(AB4="",AB42=""),"",IFERROR(AB4*AB42,"")) | AC41: =IF(OR(AC4="",AC42=""),"",IFERROR(AC4*AC42,""))
A42: % of Sales | C42: =IF(OR(C41="",C4=""),"",IFERROR(C41/C4,"")) | D42: =IF(OR(D41="",D4=""),"",IFERROR(D41/D4,"")) | E42: =IF(OR(E41="",E4=""),"",IFERROR(E41/E4,"")) | F42: =IF(OR(F41="",F4=""),"",IFERROR(F41/F4,"")) | G42: =IF(OR(G41="",G4=""),"",IFERROR(G41/G4,"")) | H42: =IF(OR(H41="",H4=""),"",IFERROR(H41/H4,"")) | I42: =IF(OR(I41="",I4=""),"",IFERROR(I41/I4,"")) | J42: =IF(OR(J41="",J4=""),"",IFERROR(J41/J4,"")) | ... X42: =IF(OR(X41="",X4=""),"",IFERROR(X41/X4,"")) | Y42: =IFERROR(AVERAGE(V42,W42,X42),"") | Z42: =Y42 | AA42: =Z42 | AB42: =AA42 | AC42: =AB42
A43: 법인세비용차감전순이익(손실) | F43: -12.923 | G43: 291.27 | H43: 219.989 | I43: 10.71 | J43: 100.368 | K43: 203.71 | L43: -95.849 | M43: 424.183 | N43: 526.685 | V43: 428.77 | W43: 622.337 | X43: 1058.729 | Y43: =IF(OR(Y19=""),"",IFERROR(Y19+N(Y35)-N(Y37)+N(Y39)-N(Y41),"")) | Z43: =IF(OR(Z19=""),"",IFERROR(Z19+N(Z35)-N(Z37)+N(Z39)-N(Z41),"")) | AA43: =IF(OR(AA19=""),"",IFERROR(AA19+N(AA35)-N(AA37)+N(AA39)-N(AA41),"")) | AB43: =IF(OR(AB19=""),"",IFERROR(AB19+N(AB35)-N(AB37)+N(AB39)-N(AB41),"")) | AC43: =IF(OR(AC19=""),"",IFERROR(AC19+N(AC35)-N(AC37)+N(AC39)-N(AC41),""))
A44: YoY | G44: =IF(OR(G43="",C43=""),"",IF(C43<=0,"",IFERROR(G43/C43-1,""))) | H44: =IF(OR(H43="",D43=""),"",IF(D43<=0,"",IFERROR(H43/D43-1,""))) | I44: =IF(OR(I43="",E43=""),"",IF(E43<=0,"",IFERROR(I43/E43-1,""))) | J44: =IF(OR(J43="",F43=""),"",IF(F43<=0,"",IFERROR(J43/F43-1,""))) | K44: =IF(OR(K43="",G43=""),"",IF(G43<=0,"",IFERROR(K43/G43-1,""))) | L44: =IF(OR(L43="",H43=""),"",IF(H43<=0,"",IFERROR(L43/H43-1,""))) | M44: =IF(OR(M43="",I43=""),"",IF(I43<=0,"",IFERROR(M43/I43-1,""))) | N44: =IF(OR(N43="",J43=""),"",IF(J43<=0,"",IFERROR(N43/J43-1,""))) | P44: =IF(OR(P43="",O43=""),"",IF(O43<=0,"",IFERROR(P43/O43-1,""))) | Q44: =IF(OR(Q43="",P43=""),"",IF(P43<=0,"",IFERROR(Q43/P43-1,""))) | R44: =IF(OR(R43="",Q43=""),"",IF(Q43<=0,"",IFERROR(R43/Q43-1,""))) | S44: =IF(OR(S43="",R43=""),"",IF(R43<=0,"",IFERROR(S43/R43-1,""))) | T44: =IF(OR(T43="",S43=""),"",IF(S43<=0,"",IFERROR(T43/S43-1,""))) | U44: =IF(OR(U43="",T43=""),"",IF(T43<=0,"",IFERROR(U43/T43-1,""))) | V44: =IF(OR(V43="",U43=""),"",IF(U43<=0,"",IFERROR(V43/U43-1,""))) | W44: =IF(OR(W43="",V43=""),"",IF(V43<=0,"",IFERROR(W43/V43-1,""))) | ... AC44: =IF(OR(AC43="",AB43=""),"",IF(AB43<=0,"",IFERROR(AC43/AB43-1,"")))
A45: 법인세비용(수익) | F45: -17.858 | G45: 90.913 | H45: 69.942 | I45: 3.436 | J45: 12.336 | K45: 63.052 | L45: -27.973 | M45: 130.281 | N45: 150.11 | V45: 140.292 | W45: 176.627 | X45: 315.47 | Y45: =IF(OR(Y43="",Y46=""),"",IFERROR(MAX(Y43,0)*Y46,"")) | Z45: =IF(OR(Z43="",Z46=""),"",IFERROR(MAX(Z43,0)*Z46,"")) | AA45: =IF(OR(AA43="",AA46=""),"",IFERROR(MAX(AA43,0)*AA46,"")) | AB45: =IF(OR(AB43="",AB46=""),"",IFERROR(MAX(AB43,0)*AB46,"")) | AC45: =IF(OR(AC43="",AC46=""),"",IFERROR(MAX(AC43,0)*AC46,""))
A46: 법인세율 | B46: MW 기본 30% | C46: =IF(OR(C45="",C43=""),"",IFERROR(C45/C43,"")) | D46: =IF(OR(D45="",D43=""),"",IFERROR(D45/D43,"")) | E46: =IF(OR(E45="",E43=""),"",IFERROR(E45/E43,"")) | F46: =IF(OR(F45="",F43=""),"",IFERROR(F45/F43,"")) | G46: =IF(OR(G45="",G43=""),"",IFERROR(G45/G43,"")) | H46: =IF(OR(H45="",H43=""),"",IFERROR(H45/H43,"")) | I46: =IF(OR(I45="",I43=""),"",IFERROR(I45/I43,"")) | J46: =IF(OR(J45="",J43=""),"",IFERROR(J45/J43,"")) | ... X46: =IF(OR(X45="",X43=""),"",IFERROR(X45/X43,"")) | Y46: 0.3 | Z46: 0.3 | AA46: 0.3 | AB46: 0.3 | AC46: 0.3
A47: 당기순이익(손실) | F47: 4.935 | G47: 200.356 | H47: 150.047 | I47: 7.275 | J47: 88.031 | K47: 140.657 | L47: -67.875 | M47: 293.902 | N47: 376.574 | V47: 288.477 | W47: 445.709 | X47: 743.258 | Y47: =IF(OR(Y43=""),"",IFERROR(Y43-Y45,"")) | Z47: =IF(OR(Z43=""),"",IFERROR(Z43-Z45,"")) | AA47: =IF(OR(AA43=""),"",IFERROR(AA43-AA45,"")) | AB47: =IF(OR(AB43=""),"",IFERROR(AB43-AB45,"")) | AC47: =IF(OR(AC43=""),"",IFERROR(AC43-AC45,""))
A48: YoY | G48: =IF(OR(G47="",C47=""),"",IF(C47<=0,"",IFERROR(G47/C47-1,""))) | H48: =IF(OR(H47="",D47=""),"",IF(D47<=0,"",IFERROR(H47/D47-1,""))) | I48: =IF(OR(I47="",E47=""),"",IF(E47<=0,"",IFERROR(I47/E47-1,""))) | J48: =IF(OR(J47="",F47=""),"",IF(F47<=0,"",IFERROR(J47/F47-1,""))) | K48: =IF(OR(K47="",G47=""),"",IF(G47<=0,"",IFERROR(K47/G47-1,""))) | L48: =IF(OR(L47="",H47=""),"",IF(H47<=0,"",IFERROR(L47/H47-1,""))) | M48: =IF(OR(M47="",I47=""),"",IF(I47<=0,"",IFERROR(M47/I47-1,""))) | N48: =IF(OR(N47="",J47=""),"",IF(J47<=0,"",IFERROR(N47/J47-1,""))) | P48: =IF(OR(P47="",O47=""),"",IF(O47<=0,"",IFERROR(P47/O47-1,""))) | Q48: =IF(OR(Q47="",P47=""),"",IF(P47<=0,"",IFERROR(Q47/P47-1,""))) | R48: =IF(OR(R47="",Q47=""),"",IF(Q47<=0,"",IFERROR(R47/Q47-1,""))) | S48: =IF(OR(S47="",R47=""),"",IF(R47<=0,"",IFERROR(S47/R47-1,""))) | T48: =IF(OR(T47="",S47=""),"",IF(S47<=0,"",IFERROR(T47/S47-1,""))) | U48: =IF(OR(U47="",T47=""),"",IF(T47<=0,"",IFERROR(U47/T47-1,""))) | V48: =IF(OR(V47="",U47=""),"",IF(U47<=0,"",IFERROR(V47/U47-1,""))) | W48: =IF(OR(W47="",V47=""),"",IF(V47<=0,"",IFERROR(W47/V47-1,""))) | ... AC48: =IF(OR(AC47="",AB47=""),"",IF(AB47<=0,"",IFERROR(AC47/AB47-1,"")))
A49: 지배주주 순이익 | F49: 4.935 | G49: 200.356 | H49: 150.047 | I49: 7.275 | J49: 88.031 | K49: 140.657 | L49: -67.875 | M49: 293.902 | N49: 376.574 | V49: 288.477 | W49: 445.709 | X49: 743.258 | Y49: =IF(OR(Y47="",Y50=""),"",IFERROR(Y47*Y50,"")) | Z49: =IF(OR(Z47="",Z50=""),"",IFERROR(Z47*Z50,"")) | AA49: =IF(OR(AA47="",AA50=""),"",IFERROR(AA47*AA50,"")) | AB49: =IF(OR(AB47="",AB50=""),"",IFERROR(AB47*AB50,"")) | AC49: =IF(OR(AC47="",AC50=""),"",IFERROR(AC47*AC50,""))
A50: 지배주주 순이익률 | B50: MW 기본 100% | C50: =IF(OR(C49="",C47=""),"",IFERROR(C49/C47,"")) | D50: =IF(OR(D49="",D47=""),"",IFERROR(D49/D47,"")) | E50: =IF(OR(E49="",E47=""),"",IFERROR(E49/E47,"")) | F50: =IF(OR(F49="",F47=""),"",IFERROR(F49/F47,"")) | G50: =IF(OR(G49="",G47=""),"",IFERROR(G49/G47,"")) | H50: =IF(OR(H49="",H47=""),"",IFERROR(H49/H47,"")) | I50: =IF(OR(I49="",I47=""),"",IFERROR(I49/I47,"")) | J50: =IF(OR(J49="",J47=""),"",IFERROR(J49/J47,"")) | ... X50: =IF(OR(X49="",X47=""),"",IFERROR(X49/X47,"")) | Y50: 1 | Z50: 1 | AA50: 1 | AB50: 1 | AC50: 1
A51: 지배주주 순이익 YoY | G51: =IF(OR(G49="",C49=""),"",IF(C49<=0,"",IFERROR(G49/C49-1,""))) | H51: =IF(OR(H49="",D49=""),"",IF(D49<=0,"",IFERROR(H49/D49-1,""))) | I51: =IF(OR(I49="",E49=""),"",IF(E49<=0,"",IFERROR(I49/E49-1,""))) | J51: =IF(OR(J49="",F49=""),"",IF(F49<=0,"",IFERROR(J49/F49-1,""))) | K51: =IF(OR(K49="",G49=""),"",IF(G49<=0,"",IFERROR(K49/G49-1,""))) | L51: =IF(OR(L49="",H49=""),"",IF(H49<=0,"",IFERROR(L49/H49-1,""))) | M51: =IF(OR(M49="",I49=""),"",IF(I49<=0,"",IFERROR(M49/I49-1,""))) | N51: =IF(OR(N49="",J49=""),"",IF(J49<=0,"",IFERROR(N49/J49-1,""))) | P51: =IF(OR(P49="",O49=""),"",IF(O49<=0,"",IFERROR(P49/O49-1,""))) | Q51: =IF(OR(Q49="",P49=""),"",IF(P49<=0,"",IFERROR(Q49/P49-1,""))) | R51: =IF(OR(R49="",Q49=""),"",IF(Q49<=0,"",IFERROR(R49/Q49-1,""))) | S51: =IF(OR(S49="",R49=""),"",IF(R49<=0,"",IFERROR(S49/R49-1,""))) | T51: =IF(OR(T49="",S49=""),"",IF(S49<=0,"",IFERROR(T49/S49-1,""))) | U51: =IF(OR(U49="",T49=""),"",IF(T49<=0,"",IFERROR(U49/T49-1,""))) | V51: =IF(OR(V49="",U49=""),"",IF(U49<=0,"",IFERROR(V49/U49-1,""))) | W51: =IF(OR(W49="",V49=""),"",IF(V49<=0,"",IFERROR(W49/V49-1,""))) | ... AC51: =IF(OR(AC49="",AB49=""),"",IF(AB49<=0,"",IFERROR(AC49/AB49-1,"")))
A52: 목표주가 산출
A53: 현재 주가 ()
A54: 발행주식수 (보통주)
A55: 시가총액 (백만엔) | B55: =IF(OR(B53="",B54=""),"",B53*B54/1000000.0)
A56: OPM | O56: =IF(O20="","",O20) | P56: =IF(P20="","",P20) | Q56: =IF(Q20="","",Q20) | R56: =IF(R20="","",R20) | S56: =IF(S20="","",S20) | T56: =IF(T20="","",T20) | U56: =IF(U20="","",U20) | V56: =IF(V20="","",V20) | ... AC56: =IF(AC20="","",AC20)
A57: 지배주주 순이익 증가율 | P57: =IF(OR(P49="",O49=""),"",IFERROR(P49/O49-1,"")) | Q57: =IF(OR(Q49="",P49=""),"",IFERROR(Q49/P49-1,"")) | R57: =IF(OR(R49="",Q49=""),"",IFERROR(R49/Q49-1,"")) | S57: =IF(OR(S49="",R49=""),"",IFERROR(S49/R49-1,"")) | T57: =IF(OR(T49="",S49=""),"",IFERROR(T49/S49-1,"")) | U57: =IF(OR(U49="",T49=""),"",IFERROR(U49/T49-1,"")) | V57: =IF(OR(V49="",U49=""),"",IFERROR(V49/U49-1,"")) | W57: =IF(OR(W49="",V49=""),"",IFERROR(W49/V49-1,"")) | ... AC57: =IF(OR(AC49="",AB49=""),"",IFERROR(AC49/AB49-1,""))
A58: P/E (현재 주가) | B58: 시총 ÷ 지배순이익 | X58: =IF(OR($B$55="",X49=""),"",IFERROR($B$55/X49,"")) | Y58: =IF(OR($B$55="",Y49=""),"",IFERROR($B$55/Y49,"")) | Z58: =IF(OR($B$55="",Z49=""),"",IFERROR($B$55/Z49,"")) | AA58: =IF(OR($B$55="",AA49=""),"",IFERROR($B$55/AA49,"")) | AB58: =IF(OR($B$55="",AB49=""),"",IFERROR($B$55/AB49,"")) | AC58: =IF(OR($B$55="",AC49=""),"",IFERROR($B$55/AC49,""))
A59: Target P/E | B59: 직접 입력
A60: EPS | B60: 지배순이익 ÷ 주식수 | O60: =IF(OR(O49="",$B$54=""),"",IFERROR(O49*1000000.0/$B$54,"")) | P60: =IF(OR(P49="",$B$54=""),"",IFERROR(P49*1000000.0/$B$54,"")) | Q60: =IF(OR(Q49="",$B$54=""),"",IFERROR(Q49*1000000.0/$B$54,"")) | R60: =IF(OR(R49="",$B$54=""),"",IFERROR(R49*1000000.0/$B$54,"")) | S60: =IF(OR(S49="",$B$54=""),"",IFERROR(S49*1000000.0/$B$54,"")) | T60: =IF(OR(T49="",$B$54=""),"",IFERROR(T49*1000000.0/$B$54,"")) | U60: =IF(OR(U49="",$B$54=""),"",IFERROR(U49*1000000.0/$B$54,"")) | V60: =IF(OR(V49="",$B$54=""),"",IFERROR(V49*1000000.0/$B$54,"")) | ... AC60: =IF(OR(AC49="",$B$54=""),"",IFERROR(AC49*1000000.0/$B$54,""))
A61: 목표주가 | Y61: =IF(OR(Y60="",Y59=""),"",IFERROR(Y60*Y59,"")) | Z61: =IF(OR(Z60="",Z59=""),"",IFERROR(Z60*Z59,"")) | AA61: =IF(OR(AA60="",AA59=""),"",IFERROR(AA60*AA59,"")) | AB61: =IF(OR(AB60="",AB59=""),"",IFERROR(AB60*AB59,"")) | AC61: =IF(OR(AC60="",AC59=""),"",IFERROR(AC60*AC59,""))
A62: 상승여력 | Y62: =IF(OR(Y61="",$B$53=""),"",IFERROR(Y61/$B$53-1,"")) | Z62: =IF(OR(Z61="",$B$53=""),"",IFERROR(Z61/$B$53-1,"")) | AA62: =IF(OR(AA61="",$B$53=""),"",IFERROR(AA61/$B$53-1,"")) | AB62: =IF(OR(AB61="",$B$53=""),"",IFERROR(AB61/$B$53-1,"")) | AC62: =IF(OR(AC61="",$B$53=""),"",IFERROR(AC61/$B$53-1,""))
A63: 자산가치 산출 | B63: 최신 분기 BS
A64: 현금및현금성자산 | X64: ='재무상태표'!G6 | Y64: ='재무상태표'!G6 | Z64: ='재무상태표'!G6 | AA64: ='재무상태표'!G6 | AB64: ='재무상태표'!G6 | AC64: ='재무상태표'!G6
A65: 단기금융상품 | X65: ='재무상태표'!G7 | Y65: ='재무상태표'!G7 | Z65: ='재무상태표'!G7 | AA65: ='재무상태표'!G7 | AB65: ='재무상태표'!G7 | AC65: ='재무상태표'!G7
A66: 투자부동산 | X66: ='재무상태표'!G14 | Y66: ='재무상태표'!G14 | Z66: ='재무상태표'!G14 | AA66: ='재무상태표'!G14 | AB66: ='재무상태표'!G14 | AC66: ='재무상태표'!G14
A67: 지배자본 | X67: ='재무상태표'!G31 | Y67: ='재무상태표'!G31 | Z67: ='재무상태표'!G31 | AA67: ='재무상태표'!G31 | AB67: ='재무상태표'!G31 | AC67: ='재무상태표'!G31
A68: 부채 | X68: ='재무상태표'!G27 | Y68: ='재무상태표'!G27 | Z68: ='재무상태표'!G27 | AA68: ='재무상태표'!G27 | AB68: ='재무상태표'!G27 | AC68: ='재무상태표'!G27
A69: 부채비율 | X69: =IF(OR(X68="",X67=""),"",IFERROR(X68/X67,"")) | Y69: =IF(OR(Y68="",Y67=""),"",IFERROR(Y68/Y67,"")) | Z69: =IF(OR(Z68="",Z67=""),"",IFERROR(Z68/Z67,"")) | AA69: =IF(OR(AA68="",AA67=""),"",IFERROR(AA68/AA67,"")) | AB69: =IF(OR(AB68="",AB67=""),"",IFERROR(AB68/AB67,"")) | AC69: =IF(OR(AC68="",AC67=""),"",IFERROR(AC68/AC67,""))
A70: 자산가치 | B70: 현금+단기금융+투자부동산 | X70: =SUM(X64,X65,X66) | Y70: =SUM(Y64,Y65,Y66) | Z70: =SUM(Z64,Z65,Z66) | AA70: =SUM(AA64,AA65,AA66) | AB70: =SUM(AB64,AB65,AB66) | AC70: =SUM(AC64,AC65,AC66)
A71: 기업가치 산출
A72: 목표 시가총액 (P/E) | B72: 지배순이익 × Target P/E | Y72: =IF(OR(Y49="",Y59=""),"",IFERROR(Y49*Y59,"")) | Z72: =IF(OR(Z49="",Z59=""),"",IFERROR(Z49*Z59,"")) | AA72: =IF(OR(AA49="",AA59=""),"",IFERROR(AA49*AA59,"")) | AB72: =IF(OR(AB49="",AB59=""),"",IFERROR(AB49*AB59,"")) | AC72: =IF(OR(AC49="",AC59=""),"",IFERROR(AC49*AC59,""))
A73: 기업가치 | B73: 목표시총 + 자산가치 | Y73: =IF(OR(Y72=""),"",IFERROR(Y72+Y70,"")) | Z73: =IF(OR(Z72=""),"",IFERROR(Z72+Z70,"")) | AA73: =IF(OR(AA72=""),"",IFERROR(AA72+AA70,"")) | AB73: =IF(OR(AB72=""),"",IFERROR(AB72+AB70,"")) | AC73: =IF(OR(AC72=""),"",IFERROR(AC72+AC70,""))
A74: 현재 시가총액 | Y74: =$B$55 | Z74: =$B$55 | AA74: =$B$55 | AB74: =$B$55 | AC74: =$B$55
A75: 상승여력 | Y75: =IF(OR(Y73="",Y74=""),"",IFERROR(Y73/Y74-1,"")) | Z75: =IF(OR(Z73="",Z74=""),"",IFERROR(Z73/Z74-1,"")) | AA75: =IF(OR(AA73="",AA74=""),"",IFERROR(AA73/AA74-1,"")) | AB75: =IF(OR(AB73="",AB74=""),"",IFERROR(AB73/AB74-1,"")) | AC75: =IF(OR(AC73="",AC74=""),"",IFERROR(AC73/AC74-1,""))
A77: 출처
A78: 결산단신 XBRL(TDnet·JPX 보관소) — 쓴 문서는 '출처' 시트
A79: 분기 = 누계에서 앞 분기를 뺀 3개월 값
A80: 주가: 야후 파이낸스 일봉
A82: 손익계산서 · 전 항목 | B82: 분기 = 3개월 단독
A83: 항목 | B83: 참고 | C83: 2024.1Q | D83: 2024.2Q | E83: 2024.3Q | F83: 2024.4Q | G83: 2025.1Q | H83: 2025.2Q | I83: 2025.3Q | J83: 2025.4Q | K83: 2026.1Q | L83: 2026.2Q | M83: 2026.3Q | N83: 2026.4Q | O83: 2017 | P83: 2018 | Q83: 2019 | R83: 2020 | S83: 2021 | T83: 2022 | U83: 2023 | V83: 2024 | W83: 2025 | X83: 2026 | Y83: 2027(MW) | Z83: 2028(MW) | AA83: 2029(MW) | AB83: 2030(MW) | AC83: 2031(MW)
A84: 매출액 | F84: 219.337 | G84: 681.93 | H84: 972.877 | I84: 314.592 | J84: 585.647 | K84: 730.585 | L84: 178.465 | M84: 2226.174 | N84: 3885.273 | V84: 219.337 | W84: 585.647 | X84: 3885.273
A85: YoY | B85: 전년 같은 분기·전년 대비 | G85: =IF(OR(G84="",C84=""),"",IF(C84<=0,"",IFERROR(G84/C84-1,""))) | H85: =IF(OR(H84="",D84=""),"",IF(D84<=0,"",IFERROR(H84/D84-1,""))) | I85: =IF(OR(I84="",E84=""),"",IF(E84<=0,"",IFERROR(I84/E84-1,""))) | J85: =IF(OR(J84="",F84=""),"",IF(F84<=0,"",IFERROR(J84/F84-1,""))) | K85: =IF(OR(K84="",G84=""),"",IF(G84<=0,"",IFERROR(K84/G84-1,""))) | L85: =IF(OR(L84="",H84=""),"",IF(H84<=0,"",IFERROR(L84/H84-1,""))) | M85: =IF(OR(M84="",I84=""),"",IF(I84<=0,"",IFERROR(M84/I84-1,""))) | N85: =IF(OR(N84="",J84=""),"",IF(J84<=0,"",IFERROR(N84/J84-1,""))) | V85: =IF(OR(V84="",U84=""),"",IF(U84<=0,"",IFERROR(V84/U84-1,""))) | W85: =IF(OR(W84="",V84=""),"",IF(V84<=0,"",IFERROR(W84/V84-1,""))) | X85: =IF(OR(X84="",W84=""),"",IF(W84<=0,"",IFERROR(X84/W84-1,"")))
A86: 매출원가 | F86: 93.727 | G86: 255.855 | H86: 627.894 | I86: 179.79 | J86: 372.086 | K86: 331.295 | L86: 103.926 | M86: 1597.534 | N86: 3171.325 | V86: 93.727 | W86: 372.086 | X86: 3171.325
A87: YoY | B87: 전년 같은 분기·전년 대비 | G87: =IF(OR(G86="",C86=""),"",IF(G86*C86<=0,"",IFERROR(G86/C86-1,""))) | H87: =IF(OR(H86="",D86=""),"",IF(H86*D86<=0,"",IFERROR(H86/D86-1,""))) | I87: =IF(OR(I86="",E86=""),"",IF(I86*E86<=0,"",IFERROR(I86/E86-1,""))) | J87: =IF(OR(J86="",F86=""),"",IF(J86*F86<=0,"",IFERROR(J86/F86-1,""))) | K87: =IF(OR(K86="",G86=""),"",IF(K86*G86<=0,"",IFERROR(K86/G86-1,""))) | L87: =IF(OR(L86="",H86=""),"",IF(L86*H86<=0,"",IFERROR(L86/H86-1,""))) | M87: =IF(OR(M86="",I86=""),"",IF(M86*I86<=0,"",IFERROR(M86/I86-1,""))) | N87: =IF(OR(N86="",J86=""),"",IF(N86*J86<=0,"",IFERROR(N86/J86-1,""))) | V87: =IF(OR(V86="",U86=""),"",IF(V86*U86<=0,"",IFERROR(V86/U86-1,""))) | W87: =IF(OR(W86="",V86=""),"",IF(W86*V86<=0,"",IFERROR(W86/V86-1,""))) | X87: =IF(OR(X86="",W86=""),"",IF(X86*W86<=0,"",IFERROR(X86/W86-1,"")))
A88: 매출총이익 | F88: 125.609 | G88: 426.075 | H88: 344.982 | I88: 134.803 | J88: 213.56 | K88: 399.289 | L88: 74.539 | M88: 628.64 | N88: 713.948 | V88: 125.609 | W88: 213.56 | X88: 713.948
A89: YoY | B89: 전년 같은 분기·전년 대비 | G89: =IF(OR(G88="",C88=""),"",IF(C88<=0,"",IFERROR(G88/C88-1,""))) | H89: =IF(OR(H88="",D88=""),"",IF(D88<=0,"",IFERROR(H88/D88-1,""))) | I89: =IF(OR(I88="",E88=""),"",IF(E88<=0,"",IFERROR(I88/E88-1,""))) | J89: =IF(OR(J88="",F88=""),"",IF(F88<=0,"",IFERROR(J88/F88-1,""))) | K89: =IF(OR(K88="",G88=""),"",IF(G88<=0,"",IFERROR(K88/G88-1,""))) | L89: =IF(OR(L88="",H88=""),"",IF(H88<=0,"",IFERROR(L88/H88-1,""))) | M89: =IF(OR(M88="",I88=""),"",IF(I88<=0,"",IFERROR(M88/I88-1,""))) | N89: =IF(OR(N88="",J88=""),"",IF(J88<=0,"",IFERROR(N88/J88-1,""))) | V89: =IF(OR(V88="",U88=""),"",IF(U88<=0,"",IFERROR(V88/U88-1,""))) | W89: =IF(OR(W88="",V88=""),"",IF(V88<=0,"",IFERROR(W88/V88-1,""))) | X89: =IF(OR(X88="",W88=""),"",IF(W88<=0,"",IFERROR(X88/W88-1,"")))
A90: 판매비와 관리비 | F90: 135.333 | G90: 118.964 | H90: 124.32 | I90: 124.284 | J90: 138.854 | K90: 155.948 | L90: 159.973 | M90: 177.053 | N90: 179.065 | V90: 135.333 | W90: 138.854 | X90: 179.065
A91: YoY | B91: 전년 같은 분기·전년 대비 | G91: =IF(OR(G90="",C90=""),"",IF(G90*C90<=0,"",IFERROR(G90/C90-1,""))) | H91: =IF(OR(H90="",D90=""),"",IF(H90*D90<=0,"",IFERROR(H90/D90-1,""))) | I91: =IF(OR(I90="",E90=""),"",IF(I90*E90<=0,"",IFERROR(I90/E90-1,""))) | J91: =IF(OR(J90="",F90=""),"",IF(J90*F90<=0,"",IFERROR(J90/F90-1,""))) | K91: =IF(OR(K90="",G90=""),"",IF(K90*G90<=0,"",IFERROR(K90/G90-1,""))) | L91: =IF(OR(L90="",H90=""),"",IF(L90*H90<=0,"",IFERROR(L90/H90-1,""))) | M91: =IF(OR(M90="",I90=""),"",IF(M90*I90<=0,"",IFERROR(M90/I90-1,""))) | N91: =IF(OR(N90="",J90=""),"",IF(N90*J90<=0,"",IFERROR(N90/J90-1,""))) | V91: =IF(OR(V90="",U90=""),"",IF(V90*U90<=0,"",IFERROR(V90/U90-1,""))) | W91: =IF(OR(W90="",V90=""),"",IF(W90*V90<=0,"",IFERROR(W90/V90-1,""))) | X91: =IF(OR(X90="",W90=""),"",IF(X90*W90<=0,"",IFERROR(X90/W90-1,"")))
A92: 영업이익 | F92: -9.723 | G92: 307.11 | H92: 220.662 | I92: 10.52 | J92: 74.706 | K92: 243.341 | L92: -85.434 | M92: 451.587 | N92: 534.882 | V92: -9.723 | W92: 74.706 | X92: 534.882
A93: OPM | B93: 영업이익 ÷ 매출 | F93: =IF(OR(F92="",F84=""),"",IF(F84<=0,"",IFERROR(F92/F84,""))) | G93: =IF(OR(G92="",G84=""),"",IF(G84<=0,"",IFERROR(G92/G84,""))) | H93: =IF(OR(H92="",H84=""),"",IF(H84<=0,"",IFERROR(H92/H84,""))) | I93: =IF(OR(I92="",I84=""),"",IF(I84<=0,"",IFERROR(I92/I84,""))) | J93: =IF(OR(J92="",J84=""),"",IF(J84<=0,"",IFERROR(J92/J84,""))) | K93: =IF(OR(K92="",K84=""),"",IF(K84<=0,"",IFERROR(K92/K84,""))) | L93: =IF(OR(L92="",L84=""),"",IF(L84<=0,"",IFERROR(L92/L84,""))) | M93: =IF(OR(M92="",M84=""),"",IF(M84<=0,"",IFERROR(M92/M84,""))) | N93: =IF(OR(N92="",N84=""),"",IF(N84<=0,"",IFERROR(N92/N84,""))) | V93: =IF(OR(V92="",V84=""),"",IF(V84<=0,"",IFERROR(V92/V84,""))) | W93: =IF(OR(W92="",W84=""),"",IF(W84<=0,"",IFERROR(W92/W84,""))) | X93: =IF(OR(X92="",X84=""),"",IF(X84<=0,"",IFERROR(X92/X84,"")))
A94: YoY | B94: 전년 같은 분기·전년 대비 | G94: =IF(OR(G92="",C92=""),"",IF(C92<=0,"",IFERROR(G92/C92-1,""))) | H94: =IF(OR(H92="",D92=""),"",IF(D92<=0,"",IFERROR(H92/D92-1,""))) | I94: =IF(OR(I92="",E92=""),"",IF(E92<=0,"",IFERROR(I92/E92-1,""))) | J94: =IF(OR(J92="",F92=""),"",IF(F92<=0,"",IFERROR(J92/F92-1,""))) | K94: =IF(OR(K92="",G92=""),"",IF(G92<=0,"",IFERROR(K92/G92-1,""))) | L94: =IF(OR(L92="",H92=""),"",IF(H92<=0,"",IFERROR(L92/H92-1,""))) | M94: =IF(OR(M92="",I92=""),"",IF(I92<=0,"",IFERROR(M92/I92-1,""))) | N94: =IF(OR(N92="",J92=""),"",IF(J92<=0,"",IFERROR(N92/J92-1,""))) | V94: =IF(OR(V92="",U92=""),"",IF(U92<=0,"",IFERROR(V92/U92-1,""))) | W94: =IF(OR(W92="",V92=""),"",IF(V92<=0,"",IFERROR(W92/V92-1,""))) | X94: =IF(OR(X92="",W92=""),"",IF(W92<=0,"",IFERROR(X92/W92-1,"")))
A95: 이자수익 | F95: 0.02 | G95: 0.009 | H95: 0.401 | I95: 0.026 | J95: 1.666 | K95: 0.367 | L95: 2.643 | M95: 0.726 | N95: 3.285 | V95: 0.02 | W95: 1.666 | X95: 3.285
A96: 외환차익 | G96: 0.017 | H96: 0.009 | I96: -0.007
A97: 보험 해약환급금 | F97: 0 | G97: 0.488 | H97: 0 | I97: 0.226 | J97: 0.492 | K97: 0.264 | L97: -0.264 | M97: 0 | N97: 0 | V97: 0 | W97: 0.492 | X97: 0
A98: 소비세 등 차액 | F98: -0.282 | J98: 0 | V98: -0.282 | W98: 0
A99: 기타 | F99: 0.152 | G99: 0.017 | H99: 0.228 | I99: 0.058 | J99: 0.142 | K99: 0.064 | L99: 0.713 | M99: 0.064 | N99: 0.955 | V99: 0.152 | W99: 0.142 | X99: 0.955
A100: 영업외수익 합계 | F100: -0.169 | G100: 0.514 | H100: 0.63 | I100: 0.31 | J100: 2.3 | K100: 0.696 | L100: 3.092 | M100: 0.789 | N100: 4.24 | V100: -0.169 | W100: 2.3 | X100: 4.24
A101: YoY | B101: 전년 같은 분기·전년 대비 | G101: =IF(OR(G100="",C100=""),"",IF(G100*C100<=0,"",IFERROR(G100/C100-1,""))) | H101: =IF(OR(H100="",D100=""),"",IF(H100*D100<=0,"",IFERROR(H100/D100-1,""))) | I101: =IF(OR(I100="",E100=""),"",IF(I100*E100<=0,"",IFERROR(I100/E100-1,""))) | J101: =IF(OR(J100="",F100=""),"",IF(J100*F100<=0,"",IFERROR(J100/F100-1,""))) | K101: =IF(OR(K100="",G100=""),"",IF(K100*G100<=0,"",IFERROR(K100/G100-1,""))) | L101: =IF(OR(L100="",H100=""),"",IF(L100*H100<=0,"",IFERROR(L100/H100-1,""))) | M101: =IF(OR(M100="",I100=""),"",IF(M100*I100<=0,"",IFERROR(M100/I100-1,""))) | N101: =IF(OR(N100="",J100=""),"",IF(N100*J100<=0,"",IFERROR(N100/J100-1,""))) | V101: =IF(OR(V100="",U100=""),"",IF(V100*U100<=0,"",IFERROR(V100/U100-1,""))) | W101: =IF(OR(W100="",V100=""),"",IF(W100*V100<=0,"",IFERROR(W100/V100-1,""))) | X101: =IF(OR(X100="",W100=""),"",IF(X100*W100<=0,"",IFERROR(X100/W100-1,"")))
A102: 이자비용 | F102: 0.857 | G102: 0.131 | H102: 0.16 | I102: 0.12 | J102: 0.376 | K102: 6.972 | L102: 13.081 | M102: 12.264 | N102: 12.422 | V102: 0.857 | W102: 0.376 | X102: 12.422
...

Sheet 재무상태표
A1: 쿠쿠레브어드바이저즈 재무상태표
A2: 재무비율은 기말 잔액 기준 · 분기 손익은 최근 4분기 합산(TTM) | B2: (단위: 백만엔)
A3: 항목 | B3: 참고 | C3: 2025.4Q | D3: 2026.1Q | E3: 2026.2Q | F3: 2026.3Q | G3: 2026.4Q | H3: 2024 | I3: 2025 | J3: 2026
A4: 자산
A5: 유동자산 | C5: 3217.408 | D5: 5418.21 | E5: 5098.441 | F5: 5410.701 | G5: 4801.909 | H5: 1073.019 | I5: 3217.408 | J5: 4801.909
A6: 현금및현금성자산 | C6: 1639.195 | D6: 3841.304 | E6: 2587.658 | F6: 1348.883 | G6: 3035.544 | H6: 262.425 | I6: 1639.195 | J6: 3035.544
A7: 단기금융상품
A8: 매출채권 | C8: 41.981 | D8: 28.795 | E8: 15.235 | F8: 21.96 | G8: 204.44 | H8: 13.359 | I8: 41.981 | J8: 204.44
A9: 재고자산 | C9: 1475.328 | D9: 1477.984 | E9: 2279.063 | F9: 3827.57 | G9: 1352.145 | H9: 715.658 | I9: 1475.328 | J9: 1352.145
A10: 기타유동자산 | B10: 총계 − 위 항목 | C10: =IF(OR(C5=""),"",IFERROR(C5-SUM(C6,C7,C8,C9),"")) | D10: =IF(OR(D5=""),"",IFERROR(D5-SUM(D6,D7,D8,D9),"")) | E10: =IF(OR(E5=""),"",IFERROR(E5-SUM(E6,E7,E8,E9),"")) | F10: =IF(OR(F5=""),"",IFERROR(F5-SUM(F6,F7,F8,F9),"")) | G10: =IF(OR(G5=""),"",IFERROR(G5-SUM(G6,G7,G8,G9),"")) | H10: =IF(OR(H5=""),"",IFERROR(H5-SUM(H6,H7,H8,H9),"")) | I10: =IF(OR(I5=""),"",IFERROR(I5-SUM(I6,I7,I8,I9),"")) | J10: =IF(OR(J5=""),"",IFERROR(J5-SUM(J6,J7,J8,J9),""))
A11: 비유동자산 | C11: 574.344 | D11: 890.096 | E11: 2481.965 | F11: 2841.807 | G11: 2468.267 | H11: 438.595 | I11: 574.344 | J11: 2468.267
A12: 유형자산 | C12: 320.906 | D12: 623.725 | E12: 2176.022 | F12: 2524.289 | G12: 2014.807 | H12: 278.887 | I12: 320.906 | J12: 2014.807
A13: 무형자산 | C13: 30.786 | D13: 27.94 | E13: 27.18 | F13: 25.932 | G13: 27.443 | H13: 32.327 | I13: 30.786 | J13: 27.443
A14: 투자부동산
A15: 기타비유동자산 | B15: 총계 − 위 항목 | C15: =IF(OR(C11=""),"",IFERROR(C11-SUM(C12,C13,C14),"")) | D15: =IF(OR(D11=""),"",IFERROR(D11-SUM(D12,D13,D14),"")) | E15: =IF(OR(E11=""),"",IFERROR(E11-SUM(E12,E13,E14),"")) | F15: =IF(OR(F11=""),"",IFERROR(F11-SUM(F12,F13,F14),"")) | G15: =IF(OR(G11=""),"",IFERROR(G11-SUM(G12,G13,G14),"")) | H15: =IF(OR(H11=""),"",IFERROR(H11-SUM(H12,H13,H14),"")) | I15: =IF(OR(I11=""),"",IFERROR(I11-SUM(I12,I13,I14),"")) | J15: =IF(OR(J11=""),"",IFERROR(J11-SUM(J12,J13,J14),""))
A16: 자산총계 | C16: 3791.752 | D16: 6308.307 | E16: 7580.406 | F16: 8252.508 | G16: 7270.177 | H16: 1511.615 | I16: 3791.752 | J16: 7270.177
A17: 부채
A18: 유동부채 | C18: 1650.27 | D18: 1659.308 | E18: 2191.217 | F18: 952.936 | G18: 1088.289 | H18: 494.645 | I18: 1650.27 | J18: 1088.289
A19: 매입채무 | C19: 3.056 | D19: 9.107 | E19: 10.007 | F19: 8.898 | G19: 36.952 | H19: 43.929 | I19: 3.056 | J19: 36.952
A20: 단기차입금 | C20: 1450 | D20: 1450 | E20: 2010 | F20: 610 | G20: 610 | H20: 220 | I20: 1450 | J20: 610
A21: 유동성장기부채 | C21: 0 | E21: 38.1 | F21: 38.1 | G21: 38.1 | I21: 0 | J21: 38.1
A22: 기타유동부채 | B22: 총계 − 위 항목 | C22: =IF(OR(C18=""),"",IFERROR(C18-SUM(C19,C20,C21),"")) | D22: =IF(OR(D18=""),"",IFERROR(D18-SUM(D19,D20,D21),"")) | E22: =IF(OR(E18=""),"",IFERROR(E18-SUM(E19,E20,E21),"")) | F22: =IF(OR(F18=""),"",IFERROR(F18-SUM(F19,F20,F21),"")) | G22: =IF(OR(G18=""),"",IFERROR(G18-SUM(G19,G20,G21),"")) | H22: =IF(OR(H18=""),"",IFERROR(H18-SUM(H19,H20,H21),"")) | I22: =IF(OR(I18=""),"",IFERROR(I18-SUM(I19,I20,I21),"")) | J22: =IF(OR(J18=""),"",IFERROR(J18-SUM(J19,J20,J21),""))
A23: 비유동부채 | C23: 45.936 | D23: 57.856 | E23: 863.557 | F23: 2480.036 | G23: 879.208 | H23: 44.206 | I23: 45.936 | J23: 879.208
A24: 장기차입금 | C24: 0 | E24: 752.375 | F24: 2332.65 | G24: 733.325 | I24: 0 | J24: 733.325
A25: 사채
A26: 기타비유동부채 | B26: 총계 − 위 항목 | C26: =IF(OR(C23=""),"",IFERROR(C23-SUM(C24,C25),"")) | D26: =IF(OR(D23=""),"",IFERROR(D23-SUM(D24,D25),"")) | E26: =IF(OR(E23=""),"",IFERROR(E23-SUM(E24,E25),"")) | F26: =IF(OR(F23=""),"",IFERROR(F23-SUM(F24,F25),"")) | G26: =IF(OR(G23=""),"",IFERROR(G23-SUM(G24,G25),"")) | H26: =IF(OR(H23=""),"",IFERROR(H23-SUM(H24,H25),"")) | I26: =IF(OR(I23=""),"",IFERROR(I23-SUM(I24,I25),"")) | J26: =IF(OR(J23=""),"",IFERROR(J23-SUM(J24,J25),""))
A27: 부채총계 | C27: 1696.207 | D27: 1717.165 | E27: 3054.774 | F27: 3432.973 | G27: 1967.497 | H27: 538.852 | I27: 1696.207 | J27: 1967.497
A28: 총차입금 | B28: 단기+유동성장기+장기+사채 | C28: =SUM(C20,C21,C24,C25) | D28: =SUM(D20,D21,D24,D25) | E28: =SUM(E20,E21,E24,E25) | F28: =SUM(F20,F21,F24,F25) | G28: =SUM(G20,G21,G24,G25) | H28: =SUM(H20,H21,H24,H25) | I28: =SUM(I20,I21,I24,I25) | J28: =SUM(J20,J21,J24,J25)
A29: 순차입금 | B29: 음수 = 순현금 | C29: =C28-C6-N(C7) | D29: =D28-D6-N(D7) | E29: =E28-E6-N(E7) | F29: =F28-F6-N(F7) | G29: =G28-G6-N(G7) | H29: =H28-H6-N(H7) | I29: =I28-I6-N(I7) | J29: =J28-J6-N(J7)
A30: 자본
A31: 지배주주지분 | C31: 2093.97 | D31: 4589.877 | E31: 4524.389 | F31: 4818.291 | G31: 5301.796 | H31: 971.032 | I31: 2093.97 | J31: 5301.796
A32: 자본금 | C32: 567.71 | D32: 1792.369 | E32: 1793.562 | F32: 1793.562 | G32: 1847.027 | H32: 200 | I32: 567.71 | J32: 1847.027
A33: 이익잉여금 | C33: 979.3 | D33: 1025.889 | E33: 958.014 | F33: 1251.916 | G33: 1628.49 | H33: 591.781 | I33: 979.3 | J33: 1628.49
A34: 비지배지분
A35: 자본총계 | C35: 2095.545 | D35: 4591.142 | E35: 4525.632 | F35: 4819.534 | G35: 5302.679 | H35: 972.763 | I35: 2095.545 | J35: 5302.679
A36: 현금흐름 요약 | B36: 분기 = TTM (있을 때만)
A37: 영업활동현금흐름 | C37: -382.181 | E37: -2270.656 | G37: 1460.169 | H37: -299.354 | I37: -382.181 | J37: 1460.169
A38: CAPEX (유·무형 취득) | B38: 양수로 입력 | C38: 117.47 | E38: 1990.941 | G38: 2313.056 | H38: 198.409 | I38: 117.47 | J38: 2313.056
A39: FCF | C39: =IF(OR(C37="",C38=""),"",IFERROR(C37-C38,"")) | D39: =IF(OR(D37="",D38=""),"",IFERROR(D37-D38,"")) | E39: =IF(OR(E37="",E38=""),"",IFERROR(E37-E38,"")) | F39: =IF(OR(F37="",F38=""),"",IFERROR(F37-F38,"")) | G39: =IF(OR(G37="",G38=""),"",IFERROR(G37-G38,"")) | H39: =IF(OR(H37="",H38=""),"",IFERROR(H37-H38,"")) | I39: =IF(OR(I37="",I38=""),"",IFERROR(I37-I38,"")) | J39: =IF(OR(J37="",J38=""),"",IFERROR(J37-J38,""))
A40: 배당금 지급 | B40: 양수로 입력 | C40: 58.191 | E40: 94.01 | G40: 94.015 | H40: 34.2 | I40: 58.191 | J40: 94.015
A41: 주요 재무 비율 | B41: 기준 (빨간 글씨 = 미달)
A42: 안정성
A43: 부채비율 | B43: 100%↓ | C43: =IF(OR(C27="",C35=""),"",IFERROR(C27/C35,"")) | D43: =IF(OR(D27="",D35=""),"",IFERROR(D27/D35,"")) | E43: =IF(OR(E27="",E35=""),"",IFERROR(E27/E35,"")) | F43: =IF(OR(F27="",F35=""),"",IFERROR(F27/F35,"")) | G43: =IF(OR(G27="",G35=""),"",IFERROR(G27/G35,"")) | H43: =IF(OR(H27="",H35=""),"",IFERROR(H27/H35,"")) | I43: =IF(OR(I27="",I35=""),"",IFERROR(I27/I35,"")) | J43: =IF(OR(J27="",J35=""),"",IFERROR(J27/J35,""))
A44: 순차입금비율 | B44: 0%↓ 순현금 | C44: =IF(OR(C29="",C35=""),"",IFERROR(C29/C35,"")) | D44: =IF(OR(D29="",D35=""),"",IFERROR(D29/D35,"")) | E44: =IF(OR(E29="",E35=""),"",IFERROR(E29/E35,"")) | F44: =IF(OR(F29="",F35=""),"",IFERROR(F29/F35,"")) | G44: =IF(OR(G29="",G35=""),"",IFERROR(G29/G35,"")) | H44: =IF(OR(H29="",H35=""),"",IFERROR(H29/H35,"")) | I44: =IF(OR(I29="",I35=""),"",IFERROR(I29/I35,"")) | J44: =IF(OR(J29="",J35=""),"",IFERROR(J29/J35,""))
A45: 자기자본비율 | B45: 50%↑ | C45: =IF(OR(C35="",C16=""),"",IFERROR(C35/C16,"")) | D45: =IF(OR(D35="",D16=""),"",IFERROR(D35/D16,"")) | E45: =IF(OR(E35="",E16=""),"",IFERROR(E35/E16,"")) | F45: =IF(OR(F35="",F16=""),"",IFERROR(F35/F16,"")) | G45: =IF(OR(G35="",G16=""),"",IFERROR(G35/G16,"")) | H45: =IF(OR(H35="",H16=""),"",IFERROR(H35/H16,"")) | I45: =IF(OR(I35="",I16=""),"",IFERROR(I35/I16,"")) | J45: =IF(OR(J35="",J16=""),"",IFERROR(J35/J16,""))
A46: 유동비율 | B46: 150%↑ | C46: =IF(OR(C5="",C18=""),"",IFERROR(C5/C18,"")) | D46: =IF(OR(D5="",D18=""),"",IFERROR(D5/D18,"")) | E46: =IF(OR(E5="",E18=""),"",IFERROR(E5/E18,"")) | F46: =IF(OR(F5="",F18=""),"",IFERROR(F5/F18,"")) | G46: =IF(OR(G5="",G18=""),"",IFERROR(G5/G18,"")) | H46: =IF(OR(H5="",H18=""),"",IFERROR(H5/H18,"")) | I46: =IF(OR(I5="",I18=""),"",IFERROR(I5/I18,"")) | J46: =IF(OR(J5="",J18=""),"",IFERROR(J5/J18,""))
A47: 당좌비율 | B47: 100%↑ | C47: =IF(OR(C5="",C18=""),"",IFERROR((C5-N(C9))/C18,"")) | D47: =IF(OR(D5="",D18=""),"",IFERROR((D5-N(D9))/D18,"")) | E47: =IF(OR(E5="",E18=""),"",IFERROR((E5-N(E9))/E18,"")) | F47: =IF(OR(F5="",F18=""),"",IFERROR((F5-N(F9))/F18,"")) | G47: =IF(OR(G5="",G18=""),"",IFERROR((G5-N(G9))/G18,"")) | H47: =IF(OR(H5="",H18=""),"",IFERROR((H5-N(H9))/H18,"")) | I47: =IF(OR(I5="",I18=""),"",IFERROR((I5-N(I9))/I18,"")) | J47: =IF(OR(J5="",J18=""),"",IFERROR((J5-N(J9))/J18,""))
A48: 이자보상배율 | B48: 5x↑ (금융원가 기준) | C48: =IFERROR((IF(COUNT('연간'!G19:J19)<4,"",SUM('연간'!G19:J19)))/(IF(COUNT('연간'!G41:J41)<4,"",SUM('연간'!G41:J41))),"") | D48: =IFERROR((IF(COUNT('연간'!H19:K19)<4,"",SUM('연간'!H19:K19)))/(IF(COUNT('연간'!H41:K41)<4,"",SUM('연간'!H41:K41))),"") | E48: =IFERROR((IF(COUNT('연간'!I19:L19)<4,"",SUM('연간'!I19:L19)))/(IF(COUNT('연간'!I41:L41)<4,"",SUM('연간'!I41:L41))),"") | F48: =IFERROR((IF(COUNT('연간'!J19:M19)<4,"",SUM('연간'!J19:M19)))/(IF(COUNT('연간'!J41:M41)<4,"",SUM('연간'!J41:M41))),"") | G48: =IFERROR((IF(COUNT('연간'!K19:N19)<4,"",SUM('연간'!K19:N19)))/(IF(COUNT('연간'!K41:N41)<4,"",SUM('연간'!K41:N41))),"") | H48: =IFERROR(('연간'!V19)/('연간'!V41),"") | I48: =IFERROR(('연간'!W19)/('연간'!W41),"") | J48: =IFERROR(('연간'!X19)/('연간'!X41),"")
A49: 차입금 상환연수 | B49: 4년↓ (버핏) | C49: =IFERROR(IF((IF(COUNT('연간'!G49:J49)<4,"",SUM('연간'!G49:J49)))<=0,"적자",C28/(IF(COUNT('연간'!G49:J49)<4,"",SUM('연간'!G49:J49)))),"") | D49: =IFERROR(IF((IF(COUNT('연간'!H49:K49)<4,"",SUM('연간'!H49:K49)))<=0,"적자",D28/(IF(COUNT('연간'!H49:K49)<4,"",SUM('연간'!H49:K49)))),"") | E49: =IFERROR(IF((IF(COUNT('연간'!I49:L49)<4,"",SUM('연간'!I49:L49)))<=0,"적자",E28/(IF(COUNT('연간'!I49:L49)<4,"",SUM('연간'!I49:L49)))),"") | F49: =IFERROR(IF((IF(COUNT('연간'!J49:M49)<4,"",SUM('연간'!J49:M49)))<=0,"적자",F28/(IF(COUNT('연간'!J49:M49)<4,"",SUM('연간'!J49:M49)))),"") | G49: =IFERROR(IF((IF(COUNT('연간'!K49:N49)<4,"",SUM('연간'!K49:N49)))<=0,"적자",G28/(IF(COUNT('연간'!K49:N49)<4,"",SUM('연간'!K49:N49)))),"") | H49: =IFERROR(IF(('연간'!V49)<=0,"적자",H28/('연간'!V49)),"") | I49: =IFERROR(IF(('연간'!W49)<=0,"적자",I28/('연간'!W49)),"") | J49: =IFERROR(IF(('연간'!X49)<=0,"적자",J28/('연간'!X49)),"")
A50: 수익성
A51: ROE | B51: 15%↑ (버핏) | C51: =IFERROR((IF(COUNT('연간'!G49:J49)<4,"",SUM('연간'!G49:J49)))/C31,"") | D51: =IFERROR((IF(COUNT('연간'!H49:K49)<4,"",SUM('연간'!H49:K49)))/D31,"") | E51: =IFERROR((IF(COUNT('연간'!I49:L49)<4,"",SUM('연간'!I49:L49)))/E31,"") | F51: =IFERROR((IF(COUNT('연간'!J49:M49)<4,"",SUM('연간'!J49:M49)))/F31,"") | G51: =IFERROR((IF(COUNT('연간'!K49:N49)<4,"",SUM('연간'!K49:N49)))/G31,"") | H51: =IFERROR(('연간'!V49)/H31,"") | I51: =IFERROR(('연간'!W49)/I31,"") | J51: =IFERROR(('연간'!X49)/J31,"")
A52: ROA | B52: 5%↑ | C52: =IFERROR((IF(COUNT('연간'!G47:J47)<4,"",SUM('연간'!G47:J47)))/C16,"") | D52: =IFERROR((IF(COUNT('연간'!H47:K47)<4,"",SUM('연간'!H47:K47)))/D16,"") | E52: =IFERROR((IF(COUNT('연간'!I47:L47)<4,"",SUM('연간'!I47:L47)))/E16,"") | F52: =IFERROR((IF(COUNT('연간'!J47:M47)<4,"",SUM('연간'!J47:M47)))/F16,"") | G52: =IFERROR((IF(COUNT('연간'!K47:N47)<4,"",SUM('연간'!K47:N47)))/G16,"") | H52: =IFERROR(('연간'!V47)/H16,"") | I52: =IFERROR(('연간'!W47)/I16,"") | J52: =IFERROR(('연간'!X47)/J16,"")
A53: ROIC | B53: 10%↑ (세후영업이익 기준) | C53: =IFERROR((IF(COUNT('연간'!G19:J19)<4,"",SUM('연간'!G19:J19)))*(1-0.3)/(C35+C29),"") | D53: =IFERROR((IF(COUNT('연간'!H19:K19)<4,"",SUM('연간'!H19:K19)))*(1-0.3)/(D35+D29),"") | E53: =IFERROR((IF(COUNT('연간'!I19:L19)<4,"",SUM('연간'!I19:L19)))*(1-0.3)/(E35+E29),"") | F53: =IFERROR((IF(COUNT('연간'!J19:M19)<4,"",SUM('연간'!J19:M19)))*(1-0.3)/(F35+F29),"") | G53: =IFERROR((IF(COUNT('연간'!K19:N19)<4,"",SUM('연간'!K19:N19)))*(1-0.3)/(G35+G29),"") | H53: =IFERROR(('연간'!V19)*(1-0.3)/(H35+H29),"") | I53: =IFERROR(('연간'!W19)*(1-0.3)/(I35+I29),"") | J53: =IFERROR(('연간'!X19)*(1-0.3)/(J35+J29),"")
A54: 매출총이익률 (GPM) | B54: 40%↑ (해자 신호) | C54: =IFERROR((IF(COUNT('연간'!G13:J13)<4,"",SUM('연간'!G13:J13)))/(IF(COUNT('연간'!G4:J4)<4,"",SUM('연간'!G4:J4))),"") | D54: =IFERROR((IF(COUNT('연간'!H13:K13)<4,"",SUM('연간'!H13:K13)))/(IF(COUNT('연간'!H4:K4)<4,"",SUM('연간'!H4:K4))),"") | E54: =IFERROR((IF(COUNT('연간'!I13:L13)<4,"",SUM('연간'!I13:L13)))/(IF(COUNT('연간'!I4:L4)<4,"",SUM('연간'!I4:L4))),"") | F54: =IFERROR((IF(COUNT('연간'!J13:M13)<4,"",SUM('연간'!J13:M13)))/(IF(COUNT('연간'!J4:M4)<4,"",SUM('연간'!J4:M4))),"") | G54: =IFERROR((IF(COUNT('연간'!K13:N13)<4,"",SUM('연간'!K13:N13)))/(IF(COUNT('연간'!K4:N4)<4,"",SUM('연간'!K4:N4))),"") | H54: =IFERROR(('연간'!V13)/('연간'!V4),"") | I54: =IFERROR(('연간'!W13)/('연간'!W4),"") | J54: =IFERROR(('연간'!X13)/('연간'!X4),"")
A55: 영업이익률 (OPM) | B55: 15%↑ | C55: =IFERROR((IF(COUNT('연간'!G19:J19)<4,"",SUM('연간'!G19:J19)))/(IF(COUNT('연간'!G4:J4)<4,"",SUM('연간'!G4:J4))),"") | D55: =IFERROR((IF(COUNT('연간'!H19:K19)<4,"",SUM('연간'!H19:K19)))/(IF(COUNT('연간'!H4:K4)<4,"",SUM('연간'!H4:K4))),"") | E55: =IFERROR((IF(COUNT('연간'!I19:L19)<4,"",SUM('연간'!I19:L19)))/(IF(COUNT('연간'!I4:L4)<4,"",SUM('연간'!I4:L4))),"") | F55: =IFERROR((IF(COUNT('연간'!J19:M19)<4,"",SUM('연간'!J19:M19)))/(IF(COUNT('연간'!J4:M4)<4,"",SUM('연간'!J4:M4))),"") | G55: =IFERROR((IF(COUNT('연간'!K19:N19)<4,"",SUM('연간'!K19:N19)))/(IF(COUNT('연간'!K4:N4)<4,"",SUM('연간'!K4:N4))),"") | H55: =IFERROR(('연간'!V19)/('연간'!V4),"") | I55: =IFERROR(('연간'!W19)/('연간'!W4),"") | J55: =IFERROR(('연간'!X19)/('연간'!X4),"")
A56: 순이익률 | B56: 10%↑ | C56: =IFERROR((IF(COUNT('연간'!G47:J47)<4,"",SUM('연간'!G47:J47)))/(IF(COUNT('연간'!G4:J4)<4,"",SUM('연간'!G4:J4))),"") | D56: =IFERROR((IF(COUNT('연간'!H47:K47)<4,"",SUM('연간'!H47:K47)))/(IF(COUNT('연간'!H4:K4)<4,"",SUM('연간'!H4:K4))),"") | E56: =IFERROR((IF(COUNT('연간'!I47:L47)<4,"",SUM('연간'!I47:L47)))/(IF(COUNT('연간'!I4:L4)<4,"",SUM('연간'!I4:L4))),"") | F56: =IFERROR((IF(COUNT('연간'!J47:M47)<4,"",SUM('연간'!J47:M47)))/(IF(COUNT('연간'!J4:M4)<4,"",SUM('연간'!J4:M4))),"") | G56: =IFERROR((IF(COUNT('연간'!K47:N47)<4,"",SUM('연간'!K47:N47)))/(IF(COUNT('연간'!K4:N4)<4,"",SUM('연간'!K4:N4))),"") | H56: =IFERROR(('연간'!V47)/('연간'!V4),"") | I56: =IFERROR(('연간'!W47)/('연간'!W4),"") | J56: =IFERROR(('연간'!X47)/('연간'!X4),"")
A57: 효율성 (회전율)
A58: 총자산회전율 | B58: 높을수록↑ | C58: =IFERROR((IF(COUNT('연간'!G4:J4)<4,"",SUM('연간'!G4:J4)))/C16,"") | D58: =IFERROR((IF(COUNT('연간'!H4:K4)<4,"",SUM('연간'!H4:K4)))/D16,"") | E58: =IFERROR((IF(COUNT('연간'!I4:L4)<4,"",SUM('연간'!I4:L4)))/E16,"") | F58: =IFERROR((IF(COUNT('연간'!J4:M4)<4,"",SUM('연간'!J4:M4)))/F16,"") | G58: =IFERROR((IF(COUNT('연간'!K4:N4)<4,"",SUM('연간'!K4:N4)))/G16,"") | H58: =IFERROR(('연간'!V4)/H16,"") | I58: =IFERROR(('연간'!W4)/I16,"") | J58: =IFERROR(('연간'!X4)/J16,"")
A59: 매출채권회전일수 | B59: 짧을수록↑ | C59: =IFERROR(C8/(IF(COUNT('연간'!G4:J4)<4,"",SUM('연간'!G4:J4)))*365,"") | D59: =IFERROR(D8/(IF(COUNT('연간'!H4:K4)<4,"",SUM('연간'!H4:K4)))*365,"") | E59: =IFERROR(E8/(IF(COUNT('연간'!I4:L4)<4,"",SUM('연간'!I4:L4)))*365,"") | F59: =IFERROR(F8/(IF(COUNT('연간'!J4:M4)<4,"",SUM('연간'!J4:M4)))*365,"") | G59: =IFERROR(G8/(IF(COUNT('연간'!K4:N4)<4,"",SUM('연간'!K4:N4)))*365,"") | H59: =IFERROR(H8/('연간'!V4)*365,"") | I59: =IFERROR(I8/('연간'!W4)*365,"") | J59: =IFERROR(J8/('연간'!X4)*365,"")
A60: 재고자산회전일수 | B60: 짧을수록↑ | C60: =IFERROR(C9/(IF(COUNT('연간'!G11:J11)<4,"",SUM('연간'!G11:J11)))*365,"") | D60: =IFERROR(D9/(IF(COUNT('연간'!H11:K11)<4,"",SUM('연간'!H11:K11)))*365,"") | E60: =IFERROR(E9/(IF(COUNT('연간'!I11:L11)<4,"",SUM('연간'!I11:L11)))*365,"") | F60: =IFERROR(F9/(IF(COUNT('연간'!J11:M11)<4,"",SUM('연간'!J11:M11)))*365,"") | G60: =IFERROR(G9/(IF(COUNT('연간'!K11:N11)<4,"",SUM('연간'!K11:N11)))*365,"") | H60: =IFERROR(H9/('연간'!V11)*365,"") | I60: =IFERROR(I9/('연간'!W11)*365,"") | J60: =IFERROR(J9/('연간'!X11)*365,"")
A61: 매입채무회전일수 | B61: 길수록 유리 | C61: =IFERROR(C19/(IF(COUNT('연간'!G11:J11)<4,"",SUM('연간'!G11:J11)))*365,"") | D61: =IFERROR(D19/(IF(COUNT('연간'!H11:K11)<4,"",SUM('연간'!H11:K11)))*365,"") | E61: =IFERROR(E19/(IF(COUNT('연간'!I11:L11)<4,"",SUM('연간'!I11:L11)))*365,"") | F61: =IFERROR(F19/(IF(COUNT('연간'!J11:M11)<4,"",SUM('연간'!J11:M11)))*365,"") | G61: =IFERROR(G19/(IF(COUNT('연간'!K11:N11)<4,"",SUM('연간'!K11:N11)))*365,"") | H61: =IFERROR(H19/('연간'!V11)*365,"") | I61: =IFERROR(I19/('연간'!W11)*365,"") | J61: =IFERROR(J19/('연간'!X11)*365,"")
A62: 현금전환주기 (CCC) | B62: 짧을수록↑ | C62: =IF(OR(C59="",C60="",C61=""),"",IFERROR(C59+C60-C61,"")) | D62: =IF(OR(D59="",D60="",D61=""),"",IFERROR(D59+D60-D61,"")) | E62: =IF(OR(E59="",E60="",E61=""),"",IFERROR(E59+E60-E61,"")) | F62: =IF(OR(F59="",F60="",F61=""),"",IFERROR(F59+F60-F61,"")) | G62: =IF(OR(G59="",G60="",G61=""),"",IFERROR(G59+G60-G61,"")) | H62: =IF(OR(H59="",H60="",H61=""),"",IFERROR(H59+H60-H61,"")) | I62: =IF(OR(I59="",I60="",I61=""),"",IFERROR(I59+I60-I61,"")) | J62: =IF(OR(J59="",J60="",J61=""),"",IFERROR(J59+J60-J61,""))
A63: 현금흐름
A64: 영업현금흐름 / 순이익 | B64: 1x↑ (이익의 질) | C64: =IF(C37="","",IFERROR(C37/(IF(COUNT('연간'!G47:J47)<4,"",SUM('연간'!G47:J47))),"")) | D64: =IF(D37="","",IFERROR(D37/(IF(COUNT('연간'!H47:K47)<4,"",SUM('연간'!H47:K47))),"")) | E64: =IF(E37="","",IFERROR(E37/(IF(COUNT('연간'!I47:L47)<4,"",SUM('연간'!I47:L47))),"")) | F64: =IF(F37="","",IFERROR(F37/(IF(COUNT('연간'!J47:M47)<4,"",SUM('연간'!J47:M47))),"")) | G64: =IF(G37="","",IFERROR(G37/(IF(COUNT('연간'!K47:N47)<4,"",SUM('연간'!K47:N47))),"")) | H64: =IF(H37="","",IFERROR(H37/('연간'!V47),"")) | I64: =IF(I37="","",IFERROR(I37/('연간'!W47),"")) | J64: =IF(J37="","",IFERROR(J37/('연간'!X47),""))
A65: FCF 마진 | B65: 5%↑ | C65: =IF(C39="","",IFERROR(C39/(IF(COUNT('연간'!G4:J4)<4,"",SUM('연간'!G4:J4))),"")) | D65: =IF(D39="","",IFERROR(D39/(IF(COUNT('연간'!H4:K4)<4,"",SUM('연간'!H4:K4))),"")) | E65: =IF(E39="","",IFERROR(E39/(IF(COUNT('연간'!I4:L4)<4,"",SUM('연간'!I4:L4))),"")) | F65: =IF(F39="","",IFERROR(F39/(IF(COUNT('연간'!J4:M4)<4,"",SUM('연간'!J4:M4))),"")) | G65: =IF(G39="","",IFERROR(G39/(IF(COUNT('연간'!K4:N4)<4,"",SUM('연간'!K4:N4))),"")) | H65: =IF(H39="","",IFERROR(H39/('연간'!V4),"")) | I65: =IF(I39="","",IFERROR(I39/('연간'!W4),"")) | J65: =IF(J39="","",IFERROR(J39/('연간'!X4),""))
A66: CAPEX / 매출 | B66: 낮을수록↑ (자본 가벼움) | C66: =IF(C38="","",IFERROR(C38/(IF(COUNT('연간'!G4:J4)<4,"",SUM('연간'!G4:J4))),"")) | D66: =IF(D38="","",IFERROR(D38/(IF(COUNT('연간'!H4:K4)<4,"",SUM('연간'!H4:K4))),"")) | E66: =IF(E38="","",IFERROR(E38/(IF(COUNT('연간'!I4:L4)<4,"",SUM('연간'!I4:L4))),"")) | F66: =IF(F38="","",IFERROR(F38/(IF(COUNT('연간'!J4:M4)<4,"",SUM('연간'!J4:M4))),"")) | G66: =IF(G38="","",IFERROR(G38/(IF(COUNT('연간'!K4:N4)<4,"",SUM('연간'!K4:N4))),"")) | H66: =IF(H38="","",IFERROR(H38/('연간'!V4),"")) | I66: =IF(I38="","",IFERROR(I38/('연간'!W4),"")) | J66: =IF(J38="","",IFERROR(J38/('연간'!X4),""))
A67: 배당성향 | B67: 참고 | C67: =IF(C40="","",IFERROR(C40/(IF(COUNT('연간'!G49:J49)<4,"",SUM('연간'!G49:J49))),"")) | D67: =IF(D40="","",IFERROR(D40/(IF(COUNT('연간'!H49:K49)<4,"",SUM('연간'!H49:K49))),"")) | E67: =IF(E40="","",IFERROR(E40/(IF(COUNT('연간'!I49:L49)<4,"",SUM('연간'!I49:L49))),"")) | F67: =IF(F40="","",IFERROR(F40/(IF(COUNT('연간'!J49:M49)<4,"",SUM('연간'!J49:M49))),"")) | G67: =IF(G40="","",IFERROR(G40/(IF(COUNT('연간'!K49:N49)<4,"",SUM('연간'!K49:N49))),"")) | H67: =IF(H40="","",IFERROR(H40/('연간'!V49),"")) | I67: =IF(I40="","",IFERROR(I40/('연간'!W49),"")) | J67: =IF(J40="","",IFERROR(J40/('연간'!X49),""))
A69: 재무상태표 · 전 항목 | B69: 분기 말 잔액
A70: 항목 | B70: 참고 | C70: 2025.4Q | D70: 2026.1Q | E70: 2026.2Q | F70: 2026.3Q | G70: 2026.4Q | H70: 2024 | I70: 2025 | J70: 2026
A71: 현금 및 예금 | C71: 1639.195 | D71: 3841.304 | E71: 2587.658 | F71: 1348.883 | G71: 3035.544 | H71: 262.425 | I71: 1639.195 | J71: 3035.544
A72: 매출채권 | H72: 13.359
A73: 매출채권·계약자산 | C73: 41.981 | D73: 28.795 | E73: 15.235 | F73: 21.96 | G73: 204.44 | H73: 13.359 | I73: 41.981 | J73: 204.44
A74: 판매용 부동산 | C74: 1475.328 | D74: 1477.984 | E74: 2279.063 | F74: 3827.57 | G74: 1352.145 | H74: 715.658 | I74: 1475.328 | J74: 1352.145
A75: 영업투자유가증권 | C75: 0 | F75: 75 | G75: 75 | H75: 50 | I75: 0 | J75: 75
A76: 선급비용 | C76: 46.701 | D76: 43.562 | E76: 48.461 | F76: 48.281 | G76: 89.323 | H76: 25.215 | I76: 46.701 | J76: 89.323
A77: 기타 | C77: 14.201 | D77: 26.563 | E77: 168.023 | F77: 89.005 | G77: 45.455 | H77: 6.36 | I77: 14.201 | J77: 45.455
A78: 유동자산 합계 | C78: 3217.408 | D78: 5418.21 | E78: 5098.441 | F78: 5410.701 | G78: 4801.909 | H78: 1073.019 | I78: 3217.408 | J78: 4801.909
A79: 건물·구축물 | C79: 107.089 | G79: 837.342 | H79: 158.89 | I79: 107.089 | J79: 837.342
A80: 감가상각누계액 | C80: -22.695 | G80: -55.761 | H80: -15.282 | I80: -22.695 | J80: -55.761
A81: 건물·구축물(순액) | C81: 84.393 | D81: 85.615 | E81: 434.086 | F81: 753.115 | G81: 781.581 | H81: 143.608 | I81: 84.393 | J81: 781.581
A82: 기계장치·운반구 | C82: 2.864 | G82: 0.341 | H82: 2.864 | I82: 2.864 | J82: 0.341
A83: 감가상각누계액 | C83: -2.536 | G83: -0.255 | H83: -2.271 | I83: -2.536 | J83: -0.255
A84: 기계장치·운반구(순액) | C84: 0.328 | G84: 0.085 | H84: 0.593 | I84: 0.328 | J84: 0.085
A85: 공구·기구·비품 | C85: 12.562 | G85: 13.241 | H85: 12.562 | I85: 12.562 | J85: 13.241
A86: 감가상각누계액 | C86: -8.679 | G86: -12.04 | H86: -7.153 | I86: -8.679 | J86: -12.04
A87: 공구·기구·비품(순액) | C87: 3.882 | G87: 1.2 | H87: 5.409 | I87: 3.882 | J87: 1.2
A88: 토지 | C88: 232.301 | D88: 534.793 | E88: 1739.492 | F88: 1739.492 | G88: 1202.566 | H88: 129.275 | I88: 232.301 | J88: 1202.566
A89: 건설중인자산 | C89: 0 | F89: 29.865 | G89: 29.374 | I89: 0 | J89: 29.374
A90: 기타(순액) | C90: 4.21 | D90: 3.315 | E90: 2.442 | F90: 1.816 | H90: 6.002 | I90: 4.21
A91: 유형자산 합계 | C91: 320.906 | D91: 623.725 | E91: 2176.022 | F91: 2524.289 | G91: 2014.807 | H91: 278.887 | I91: 320.906 | J91: 2014.807
A92: 기타 | C92: 30.786 | D92: 27.94 | E92: 27.18 | F92: 25.932 | G92: 27.443 | H92: 32.327 | I92: 30.786 | J92: 27.443
A93: 무형자산 합계 | C93: 30.786 | D93: 27.94 | E93: 27.18 | F93: 25.932 | G93: 27.443 | H93: 32.327 | I93: 30.786 | J93: 27.443
A94: 임차보증금 | C94: 81.509 | D94: 86.209 | E94: 85.279 | F94: 88.949 | G94: 122.455 | H94: 73.039 | I94: 81.509 | J94: 122.455
A95: 종업원 장기대여금 | C95: 69.646 | D95: 82.494 | E95: 118.44 | F95: 122.216 | G95: 123.616 | H95: 0 | I95: 69.646 | J95: 123.616
A96: 임원 장기대여금 | C96: 0 | G96: 41.725 | I96: 0 | J96: 41.725
A97: 보험적립금 | C97: 37.023 | D97: 38.272 | E97: 42.686 | F97: 43.966 | G97: 47.439 | H97: 28.845 | I97: 37.023 | J97: 47.439
A98: 이연법인세자산 | C98: 24.887 | D98: 21.683 | E98: 22.586 | F98: 26.672 | G98: 50.397 | H98: 24.38 | I98: 24.887 | J98: 50.397
A99: 기타 | C99: 9.585 | D99: 9.77 | E99: 9.77 | F99: 9.78 | G99: 40.383 | H99: 1.115 | I99: 9.585 | J99: 40.383
A100: 투자 및 기타자산 합계 | C100: 222.652 | D100: 238.431 | E100: 278.762 | F100: 291.584 | G100: 426.017 | H100: 127.38 | I100: 222.652 | J100: 426.017
A101: 비유동자산 합계 | C101: 574.344 | D101: 890.096 | E101: 2481.965 | F101: 2841.807 | G101: 2468.267 | H101: 438.595 | I101: 574.344 | J101: 2468.267
...

Sheet 섹터 데이터
A1: 쿠쿠레브어드바이저즈 섹터·사업 데이터
A2: 2단계 보고서를 만들 때 모은 자료 · 월차 · 출처는 맨 오른쪽
A4: THIS RESULT · 4Q
A5: 항목 | B5: 값 | E5: 출처
A6: 매출 | B6: 38.85 | E6: 2단계 보고서 자료(회사 설명회 자료·공시)
A7: gp | B7: 7.1
A8: 영업이익 | B8: 5.35
A9: ordinary | B9: 5.27
A10: 순이익 | B10: 3.77
A11: flow | B11: 36.81
A12: stock | B12: 2.03
A13: 영업이익률 % | B13: 13.8
A15: THIS RESULT · fy26
A16: 항목 | B16: 값 | E16: 출처
A17: 매출 | B17: 70.2 | E17: 2단계 보고서 자료(회사 설명회 자료·공시)
A18: gp | B18: 18.16
A19: sga | B19: 6.72
A20: 영업이익 | B20: 11.44
A21: ordinary | B21: 10.58
A22: 순이익 | B22: 7.43
A23: EPS | B23: 151.86
A24: dps | B24: 30
A25: flow | B25: 63.24
A26: stock | B26: 6.96
A27: bs invest 비중 % | B27: 77.8
A28: 영업이익률 % | B28: 16.3
A30: THIS RESULT · fy26 vs 계획
A31: 항목 | B31: 값 | E31: 출처
A32: 매출 계획 | B32: 70 | E32: 2단계 보고서 자료(회사 설명회 자료·공시)
A33: 영업이익 계획 | B33: 11
A34: 순이익 계획 | B34: 7
A35: 매출 % | B35: 0.3
A36: 영업이익 % | B36: 4
A37: 순이익 % | B37: 6.2
A39: THIS RESULT · fy27 guide
A40: 항목 | B40: 값 | E40: 출처
A41: 매출 | B41: 110 | E41: 2단계 보고서 자료(회사 설명회 자료·공시)
A42: 영업이익 | B42: 22
A43: ordinary | B43: 20
A44: 순이익 | B44: 14
A45: EPS | B45: 271.88
A46: dps | B46: 50
A47: bs invest 비중 % | B47: 80
A48: flow | B48: 94.5
A49: stock | B49: 15.5
A51: THIS RESULT · pipeline
A52: 항목 | B52: 값 | E52: 출처
A53: 상장 전 | B53: 400 | E53: 2단계 보고서 자료(회사 설명회 자료·공시)
A54: FY27_1Q_계약(예정) | B54: 55
A56: bs annual
A57: 항목 | B57: 2024 | C57: 2025 | D57: 2026 | E57: 출처
A58: labels | B58: 2024 | C58: 2025 | D58: 2026 | E58: 2단계 보고서 자료(회사 설명회 자료·공시)
A59: current assets | B59: 10.7 | C59: 32.2 | D59: 48
A60: cash | B60: 2.6 | C60: 16.4 | D60: 30.4
A61: st fin
A62: receivables | B62: 0.1 | C62: 0.4 | D62: 2
A63: inventory | B63: 7.2 | C63: 14.8 | D63: 13.5
A64: noncurrent assets | B64: 4.4 | C64: 5.7 | D64: 24.7
A65: ppe | B65: 2.8 | C65: 3.2 | D65: 20.1
A66: intangibles | B66: 0.3 | C66: 0.3 | D66: 0.3
A67: inv property
A68: 합계 assets | B68: 15.1 | C68: 37.9 | D68: 72.7
A69: current liab | B69: 4.9 | C69: 16.5 | D69: 10.9
A70: payables | B70: 0.4 | C70: 0 | D70: 0.4
A71: st debt | B71: 2.2 | C71: 14.5 | D71: 6.1
A72: noncurrent liab | B72: 0.4 | C72: 0.5 | D72: 8.8
A73: lt debt | C73: 0 | D73: 7.3
A74: bonds
A75: 합계 liab | B75: 5.4 | C75: 17 | D75: 19.7
A76: capital stock | B76: 2 | C76: 5.7 | D76: 18.5
A77: retained | B77: 5.9 | C77: 9.8 | D77: 16.3
A78: nci
A79: 합계 equity | B79: 9.7 | C79: 21 | D79: 53
A80: current ltd | C80: 0 | D80: 0.4
A81: equity owner | B81: 9.7 | C81: 20.9 | D81: 53
A83: cf annual
A84: 항목 | B84: 2024 | C84: 2025 | D84: 2026 | E84: 출처
A85: labels | B85: 2024 | C85: 2025 | D85: 2026 | E85: 2단계 보고서 자료(회사 설명회 자료·공시)
A86: ocf | B86: -3 | C86: -3.8 | D86: 14.6
A87: 설비투자 | B87: 2 | C87: 1.2 | D87: 23.1
A88: dividends | B88: 0.3 | C88: 0.6 | D88: 0.9
A90: dps
A91: 항목 | B91: 값 | E91: 출처
A92: FY25 | B92: 22 | E92: 2단계 보고서 자료(회사 설명회 자료·공시)
A93: FY26 | B93: 30
A94: FY27G | B94: 50
A96: shares
A97: 항목 | B97: 값 | E97: 출처
A98: issued 2026-08 | B98: 5189960 | E98: 2단계 보고서 자료(회사 설명회 자료·공시)
A99: treasury | B99: 40637
A100: outstanding | B100: 5149323
A102: reactions
A103: 항목 | B103: 기준일 | C103: 다음날 | D103: 등락% | E103: 출처
A104: 2025-01-14 | B104: 2025-01-14 | C104: 2025-01-15 | D104: 23.6 | E104: 2단계 보고서 자료(회사 설명회 자료·공시)
A105: 2025-04-14 | B105: 2025-04-14 | C105: 2025-04-15 | D105: 4.9
A106: 2025-07-14 | B106: 2025-07-14 | C106: 2025-07-15 | D106: -15.5
A107: 2025-10-14 | B107: 2025-10-14 | C107: 2025-10-15 | D107: -5.8
A108: 2026-01-14 | B108: 2026-01-14 | C108: 2026-01-15 | D108: -10.1
A109: 2026-04-13 | B109: 2026-04-13 | C109: 2026-04-14 | D109: -13.2
A110: 2026-07-14 | B110: 2026-07-14 | C110: 2026-07-15 | D110: 12.3
...

Sheet 출처
A1: 출처 · 쓴 결산단신
A3: 공시일 | B3: 문서 | C3: PDF
A4: 2026-10-15 | B4: 2026년 8월 결산기 연간 결산단신 | C4: https://www2.jpx.co.jp/disc/276A0/140120261008548118.pdf
A5: 2026-07-14 | B5: 2026년 8월 결산기 3분기 결산단신 | C5: https://www2.jpx.co.jp/disc/276A0/140120260706588143.pdf
A6: 2026-04-13 | B6: 2026년 8월 결산기 2분기 결산단신 | C6: https://www2.jpx.co.jp/disc/276A0/140120260410501502.pdf
A7: 2026-01-14 | B7: 2026년 8월 결산기 1분기 결산단신 | C7: https://www2.jpx.co.jp/disc/276A0/140120260109531363.pdf
A8: 2025-10-14 | B8: 2025년 8월 결산기 연간 결산단신 | C8: https://www2.jpx.co.jp/disc/276A0/140120251010572124.pdf
A9: 2025-07-14 | B9: 2025년 8월 결산기 ３분기 결산단신 | C9: https://www2.jpx.co.jp/disc/276A0/140120250714513706.pdf
A10: 2025-04-14 | B10: 2025년 8월 결산기 ２분기 결산단신 | C10: https://www2.jpx.co.jp/disc/276A0/140120250414514645.pdf
A11: 2025-01-14 | B11: 2025년 8월 결산기 １분기 결산단신 | C11: https://www2.jpx.co.jp/disc/276A0/140120250114550530.pdf
