Workbook

Sheet 연간
A1: 285A Model
A2: 모를 땐 보수적으로 | B2: (단위: 백만엔) | C2: 3월 결산 · IFRS · 2027.1Q = 2027년 3월 결산기 1분기 | Y2: (추정: 파란 글씨 = 직접 입력)
A3: 항목 | B3: 참고 | C3: 2024.2Q | D3: 2024.3Q | E3: 2024.4Q | F3: 2025.1Q | G3: 2025.2Q | H3: 2025.3Q | I3: 2025.4Q | J3: 2026.1Q | K3: 2026.2Q | L3: 2026.3Q | M3: 2026.4Q | N3: 2027.1Q | O3: 2017 | P3: 2018 | Q3: 2019 | R3: 2020 | S3: 2021 | T3: 2022 | U3: 2023 | V3: 2024 | W3: 2025 | X3: 2026 | Y3: 2027(MW) | Z3: 2028(MW) | AA3: 2029(MW) | AB3: 2030(MW) | AC3: 2031(MW)
A4: 매출액 | B4: MW 직접 입력 | E4: 322078 | F4: 428497 | G4: 480911 | H4: 449958 | I4: 347094 | J4: 342799 | K4: 448346 | L4: 543631 | M4: 1002852 | N4: 1767117 | V4: 1076584 | W4: 1706460 | X4: 2337628 | Y4: =IF(COUNT(Y7)=0,"",SUM(Y7)) | Z4: =IF(COUNT(Z7)=0,"",SUM(Z7)) | AA4: =IF(COUNT(AA7)=0,"",SUM(AA7)) | AB4: =IF(COUNT(AB7)=0,"",SUM(AB7)) | AC4: =IF(COUNT(AC7)=0,"",SUM(AC7))
A5: YoY | G5: =IF(OR(G4="",C4=""),"",IFERROR(G4/C4-1,"")) | H5: =IF(OR(H4="",D4=""),"",IFERROR(H4/D4-1,"")) | I5: =IF(OR(I4="",E4=""),"",IFERROR(I4/E4-1,"")) | J5: =IF(OR(J4="",F4=""),"",IFERROR(J4/F4-1,"")) | K5: =IF(OR(K4="",G4=""),"",IFERROR(K4/G4-1,"")) | L5: =IF(OR(L4="",H4=""),"",IFERROR(L4/H4-1,"")) | M5: =IF(OR(M4="",I4=""),"",IFERROR(M4/I4-1,"")) | N5: =IF(OR(N4="",J4=""),"",IFERROR(N4/J4-1,"")) | P5: =IF(OR(P4="",O4=""),"",IFERROR(P4/O4-1,"")) | Q5: =IF(OR(Q4="",P4=""),"",IFERROR(Q4/P4-1,"")) | R5: =IF(OR(R4="",Q4=""),"",IFERROR(R4/Q4-1,"")) | S5: =IF(OR(S4="",R4=""),"",IFERROR(S4/R4-1,"")) | T5: =IF(OR(T4="",S4=""),"",IFERROR(T4/S4-1,"")) | U5: =IF(OR(U4="",T4=""),"",IFERROR(U4/T4-1,"")) | V5: =IF(OR(V4="",U4=""),"",IFERROR(V4/U4-1,"")) | W5: =IF(OR(W4="",V4=""),"",IFERROR(W4/V4-1,"")) | ... AC5: =IF(OR(AC4="",AB4=""),"",IFERROR(AC4/AB4-1,""))
A6: 제품별 매출 분류 | B6: 사업보고서 매출실적
A7: (제품별 매출 미공시 — 직접 입력)
A8: 비중 | C8: =IF(OR(C7="",C4=""),"",IFERROR(C7/C4,"")) | D8: =IF(OR(D7="",D4=""),"",IFERROR(D7/D4,"")) | E8: =IF(OR(E7="",E4=""),"",IFERROR(E7/E4,"")) | F8: =IF(OR(F7="",F4=""),"",IFERROR(F7/F4,"")) | G8: =IF(OR(G7="",G4=""),"",IFERROR(G7/G4,"")) | H8: =IF(OR(H7="",H4=""),"",IFERROR(H7/H4,"")) | I8: =IF(OR(I7="",I4=""),"",IFERROR(I7/I4,"")) | J8: =IF(OR(J7="",J4=""),"",IFERROR(J7/J4,"")) | ... AC8: =IF(OR(AC7="",AC4=""),"",IFERROR(AC7/AC4,""))
A9: YoY | G9: =IF(OR(G7="",C7=""),"",IFERROR(G7/C7-1,"")) | H9: =IF(OR(H7="",D7=""),"",IFERROR(H7/D7-1,"")) | I9: =IF(OR(I7="",E7=""),"",IFERROR(I7/E7-1,"")) | J9: =IF(OR(J7="",F7=""),"",IFERROR(J7/F7-1,"")) | K9: =IF(OR(K7="",G7=""),"",IFERROR(K7/G7-1,"")) | L9: =IF(OR(L7="",H7=""),"",IFERROR(L7/H7-1,"")) | M9: =IF(OR(M7="",I7=""),"",IFERROR(M7/I7-1,"")) | N9: =IF(OR(N7="",J7=""),"",IFERROR(N7/J7-1,"")) | P9: =IF(OR(P7="",O7=""),"",IFERROR(P7/O7-1,"")) | Q9: =IF(OR(Q7="",P7=""),"",IFERROR(Q7/P7-1,"")) | R9: =IF(OR(R7="",Q7=""),"",IFERROR(R7/Q7-1,"")) | S9: =IF(OR(S7="",R7=""),"",IFERROR(S7/R7-1,"")) | T9: =IF(OR(T7="",S7=""),"",IFERROR(T7/S7-1,"")) | U9: =IF(OR(U7="",T7=""),"",IFERROR(U7/T7-1,"")) | V9: =IF(OR(V7="",U7=""),"",IFERROR(V7/U7-1,"")) | W9: =IF(OR(W7="",V7=""),"",IFERROR(W7/V7-1,"")) | ... AC9: =IF(OR(AC7="",AB7=""),"",IFERROR(AC7/AB7-1,""))
A10: 매출원가
A11: 전체 매출원가 | E11: 247291 | F11: 271905 | G11: 284460 | H11: 297584 | I11: 283078 | J11: 271620 | K11: 326208 | L11: 366991 | M11: 359905 | N11: 387051 | V11: 1205927 | W11: 1137027 | X11: 1324724
A12: 매출총이익 | C12: =IF(OR(C4="",C11=""),"",IFERROR(C4-C11,"")) | D12: =IF(OR(D4="",D11=""),"",IFERROR(D4-D11,"")) | E12: =IF(OR(E4="",E11=""),"",IFERROR(E4-E11,"")) | F12: =IF(OR(F4="",F11=""),"",IFERROR(F4-F11,"")) | G12: =IF(OR(G4="",G11=""),"",IFERROR(G4-G11,"")) | H12: =IF(OR(H4="",H11=""),"",IFERROR(H4-H11,"")) | I12: =IF(OR(I4="",I11=""),"",IFERROR(I4-I11,"")) | J12: =IF(OR(J4="",J11=""),"",IFERROR(J4-J11,"")) | ... X12: =IF(OR(X4="",X11=""),"",IFERROR(X4-X11,""))
A13: GPM | C13: =IF(OR(C12="",C4=""),"",IFERROR(C12/C4,"")) | D13: =IF(OR(D12="",D4=""),"",IFERROR(D12/D4,"")) | E13: =IF(OR(E12="",E4=""),"",IFERROR(E12/E4,"")) | F13: =IF(OR(F12="",F4=""),"",IFERROR(F12/F4,"")) | G13: =IF(OR(G12="",G4=""),"",IFERROR(G12/G4,"")) | H13: =IF(OR(H12="",H4=""),"",IFERROR(H12/H4,"")) | I13: =IF(OR(I12="",I4=""),"",IFERROR(I12/I4,"")) | J13: =IF(OR(J12="",J4=""),"",IFERROR(J12/J4,"")) | ... AC13: =IF(OR(AC12="",AC4=""),"",IFERROR(AC12/AC4,""))
A14: 판매관리비
A15: 전체 판관비 | E15: 31478 | F15: 31001 | G15: 31631 | H15: 34778 | I15: 30441 | J15: 29847 | K15: 36235 | L15: 33847 | M15: 46652 | N15: 71727 | V15: 128774 | W15: 127851 | X15: 146581
A16: 영업이익 | B16: MW = 매출 × OPM | E16: 43858 | F16: 125859 | G16: 166032 | H16: 122715 | I16: 37142 | J16: 44899 | K16: 85921 | L16: 142754 | M16: 596795 | N16: 1270017 | V16: -252698 | W16: 451748 | X16: 870369 | Y16: =IF(OR(Y4="",Y17=""),"",IFERROR(Y4*Y17,"")) | Z16: =IF(OR(Z4="",Z17=""),"",IFERROR(Z4*Z17,"")) | AA16: =IF(OR(AA4="",AA17=""),"",IFERROR(AA4*AA17,"")) | AB16: =IF(OR(AB4="",AB17=""),"",IFERROR(AB4*AB17,"")) | AC16: =IF(OR(AC4="",AC17=""),"",IFERROR(AC4*AC17,""))
A17: OPM | B17: MW 입력 | C17: =IF(OR(C16="",C4=""),"",IFERROR(C16/C4,"")) | D17: =IF(OR(D16="",D4=""),"",IFERROR(D16/D4,"")) | E17: =IF(OR(E16="",E4=""),"",IFERROR(E16/E4,"")) | F17: =IF(OR(F16="",F4=""),"",IFERROR(F16/F4,"")) | G17: =IF(OR(G16="",G4=""),"",IFERROR(G16/G4,"")) | H17: =IF(OR(H16="",H4=""),"",IFERROR(H16/H4,"")) | I17: =IF(OR(I16="",I4=""),"",IFERROR(I16/I4,"")) | J17: =IF(OR(J16="",J4=""),"",IFERROR(J16/J4,"")) | ... X17: =IF(OR(X16="",X4=""),"",IFERROR(X16/X4,""))
A18: 증가율 | G18: =IF(OR(G16="",C16=""),"",IFERROR(G16/C16-1,"")) | H18: =IF(OR(H16="",D16=""),"",IFERROR(H16/D16-1,"")) | I18: =IF(OR(I16="",E16=""),"",IFERROR(I16/E16-1,"")) | J18: =IF(OR(J16="",F16=""),"",IFERROR(J16/F16-1,"")) | K18: =IF(OR(K16="",G16=""),"",IFERROR(K16/G16-1,"")) | L18: =IF(OR(L16="",H16=""),"",IFERROR(L16/H16-1,"")) | M18: =IF(OR(M16="",I16=""),"",IFERROR(M16/I16-1,"")) | N18: =IF(OR(N16="",J16=""),"",IFERROR(N16/J16-1,"")) | P18: =IF(OR(P16="",O16=""),"",IFERROR(P16/O16-1,"")) | Q18: =IF(OR(Q16="",P16=""),"",IFERROR(Q16/P16-1,"")) | R18: =IF(OR(R16="",Q16=""),"",IFERROR(R16/Q16-1,"")) | S18: =IF(OR(S16="",R16=""),"",IFERROR(S16/R16-1,"")) | T18: =IF(OR(T16="",S16=""),"",IFERROR(T16/S16-1,"")) | U18: =IF(OR(U16="",T16=""),"",IFERROR(U16/T16-1,"")) | V18: =IF(OR(V16="",U16=""),"",IFERROR(V16/U16-1,"")) | W18: =IF(OR(W16="",V16=""),"",IFERROR(W16/V16-1,"")) | ... AC18: =IF(OR(AC16="",AB16=""),"",IFERROR(AC16/AB16-1,""))
A19: 비용의 성격별 분류 | B19: 참고 데이터
A20: 총 판관비 | O20: =IF(O15="","",O15) | P20: =IF(P15="","",P15) | Q20: =IF(Q15="","",Q15) | R20: =IF(R15="","",R15) | S20: =IF(S15="","",S15) | T20: =IF(T15="","",T15) | U20: =IF(U15="","",U15) | V20: =IF(V15="","",V15) | ... X20: =IF(X15="","",X15)
A21: 급여 | B21: 고정비
A22: % of Sales | O22: =IF(OR(O21="",O4=""),"",IFERROR(O21/O4,"")) | P22: =IF(OR(P21="",P4=""),"",IFERROR(P21/P4,"")) | Q22: =IF(OR(Q21="",Q4=""),"",IFERROR(Q21/Q4,"")) | R22: =IF(OR(R21="",R4=""),"",IFERROR(R21/R4,"")) | S22: =IF(OR(S21="",S4=""),"",IFERROR(S21/S4,"")) | T22: =IF(OR(T21="",T4=""),"",IFERROR(T21/T4,"")) | U22: =IF(OR(U21="",U4=""),"",IFERROR(U21/U4,"")) | V22: =IF(OR(V21="",V4=""),"",IFERROR(V21/V4,"")) | ... X22: =IF(OR(X21="",X4=""),"",IFERROR(X21/X4,""))
A23: 감가상각비 | B23: 고정비
A24: % of Sales | O24: =IF(OR(O23="",O4=""),"",IFERROR(O23/O4,"")) | P24: =IF(OR(P23="",P4=""),"",IFERROR(P23/P4,"")) | Q24: =IF(OR(Q23="",Q4=""),"",IFERROR(Q23/Q4,"")) | R24: =IF(OR(R23="",R4=""),"",IFERROR(R23/R4,"")) | S24: =IF(OR(S23="",S4=""),"",IFERROR(S23/S4,"")) | T24: =IF(OR(T23="",T4=""),"",IFERROR(T23/T4,"")) | U24: =IF(OR(U23="",U4=""),"",IFERROR(U23/U4,"")) | V24: =IF(OR(V23="",V4=""),"",IFERROR(V23/V4,"")) | ... X24: =IF(OR(X23="",X4=""),"",IFERROR(X23/X4,""))
A25: 지급수수료 | B25: 고정비
A26: % of Sales | O26: =IF(OR(O25="",O4=""),"",IFERROR(O25/O4,"")) | P26: =IF(OR(P25="",P4=""),"",IFERROR(P25/P4,"")) | Q26: =IF(OR(Q25="",Q4=""),"",IFERROR(Q25/Q4,"")) | R26: =IF(OR(R25="",R4=""),"",IFERROR(R25/R4,"")) | S26: =IF(OR(S25="",S4=""),"",IFERROR(S25/S4,"")) | T26: =IF(OR(T25="",T4=""),"",IFERROR(T25/T4,"")) | U26: =IF(OR(U25="",U4=""),"",IFERROR(U25/U4,"")) | V26: =IF(OR(V25="",V4=""),"",IFERROR(V25/V4,"")) | ... X26: =IF(OR(X25="",X4=""),"",IFERROR(X25/X4,""))
A27: 연구개발비 | B27: 변동비
A28: % of Sales | O28: =IF(OR(O27="",O4=""),"",IFERROR(O27/O4,"")) | P28: =IF(OR(P27="",P4=""),"",IFERROR(P27/P4,"")) | Q28: =IF(OR(Q27="",Q4=""),"",IFERROR(Q27/Q4,"")) | R28: =IF(OR(R27="",R4=""),"",IFERROR(R27/R4,"")) | S28: =IF(OR(S27="",S4=""),"",IFERROR(S27/S4,"")) | T28: =IF(OR(T27="",T4=""),"",IFERROR(T27/T4,"")) | U28: =IF(OR(U27="",U4=""),"",IFERROR(U27/U4,"")) | V28: =IF(OR(V27="",V4=""),"",IFERROR(V27/V4,"")) | ... X28: =IF(OR(X27="",X4=""),"",IFERROR(X27/X4,""))
A29: 기타비용 | B29: 변동비 | O29: =IF(OR(O20="",O21="",O23="",O25="",O27=""),"",IFERROR(O20-O21-O23-O25-O27,"")) | P29: =IF(OR(P20="",P21="",P23="",P25="",P27=""),"",IFERROR(P20-P21-P23-P25-P27,"")) | Q29: =IF(OR(Q20="",Q21="",Q23="",Q25="",Q27=""),"",IFERROR(Q20-Q21-Q23-Q25-Q27,"")) | R29: =IF(OR(R20="",R21="",R23="",R25="",R27=""),"",IFERROR(R20-R21-R23-R25-R27,"")) | S29: =IF(OR(S20="",S21="",S23="",S25="",S27=""),"",IFERROR(S20-S21-S23-S25-S27,"")) | T29: =IF(OR(T20="",T21="",T23="",T25="",T27=""),"",IFERROR(T20-T21-T23-T25-T27,"")) | U29: =IF(OR(U20="",U21="",U23="",U25="",U27=""),"",IFERROR(U20-U21-U23-U25-U27,"")) | V29: =IF(OR(V20="",V21="",V23="",V25="",V27=""),"",IFERROR(V20-V21-V23-V25-V27,"")) | ... X29: =IF(OR(X20="",X21="",X23="",X25="",X27=""),"",IFERROR(X20-X21-X23-X25-X27,""))
A30: % of Sales | O30: =IF(OR(O29="",O4=""),"",IFERROR(O29/O4,"")) | P30: =IF(OR(P29="",P4=""),"",IFERROR(P29/P4,"")) | Q30: =IF(OR(Q29="",Q4=""),"",IFERROR(Q29/Q4,"")) | R30: =IF(OR(R29="",R4=""),"",IFERROR(R29/R4,"")) | S30: =IF(OR(S29="",S4=""),"",IFERROR(S29/S4,"")) | T30: =IF(OR(T29="",T4=""),"",IFERROR(T29/T4,"")) | U30: =IF(OR(U29="",U4=""),"",IFERROR(U29/U4,"")) | V30: =IF(OR(V29="",V4=""),"",IFERROR(V29/V4,"")) | ... X30: =IF(OR(X29="",X4=""),"",IFERROR(X29/X4,""))
A31: 당기순이익 추정
A32: 기타이익 | E32: 9000 | F32: 1477 | G32: 2586 | H32: 6109 | I32: 4503 | J32: 3921 | K32: 1569 | L32: 1262 | M32: 2150 | N32: 530 | V32: 19676 | W32: 14675 | X32: 8902 | Y32: =IF(OR(Y4="",Y33=""),"",IFERROR(Y4*Y33,"")) | Z32: =IF(OR(Z4="",Z33=""),"",IFERROR(Z4*Z33,"")) | AA32: =IF(OR(AA4="",AA33=""),"",IFERROR(AA4*AA33,"")) | AB32: =IF(OR(AB4="",AB33=""),"",IFERROR(AB4*AB33,"")) | AC32: =IF(OR(AC4="",AC33=""),"",IFERROR(AC4*AC33,""))
A33: % of Sales | B33: MW = 최근 3년 평균 | C33: =IF(OR(C32="",C4=""),"",IFERROR(C32/C4,"")) | D33: =IF(OR(D32="",D4=""),"",IFERROR(D32/D4,"")) | E33: =IF(OR(E32="",E4=""),"",IFERROR(E32/E4,"")) | F33: =IF(OR(F32="",F4=""),"",IFERROR(F32/F4,"")) | G33: =IF(OR(G32="",G4=""),"",IFERROR(G32/G4,"")) | H33: =IF(OR(H32="",H4=""),"",IFERROR(H32/H4,"")) | I33: =IF(OR(I32="",I4=""),"",IFERROR(I32/I4,"")) | J33: =IF(OR(J32="",J4=""),"",IFERROR(J32/J4,"")) | ... X33: =IF(OR(X32="",X4=""),"",IFERROR(X32/X4,"")) | Y33: =IFERROR(AVERAGE(V33,W33,X33),"") | Z33: =Y33 | AA33: =Z33 | AB33: =AA33 | AC33: =AB33
A34: 기타손실 | E34: 8451 | F34: 1209 | G34: 1374 | H34: 990 | I34: 936 | J34: 354 | K34: 1551 | L34: 1301 | M34: 1650 | N34: 38852 | V34: 14257 | W34: 4509 | X34: 4856 | Y34: =IF(OR(Y4="",Y35=""),"",IFERROR(Y4*Y35,"")) | Z34: =IF(OR(Z4="",Z35=""),"",IFERROR(Z4*Z35,"")) | AA34: =IF(OR(AA4="",AA35=""),"",IFERROR(AA4*AA35,"")) | AB34: =IF(OR(AB4="",AB35=""),"",IFERROR(AB4*AB35,"")) | AC34: =IF(OR(AC4="",AC35=""),"",IFERROR(AC4*AC35,""))
A35: % of Sales | C35: =IF(OR(C34="",C4=""),"",IFERROR(C34/C4,"")) | D35: =IF(OR(D34="",D4=""),"",IFERROR(D34/D4,"")) | E35: =IF(OR(E34="",E4=""),"",IFERROR(E34/E4,"")) | F35: =IF(OR(F34="",F4=""),"",IFERROR(F34/F4,"")) | G35: =IF(OR(G34="",G4=""),"",IFERROR(G34/G4,"")) | H35: =IF(OR(H34="",H4=""),"",IFERROR(H34/H4,"")) | I35: =IF(OR(I34="",I4=""),"",IFERROR(I34/I4,"")) | J35: =IF(OR(J34="",J4=""),"",IFERROR(J34/J4,"")) | ... X35: =IF(OR(X34="",X4=""),"",IFERROR(X34/X4,"")) | Y35: =IFERROR(AVERAGE(V35,W35,X35),"") | Z35: =Y35 | AA35: =Z35 | AB35: =AA35 | AC35: =AB35
A36: 금융수익 | E36: 11 | F36: 199 | G36: 1231 | H36: 1135 | I36: 1142 | J36: 2398 | K36: -402 | L36: 1608 | M36: 5895 | N36: 17170 | V36: 1847 | W36: 3707 | X36: 9499 | Y36: =IF(OR(Y4="",Y37=""),"",IFERROR(Y4*Y37,"")) | Z36: =IF(OR(Z4="",Z37=""),"",IFERROR(Z4*Z37,"")) | AA36: =IF(OR(AA4="",AA37=""),"",IFERROR(AA4*AA37,"")) | AB36: =IF(OR(AB4="",AB37=""),"",IFERROR(AB4*AB37,"")) | AC36: =IF(OR(AC4="",AC37=""),"",IFERROR(AC4*AC37,""))
A37: % of Sales | C37: =IF(OR(C36="",C4=""),"",IFERROR(C36/C4,"")) | D37: =IF(OR(D36="",D4=""),"",IFERROR(D36/D4,"")) | E37: =IF(OR(E36="",E4=""),"",IFERROR(E36/E4,"")) | F37: =IF(OR(F36="",F4=""),"",IFERROR(F36/F4,"")) | G37: =IF(OR(G36="",G4=""),"",IFERROR(G36/G4,"")) | H37: =IF(OR(H36="",H4=""),"",IFERROR(H36/H4,"")) | I37: =IF(OR(I36="",I4=""),"",IFERROR(I36/I4,"")) | J37: =IF(OR(J36="",J4=""),"",IFERROR(J36/J4,"")) | ... X37: =IF(OR(X36="",X4=""),"",IFERROR(X36/X4,"")) | Y37: =IFERROR(AVERAGE(V37,W37,X37),"") | Z37: =Y37 | AA37: =Z37 | AB37: =AA37 | AC37: =AB37
A38: 금융원가 | E38: 26856 | F38: 26192 | G38: 18282 | H38: 17428 | I38: 23426 | J38: 19860 | K38: 29102 | L38: 22769 | M38: 24977 | N38: 52801 | V38: 92740 | W38: 85328 | X38: 96708 | Y38: =IF(OR(Y4="",Y39=""),"",IFERROR(Y4*Y39,"")) | Z38: =IF(OR(Z4="",Z39=""),"",IFERROR(Z4*Z39,"")) | AA38: =IF(OR(AA4="",AA39=""),"",IFERROR(AA4*AA39,"")) | AB38: =IF(OR(AB4="",AB39=""),"",IFERROR(AB4*AB39,"")) | AC38: =IF(OR(AC4="",AC39=""),"",IFERROR(AC4*AC39,""))
A39: % of Sales | C39: =IF(OR(C38="",C4=""),"",IFERROR(C38/C4,"")) | D39: =IF(OR(D38="",D4=""),"",IFERROR(D38/D4,"")) | E39: =IF(OR(E38="",E4=""),"",IFERROR(E38/E4,"")) | F39: =IF(OR(F38="",F4=""),"",IFERROR(F38/F4,"")) | G39: =IF(OR(G38="",G4=""),"",IFERROR(G38/G4,"")) | H39: =IF(OR(H38="",H4=""),"",IFERROR(H38/H4,"")) | I39: =IF(OR(I38="",I4=""),"",IFERROR(I38/I4,"")) | J39: =IF(OR(J38="",J4=""),"",IFERROR(J38/J4,"")) | ... X39: =IF(OR(X38="",X4=""),"",IFERROR(X38/X4,"")) | Y39: =IFERROR(AVERAGE(V39,W39,X39),"") | Z39: =Y39 | AA39: =Z39 | AB39: =AA39 | AC39: =AB39
A40: 법인세비용차감전순이익(손실) | E40: 17159 | F40: 99746 | G40: 149173 | H40: 106687 | I40: 15063 | J40: 27294 | K40: 56716 | L40: 121740 | M40: 578345 | N40: 1234720 | V40: -343330 | W40: 370669 | X40: 784095 | Y40: =IF(OR(Y16=""),"",IFERROR(Y16+N(Y32)-N(Y34)+N(Y36)-N(Y38),"")) | Z40: =IF(OR(Z16=""),"",IFERROR(Z16+N(Z32)-N(Z34)+N(Z36)-N(Z38),"")) | AA40: =IF(OR(AA16=""),"",IFERROR(AA16+N(AA32)-N(AA34)+N(AA36)-N(AA38),"")) | AB40: =IF(OR(AB16=""),"",IFERROR(AB16+N(AB32)-N(AB34)+N(AB36)-N(AB38),"")) | AC40: =IF(OR(AC16=""),"",IFERROR(AC16+N(AC32)-N(AC34)+N(AC36)-N(AC38),""))
A41: 법인세비용(수익) | E41: 6906 | F41: 29988 | G41: 42951 | H41: 30612 | I41: -5203 | J41: 9021 | K41: 16046 | L41: 33926 | M41: 170606 | N41: 392549 | V41: -99609 | W41: 98348 | X41: 229599 | Y41: =IF(OR(Y40="",Y42=""),"",IFERROR(MAX(Y40,0)*Y42,"")) | Z41: =IF(OR(Z40="",Z42=""),"",IFERROR(MAX(Z40,0)*Z42,"")) | AA41: =IF(OR(AA40="",AA42=""),"",IFERROR(MAX(AA40,0)*AA42,"")) | AB41: =IF(OR(AB40="",AB42=""),"",IFERROR(MAX(AB40,0)*AB42,"")) | AC41: =IF(OR(AC40="",AC42=""),"",IFERROR(MAX(AC40,0)*AC42,""))
A42: 법인세율 | B42: MW 기본 30% | C42: =IF(OR(C41="",C40=""),"",IFERROR(C41/C40,"")) | D42: =IF(OR(D41="",D40=""),"",IFERROR(D41/D40,"")) | E42: =IF(OR(E41="",E40=""),"",IFERROR(E41/E40,"")) | F42: =IF(OR(F41="",F40=""),"",IFERROR(F41/F40,"")) | G42: =IF(OR(G41="",G40=""),"",IFERROR(G41/G40,"")) | H42: =IF(OR(H41="",H40=""),"",IFERROR(H41/H40,"")) | I42: =IF(OR(I41="",I40=""),"",IFERROR(I41/I40,"")) | J42: =IF(OR(J41="",J40=""),"",IFERROR(J41/J40,"")) | ... X42: =IF(OR(X41="",X40=""),"",IFERROR(X41/X40,"")) | Y42: 0.3 | Z42: 0.3 | AA42: 0.3 | AB42: 0.3 | AC42: 0.3
A43: 당기순이익(손실) | E43: 10253 | F43: 69758 | G43: 106222 | H43: 76075 | I43: 20266 | J43: 18273 | K43: 40670 | L43: 87814 | M43: 407739 | N43: 842171 | V43: -243721 | W43: 272321 | X43: 554496 | Y43: =IF(OR(Y40=""),"",IFERROR(Y40-Y41,"")) | Z43: =IF(OR(Z40=""),"",IFERROR(Z40-Z41,"")) | AA43: =IF(OR(AA40=""),"",IFERROR(AA40-AA41,"")) | AB43: =IF(OR(AB40=""),"",IFERROR(AB40-AB41,"")) | AC43: =IF(OR(AC40=""),"",IFERROR(AC40-AC41,""))
A44: 지배주주 순이익 | E44: 10246 | F44: 69758 | G44: 106222 | H44: 76068 | I44: 20267 | J44: 18284 | K44: 40662 | L44: 87810 | M44: 407734 | N44: 842165 | V44: -243728 | W44: 272315 | X44: 554490 | Y44: =IF(OR(Y43="",Y45=""),"",IFERROR(Y43*Y45,"")) | Z44: =IF(OR(Z43="",Z45=""),"",IFERROR(Z43*Z45,"")) | AA44: =IF(OR(AA43="",AA45=""),"",IFERROR(AA43*AA45,"")) | AB44: =IF(OR(AB43="",AB45=""),"",IFERROR(AB43*AB45,"")) | AC44: =IF(OR(AC43="",AC45=""),"",IFERROR(AC43*AC45,""))
A45: 지배주주 순이익률 | B45: MW 기본 100% | C45: =IF(OR(C44="",C43=""),"",IFERROR(C44/C43,"")) | D45: =IF(OR(D44="",D43=""),"",IFERROR(D44/D43,"")) | E45: =IF(OR(E44="",E43=""),"",IFERROR(E44/E43,"")) | F45: =IF(OR(F44="",F43=""),"",IFERROR(F44/F43,"")) | G45: =IF(OR(G44="",G43=""),"",IFERROR(G44/G43,"")) | H45: =IF(OR(H44="",H43=""),"",IFERROR(H44/H43,"")) | I45: =IF(OR(I44="",I43=""),"",IFERROR(I44/I43,"")) | J45: =IF(OR(J44="",J43=""),"",IFERROR(J44/J43,"")) | ... X45: =IF(OR(X44="",X43=""),"",IFERROR(X44/X43,"")) | Y45: 1 | Z45: 1 | AA45: 1 | AB45: 1 | AC45: 1
A46: 목표주가 산출
A47: 현재 주가 (2026.10.26) | B47: 12550
A48: 발행주식수 (보통주) | B48: 548015088
A49: 시가총액 (백만엔) | B49: =IF(OR(B47="",B48=""),"",B47*B48/1000000.0)
A50: OPM | O50: =IF(O17="","",O17) | P50: =IF(P17="","",P17) | Q50: =IF(Q17="","",Q17) | R50: =IF(R17="","",R17) | S50: =IF(S17="","",S17) | T50: =IF(T17="","",T17) | U50: =IF(U17="","",U17) | V50: =IF(V17="","",V17) | ... AC50: =IF(AC17="","",AC17)
A51: 지배주주 순이익 증가율 | P51: =IF(OR(P44="",O44=""),"",IFERROR(P44/O44-1,"")) | Q51: =IF(OR(Q44="",P44=""),"",IFERROR(Q44/P44-1,"")) | R51: =IF(OR(R44="",Q44=""),"",IFERROR(R44/Q44-1,"")) | S51: =IF(OR(S44="",R44=""),"",IFERROR(S44/R44-1,"")) | T51: =IF(OR(T44="",S44=""),"",IFERROR(T44/S44-1,"")) | U51: =IF(OR(U44="",T44=""),"",IFERROR(U44/T44-1,"")) | V51: =IF(OR(V44="",U44=""),"",IFERROR(V44/U44-1,"")) | W51: =IF(OR(W44="",V44=""),"",IFERROR(W44/V44-1,"")) | ... AC51: =IF(OR(AC44="",AB44=""),"",IFERROR(AC44/AB44-1,""))
A52: P/E (현재 주가) | B52: 시총 ÷ 지배순이익 | X52: =IF(OR($B$49="",X44=""),"",IFERROR($B$49/X44,"")) | Y52: =IF(OR($B$49="",Y44=""),"",IFERROR($B$49/Y44,"")) | Z52: =IF(OR($B$49="",Z44=""),"",IFERROR($B$49/Z44,"")) | AA52: =IF(OR($B$49="",AA44=""),"",IFERROR($B$49/AA44,"")) | AB52: =IF(OR($B$49="",AB44=""),"",IFERROR($B$49/AB44,"")) | AC52: =IF(OR($B$49="",AC44=""),"",IFERROR($B$49/AC44,""))
A53: Target P/E | B53: 직접 입력
A54: EPS | B54: 지배순이익 ÷ 주식수 | O54: =IF(OR(O44="",$B$48=""),"",IFERROR(O44*1000000.0/$B$48,"")) | P54: =IF(OR(P44="",$B$48=""),"",IFERROR(P44*1000000.0/$B$48,"")) | Q54: =IF(OR(Q44="",$B$48=""),"",IFERROR(Q44*1000000.0/$B$48,"")) | R54: =IF(OR(R44="",$B$48=""),"",IFERROR(R44*1000000.0/$B$48,"")) | S54: =IF(OR(S44="",$B$48=""),"",IFERROR(S44*1000000.0/$B$48,"")) | T54: =IF(OR(T44="",$B$48=""),"",IFERROR(T44*1000000.0/$B$48,"")) | U54: =IF(OR(U44="",$B$48=""),"",IFERROR(U44*1000000.0/$B$48,"")) | V54: =IF(OR(V44="",$B$48=""),"",IFERROR(V44*1000000.0/$B$48,"")) | ... AC54: =IF(OR(AC44="",$B$48=""),"",IFERROR(AC44*1000000.0/$B$48,""))
A55: 목표주가 | Y55: =IF(OR(Y54="",Y53=""),"",IFERROR(Y54*Y53,"")) | Z55: =IF(OR(Z54="",Z53=""),"",IFERROR(Z54*Z53,"")) | AA55: =IF(OR(AA54="",AA53=""),"",IFERROR(AA54*AA53,"")) | AB55: =IF(OR(AB54="",AB53=""),"",IFERROR(AB54*AB53,"")) | AC55: =IF(OR(AC54="",AC53=""),"",IFERROR(AC54*AC53,""))
A56: 상승여력 | Y56: =IF(OR(Y55="",$B$47=""),"",IFERROR(Y55/$B$47-1,"")) | Z56: =IF(OR(Z55="",$B$47=""),"",IFERROR(Z55/$B$47-1,"")) | AA56: =IF(OR(AA55="",$B$47=""),"",IFERROR(AA55/$B$47-1,"")) | AB56: =IF(OR(AB55="",$B$47=""),"",IFERROR(AB55/$B$47-1,"")) | AC56: =IF(OR(AC55="",$B$47=""),"",IFERROR(AC55/$B$47-1,""))
A57: 자산가치 산출 | B57: 최신 분기 BS
A58: 현금및현금성자산 | X58: ='재무상태표'!G6 | Y58: ='재무상태표'!G6 | Z58: ='재무상태표'!G6 | AA58: ='재무상태표'!G6 | AB58: ='재무상태표'!G6 | AC58: ='재무상태표'!G6
A59: 단기금융상품 | X59: ='재무상태표'!G7 | Y59: ='재무상태표'!G7 | Z59: ='재무상태표'!G7 | AA59: ='재무상태표'!G7 | AB59: ='재무상태표'!G7 | AC59: ='재무상태표'!G7
A60: 투자부동산 | X60: ='재무상태표'!G14 | Y60: ='재무상태표'!G14 | Z60: ='재무상태표'!G14 | AA60: ='재무상태표'!G14 | AB60: ='재무상태표'!G14 | AC60: ='재무상태표'!G14
A61: 지배자본 | X61: ='재무상태표'!G31 | Y61: ='재무상태표'!G31 | Z61: ='재무상태표'!G31 | AA61: ='재무상태표'!G31 | AB61: ='재무상태표'!G31 | AC61: ='재무상태표'!G31
A62: 부채 | X62: ='재무상태표'!G27 | Y62: ='재무상태표'!G27 | Z62: ='재무상태표'!G27 | AA62: ='재무상태표'!G27 | AB62: ='재무상태표'!G27 | AC62: ='재무상태표'!G27
A63: 부채비율 | X63: =IF(OR(X62="",X61=""),"",IFERROR(X62/X61,"")) | Y63: =IF(OR(Y62="",Y61=""),"",IFERROR(Y62/Y61,"")) | Z63: =IF(OR(Z62="",Z61=""),"",IFERROR(Z62/Z61,"")) | AA63: =IF(OR(AA62="",AA61=""),"",IFERROR(AA62/AA61,"")) | AB63: =IF(OR(AB62="",AB61=""),"",IFERROR(AB62/AB61,"")) | AC63: =IF(OR(AC62="",AC61=""),"",IFERROR(AC62/AC61,""))
A64: 자산가치 | B64: 현금+단기금융+투자부동산 | X64: =SUM(X58,X59,X60) | Y64: =SUM(Y58,Y59,Y60) | Z64: =SUM(Z58,Z59,Z60) | AA64: =SUM(AA58,AA59,AA60) | AB64: =SUM(AB58,AB59,AB60) | AC64: =SUM(AC58,AC59,AC60)
A65: 기업가치 산출
A66: 목표 시가총액 (P/E) | B66: 지배순이익 × Target P/E | Y66: =IF(OR(Y44="",Y53=""),"",IFERROR(Y44*Y53,"")) | Z66: =IF(OR(Z44="",Z53=""),"",IFERROR(Z44*Z53,"")) | AA66: =IF(OR(AA44="",AA53=""),"",IFERROR(AA44*AA53,"")) | AB66: =IF(OR(AB44="",AB53=""),"",IFERROR(AB44*AB53,"")) | AC66: =IF(OR(AC44="",AC53=""),"",IFERROR(AC44*AC53,""))
A67: 기업가치 | B67: 목표시총 + 자산가치 | Y67: =IF(OR(Y66=""),"",IFERROR(Y66+Y64,"")) | Z67: =IF(OR(Z66=""),"",IFERROR(Z66+Z64,"")) | AA67: =IF(OR(AA66=""),"",IFERROR(AA66+AA64,"")) | AB67: =IF(OR(AB66=""),"",IFERROR(AB66+AB64,"")) | AC67: =IF(OR(AC66=""),"",IFERROR(AC66+AC64,""))
A68: 현재 시가총액 | Y68: =$B$49 | Z68: =$B$49 | AA68: =$B$49 | AB68: =$B$49 | AC68: =$B$49
A69: 상승여력 | Y69: =IF(OR(Y67="",Y68=""),"",IFERROR(Y67/Y68-1,"")) | Z69: =IF(OR(Z67="",Z68=""),"",IFERROR(Z67/Z68-1,"")) | AA69: =IF(OR(AA67="",AA68=""),"",IFERROR(AA67/AA68-1,"")) | AB69: =IF(OR(AB67="",AB68=""),"",IFERROR(AB67/AB68-1,"")) | AC69: =IF(OR(AC67="",AC68=""),"",IFERROR(AC67/AC68-1,""))
A71: 출처
A72: 결산단신 XBRL(TDnet·JPX 보관소) — 쓴 문서는 '출처' 시트
A73: 분기 = 누계에서 앞 분기를 뺀 3개월 값
A74: 주가: 야후 파이낸스 일봉 2026.10.26
A76: 손익계산서 · 전 항목 | B76: 분기 = 3개월 단독
A77: 항목 | B77: 참고 | C77: 2024.2Q | D77: 2024.3Q | E77: 2024.4Q | F77: 2025.1Q | G77: 2025.2Q | H77: 2025.3Q | I77: 2025.4Q | J77: 2026.1Q | K77: 2026.2Q | L77: 2026.3Q | M77: 2026.4Q | N77: 2027.1Q | O77: 2017 | P77: 2018 | Q77: 2019 | R77: 2020 | S77: 2021 | T77: 2022 | U77: 2023 | V77: 2024 | W77: 2025 | X77: 2026 | Y77: 2027(MW) | Z77: 2028(MW) | AA77: 2029(MW) | AB77: 2030(MW) | AC77: 2031(MW)
A78: 매출수익 | E78: 322078 | F78: 428497 | G78: 480911 | H78: 449958 | I78: 347094 | J78: 342799 | K78: 448346 | L78: 543631 | M78: 1002852 | N78: 1767117 | V78: 322078 | W78: 347094 | X78: 1002852
A79: YoY | B79: 전년 같은 분기·전년 대비 | G79: =IF(OR(G78="",C78=""),"",IF(C78<=0,"",IFERROR(G78/C78-1,""))) | H79: =IF(OR(H78="",D78=""),"",IF(D78<=0,"",IFERROR(H78/D78-1,""))) | I79: =IF(OR(I78="",E78=""),"",IF(E78<=0,"",IFERROR(I78/E78-1,""))) | J79: =IF(OR(J78="",F78=""),"",IF(F78<=0,"",IFERROR(J78/F78-1,""))) | K79: =IF(OR(K78="",G78=""),"",IF(G78<=0,"",IFERROR(K78/G78-1,""))) | L79: =IF(OR(L78="",H78=""),"",IF(H78<=0,"",IFERROR(L78/H78-1,""))) | M79: =IF(OR(M78="",I78=""),"",IF(I78<=0,"",IFERROR(M78/I78-1,""))) | N79: =IF(OR(N78="",J78=""),"",IF(J78<=0,"",IFERROR(N78/J78-1,""))) | V79: =IF(OR(V78="",U78=""),"",IF(U78<=0,"",IFERROR(V78/U78-1,""))) | W79: =IF(OR(W78="",V78=""),"",IF(V78<=0,"",IFERROR(W78/V78-1,""))) | X79: =IF(OR(X78="",W78=""),"",IF(W78<=0,"",IFERROR(X78/W78-1,"")))
A80: 매출원가 | E80: 247291 | F80: 271905 | G80: 284460 | H80: 297584 | I80: 283078 | J80: 271620 | K80: 326208 | L80: 366991 | M80: 359905 | N80: 387051 | V80: 247291 | W80: 283078 | X80: 359905
A81: 매출총이익 | E81: 74787 | F81: 156592 | G81: 196451 | H81: 152374 | I81: 64016 | J81: 71179 | K81: 122138 | L81: 176640 | M81: 642947 | N81: 1380066 | V81: 74787 | W81: 64016 | X81: 642947
A82: YoY | B82: 전년 같은 분기·전년 대비 | G82: =IF(OR(G81="",C81=""),"",IF(C81<=0,"",IFERROR(G81/C81-1,""))) | H82: =IF(OR(H81="",D81=""),"",IF(D81<=0,"",IFERROR(H81/D81-1,""))) | I82: =IF(OR(I81="",E81=""),"",IF(E81<=0,"",IFERROR(I81/E81-1,""))) | J82: =IF(OR(J81="",F81=""),"",IF(F81<=0,"",IFERROR(J81/F81-1,""))) | K82: =IF(OR(K81="",G81=""),"",IF(G81<=0,"",IFERROR(K81/G81-1,""))) | L82: =IF(OR(L81="",H81=""),"",IF(H81<=0,"",IFERROR(L81/H81-1,""))) | M82: =IF(OR(M81="",I81=""),"",IF(I81<=0,"",IFERROR(M81/I81-1,""))) | N82: =IF(OR(N81="",J81=""),"",IF(J81<=0,"",IFERROR(N81/J81-1,""))) | V82: =IF(OR(V81="",U81=""),"",IF(U81<=0,"",IFERROR(V81/U81-1,""))) | W82: =IF(OR(W81="",V81=""),"",IF(V81<=0,"",IFERROR(W81/V81-1,""))) | X82: =IF(OR(X81="",W81=""),"",IF(W81<=0,"",IFERROR(X81/W81-1,"")))
A83: 판매비와 관리비 | E83: 31478 | F83: 31001 | G83: 31631 | H83: 34778 | I83: 30441 | J83: 29847 | K83: 36235 | L83: 33847 | M83: 46652 | N83: 71727 | V83: 31478 | W83: 30441 | X83: 46652
A84: Other Income | E84: 9000 | F84: 1477 | G84: 2586 | H84: 6109 | I84: 4503 | J84: 3921 | K84: 1569 | L84: 1262 | M84: 2150 | N84: 530 | V84: 9000 | W84: 4503 | X84: 2150
A85: 기타비용 | E85: 8451 | F85: 1209 | G85: 1374 | H85: 990 | I85: 936 | J85: 354 | K85: 1551 | L85: 1301 | M85: 1650 | N85: 38852 | V85: 8451 | W85: 936 | X85: 1650
A86: 영업이익 | E86: 43858 | F86: 125859 | G86: 166032 | H86: 122715 | I86: 37142 | J86: 44899 | K86: 85921 | L86: 142754 | M86: 596795 | N86: 1270017 | V86: 43858 | W86: 37142 | X86: 596795
A87: OPM | B87: 영업이익 ÷ 매출 | E87: =IF(OR(E86="",E78=""),"",IF(E78<=0,"",IFERROR(E86/E78,""))) | F87: =IF(OR(F86="",F78=""),"",IF(F78<=0,"",IFERROR(F86/F78,""))) | G87: =IF(OR(G86="",G78=""),"",IF(G78<=0,"",IFERROR(G86/G78,""))) | H87: =IF(OR(H86="",H78=""),"",IF(H78<=0,"",IFERROR(H86/H78,""))) | I87: =IF(OR(I86="",I78=""),"",IF(I78<=0,"",IFERROR(I86/I78,""))) | J87: =IF(OR(J86="",J78=""),"",IF(J78<=0,"",IFERROR(J86/J78,""))) | K87: =IF(OR(K86="",K78=""),"",IF(K78<=0,"",IFERROR(K86/K78,""))) | L87: =IF(OR(L86="",L78=""),"",IF(L78<=0,"",IFERROR(L86/L78,""))) | ... N87: =IF(OR(N86="",N78=""),"",IF(N78<=0,"",IFERROR(N86/N78,""))) | V87: =IF(OR(V86="",V78=""),"",IF(V78<=0,"",IFERROR(V86/V78,""))) | W87: =IF(OR(W86="",W78=""),"",IF(W78<=0,"",IFERROR(W86/W78,""))) | X87: =IF(OR(X86="",X78=""),"",IF(X78<=0,"",IFERROR(X86/X78,"")))
A88: YoY | B88: 전년 같은 분기·전년 대비 | G88: =IF(OR(G86="",C86=""),"",IF(C86<=0,"",IFERROR(G86/C86-1,""))) | H88: =IF(OR(H86="",D86=""),"",IF(D86<=0,"",IFERROR(H86/D86-1,""))) | I88: =IF(OR(I86="",E86=""),"",IF(E86<=0,"",IFERROR(I86/E86-1,""))) | J88: =IF(OR(J86="",F86=""),"",IF(F86<=0,"",IFERROR(J86/F86-1,""))) | K88: =IF(OR(K86="",G86=""),"",IF(G86<=0,"",IFERROR(K86/G86-1,""))) | L88: =IF(OR(L86="",H86=""),"",IF(H86<=0,"",IFERROR(L86/H86-1,""))) | M88: =IF(OR(M86="",I86=""),"",IF(I86<=0,"",IFERROR(M86/I86-1,""))) | N88: =IF(OR(N86="",J86=""),"",IF(J86<=0,"",IFERROR(N86/J86-1,""))) | V88: =IF(OR(V86="",U86=""),"",IF(U86<=0,"",IFERROR(V86/U86-1,""))) | W88: =IF(OR(W86="",V86=""),"",IF(V86<=0,"",IFERROR(W86/V86-1,""))) | X88: =IF(OR(X86="",W86=""),"",IF(W86<=0,"",IFERROR(X86/W86-1,"")))
A89: 금융수익 | E89: 11 | F89: 199 | G89: 1231 | H89: 1135 | I89: 1142 | J89: 2398 | K89: -402 | L89: 1608 | M89: 5895 | N89: 17170 | V89: 11 | W89: 1142 | X89: 5895
A90: 금융비용 | E90: 26856 | F90: 26192 | G90: 18282 | H90: 17428 | I90: 23426 | J90: 19860 | K90: 29102 | L90: 22769 | M90: 24977 | N90: 52801 | V90: 26856 | W90: 23426 | X90: 24977
A91: 지분법이익 | E91: 146 | F91: -120 | G91: 192 | H91: 265 | I91: 205 | J91: -143 | K91: 299 | L91: 147 | M91: 632 | N91: 334 | V91: 146 | W91: 205 | X91: 632
A92: 법인세비용차감전 중간이익 | E92: 17159 | F92: 99746 | G92: 149173 | H92: 106687 | I92: 15063 | J92: 27294 | K92: 56716 | L92: 121740 | M92: 578345 | N92: 1234720 | V92: 17159 | W92: 15063 | X92: 578345
A93: Income Tax Expense | E93: 6906 | F93: 29988 | G93: 42951 | H93: 30612 | I93: -5203 | J93: 9021 | K93: 16046 | L93: 33926 | M93: 170606 | N93: 392549 | V93: 6906 | W93: -5203 | X93: 170606
A94: 중간이익 | E94: 10253 | F94: 69758 | G94: 106222 | H94: 76075 | I94: 20266 | J94: 18273 | K94: 40670 | L94: 87814 | M94: 407739 | N94: 842171 | V94: 10253 | W94: 20266 | X94: 407739
A95: 기본 주당 중간이익(엔) | E95: 1.98e-05 | F95: 0.0001348 | G95: 0.00020526 | H95: 0.00014588 | I95: 3.402e-05 | J95: 3.39e-05 | K95: 7.536e-05 | L95: 0.00016241 | M95: 0.0007524 | N95: 0.00153991 | V95: 1.98e-05 | W95: 3.402e-05 | X95: 0.0007524
A96: 희석 주당 중간이익(엔) | E96: 1.98e-05 | F96: 0.00013316 | G96: 0.00020279 | H96: 0.00014535 | I96: 3.415e-05 | J96: 3.375e-05 | K96: 7.465e-05 | L96: 0.00015954 | M96: 0.00074121 | N96: 0.00152509 | V96: 1.98e-05 | W96: 3.415e-05 | X96: 0.00074121
A97: Profit Loss Attributable To Owners Of Parent | E97: 10246 | F97: 69758 | G97: 106222 | H97: 76068 | I97: 20267 | J97: 18284 | K97: 40662 | L97: 87810 | M97: 407734 | N97: 842165 | V97: 10246 | W97: 20267 | X97: 407734
A98: YoY | B98: 전년 같은 분기·전년 대비 | G98: =IF(OR(G97="",C97=""),"",IF(C97<=0,"",IFERROR(G97/C97-1,""))) | H98: =IF(OR(H97="",D97=""),"",IF(D97<=0,"",IFERROR(H97/D97-1,""))) | I98: =IF(OR(I97="",E97=""),"",IF(E97<=0,"",IFERROR(I97/E97-1,""))) | J98: =IF(OR(J97="",F97=""),"",IF(F97<=0,"",IFERROR(J97/F97-1,""))) | K98: =IF(OR(K97="",G97=""),"",IF(G97<=0,"",IFERROR(K97/G97-1,""))) | L98: =IF(OR(L97="",H97=""),"",IF(H97<=0,"",IFERROR(L97/H97-1,""))) | M98: =IF(OR(M97="",I97=""),"",IF(I97<=0,"",IFERROR(M97/I97-1,""))) | N98: =IF(OR(N97="",J97=""),"",IF(J97<=0,"",IFERROR(N97/J97-1,""))) | V98: =IF(OR(V97="",U97=""),"",IF(U97<=0,"",IFERROR(V97/U97-1,""))) | W98: =IF(OR(W97="",V97=""),"",IF(V97<=0,"",IFERROR(W97/V97-1,""))) | X98: =IF(OR(X97="",W97=""),"",IF(W97<=0,"",IFERROR(X97/W97-1,"")))
A99: 비지배지분 | E99: 7 | F99: 0 | G99: 0 | H99: 7 | I99: -1 | J99: -11 | K99: 8 | L99: 4 | M99: 5 | N99: 6 | V99: 7 | W99: -1 | X99: 5
A101: 포괄손익 · 전 항목 | B101: 분기 = 3개월 단독
A102: 항목 | B102: 참고 | C102: 2024.2Q | D102: 2024.3Q | E102: 2024.4Q | F102: 2025.1Q | G102: 2025.2Q | H102: 2025.3Q | I102: 2025.4Q | J102: 2026.1Q | K102: 2026.2Q | L102: 2026.3Q | M102: 2026.4Q | N102: 2027.1Q | O102: 2017 | P102: 2018 | Q102: 2019 | R102: 2020 | S102: 2021 | T102: 2022 | U102: 2023 | V102: 2024 | W102: 2025 | X102: 2026 | Y102: 2027(MW) | Z102: 2028(MW) | AA102: 2029(MW) | AB102: 2030(MW) | AC102: 2031(MW)
A103: 중간이익 | E103: 10253 | F103: 69758 | G103: 106222 | H103: 76075 | I103: 20266 | J103: 18273 | K103: 40670 | L103: 87814 | M103: 407739 | N103: 842171 | V103: 10253 | W103: 20266 | X103: 407739
...

Sheet 재무상태표
A1: 285A 재무상태표
A2: 재무비율은 기말 잔액 기준 · 분기 손익은 최근 4분기 합산(TTM) | B2: (단위: 백만엔)
A3: 항목 | B3: 참고 | C3: 2026.1Q | D3: 2026.2Q | E3: 2026.3Q | F3: 2026.4Q | G3: 2027.1Q | H3: 2024 | I3: 2025 | J3: 2026
A4: 자산
A5: 유동자산 | C5: 890275 | E5: 1059602 | F5: 1617829 | G5: 2471978 | H5: 651375 | I5: 806709 | J5: 1617829
A6: 현금및현금성자산 | C6: 235546 | E6: 281527 | F6: 470707 | G6: 791014 | H6: 187593 | I6: 167932 | J6: 470707
A7: 단기금융상품 | C7: 3929 | E7: 7955 | F7: 7191 | G7: 4751 | H7: 5353 | I7: 3971 | J7: 7191
A8: 매출채권 | C8: 236412 | E8: 347780 | F8: 660559 | G8: 1151562 | H8: 149815 | I8: 238594 | J8: 660559
A9: 재고자산 | C9: 361634 | E9: 353486 | F9: 412612 | G9: 438111 | H9: 271781 | I9: 352863 | J9: 412612
A10: 기타유동자산 | B10: 총계 − 위 항목 | C10: =IF(OR(C5=""),"",IFERROR(C5-SUM(C6,C7,C8,C9),"")) | D10: =IF(OR(D5=""),"",IFERROR(D5-SUM(D6,D7,D8,D9),"")) | E10: =IF(OR(E5=""),"",IFERROR(E5-SUM(E6,E7,E8,E9),"")) | F10: =IF(OR(F5=""),"",IFERROR(F5-SUM(F6,F7,F8,F9),"")) | G10: =IF(OR(G5=""),"",IFERROR(G5-SUM(G6,G7,G8,G9),"")) | H10: =IF(OR(H5=""),"",IFERROR(H5-SUM(H6,H7,H8,H9),"")) | I10: =IF(OR(I5=""),"",IFERROR(I5-SUM(I6,I7,I8,I9),"")) | J10: =IF(OR(J5=""),"",IFERROR(J5-SUM(J6,J7,J8,J9),""))
A11: 비유동자산 | C11: 2091944 | E11: 2135240 | F11: 2072242 | G11: 2258498 | H11: 2213566 | I11: 2112970 | J11: 2072242
A12: 유형자산 | C12: 1068664 | E12: 1056828 | F12: 1055255 | G12: 1055840 | H12: 1168765 | I12: 1100181 | J12: 1055255
A13: 무형자산 | C13: 11244 | E13: 11071 | F13: 11192 | G13: 11657 | H13: 11259 | I13: 10658 | J13: 11192
A14: 투자부동산
A15: 기타비유동자산 | B15: 총계 − 위 항목 | C15: =IF(OR(C11=""),"",IFERROR(C11-SUM(C12,C13,C14),"")) | D15: =IF(OR(D11=""),"",IFERROR(D11-SUM(D12,D13,D14),"")) | E15: =IF(OR(E11=""),"",IFERROR(E11-SUM(E12,E13,E14),"")) | F15: =IF(OR(F11=""),"",IFERROR(F11-SUM(F12,F13,F14),"")) | G15: =IF(OR(G11=""),"",IFERROR(G11-SUM(G12,G13,G14),"")) | H15: =IF(OR(H11=""),"",IFERROR(H11-SUM(H12,H13,H14),"")) | I15: =IF(OR(I11=""),"",IFERROR(I11-SUM(I12,I13,I14),"")) | J15: =IF(OR(J11=""),"",IFERROR(J11-SUM(J12,J13,J14),""))
A16: 자산총계 | C16: 2982219 | E16: 3194842 | F16: 3690071 | G16: 4730476 | H16: 2864941 | I16: 2919679 | J16: 3690071
A17: 부채
A18: 유동부채 | C18: 904439 | E18: 986360 | F18: 1098008 | G18: 1395780 | H18: 1866127 | I18: 985173 | J18: 1098008
A19: 매입채무 | C19: 544641 | E19: 606755 | F19: 594917 | G19: 706802 | H19: 512502 | I19: 504011 | J19: 594917
A20: 단기차입금 | C20: 261820 | H20: 826413 | I20: 246508
A21: 유동성장기부채
A22: 기타유동부채 | B22: 총계 − 위 항목 | C22: =IF(OR(C18=""),"",IFERROR(C18-SUM(C19,C20,C21),"")) | D22: =IF(OR(D18=""),"",IFERROR(D18-SUM(D19,D20,D21),"")) | E22: =IF(OR(E18=""),"",IFERROR(E18-SUM(E19,E20,E21),"")) | F22: =IF(OR(F18=""),"",IFERROR(F18-SUM(F19,F20,F21),"")) | G22: =IF(OR(G18=""),"",IFERROR(G18-SUM(G19,G20,G21),"")) | H22: =IF(OR(H18=""),"",IFERROR(H18-SUM(H19,H20,H21),"")) | I22: =IF(OR(I18=""),"",IFERROR(I18-SUM(I19,I20,I21),"")) | J22: =IF(OR(J18=""),"",IFERROR(J18-SUM(J19,J20,J21),""))
A23: 비유동부채 | C23: 1258438 | E23: 1229835 | F23: 1192984 | G23: 930218 | H23: 549048 | I23: 1196810 | J23: 1192984
A24: 장기차입금 | C24: 507057 | H24: 284899 | I24: 531198
A25: 사채 | C25: 920910 | E25: 900872 | F25: 872116 | G25: 543009 | I25: 531198 | J25: 872116
A26: 기타비유동부채 | B26: 총계 − 위 항목 | C26: =IF(OR(C23=""),"",IFERROR(C23-SUM(C24,C25),"")) | D26: =IF(OR(D23=""),"",IFERROR(D23-SUM(D24,D25),"")) | E26: =IF(OR(E23=""),"",IFERROR(E23-SUM(E24,E25),"")) | F26: =IF(OR(F23=""),"",IFERROR(F23-SUM(F24,F25),"")) | G26: =IF(OR(G23=""),"",IFERROR(G23-SUM(G24,G25),"")) | H26: =IF(OR(H23=""),"",IFERROR(H23-SUM(H24,H25),"")) | I26: =IF(OR(I23=""),"",IFERROR(I23-SUM(I24,I25),"")) | J26: =IF(OR(J23=""),"",IFERROR(J23-SUM(J24,J25),""))
A27: 부채총계 | C27: 2162877 | E27: 2216195 | F27: 2290992 | G27: 2325998 | H27: 2415175 | I27: 2181983 | J27: 2290992
A28: 총차입금 | B28: 단기+유동성장기+장기+사채 | C28: =SUM(C20,C21,C24,C25) | D28: =SUM(D20,D21,D24,D25) | E28: =SUM(E20,E21,E24,E25) | F28: =SUM(F20,F21,F24,F25) | G28: =SUM(G20,G21,G24,G25) | H28: =SUM(H20,H21,H24,H25) | I28: =SUM(I20,I21,I24,I25) | J28: =SUM(J20,J21,J24,J25)
A29: 순차입금 | B29: 음수 = 순현금 | C29: =C28-C6-N(C7) | D29: =D28-D6-N(D7) | E29: =E28-E6-N(E7) | F29: =F28-F6-N(F7) | G29: =G28-G6-N(G7) | H29: =H28-H6-N(H7) | I29: =I28-I6-N(I7) | J29: =J28-J6-N(J7)
A30: 자본
A31: 지배주주지분 | C31: 819203 | E31: 978502 | F31: 1398929 | G31: 2404320 | H31: 449635 | I31: 737565 | J31: 1398929
A32: 자본금 | C32: 25578 | E32: 29880 | F32: 31284 | G32: 33133 | H32: 10000 | I32: 25239 | J32: 31284
A33: 이익잉여금 | C33: -130594 | E33: -42784 | F33: 366955 | G33: 1209116 | H33: -463054 | I33: -189547 | J33: 366955
A34: 비지배지분 | C34: 139 | E34: 145 | F34: 150 | G34: 158 | H34: 131 | I34: 131 | J34: 150
A35: 자본총계 | C35: 819342 | E35: 978647 | F35: 1399079 | G35: 2404478 | H35: 449766 | I35: 737696 | J35: 1399079
A36: 현금흐름 요약 | B36: 분기 = TTM (있을 때만)
A37: 영업활동현금흐름 | C37: 442380 | D37: 409703 | E37: 426023 | F37: 616540 | G37: 1421771 | H37: 195111 | I37: 476416 | J37: 616540
A38: CAPEX (유·무형 취득) | B38: 양수로 입력 | C38: 233014 | D38: 283197 | E38: 296284 | F38: 283674 | G38: 282499 | H38: 305097 | I38: 225603 | J38: 283674
A39: FCF | C39: =IF(OR(C37="",C38=""),"",IFERROR(C37-C38,"")) | D39: =IF(OR(D37="",D38=""),"",IFERROR(D37-D38,"")) | E39: =IF(OR(E37="",E38=""),"",IFERROR(E37-E38,"")) | F39: =IF(OR(F37="",F38=""),"",IFERROR(F37-F38,"")) | G39: =IF(OR(G37="",G38=""),"",IFERROR(G37-G38,"")) | H39: =IF(OR(H37="",H38=""),"",IFERROR(H37-H38,"")) | I39: =IF(OR(I37="",I38=""),"",IFERROR(I37-I38,"")) | J39: =IF(OR(J37="",J38=""),"",IFERROR(J37-J38,""))
A40: 배당금 지급 | B40: 양수로 입력
A41: 주요 재무 비율 | B41: 기준 (빨간 글씨 = 미달)
A42: 안정성
A43: 부채비율 | B43: 100%↓ | C43: =IF(OR(C27="",C35=""),"",IFERROR(C27/C35,"")) | D43: =IF(OR(D27="",D35=""),"",IFERROR(D27/D35,"")) | E43: =IF(OR(E27="",E35=""),"",IFERROR(E27/E35,"")) | F43: =IF(OR(F27="",F35=""),"",IFERROR(F27/F35,"")) | G43: =IF(OR(G27="",G35=""),"",IFERROR(G27/G35,"")) | H43: =IF(OR(H27="",H35=""),"",IFERROR(H27/H35,"")) | I43: =IF(OR(I27="",I35=""),"",IFERROR(I27/I35,"")) | J43: =IF(OR(J27="",J35=""),"",IFERROR(J27/J35,""))
A44: 순차입금비율 | B44: 0%↓ 순현금 | C44: =IF(OR(C29="",C35=""),"",IFERROR(C29/C35,"")) | D44: =IF(OR(D29="",D35=""),"",IFERROR(D29/D35,"")) | E44: =IF(OR(E29="",E35=""),"",IFERROR(E29/E35,"")) | F44: =IF(OR(F29="",F35=""),"",IFERROR(F29/F35,"")) | G44: =IF(OR(G29="",G35=""),"",IFERROR(G29/G35,"")) | H44: =IF(OR(H29="",H35=""),"",IFERROR(H29/H35,"")) | I44: =IF(OR(I29="",I35=""),"",IFERROR(I29/I35,"")) | J44: =IF(OR(J29="",J35=""),"",IFERROR(J29/J35,""))
A45: 자기자본비율 | B45: 50%↑ | C45: =IF(OR(C35="",C16=""),"",IFERROR(C35/C16,"")) | D45: =IF(OR(D35="",D16=""),"",IFERROR(D35/D16,"")) | E45: =IF(OR(E35="",E16=""),"",IFERROR(E35/E16,"")) | F45: =IF(OR(F35="",F16=""),"",IFERROR(F35/F16,"")) | G45: =IF(OR(G35="",G16=""),"",IFERROR(G35/G16,"")) | H45: =IF(OR(H35="",H16=""),"",IFERROR(H35/H16,"")) | I45: =IF(OR(I35="",I16=""),"",IFERROR(I35/I16,"")) | J45: =IF(OR(J35="",J16=""),"",IFERROR(J35/J16,""))
A46: 유동비율 | B46: 150%↑ | C46: =IF(OR(C5="",C18=""),"",IFERROR(C5/C18,"")) | D46: =IF(OR(D5="",D18=""),"",IFERROR(D5/D18,"")) | E46: =IF(OR(E5="",E18=""),"",IFERROR(E5/E18,"")) | F46: =IF(OR(F5="",F18=""),"",IFERROR(F5/F18,"")) | G46: =IF(OR(G5="",G18=""),"",IFERROR(G5/G18,"")) | H46: =IF(OR(H5="",H18=""),"",IFERROR(H5/H18,"")) | I46: =IF(OR(I5="",I18=""),"",IFERROR(I5/I18,"")) | J46: =IF(OR(J5="",J18=""),"",IFERROR(J5/J18,""))
A47: 당좌비율 | B47: 100%↑ | C47: =IF(OR(C5="",C18=""),"",IFERROR((C5-N(C9))/C18,"")) | D47: =IF(OR(D5="",D18=""),"",IFERROR((D5-N(D9))/D18,"")) | E47: =IF(OR(E5="",E18=""),"",IFERROR((E5-N(E9))/E18,"")) | F47: =IF(OR(F5="",F18=""),"",IFERROR((F5-N(F9))/F18,"")) | G47: =IF(OR(G5="",G18=""),"",IFERROR((G5-N(G9))/G18,"")) | H47: =IF(OR(H5="",H18=""),"",IFERROR((H5-N(H9))/H18,"")) | I47: =IF(OR(I5="",I18=""),"",IFERROR((I5-N(I9))/I18,"")) | J47: =IF(OR(J5="",J18=""),"",IFERROR((J5-N(J9))/J18,""))
A48: 이자보상배율 | B48: 5x↑ (금융원가 기준) | C48: =IFERROR((IF(COUNT('연간'!G16:J16)<4,"",SUM('연간'!G16:J16)))/(IF(COUNT('연간'!G38:J38)<4,"",SUM('연간'!G38:J38))),"") | D48: =IFERROR((IF(COUNT('연간'!H16:K16)<4,"",SUM('연간'!H16:K16)))/(IF(COUNT('연간'!H38:K38)<4,"",SUM('연간'!H38:K38))),"") | E48: =IFERROR((IF(COUNT('연간'!I16:L16)<4,"",SUM('연간'!I16:L16)))/(IF(COUNT('연간'!I38:L38)<4,"",SUM('연간'!I38:L38))),"") | F48: =IFERROR((IF(COUNT('연간'!J16:M16)<4,"",SUM('연간'!J16:M16)))/(IF(COUNT('연간'!J38:M38)<4,"",SUM('연간'!J38:M38))),"") | G48: =IFERROR((IF(COUNT('연간'!K16:N16)<4,"",SUM('연간'!K16:N16)))/(IF(COUNT('연간'!K38:N38)<4,"",SUM('연간'!K38:N38))),"") | H48: =IFERROR(('연간'!V16)/('연간'!V38),"") | I48: =IFERROR(('연간'!W16)/('연간'!W38),"") | J48: =IFERROR(('연간'!X16)/('연간'!X38),"")
A49: 차입금 상환연수 | B49: 4년↓ (버핏) | C49: =IFERROR(IF((IF(COUNT('연간'!G44:J44)<4,"",SUM('연간'!G44:J44)))<=0,"적자",C28/(IF(COUNT('연간'!G44:J44)<4,"",SUM('연간'!G44:J44)))),"") | D49: =IFERROR(IF((IF(COUNT('연간'!H44:K44)<4,"",SUM('연간'!H44:K44)))<=0,"적자",D28/(IF(COUNT('연간'!H44:K44)<4,"",SUM('연간'!H44:K44)))),"") | E49: =IFERROR(IF((IF(COUNT('연간'!I44:L44)<4,"",SUM('연간'!I44:L44)))<=0,"적자",E28/(IF(COUNT('연간'!I44:L44)<4,"",SUM('연간'!I44:L44)))),"") | F49: =IFERROR(IF((IF(COUNT('연간'!J44:M44)<4,"",SUM('연간'!J44:M44)))<=0,"적자",F28/(IF(COUNT('연간'!J44:M44)<4,"",SUM('연간'!J44:M44)))),"") | G49: =IFERROR(IF((IF(COUNT('연간'!K44:N44)<4,"",SUM('연간'!K44:N44)))<=0,"적자",G28/(IF(COUNT('연간'!K44:N44)<4,"",SUM('연간'!K44:N44)))),"") | H49: =IFERROR(IF(('연간'!V44)<=0,"적자",H28/('연간'!V44)),"") | I49: =IFERROR(IF(('연간'!W44)<=0,"적자",I28/('연간'!W44)),"") | J49: =IFERROR(IF(('연간'!X44)<=0,"적자",J28/('연간'!X44)),"")
A50: 수익성
A51: ROE | B51: 15%↑ (버핏) | C51: =IFERROR((IF(COUNT('연간'!G44:J44)<4,"",SUM('연간'!G44:J44)))/C31,"") | D51: =IFERROR((IF(COUNT('연간'!H44:K44)<4,"",SUM('연간'!H44:K44)))/D31,"") | E51: =IFERROR((IF(COUNT('연간'!I44:L44)<4,"",SUM('연간'!I44:L44)))/E31,"") | F51: =IFERROR((IF(COUNT('연간'!J44:M44)<4,"",SUM('연간'!J44:M44)))/F31,"") | G51: =IFERROR((IF(COUNT('연간'!K44:N44)<4,"",SUM('연간'!K44:N44)))/G31,"") | H51: =IFERROR(('연간'!V44)/H31,"") | I51: =IFERROR(('연간'!W44)/I31,"") | J51: =IFERROR(('연간'!X44)/J31,"")
A52: ROA | B52: 5%↑ | C52: =IFERROR((IF(COUNT('연간'!G43:J43)<4,"",SUM('연간'!G43:J43)))/C16,"") | D52: =IFERROR((IF(COUNT('연간'!H43:K43)<4,"",SUM('연간'!H43:K43)))/D16,"") | E52: =IFERROR((IF(COUNT('연간'!I43:L43)<4,"",SUM('연간'!I43:L43)))/E16,"") | F52: =IFERROR((IF(COUNT('연간'!J43:M43)<4,"",SUM('연간'!J43:M43)))/F16,"") | G52: =IFERROR((IF(COUNT('연간'!K43:N43)<4,"",SUM('연간'!K43:N43)))/G16,"") | H52: =IFERROR(('연간'!V43)/H16,"") | I52: =IFERROR(('연간'!W43)/I16,"") | J52: =IFERROR(('연간'!X43)/J16,"")
A53: ROIC | B53: 10%↑ (세후영업이익 기준) | C53: =IFERROR((IF(COUNT('연간'!G16:J16)<4,"",SUM('연간'!G16:J16)))*(1-0.3)/(C35+C29),"") | D53: =IFERROR((IF(COUNT('연간'!H16:K16)<4,"",SUM('연간'!H16:K16)))*(1-0.3)/(D35+D29),"") | E53: =IFERROR((IF(COUNT('연간'!I16:L16)<4,"",SUM('연간'!I16:L16)))*(1-0.3)/(E35+E29),"") | F53: =IFERROR((IF(COUNT('연간'!J16:M16)<4,"",SUM('연간'!J16:M16)))*(1-0.3)/(F35+F29),"") | G53: =IFERROR((IF(COUNT('연간'!K16:N16)<4,"",SUM('연간'!K16:N16)))*(1-0.3)/(G35+G29),"") | H53: =IFERROR(('연간'!V16)*(1-0.3)/(H35+H29),"") | I53: =IFERROR(('연간'!W16)*(1-0.3)/(I35+I29),"") | J53: =IFERROR(('연간'!X16)*(1-0.3)/(J35+J29),"")
A54: 매출총이익률 (GPM) | B54: 40%↑ (해자 신호) | C54: =IFERROR((IF(COUNT('연간'!G12:J12)<4,"",SUM('연간'!G12:J12)))/(IF(COUNT('연간'!G4:J4)<4,"",SUM('연간'!G4:J4))),"") | D54: =IFERROR((IF(COUNT('연간'!H12:K12)<4,"",SUM('연간'!H12:K12)))/(IF(COUNT('연간'!H4:K4)<4,"",SUM('연간'!H4:K4))),"") | E54: =IFERROR((IF(COUNT('연간'!I12:L12)<4,"",SUM('연간'!I12:L12)))/(IF(COUNT('연간'!I4:L4)<4,"",SUM('연간'!I4:L4))),"") | F54: =IFERROR((IF(COUNT('연간'!J12:M12)<4,"",SUM('연간'!J12:M12)))/(IF(COUNT('연간'!J4:M4)<4,"",SUM('연간'!J4:M4))),"") | G54: =IFERROR((IF(COUNT('연간'!K12:N12)<4,"",SUM('연간'!K12:N12)))/(IF(COUNT('연간'!K4:N4)<4,"",SUM('연간'!K4:N4))),"") | H54: =IFERROR(('연간'!V12)/('연간'!V4),"") | I54: =IFERROR(('연간'!W12)/('연간'!W4),"") | J54: =IFERROR(('연간'!X12)/('연간'!X4),"")
A55: 영업이익률 (OPM) | B55: 15%↑ | C55: =IFERROR((IF(COUNT('연간'!G16:J16)<4,"",SUM('연간'!G16:J16)))/(IF(COUNT('연간'!G4:J4)<4,"",SUM('연간'!G4:J4))),"") | D55: =IFERROR((IF(COUNT('연간'!H16:K16)<4,"",SUM('연간'!H16:K16)))/(IF(COUNT('연간'!H4:K4)<4,"",SUM('연간'!H4:K4))),"") | E55: =IFERROR((IF(COUNT('연간'!I16:L16)<4,"",SUM('연간'!I16:L16)))/(IF(COUNT('연간'!I4:L4)<4,"",SUM('연간'!I4:L4))),"") | F55: =IFERROR((IF(COUNT('연간'!J16:M16)<4,"",SUM('연간'!J16:M16)))/(IF(COUNT('연간'!J4:M4)<4,"",SUM('연간'!J4:M4))),"") | G55: =IFERROR((IF(COUNT('연간'!K16:N16)<4,"",SUM('연간'!K16:N16)))/(IF(COUNT('연간'!K4:N4)<4,"",SUM('연간'!K4:N4))),"") | H55: =IFERROR(('연간'!V16)/('연간'!V4),"") | I55: =IFERROR(('연간'!W16)/('연간'!W4),"") | J55: =IFERROR(('연간'!X16)/('연간'!X4),"")
A56: 순이익률 | B56: 10%↑ | C56: =IFERROR((IF(COUNT('연간'!G43:J43)<4,"",SUM('연간'!G43:J43)))/(IF(COUNT('연간'!G4:J4)<4,"",SUM('연간'!G4:J4))),"") | D56: =IFERROR((IF(COUNT('연간'!H43:K43)<4,"",SUM('연간'!H43:K43)))/(IF(COUNT('연간'!H4:K4)<4,"",SUM('연간'!H4:K4))),"") | E56: =IFERROR((IF(COUNT('연간'!I43:L43)<4,"",SUM('연간'!I43:L43)))/(IF(COUNT('연간'!I4:L4)<4,"",SUM('연간'!I4:L4))),"") | F56: =IFERROR((IF(COUNT('연간'!J43:M43)<4,"",SUM('연간'!J43:M43)))/(IF(COUNT('연간'!J4:M4)<4,"",SUM('연간'!J4:M4))),"") | G56: =IFERROR((IF(COUNT('연간'!K43:N43)<4,"",SUM('연간'!K43:N43)))/(IF(COUNT('연간'!K4:N4)<4,"",SUM('연간'!K4:N4))),"") | H56: =IFERROR(('연간'!V43)/('연간'!V4),"") | I56: =IFERROR(('연간'!W43)/('연간'!W4),"") | J56: =IFERROR(('연간'!X43)/('연간'!X4),"")
A57: 효율성 (회전율)
A58: 총자산회전율 | B58: 높을수록↑ | C58: =IFERROR((IF(COUNT('연간'!G4:J4)<4,"",SUM('연간'!G4:J4)))/C16,"") | D58: =IFERROR((IF(COUNT('연간'!H4:K4)<4,"",SUM('연간'!H4:K4)))/D16,"") | E58: =IFERROR((IF(COUNT('연간'!I4:L4)<4,"",SUM('연간'!I4:L4)))/E16,"") | F58: =IFERROR((IF(COUNT('연간'!J4:M4)<4,"",SUM('연간'!J4:M4)))/F16,"") | G58: =IFERROR((IF(COUNT('연간'!K4:N4)<4,"",SUM('연간'!K4:N4)))/G16,"") | H58: =IFERROR(('연간'!V4)/H16,"") | I58: =IFERROR(('연간'!W4)/I16,"") | J58: =IFERROR(('연간'!X4)/J16,"")
A59: 매출채권회전일수 | B59: 짧을수록↑ | C59: =IFERROR(C8/(IF(COUNT('연간'!G4:J4)<4,"",SUM('연간'!G4:J4)))*365,"") | D59: =IFERROR(D8/(IF(COUNT('연간'!H4:K4)<4,"",SUM('연간'!H4:K4)))*365,"") | E59: =IFERROR(E8/(IF(COUNT('연간'!I4:L4)<4,"",SUM('연간'!I4:L4)))*365,"") | F59: =IFERROR(F8/(IF(COUNT('연간'!J4:M4)<4,"",SUM('연간'!J4:M4)))*365,"") | G59: =IFERROR(G8/(IF(COUNT('연간'!K4:N4)<4,"",SUM('연간'!K4:N4)))*365,"") | H59: =IFERROR(H8/('연간'!V4)*365,"") | I59: =IFERROR(I8/('연간'!W4)*365,"") | J59: =IFERROR(J8/('연간'!X4)*365,"")
A60: 재고자산회전일수 | B60: 짧을수록↑ | C60: =IFERROR(C9/(IF(COUNT('연간'!G11:J11)<4,"",SUM('연간'!G11:J11)))*365,"") | D60: =IFERROR(D9/(IF(COUNT('연간'!H11:K11)<4,"",SUM('연간'!H11:K11)))*365,"") | E60: =IFERROR(E9/(IF(COUNT('연간'!I11:L11)<4,"",SUM('연간'!I11:L11)))*365,"") | F60: =IFERROR(F9/(IF(COUNT('연간'!J11:M11)<4,"",SUM('연간'!J11:M11)))*365,"") | G60: =IFERROR(G9/(IF(COUNT('연간'!K11:N11)<4,"",SUM('연간'!K11:N11)))*365,"") | H60: =IFERROR(H9/('연간'!V11)*365,"") | I60: =IFERROR(I9/('연간'!W11)*365,"") | J60: =IFERROR(J9/('연간'!X11)*365,"")
A61: 매입채무회전일수 | B61: 길수록 유리 | C61: =IFERROR(C19/(IF(COUNT('연간'!G11:J11)<4,"",SUM('연간'!G11:J11)))*365,"") | D61: =IFERROR(D19/(IF(COUNT('연간'!H11:K11)<4,"",SUM('연간'!H11:K11)))*365,"") | E61: =IFERROR(E19/(IF(COUNT('연간'!I11:L11)<4,"",SUM('연간'!I11:L11)))*365,"") | F61: =IFERROR(F19/(IF(COUNT('연간'!J11:M11)<4,"",SUM('연간'!J11:M11)))*365,"") | G61: =IFERROR(G19/(IF(COUNT('연간'!K11:N11)<4,"",SUM('연간'!K11:N11)))*365,"") | H61: =IFERROR(H19/('연간'!V11)*365,"") | I61: =IFERROR(I19/('연간'!W11)*365,"") | J61: =IFERROR(J19/('연간'!X11)*365,"")
A62: 현금전환주기 (CCC) | B62: 짧을수록↑ | C62: =IF(OR(C59="",C60="",C61=""),"",IFERROR(C59+C60-C61,"")) | D62: =IF(OR(D59="",D60="",D61=""),"",IFERROR(D59+D60-D61,"")) | E62: =IF(OR(E59="",E60="",E61=""),"",IFERROR(E59+E60-E61,"")) | F62: =IF(OR(F59="",F60="",F61=""),"",IFERROR(F59+F60-F61,"")) | G62: =IF(OR(G59="",G60="",G61=""),"",IFERROR(G59+G60-G61,"")) | H62: =IF(OR(H59="",H60="",H61=""),"",IFERROR(H59+H60-H61,"")) | I62: =IF(OR(I59="",I60="",I61=""),"",IFERROR(I59+I60-I61,"")) | J62: =IF(OR(J59="",J60="",J61=""),"",IFERROR(J59+J60-J61,""))
A63: 현금흐름
A64: 영업현금흐름 / 순이익 | B64: 1x↑ (이익의 질) | C64: =IF(C37="","",IFERROR(C37/(IF(COUNT('연간'!G43:J43)<4,"",SUM('연간'!G43:J43))),"")) | D64: =IF(D37="","",IFERROR(D37/(IF(COUNT('연간'!H43:K43)<4,"",SUM('연간'!H43:K43))),"")) | E64: =IF(E37="","",IFERROR(E37/(IF(COUNT('연간'!I43:L43)<4,"",SUM('연간'!I43:L43))),"")) | F64: =IF(F37="","",IFERROR(F37/(IF(COUNT('연간'!J43:M43)<4,"",SUM('연간'!J43:M43))),"")) | G64: =IF(G37="","",IFERROR(G37/(IF(COUNT('연간'!K43:N43)<4,"",SUM('연간'!K43:N43))),"")) | H64: =IF(H37="","",IFERROR(H37/('연간'!V43),"")) | I64: =IF(I37="","",IFERROR(I37/('연간'!W43),"")) | J64: =IF(J37="","",IFERROR(J37/('연간'!X43),""))
A65: FCF 마진 | B65: 5%↑ | C65: =IF(C39="","",IFERROR(C39/(IF(COUNT('연간'!G4:J4)<4,"",SUM('연간'!G4:J4))),"")) | D65: =IF(D39="","",IFERROR(D39/(IF(COUNT('연간'!H4:K4)<4,"",SUM('연간'!H4:K4))),"")) | E65: =IF(E39="","",IFERROR(E39/(IF(COUNT('연간'!I4:L4)<4,"",SUM('연간'!I4:L4))),"")) | F65: =IF(F39="","",IFERROR(F39/(IF(COUNT('연간'!J4:M4)<4,"",SUM('연간'!J4:M4))),"")) | G65: =IF(G39="","",IFERROR(G39/(IF(COUNT('연간'!K4:N4)<4,"",SUM('연간'!K4:N4))),"")) | H65: =IF(H39="","",IFERROR(H39/('연간'!V4),"")) | I65: =IF(I39="","",IFERROR(I39/('연간'!W4),"")) | J65: =IF(J39="","",IFERROR(J39/('연간'!X4),""))
A66: CAPEX / 매출 | B66: 낮을수록↑ (자본 가벼움) | C66: =IF(C38="","",IFERROR(C38/(IF(COUNT('연간'!G4:J4)<4,"",SUM('연간'!G4:J4))),"")) | D66: =IF(D38="","",IFERROR(D38/(IF(COUNT('연간'!H4:K4)<4,"",SUM('연간'!H4:K4))),"")) | E66: =IF(E38="","",IFERROR(E38/(IF(COUNT('연간'!I4:L4)<4,"",SUM('연간'!I4:L4))),"")) | F66: =IF(F38="","",IFERROR(F38/(IF(COUNT('연간'!J4:M4)<4,"",SUM('연간'!J4:M4))),"")) | G66: =IF(G38="","",IFERROR(G38/(IF(COUNT('연간'!K4:N4)<4,"",SUM('연간'!K4:N4))),"")) | H66: =IF(H38="","",IFERROR(H38/('연간'!V4),"")) | I66: =IF(I38="","",IFERROR(I38/('연간'!W4),"")) | J66: =IF(J38="","",IFERROR(J38/('연간'!X4),""))
A67: 배당성향 | B67: 참고 | C67: =IF(C40="","",IFERROR(C40/(IF(COUNT('연간'!G44:J44)<4,"",SUM('연간'!G44:J44))),"")) | D67: =IF(D40="","",IFERROR(D40/(IF(COUNT('연간'!H44:K44)<4,"",SUM('연간'!H44:K44))),"")) | E67: =IF(E40="","",IFERROR(E40/(IF(COUNT('연간'!I44:L44)<4,"",SUM('연간'!I44:L44))),"")) | F67: =IF(F40="","",IFERROR(F40/(IF(COUNT('연간'!J44:M44)<4,"",SUM('연간'!J44:M44))),"")) | G67: =IF(G40="","",IFERROR(G40/(IF(COUNT('연간'!K44:N44)<4,"",SUM('연간'!K44:N44))),"")) | H67: =IF(H40="","",IFERROR(H40/('연간'!V44),"")) | I67: =IF(I40="","",IFERROR(I40/('연간'!W44),"")) | J67: =IF(J40="","",IFERROR(J40/('연간'!X44),""))
A69: 재무상태표 · 전 항목 | B69: 분기 말 잔액
A70: 항목 | B70: 참고 | C70: 2026.1Q | D70: 2026.2Q | E70: 2026.3Q | F70: 2026.4Q | G70: 2027.1Q | H70: 2024 | I70: 2025 | J70: 2026
A71: 현금및현금성자산 | C71: 235546 | E71: 281527 | F71: 470707 | G71: 791014 | H71: 187593 | I71: 167932 | J71: 470707
A72: 영업채권 및 기타채권 | C72: 236412 | E72: 347780 | F72: 660559 | G72: 1151562 | H72: 149815 | I72: 238594 | J72: 660559
A73: 기타금융자산 | C73: 3929 | E73: 7955 | F73: 7191 | G73: 4751 | H73: 5353 | I73: 3971 | J73: 7191
A74: 재고자산 | C74: 361634 | E74: 353486 | F74: 412612 | G74: 438111 | H74: 271781 | I74: 352863 | J74: 412612
A75: 기타유동자산 | C75: 52754 | E75: 68854 | F75: 66760 | G75: 86540 | H75: 36833 | I75: 43349 | J75: 66760
A76: 유동자산 합계 | C76: 890275 | E76: 1059602 | F76: 1617829 | G76: 2471978 | H76: 651375 | I76: 806709 | J76: 1617829
A77: 유형자산 | C77: 1068664 | E77: 1056828 | F77: 1055255 | G77: 1055840 | H77: 1168765 | I77: 1100181 | J77: 1055255
A78: 사용권자산 | C78: 192407 | E78: 186408 | F78: 178092 | G78: 175510 | H78: 159719 | I78: 197063 | J78: 178092
A79: 영업권 | C79: 395511 | E79: 395577 | F79: 395585 | G79: 395660 | H79: 395405 | I79: 395256 | J79: 395585
A80: 무형자산 | C80: 11244 | E80: 11071 | F80: 11192 | G80: 11657 | H80: 11259 | I80: 10658 | J80: 11192
A81: 지분법 투자 | C81: 7285 | E81: 7441 | F81: 8097 | G81: 8434 | H81: 6869 | I81: 7401 | J81: 8097
A82: 기타금융자산 | C82: 93200 | E82: 198068 | F82: 219230 | G82: 522327 | H82: 87139 | I82: 63179 | J82: 219230
... A86: 자산 합계 | C86: 2982219 | E86: 3194842 | F86: 3690071 | G86: 4730476 | H86: 2864941 | I86: 2919679 | J86: 3690071
A87: 차입금 | C87: 261820 | H87: 826413 | I87: 246508
A88: 사채 및 차입금 | C88: 189224 | E88: 185170 | F88: 175452 | G88: 91545 | I88: 246508 | J88: 175452
A89: 영업채무 및 기타채무 | C89: 544641 | E89: 606755 | F89: 594917 | G89: 706802 | H89: 512502 | I89: 504011 | J89: 594917
A90: 리스부채 | C90: 44244 | E90: 44621 | F90: 43911 | G90: 43544 | H90: 40025 | I90: 42521 | J90: 43911
A91: 기타금융부채 | C91: 7422 | E91: 18329 | F91: 28338 | G91: 36743 | H91: 344341 | I91: 28058 | J91: 28338
A92: 미지급법인세 | C92: 10886 | E92: 8706 | F92: 104516 | G92: 340035 | H92: 6182 | I92: 38183 | J92: 104516
A93: 충당금 | C93: 2179 | E93: 2079 | F93: 3876 | G93: 7650 | H93: 4694 | I93: 3328 | J93: 3876
A94: 기타유동부채 | C94: 105843 | E94: 120700 | F94: 146998 | G94: 169461 | H94: 131970 | I94: 122564 | J94: 146998
A95: 유동부채 합계 | C95: 904439 | E95: 986360 | F95: 1098008 | G95: 1395780 | H95: 1866127 | I95: 985173 | J95: 1098008
A96: 차입금 | C96: 507057 | H96: 284899 | I96: 531198
A97: 사채 및 차입금 | C97: 920910 | E97: 900872 | F97: 872116 | G97: 543009 | I97: 531198 | J97: 872116
A98: 리스부채 | C98: 175172 | E98: 169177 | F98: 161710 | G98: 159733 | H98: 142871 | I98: 179294 | J98: 161710
A99: 기타금융부채 | C99: 0 | E99: 0 | F99: 0 | H99: 0 | I99: 321261 | J99: 0
A100: 퇴직급여부채 | C100: 46138 | E100: 46067 | F100: 42871 | G100: 42842 | H100: 48492 | I100: 46477 | J100: 42871
A101: 충당금 | C101: 8379 | E101: 9727 | F101: 12840 | G101: 58335 | H101: 7331 | I101: 7560 | J101: 12840
A102: 기타비유동부채 | C102: 107836 | E102: 103425 | F102: 102725 | G102: 119630 | H102: 65419 | I102: 111017 | J102: 102725
A103: 이연법인세부채 | C103: 3 | E103: 567 | F103: 722 | G103: 6669 | H103: 36 | I103: 3 | J103: 722
A104: 비유동부채 합계 | C104: 1258438 | E104: 1229835 | F104: 1192984 | G104: 930218 | H104: 549048 | I104: 1196810 | J104: 1192984
...

Sheet 출처
A1: 출처 · 쓴 결산단신
A3: 공시일 | B3: 문서 | C3: PDF
A4: 2026-07-31 | B4: 2027년 3월 결산기 １분기 결산단신 | C4: https://www2.jpx.co.jp/disc/285A0/140120260731505265.pdf
A5: 2026-05-15 | B5: 2026년 3월 결산기 연간 결산단신 | C5: https://www2.jpx.co.jp/disc/285A0/140120260515537803.pdf
A6: 2026-02-12 | B6: 2026년 3월 결산기 ３분기 결산단신 | C6: https://www2.jpx.co.jp/disc/285A0/140120260212556330.pdf
A7: 2025-11-13 | B7: 2026년 3월 결산기 ２분기 결산단신 | C7: https://www2.jpx.co.jp/disc/285A0/140120251113599856.pdf
A8: 2025-08-08 | B8: 2026년 3월 결산기 １분기 결산단신 | C8: https://www2.jpx.co.jp/disc/285A0/140120250808536248.pdf
A9: 2025-05-15 | B9: 2025년 3월 결산기 연간 결산단신 | C9: https://www2.jpx.co.jp/disc/285A0/140120250515552869.pdf
A10: 2025-02-14 | B10: 2025년 3월 결산기 ３분기 결산단신 | C10: https://www2.jpx.co.jp/disc/285A0/140120250207566970.pdf
