Workbook

Sheet 연간
A1: 필컴퍼니 Model
A2: 모를 땐 보수적으로 | B2: (단위: 백만엔) | C2: 11월 결산 · 일본 기준 · 2026.3Q = 2026년 11월 결산기 3분기 | Y2: (추정: 파란 글씨 = 직접 입력)
A3: 항목 | B3: 참고 | C3: 2023.4Q | D3: 2024.1Q | E3: 2024.2Q | F3: 2024.3Q | G3: 2024.4Q | H3: 2025.1Q | I3: 2025.2Q | J3: 2025.3Q | K3: 2025.4Q | L3: 2026.1Q | M3: 2026.2Q | N3: 2026.3Q | O3: 2016 | P3: 2017 | Q3: 2018 | R3: 2019 | S3: 2020 | T3: 2021 | U3: 2022 | V3: 2023 | W3: 2024 | X3: 2025 | Y3: 2026(MW) | Z3: 2027(MW) | AA3: 2028(MW) | AB3: 2029(MW) | AC3: 2030(MW)
A4: 매출액 | B4: MW 직접 입력 | C4: 2927.053 | D4: 606.083 | E4: 720.626 | F4: 2538.831 | G4: 3319.417 | H4: 1772.464 | I4: 2171.803 | J4: 1684.552 | K4: 2604.686 | L4: 2043.037 | M4: 1209.707 | N4: 2843.707 | O4: 1668.312 | P4: 2950.117 | Q4: 4739.078 | R4: 7024.711 | S4: 3970.76 | T4: 5432.354 | U4: 4378.593 | V4: 5963.519 | W4: 7184.957 | X4: 8233.505 | Y4: =IF(COUNT(Y7)=0,"",SUM(Y7)) | Z4: =IF(COUNT(Z7)=0,"",SUM(Z7)) | AA4: =IF(COUNT(AA7)=0,"",SUM(AA7)) | AB4: =IF(COUNT(AB7)=0,"",SUM(AB7)) | AC4: =IF(COUNT(AC7)=0,"",SUM(AC7))
A5: YoY | G5: =IF(OR(G4="",C4=""),"",IFERROR(G4/C4-1,"")) | H5: =IF(OR(H4="",D4=""),"",IFERROR(H4/D4-1,"")) | I5: =IF(OR(I4="",E4=""),"",IFERROR(I4/E4-1,"")) | J5: =IF(OR(J4="",F4=""),"",IFERROR(J4/F4-1,"")) | K5: =IF(OR(K4="",G4=""),"",IFERROR(K4/G4-1,"")) | L5: =IF(OR(L4="",H4=""),"",IFERROR(L4/H4-1,"")) | M5: =IF(OR(M4="",I4=""),"",IFERROR(M4/I4-1,"")) | N5: =IF(OR(N4="",J4=""),"",IFERROR(N4/J4-1,"")) | P5: =IF(OR(P4="",O4=""),"",IFERROR(P4/O4-1,"")) | Q5: =IF(OR(Q4="",P4=""),"",IFERROR(Q4/P4-1,"")) | R5: =IF(OR(R4="",Q4=""),"",IFERROR(R4/Q4-1,"")) | S5: =IF(OR(S4="",R4=""),"",IFERROR(S4/R4-1,"")) | T5: =IF(OR(T4="",S4=""),"",IFERROR(T4/S4-1,"")) | U5: =IF(OR(U4="",T4=""),"",IFERROR(U4/T4-1,"")) | V5: =IF(OR(V4="",U4=""),"",IFERROR(V4/U4-1,"")) | W5: =IF(OR(W4="",V4=""),"",IFERROR(W4/V4-1,"")) | ... AC5: =IF(OR(AC4="",AB4=""),"",IFERROR(AC4/AB4-1,""))
A6: 제품별 매출 분류 | B6: 사업보고서 매출실적
A7: (제품별 매출 미공시 — 직접 입력)
A8: 비중 | C8: =IF(OR(C7="",C4=""),"",IFERROR(C7/C4,"")) | D8: =IF(OR(D7="",D4=""),"",IFERROR(D7/D4,"")) | E8: =IF(OR(E7="",E4=""),"",IFERROR(E7/E4,"")) | F8: =IF(OR(F7="",F4=""),"",IFERROR(F7/F4,"")) | G8: =IF(OR(G7="",G4=""),"",IFERROR(G7/G4,"")) | H8: =IF(OR(H7="",H4=""),"",IFERROR(H7/H4,"")) | I8: =IF(OR(I7="",I4=""),"",IFERROR(I7/I4,"")) | J8: =IF(OR(J7="",J4=""),"",IFERROR(J7/J4,"")) | ... AC8: =IF(OR(AC7="",AC4=""),"",IFERROR(AC7/AC4,""))
A9: YoY | G9: =IF(OR(G7="",C7=""),"",IFERROR(G7/C7-1,"")) | H9: =IF(OR(H7="",D7=""),"",IFERROR(H7/D7-1,"")) | I9: =IF(OR(I7="",E7=""),"",IFERROR(I7/E7-1,"")) | J9: =IF(OR(J7="",F7=""),"",IFERROR(J7/F7-1,"")) | K9: =IF(OR(K7="",G7=""),"",IFERROR(K7/G7-1,"")) | L9: =IF(OR(L7="",H7=""),"",IFERROR(L7/H7-1,"")) | M9: =IF(OR(M7="",I7=""),"",IFERROR(M7/I7-1,"")) | N9: =IF(OR(N7="",J7=""),"",IFERROR(N7/J7-1,"")) | P9: =IF(OR(P7="",O7=""),"",IFERROR(P7/O7-1,"")) | Q9: =IF(OR(Q7="",P7=""),"",IFERROR(Q7/P7-1,"")) | R9: =IF(OR(R7="",Q7=""),"",IFERROR(R7/Q7-1,"")) | S9: =IF(OR(S7="",R7=""),"",IFERROR(S7/R7-1,"")) | T9: =IF(OR(T7="",S7=""),"",IFERROR(T7/S7-1,"")) | U9: =IF(OR(U7="",T7=""),"",IFERROR(U7/T7-1,"")) | V9: =IF(OR(V7="",U7=""),"",IFERROR(V7/U7-1,"")) | W9: =IF(OR(W7="",V7=""),"",IFERROR(W7/V7-1,"")) | ... AC9: =IF(OR(AC7="",AB7=""),"",IFERROR(AC7/AB7-1,""))
A10: 매출원가
A11: 전체 매출원가 | C11: 2204.773 | D11: 398.395 | E11: 503.784 | F11: 1834.995 | G11: 2637.378 | H11: 1283.981 | I11: 1716.724 | J11: 1216.941 | K11: 1791.833 | L11: 1591.071 | M11: 924.291 | N11: 2015.685 | O11: 1215.858 | P11: 2303.501 | Q11: 3521.5 | R11: 5137.812 | S11: 3101.083 | T11: 3726.568 | U11: 3350.502 | V11: 4526.857 | W11: 5374.552 | X11: 6009.479
A12: YoY | G12: =IF(OR(G11="",C11=""),"",IF(C11<=0,"",IFERROR(G11/C11-1,""))) | H12: =IF(OR(H11="",D11=""),"",IF(D11<=0,"",IFERROR(H11/D11-1,""))) | I12: =IF(OR(I11="",E11=""),"",IF(E11<=0,"",IFERROR(I11/E11-1,""))) | J12: =IF(OR(J11="",F11=""),"",IF(F11<=0,"",IFERROR(J11/F11-1,""))) | K12: =IF(OR(K11="",G11=""),"",IF(G11<=0,"",IFERROR(K11/G11-1,""))) | L12: =IF(OR(L11="",H11=""),"",IF(H11<=0,"",IFERROR(L11/H11-1,""))) | M12: =IF(OR(M11="",I11=""),"",IF(I11<=0,"",IFERROR(M11/I11-1,""))) | N12: =IF(OR(N11="",J11=""),"",IF(J11<=0,"",IFERROR(N11/J11-1,""))) | P12: =IF(OR(P11="",O11=""),"",IF(O11<=0,"",IFERROR(P11/O11-1,""))) | Q12: =IF(OR(Q11="",P11=""),"",IF(P11<=0,"",IFERROR(Q11/P11-1,""))) | R12: =IF(OR(R11="",Q11=""),"",IF(Q11<=0,"",IFERROR(R11/Q11-1,""))) | S12: =IF(OR(S11="",R11=""),"",IF(R11<=0,"",IFERROR(S11/R11-1,""))) | T12: =IF(OR(T11="",S11=""),"",IF(S11<=0,"",IFERROR(T11/S11-1,""))) | U12: =IF(OR(U11="",T11=""),"",IF(T11<=0,"",IFERROR(U11/T11-1,""))) | V12: =IF(OR(V11="",U11=""),"",IF(U11<=0,"",IFERROR(V11/U11-1,""))) | W12: =IF(OR(W11="",V11=""),"",IF(V11<=0,"",IFERROR(W11/V11-1,""))) | ... AC12: =IF(OR(AC11="",AB11=""),"",IF(AB11<=0,"",IFERROR(AC11/AB11-1,"")))
A13: 매출총이익 | C13: =IF(OR(C4="",C11=""),"",IFERROR(C4-C11,"")) | D13: =IF(OR(D4="",D11=""),"",IFERROR(D4-D11,"")) | E13: =IF(OR(E4="",E11=""),"",IFERROR(E4-E11,"")) | F13: =IF(OR(F4="",F11=""),"",IFERROR(F4-F11,"")) | G13: =IF(OR(G4="",G11=""),"",IFERROR(G4-G11,"")) | H13: =IF(OR(H4="",H11=""),"",IFERROR(H4-H11,"")) | I13: =IF(OR(I4="",I11=""),"",IFERROR(I4-I11,"")) | J13: =IF(OR(J4="",J11=""),"",IFERROR(J4-J11,"")) | ... X13: =IF(OR(X4="",X11=""),"",IFERROR(X4-X11,""))
A14: GPM | C14: =IF(OR(C13="",C4=""),"",IFERROR(C13/C4,"")) | D14: =IF(OR(D13="",D4=""),"",IFERROR(D13/D4,"")) | E14: =IF(OR(E13="",E4=""),"",IFERROR(E13/E4,"")) | F14: =IF(OR(F13="",F4=""),"",IFERROR(F13/F4,"")) | G14: =IF(OR(G13="",G4=""),"",IFERROR(G13/G4,"")) | H14: =IF(OR(H13="",H4=""),"",IFERROR(H13/H4,"")) | I14: =IF(OR(I13="",I4=""),"",IFERROR(I13/I4,"")) | J14: =IF(OR(J13="",J4=""),"",IFERROR(J13/J4,"")) | ... AC14: =IF(OR(AC13="",AC4=""),"",IFERROR(AC13/AC4,""))
A15: YoY | G15: =IF(OR(G13="",C13=""),"",IF(C13<=0,"",IFERROR(G13/C13-1,""))) | H15: =IF(OR(H13="",D13=""),"",IF(D13<=0,"",IFERROR(H13/D13-1,""))) | I15: =IF(OR(I13="",E13=""),"",IF(E13<=0,"",IFERROR(I13/E13-1,""))) | J15: =IF(OR(J13="",F13=""),"",IF(F13<=0,"",IFERROR(J13/F13-1,""))) | K15: =IF(OR(K13="",G13=""),"",IF(G13<=0,"",IFERROR(K13/G13-1,""))) | L15: =IF(OR(L13="",H13=""),"",IF(H13<=0,"",IFERROR(L13/H13-1,""))) | M15: =IF(OR(M13="",I13=""),"",IF(I13<=0,"",IFERROR(M13/I13-1,""))) | N15: =IF(OR(N13="",J13=""),"",IF(J13<=0,"",IFERROR(N13/J13-1,""))) | P15: =IF(OR(P13="",O13=""),"",IF(O13<=0,"",IFERROR(P13/O13-1,""))) | Q15: =IF(OR(Q13="",P13=""),"",IF(P13<=0,"",IFERROR(Q13/P13-1,""))) | R15: =IF(OR(R13="",Q13=""),"",IF(Q13<=0,"",IFERROR(R13/Q13-1,""))) | S15: =IF(OR(S13="",R13=""),"",IF(R13<=0,"",IFERROR(S13/R13-1,""))) | T15: =IF(OR(T13="",S13=""),"",IF(S13<=0,"",IFERROR(T13/S13-1,""))) | U15: =IF(OR(U13="",T13=""),"",IF(T13<=0,"",IFERROR(U13/T13-1,""))) | V15: =IF(OR(V13="",U13=""),"",IF(U13<=0,"",IFERROR(V13/U13-1,""))) | W15: =IF(OR(W13="",V13=""),"",IF(V13<=0,"",IFERROR(W13/V13-1,""))) | ... AC15: =IF(OR(AC13="",AB13=""),"",IF(AB13<=0,"",IFERROR(AC13/AB13-1,"")))
A16: 판매관리비
A17: 전체 판관비 | C17: 355.604 | D17: 296.342 | E17: 312.202 | F17: 365.879 | G17: 411.891 | H17: 360.576 | I17: 383.18 | J17: 406.022 | K17: 485.543 | L17: 427.669 | M17: 430.506 | N17: 436.903 | O17: 246.009 | P17: 350.217 | Q17: 580.449 | R17: 790.553 | S17: 739.42 | T17: 980.873 | U17: 858.25 | V17: 1221.847 | W17: 1386.314 | X17: 1635.321
A18: YoY | G18: =IF(OR(G17="",C17=""),"",IF(C17<=0,"",IFERROR(G17/C17-1,""))) | H18: =IF(OR(H17="",D17=""),"",IF(D17<=0,"",IFERROR(H17/D17-1,""))) | I18: =IF(OR(I17="",E17=""),"",IF(E17<=0,"",IFERROR(I17/E17-1,""))) | J18: =IF(OR(J17="",F17=""),"",IF(F17<=0,"",IFERROR(J17/F17-1,""))) | K18: =IF(OR(K17="",G17=""),"",IF(G17<=0,"",IFERROR(K17/G17-1,""))) | L18: =IF(OR(L17="",H17=""),"",IF(H17<=0,"",IFERROR(L17/H17-1,""))) | M18: =IF(OR(M17="",I17=""),"",IF(I17<=0,"",IFERROR(M17/I17-1,""))) | N18: =IF(OR(N17="",J17=""),"",IF(J17<=0,"",IFERROR(N17/J17-1,""))) | P18: =IF(OR(P17="",O17=""),"",IF(O17<=0,"",IFERROR(P17/O17-1,""))) | Q18: =IF(OR(Q17="",P17=""),"",IF(P17<=0,"",IFERROR(Q17/P17-1,""))) | R18: =IF(OR(R17="",Q17=""),"",IF(Q17<=0,"",IFERROR(R17/Q17-1,""))) | S18: =IF(OR(S17="",R17=""),"",IF(R17<=0,"",IFERROR(S17/R17-1,""))) | T18: =IF(OR(T17="",S17=""),"",IF(S17<=0,"",IFERROR(T17/S17-1,""))) | U18: =IF(OR(U17="",T17=""),"",IF(T17<=0,"",IFERROR(U17/T17-1,""))) | V18: =IF(OR(V17="",U17=""),"",IF(U17<=0,"",IFERROR(V17/U17-1,""))) | W18: =IF(OR(W17="",V17=""),"",IF(V17<=0,"",IFERROR(W17/V17-1,""))) | ... AC18: =IF(OR(AC17="",AB17=""),"",IF(AB17<=0,"",IFERROR(AC17/AB17-1,"")))
A19: 영업이익 | B19: MW = 매출 × OPM | C19: 366.675 | D19: -88.654 | E19: -95.36 | F19: 337.956 | G19: 270.149 | H19: 127.906 | I19: 71.898 | J19: 61.59 | K19: 327.311 | L19: 24.296 | M19: -145.088 | N19: 391.116 | O19: 206.443 | P19: 296.398 | Q19: 637.128 | R19: 1096.344 | S19: 130.256 | T19: 724.912 | U19: 169.84 | V19: 214.815 | W19: 424.091 | X19: 588.705 | Y19: =IF(OR(Y4="",Y20=""),"",IFERROR(Y4*Y20,"")) | Z19: =IF(OR(Z4="",Z20=""),"",IFERROR(Z4*Z20,"")) | AA19: =IF(OR(AA4="",AA20=""),"",IFERROR(AA4*AA20,"")) | AB19: =IF(OR(AB4="",AB20=""),"",IFERROR(AB4*AB20,"")) | AC19: =IF(OR(AC4="",AC20=""),"",IFERROR(AC4*AC20,""))
A20: OPM | B20: MW 입력 | C20: =IF(OR(C19="",C4=""),"",IFERROR(C19/C4,"")) | D20: =IF(OR(D19="",D4=""),"",IFERROR(D19/D4,"")) | E20: =IF(OR(E19="",E4=""),"",IFERROR(E19/E4,"")) | F20: =IF(OR(F19="",F4=""),"",IFERROR(F19/F4,"")) | G20: =IF(OR(G19="",G4=""),"",IFERROR(G19/G4,"")) | H20: =IF(OR(H19="",H4=""),"",IFERROR(H19/H4,"")) | I20: =IF(OR(I19="",I4=""),"",IFERROR(I19/I4,"")) | J20: =IF(OR(J19="",J4=""),"",IFERROR(J19/J4,"")) | ... X20: =IF(OR(X19="",X4=""),"",IFERROR(X19/X4,""))
A21: 증가율 | G21: =IF(OR(G19="",C19=""),"",IFERROR(G19/C19-1,"")) | H21: =IF(OR(H19="",D19=""),"",IFERROR(H19/D19-1,"")) | I21: =IF(OR(I19="",E19=""),"",IFERROR(I19/E19-1,"")) | J21: =IF(OR(J19="",F19=""),"",IFERROR(J19/F19-1,"")) | K21: =IF(OR(K19="",G19=""),"",IFERROR(K19/G19-1,"")) | L21: =IF(OR(L19="",H19=""),"",IFERROR(L19/H19-1,"")) | M21: =IF(OR(M19="",I19=""),"",IFERROR(M19/I19-1,"")) | N21: =IF(OR(N19="",J19=""),"",IFERROR(N19/J19-1,"")) | P21: =IF(OR(P19="",O19=""),"",IFERROR(P19/O19-1,"")) | Q21: =IF(OR(Q19="",P19=""),"",IFERROR(Q19/P19-1,"")) | R21: =IF(OR(R19="",Q19=""),"",IFERROR(R19/Q19-1,"")) | S21: =IF(OR(S19="",R19=""),"",IFERROR(S19/R19-1,"")) | T21: =IF(OR(T19="",S19=""),"",IFERROR(T19/S19-1,"")) | U21: =IF(OR(U19="",T19=""),"",IFERROR(U19/T19-1,"")) | V21: =IF(OR(V19="",U19=""),"",IFERROR(V19/U19-1,"")) | W21: =IF(OR(W19="",V19=""),"",IFERROR(W19/V19-1,"")) | ... AC21: =IF(OR(AC19="",AB19=""),"",IFERROR(AC19/AB19-1,""))
A22: 비용의 성격별 분류 | B22: 참고 데이터
A23: 총 판관비 | O23: =IF(O17="","",O17) | P23: =IF(P17="","",P17) | Q23: =IF(Q17="","",Q17) | R23: =IF(R17="","",R17) | S23: =IF(S17="","",S17) | T23: =IF(T17="","",T17) | U23: =IF(U17="","",U17) | V23: =IF(V17="","",V17) | ... X23: =IF(X17="","",X17)
A24: 급여 | B24: 고정비 | O24: 58.048 | P24: 95.965 | Q24: 135.916
A25: % of Sales | O25: =IF(OR(O24="",O4=""),"",IFERROR(O24/O4,"")) | P25: =IF(OR(P24="",P4=""),"",IFERROR(P24/P4,"")) | Q25: =IF(OR(Q24="",Q4=""),"",IFERROR(Q24/Q4,"")) | R25: =IF(OR(R24="",R4=""),"",IFERROR(R24/R4,"")) | S25: =IF(OR(S24="",S4=""),"",IFERROR(S24/S4,"")) | T25: =IF(OR(T24="",T4=""),"",IFERROR(T24/T4,"")) | U25: =IF(OR(U24="",U4=""),"",IFERROR(U24/U4,"")) | V25: =IF(OR(V24="",V4=""),"",IFERROR(V24/V4,"")) | ... X25: =IF(OR(X24="",X4=""),"",IFERROR(X24/X4,""))
A26: 감가상각비 | B26: 고정비
A27: % of Sales | O27: =IF(OR(O26="",O4=""),"",IFERROR(O26/O4,"")) | P27: =IF(OR(P26="",P4=""),"",IFERROR(P26/P4,"")) | Q27: =IF(OR(Q26="",Q4=""),"",IFERROR(Q26/Q4,"")) | R27: =IF(OR(R26="",R4=""),"",IFERROR(R26/R4,"")) | S27: =IF(OR(S26="",S4=""),"",IFERROR(S26/S4,"")) | T27: =IF(OR(T26="",T4=""),"",IFERROR(T26/T4,"")) | U27: =IF(OR(U26="",U4=""),"",IFERROR(U26/U4,"")) | V27: =IF(OR(V26="",V4=""),"",IFERROR(V26/V4,"")) | ... X27: =IF(OR(X26="",X4=""),"",IFERROR(X26/X4,""))
A28: 지급수수료 | B28: 고정비
A29: % of Sales | O29: =IF(OR(O28="",O4=""),"",IFERROR(O28/O4,"")) | P29: =IF(OR(P28="",P4=""),"",IFERROR(P28/P4,"")) | Q29: =IF(OR(Q28="",Q4=""),"",IFERROR(Q28/Q4,"")) | R29: =IF(OR(R28="",R4=""),"",IFERROR(R28/R4,"")) | S29: =IF(OR(S28="",S4=""),"",IFERROR(S28/S4,"")) | T29: =IF(OR(T28="",T4=""),"",IFERROR(T28/T4,"")) | U29: =IF(OR(U28="",U4=""),"",IFERROR(U28/U4,"")) | V29: =IF(OR(V28="",V4=""),"",IFERROR(V28/V4,"")) | ... X29: =IF(OR(X28="",X4=""),"",IFERROR(X28/X4,""))
A30: 연구개발비 | B30: 변동비
A31: % of Sales | O31: =IF(OR(O30="",O4=""),"",IFERROR(O30/O4,"")) | P31: =IF(OR(P30="",P4=""),"",IFERROR(P30/P4,"")) | Q31: =IF(OR(Q30="",Q4=""),"",IFERROR(Q30/Q4,"")) | R31: =IF(OR(R30="",R4=""),"",IFERROR(R30/R4,"")) | S31: =IF(OR(S30="",S4=""),"",IFERROR(S30/S4,"")) | T31: =IF(OR(T30="",T4=""),"",IFERROR(T30/T4,"")) | U31: =IF(OR(U30="",U4=""),"",IFERROR(U30/U4,"")) | V31: =IF(OR(V30="",V4=""),"",IFERROR(V30/V4,"")) | ... X31: =IF(OR(X30="",X4=""),"",IFERROR(X30/X4,""))
A32: 기타비용 | B32: 변동비 | O32: =IF(OR(O23="",O24="",O26="",O28="",O30=""),"",IFERROR(O23-O24-O26-O28-O30,"")) | P32: =IF(OR(P23="",P24="",P26="",P28="",P30=""),"",IFERROR(P23-P24-P26-P28-P30,"")) | Q32: =IF(OR(Q23="",Q24="",Q26="",Q28="",Q30=""),"",IFERROR(Q23-Q24-Q26-Q28-Q30,"")) | R32: =IF(OR(R23="",R24="",R26="",R28="",R30=""),"",IFERROR(R23-R24-R26-R28-R30,"")) | S32: =IF(OR(S23="",S24="",S26="",S28="",S30=""),"",IFERROR(S23-S24-S26-S28-S30,"")) | T32: =IF(OR(T23="",T24="",T26="",T28="",T30=""),"",IFERROR(T23-T24-T26-T28-T30,"")) | U32: =IF(OR(U23="",U24="",U26="",U28="",U30=""),"",IFERROR(U23-U24-U26-U28-U30,"")) | V32: =IF(OR(V23="",V24="",V26="",V28="",V30=""),"",IFERROR(V23-V24-V26-V28-V30,"")) | ... X32: =IF(OR(X23="",X24="",X26="",X28="",X30=""),"",IFERROR(X23-X24-X26-X28-X30,""))
A33: % of Sales | O33: =IF(OR(O32="",O4=""),"",IFERROR(O32/O4,"")) | P33: =IF(OR(P32="",P4=""),"",IFERROR(P32/P4,"")) | Q33: =IF(OR(Q32="",Q4=""),"",IFERROR(Q32/Q4,"")) | R33: =IF(OR(R32="",R4=""),"",IFERROR(R32/R4,"")) | S33: =IF(OR(S32="",S4=""),"",IFERROR(S32/S4,"")) | T33: =IF(OR(T32="",T4=""),"",IFERROR(T32/T4,"")) | U33: =IF(OR(U32="",U4=""),"",IFERROR(U32/U4,"")) | V33: =IF(OR(V32="",V4=""),"",IFERROR(V32/V4,"")) | ... X33: =IF(OR(X32="",X4=""),"",IFERROR(X32/X4,""))
A34: 당기순이익 추정
A35: 특별이익 | C35: 0 | J35: 0 | N35: 0 | R35: 0 | S35: 0.15 | T35: 0 | U35: 21.525 | V35: 0 | Y35: =IF(OR(Y4="",Y36=""),"",IFERROR(Y4*Y36,"")) | Z35: =IF(OR(Z4="",Z36=""),"",IFERROR(Z4*Z36,"")) | AA35: =IF(OR(AA4="",AA36=""),"",IFERROR(AA4*AA36,"")) | AB35: =IF(OR(AB4="",AB36=""),"",IFERROR(AB4*AB36,"")) | AC35: =IF(OR(AC4="",AC36=""),"",IFERROR(AC4*AC36,""))
A36: % of Sales | B36: MW = 최근 3년 평균 | C36: =IF(OR(C35="",C4=""),"",IFERROR(C35/C4,"")) | D36: =IF(OR(D35="",D4=""),"",IFERROR(D35/D4,"")) | E36: =IF(OR(E35="",E4=""),"",IFERROR(E35/E4,"")) | F36: =IF(OR(F35="",F4=""),"",IFERROR(F35/F4,"")) | G36: =IF(OR(G35="",G4=""),"",IFERROR(G35/G4,"")) | H36: =IF(OR(H35="",H4=""),"",IFERROR(H35/H4,"")) | I36: =IF(OR(I35="",I4=""),"",IFERROR(I35/I4,"")) | J36: =IF(OR(J35="",J4=""),"",IFERROR(J35/J4,"")) | ... X36: =IF(OR(X35="",X4=""),"",IFERROR(X35/X4,"")) | Y36: =IFERROR(AVERAGE(V36,W36,X36),"") | Z36: =Y36 | AA36: =Z36 | AB36: =AA36 | AC36: =AB36
A37: 특별손실 | J37: 0 | K37: 0 | N37: 0 | Q37: 0 | R37: 100.991 | S37: 33.328 | T37: 73.933 | U37: 0 | V37: 0 | W37: 2.516 | X37: 0 | Y37: =IF(OR(Y4="",Y38=""),"",IFERROR(Y4*Y38,"")) | Z37: =IF(OR(Z4="",Z38=""),"",IFERROR(Z4*Z38,"")) | AA37: =IF(OR(AA4="",AA38=""),"",IFERROR(AA4*AA38,"")) | AB37: =IF(OR(AB4="",AB38=""),"",IFERROR(AB4*AB38,"")) | AC37: =IF(OR(AC4="",AC38=""),"",IFERROR(AC4*AC38,""))
A38: % of Sales | C38: =IF(OR(C37="",C4=""),"",IFERROR(C37/C4,"")) | D38: =IF(OR(D37="",D4=""),"",IFERROR(D37/D4,"")) | E38: =IF(OR(E37="",E4=""),"",IFERROR(E37/E4,"")) | F38: =IF(OR(F37="",F4=""),"",IFERROR(F37/F4,"")) | G38: =IF(OR(G37="",G4=""),"",IFERROR(G37/G4,"")) | H38: =IF(OR(H37="",H4=""),"",IFERROR(H37/H4,"")) | I38: =IF(OR(I37="",I4=""),"",IFERROR(I37/I4,"")) | J38: =IF(OR(J37="",J4=""),"",IFERROR(J37/J4,"")) | ... X38: =IF(OR(X37="",X4=""),"",IFERROR(X37/X4,"")) | Y38: =IFERROR(AVERAGE(V38,W38,X38),"") | Z38: =Y38 | AA38: =Z38 | AB38: =AA38 | AC38: =AB38
A39: 영업외수익 | C39: 0.198 | D39: 0.396 | E39: 2.478 | F39: 26.597 | G39: 2.974 | H39: 6.177 | I39: 10.584 | J39: 0.82 | K39: 2.874 | L39: 14.838 | M39: 7.619 | N39: 7.664 | O39: 27.905 | P39: 16.2 | Q39: 1.15 | R39: 3.391 | S39: 2.374 | T39: 3.409 | U39: 52.092 | V39: 3.808 | W39: 32.445 | X39: 20.455 | Y39: =IF(OR(Y4="",Y40=""),"",IFERROR(Y4*Y40,"")) | Z39: =IF(OR(Z4="",Z40=""),"",IFERROR(Z4*Z40,"")) | AA39: =IF(OR(AA4="",AA40=""),"",IFERROR(AA4*AA40,"")) | AB39: =IF(OR(AB4="",AB40=""),"",IFERROR(AB4*AB40,"")) | AC39: =IF(OR(AC4="",AC40=""),"",IFERROR(AC4*AC40,""))
A40: % of Sales | C40: =IF(OR(C39="",C4=""),"",IFERROR(C39/C4,"")) | D40: =IF(OR(D39="",D4=""),"",IFERROR(D39/D4,"")) | E40: =IF(OR(E39="",E4=""),"",IFERROR(E39/E4,"")) | F40: =IF(OR(F39="",F4=""),"",IFERROR(F39/F4,"")) | G40: =IF(OR(G39="",G4=""),"",IFERROR(G39/G4,"")) | H40: =IF(OR(H39="",H4=""),"",IFERROR(H39/H4,"")) | I40: =IF(OR(I39="",I4=""),"",IFERROR(I39/I4,"")) | J40: =IF(OR(J39="",J4=""),"",IFERROR(J39/J4,"")) | ... X40: =IF(OR(X39="",X4=""),"",IFERROR(X39/X4,"")) | Y40: =IFERROR(AVERAGE(V40,W40,X40),"") | Z40: =Y40 | AA40: =Z40 | AB40: =AA40 | AC40: =AB40
A41: 영업외비용 | C41: 6.556 | D41: 8.332 | E41: 7.596 | F41: 26.818 | G41: 5.015 | H41: 5.6 | I41: 6.037 | J41: 10.945 | K41: 17.091 | L41: 14.838 | M41: 26.607 | N41: 25.347 | O41: 5.917 | P41: 7.854 | Q41: 22.496 | R41: 23.131 | S41: 34.438 | T41: 15.045 | U41: 21.831 | V41: 82.807 | W41: 47.761 | X41: 39.673 | Y41: =IF(OR(Y4="",Y42=""),"",IFERROR(Y4*Y42,"")) | Z41: =IF(OR(Z4="",Z42=""),"",IFERROR(Z4*Z42,"")) | AA41: =IF(OR(AA4="",AA42=""),"",IFERROR(AA4*AA42,"")) | AB41: =IF(OR(AB4="",AB42=""),"",IFERROR(AB4*AB42,"")) | AC41: =IF(OR(AC4="",AC42=""),"",IFERROR(AC4*AC42,""))
A42: % of Sales | C42: =IF(OR(C41="",C4=""),"",IFERROR(C41/C4,"")) | D42: =IF(OR(D41="",D4=""),"",IFERROR(D41/D4,"")) | E42: =IF(OR(E41="",E4=""),"",IFERROR(E41/E4,"")) | F42: =IF(OR(F41="",F4=""),"",IFERROR(F41/F4,"")) | G42: =IF(OR(G41="",G4=""),"",IFERROR(G41/G4,"")) | H42: =IF(OR(H41="",H4=""),"",IFERROR(H41/H4,"")) | I42: =IF(OR(I41="",I4=""),"",IFERROR(I41/I4,"")) | J42: =IF(OR(J41="",J4=""),"",IFERROR(J41/J4,"")) | ... X42: =IF(OR(X41="",X4=""),"",IFERROR(X41/X4,"")) | Y42: =IFERROR(AVERAGE(V42,W42,X42),"") | Z42: =Y42 | AA42: =Z42 | AB42: =AA42 | AC42: =AB42
A43: 법인세비용차감전순이익(손실) | C43: 360.317 | D43: -96.589 | E43: -100.479 | F43: 337.735 | G43: 265.591 | H43: 128.482 | I43: 76.447 | J43: 51.464 | K43: 313.094 | L43: 24.297 | M43: -3.473 | N43: 373.435 | O43: 228.432 | P43: 304.744 | Q43: 615.782 | R43: 975.613 | S43: 65.014 | T43: 639.342 | U43: 221.626 | V43: 135.816 | W43: 406.258 | X43: 569.487 | Y43: =IF(OR(Y19=""),"",IFERROR(Y19+N(Y35)-N(Y37)+N(Y39)-N(Y41),"")) | Z43: =IF(OR(Z19=""),"",IFERROR(Z19+N(Z35)-N(Z37)+N(Z39)-N(Z41),"")) | AA43: =IF(OR(AA19=""),"",IFERROR(AA19+N(AA35)-N(AA37)+N(AA39)-N(AA41),"")) | AB43: =IF(OR(AB19=""),"",IFERROR(AB19+N(AB35)-N(AB37)+N(AB39)-N(AB41),"")) | AC43: =IF(OR(AC19=""),"",IFERROR(AC19+N(AC35)-N(AC37)+N(AC39)-N(AC41),""))
A44: YoY | G44: =IF(OR(G43="",C43=""),"",IF(C43<=0,"",IFERROR(G43/C43-1,""))) | H44: =IF(OR(H43="",D43=""),"",IF(D43<=0,"",IFERROR(H43/D43-1,""))) | I44: =IF(OR(I43="",E43=""),"",IF(E43<=0,"",IFERROR(I43/E43-1,""))) | J44: =IF(OR(J43="",F43=""),"",IF(F43<=0,"",IFERROR(J43/F43-1,""))) | K44: =IF(OR(K43="",G43=""),"",IF(G43<=0,"",IFERROR(K43/G43-1,""))) | L44: =IF(OR(L43="",H43=""),"",IF(H43<=0,"",IFERROR(L43/H43-1,""))) | M44: =IF(OR(M43="",I43=""),"",IF(I43<=0,"",IFERROR(M43/I43-1,""))) | N44: =IF(OR(N43="",J43=""),"",IF(J43<=0,"",IFERROR(N43/J43-1,""))) | P44: =IF(OR(P43="",O43=""),"",IF(O43<=0,"",IFERROR(P43/O43-1,""))) | Q44: =IF(OR(Q43="",P43=""),"",IF(P43<=0,"",IFERROR(Q43/P43-1,""))) | R44: =IF(OR(R43="",Q43=""),"",IF(Q43<=0,"",IFERROR(R43/Q43-1,""))) | S44: =IF(OR(S43="",R43=""),"",IF(R43<=0,"",IFERROR(S43/R43-1,""))) | T44: =IF(OR(T43="",S43=""),"",IF(S43<=0,"",IFERROR(T43/S43-1,""))) | U44: =IF(OR(U43="",T43=""),"",IF(T43<=0,"",IFERROR(U43/T43-1,""))) | V44: =IF(OR(V43="",U43=""),"",IF(U43<=0,"",IFERROR(V43/U43-1,""))) | W44: =IF(OR(W43="",V43=""),"",IF(V43<=0,"",IFERROR(W43/V43-1,""))) | ... AC44: =IF(OR(AC43="",AB43=""),"",IF(AB43<=0,"",IFERROR(AC43/AB43-1,"")))
A45: 법인세비용(수익) | C45: 137.516 | D45: -25.18 | E45: -28.256 | F45: 107.1 | G45: 90.729 | H45: 46.434 | I45: 30.868 | J45: 24.159 | K45: 69.949 | L45: 12.94 | M45: 27.437 | N45: 126.275 | O45: 57.014 | P45: 117.085 | Q45: 200.705 | R45: 374.801 | S45: 45.353 | T45: 232.001 | U45: 79.607 | V45: 97.876 | W45: 144.393 | X45: 171.41 | Y45: =IF(OR(Y43="",Y46=""),"",IFERROR(MAX(Y43,0)*Y46,"")) | Z45: =IF(OR(Z43="",Z46=""),"",IFERROR(MAX(Z43,0)*Z46,"")) | AA45: =IF(OR(AA43="",AA46=""),"",IFERROR(MAX(AA43,0)*AA46,"")) | AB45: =IF(OR(AB43="",AB46=""),"",IFERROR(MAX(AB43,0)*AB46,"")) | AC45: =IF(OR(AC43="",AC46=""),"",IFERROR(MAX(AC43,0)*AC46,""))
A46: 법인세율 | B46: MW 기본 30% | C46: =IF(OR(C45="",C43=""),"",IFERROR(C45/C43,"")) | D46: =IF(OR(D45="",D43=""),"",IFERROR(D45/D43,"")) | E46: =IF(OR(E45="",E43=""),"",IFERROR(E45/E43,"")) | F46: =IF(OR(F45="",F43=""),"",IFERROR(F45/F43,"")) | G46: =IF(OR(G45="",G43=""),"",IFERROR(G45/G43,"")) | H46: =IF(OR(H45="",H43=""),"",IFERROR(H45/H43,"")) | I46: =IF(OR(I45="",I43=""),"",IFERROR(I45/I43,"")) | J46: =IF(OR(J45="",J43=""),"",IFERROR(J45/J43,"")) | ... X46: =IF(OR(X45="",X43=""),"",IFERROR(X45/X43,"")) | Y46: 0.3 | Z46: 0.3 | AA46: 0.3 | AB46: 0.3 | AC46: 0.3
A47: 당기순이익(손실) | C47: 222.801 | D47: -71.409 | E47: -72.223 | F47: 230.635 | G47: 174.862 | H47: 82.047 | I47: 45.579 | J47: 27.306 | K47: 243.145 | L47: 11.356 | M47: -30.908 | N47: 247.158 | O47: 171.417 | P47: 187.659 | Q47: 415.076 | R47: 600.812 | S47: 19.66 | T47: 407.341 | U47: 142.019 | V47: 37.94 | W47: 261.865 | X47: 398.077 | Y47: =IF(OR(Y43=""),"",IFERROR(Y43-Y45,"")) | Z47: =IF(OR(Z43=""),"",IFERROR(Z43-Z45,"")) | AA47: =IF(OR(AA43=""),"",IFERROR(AA43-AA45,"")) | AB47: =IF(OR(AB43=""),"",IFERROR(AB43-AB45,"")) | AC47: =IF(OR(AC43=""),"",IFERROR(AC43-AC45,""))
A48: YoY | G48: =IF(OR(G47="",C47=""),"",IF(C47<=0,"",IFERROR(G47/C47-1,""))) | H48: =IF(OR(H47="",D47=""),"",IF(D47<=0,"",IFERROR(H47/D47-1,""))) | I48: =IF(OR(I47="",E47=""),"",IF(E47<=0,"",IFERROR(I47/E47-1,""))) | J48: =IF(OR(J47="",F47=""),"",IF(F47<=0,"",IFERROR(J47/F47-1,""))) | K48: =IF(OR(K47="",G47=""),"",IF(G47<=0,"",IFERROR(K47/G47-1,""))) | L48: =IF(OR(L47="",H47=""),"",IF(H47<=0,"",IFERROR(L47/H47-1,""))) | M48: =IF(OR(M47="",I47=""),"",IF(I47<=0,"",IFERROR(M47/I47-1,""))) | N48: =IF(OR(N47="",J47=""),"",IF(J47<=0,"",IFERROR(N47/J47-1,""))) | P48: =IF(OR(P47="",O47=""),"",IF(O47<=0,"",IFERROR(P47/O47-1,""))) | Q48: =IF(OR(Q47="",P47=""),"",IF(P47<=0,"",IFERROR(Q47/P47-1,""))) | R48: =IF(OR(R47="",Q47=""),"",IF(Q47<=0,"",IFERROR(R47/Q47-1,""))) | S48: =IF(OR(S47="",R47=""),"",IF(R47<=0,"",IFERROR(S47/R47-1,""))) | T48: =IF(OR(T47="",S47=""),"",IF(S47<=0,"",IFERROR(T47/S47-1,""))) | U48: =IF(OR(U47="",T47=""),"",IF(T47<=0,"",IFERROR(U47/T47-1,""))) | V48: =IF(OR(V47="",U47=""),"",IF(U47<=0,"",IFERROR(V47/U47-1,""))) | W48: =IF(OR(W47="",V47=""),"",IF(V47<=0,"",IFERROR(W47/V47-1,""))) | ... AC48: =IF(OR(AC47="",AB47=""),"",IF(AB47<=0,"",IFERROR(AC47/AB47-1,"")))
A49: 지배주주 순이익 | C49: 222.803 | D49: -71.409 | E49: -72.223 | F49: 230.635 | G49: 174.862 | H49: 82.047 | I49: 45.579 | J49: 27.306 | K49: 243.145 | L49: 11.356 | M49: -30.908 | N49: 247.158 | O49: 171.417 | P49: 187.659 | Q49: 415.076 | R49: 600.812 | S49: 19.66 | T49: 407.47 | U49: 142.103 | V49: 38.035 | W49: 261.865 | X49: 398.077 | Y49: =IF(OR(Y47="",Y50=""),"",IFERROR(Y47*Y50,"")) | Z49: =IF(OR(Z47="",Z50=""),"",IFERROR(Z47*Z50,"")) | AA49: =IF(OR(AA47="",AA50=""),"",IFERROR(AA47*AA50,"")) | AB49: =IF(OR(AB47="",AB50=""),"",IFERROR(AB47*AB50,"")) | AC49: =IF(OR(AC47="",AC50=""),"",IFERROR(AC47*AC50,""))
A50: 지배주주 순이익률 | B50: MW 기본 100% | C50: =IF(OR(C49="",C47=""),"",IFERROR(C49/C47,"")) | D50: =IF(OR(D49="",D47=""),"",IFERROR(D49/D47,"")) | E50: =IF(OR(E49="",E47=""),"",IFERROR(E49/E47,"")) | F50: =IF(OR(F49="",F47=""),"",IFERROR(F49/F47,"")) | G50: =IF(OR(G49="",G47=""),"",IFERROR(G49/G47,"")) | H50: =IF(OR(H49="",H47=""),"",IFERROR(H49/H47,"")) | I50: =IF(OR(I49="",I47=""),"",IFERROR(I49/I47,"")) | J50: =IF(OR(J49="",J47=""),"",IFERROR(J49/J47,"")) | ... X50: =IF(OR(X49="",X47=""),"",IFERROR(X49/X47,"")) | Y50: 1 | Z50: 1 | AA50: 1 | AB50: 1 | AC50: 1
A51: 지배주주 순이익 YoY | G51: =IF(OR(G49="",C49=""),"",IF(C49<=0,"",IFERROR(G49/C49-1,""))) | H51: =IF(OR(H49="",D49=""),"",IF(D49<=0,"",IFERROR(H49/D49-1,""))) | I51: =IF(OR(I49="",E49=""),"",IF(E49<=0,"",IFERROR(I49/E49-1,""))) | J51: =IF(OR(J49="",F49=""),"",IF(F49<=0,"",IFERROR(J49/F49-1,""))) | K51: =IF(OR(K49="",G49=""),"",IF(G49<=0,"",IFERROR(K49/G49-1,""))) | L51: =IF(OR(L49="",H49=""),"",IF(H49<=0,"",IFERROR(L49/H49-1,""))) | M51: =IF(OR(M49="",I49=""),"",IF(I49<=0,"",IFERROR(M49/I49-1,""))) | N51: =IF(OR(N49="",J49=""),"",IF(J49<=0,"",IFERROR(N49/J49-1,""))) | P51: =IF(OR(P49="",O49=""),"",IF(O49<=0,"",IFERROR(P49/O49-1,""))) | Q51: =IF(OR(Q49="",P49=""),"",IF(P49<=0,"",IFERROR(Q49/P49-1,""))) | R51: =IF(OR(R49="",Q49=""),"",IF(Q49<=0,"",IFERROR(R49/Q49-1,""))) | S51: =IF(OR(S49="",R49=""),"",IF(R49<=0,"",IFERROR(S49/R49-1,""))) | T51: =IF(OR(T49="",S49=""),"",IF(S49<=0,"",IFERROR(T49/S49-1,""))) | U51: =IF(OR(U49="",T49=""),"",IF(T49<=0,"",IFERROR(U49/T49-1,""))) | V51: =IF(OR(V49="",U49=""),"",IF(U49<=0,"",IFERROR(V49/U49-1,""))) | W51: =IF(OR(W49="",V49=""),"",IF(V49<=0,"",IFERROR(W49/V49-1,""))) | ... AC51: =IF(OR(AC49="",AB49=""),"",IF(AB49<=0,"",IFERROR(AC49/AB49-1,"")))
A52: 목표주가 산출
A53: 현재 주가 ()
A54: 발행주식수 (보통주)
A55: 시가총액 (백만엔) | B55: =IF(OR(B53="",B54=""),"",B53*B54/1000000.0)
A56: OPM | O56: =IF(O20="","",O20) | P56: =IF(P20="","",P20) | Q56: =IF(Q20="","",Q20) | R56: =IF(R20="","",R20) | S56: =IF(S20="","",S20) | T56: =IF(T20="","",T20) | U56: =IF(U20="","",U20) | V56: =IF(V20="","",V20) | ... AC56: =IF(AC20="","",AC20)
A57: 지배주주 순이익 증가율 | P57: =IF(OR(P49="",O49=""),"",IFERROR(P49/O49-1,"")) | Q57: =IF(OR(Q49="",P49=""),"",IFERROR(Q49/P49-1,"")) | R57: =IF(OR(R49="",Q49=""),"",IFERROR(R49/Q49-1,"")) | S57: =IF(OR(S49="",R49=""),"",IFERROR(S49/R49-1,"")) | T57: =IF(OR(T49="",S49=""),"",IFERROR(T49/S49-1,"")) | U57: =IF(OR(U49="",T49=""),"",IFERROR(U49/T49-1,"")) | V57: =IF(OR(V49="",U49=""),"",IFERROR(V49/U49-1,"")) | W57: =IF(OR(W49="",V49=""),"",IFERROR(W49/V49-1,"")) | ... AC57: =IF(OR(AC49="",AB49=""),"",IFERROR(AC49/AB49-1,""))
A58: P/E (현재 주가) | B58: 시총 ÷ 지배순이익 | X58: =IF(OR($B$55="",X49=""),"",IFERROR($B$55/X49,"")) | Y58: =IF(OR($B$55="",Y49=""),"",IFERROR($B$55/Y49,"")) | Z58: =IF(OR($B$55="",Z49=""),"",IFERROR($B$55/Z49,"")) | AA58: =IF(OR($B$55="",AA49=""),"",IFERROR($B$55/AA49,"")) | AB58: =IF(OR($B$55="",AB49=""),"",IFERROR($B$55/AB49,"")) | AC58: =IF(OR($B$55="",AC49=""),"",IFERROR($B$55/AC49,""))
A59: Target P/E | B59: 직접 입력
A60: EPS | B60: 지배순이익 ÷ 주식수 | O60: =IF(OR(O49="",$B$54=""),"",IFERROR(O49*1000000.0/$B$54,"")) | P60: =IF(OR(P49="",$B$54=""),"",IFERROR(P49*1000000.0/$B$54,"")) | Q60: =IF(OR(Q49="",$B$54=""),"",IFERROR(Q49*1000000.0/$B$54,"")) | R60: =IF(OR(R49="",$B$54=""),"",IFERROR(R49*1000000.0/$B$54,"")) | S60: =IF(OR(S49="",$B$54=""),"",IFERROR(S49*1000000.0/$B$54,"")) | T60: =IF(OR(T49="",$B$54=""),"",IFERROR(T49*1000000.0/$B$54,"")) | U60: =IF(OR(U49="",$B$54=""),"",IFERROR(U49*1000000.0/$B$54,"")) | V60: =IF(OR(V49="",$B$54=""),"",IFERROR(V49*1000000.0/$B$54,"")) | ... AC60: =IF(OR(AC49="",$B$54=""),"",IFERROR(AC49*1000000.0/$B$54,""))
A61: 목표주가 | Y61: =IF(OR(Y60="",Y59=""),"",IFERROR(Y60*Y59,"")) | Z61: =IF(OR(Z60="",Z59=""),"",IFERROR(Z60*Z59,"")) | AA61: =IF(OR(AA60="",AA59=""),"",IFERROR(AA60*AA59,"")) | AB61: =IF(OR(AB60="",AB59=""),"",IFERROR(AB60*AB59,"")) | AC61: =IF(OR(AC60="",AC59=""),"",IFERROR(AC60*AC59,""))
A62: 상승여력 | Y62: =IF(OR(Y61="",$B$53=""),"",IFERROR(Y61/$B$53-1,"")) | Z62: =IF(OR(Z61="",$B$53=""),"",IFERROR(Z61/$B$53-1,"")) | AA62: =IF(OR(AA61="",$B$53=""),"",IFERROR(AA61/$B$53-1,"")) | AB62: =IF(OR(AB61="",$B$53=""),"",IFERROR(AB61/$B$53-1,"")) | AC62: =IF(OR(AC61="",$B$53=""),"",IFERROR(AC61/$B$53-1,""))
A63: 자산가치 산출 | B63: 최신 분기 BS
A64: 현금및현금성자산 | X64: ='재무상태표'!G6 | Y64: ='재무상태표'!G6 | Z64: ='재무상태표'!G6 | AA64: ='재무상태표'!G6 | AB64: ='재무상태표'!G6 | AC64: ='재무상태표'!G6
A65: 단기금융상품 | X65: ='재무상태표'!G7 | Y65: ='재무상태표'!G7 | Z65: ='재무상태표'!G7 | AA65: ='재무상태표'!G7 | AB65: ='재무상태표'!G7 | AC65: ='재무상태표'!G7
A66: 투자부동산 | X66: ='재무상태표'!G14 | Y66: ='재무상태표'!G14 | Z66: ='재무상태표'!G14 | AA66: ='재무상태표'!G14 | AB66: ='재무상태표'!G14 | AC66: ='재무상태표'!G14
A67: 지배자본 | X67: ='재무상태표'!G31 | Y67: ='재무상태표'!G31 | Z67: ='재무상태표'!G31 | AA67: ='재무상태표'!G31 | AB67: ='재무상태표'!G31 | AC67: ='재무상태표'!G31
A68: 부채 | X68: ='재무상태표'!G27 | Y68: ='재무상태표'!G27 | Z68: ='재무상태표'!G27 | AA68: ='재무상태표'!G27 | AB68: ='재무상태표'!G27 | AC68: ='재무상태표'!G27
A69: 부채비율 | X69: =IF(OR(X68="",X67=""),"",IFERROR(X68/X67,"")) | Y69: =IF(OR(Y68="",Y67=""),"",IFERROR(Y68/Y67,"")) | Z69: =IF(OR(Z68="",Z67=""),"",IFERROR(Z68/Z67,"")) | AA69: =IF(OR(AA68="",AA67=""),"",IFERROR(AA68/AA67,"")) | AB69: =IF(OR(AB68="",AB67=""),"",IFERROR(AB68/AB67,"")) | AC69: =IF(OR(AC68="",AC67=""),"",IFERROR(AC68/AC67,""))
A70: 자산가치 | B70: 현금+단기금융+투자부동산 | X70: =SUM(X64,X65,X66) | Y70: =SUM(Y64,Y65,Y66) | Z70: =SUM(Z64,Z65,Z66) | AA70: =SUM(AA64,AA65,AA66) | AB70: =SUM(AB64,AB65,AB66) | AC70: =SUM(AC64,AC65,AC66)
A71: 기업가치 산출
A72: 목표 시가총액 (P/E) | B72: 지배순이익 × Target P/E | Y72: =IF(OR(Y49="",Y59=""),"",IFERROR(Y49*Y59,"")) | Z72: =IF(OR(Z49="",Z59=""),"",IFERROR(Z49*Z59,"")) | AA72: =IF(OR(AA49="",AA59=""),"",IFERROR(AA49*AA59,"")) | AB72: =IF(OR(AB49="",AB59=""),"",IFERROR(AB49*AB59,"")) | AC72: =IF(OR(AC49="",AC59=""),"",IFERROR(AC49*AC59,""))
A73: 기업가치 | B73: 목표시총 + 자산가치 | Y73: =IF(OR(Y72=""),"",IFERROR(Y72+Y70,"")) | Z73: =IF(OR(Z72=""),"",IFERROR(Z72+Z70,"")) | AA73: =IF(OR(AA72=""),"",IFERROR(AA72+AA70,"")) | AB73: =IF(OR(AB72=""),"",IFERROR(AB72+AB70,"")) | AC73: =IF(OR(AC72=""),"",IFERROR(AC72+AC70,""))
A74: 현재 시가총액 | Y74: =$B$55 | Z74: =$B$55 | AA74: =$B$55 | AB74: =$B$55 | AC74: =$B$55
A75: 상승여력 | Y75: =IF(OR(Y73="",Y74=""),"",IFERROR(Y73/Y74-1,"")) | Z75: =IF(OR(Z73="",Z74=""),"",IFERROR(Z73/Z74-1,"")) | AA75: =IF(OR(AA73="",AA74=""),"",IFERROR(AA73/AA74-1,"")) | AB75: =IF(OR(AB73="",AB74=""),"",IFERROR(AB73/AB74-1,"")) | AC75: =IF(OR(AC73="",AC74=""),"",IFERROR(AC73/AC74-1,""))
A77: 출처
A78: 결산단신 XBRL(TDnet·JPX 보관소) — 쓴 문서는 '출처' 시트
A79: 분기 = 누계에서 앞 분기를 뺀 3개월 값
A80: 주가: 야후 파이낸스 일봉
A82: 손익계산서 · 전 항목 | B82: 분기 = 3개월 단독
A83: 항목 | B83: 참고 | C83: 2023.4Q | D83: 2024.1Q | E83: 2024.2Q | F83: 2024.3Q | G83: 2024.4Q | H83: 2025.1Q | I83: 2025.2Q | J83: 2025.3Q | K83: 2025.4Q | L83: 2026.1Q | M83: 2026.2Q | N83: 2026.3Q | O83: 2016 | P83: 2017 | Q83: 2018 | R83: 2019 | S83: 2020 | T83: 2021 | U83: 2022 | V83: 2023 | W83: 2024 | X83: 2025 | Y83: 2026(MW) | Z83: 2027(MW) | AA83: 2028(MW) | AB83: 2029(MW) | AC83: 2030(MW)
A84: 매출액 | C84: 2927.053 | D84: 606.083 | E84: 720.626 | F84: 2538.831 | G84: 3319.417 | H84: 1772.464 | I84: 2171.803 | J84: 1684.552 | K84: 2604.686 | L84: 2043.037 | M84: 1209.707 | N84: 2843.707 | U84: 1913.902 | V84: 2927.053 | W84: 3319.417 | X84: 2604.686
A85: YoY | B85: 전년 같은 분기·전년 대비 | G85: =IF(OR(G84="",C84=""),"",IF(C84<=0,"",IFERROR(G84/C84-1,""))) | H85: =IF(OR(H84="",D84=""),"",IF(D84<=0,"",IFERROR(H84/D84-1,""))) | I85: =IF(OR(I84="",E84=""),"",IF(E84<=0,"",IFERROR(I84/E84-1,""))) | J85: =IF(OR(J84="",F84=""),"",IF(F84<=0,"",IFERROR(J84/F84-1,""))) | K85: =IF(OR(K84="",G84=""),"",IF(G84<=0,"",IFERROR(K84/G84-1,""))) | L85: =IF(OR(L84="",H84=""),"",IF(H84<=0,"",IFERROR(L84/H84-1,""))) | M85: =IF(OR(M84="",I84=""),"",IF(I84<=0,"",IFERROR(M84/I84-1,""))) | N85: =IF(OR(N84="",J84=""),"",IF(J84<=0,"",IFERROR(N84/J84-1,""))) | U85: =IF(OR(U84="",T84=""),"",IF(T84<=0,"",IFERROR(U84/T84-1,""))) | V85: =IF(OR(V84="",U84=""),"",IF(U84<=0,"",IFERROR(V84/U84-1,""))) | W85: =IF(OR(W84="",V84=""),"",IF(V84<=0,"",IFERROR(W84/V84-1,""))) | X85: =IF(OR(X84="",W84=""),"",IF(W84<=0,"",IFERROR(X84/W84-1,"")))
A86: 매출원가 | C86: 2204.773 | D86: 398.395 | E86: 503.784 | F86: 1834.995 | G86: 2637.378 | H86: 1283.981 | I86: 1716.724 | J86: 1216.941 | K86: 1791.833 | L86: 1591.071 | M86: 924.291 | N86: 2015.685 | U86: 1446.725 | V86: 2204.773 | W86: 2637.378 | X86: 1791.833
A87: YoY | B87: 전년 같은 분기·전년 대비 | G87: =IF(OR(G86="",C86=""),"",IF(G86*C86<=0,"",IFERROR(G86/C86-1,""))) | H87: =IF(OR(H86="",D86=""),"",IF(H86*D86<=0,"",IFERROR(H86/D86-1,""))) | I87: =IF(OR(I86="",E86=""),"",IF(I86*E86<=0,"",IFERROR(I86/E86-1,""))) | J87: =IF(OR(J86="",F86=""),"",IF(J86*F86<=0,"",IFERROR(J86/F86-1,""))) | K87: =IF(OR(K86="",G86=""),"",IF(K86*G86<=0,"",IFERROR(K86/G86-1,""))) | L87: =IF(OR(L86="",H86=""),"",IF(L86*H86<=0,"",IFERROR(L86/H86-1,""))) | M87: =IF(OR(M86="",I86=""),"",IF(M86*I86<=0,"",IFERROR(M86/I86-1,""))) | N87: =IF(OR(N86="",J86=""),"",IF(N86*J86<=0,"",IFERROR(N86/J86-1,""))) | U87: =IF(OR(U86="",T86=""),"",IF(U86*T86<=0,"",IFERROR(U86/T86-1,""))) | V87: =IF(OR(V86="",U86=""),"",IF(V86*U86<=0,"",IFERROR(V86/U86-1,""))) | W87: =IF(OR(W86="",V86=""),"",IF(W86*V86<=0,"",IFERROR(W86/V86-1,""))) | X87: =IF(OR(X86="",W86=""),"",IF(X86*W86<=0,"",IFERROR(X86/W86-1,"")))
A88: 매출총이익 | C88: 722.28 | D88: 207.688 | E88: 216.842 | F88: 703.835 | G88: 682.04 | H88: 488.483 | I88: 455.078 | J88: 467.611 | K88: 812.854 | L88: 451.965 | M88: 285.417 | N88: 828.021 | U88: 467.176 | V88: 722.28 | W88: 682.04 | X88: 812.854
A89: YoY | B89: 전년 같은 분기·전년 대비 | G89: =IF(OR(G88="",C88=""),"",IF(C88<=0,"",IFERROR(G88/C88-1,""))) | H89: =IF(OR(H88="",D88=""),"",IF(D88<=0,"",IFERROR(H88/D88-1,""))) | I89: =IF(OR(I88="",E88=""),"",IF(E88<=0,"",IFERROR(I88/E88-1,""))) | J89: =IF(OR(J88="",F88=""),"",IF(F88<=0,"",IFERROR(J88/F88-1,""))) | K89: =IF(OR(K88="",G88=""),"",IF(G88<=0,"",IFERROR(K88/G88-1,""))) | L89: =IF(OR(L88="",H88=""),"",IF(H88<=0,"",IFERROR(L88/H88-1,""))) | M89: =IF(OR(M88="",I88=""),"",IF(I88<=0,"",IFERROR(M88/I88-1,""))) | N89: =IF(OR(N88="",J88=""),"",IF(J88<=0,"",IFERROR(N88/J88-1,""))) | U89: =IF(OR(U88="",T88=""),"",IF(T88<=0,"",IFERROR(U88/T88-1,""))) | V89: =IF(OR(V88="",U88=""),"",IF(U88<=0,"",IFERROR(V88/U88-1,""))) | W89: =IF(OR(W88="",V88=""),"",IF(V88<=0,"",IFERROR(W88/V88-1,""))) | X89: =IF(OR(X88="",W88=""),"",IF(W88<=0,"",IFERROR(X88/W88-1,"")))
A90: 판매비와 관리비 | C90: 355.604 | D90: 296.342 | E90: 312.202 | F90: 365.879 | G90: 411.891 | H90: 360.576 | I90: 383.18 | J90: 406.022 | K90: 485.543 | L90: 427.669 | M90: 430.506 | N90: 436.903 | U90: 262.056 | V90: 355.604 | W90: 411.891 | X90: 485.543
A91: YoY | B91: 전년 같은 분기·전년 대비 | G91: =IF(OR(G90="",C90=""),"",IF(G90*C90<=0,"",IFERROR(G90/C90-1,""))) | H91: =IF(OR(H90="",D90=""),"",IF(H90*D90<=0,"",IFERROR(H90/D90-1,""))) | I91: =IF(OR(I90="",E90=""),"",IF(I90*E90<=0,"",IFERROR(I90/E90-1,""))) | J91: =IF(OR(J90="",F90=""),"",IF(J90*F90<=0,"",IFERROR(J90/F90-1,""))) | K91: =IF(OR(K90="",G90=""),"",IF(K90*G90<=0,"",IFERROR(K90/G90-1,""))) | L91: =IF(OR(L90="",H90=""),"",IF(L90*H90<=0,"",IFERROR(L90/H90-1,""))) | M91: =IF(OR(M90="",I90=""),"",IF(M90*I90<=0,"",IFERROR(M90/I90-1,""))) | N91: =IF(OR(N90="",J90=""),"",IF(N90*J90<=0,"",IFERROR(N90/J90-1,""))) | U91: =IF(OR(U90="",T90=""),"",IF(U90*T90<=0,"",IFERROR(U90/T90-1,""))) | V91: =IF(OR(V90="",U90=""),"",IF(V90*U90<=0,"",IFERROR(V90/U90-1,""))) | W91: =IF(OR(W90="",V90=""),"",IF(W90*V90<=0,"",IFERROR(W90/V90-1,""))) | X91: =IF(OR(X90="",W90=""),"",IF(X90*W90<=0,"",IFERROR(X90/W90-1,"")))
A92: 영업이익 | C92: 366.675 | D92: -88.654 | E92: -95.36 | F92: 337.956 | G92: 270.149 | H92: 127.906 | I92: 71.898 | J92: 61.59 | K92: 327.311 | L92: 24.296 | M92: -145.088 | N92: 391.116 | U92: 205.12 | V92: 366.675 | W92: 270.149 | X92: 327.311
A93: OPM | B93: 영업이익 ÷ 매출 | C93: =IF(OR(C92="",C84=""),"",IF(C84<=0,"",IFERROR(C92/C84,""))) | D93: =IF(OR(D92="",D84=""),"",IF(D84<=0,"",IFERROR(D92/D84,""))) | E93: =IF(OR(E92="",E84=""),"",IF(E84<=0,"",IFERROR(E92/E84,""))) | F93: =IF(OR(F92="",F84=""),"",IF(F84<=0,"",IFERROR(F92/F84,""))) | G93: =IF(OR(G92="",G84=""),"",IF(G84<=0,"",IFERROR(G92/G84,""))) | H93: =IF(OR(H92="",H84=""),"",IF(H84<=0,"",IFERROR(H92/H84,""))) | I93: =IF(OR(I92="",I84=""),"",IF(I84<=0,"",IFERROR(I92/I84,""))) | J93: =IF(OR(J92="",J84=""),"",IF(J84<=0,"",IFERROR(J92/J84,""))) | ... N93: =IF(OR(N92="",N84=""),"",IF(N84<=0,"",IFERROR(N92/N84,""))) | U93: =IF(OR(U92="",U84=""),"",IF(U84<=0,"",IFERROR(U92/U84,""))) | V93: =IF(OR(V92="",V84=""),"",IF(V84<=0,"",IFERROR(V92/V84,""))) | W93: =IF(OR(W92="",W84=""),"",IF(W84<=0,"",IFERROR(W92/W84,""))) | X93: =IF(OR(X92="",X84=""),"",IF(X84<=0,"",IFERROR(X92/X84,"")))
A94: YoY | B94: 전년 같은 분기·전년 대비 | G94: =IF(OR(G92="",C92=""),"",IF(C92<=0,"",IFERROR(G92/C92-1,""))) | H94: =IF(OR(H92="",D92=""),"",IF(D92<=0,"",IFERROR(H92/D92-1,""))) | I94: =IF(OR(I92="",E92=""),"",IF(E92<=0,"",IFERROR(I92/E92-1,""))) | J94: =IF(OR(J92="",F92=""),"",IF(F92<=0,"",IFERROR(J92/F92-1,""))) | K94: =IF(OR(K92="",G92=""),"",IF(G92<=0,"",IFERROR(K92/G92-1,""))) | L94: =IF(OR(L92="",H92=""),"",IF(H92<=0,"",IFERROR(L92/H92-1,""))) | M94: =IF(OR(M92="",I92=""),"",IF(I92<=0,"",IFERROR(M92/I92-1,""))) | N94: =IF(OR(N92="",J92=""),"",IF(J92<=0,"",IFERROR(N92/J92-1,""))) | U94: =IF(OR(U92="",T92=""),"",IF(T92<=0,"",IFERROR(U92/T92-1,""))) | V94: =IF(OR(V92="",U92=""),"",IF(U92<=0,"",IFERROR(V92/U92-1,""))) | W94: =IF(OR(W92="",V92=""),"",IF(V92<=0,"",IFERROR(W92/V92-1,""))) | X94: =IF(OR(X92="",W92=""),"",IF(W92<=0,"",IFERROR(X92/W92-1,"")))
A95: 이자수익 | C95: 0.196 | D95: 0.204 | E95: 0.203 | F95: 0.875 | G95: 0.068 | H95: 1.837 | I95: 0.07 | J95: 4.847 | K95: 1.624 | L95: 7.982 | M95: 4.236 | N95: 6.897 | U95: 0.258 | V95: 0.196 | W95: 0.068 | X95: 1.624
A96: 보험금 수익 | D96: 0.186 | H96: 0
A97: 배당금수익 | C97: 0 | G97: 0 | K97: 0 | U97: 0 | V97: 0 | W97: 0 | X97: 0
A98: 환급 가산금 | C98: 0 | F98: 0 | G98: 0 | J98: 0 | K98: 0 | U98: 0 | V98: 0 | W98: 0 | X98: 0
A99: 지분법이익 | C99: 0 | D99: 0 | E99: 0 | H99: 4.339 | I99: 0.168 | J99: -4.507 | K99: 0 | L99: 2.875 | M99: 1.49 | N99: -1.894 | U99: 45.053 | V99: 0 | X99: 0
A100: 보조금 수입 | C100: 0 | F100: 0 | G100: 0 | J100: 0 | K100: 0 | N100: 0 | U100: 0 | V100: 0 | W100: 0 | X100: 0
A101: 고정자산 매각이익 | C101: 0 | F101: 0 | G101: 0 | J101: 0 | K101: 0 | V101: 0 | W101: 0 | X101: 0
A102: 대손충당금 환입이익 | H102: 0 | L102: 1.5
...

Sheet 재무상태표
A1: 필컴퍼니 재무상태표
A2: 재무비율은 기말 잔액 기준 · 분기 손익은 최근 4분기 합산(TTM) | B2: (단위: 백만엔)
A3: 항목 | B3: 참고 | C3: 2025.3Q | D3: 2025.4Q | E3: 2026.1Q | F3: 2026.2Q | G3: 2026.3Q | H3: 2021 | I3: 2022 | J3: 2023 | K3: 2024 | L3: 2025
A4: 자산
A5: 유동자산 | C5: 7352.005 | D5: 8728.144 | E5: 7499.756 | F5: 7990.829 | G5: 7798.13 | H5: 4575.914 | I5: 3886.695 | J5: 4433.676 | K5: 6616.406 | L5: 8728.144
A6: 현금및현금성자산 | C6: 3970.53 | D6: 5044.657 | E6: 3529.309 | F6: 2989.969 | G6: 3393.185 | H6: 4193.33 | I6: 2250.657 | J6: 2456.383 | K6: 4822.267 | L6: 5044.657
A7: 단기금융상품 | C7: 398.97 | D7: 399.276 | E7: 500.293 | F7: 400.206 | G7: 500.008 | K7: 0 | L7: 399.276
A8: 매출채권 | C8: 283.911 | D8: 132.036 | E8: 146.647 | F8: 243.89 | G8: 115.483 | H8: 5.127 | I8: 43.826 | J8: 65.461 | K8: 211.149 | L8: 132.036
A9: 재고자산 | C9: 71.357 | D9: 802.073 | E9: 414.21 | F9: 482.064 | G9: 1265.245 | H9: 168.903 | I9: 616.347 | J9: 836.026 | K9: 246.578 | L9: 802.073
A10: 기타유동자산 | B10: 총계 − 위 항목 | C10: =IF(OR(C5=""),"",IFERROR(C5-SUM(C6,C7,C8,C9),"")) | D10: =IF(OR(D5=""),"",IFERROR(D5-SUM(D6,D7,D8,D9),"")) | E10: =IF(OR(E5=""),"",IFERROR(E5-SUM(E6,E7,E8,E9),"")) | F10: =IF(OR(F5=""),"",IFERROR(F5-SUM(F6,F7,F8,F9),"")) | G10: =IF(OR(G5=""),"",IFERROR(G5-SUM(G6,G7,G8,G9),"")) | H10: =IF(OR(H5=""),"",IFERROR(H5-SUM(H6,H7,H8,H9),"")) | I10: =IF(OR(I5=""),"",IFERROR(I5-SUM(I6,I7,I8,I9),"")) | J10: =IF(OR(J5=""),"",IFERROR(J5-SUM(J6,J7,J8,J9),"")) | ... L10: =IF(OR(L5=""),"",IFERROR(L5-SUM(L6,L7,L8,L9),""))
A11: 비유동자산 | C11: 1108.247 | D11: 1211.99 | E11: 1196.803 | F11: 1110.499 | G11: 959.13 | H11: 874.397 | I11: 863.352 | J11: 1017.098 | K11: 879.933 | L11: 1211.99
A12: 유형자산 | C12: 477.24 | D12: 477.785 | E12: 471.492 | F12: 468.801 | G12: 581.622 | H12: 329.756 | I12: 301.477 | J12: 504.647 | K12: 482.18 | L12: 477.785
A13: 무형자산 | C13: 81.589 | D13: 73.17 | E13: 65.707 | F13: 57.248 | G13: 48.788 | H13: 168.771 | I13: 144.384 | J13: 141.881 | K13: 106.847 | L13: 73.17
A14: 투자부동산
A15: 기타비유동자산 | B15: 총계 − 위 항목 | C15: =IF(OR(C11=""),"",IFERROR(C11-SUM(C12,C13,C14),"")) | D15: =IF(OR(D11=""),"",IFERROR(D11-SUM(D12,D13,D14),"")) | E15: =IF(OR(E11=""),"",IFERROR(E11-SUM(E12,E13,E14),"")) | F15: =IF(OR(F11=""),"",IFERROR(F11-SUM(F12,F13,F14),"")) | G15: =IF(OR(G11=""),"",IFERROR(G11-SUM(G12,G13,G14),"")) | H15: =IF(OR(H11=""),"",IFERROR(H11-SUM(H12,H13,H14),"")) | I15: =IF(OR(I11=""),"",IFERROR(I11-SUM(I12,I13,I14),"")) | J15: =IF(OR(J11=""),"",IFERROR(J11-SUM(J12,J13,J14),"")) | ... L15: =IF(OR(L11=""),"",IFERROR(L11-SUM(L12,L13,L14),""))
A16: 자산총계 | C16: 8460.252 | D16: 9940.134 | E16: 8696.56 | F16: 9101.328 | G16: 8757.26 | H16: 5450.312 | I16: 4750.048 | J16: 5450.775 | K16: 7496.339 | L16: 9940.134
A17: 부채
A18: 유동부채 | C18: 4408.618 | D18: 4794.001 | E18: 3318.047 | F18: 3922.868 | G18: 3710.393 | H18: 2128.446 | I18: 1528.719 | J18: 1621.062 | K18: 3267.672 | L18: 4794.001
A19: 매입채무 | C19: 587.268 | D19: 733.454 | E19: 479.54 | F19: 429.078 | G19: 526.376 | H19: 168.205 | I19: 458.167 | J19: 389.72 | K19: 870.523 | L19: 733.454
A20: 단기차입금 | C20: 934.858 | D20: 920 | E20: 810 | F20: 810 | G20: 474.25 | H20: 0 | I20: 0 | J20: 437.5 | K20: 424.08 | L20: 920
A21: 유동성장기부채 | C21: 867.533 | D21: 696.081 | E21: 436.081 | F21: 1384.081 | G21: 1055.063 | H21: 37.28 | I21: 70.236 | J21: 83.092 | K21: 230.984 | L21: 696.081
A22: 기타유동부채 | B22: 총계 − 위 항목 | C22: =IF(OR(C18=""),"",IFERROR(C18-SUM(C19,C20,C21),"")) | D22: =IF(OR(D18=""),"",IFERROR(D18-SUM(D19,D20,D21),"")) | E22: =IF(OR(E18=""),"",IFERROR(E18-SUM(E19,E20,E21),"")) | F22: =IF(OR(F18=""),"",IFERROR(F18-SUM(F19,F20,F21),"")) | G22: =IF(OR(G18=""),"",IFERROR(G18-SUM(G19,G20,G21),"")) | H22: =IF(OR(H18=""),"",IFERROR(H18-SUM(H19,H20,H21),"")) | I22: =IF(OR(I18=""),"",IFERROR(I18-SUM(I19,I20,I21),"")) | J22: =IF(OR(J18=""),"",IFERROR(J18-SUM(J19,J20,J21),"")) | ... L22: =IF(OR(L18=""),"",IFERROR(L18-SUM(L19,L20,L21),""))
A23: 비유동부채 | C23: 954.548 | D23: 1801.621 | E23: 2124.642 | F23: 1862.854 | G23: 1481.482 | H23: 547.75 | I23: 777.593 | J23: 1099.247 | K23: 1247.623 | L23: 1801.621
A24: 장기차입금 | C24: 529.563 | D24: 1342.968 | E24: 1663.702 | F24: 1505.436 | G24: 1114.5 | H24: 202.792 | I24: 439.22 | J24: 683.986 | K24: 826.13 | L24: 1342.968
A25: 사채
A26: 기타비유동부채 | B26: 총계 − 위 항목 | C26: =IF(OR(C23=""),"",IFERROR(C23-SUM(C24,C25),"")) | D26: =IF(OR(D23=""),"",IFERROR(D23-SUM(D24,D25),"")) | E26: =IF(OR(E23=""),"",IFERROR(E23-SUM(E24,E25),"")) | F26: =IF(OR(F23=""),"",IFERROR(F23-SUM(F24,F25),"")) | G26: =IF(OR(G23=""),"",IFERROR(G23-SUM(G24,G25),"")) | H26: =IF(OR(H23=""),"",IFERROR(H23-SUM(H24,H25),"")) | I26: =IF(OR(I23=""),"",IFERROR(I23-SUM(I24,I25),"")) | J26: =IF(OR(J23=""),"",IFERROR(J23-SUM(J24,J25),"")) | ... L26: =IF(OR(L23=""),"",IFERROR(L23-SUM(L24,L25),""))
A27: 부채총계 | C27: 5363.166 | D27: 6595.622 | E27: 5442.689 | F27: 5785.722 | G27: 5191.876 | H27: 2676.197 | I27: 2306.313 | J27: 2720.309 | K27: 4515.296 | L27: 6595.622
A28: 총차입금 | B28: 단기+유동성장기+장기+사채 | C28: =SUM(C20,C21,C24,C25) | D28: =SUM(D20,D21,D24,D25) | E28: =SUM(E20,E21,E24,E25) | F28: =SUM(F20,F21,F24,F25) | G28: =SUM(G20,G21,G24,G25) | H28: =SUM(H20,H21,H24,H25) | I28: =SUM(I20,I21,I24,I25) | J28: =SUM(J20,J21,J24,J25) | ... L28: =SUM(L20,L21,L24,L25)
A29: 순차입금 | B29: 음수 = 순현금 | C29: =C28-C6-N(C7) | D29: =D28-D6-N(D7) | E29: =E28-E6-N(E7) | F29: =F28-F6-N(F7) | G29: =G28-G6-N(G7) | H29: =H28-H6-N(H7) | I29: =I28-I6-N(I7) | J29: =J28-J6-N(J7) | ... L29: =L28-L6-N(L7)
A30: 자본
A31: 지배주주지분 | C31: 3062.181 | D31: 3305.325 | E31: 3208.575 | F31: 3264.202 | G31: 3511.362 | H31: 2770.989 | I31: 2438.869 | J31: 2726.491 | K31: 2961.303 | L31: 3305.325
A32: 자본금 | C32: 789.647 | D32: 789.647 | E32: 789.647 | F32: 789.647 | G32: 789.647 | H32: 789.647 | I32: 789.647 | J32: 789.647 | K32: 789.647 | L32: 789.647
A33: 이익잉여금 | C33: 2183.866 | D33: 2427.011 | E33: 2330.262 | F33: 2299.353 | G33: 2546.513 | H33: 1801.442 | I33: 1936.076 | J33: 1848.148 | K33: 2082.987 | L33: 2427.011
A34: 비지배지분 | H34: 0.977 | I34: 0.892 | J34: 0
A35: 자본총계 | C35: 3097.085 | D35: 3344.511 | E35: 3253.87 | F35: 3315.606 | G35: 3565.384 | H35: 2774.114 | I35: 2443.735 | J35: 2730.465 | K35: 2981.043 | L35: 3344.511
A36: 현금흐름 요약 | B36: 분기 = TTM (있을 때만)
A37: 영업활동현금흐름 | D37: -442.819 | F37: -2537.163 | H37: 3291.115 | I37: -1663.383 | J37: -541.35 | K37: 2076.091 | L37: -442.819
A38: CAPEX (유·무형 취득) | B38: 양수로 입력 | D38: 39.728 | F38: 123.148 | H38: 8.336 | I38: 7.203 | J38: 131.961 | K38: 17.683 | L38: 39.728
A39: FCF | C39: =IF(OR(C37="",C38=""),"",IFERROR(C37-C38,"")) | D39: =IF(OR(D37="",D38=""),"",IFERROR(D37-D38,"")) | E39: =IF(OR(E37="",E38=""),"",IFERROR(E37-E38,"")) | F39: =IF(OR(F37="",F38=""),"",IFERROR(F37-F38,"")) | G39: =IF(OR(G37="",G38=""),"",IFERROR(G37-G38,"")) | H39: =IF(OR(H37="",H38=""),"",IFERROR(H37-H38,"")) | I39: =IF(OR(I37="",I38=""),"",IFERROR(I37-I38,"")) | J39: =IF(OR(J37="",J38=""),"",IFERROR(J37-J38,"")) | ... L39: =IF(OR(L37="",L38=""),"",IFERROR(L37-L38,""))
A40: 배당금 지급 | B40: 양수로 입력 | D40: 53.9 | F40: 107.626 | H40: 0.055 | I40: 56.284 | J40: 0.023 | K40: 26.94 | L40: 53.9
A41: 주요 재무 비율 | B41: 기준 (빨간 글씨 = 미달)
A42: 안정성
A43: 부채비율 | B43: 100%↓ | C43: =IF(OR(C27="",C35=""),"",IFERROR(C27/C35,"")) | D43: =IF(OR(D27="",D35=""),"",IFERROR(D27/D35,"")) | E43: =IF(OR(E27="",E35=""),"",IFERROR(E27/E35,"")) | F43: =IF(OR(F27="",F35=""),"",IFERROR(F27/F35,"")) | G43: =IF(OR(G27="",G35=""),"",IFERROR(G27/G35,"")) | H43: =IF(OR(H27="",H35=""),"",IFERROR(H27/H35,"")) | I43: =IF(OR(I27="",I35=""),"",IFERROR(I27/I35,"")) | J43: =IF(OR(J27="",J35=""),"",IFERROR(J27/J35,"")) | ... L43: =IF(OR(L27="",L35=""),"",IFERROR(L27/L35,""))
A44: 순차입금비율 | B44: 0%↓ 순현금 | C44: =IF(OR(C29="",C35=""),"",IFERROR(C29/C35,"")) | D44: =IF(OR(D29="",D35=""),"",IFERROR(D29/D35,"")) | E44: =IF(OR(E29="",E35=""),"",IFERROR(E29/E35,"")) | F44: =IF(OR(F29="",F35=""),"",IFERROR(F29/F35,"")) | G44: =IF(OR(G29="",G35=""),"",IFERROR(G29/G35,"")) | H44: =IF(OR(H29="",H35=""),"",IFERROR(H29/H35,"")) | I44: =IF(OR(I29="",I35=""),"",IFERROR(I29/I35,"")) | J44: =IF(OR(J29="",J35=""),"",IFERROR(J29/J35,"")) | ... L44: =IF(OR(L29="",L35=""),"",IFERROR(L29/L35,""))
A45: 자기자본비율 | B45: 50%↑ | C45: =IF(OR(C35="",C16=""),"",IFERROR(C35/C16,"")) | D45: =IF(OR(D35="",D16=""),"",IFERROR(D35/D16,"")) | E45: =IF(OR(E35="",E16=""),"",IFERROR(E35/E16,"")) | F45: =IF(OR(F35="",F16=""),"",IFERROR(F35/F16,"")) | G45: =IF(OR(G35="",G16=""),"",IFERROR(G35/G16,"")) | H45: =IF(OR(H35="",H16=""),"",IFERROR(H35/H16,"")) | I45: =IF(OR(I35="",I16=""),"",IFERROR(I35/I16,"")) | J45: =IF(OR(J35="",J16=""),"",IFERROR(J35/J16,"")) | ... L45: =IF(OR(L35="",L16=""),"",IFERROR(L35/L16,""))
A46: 유동비율 | B46: 150%↑ | C46: =IF(OR(C5="",C18=""),"",IFERROR(C5/C18,"")) | D46: =IF(OR(D5="",D18=""),"",IFERROR(D5/D18,"")) | E46: =IF(OR(E5="",E18=""),"",IFERROR(E5/E18,"")) | F46: =IF(OR(F5="",F18=""),"",IFERROR(F5/F18,"")) | G46: =IF(OR(G5="",G18=""),"",IFERROR(G5/G18,"")) | H46: =IF(OR(H5="",H18=""),"",IFERROR(H5/H18,"")) | I46: =IF(OR(I5="",I18=""),"",IFERROR(I5/I18,"")) | J46: =IF(OR(J5="",J18=""),"",IFERROR(J5/J18,"")) | ... L46: =IF(OR(L5="",L18=""),"",IFERROR(L5/L18,""))
A47: 당좌비율 | B47: 100%↑ | C47: =IF(OR(C5="",C18=""),"",IFERROR((C5-N(C9))/C18,"")) | D47: =IF(OR(D5="",D18=""),"",IFERROR((D5-N(D9))/D18,"")) | E47: =IF(OR(E5="",E18=""),"",IFERROR((E5-N(E9))/E18,"")) | F47: =IF(OR(F5="",F18=""),"",IFERROR((F5-N(F9))/F18,"")) | G47: =IF(OR(G5="",G18=""),"",IFERROR((G5-N(G9))/G18,"")) | H47: =IF(OR(H5="",H18=""),"",IFERROR((H5-N(H9))/H18,"")) | I47: =IF(OR(I5="",I18=""),"",IFERROR((I5-N(I9))/I18,"")) | J47: =IF(OR(J5="",J18=""),"",IFERROR((J5-N(J9))/J18,"")) | ... L47: =IF(OR(L5="",L18=""),"",IFERROR((L5-N(L9))/L18,""))
A48: 이자보상배율 | B48: 5x↑ (금융원가 기준) | C48: =IFERROR((IF(COUNT('연간'!G19:J19)<4,"",SUM('연간'!G19:J19)))/(IF(COUNT('연간'!G41:J41)<4,"",SUM('연간'!G41:J41))),"") | D48: =IFERROR((IF(COUNT('연간'!H19:K19)<4,"",SUM('연간'!H19:K19)))/(IF(COUNT('연간'!H41:K41)<4,"",SUM('연간'!H41:K41))),"") | E48: =IFERROR((IF(COUNT('연간'!I19:L19)<4,"",SUM('연간'!I19:L19)))/(IF(COUNT('연간'!I41:L41)<4,"",SUM('연간'!I41:L41))),"") | F48: =IFERROR((IF(COUNT('연간'!J19:M19)<4,"",SUM('연간'!J19:M19)))/(IF(COUNT('연간'!J41:M41)<4,"",SUM('연간'!J41:M41))),"") | G48: =IFERROR((IF(COUNT('연간'!K19:N19)<4,"",SUM('연간'!K19:N19)))/(IF(COUNT('연간'!K41:N41)<4,"",SUM('연간'!K41:N41))),"") | H48: =IFERROR(('연간'!T19)/('연간'!T41),"") | I48: =IFERROR(('연간'!U19)/('연간'!U41),"") | J48: =IFERROR(('연간'!V19)/('연간'!V41),"") | K48: =IFERROR(('연간'!W19)/('연간'!W41),"") | L48: =IFERROR(('연간'!X19)/('연간'!X41),"")
A49: 차입금 상환연수 | B49: 4년↓ (버핏) | C49: =IFERROR(IF((IF(COUNT('연간'!G49:J49)<4,"",SUM('연간'!G49:J49)))<=0,"적자",C28/(IF(COUNT('연간'!G49:J49)<4,"",SUM('연간'!G49:J49)))),"") | D49: =IFERROR(IF((IF(COUNT('연간'!H49:K49)<4,"",SUM('연간'!H49:K49)))<=0,"적자",D28/(IF(COUNT('연간'!H49:K49)<4,"",SUM('연간'!H49:K49)))),"") | E49: =IFERROR(IF((IF(COUNT('연간'!I49:L49)<4,"",SUM('연간'!I49:L49)))<=0,"적자",E28/(IF(COUNT('연간'!I49:L49)<4,"",SUM('연간'!I49:L49)))),"") | F49: =IFERROR(IF((IF(COUNT('연간'!J49:M49)<4,"",SUM('연간'!J49:M49)))<=0,"적자",F28/(IF(COUNT('연간'!J49:M49)<4,"",SUM('연간'!J49:M49)))),"") | G49: =IFERROR(IF((IF(COUNT('연간'!K49:N49)<4,"",SUM('연간'!K49:N49)))<=0,"적자",G28/(IF(COUNT('연간'!K49:N49)<4,"",SUM('연간'!K49:N49)))),"") | H49: =IFERROR(IF(('연간'!T49)<=0,"적자",H28/('연간'!T49)),"") | I49: =IFERROR(IF(('연간'!U49)<=0,"적자",I28/('연간'!U49)),"") | J49: =IFERROR(IF(('연간'!V49)<=0,"적자",J28/('연간'!V49)),"") | K49: =IFERROR(IF(('연간'!W49)<=0,"적자",K28/('연간'!W49)),"") | L49: =IFERROR(IF(('연간'!X49)<=0,"적자",L28/('연간'!X49)),"")
A50: 수익성
A51: ROE | B51: 15%↑ (버핏) | C51: =IFERROR((IF(COUNT('연간'!G49:J49)<4,"",SUM('연간'!G49:J49)))/C31,"") | D51: =IFERROR((IF(COUNT('연간'!H49:K49)<4,"",SUM('연간'!H49:K49)))/D31,"") | E51: =IFERROR((IF(COUNT('연간'!I49:L49)<4,"",SUM('연간'!I49:L49)))/E31,"") | F51: =IFERROR((IF(COUNT('연간'!J49:M49)<4,"",SUM('연간'!J49:M49)))/F31,"") | G51: =IFERROR((IF(COUNT('연간'!K49:N49)<4,"",SUM('연간'!K49:N49)))/G31,"") | H51: =IFERROR(('연간'!T49)/H31,"") | I51: =IFERROR(('연간'!U49)/I31,"") | J51: =IFERROR(('연간'!V49)/J31,"") | K51: =IFERROR(('연간'!W49)/K31,"") | L51: =IFERROR(('연간'!X49)/L31,"")
A52: ROA | B52: 5%↑ | C52: =IFERROR((IF(COUNT('연간'!G47:J47)<4,"",SUM('연간'!G47:J47)))/C16,"") | D52: =IFERROR((IF(COUNT('연간'!H47:K47)<4,"",SUM('연간'!H47:K47)))/D16,"") | E52: =IFERROR((IF(COUNT('연간'!I47:L47)<4,"",SUM('연간'!I47:L47)))/E16,"") | F52: =IFERROR((IF(COUNT('연간'!J47:M47)<4,"",SUM('연간'!J47:M47)))/F16,"") | G52: =IFERROR((IF(COUNT('연간'!K47:N47)<4,"",SUM('연간'!K47:N47)))/G16,"") | H52: =IFERROR(('연간'!T47)/H16,"") | I52: =IFERROR(('연간'!U47)/I16,"") | J52: =IFERROR(('연간'!V47)/J16,"") | K52: =IFERROR(('연간'!W47)/K16,"") | L52: =IFERROR(('연간'!X47)/L16,"")
A53: ROIC | B53: 10%↑ (세후영업이익 기준) | C53: =IFERROR((IF(COUNT('연간'!G19:J19)<4,"",SUM('연간'!G19:J19)))*(1-0.3)/(C35+C29),"") | D53: =IFERROR((IF(COUNT('연간'!H19:K19)<4,"",SUM('연간'!H19:K19)))*(1-0.3)/(D35+D29),"") | E53: =IFERROR((IF(COUNT('연간'!I19:L19)<4,"",SUM('연간'!I19:L19)))*(1-0.3)/(E35+E29),"") | F53: =IFERROR((IF(COUNT('연간'!J19:M19)<4,"",SUM('연간'!J19:M19)))*(1-0.3)/(F35+F29),"") | G53: =IFERROR((IF(COUNT('연간'!K19:N19)<4,"",SUM('연간'!K19:N19)))*(1-0.3)/(G35+G29),"") | H53: =IFERROR(('연간'!T19)*(1-0.3)/(H35+H29),"") | I53: =IFERROR(('연간'!U19)*(1-0.3)/(I35+I29),"") | J53: =IFERROR(('연간'!V19)*(1-0.3)/(J35+J29),"") | K53: =IFERROR(('연간'!W19)*(1-0.3)/(K35+K29),"") | L53: =IFERROR(('연간'!X19)*(1-0.3)/(L35+L29),"")
A54: 매출총이익률 (GPM) | B54: 40%↑ (해자 신호) | C54: =IFERROR((IF(COUNT('연간'!G13:J13)<4,"",SUM('연간'!G13:J13)))/(IF(COUNT('연간'!G4:J4)<4,"",SUM('연간'!G4:J4))),"") | D54: =IFERROR((IF(COUNT('연간'!H13:K13)<4,"",SUM('연간'!H13:K13)))/(IF(COUNT('연간'!H4:K4)<4,"",SUM('연간'!H4:K4))),"") | E54: =IFERROR((IF(COUNT('연간'!I13:L13)<4,"",SUM('연간'!I13:L13)))/(IF(COUNT('연간'!I4:L4)<4,"",SUM('연간'!I4:L4))),"") | F54: =IFERROR((IF(COUNT('연간'!J13:M13)<4,"",SUM('연간'!J13:M13)))/(IF(COUNT('연간'!J4:M4)<4,"",SUM('연간'!J4:M4))),"") | G54: =IFERROR((IF(COUNT('연간'!K13:N13)<4,"",SUM('연간'!K13:N13)))/(IF(COUNT('연간'!K4:N4)<4,"",SUM('연간'!K4:N4))),"") | H54: =IFERROR(('연간'!T13)/('연간'!T4),"") | I54: =IFERROR(('연간'!U13)/('연간'!U4),"") | J54: =IFERROR(('연간'!V13)/('연간'!V4),"") | K54: =IFERROR(('연간'!W13)/('연간'!W4),"") | L54: =IFERROR(('연간'!X13)/('연간'!X4),"")
A55: 영업이익률 (OPM) | B55: 15%↑ | C55: =IFERROR((IF(COUNT('연간'!G19:J19)<4,"",SUM('연간'!G19:J19)))/(IF(COUNT('연간'!G4:J4)<4,"",SUM('연간'!G4:J4))),"") | D55: =IFERROR((IF(COUNT('연간'!H19:K19)<4,"",SUM('연간'!H19:K19)))/(IF(COUNT('연간'!H4:K4)<4,"",SUM('연간'!H4:K4))),"") | E55: =IFERROR((IF(COUNT('연간'!I19:L19)<4,"",SUM('연간'!I19:L19)))/(IF(COUNT('연간'!I4:L4)<4,"",SUM('연간'!I4:L4))),"") | F55: =IFERROR((IF(COUNT('연간'!J19:M19)<4,"",SUM('연간'!J19:M19)))/(IF(COUNT('연간'!J4:M4)<4,"",SUM('연간'!J4:M4))),"") | G55: =IFERROR((IF(COUNT('연간'!K19:N19)<4,"",SUM('연간'!K19:N19)))/(IF(COUNT('연간'!K4:N4)<4,"",SUM('연간'!K4:N4))),"") | H55: =IFERROR(('연간'!T19)/('연간'!T4),"") | I55: =IFERROR(('연간'!U19)/('연간'!U4),"") | J55: =IFERROR(('연간'!V19)/('연간'!V4),"") | K55: =IFERROR(('연간'!W19)/('연간'!W4),"") | L55: =IFERROR(('연간'!X19)/('연간'!X4),"")
A56: 순이익률 | B56: 10%↑ | C56: =IFERROR((IF(COUNT('연간'!G47:J47)<4,"",SUM('연간'!G47:J47)))/(IF(COUNT('연간'!G4:J4)<4,"",SUM('연간'!G4:J4))),"") | D56: =IFERROR((IF(COUNT('연간'!H47:K47)<4,"",SUM('연간'!H47:K47)))/(IF(COUNT('연간'!H4:K4)<4,"",SUM('연간'!H4:K4))),"") | E56: =IFERROR((IF(COUNT('연간'!I47:L47)<4,"",SUM('연간'!I47:L47)))/(IF(COUNT('연간'!I4:L4)<4,"",SUM('연간'!I4:L4))),"") | F56: =IFERROR((IF(COUNT('연간'!J47:M47)<4,"",SUM('연간'!J47:M47)))/(IF(COUNT('연간'!J4:M4)<4,"",SUM('연간'!J4:M4))),"") | G56: =IFERROR((IF(COUNT('연간'!K47:N47)<4,"",SUM('연간'!K47:N47)))/(IF(COUNT('연간'!K4:N4)<4,"",SUM('연간'!K4:N4))),"") | H56: =IFERROR(('연간'!T47)/('연간'!T4),"") | I56: =IFERROR(('연간'!U47)/('연간'!U4),"") | J56: =IFERROR(('연간'!V47)/('연간'!V4),"") | K56: =IFERROR(('연간'!W47)/('연간'!W4),"") | L56: =IFERROR(('연간'!X47)/('연간'!X4),"")
A57: 효율성 (회전율)
A58: 총자산회전율 | B58: 높을수록↑ | C58: =IFERROR((IF(COUNT('연간'!G4:J4)<4,"",SUM('연간'!G4:J4)))/C16,"") | D58: =IFERROR((IF(COUNT('연간'!H4:K4)<4,"",SUM('연간'!H4:K4)))/D16,"") | E58: =IFERROR((IF(COUNT('연간'!I4:L4)<4,"",SUM('연간'!I4:L4)))/E16,"") | F58: =IFERROR((IF(COUNT('연간'!J4:M4)<4,"",SUM('연간'!J4:M4)))/F16,"") | G58: =IFERROR((IF(COUNT('연간'!K4:N4)<4,"",SUM('연간'!K4:N4)))/G16,"") | H58: =IFERROR(('연간'!T4)/H16,"") | I58: =IFERROR(('연간'!U4)/I16,"") | J58: =IFERROR(('연간'!V4)/J16,"") | K58: =IFERROR(('연간'!W4)/K16,"") | L58: =IFERROR(('연간'!X4)/L16,"")
A59: 매출채권회전일수 | B59: 짧을수록↑ | C59: =IFERROR(C8/(IF(COUNT('연간'!G4:J4)<4,"",SUM('연간'!G4:J4)))*365,"") | D59: =IFERROR(D8/(IF(COUNT('연간'!H4:K4)<4,"",SUM('연간'!H4:K4)))*365,"") | E59: =IFERROR(E8/(IF(COUNT('연간'!I4:L4)<4,"",SUM('연간'!I4:L4)))*365,"") | F59: =IFERROR(F8/(IF(COUNT('연간'!J4:M4)<4,"",SUM('연간'!J4:M4)))*365,"") | G59: =IFERROR(G8/(IF(COUNT('연간'!K4:N4)<4,"",SUM('연간'!K4:N4)))*365,"") | H59: =IFERROR(H8/('연간'!T4)*365,"") | I59: =IFERROR(I8/('연간'!U4)*365,"") | J59: =IFERROR(J8/('연간'!V4)*365,"") | K59: =IFERROR(K8/('연간'!W4)*365,"") | L59: =IFERROR(L8/('연간'!X4)*365,"")
A60: 재고자산회전일수 | B60: 짧을수록↑ | C60: =IFERROR(C9/(IF(COUNT('연간'!G11:J11)<4,"",SUM('연간'!G11:J11)))*365,"") | D60: =IFERROR(D9/(IF(COUNT('연간'!H11:K11)<4,"",SUM('연간'!H11:K11)))*365,"") | E60: =IFERROR(E9/(IF(COUNT('연간'!I11:L11)<4,"",SUM('연간'!I11:L11)))*365,"") | F60: =IFERROR(F9/(IF(COUNT('연간'!J11:M11)<4,"",SUM('연간'!J11:M11)))*365,"") | G60: =IFERROR(G9/(IF(COUNT('연간'!K11:N11)<4,"",SUM('연간'!K11:N11)))*365,"") | H60: =IFERROR(H9/('연간'!T11)*365,"") | I60: =IFERROR(I9/('연간'!U11)*365,"") | J60: =IFERROR(J9/('연간'!V11)*365,"") | K60: =IFERROR(K9/('연간'!W11)*365,"") | L60: =IFERROR(L9/('연간'!X11)*365,"")
A61: 매입채무회전일수 | B61: 길수록 유리 | C61: =IFERROR(C19/(IF(COUNT('연간'!G11:J11)<4,"",SUM('연간'!G11:J11)))*365,"") | D61: =IFERROR(D19/(IF(COUNT('연간'!H11:K11)<4,"",SUM('연간'!H11:K11)))*365,"") | E61: =IFERROR(E19/(IF(COUNT('연간'!I11:L11)<4,"",SUM('연간'!I11:L11)))*365,"") | F61: =IFERROR(F19/(IF(COUNT('연간'!J11:M11)<4,"",SUM('연간'!J11:M11)))*365,"") | G61: =IFERROR(G19/(IF(COUNT('연간'!K11:N11)<4,"",SUM('연간'!K11:N11)))*365,"") | H61: =IFERROR(H19/('연간'!T11)*365,"") | I61: =IFERROR(I19/('연간'!U11)*365,"") | J61: =IFERROR(J19/('연간'!V11)*365,"") | K61: =IFERROR(K19/('연간'!W11)*365,"") | L61: =IFERROR(L19/('연간'!X11)*365,"")
A62: 현금전환주기 (CCC) | B62: 짧을수록↑ | C62: =IF(OR(C59="",C60="",C61=""),"",IFERROR(C59+C60-C61,"")) | D62: =IF(OR(D59="",D60="",D61=""),"",IFERROR(D59+D60-D61,"")) | E62: =IF(OR(E59="",E60="",E61=""),"",IFERROR(E59+E60-E61,"")) | F62: =IF(OR(F59="",F60="",F61=""),"",IFERROR(F59+F60-F61,"")) | G62: =IF(OR(G59="",G60="",G61=""),"",IFERROR(G59+G60-G61,"")) | H62: =IF(OR(H59="",H60="",H61=""),"",IFERROR(H59+H60-H61,"")) | I62: =IF(OR(I59="",I60="",I61=""),"",IFERROR(I59+I60-I61,"")) | J62: =IF(OR(J59="",J60="",J61=""),"",IFERROR(J59+J60-J61,"")) | ... L62: =IF(OR(L59="",L60="",L61=""),"",IFERROR(L59+L60-L61,""))
A63: 현금흐름
A64: 영업현금흐름 / 순이익 | B64: 1x↑ (이익의 질) | C64: =IF(C37="","",IFERROR(C37/(IF(COUNT('연간'!G47:J47)<4,"",SUM('연간'!G47:J47))),"")) | D64: =IF(D37="","",IFERROR(D37/(IF(COUNT('연간'!H47:K47)<4,"",SUM('연간'!H47:K47))),"")) | E64: =IF(E37="","",IFERROR(E37/(IF(COUNT('연간'!I47:L47)<4,"",SUM('연간'!I47:L47))),"")) | F64: =IF(F37="","",IFERROR(F37/(IF(COUNT('연간'!J47:M47)<4,"",SUM('연간'!J47:M47))),"")) | G64: =IF(G37="","",IFERROR(G37/(IF(COUNT('연간'!K47:N47)<4,"",SUM('연간'!K47:N47))),"")) | H64: =IF(H37="","",IFERROR(H37/('연간'!T47),"")) | I64: =IF(I37="","",IFERROR(I37/('연간'!U47),"")) | J64: =IF(J37="","",IFERROR(J37/('연간'!V47),"")) | K64: =IF(K37="","",IFERROR(K37/('연간'!W47),"")) | L64: =IF(L37="","",IFERROR(L37/('연간'!X47),""))
A65: FCF 마진 | B65: 5%↑ | C65: =IF(C39="","",IFERROR(C39/(IF(COUNT('연간'!G4:J4)<4,"",SUM('연간'!G4:J4))),"")) | D65: =IF(D39="","",IFERROR(D39/(IF(COUNT('연간'!H4:K4)<4,"",SUM('연간'!H4:K4))),"")) | E65: =IF(E39="","",IFERROR(E39/(IF(COUNT('연간'!I4:L4)<4,"",SUM('연간'!I4:L4))),"")) | F65: =IF(F39="","",IFERROR(F39/(IF(COUNT('연간'!J4:M4)<4,"",SUM('연간'!J4:M4))),"")) | G65: =IF(G39="","",IFERROR(G39/(IF(COUNT('연간'!K4:N4)<4,"",SUM('연간'!K4:N4))),"")) | H65: =IF(H39="","",IFERROR(H39/('연간'!T4),"")) | I65: =IF(I39="","",IFERROR(I39/('연간'!U4),"")) | J65: =IF(J39="","",IFERROR(J39/('연간'!V4),"")) | K65: =IF(K39="","",IFERROR(K39/('연간'!W4),"")) | L65: =IF(L39="","",IFERROR(L39/('연간'!X4),""))
A66: CAPEX / 매출 | B66: 낮을수록↑ (자본 가벼움) | C66: =IF(C38="","",IFERROR(C38/(IF(COUNT('연간'!G4:J4)<4,"",SUM('연간'!G4:J4))),"")) | D66: =IF(D38="","",IFERROR(D38/(IF(COUNT('연간'!H4:K4)<4,"",SUM('연간'!H4:K4))),"")) | E66: =IF(E38="","",IFERROR(E38/(IF(COUNT('연간'!I4:L4)<4,"",SUM('연간'!I4:L4))),"")) | F66: =IF(F38="","",IFERROR(F38/(IF(COUNT('연간'!J4:M4)<4,"",SUM('연간'!J4:M4))),"")) | G66: =IF(G38="","",IFERROR(G38/(IF(COUNT('연간'!K4:N4)<4,"",SUM('연간'!K4:N4))),"")) | H66: =IF(H38="","",IFERROR(H38/('연간'!T4),"")) | I66: =IF(I38="","",IFERROR(I38/('연간'!U4),"")) | J66: =IF(J38="","",IFERROR(J38/('연간'!V4),"")) | K66: =IF(K38="","",IFERROR(K38/('연간'!W4),"")) | L66: =IF(L38="","",IFERROR(L38/('연간'!X4),""))
A67: 배당성향 | B67: 참고 | C67: =IF(C40="","",IFERROR(C40/(IF(COUNT('연간'!G49:J49)<4,"",SUM('연간'!G49:J49))),"")) | D67: =IF(D40="","",IFERROR(D40/(IF(COUNT('연간'!H49:K49)<4,"",SUM('연간'!H49:K49))),"")) | E67: =IF(E40="","",IFERROR(E40/(IF(COUNT('연간'!I49:L49)<4,"",SUM('연간'!I49:L49))),"")) | F67: =IF(F40="","",IFERROR(F40/(IF(COUNT('연간'!J49:M49)<4,"",SUM('연간'!J49:M49))),"")) | G67: =IF(G40="","",IFERROR(G40/(IF(COUNT('연간'!K49:N49)<4,"",SUM('연간'!K49:N49))),"")) | H67: =IF(H40="","",IFERROR(H40/('연간'!T49),"")) | I67: =IF(I40="","",IFERROR(I40/('연간'!U49),"")) | J67: =IF(J40="","",IFERROR(J40/('연간'!V49),"")) | K67: =IF(K40="","",IFERROR(K40/('연간'!W49),"")) | L67: =IF(L40="","",IFERROR(L40/('연간'!X49),""))
A69: 재무상태표 · 전 항목 | B69: 분기 말 잔액
A70: 항목 | B70: 참고 | C70: 2025.3Q | D70: 2025.4Q | E70: 2026.1Q | F70: 2026.2Q | G70: 2026.3Q | H70: 2021 | I70: 2022 | J70: 2023 | K70: 2024 | L70: 2025
A71: 현금 및 예금 | C71: 3970.53 | D71: 5044.657 | E71: 3529.309 | F71: 2989.969 | G71: 3393.185 | H71: 4193.33 | I71: 2250.657 | J71: 2456.383 | K71: 4822.267 | L71: 5044.657
A72: 매출채권 | C72: 283.911 | D72: 132.036 | E72: 146.647 | F72: 243.89 | G72: 115.483 | H72: 5.127 | I72: 43.826 | J72: 65.461 | K72: 211.149 | L72: 132.036
A73: 유가증권 | C73: 398.97 | D73: 399.276 | E73: 500.293 | F73: 400.206 | G73: 500.008 | K73: 0 | L73: 399.276
A74: 판매용 부동산 | C74: 71.357 | D74: 802.073 | E74: 414.21 | F74: 482.064 | G74: 1265.245 | H74: 168.903 | I74: 616.347 | J74: 836.026 | K74: 246.578 | L74: 802.073
A75: 개발 중 판매용 부동산 | C75: 2408.022 | D75: 2105.748 | E75: 2664.846 | F75: 3696.133 | G75: 2311.064 | H75: 95.76 | I75: 740.674 | J75: 925.864 | K75: 1225.684 | L75: 2105.748
A76: 미성업무 지출금 | C76: 36.486 | D76: 80.306 | E76: 61.15 | F76: 54.683 | G76: 37.423 | H76: 40.022 | I76: 14.562 | J76: 20.612 | K76: 25.925 | L76: 80.306
A77: 단기대여금 | C77: 0 | D77: 0 | I77: 0 | J77: 58.5 | K77: 52 | L77: 0
A78: 미수 환급법인세 | C78: 19.857 | D78: 22.04 | E78: 22.04 | F78: 0 | G78: 6.355 | H78: 0 | I78: 132.382 | J78: 49.269 | K78: 0.432 | L78: 22.04
A79: 기타 | C79: 162.869 | D79: 142.004 | E79: 161.257 | F79: 123.881 | G79: 169.365 | H79: 72.77 | I79: 88.245 | J79: 82.458 | K79: 86.642 | L79: 142.004
A80: 대손충당금 | C80: 0 | D80: 0 | I80: 0 | J80: -60.9 | K80: -54.275 | L80: 0
A81: 유동자산 합계 | C81: 7352.005 | D81: 8728.144 | E81: 7499.756 | F81: 7990.829 | G81: 7798.13 | H81: 4575.914 | I81: 3886.695 | J81: 4433.676 | K81: 6616.406 | L81: 8728.144
A82: 건물·구축물(순액) | D82: 331.82 | H82: 216.911 | I82: 195.899 | J82: 347.123 | K82: 322.167 | L82: 331.82
A83: 공구·기구·비품(순액) | D83: 11.133 | H83: 3.491 | I83: 3.203 | J83: 13.641 | K83: 10.795 | L83: 11.133
A84: 토지 | D84: 48.49 | I84: 0 | J84: 48.49 | K84: 48.49 | L84: 48.49
A85: 리스자산(순액) | D85: 81.433 | H85: 109.353 | I85: 102.373 | J85: 95.393 | K85: 88.413 | L85: 81.433
A86: 건설중인자산 | D86: 4.907 | J86: 0 | K86: 12.313 | L86: 4.907
A87: 유형자산 | C87: 477.24 | D87: 477.785 | E87: 471.492 | F87: 468.801 | G87: 581.622 | H87: 329.756 | I87: 301.477 | J87: 504.647 | K87: 482.18 | L87: 477.785
A88: 영업권 | C88: 63.26 | D88: 56.716 | E88: 50.172 | F88: 43.628 | G88: 37.083 | H88: 161.423 | I88: 135.247 | J88: 109.07 | K88: 82.893 | L88: 56.716
A89: 소프트웨어 | D89: 16.454 | H89: 7.347 | I89: 9.137 | J89: 32.811 | K89: 23.954 | L89: 16.454
A90: 기타 | C90: 18.329 | D90: 16.454 | E90: 15.535 | F90: 13.619 | G90: 11.704 | I90: 9.137 | J90: 32.811 | K90: 23.954 | L90: 16.454
A91: 무형자산 합계 | C91: 81.589 | D91: 73.17 | E91: 65.707 | F91: 57.248 | G91: 48.788 | H91: 168.771 | I91: 144.384 | J91: 141.881 | K91: 106.847 | L91: 73.17
A92: 투자유가증권 | C92: 311.477 | D92: 311.674 | E92: 314.594 | F92: 323.41 | G92: 51.665 | H92: 90.581 | I92: 103.141 | J92: 105.869 | K92: 15.56 | L92: 311.674
A93: 장기대여금 | D93: 51 | H93: 5.042 | I93: 28.042 | J93: 21.542 | K93: 5.042 | L93: 51
A94: 보증금 | D94: 186.936 | H94: 143.078 | I94: 138.895 | J94: 133.349 | K94: 149.216 | L94: 186.936
A95: 파산갱생채권 등 | H95: 23.658 | I95: 23.658 | J95: 23.658 | K95: 0
A96: 이연법인세자산 | C96: 23.403 | D96: 89.275 | E96: 81.405 | F96: 58.127 | G96: 70.731 | H96: 128.719 | I96: 140.363 | J96: 103.577 | K96: 65.962 | L96: 89.275
A97: 기타 | C97: 273.855 | D97: 311.741 | E97: 313.76 | F97: 251.566 | G97: 253.478 | H97: 13.49 | I97: 12.09 | J97: 11.273 | K97: 60.166 | L97: 311.741
A98: 대손충당금 | C98: -59.318 | D98: -51.656 | E98: -50.156 | F98: -48.656 | G98: -47.156 | H98: -28.701 | I98: -28.701 | J98: -28.701 | K98: -5.042 | L98: -51.656
A99: 투자 및 기타자산 합계 | C99: 549.417 | D99: 661.034 | E99: 659.603 | F99: 584.449 | G99: 328.718 | H99: 375.869 | I99: 417.49 | J99: 370.569 | K99: 290.906 | L99: 661.034
A100: 비유동자산 합계 | C100: 1108.247 | D100: 1211.99 | E100: 1196.803 | F100: 1110.499 | G100: 959.13 | H100: 874.397 | I100: 863.352 | J100: 1017.098 | K100: 879.933 | L100: 1211.99
A101: 자산 합계 | C101: 8460.252 | D101: 9940.134 | E101: 8696.56 | F101: 9101.328 | G101: 8757.26 | H101: 5450.312 | I101: 4750.048 | J101: 5450.775 | K101: 7496.339 | L101: 9940.134
...

Sheet 섹터 데이터
A1: 필컴퍼니 섹터·사업 데이터
A2: 2단계 보고서를 만들 때 모은 자료 · 월차 · 출처는 맨 오른쪽
A4: this quarter · q single
A5: 항목 | B5: 값 | L5: 출처
A6: 매출 | B6: 28.4 | L6: 2단계 보고서 자료(회사 설명회 자료·공시)
A7: gp | B7: 8.3
A8: 매출총이익률 % | B8: 29.1
A9: sga | B9: 4.4
A10: 영업이익 | B10: 3.9
A11: ord | B11: 3.7
A12: 순이익 | B12: 2.5
A13: EPS approx | B13: 46.02
A15: this quarter · q single ly
A16: 항목 | B16: 값 | L16: 출처
A17: 매출 | B17: 16.8 | L17: 2단계 보고서 자료(회사 설명회 자료·공시)
A18: gp | B18: 4.7
A19: 매출총이익률 % | B19: 27.8
A20: 영업이익 | B20: 0.6
A21: 순이익 | B21: 0.3
A23: this quarter · ytd 9m
A24: 항목 | B24: 값 | L24: 출처
A25: 매출 | B25: 60.96 | L25: 2단계 보고서 자료(회사 설명회 자료·공시)
A26: 매출 YoY % | B26: 8.3
A27: gp | B27: 15.65
A28: 매출총이익률 % | B28: 25.7
A29: sga | B29: 12.95
A30: 영업이익 | B30: 2.7
A31: 영업이익 YoY % | B31: 3.4
A32: ord | B32: 2.34
A33: ord YoY % | B33: -8.9
A34: 순이익 | B34: 2.28
A35: 순이익 YoY % | B35: 46.9
A36: EPS | B36: 42.38
A38: this quarter · ytd 9m ly
A39: 항목 | B39: 값 | L39: 출처
A40: 매출 | B40: 56.29 | L40: 2단계 보고서 자료(회사 설명회 자료·공시)
A41: gp | B41: 14.11
A42: 매출총이익률 % | B42: 25.1
A43: sga | B43: 11.5
A44: 영업이익 | B44: 2.61
A45: ord | B45: 2.56
A46: 순이익 | B46: 1.55
A47: EPS | B47: 28.85
A49: this quarter · nonop 9m
A50: 항목 | B50: 값 | L50: 출처
A51: 영업외수익 | B51: 0.3 | L51: 2단계 보고서 자료(회사 설명회 자료·공시)
A52: 이자수익 | B52: 0.19
A53: 영업외비용 | B53: 0.67
A54: 이자비용 | B54: 0.46
A55: 투자유가증권 평가손 | B55: 0.08
A56: 경상이익 | B56: 2.34
A57: 특별이익 | B57: 2.58
A58: 고정자산 매각익 | B58: 0.84
A59: 보상금 수령 | B59: 1.5
A60: 기타 특별이익 | B60: 0.24
A61: 특별손실 | B61: 0.97
A62: 주식급부신탁 종료손 | B62: 0.97
A63: 세전이익 | B63: 3.94
A64: 법인세 등 | B64: 1.67
A66: this quarter · bs 3q
A67: 항목 | B67: 값 | L67: 출처
A68: 총자산 | B68: 87.6 | L68: 2단계 보고서 자료(회사 설명회 자료·공시)
A69: 순자산 | B69: 35.7
A70: 자기자본비율_pct | B70: 40.1
A71: 현금 | B71: 33.9
A72: 유가증권 | B72: 5
A73: 판매용 부동산 | B73: 12.7
A74: 개발 중 판매용 부동산 | B74: 23.1
A75: 단기차입 | B75: 4.7
A76: 1년내 장기차입 | B76: 10.6
A77: 선수금 | B77: 13.3
A79: shares
A80: 항목 | B80: 값 | L80: 출처
A81: issued | B81: 5744900 | L81: 2단계 보고서 자료(회사 설명회 자료·공시)
A82: treasury | B82: 372724
A83: outstanding | B83: 5372176
A85: bs annual
A86: 항목 | B86: 2021 | C86: 2022 | D86: 2023 | E86: 2024 | F86: 2025 | L86: 출처
A87: labels | B87: 2021 | C87: 2022 | D87: 2023 | E87: 2024 | F87: 2025 | L87: 2단계 보고서 자료(회사 설명회 자료·공시)
A88: current assets | B88: 45.8 | C88: 38.9 | D88: 44.3 | E88: 66.2 | F88: 87.3
A89: cash | B89: 41.9 | C89: 22.5 | D89: 24.6 | E89: 48.2 | F89: 50.4
A90: st fin | E90: 0 | F90: 4
A91: receivables | B91: 0.1 | C91: 0.4 | D91: 0.7 | E91: 2.1 | F91: 1.3
A92: inventory | B92: 1.7 | C92: 6.2 | D92: 8.4 | E92: 2.5 | F92: 8
A93: noncurrent assets | B93: 8.7 | C93: 8.6 | D93: 10.2 | E93: 8.8 | F93: 12.1
A94: ppe | B94: 3.3 | C94: 3 | D94: 5 | E94: 4.8 | F94: 4.8
A95: intangibles | B95: 1.7 | C95: 1.4 | D95: 1.4 | E95: 1.1 | F95: 0.7
A96: inv property
A97: 합계 assets | B97: 54.5 | C97: 47.5 | D97: 54.5 | E97: 75 | F97: 99.4
A98: current liab | B98: 21.3 | C98: 15.3 | D98: 16.2 | E98: 32.7 | F98: 47.9
A99: payables | B99: 1.7 | C99: 4.6 | D99: 3.9 | E99: 8.7 | F99: 7.3
A100: st debt | B100: 0 | C100: 0 | D100: 4.4 | E100: 4.2 | F100: 9.2
A101: noncurrent liab | B101: 5.5 | C101: 7.8 | D101: 11 | E101: 12.5 | F101: 18
A102: lt debt | B102: 2 | C102: 4.4 | D102: 6.8 | E102: 8.3 | F102: 13.4
A103: bonds
A104: 합계 liab | B104: 26.8 | C104: 23.1 | D104: 27.2 | E104: 45.2 | F104: 66
A105: capital stock | B105: 7.9 | C105: 7.9 | D105: 7.9 | E105: 7.9 | F105: 7.9
A106: retained | B106: 18 | C106: 19.4 | D106: 18.5 | E106: 20.8 | F106: 24.3
A107: nci | B107: 0 | C107: 0 | D107: 0
A108: 합계 equity | B108: 27.7 | C108: 24.4 | D108: 27.3 | E108: 29.8 | F108: 33.4
...

Sheet 출처
A1: 출처 · 쓴 결산단신
A3: 공시일 | B3: 문서 | C3: PDF
A4: 2026-10-13 | B4: 2026년 11월 결산기 ３분기 결산단신 | C4: https://www2.jpx.co.jp/disc/32670/140120261012549072.pdf
A5: 2026-07-14 | B5: 2026년 11월 결산기 ２분기 결산단신 | C5: https://www2.jpx.co.jp/disc/32670/140120260701586068.pdf
A6: 2026-04-14 | B6: 2026년 11월 결산기 １분기 결산단신 | C6: https://www2.jpx.co.jp/disc/32670/140120260413503112.pdf
A7: 2026-01-14 | B7: 2025년 11월 결산기 연간 결산단신 | C7: https://www2.jpx.co.jp/disc/32670/140120260113533027.pdf
A8: 2025-10-10 | B8: 2025년 11월 결산기 ３분기 결산단신 | C8: https://www2.jpx.co.jp/disc/32670/140120251010571624.pdf
A9: 2025-07-11 | B9: 2025년 11월 결산기 ２분기 결산단신 | C9: https://www2.jpx.co.jp/disc/32670/140120250710512001.pdf
A10: 2025-04-11 | B10: 2025년 11월 결산기 １분기 결산단신 | C10: https://www2.jpx.co.jp/disc/32670/140120250411513226.pdf
A11: 2025-01-10 | B11: 2024년 11월 결산기 연간 결산단신 | C11: https://www2.jpx.co.jp/disc/32670/140120250109548694.pdf
A12: 2024-10-10 | B12: 2024년 11월 결산기 ３분기 결산단신 | C12: https://www2.jpx.co.jp/disc/32670/140120241009595868.pdf
A13: 2024-07-11 | B13: 2024년 11월 결산기 ２분기 결산단신 | C13: https://www2.jpx.co.jp/disc/32670/140120240710547101.pdf
A14: 2024-04-11 | B14: 2024년 11월 결산기 １분기 결산단신 | C14: https://www2.jpx.co.jp/disc/32670/140120240410568387.pdf
... A24: 2018-01-12 | B24: 연간 결산단신 | C24: https://www2.jpx.co.jp/disc/32670/140120180112449908.pdf
