Workbook

Sheet 연간
A1: 3778 Model
A2: 모를 땐 보수적으로 | B2: (단위: 백만엔) | C2: 3월 결산 · 일본 기준 · 2027.1Q = 2027년 3월 결산기 1분기 | Y2: (추정: 파란 글씨 = 직접 입력)
A3: 항목 | B3: 참고 | C3: 2024.2Q | D3: 2024.3Q | E3: 2024.4Q | F3: 2025.1Q | G3: 2025.2Q | H3: 2025.3Q | I3: 2025.4Q | J3: 2026.1Q | K3: 2026.2Q | L3: 2026.3Q | M3: 2026.4Q | N3: 2027.1Q | O3: 2017 | P3: 2018 | Q3: 2019 | R3: 2020 | S3: 2021 | T3: 2022 | U3: 2023 | V3: 2024 | W3: 2025 | X3: 2026 | Y3: 2027(MW) | Z3: 2028(MW) | AA3: 2029(MW) | AB3: 2030(MW) | AC3: 2031(MW)
A4: 매출액 | B4: MW 직접 입력 | C4: 5237.51 | D4: 5315.83 | E4: 6167.796 | F4: 5935.785 | G4: 7335.885 | H4: 8125.387 | I4: 10015.325 | J4: 7492.152 | K4: 8139.01 | L4: 8393.405 | M4: 11277.082 | N4: 11134.597 | O4: 13961.972 | P4: 17033.374 | Q4: 19501.463 | R4: 21908.899 | S4: 22168.022 | T4: 20019.177 | U4: 20622.9 | V4: 21826.794 | W4: 31412.382 | X4: 35301.649 | Y4: =IF(COUNT(Y7)=0,"",SUM(Y7)) | Z4: =IF(COUNT(Z7)=0,"",SUM(Z7)) | AA4: =IF(COUNT(AA7)=0,"",SUM(AA7)) | AB4: =IF(COUNT(AB7)=0,"",SUM(AB7)) | AC4: =IF(COUNT(AC7)=0,"",SUM(AC7))
A5: YoY | G5: =IF(OR(G4="",C4=""),"",IFERROR(G4/C4-1,"")) | H5: =IF(OR(H4="",D4=""),"",IFERROR(H4/D4-1,"")) | I5: =IF(OR(I4="",E4=""),"",IFERROR(I4/E4-1,"")) | J5: =IF(OR(J4="",F4=""),"",IFERROR(J4/F4-1,"")) | K5: =IF(OR(K4="",G4=""),"",IFERROR(K4/G4-1,"")) | L5: =IF(OR(L4="",H4=""),"",IFERROR(L4/H4-1,"")) | M5: =IF(OR(M4="",I4=""),"",IFERROR(M4/I4-1,"")) | N5: =IF(OR(N4="",J4=""),"",IFERROR(N4/J4-1,"")) | P5: =IF(OR(P4="",O4=""),"",IFERROR(P4/O4-1,"")) | Q5: =IF(OR(Q4="",P4=""),"",IFERROR(Q4/P4-1,"")) | R5: =IF(OR(R4="",Q4=""),"",IFERROR(R4/Q4-1,"")) | S5: =IF(OR(S4="",R4=""),"",IFERROR(S4/R4-1,"")) | T5: =IF(OR(T4="",S4=""),"",IFERROR(T4/S4-1,"")) | U5: =IF(OR(U4="",T4=""),"",IFERROR(U4/T4-1,"")) | V5: =IF(OR(V4="",U4=""),"",IFERROR(V4/U4-1,"")) | W5: =IF(OR(W4="",V4=""),"",IFERROR(W4/V4-1,"")) | ... AC5: =IF(OR(AC4="",AB4=""),"",IFERROR(AC4/AB4-1,""))
A6: 제품별 매출 분류 | B6: 사업보고서 매출실적
A7: (제품별 매출 미공시 — 직접 입력)
A8: 비중 | C8: =IF(OR(C7="",C4=""),"",IFERROR(C7/C4,"")) | D8: =IF(OR(D7="",D4=""),"",IFERROR(D7/D4,"")) | E8: =IF(OR(E7="",E4=""),"",IFERROR(E7/E4,"")) | F8: =IF(OR(F7="",F4=""),"",IFERROR(F7/F4,"")) | G8: =IF(OR(G7="",G4=""),"",IFERROR(G7/G4,"")) | H8: =IF(OR(H7="",H4=""),"",IFERROR(H7/H4,"")) | I8: =IF(OR(I7="",I4=""),"",IFERROR(I7/I4,"")) | J8: =IF(OR(J7="",J4=""),"",IFERROR(J7/J4,"")) | ... AC8: =IF(OR(AC7="",AC4=""),"",IFERROR(AC7/AC4,""))
A9: YoY | G9: =IF(OR(G7="",C7=""),"",IFERROR(G7/C7-1,"")) | H9: =IF(OR(H7="",D7=""),"",IFERROR(H7/D7-1,"")) | I9: =IF(OR(I7="",E7=""),"",IFERROR(I7/E7-1,"")) | J9: =IF(OR(J7="",F7=""),"",IFERROR(J7/F7-1,"")) | K9: =IF(OR(K7="",G7=""),"",IFERROR(K7/G7-1,"")) | L9: =IF(OR(L7="",H7=""),"",IFERROR(L7/H7-1,"")) | M9: =IF(OR(M7="",I7=""),"",IFERROR(M7/I7-1,"")) | N9: =IF(OR(N7="",J7=""),"",IFERROR(N7/J7-1,"")) | P9: =IF(OR(P7="",O7=""),"",IFERROR(P7/O7-1,"")) | Q9: =IF(OR(Q7="",P7=""),"",IFERROR(Q7/P7-1,"")) | R9: =IF(OR(R7="",Q7=""),"",IFERROR(R7/Q7-1,"")) | S9: =IF(OR(S7="",R7=""),"",IFERROR(S7/R7-1,"")) | T9: =IF(OR(T7="",S7=""),"",IFERROR(T7/S7-1,"")) | U9: =IF(OR(U7="",T7=""),"",IFERROR(U7/T7-1,"")) | V9: =IF(OR(V7="",U7=""),"",IFERROR(V7/U7-1,"")) | W9: =IF(OR(W7="",V7=""),"",IFERROR(W7/V7-1,"")) | ... AC9: =IF(OR(AC7="",AB7=""),"",IFERROR(AC7/AB7-1,""))
A10: 매출원가
A11: 전체 매출원가 | C11: 3884.069 | D11: 3929.928 | E11: 4457.149 | F11: 4236.884 | G11: 4685.563 | H11: 5159.102 | I11: 6100.555 | J11: 5948.216 | K11: 6534.127 | L11: 6504.314 | M11: 8358.476 | N11: 7713.234 | O11: 9784.241 | P11: 12214.571 | Q11: 14155.609 | R11: 16076.933 | S11: 16478.309 | T11: 15311.108 | U11: 15255.276 | V11: 16091 | W11: 20182.104 | X11: 27345.133
A12: 매출총이익 | C12: =IF(OR(C4="",C11=""),"",IFERROR(C4-C11,"")) | D12: =IF(OR(D4="",D11=""),"",IFERROR(D4-D11,"")) | E12: =IF(OR(E4="",E11=""),"",IFERROR(E4-E11,"")) | F12: =IF(OR(F4="",F11=""),"",IFERROR(F4-F11,"")) | G12: =IF(OR(G4="",G11=""),"",IFERROR(G4-G11,"")) | H12: =IF(OR(H4="",H11=""),"",IFERROR(H4-H11,"")) | I12: =IF(OR(I4="",I11=""),"",IFERROR(I4-I11,"")) | J12: =IF(OR(J4="",J11=""),"",IFERROR(J4-J11,"")) | ... X12: =IF(OR(X4="",X11=""),"",IFERROR(X4-X11,""))
A13: GPM | C13: =IF(OR(C12="",C4=""),"",IFERROR(C12/C4,"")) | D13: =IF(OR(D12="",D4=""),"",IFERROR(D12/D4,"")) | E13: =IF(OR(E12="",E4=""),"",IFERROR(E12/E4,"")) | F13: =IF(OR(F12="",F4=""),"",IFERROR(F12/F4,"")) | G13: =IF(OR(G12="",G4=""),"",IFERROR(G12/G4,"")) | H13: =IF(OR(H12="",H4=""),"",IFERROR(H12/H4,"")) | I13: =IF(OR(I12="",I4=""),"",IFERROR(I12/I4,"")) | J13: =IF(OR(J12="",J4=""),"",IFERROR(J12/J4,"")) | ... AC13: =IF(OR(AC12="",AC4=""),"",IFERROR(AC12/AC4,""))
A14: 판매관리비
A15: 전체 판관비 | C15: 1208.361 | D15: 1186.81 | E15: 1274.723 | F15: 1467.133 | G15: 1586.202 | H15: 1676.755 | I15: 2354.602 | J15: 2001.106 | K15: 2068.527 | L15: 2085.757 | M15: 2204.78 | N15: 2190.684 | O15: 3159.669 | P15: 4072.827 | Q15: 4778.645 | R15: 4892.759 | S15: 4317.243 | T15: 3944.927 | U15: 4274.57 | V15: 4851.285 | W15: 7084.692 | X15: 8360.17
A16: 영업이익 | B16: MW = 매출 × OPM | C16: 145.081 | D16: 199.092 | E16: 435.923 | F16: 231.767 | G16: 1064.12 | H16: 1289.53 | I16: 1560.169 | J16: -457.171 | K16: -463.644 | L16: -196.665 | M16: 713.826 | N16: 1230.678 | O16: 1018.061 | P16: 745.974 | Q16: 567.208 | R16: 939.206 | S16: 1372.469 | T16: 763.141 | U16: 1093.053 | V16: 884.507 | W16: 4145.586 | X16: -403.654 | Y16: =IF(OR(Y4="",Y17=""),"",IFERROR(Y4*Y17,"")) | Z16: =IF(OR(Z4="",Z17=""),"",IFERROR(Z4*Z17,"")) | AA16: =IF(OR(AA4="",AA17=""),"",IFERROR(AA4*AA17,"")) | AB16: =IF(OR(AB4="",AB17=""),"",IFERROR(AB4*AB17,"")) | AC16: =IF(OR(AC4="",AC17=""),"",IFERROR(AC4*AC17,""))
A17: OPM | B17: MW 입력 | C17: =IF(OR(C16="",C4=""),"",IFERROR(C16/C4,"")) | D17: =IF(OR(D16="",D4=""),"",IFERROR(D16/D4,"")) | E17: =IF(OR(E16="",E4=""),"",IFERROR(E16/E4,"")) | F17: =IF(OR(F16="",F4=""),"",IFERROR(F16/F4,"")) | G17: =IF(OR(G16="",G4=""),"",IFERROR(G16/G4,"")) | H17: =IF(OR(H16="",H4=""),"",IFERROR(H16/H4,"")) | I17: =IF(OR(I16="",I4=""),"",IFERROR(I16/I4,"")) | J17: =IF(OR(J16="",J4=""),"",IFERROR(J16/J4,"")) | ... X17: =IF(OR(X16="",X4=""),"",IFERROR(X16/X4,""))
A18: 증가율 | G18: =IF(OR(G16="",C16=""),"",IFERROR(G16/C16-1,"")) | H18: =IF(OR(H16="",D16=""),"",IFERROR(H16/D16-1,"")) | I18: =IF(OR(I16="",E16=""),"",IFERROR(I16/E16-1,"")) | J18: =IF(OR(J16="",F16=""),"",IFERROR(J16/F16-1,"")) | K18: =IF(OR(K16="",G16=""),"",IFERROR(K16/G16-1,"")) | L18: =IF(OR(L16="",H16=""),"",IFERROR(L16/H16-1,"")) | M18: =IF(OR(M16="",I16=""),"",IFERROR(M16/I16-1,"")) | N18: =IF(OR(N16="",J16=""),"",IFERROR(N16/J16-1,"")) | P18: =IF(OR(P16="",O16=""),"",IFERROR(P16/O16-1,"")) | Q18: =IF(OR(Q16="",P16=""),"",IFERROR(Q16/P16-1,"")) | R18: =IF(OR(R16="",Q16=""),"",IFERROR(R16/Q16-1,"")) | S18: =IF(OR(S16="",R16=""),"",IFERROR(S16/R16-1,"")) | T18: =IF(OR(T16="",S16=""),"",IFERROR(T16/S16-1,"")) | U18: =IF(OR(U16="",T16=""),"",IFERROR(U16/T16-1,"")) | V18: =IF(OR(V16="",U16=""),"",IFERROR(V16/U16-1,"")) | W18: =IF(OR(W16="",V16=""),"",IFERROR(W16/V16-1,"")) | ... AC18: =IF(OR(AC16="",AB16=""),"",IFERROR(AC16/AB16-1,""))
A19: 비용의 성격별 분류 | B19: 참고 데이터
A20: 총 판관비 | O20: =IF(O15="","",O15) | P20: =IF(P15="","",P15) | Q20: =IF(Q15="","",Q15) | R20: =IF(R15="","",R15) | S20: =IF(S15="","",S15) | T20: =IF(T15="","",T15) | U20: =IF(U15="","",U15) | V20: =IF(V15="","",V15) | ... X20: =IF(X15="","",X15)
A21: 급여 | B21: 고정비 | O21: 870.649 | P21: 1192.232 | Q21: 1408.291 | R21: 1494.757 | S21: 1356.345 | T21: 1255.128 | U21: 1372.555 | V21: 1555.223 | W21: 2182.757 | X21: 2936.951
A22: % of Sales | O22: =IF(OR(O21="",O4=""),"",IFERROR(O21/O4,"")) | P22: =IF(OR(P21="",P4=""),"",IFERROR(P21/P4,"")) | Q22: =IF(OR(Q21="",Q4=""),"",IFERROR(Q21/Q4,"")) | R22: =IF(OR(R21="",R4=""),"",IFERROR(R21/R4,"")) | S22: =IF(OR(S21="",S4=""),"",IFERROR(S21/S4,"")) | T22: =IF(OR(T21="",T4=""),"",IFERROR(T21/T4,"")) | U22: =IF(OR(U21="",U4=""),"",IFERROR(U21/U4,"")) | V22: =IF(OR(V21="",V4=""),"",IFERROR(V21/V4,"")) | ... X22: =IF(OR(X21="",X4=""),"",IFERROR(X21/X4,""))
A23: 감가상각비 | B23: 고정비
A24: % of Sales | O24: =IF(OR(O23="",O4=""),"",IFERROR(O23/O4,"")) | P24: =IF(OR(P23="",P4=""),"",IFERROR(P23/P4,"")) | Q24: =IF(OR(Q23="",Q4=""),"",IFERROR(Q23/Q4,"")) | R24: =IF(OR(R23="",R4=""),"",IFERROR(R23/R4,"")) | S24: =IF(OR(S23="",S4=""),"",IFERROR(S23/S4,"")) | T24: =IF(OR(T23="",T4=""),"",IFERROR(T23/T4,"")) | U24: =IF(OR(U23="",U4=""),"",IFERROR(U23/U4,"")) | V24: =IF(OR(V23="",V4=""),"",IFERROR(V23/V4,"")) | ... X24: =IF(OR(X23="",X4=""),"",IFERROR(X23/X4,""))
A25: 지급수수료 | B25: 고정비 | O25: 663.968 | P25: 769.364 | Q25: 907.336 | R25: 897.56 | S25: 950.291 | T25: 861.663 | U25: 935.541 | V25: 1051.952 | W25: 1456.992 | X25: 1610.716
A26: % of Sales | O26: =IF(OR(O25="",O4=""),"",IFERROR(O25/O4,"")) | P26: =IF(OR(P25="",P4=""),"",IFERROR(P25/P4,"")) | Q26: =IF(OR(Q25="",Q4=""),"",IFERROR(Q25/Q4,"")) | R26: =IF(OR(R25="",R4=""),"",IFERROR(R25/R4,"")) | S26: =IF(OR(S25="",S4=""),"",IFERROR(S25/S4,"")) | T26: =IF(OR(T25="",T4=""),"",IFERROR(T25/T4,"")) | U26: =IF(OR(U25="",U4=""),"",IFERROR(U25/U4,"")) | V26: =IF(OR(V25="",V4=""),"",IFERROR(V25/V4,"")) | ... X26: =IF(OR(X25="",X4=""),"",IFERROR(X25/X4,""))
A27: 연구개발비 | B27: 변동비
A28: % of Sales | O28: =IF(OR(O27="",O4=""),"",IFERROR(O27/O4,"")) | P28: =IF(OR(P27="",P4=""),"",IFERROR(P27/P4,"")) | Q28: =IF(OR(Q27="",Q4=""),"",IFERROR(Q27/Q4,"")) | R28: =IF(OR(R27="",R4=""),"",IFERROR(R27/R4,"")) | S28: =IF(OR(S27="",S4=""),"",IFERROR(S27/S4,"")) | T28: =IF(OR(T27="",T4=""),"",IFERROR(T27/T4,"")) | U28: =IF(OR(U27="",U4=""),"",IFERROR(U27/U4,"")) | V28: =IF(OR(V27="",V4=""),"",IFERROR(V27/V4,"")) | ... X28: =IF(OR(X27="",X4=""),"",IFERROR(X27/X4,""))
A29: 기타비용 | B29: 변동비 | O29: =IF(OR(O20="",O21="",O23="",O25="",O27=""),"",IFERROR(O20-O21-O23-O25-O27,"")) | P29: =IF(OR(P20="",P21="",P23="",P25="",P27=""),"",IFERROR(P20-P21-P23-P25-P27,"")) | Q29: =IF(OR(Q20="",Q21="",Q23="",Q25="",Q27=""),"",IFERROR(Q20-Q21-Q23-Q25-Q27,"")) | R29: =IF(OR(R20="",R21="",R23="",R25="",R27=""),"",IFERROR(R20-R21-R23-R25-R27,"")) | S29: =IF(OR(S20="",S21="",S23="",S25="",S27=""),"",IFERROR(S20-S21-S23-S25-S27,"")) | T29: =IF(OR(T20="",T21="",T23="",T25="",T27=""),"",IFERROR(T20-T21-T23-T25-T27,"")) | U29: =IF(OR(U20="",U21="",U23="",U25="",U27=""),"",IFERROR(U20-U21-U23-U25-U27,"")) | V29: =IF(OR(V20="",V21="",V23="",V25="",V27=""),"",IFERROR(V20-V21-V23-V25-V27,"")) | ... X29: =IF(OR(X20="",X21="",X23="",X25="",X27=""),"",IFERROR(X20-X21-X23-X25-X27,""))
A30: % of Sales | O30: =IF(OR(O29="",O4=""),"",IFERROR(O29/O4,"")) | P30: =IF(OR(P29="",P4=""),"",IFERROR(P29/P4,"")) | Q30: =IF(OR(Q29="",Q4=""),"",IFERROR(Q29/Q4,"")) | R30: =IF(OR(R29="",R4=""),"",IFERROR(R29/R4,"")) | S30: =IF(OR(S29="",S4=""),"",IFERROR(S29/S4,"")) | T30: =IF(OR(T29="",T4=""),"",IFERROR(T29/T4,"")) | U30: =IF(OR(U29="",U4=""),"",IFERROR(U29/U4,"")) | V30: =IF(OR(V29="",V4=""),"",IFERROR(V29/V4,"")) | ... X30: =IF(OR(X29="",X4=""),"",IFERROR(X29/X4,""))
A31: 당기순이익 추정
A32: 특별이익 | C32: 0 | D32: 5.868 | E32: 1624.819 | F32: 3709.415 | G32: 0 | H32: 1623.376 | I32: 787.759 | J32: 6283.839 | K32: 0 | L32: 137.447 | M32: 8046.062 | N32: 2503.629 | O32: 21.773 | P32: 0 | Q32: 311.218 | R32: 87.202 | S32: 127.193 | T32: 12.84 | U32: 8.574 | V32: 1692.005 | W32: 6120.55 | X32: 14467.348 | Y32: =IF(OR(Y4="",Y33=""),"",IFERROR(Y4*Y33,"")) | Z32: =IF(OR(Z4="",Z33=""),"",IFERROR(Z4*Z33,"")) | AA32: =IF(OR(AA4="",AA33=""),"",IFERROR(AA4*AA33,"")) | AB32: =IF(OR(AB4="",AB33=""),"",IFERROR(AB4*AB33,"")) | AC32: =IF(OR(AC4="",AC33=""),"",IFERROR(AC4*AC33,""))
A33: % of Sales | B33: MW = 최근 3년 평균 | C33: =IF(OR(C32="",C4=""),"",IFERROR(C32/C4,"")) | D33: =IF(OR(D32="",D4=""),"",IFERROR(D32/D4,"")) | E33: =IF(OR(E32="",E4=""),"",IFERROR(E32/E4,"")) | F33: =IF(OR(F32="",F4=""),"",IFERROR(F32/F4,"")) | G33: =IF(OR(G32="",G4=""),"",IFERROR(G32/G4,"")) | H33: =IF(OR(H32="",H4=""),"",IFERROR(H32/H4,"")) | I33: =IF(OR(I32="",I4=""),"",IFERROR(I32/I4,"")) | J33: =IF(OR(J32="",J4=""),"",IFERROR(J32/J4,"")) | ... X33: =IF(OR(X32="",X4=""),"",IFERROR(X32/X4,"")) | Y33: =IFERROR(AVERAGE(V33,W33,X33),"") | Z33: =Y33 | AA33: =Z33 | AB33: =AA33 | AC33: =AB33
A34: 특별손실 | C34: 1.335 | D34: 0.014 | E34: 1624.953 | F34: 3709.493 | G34: 30.016 | H34: 1631.954 | I34: 830.294 | J34: 6283.862 | K34: 14.609 | L34: 1.174 | M34: 8028.858 | N34: 2504.089 | O34: 30.15 | P34: 32.195 | Q34: 383.154 | R34: 500.042 | S34: 142.014 | T34: 275.722 | U34: 14.605 | V34: 1626.416 | W34: 6201.757 | X34: 14328.503 | Y34: =IF(OR(Y4="",Y35=""),"",IFERROR(Y4*Y35,"")) | Z34: =IF(OR(Z4="",Z35=""),"",IFERROR(Z4*Z35,"")) | AA34: =IF(OR(AA4="",AA35=""),"",IFERROR(AA4*AA35,"")) | AB34: =IF(OR(AB4="",AB35=""),"",IFERROR(AB4*AB35,"")) | AC34: =IF(OR(AC4="",AC35=""),"",IFERROR(AC4*AC35,""))
A35: % of Sales | C35: =IF(OR(C34="",C4=""),"",IFERROR(C34/C4,"")) | D35: =IF(OR(D34="",D4=""),"",IFERROR(D34/D4,"")) | E35: =IF(OR(E34="",E4=""),"",IFERROR(E34/E4,"")) | F35: =IF(OR(F34="",F4=""),"",IFERROR(F34/F4,"")) | G35: =IF(OR(G34="",G4=""),"",IFERROR(G34/G4,"")) | H35: =IF(OR(H34="",H4=""),"",IFERROR(H34/H4,"")) | I35: =IF(OR(I34="",I4=""),"",IFERROR(I34/I4,"")) | J35: =IF(OR(J34="",J4=""),"",IFERROR(J34/J4,"")) | ... X35: =IF(OR(X34="",X4=""),"",IFERROR(X34/X4,"")) | Y35: =IFERROR(AVERAGE(V35,W35,X35),"") | Z35: =Y35 | AA35: =Z35 | AB35: =AA35 | AC35: =AB35
A36: 영업외수익 | C36: 15.082 | D36: 7.783 | E36: 91.265 | F36: 46.58 | G36: 29.343 | H36: 128.899 | I36: 92.161 | J36: 149.528 | K36: 223.472 | L36: 327.182 | M36: 363.977 | N36: 226.474 | O36: 12.075 | P36: 30.848 | Q36: 42.876 | R36: 63.135 | S36: 43.324 | T36: 110.995 | U36: 68.81 | V36: 138.701 | W36: 296.983 | X36: 1064.159 | Y36: =IF(OR(Y4="",Y37=""),"",IFERROR(Y4*Y37,"")) | Z36: =IF(OR(Z4="",Z37=""),"",IFERROR(Z4*Z37,"")) | AA36: =IF(OR(AA4="",AA37=""),"",IFERROR(AA4*AA37,"")) | AB36: =IF(OR(AB4="",AB37=""),"",IFERROR(AB4*AB37,"")) | AC36: =IF(OR(AC4="",AC37=""),"",IFERROR(AC4*AC37,""))
A37: % of Sales | C37: =IF(OR(C36="",C4=""),"",IFERROR(C36/C4,"")) | D37: =IF(OR(D36="",D4=""),"",IFERROR(D36/D4,"")) | E37: =IF(OR(E36="",E4=""),"",IFERROR(E36/E4,"")) | F37: =IF(OR(F36="",F4=""),"",IFERROR(F36/F4,"")) | G37: =IF(OR(G36="",G4=""),"",IFERROR(G36/G4,"")) | H37: =IF(OR(H36="",H4=""),"",IFERROR(H36/H4,"")) | I37: =IF(OR(I36="",I4=""),"",IFERROR(I36/I4,"")) | J37: =IF(OR(J36="",J4=""),"",IFERROR(J36/J4,"")) | ... X37: =IF(OR(X36="",X4=""),"",IFERROR(X36/X4,"")) | Y37: =IFERROR(AVERAGE(V37,W37,X37),"") | Z37: =Y37 | AA37: =Z37 | AB37: =AA37 | AC37: =AB37
A38: 영업외비용 | C38: 60.544 | D38: 59.823 | E38: 82.841 | F38: 183.138 | G38: 86.565 | H38: 32.07 | I38: 80.364 | J38: 130.634 | K38: 133.313 | L38: 118.343 | M38: 172.737 | N38: 199.088 | O38: 225.73 | P38: 202.378 | Q38: 214.243 | R38: 212.697 | S38: 316.115 | T38: 224.704 | U38: 196.032 | V38: 259.129 | W38: 382.137 | X38: 555.027 | Y38: =IF(OR(Y4="",Y39=""),"",IFERROR(Y4*Y39,"")) | Z38: =IF(OR(Z4="",Z39=""),"",IFERROR(Z4*Z39,"")) | AA38: =IF(OR(AA4="",AA39=""),"",IFERROR(AA4*AA39,"")) | AB38: =IF(OR(AB4="",AB39=""),"",IFERROR(AB4*AB39,"")) | AC38: =IF(OR(AC4="",AC39=""),"",IFERROR(AC4*AC39,""))
A39: % of Sales | C39: =IF(OR(C38="",C4=""),"",IFERROR(C38/C4,"")) | D39: =IF(OR(D38="",D4=""),"",IFERROR(D38/D4,"")) | E39: =IF(OR(E38="",E4=""),"",IFERROR(E38/E4,"")) | F39: =IF(OR(F38="",F4=""),"",IFERROR(F38/F4,"")) | G39: =IF(OR(G38="",G4=""),"",IFERROR(G38/G4,"")) | H39: =IF(OR(H38="",H4=""),"",IFERROR(H38/H4,"")) | I39: =IF(OR(I38="",I4=""),"",IFERROR(I38/I4,"")) | J39: =IF(OR(J38="",J4=""),"",IFERROR(J38/J4,"")) | ... X39: =IF(OR(X38="",X4=""),"",IFERROR(X38/X4,"")) | Y39: =IFERROR(AVERAGE(V39,W39,X39),"") | Z39: =Y39 | AA39: =Z39 | AB39: =AA39 | AC39: =AB39
A40: 법인세비용차감전순이익(손실) | C40: 98.284 | D40: 152.906 | E40: 444.214 | F40: 95.13 | G40: 976.883 | H40: 1377.78 | I40: 1529.431 | J40: -438.299 | K40: -388.094 | L40: 148.446 | M40: 922.269 | N40: 1257.605 | O40: 796.029 | P40: 542.249 | Q40: 323.905 | R40: 376.804 | S40: 1084.857 | T40: 386.549 | U40: 959.799 | V40: 829.668 | W40: 3979.224 | X40: 244.322 | Y40: =IF(OR(Y16=""),"",IFERROR(Y16+N(Y32)-N(Y34)+N(Y36)-N(Y38),"")) | Z40: =IF(OR(Z16=""),"",IFERROR(Z16+N(Z32)-N(Z34)+N(Z36)-N(Z38),"")) | AA40: =IF(OR(AA16=""),"",IFERROR(AA16+N(AA32)-N(AA34)+N(AA36)-N(AA38),"")) | AB40: =IF(OR(AB16=""),"",IFERROR(AB16+N(AB32)-N(AB34)+N(AB36)-N(AB38),"")) | AC40: =IF(OR(AC16=""),"",IFERROR(AC16+N(AC32)-N(AC34)+N(AC36)-N(AC38),""))
A41: 법인세비용(수익) | C41: 46.442 | D41: 22.421 | E41: 90.515 | F41: 54.421 | G41: 309.433 | H41: 441.617 | I41: 220.398 | J41: -119.319 | K41: -89.794 | L41: 67.034 | M41: 151.604 | N41: 400.032 | O41: 247.158 | P41: 190.151 | Q41: 175.535 | R41: 171.579 | S41: 304.897 | T41: 86.342 | U41: 288.045 | V41: 194.436 | W41: 1025.869 | X41: 9.525 | Y41: =IF(OR(Y40="",Y42=""),"",IFERROR(MAX(Y40,0)*Y42,"")) | Z41: =IF(OR(Z40="",Z42=""),"",IFERROR(MAX(Z40,0)*Z42,"")) | AA41: =IF(OR(AA40="",AA42=""),"",IFERROR(MAX(AA40,0)*AA42,"")) | AB41: =IF(OR(AB40="",AB42=""),"",IFERROR(MAX(AB40,0)*AB42,"")) | AC41: =IF(OR(AC40="",AC42=""),"",IFERROR(MAX(AC40,0)*AC42,""))
A42: 법인세율 | B42: MW 기본 30% | C42: =IF(OR(C41="",C40=""),"",IFERROR(C41/C40,"")) | D42: =IF(OR(D41="",D40=""),"",IFERROR(D41/D40,"")) | E42: =IF(OR(E41="",E40=""),"",IFERROR(E41/E40,"")) | F42: =IF(OR(F41="",F40=""),"",IFERROR(F41/F40,"")) | G42: =IF(OR(G41="",G40=""),"",IFERROR(G41/G40,"")) | H42: =IF(OR(H41="",H40=""),"",IFERROR(H41/H40,"")) | I42: =IF(OR(I41="",I40=""),"",IFERROR(I41/I40,"")) | J42: =IF(OR(J41="",J40=""),"",IFERROR(J41/J40,"")) | ... X42: =IF(OR(X41="",X40=""),"",IFERROR(X41/X40,"")) | Y42: 0.3 | Z42: 0.3 | AA42: 0.3 | AB42: 0.3 | AC42: 0.3
A43: 당기순이익(손실) | C43: 51.842 | D43: 130.486 | E43: 353.699 | F43: 40.709 | G43: 667.449 | H43: 936.164 | I43: 1309.033 | J43: -318.98 | K43: -298.3 | L43: 81.413 | M43: 770.664 | N43: 857.572 | O43: 548.871 | P43: 352.098 | Q43: 148.369 | R43: 205.224 | S43: 779.959 | T43: 300.206 | U43: 671.754 | V43: 635.232 | W43: 2953.355 | X43: 234.797 | Y43: =IF(OR(Y40=""),"",IFERROR(Y40-Y41,"")) | Z43: =IF(OR(Z40=""),"",IFERROR(Z40-Z41,"")) | AA43: =IF(OR(AA40=""),"",IFERROR(AA40-AA41,"")) | AB43: =IF(OR(AB40=""),"",IFERROR(AB40-AB41,"")) | AC43: =IF(OR(AC40=""),"",IFERROR(AC40-AC41,""))
A44: 지배주주 순이익 | C44: 66.672 | D44: 128.866 | E44: 347.712 | F44: 41.721 | G44: 668.35 | H44: 932.2 | I44: 1295.188 | J44: -324.379 | K44: -302.384 | L44: 75.738 | M44: 767.048 | N44: 855.926 | O44: 548.871 | P44: 349.469 | Q44: 91.639 | R44: 160.091 | S44: 758.363 | T44: 275.451 | U44: 666.551 | V44: 651.716 | W44: 2937.459 | X44: 216.023 | Y44: =IF(OR(Y43="",Y45=""),"",IFERROR(Y43*Y45,"")) | Z44: =IF(OR(Z43="",Z45=""),"",IFERROR(Z43*Z45,"")) | AA44: =IF(OR(AA43="",AA45=""),"",IFERROR(AA43*AA45,"")) | AB44: =IF(OR(AB43="",AB45=""),"",IFERROR(AB43*AB45,"")) | AC44: =IF(OR(AC43="",AC45=""),"",IFERROR(AC43*AC45,""))
A45: 지배주주 순이익률 | B45: MW 기본 100% | C45: =IF(OR(C44="",C43=""),"",IFERROR(C44/C43,"")) | D45: =IF(OR(D44="",D43=""),"",IFERROR(D44/D43,"")) | E45: =IF(OR(E44="",E43=""),"",IFERROR(E44/E43,"")) | F45: =IF(OR(F44="",F43=""),"",IFERROR(F44/F43,"")) | G45: =IF(OR(G44="",G43=""),"",IFERROR(G44/G43,"")) | H45: =IF(OR(H44="",H43=""),"",IFERROR(H44/H43,"")) | I45: =IF(OR(I44="",I43=""),"",IFERROR(I44/I43,"")) | J45: =IF(OR(J44="",J43=""),"",IFERROR(J44/J43,"")) | ... X45: =IF(OR(X44="",X43=""),"",IFERROR(X44/X43,"")) | Y45: 1 | Z45: 1 | AA45: 1 | AB45: 1 | AC45: 1
A46: 목표주가 산출
A47: 현재 주가 (2026.10.26) | B47: 2927
A48: 발행주식수 (보통주) | B48: 41890700
A49: 시가총액 (백만엔) | B49: =IF(OR(B47="",B48=""),"",B47*B48/1000000.0)
A50: OPM | O50: =IF(O17="","",O17) | P50: =IF(P17="","",P17) | Q50: =IF(Q17="","",Q17) | R50: =IF(R17="","",R17) | S50: =IF(S17="","",S17) | T50: =IF(T17="","",T17) | U50: =IF(U17="","",U17) | V50: =IF(V17="","",V17) | ... AC50: =IF(AC17="","",AC17)
A51: 지배주주 순이익 증가율 | P51: =IF(OR(P44="",O44=""),"",IFERROR(P44/O44-1,"")) | Q51: =IF(OR(Q44="",P44=""),"",IFERROR(Q44/P44-1,"")) | R51: =IF(OR(R44="",Q44=""),"",IFERROR(R44/Q44-1,"")) | S51: =IF(OR(S44="",R44=""),"",IFERROR(S44/R44-1,"")) | T51: =IF(OR(T44="",S44=""),"",IFERROR(T44/S44-1,"")) | U51: =IF(OR(U44="",T44=""),"",IFERROR(U44/T44-1,"")) | V51: =IF(OR(V44="",U44=""),"",IFERROR(V44/U44-1,"")) | W51: =IF(OR(W44="",V44=""),"",IFERROR(W44/V44-1,"")) | ... AC51: =IF(OR(AC44="",AB44=""),"",IFERROR(AC44/AB44-1,""))
A52: P/E (현재 주가) | B52: 시총 ÷ 지배순이익 | X52: =IF(OR($B$49="",X44=""),"",IFERROR($B$49/X44,"")) | Y52: =IF(OR($B$49="",Y44=""),"",IFERROR($B$49/Y44,"")) | Z52: =IF(OR($B$49="",Z44=""),"",IFERROR($B$49/Z44,"")) | AA52: =IF(OR($B$49="",AA44=""),"",IFERROR($B$49/AA44,"")) | AB52: =IF(OR($B$49="",AB44=""),"",IFERROR($B$49/AB44,"")) | AC52: =IF(OR($B$49="",AC44=""),"",IFERROR($B$49/AC44,""))
A53: Target P/E | B53: 직접 입력
A54: EPS | B54: 지배순이익 ÷ 주식수 | O54: =IF(OR(O44="",$B$48=""),"",IFERROR(O44*1000000.0/$B$48,"")) | P54: =IF(OR(P44="",$B$48=""),"",IFERROR(P44*1000000.0/$B$48,"")) | Q54: =IF(OR(Q44="",$B$48=""),"",IFERROR(Q44*1000000.0/$B$48,"")) | R54: =IF(OR(R44="",$B$48=""),"",IFERROR(R44*1000000.0/$B$48,"")) | S54: =IF(OR(S44="",$B$48=""),"",IFERROR(S44*1000000.0/$B$48,"")) | T54: =IF(OR(T44="",$B$48=""),"",IFERROR(T44*1000000.0/$B$48,"")) | U54: =IF(OR(U44="",$B$48=""),"",IFERROR(U44*1000000.0/$B$48,"")) | V54: =IF(OR(V44="",$B$48=""),"",IFERROR(V44*1000000.0/$B$48,"")) | ... AC54: =IF(OR(AC44="",$B$48=""),"",IFERROR(AC44*1000000.0/$B$48,""))
A55: 목표주가 | Y55: =IF(OR(Y54="",Y53=""),"",IFERROR(Y54*Y53,"")) | Z55: =IF(OR(Z54="",Z53=""),"",IFERROR(Z54*Z53,"")) | AA55: =IF(OR(AA54="",AA53=""),"",IFERROR(AA54*AA53,"")) | AB55: =IF(OR(AB54="",AB53=""),"",IFERROR(AB54*AB53,"")) | AC55: =IF(OR(AC54="",AC53=""),"",IFERROR(AC54*AC53,""))
A56: 상승여력 | Y56: =IF(OR(Y55="",$B$47=""),"",IFERROR(Y55/$B$47-1,"")) | Z56: =IF(OR(Z55="",$B$47=""),"",IFERROR(Z55/$B$47-1,"")) | AA56: =IF(OR(AA55="",$B$47=""),"",IFERROR(AA55/$B$47-1,"")) | AB56: =IF(OR(AB55="",$B$47=""),"",IFERROR(AB55/$B$47-1,"")) | AC56: =IF(OR(AC55="",$B$47=""),"",IFERROR(AC55/$B$47-1,""))
A57: 자산가치 산출 | B57: 최신 분기 BS
A58: 현금및현금성자산 | X58: ='재무상태표'!G6 | Y58: ='재무상태표'!G6 | Z58: ='재무상태표'!G6 | AA58: ='재무상태표'!G6 | AB58: ='재무상태표'!G6 | AC58: ='재무상태표'!G6
A59: 단기금융상품 | X59: ='재무상태표'!G7 | Y59: ='재무상태표'!G7 | Z59: ='재무상태표'!G7 | AA59: ='재무상태표'!G7 | AB59: ='재무상태표'!G7 | AC59: ='재무상태표'!G7
A60: 투자부동산 | X60: ='재무상태표'!G14 | Y60: ='재무상태표'!G14 | Z60: ='재무상태표'!G14 | AA60: ='재무상태표'!G14 | AB60: ='재무상태표'!G14 | AC60: ='재무상태표'!G14
A61: 지배자본 | X61: ='재무상태표'!G31 | Y61: ='재무상태표'!G31 | Z61: ='재무상태표'!G31 | AA61: ='재무상태표'!G31 | AB61: ='재무상태표'!G31 | AC61: ='재무상태표'!G31
A62: 부채 | X62: ='재무상태표'!G27 | Y62: ='재무상태표'!G27 | Z62: ='재무상태표'!G27 | AA62: ='재무상태표'!G27 | AB62: ='재무상태표'!G27 | AC62: ='재무상태표'!G27
A63: 부채비율 | X63: =IF(OR(X62="",X61=""),"",IFERROR(X62/X61,"")) | Y63: =IF(OR(Y62="",Y61=""),"",IFERROR(Y62/Y61,"")) | Z63: =IF(OR(Z62="",Z61=""),"",IFERROR(Z62/Z61,"")) | AA63: =IF(OR(AA62="",AA61=""),"",IFERROR(AA62/AA61,"")) | AB63: =IF(OR(AB62="",AB61=""),"",IFERROR(AB62/AB61,"")) | AC63: =IF(OR(AC62="",AC61=""),"",IFERROR(AC62/AC61,""))
A64: 자산가치 | B64: 현금+단기금융+투자부동산 | X64: =SUM(X58,X59,X60) | Y64: =SUM(Y58,Y59,Y60) | Z64: =SUM(Z58,Z59,Z60) | AA64: =SUM(AA58,AA59,AA60) | AB64: =SUM(AB58,AB59,AB60) | AC64: =SUM(AC58,AC59,AC60)
A65: 기업가치 산출
A66: 목표 시가총액 (P/E) | B66: 지배순이익 × Target P/E | Y66: =IF(OR(Y44="",Y53=""),"",IFERROR(Y44*Y53,"")) | Z66: =IF(OR(Z44="",Z53=""),"",IFERROR(Z44*Z53,"")) | AA66: =IF(OR(AA44="",AA53=""),"",IFERROR(AA44*AA53,"")) | AB66: =IF(OR(AB44="",AB53=""),"",IFERROR(AB44*AB53,"")) | AC66: =IF(OR(AC44="",AC53=""),"",IFERROR(AC44*AC53,""))
A67: 기업가치 | B67: 목표시총 + 자산가치 | Y67: =IF(OR(Y66=""),"",IFERROR(Y66+Y64,"")) | Z67: =IF(OR(Z66=""),"",IFERROR(Z66+Z64,"")) | AA67: =IF(OR(AA66=""),"",IFERROR(AA66+AA64,"")) | AB67: =IF(OR(AB66=""),"",IFERROR(AB66+AB64,"")) | AC67: =IF(OR(AC66=""),"",IFERROR(AC66+AC64,""))
A68: 현재 시가총액 | Y68: =$B$49 | Z68: =$B$49 | AA68: =$B$49 | AB68: =$B$49 | AC68: =$B$49
A69: 상승여력 | Y69: =IF(OR(Y67="",Y68=""),"",IFERROR(Y67/Y68-1,"")) | Z69: =IF(OR(Z67="",Z68=""),"",IFERROR(Z67/Z68-1,"")) | AA69: =IF(OR(AA67="",AA68=""),"",IFERROR(AA67/AA68-1,"")) | AB69: =IF(OR(AB67="",AB68=""),"",IFERROR(AB67/AB68-1,"")) | AC69: =IF(OR(AC67="",AC68=""),"",IFERROR(AC67/AC68-1,""))
A71: 출처
A72: 결산단신 XBRL(TDnet·JPX 보관소) — 쓴 문서는 '출처' 시트
A73: 분기 = 누계에서 앞 분기를 뺀 3개월 값
A74: 주가: 야후 파이낸스 일봉 2026.10.26
A76: 손익계산서 · 전 항목 | B76: 분기 = 3개월 단독
A77: 항목 | B77: 참고 | C77: 2024.2Q | D77: 2024.3Q | E77: 2024.4Q | F77: 2025.1Q | G77: 2025.2Q | H77: 2025.3Q | I77: 2025.4Q | J77: 2026.1Q | K77: 2026.2Q | L77: 2026.3Q | M77: 2026.4Q | N77: 2027.1Q | O77: 2017 | P77: 2018 | Q77: 2019 | R77: 2020 | S77: 2021 | T77: 2022 | U77: 2023 | V77: 2024 | W77: 2025 | X77: 2026 | Y77: 2027(MW) | Z77: 2028(MW) | AA77: 2029(MW) | AB77: 2030(MW) | AC77: 2031(MW)
A78: 매출액 | C78: 5237.51 | D78: 5315.83 | E78: 6167.796 | F78: 5935.785 | G78: 7335.885 | H78: 8125.387 | I78: 10015.325 | J78: 7492.152 | K78: 8139.01 | L78: 8393.405 | M78: 11277.082 | N78: 11134.597 | T78: 5396.722 | U78: 5578.95 | V78: 6167.796 | W78: 10015.325 | X78: 11277.082
A79: YoY | B79: 전년 같은 분기·전년 대비 | G79: =IF(OR(G78="",C78=""),"",IF(C78<=0,"",IFERROR(G78/C78-1,""))) | H79: =IF(OR(H78="",D78=""),"",IF(D78<=0,"",IFERROR(H78/D78-1,""))) | I79: =IF(OR(I78="",E78=""),"",IF(E78<=0,"",IFERROR(I78/E78-1,""))) | J79: =IF(OR(J78="",F78=""),"",IF(F78<=0,"",IFERROR(J78/F78-1,""))) | K79: =IF(OR(K78="",G78=""),"",IF(G78<=0,"",IFERROR(K78/G78-1,""))) | L79: =IF(OR(L78="",H78=""),"",IF(H78<=0,"",IFERROR(L78/H78-1,""))) | M79: =IF(OR(M78="",I78=""),"",IF(I78<=0,"",IFERROR(M78/I78-1,""))) | N79: =IF(OR(N78="",J78=""),"",IF(J78<=0,"",IFERROR(N78/J78-1,""))) | T79: =IF(OR(T78="",S78=""),"",IF(S78<=0,"",IFERROR(T78/S78-1,""))) | U79: =IF(OR(U78="",T78=""),"",IF(T78<=0,"",IFERROR(U78/T78-1,""))) | V79: =IF(OR(V78="",U78=""),"",IF(U78<=0,"",IFERROR(V78/U78-1,""))) | W79: =IF(OR(W78="",V78=""),"",IF(V78<=0,"",IFERROR(W78/V78-1,""))) | X79: =IF(OR(X78="",W78=""),"",IF(W78<=0,"",IFERROR(X78/W78-1,"")))
A80: 매출원가 | C80: 3884.069 | D80: 3929.928 | E80: 4457.149 | F80: 4236.884 | G80: 4685.563 | H80: 5159.102 | I80: 6100.555 | J80: 5948.216 | K80: 6534.127 | L80: 6504.314 | M80: 8358.476 | N80: 7713.234 | T80: 4032.635 | U80: 4032.751 | V80: 4457.149 | W80: 6100.555 | X80: 8358.476
A81: 매출총이익 | C81: 1353.442 | D81: 1385.901 | E81: 1710.647 | F81: 1698.9 | G81: 2650.323 | H81: 2966.284 | I81: 3914.771 | J81: 1543.935 | K81: 1604.883 | L81: 1889.092 | M81: 2918.605 | N81: 3421.363 | T81: 1364.087 | U81: 1546.199 | V81: 1710.647 | W81: 3914.771 | X81: 2918.605
A82: YoY | B82: 전년 같은 분기·전년 대비 | G82: =IF(OR(G81="",C81=""),"",IF(C81<=0,"",IFERROR(G81/C81-1,""))) | H82: =IF(OR(H81="",D81=""),"",IF(D81<=0,"",IFERROR(H81/D81-1,""))) | I82: =IF(OR(I81="",E81=""),"",IF(E81<=0,"",IFERROR(I81/E81-1,""))) | J82: =IF(OR(J81="",F81=""),"",IF(F81<=0,"",IFERROR(J81/F81-1,""))) | K82: =IF(OR(K81="",G81=""),"",IF(G81<=0,"",IFERROR(K81/G81-1,""))) | L82: =IF(OR(L81="",H81=""),"",IF(H81<=0,"",IFERROR(L81/H81-1,""))) | M82: =IF(OR(M81="",I81=""),"",IF(I81<=0,"",IFERROR(M81/I81-1,""))) | N82: =IF(OR(N81="",J81=""),"",IF(J81<=0,"",IFERROR(N81/J81-1,""))) | T82: =IF(OR(T81="",S81=""),"",IF(S81<=0,"",IFERROR(T81/S81-1,""))) | U82: =IF(OR(U81="",T81=""),"",IF(T81<=0,"",IFERROR(U81/T81-1,""))) | V82: =IF(OR(V81="",U81=""),"",IF(U81<=0,"",IFERROR(V81/U81-1,""))) | W82: =IF(OR(W81="",V81=""),"",IF(V81<=0,"",IFERROR(W81/V81-1,""))) | X82: =IF(OR(X81="",W81=""),"",IF(W81<=0,"",IFERROR(X81/W81-1,"")))
A83: 대손충당금 전입 | C83: 0.577 | D83: 0.316 | E83: -0.49 | F83: 0.984 | G83: 0.332 | H83: 0.345 | I83: 1.108 | J83: 1.976 | K83: -0.201 | L83: 3.618 | M83: 0.505 | N83: 0.043 | T83: 0.005 | U83: -1.174 | V83: -0.49 | W83: 1.108 | X83: 0.505
A84: 급여·수당 | C84: 352.304 | D84: 490.886 | E84: 368.378 | F84: 453.048 | G84: 465.006 | H84: 656.981 | I84: 607.722 | J84: 615.433 | K84: 679.801 | L84: 925.864 | M84: 715.853 | N84: 796.379 | T84: 289.519 | U84: 328.029 | V84: 368.378 | W84: 607.722 | X84: 715.853
A85: 상여충당금 전입 | C85: 78.821 | D85: -59.454 | E85: 67.704 | F85: 92.941 | G85: 88.996 | H85: -70.35 | I85: 178.681 | J85: 124.814 | K85: 162.47 | L85: -129.591 | M85: 179.255 | N85: 159.367 | T85: 61.683 | U85: 69.192 | V85: 67.704 | W85: 178.681 | X85: 179.255
A86: 임원 퇴직위로 충당금 전입 | F86: 0 | G86: 0 | H86: 0 | I86: 50.638 | J86: 12.802 | K86: 2.446 | L86: 2.446 | M86: 2.447 | N86: 14.446 | W86: 50.638 | X86: 2.447
A87: 퇴직급여비용 | H87: 0 | I87: 30 | J87: 0 | K87: 1.5 | L87: 0.75 | M87: 0.8 | N87: 0.9 | W87: 30 | X87: 0.8
A88: 지급수수료 | F88: 305.837 | G88: 356.703 | H88: 361.766 | I88: 432.686 | J88: 450.458 | K88: 361.404 | L88: 385.465 | M88: 413.389 | N88: 330.858 | W88: 432.686 | X88: 413.389
A89: 기타 | C89: 776.659 | D89: 755.061 | E89: -429.901 | F89: 614.321 | G89: 675.165 | H89: 728.013 | I89: 714.141 | J89: 795.621 | K89: 861.106 | L89: 897.207 | M89: 515.975 | N89: 888.688 | T89: -461.657 | U89: -383.781 | V89: -429.901 | W89: 714.141 | X89: 515.975
A90: 판매비와 관리비 합계 | C90: 1208.361 | D90: 1186.81 | E90: 1274.723 | F90: 1467.133 | G90: 1586.202 | H90: 1676.755 | I90: 2354.602 | J90: 2001.106 | K90: 2068.527 | L90: 2085.757 | M90: 2204.78 | N90: 2190.684 | T90: 1039.892 | U90: 1147.174 | V90: 1274.723 | W90: 2354.602 | X90: 2204.78
A91: 영업이익(손실) | C91: 145.081 | D91: 199.092 | E91: 435.923 | F91: 231.767 | G91: 1064.12 | H91: 1289.53 | I91: 1560.169 | J91: -457.171 | K91: -463.644 | L91: -196.665 | M91: 713.826 | N91: 1230.678 | T91: 324.195 | U91: 399.025 | V91: 435.923 | W91: 1560.169 | X91: 713.826
A92: OPM | B92: 영업이익 ÷ 매출 | C92: =IF(OR(C91="",C78=""),"",IF(C78<=0,"",IFERROR(C91/C78,""))) | D92: =IF(OR(D91="",D78=""),"",IF(D78<=0,"",IFERROR(D91/D78,""))) | E92: =IF(OR(E91="",E78=""),"",IF(E78<=0,"",IFERROR(E91/E78,""))) | F92: =IF(OR(F91="",F78=""),"",IF(F78<=0,"",IFERROR(F91/F78,""))) | G92: =IF(OR(G91="",G78=""),"",IF(G78<=0,"",IFERROR(G91/G78,""))) | H92: =IF(OR(H91="",H78=""),"",IF(H78<=0,"",IFERROR(H91/H78,""))) | I92: =IF(OR(I91="",I78=""),"",IF(I78<=0,"",IFERROR(I91/I78,""))) | J92: =IF(OR(J91="",J78=""),"",IF(J78<=0,"",IFERROR(J91/J78,""))) | ... N92: =IF(OR(N91="",N78=""),"",IF(N78<=0,"",IFERROR(N91/N78,""))) | T92: =IF(OR(T91="",T78=""),"",IF(T78<=0,"",IFERROR(T91/T78,""))) | U92: =IF(OR(U91="",U78=""),"",IF(U78<=0,"",IFERROR(U91/U78,""))) | V92: =IF(OR(V91="",V78=""),"",IF(V78<=0,"",IFERROR(V91/V78,""))) | W92: =IF(OR(W91="",W78=""),"",IF(W78<=0,"",IFERROR(W91/W78,""))) | X92: =IF(OR(X91="",X78=""),"",IF(X78<=0,"",IFERROR(X91/X78,"")))
A93: YoY | B93: 전년 같은 분기·전년 대비 | G93: =IF(OR(G91="",C91=""),"",IF(C91<=0,"",IFERROR(G91/C91-1,""))) | H93: =IF(OR(H91="",D91=""),"",IF(D91<=0,"",IFERROR(H91/D91-1,""))) | I93: =IF(OR(I91="",E91=""),"",IF(E91<=0,"",IFERROR(I91/E91-1,""))) | J93: =IF(OR(J91="",F91=""),"",IF(F91<=0,"",IFERROR(J91/F91-1,""))) | K93: =IF(OR(K91="",G91=""),"",IF(G91<=0,"",IFERROR(K91/G91-1,""))) | L93: =IF(OR(L91="",H91=""),"",IF(H91<=0,"",IFERROR(L91/H91-1,""))) | M93: =IF(OR(M91="",I91=""),"",IF(I91<=0,"",IFERROR(M91/I91-1,""))) | N93: =IF(OR(N91="",J91=""),"",IF(J91<=0,"",IFERROR(N91/J91-1,""))) | T93: =IF(OR(T91="",S91=""),"",IF(S91<=0,"",IFERROR(T91/S91-1,""))) | U93: =IF(OR(U91="",T91=""),"",IF(T91<=0,"",IFERROR(U91/T91-1,""))) | V93: =IF(OR(V91="",U91=""),"",IF(U91<=0,"",IFERROR(V91/U91-1,""))) | W93: =IF(OR(W91="",V91=""),"",IF(V91<=0,"",IFERROR(W91/V91-1,""))) | X93: =IF(OR(X91="",W91=""),"",IF(W91<=0,"",IFERROR(X91/W91-1,"")))
A94: 이자수익 | C94: 0.012 | D94: 0.011 | E94: 0.102 | F94: 1.467 | G94: 0.3 | H94: 1.04 | I94: 14.487 | J94: 0.994 | K94: 24.108 | L94: 9.543 | M94: 11.689 | N94: 14.507 | T94: 0.021 | U94: 0.015 | V94: 0.102 | W94: 14.487 | X94: 11.689
A95: 지분법이익 | C95: 0 | D95: 0 | E95: 0 | F95: 0 | G95: 0 | H95: 19.571 | I95: 6.642 | J95: 37.234 | K95: 3.122 | L95: 18.229 | M95: 18.686 | N95: 51.464 | T95: 4.56 | U95: -4.654 | V95: 0 | W95: 6.642 | X95: 18.686
A96: 대손충당금 환입 | C96: 0.081 | D96: -0.01 | E96: -0.182 | F96: 0.317 | G96: 0.079 | H96: 0.097 | I96: 0.053 | J96: 0 | K96: 0 | L96: 0 | M96: 0 | T96: -0.364 | U96: -0.274 | V96: -0.182 | W96: 0.053 | X96: 0
A97: 업무수탁료 | E97: 3.575 | U97: 4.115 | V97: 3.575
A98: 암호자산 매각이익 | C98: 0 | D98: 0
A99: Temporary Transfer Charges Income NOI | C99: 3.234 | D99: 2.89 | E99: 1.869 | T99: 5.412 | U99: 4.684 | V99: 1.869
A100: 보조금 수입 | C100: 0 | D100: 0 | E100: 9.495 | F100: 25.292 | G100: 20.066 | H100: 51.59 | I100: 63.831 | J100: 92.321 | K100: 170.64 | L100: 259.205 | M100: 95.462 | N100: 137.969 | V100: 9.495 | W100: 63.831 | X100: 95.462
A101: 기타 | C101: 14.989 | D101: 7.782 | E101: -14.155 | F101: 19.502 | G101: 8.899 | H101: 56.6 | I101: -33.707 | J101: 18.979 | K101: 25.601 | L101: 40.204 | M101: -13.139 | N101: 22.532 | T101: -11.388 | U101: -10.132 | V101: -14.155 | W101: -33.707 | X101: -13.139
A102: 영업외수익 합계 | C102: 15.082 | D102: 7.783 | E102: 91.265 | F102: 46.58 | G102: 29.343 | H102: 128.899 | I102: 92.161 | J102: 149.528 | K102: 223.472 | L102: 327.182 | M102: 363.977 | N102: 226.474 | T102: 25.772 | U102: -0.032 | V102: 91.265 | W102: 92.161 | X102: 363.977
...

Sheet 재무상태표
A1: 3778 재무상태표
A2: 재무비율은 기말 잔액 기준 · 분기 손익은 최근 4분기 합산(TTM) | B2: (단위: 백만엔)
A3: 항목 | B3: 참고 | C3: 2026.1Q | D3: 2026.2Q | E3: 2026.3Q | F3: 2026.4Q | G3: 2027.1Q | H3: 2022 | I3: 2023 | J3: 2024 | K3: 2025 | L3: 2026
A4: 자산
A5: 유동자산 | C5: 33697.89 | D5: 19694.627 | E5: 22089.296 | F5: 26255.316 | G5: 29074.46 | H5: 9776.159 | I5: 8930.987 | J5: 10574.2 | K5: 41744.592 | L5: 26255.316
A6: 현금및현금성자산 | C6: 24254.781 | D6: 10780.435 | E6: 12242.841 | F6: 15391.081 | G6: 17271.165 | H6: 5452.592 | I6: 4810.628 | J6: 5257.805 | K6: 29489.223 | L6: 15391.081
A7: 단기금융상품
A8: 매출채권 | C8: 2838.646 | D8: 2737.055 | E8: 3209.464 | F8: 4813.239 | G8: 4876.587 | H8: 2700.19 | I8: 2392.419 | J8: 3241.165 | K8: 7577.863 | L8: 4813.239
A9: 재고자산 | C9: 517.375 | D9: 441.675 | E9: 1022.395 | F9: 1021.882 | G9: 505.42 | H9: 702.027 | I9: 540.025 | J9: 525.061 | K9: 532.572 | L9: 1021.882
A10: 기타유동자산 | B10: 총계 − 위 항목 | C10: =IF(OR(C5=""),"",IFERROR(C5-SUM(C6,C7,C8,C9),"")) | D10: =IF(OR(D5=""),"",IFERROR(D5-SUM(D6,D7,D8,D9),"")) | E10: =IF(OR(E5=""),"",IFERROR(E5-SUM(E6,E7,E8,E9),"")) | F10: =IF(OR(F5=""),"",IFERROR(F5-SUM(F6,F7,F8,F9),"")) | G10: =IF(OR(G5=""),"",IFERROR(G5-SUM(G6,G7,G8,G9),"")) | H10: =IF(OR(H5=""),"",IFERROR(H5-SUM(H6,H7,H8,H9),"")) | I10: =IF(OR(I5=""),"",IFERROR(I5-SUM(I6,I7,I8,I9),"")) | J10: =IF(OR(J5=""),"",IFERROR(J5-SUM(J6,J7,J8,J9),"")) | ... L10: =IF(OR(L5=""),"",IFERROR(L5-SUM(L6,L7,L8,L9),""))
A11: 비유동자산 | C11: 47303.133 | D11: 60565.398 | E11: 60529.567 | F11: 56195.76 | G11: 58471.666 | H11: 18620.168 | I11: 17325.122 | J11: 19650.247 | K11: 39674.878 | L11: 56195.76
A12: 유형자산 | C12: 37880.622 | D12: 51190.946 | E12: 51214.577 | F12: 46722.502 | G12: 48894.327 | H12: 15725.557 | I12: 14716.102 | J12: 16656.693 | K12: 33469.545 | L12: 46722.502
A13: 무형자산 | C13: 1403.956 | D13: 1565.479 | E13: 1831.062 | F13: 2018.177 | G13: 2109.37 | H13: 426.342 | I13: 508.025 | J13: 505.262 | K13: 1259.893 | L13: 2018.177
A14: 투자부동산
A15: 기타비유동자산 | B15: 총계 − 위 항목 | C15: =IF(OR(C11=""),"",IFERROR(C11-SUM(C12,C13,C14),"")) | D15: =IF(OR(D11=""),"",IFERROR(D11-SUM(D12,D13,D14),"")) | E15: =IF(OR(E11=""),"",IFERROR(E11-SUM(E12,E13,E14),"")) | F15: =IF(OR(F11=""),"",IFERROR(F11-SUM(F12,F13,F14),"")) | G15: =IF(OR(G11=""),"",IFERROR(G11-SUM(G12,G13,G14),"")) | H15: =IF(OR(H11=""),"",IFERROR(H11-SUM(H12,H13,H14),"")) | I15: =IF(OR(I11=""),"",IFERROR(I11-SUM(I12,I13,I14),"")) | J15: =IF(OR(J11=""),"",IFERROR(J11-SUM(J12,J13,J14),"")) | ... L15: =IF(OR(L11=""),"",IFERROR(L11-SUM(L12,L13,L14),""))
A16: 자산총계 | C16: 81001.024 | D16: 80260.025 | E16: 82618.864 | F16: 82451.076 | G16: 87546.127 | H16: 28396.327 | I16: 26256.109 | J16: 30224.447 | K16: 81419.47 | L16: 82451.076
A17: 부채
A18: 유동부채 | C18: 37750.942 | D18: 34194.632 | E18: 34799.76 | F18: 33854.933 | G18: 36915.473 | H18: 11309.298 | I18: 9840.514 | J18: 10598.366 | K18: 40347.49 | L18: 33854.933
A19: 매입채무 | C19: 607.006 | D19: 660.93 | E19: 816.725 | F19: 1245.523 | G19: 554.71 | H19: 1613.404 | I19: 917.034 | J19: 628.323 | K19: 1675.464 | L19: 1245.523
A20: 단기차입금 | C20: 6741.667 | D20: 10675.668 | E20: 8255 | F20: 10687 | G20: 14742 | H20: 1451 | I20: 320 | J20: 417.668 | K20: 9261.668 | L20: 10687
A21: 유동성장기부채 | C21: 2668.38 | D21: 3657.66 | E21: 5323.383 | F21: 4796.832 | G21: 4242.518 | H21: 918.082 | I21: 813.183 | J21: 740.21 | K21: 2649.408 | L21: 4796.832
A22: 기타유동부채 | B22: 총계 − 위 항목 | C22: =IF(OR(C18=""),"",IFERROR(C18-SUM(C19,C20,C21),"")) | D22: =IF(OR(D18=""),"",IFERROR(D18-SUM(D19,D20,D21),"")) | E22: =IF(OR(E18=""),"",IFERROR(E18-SUM(E19,E20,E21),"")) | F22: =IF(OR(F18=""),"",IFERROR(F18-SUM(F19,F20,F21),"")) | G22: =IF(OR(G18=""),"",IFERROR(G18-SUM(G19,G20,G21),"")) | H22: =IF(OR(H18=""),"",IFERROR(H18-SUM(H19,H20,H21),"")) | I22: =IF(OR(I18=""),"",IFERROR(I18-SUM(I19,I20,I21),"")) | J22: =IF(OR(J18=""),"",IFERROR(J18-SUM(J19,J20,J21),"")) | ... L22: =IF(OR(L18=""),"",IFERROR(L18-SUM(L19,L20,L21),""))
A23: 비유동부채 | C23: 13430.972 | D23: 16453.494 | E23: 18244.036 | F23: 18266.988 | G23: 19641.134 | H23: 8637.099 | I23: 7929.456 | J23: 10304.872 | K23: 10814.598 | L23: 18266.988
A24: 장기차입금 | C24: 2542.612 | D24: 4917.091 | E24: 6553.073 | F24: 5777.396 | G24: 5067.428 | H24: 3475.436 | I24: 2662.253 | J24: 3617.408 | K24: 3154.471 | L24: 5777.396
A25: 사채
A26: 기타비유동부채 | B26: 총계 − 위 항목 | C26: =IF(OR(C23=""),"",IFERROR(C23-SUM(C24,C25),"")) | D26: =IF(OR(D23=""),"",IFERROR(D23-SUM(D24,D25),"")) | E26: =IF(OR(E23=""),"",IFERROR(E23-SUM(E24,E25),"")) | F26: =IF(OR(F23=""),"",IFERROR(F23-SUM(F24,F25),"")) | G26: =IF(OR(G23=""),"",IFERROR(G23-SUM(G24,G25),"")) | H26: =IF(OR(H23=""),"",IFERROR(H23-SUM(H24,H25),"")) | I26: =IF(OR(I23=""),"",IFERROR(I23-SUM(I24,I25),"")) | J26: =IF(OR(J23=""),"",IFERROR(J23-SUM(J24,J25),"")) | ... L26: =IF(OR(L23=""),"",IFERROR(L23-SUM(L24,L25),""))
A27: 부채총계 | C27: 51181.915 | D27: 50648.126 | E27: 53043.797 | F27: 52121.922 | G27: 56556.608 | H27: 19946.398 | I27: 17769.97 | J27: 20903.238 | K27: 51162.089 | L27: 52121.922
A28: 총차입금 | B28: 단기+유동성장기+장기+사채 | C28: =SUM(C20,C21,C24,C25) | D28: =SUM(D20,D21,D24,D25) | E28: =SUM(E20,E21,E24,E25) | F28: =SUM(F20,F21,F24,F25) | G28: =SUM(G20,G21,G24,G25) | H28: =SUM(H20,H21,H24,H25) | I28: =SUM(I20,I21,I24,I25) | J28: =SUM(J20,J21,J24,J25) | ... L28: =SUM(L20,L21,L24,L25)
A29: 순차입금 | B29: 음수 = 순현금 | C29: =C28-C6-N(C7) | D29: =D28-D6-N(D7) | E29: =E28-E6-N(E7) | F29: =F28-F6-N(F7) | G29: =G28-G6-N(G7) | H29: =H28-H6-N(H7) | I29: =I28-I6-N(I7) | J29: =J28-J6-N(J7) | ... L29: =L28-L6-N(L7)
A30: 자본
A31: 지배주주지분 | C31: 29611.608 | D31: 29400.315 | E31: 29357.808 | F31: 30101.279 | G31: 30759.997 | H31: 8317.704 | I31: 8348.711 | J31: 9135.003 | K31: 30055.279 | L31: 30101.279
A32: 자본금 | C32: 11283.167 | D32: 11283.167 | E32: 11283.167 | F32: 11283.167 | G32: 11283.167 | H32: 2256.921 | I32: 2256.921 | J32: 2256.921 | K32: 11283.167 | L32: 11283.167
A33: 이익잉여금 | C33: 8692.219 | D33: 8389.835 | E33: 8465.573 | F33: 9232.622 | G33: 9887.088 | H33: 5289.923 | I33: 5847.035 | J33: 6372.974 | K33: 9177.688 | L33: 9232.622
A34: 비지배지분 | C34: 207.501 | D34: 211.584 | E34: 217.259 | F34: 227.875 | G34: 229.521 | H34: 132.225 | I34: 137.428 | J34: 186.206 | K34: 202.102 | L34: 227.875
A35: 자본총계 | C35: 29819.109 | D35: 29611.899 | E35: 29575.067 | F35: 30329.154 | G35: 30989.518 | H35: 8449.929 | I35: 8486.139 | J35: 9321.209 | K35: 30257.381 | L35: 30329.154
A36: 현금흐름 요약 | B36: 분기 = TTM (있을 때만)
A37: 영업활동현금흐름 | F37: 6223.575 | H37: 3957.746 | I37: 3963.42 | J37: 2884.133 | K37: 5787.563 | L37: 6223.575
A38: CAPEX (유·무형 취득) | B38: 양수로 입력 | F38: 37442.946 | H38: 1426.077 | I38: 770.339 | J38: 3618.776 | K38: 18553.763 | L38: 37442.946
A39: FCF | C39: =IF(OR(C37="",C38=""),"",IFERROR(C37-C38,"")) | D39: =IF(OR(D37="",D38=""),"",IFERROR(D37-D38,"")) | E39: =IF(OR(E37="",E38=""),"",IFERROR(E37-E38,"")) | F39: =IF(OR(F37="",F38=""),"",IFERROR(F37-F38,"")) | G39: =IF(OR(G37="",G38=""),"",IFERROR(G37-G38,"")) | H39: =IF(OR(H37="",H38=""),"",IFERROR(H37-H38,"")) | I39: =IF(OR(I37="",I38=""),"",IFERROR(I37-I38,"")) | J39: =IF(OR(J37="",J38=""),"",IFERROR(J37-J38,"")) | ... L39: =IF(OR(L37="",L38=""),"",IFERROR(L37-L38,""))
A40: 배당금 지급 | B40: 양수로 입력 | F40: 161.619 | H40: 108.912 | I40: 109.509 | J40: 125.621 | K40: 124.699 | L40: 161.619
A41: 주요 재무 비율 | B41: 기준 (빨간 글씨 = 미달)
A42: 안정성
A43: 부채비율 | B43: 100%↓ | C43: =IF(OR(C27="",C35=""),"",IFERROR(C27/C35,"")) | D43: =IF(OR(D27="",D35=""),"",IFERROR(D27/D35,"")) | E43: =IF(OR(E27="",E35=""),"",IFERROR(E27/E35,"")) | F43: =IF(OR(F27="",F35=""),"",IFERROR(F27/F35,"")) | G43: =IF(OR(G27="",G35=""),"",IFERROR(G27/G35,"")) | H43: =IF(OR(H27="",H35=""),"",IFERROR(H27/H35,"")) | I43: =IF(OR(I27="",I35=""),"",IFERROR(I27/I35,"")) | J43: =IF(OR(J27="",J35=""),"",IFERROR(J27/J35,"")) | ... L43: =IF(OR(L27="",L35=""),"",IFERROR(L27/L35,""))
A44: 순차입금비율 | B44: 0%↓ 순현금 | C44: =IF(OR(C29="",C35=""),"",IFERROR(C29/C35,"")) | D44: =IF(OR(D29="",D35=""),"",IFERROR(D29/D35,"")) | E44: =IF(OR(E29="",E35=""),"",IFERROR(E29/E35,"")) | F44: =IF(OR(F29="",F35=""),"",IFERROR(F29/F35,"")) | G44: =IF(OR(G29="",G35=""),"",IFERROR(G29/G35,"")) | H44: =IF(OR(H29="",H35=""),"",IFERROR(H29/H35,"")) | I44: =IF(OR(I29="",I35=""),"",IFERROR(I29/I35,"")) | J44: =IF(OR(J29="",J35=""),"",IFERROR(J29/J35,"")) | ... L44: =IF(OR(L29="",L35=""),"",IFERROR(L29/L35,""))
A45: 자기자본비율 | B45: 50%↑ | C45: =IF(OR(C35="",C16=""),"",IFERROR(C35/C16,"")) | D45: =IF(OR(D35="",D16=""),"",IFERROR(D35/D16,"")) | E45: =IF(OR(E35="",E16=""),"",IFERROR(E35/E16,"")) | F45: =IF(OR(F35="",F16=""),"",IFERROR(F35/F16,"")) | G45: =IF(OR(G35="",G16=""),"",IFERROR(G35/G16,"")) | H45: =IF(OR(H35="",H16=""),"",IFERROR(H35/H16,"")) | I45: =IF(OR(I35="",I16=""),"",IFERROR(I35/I16,"")) | J45: =IF(OR(J35="",J16=""),"",IFERROR(J35/J16,"")) | ... L45: =IF(OR(L35="",L16=""),"",IFERROR(L35/L16,""))
A46: 유동비율 | B46: 150%↑ | C46: =IF(OR(C5="",C18=""),"",IFERROR(C5/C18,"")) | D46: =IF(OR(D5="",D18=""),"",IFERROR(D5/D18,"")) | E46: =IF(OR(E5="",E18=""),"",IFERROR(E5/E18,"")) | F46: =IF(OR(F5="",F18=""),"",IFERROR(F5/F18,"")) | G46: =IF(OR(G5="",G18=""),"",IFERROR(G5/G18,"")) | H46: =IF(OR(H5="",H18=""),"",IFERROR(H5/H18,"")) | I46: =IF(OR(I5="",I18=""),"",IFERROR(I5/I18,"")) | J46: =IF(OR(J5="",J18=""),"",IFERROR(J5/J18,"")) | ... L46: =IF(OR(L5="",L18=""),"",IFERROR(L5/L18,""))
A47: 당좌비율 | B47: 100%↑ | C47: =IF(OR(C5="",C18=""),"",IFERROR((C5-N(C9))/C18,"")) | D47: =IF(OR(D5="",D18=""),"",IFERROR((D5-N(D9))/D18,"")) | E47: =IF(OR(E5="",E18=""),"",IFERROR((E5-N(E9))/E18,"")) | F47: =IF(OR(F5="",F18=""),"",IFERROR((F5-N(F9))/F18,"")) | G47: =IF(OR(G5="",G18=""),"",IFERROR((G5-N(G9))/G18,"")) | H47: =IF(OR(H5="",H18=""),"",IFERROR((H5-N(H9))/H18,"")) | I47: =IF(OR(I5="",I18=""),"",IFERROR((I5-N(I9))/I18,"")) | J47: =IF(OR(J5="",J18=""),"",IFERROR((J5-N(J9))/J18,"")) | ... L47: =IF(OR(L5="",L18=""),"",IFERROR((L5-N(L9))/L18,""))
A48: 이자보상배율 | B48: 5x↑ (금융원가 기준) | C48: =IFERROR((IF(COUNT('연간'!G16:J16)<4,"",SUM('연간'!G16:J16)))/(IF(COUNT('연간'!G38:J38)<4,"",SUM('연간'!G38:J38))),"") | D48: =IFERROR((IF(COUNT('연간'!H16:K16)<4,"",SUM('연간'!H16:K16)))/(IF(COUNT('연간'!H38:K38)<4,"",SUM('연간'!H38:K38))),"") | E48: =IFERROR((IF(COUNT('연간'!I16:L16)<4,"",SUM('연간'!I16:L16)))/(IF(COUNT('연간'!I38:L38)<4,"",SUM('연간'!I38:L38))),"") | F48: =IFERROR((IF(COUNT('연간'!J16:M16)<4,"",SUM('연간'!J16:M16)))/(IF(COUNT('연간'!J38:M38)<4,"",SUM('연간'!J38:M38))),"") | G48: =IFERROR((IF(COUNT('연간'!K16:N16)<4,"",SUM('연간'!K16:N16)))/(IF(COUNT('연간'!K38:N38)<4,"",SUM('연간'!K38:N38))),"") | H48: =IFERROR(('연간'!T16)/('연간'!T38),"") | I48: =IFERROR(('연간'!U16)/('연간'!U38),"") | J48: =IFERROR(('연간'!V16)/('연간'!V38),"") | K48: =IFERROR(('연간'!W16)/('연간'!W38),"") | L48: =IFERROR(('연간'!X16)/('연간'!X38),"")
A49: 차입금 상환연수 | B49: 4년↓ (버핏) | C49: =IFERROR(IF((IF(COUNT('연간'!G44:J44)<4,"",SUM('연간'!G44:J44)))<=0,"적자",C28/(IF(COUNT('연간'!G44:J44)<4,"",SUM('연간'!G44:J44)))),"") | D49: =IFERROR(IF((IF(COUNT('연간'!H44:K44)<4,"",SUM('연간'!H44:K44)))<=0,"적자",D28/(IF(COUNT('연간'!H44:K44)<4,"",SUM('연간'!H44:K44)))),"") | E49: =IFERROR(IF((IF(COUNT('연간'!I44:L44)<4,"",SUM('연간'!I44:L44)))<=0,"적자",E28/(IF(COUNT('연간'!I44:L44)<4,"",SUM('연간'!I44:L44)))),"") | F49: =IFERROR(IF((IF(COUNT('연간'!J44:M44)<4,"",SUM('연간'!J44:M44)))<=0,"적자",F28/(IF(COUNT('연간'!J44:M44)<4,"",SUM('연간'!J44:M44)))),"") | G49: =IFERROR(IF((IF(COUNT('연간'!K44:N44)<4,"",SUM('연간'!K44:N44)))<=0,"적자",G28/(IF(COUNT('연간'!K44:N44)<4,"",SUM('연간'!K44:N44)))),"") | H49: =IFERROR(IF(('연간'!T44)<=0,"적자",H28/('연간'!T44)),"") | I49: =IFERROR(IF(('연간'!U44)<=0,"적자",I28/('연간'!U44)),"") | J49: =IFERROR(IF(('연간'!V44)<=0,"적자",J28/('연간'!V44)),"") | K49: =IFERROR(IF(('연간'!W44)<=0,"적자",K28/('연간'!W44)),"") | L49: =IFERROR(IF(('연간'!X44)<=0,"적자",L28/('연간'!X44)),"")
A50: 수익성
A51: ROE | B51: 15%↑ (버핏) | C51: =IFERROR((IF(COUNT('연간'!G44:J44)<4,"",SUM('연간'!G44:J44)))/C31,"") | D51: =IFERROR((IF(COUNT('연간'!H44:K44)<4,"",SUM('연간'!H44:K44)))/D31,"") | E51: =IFERROR((IF(COUNT('연간'!I44:L44)<4,"",SUM('연간'!I44:L44)))/E31,"") | F51: =IFERROR((IF(COUNT('연간'!J44:M44)<4,"",SUM('연간'!J44:M44)))/F31,"") | G51: =IFERROR((IF(COUNT('연간'!K44:N44)<4,"",SUM('연간'!K44:N44)))/G31,"") | H51: =IFERROR(('연간'!T44)/H31,"") | I51: =IFERROR(('연간'!U44)/I31,"") | J51: =IFERROR(('연간'!V44)/J31,"") | K51: =IFERROR(('연간'!W44)/K31,"") | L51: =IFERROR(('연간'!X44)/L31,"")
A52: ROA | B52: 5%↑ | C52: =IFERROR((IF(COUNT('연간'!G43:J43)<4,"",SUM('연간'!G43:J43)))/C16,"") | D52: =IFERROR((IF(COUNT('연간'!H43:K43)<4,"",SUM('연간'!H43:K43)))/D16,"") | E52: =IFERROR((IF(COUNT('연간'!I43:L43)<4,"",SUM('연간'!I43:L43)))/E16,"") | F52: =IFERROR((IF(COUNT('연간'!J43:M43)<4,"",SUM('연간'!J43:M43)))/F16,"") | G52: =IFERROR((IF(COUNT('연간'!K43:N43)<4,"",SUM('연간'!K43:N43)))/G16,"") | H52: =IFERROR(('연간'!T43)/H16,"") | I52: =IFERROR(('연간'!U43)/I16,"") | J52: =IFERROR(('연간'!V43)/J16,"") | K52: =IFERROR(('연간'!W43)/K16,"") | L52: =IFERROR(('연간'!X43)/L16,"")
A53: ROIC | B53: 10%↑ (세후영업이익 기준) | C53: =IFERROR((IF(COUNT('연간'!G16:J16)<4,"",SUM('연간'!G16:J16)))*(1-0.3)/(C35+C29),"") | D53: =IFERROR((IF(COUNT('연간'!H16:K16)<4,"",SUM('연간'!H16:K16)))*(1-0.3)/(D35+D29),"") | E53: =IFERROR((IF(COUNT('연간'!I16:L16)<4,"",SUM('연간'!I16:L16)))*(1-0.3)/(E35+E29),"") | F53: =IFERROR((IF(COUNT('연간'!J16:M16)<4,"",SUM('연간'!J16:M16)))*(1-0.3)/(F35+F29),"") | G53: =IFERROR((IF(COUNT('연간'!K16:N16)<4,"",SUM('연간'!K16:N16)))*(1-0.3)/(G35+G29),"") | H53: =IFERROR(('연간'!T16)*(1-0.3)/(H35+H29),"") | I53: =IFERROR(('연간'!U16)*(1-0.3)/(I35+I29),"") | J53: =IFERROR(('연간'!V16)*(1-0.3)/(J35+J29),"") | K53: =IFERROR(('연간'!W16)*(1-0.3)/(K35+K29),"") | L53: =IFERROR(('연간'!X16)*(1-0.3)/(L35+L29),"")
A54: 매출총이익률 (GPM) | B54: 40%↑ (해자 신호) | C54: =IFERROR((IF(COUNT('연간'!G12:J12)<4,"",SUM('연간'!G12:J12)))/(IF(COUNT('연간'!G4:J4)<4,"",SUM('연간'!G4:J4))),"") | D54: =IFERROR((IF(COUNT('연간'!H12:K12)<4,"",SUM('연간'!H12:K12)))/(IF(COUNT('연간'!H4:K4)<4,"",SUM('연간'!H4:K4))),"") | E54: =IFERROR((IF(COUNT('연간'!I12:L12)<4,"",SUM('연간'!I12:L12)))/(IF(COUNT('연간'!I4:L4)<4,"",SUM('연간'!I4:L4))),"") | F54: =IFERROR((IF(COUNT('연간'!J12:M12)<4,"",SUM('연간'!J12:M12)))/(IF(COUNT('연간'!J4:M4)<4,"",SUM('연간'!J4:M4))),"") | G54: =IFERROR((IF(COUNT('연간'!K12:N12)<4,"",SUM('연간'!K12:N12)))/(IF(COUNT('연간'!K4:N4)<4,"",SUM('연간'!K4:N4))),"") | H54: =IFERROR(('연간'!T12)/('연간'!T4),"") | I54: =IFERROR(('연간'!U12)/('연간'!U4),"") | J54: =IFERROR(('연간'!V12)/('연간'!V4),"") | K54: =IFERROR(('연간'!W12)/('연간'!W4),"") | L54: =IFERROR(('연간'!X12)/('연간'!X4),"")
A55: 영업이익률 (OPM) | B55: 15%↑ | C55: =IFERROR((IF(COUNT('연간'!G16:J16)<4,"",SUM('연간'!G16:J16)))/(IF(COUNT('연간'!G4:J4)<4,"",SUM('연간'!G4:J4))),"") | D55: =IFERROR((IF(COUNT('연간'!H16:K16)<4,"",SUM('연간'!H16:K16)))/(IF(COUNT('연간'!H4:K4)<4,"",SUM('연간'!H4:K4))),"") | E55: =IFERROR((IF(COUNT('연간'!I16:L16)<4,"",SUM('연간'!I16:L16)))/(IF(COUNT('연간'!I4:L4)<4,"",SUM('연간'!I4:L4))),"") | F55: =IFERROR((IF(COUNT('연간'!J16:M16)<4,"",SUM('연간'!J16:M16)))/(IF(COUNT('연간'!J4:M4)<4,"",SUM('연간'!J4:M4))),"") | G55: =IFERROR((IF(COUNT('연간'!K16:N16)<4,"",SUM('연간'!K16:N16)))/(IF(COUNT('연간'!K4:N4)<4,"",SUM('연간'!K4:N4))),"") | H55: =IFERROR(('연간'!T16)/('연간'!T4),"") | I55: =IFERROR(('연간'!U16)/('연간'!U4),"") | J55: =IFERROR(('연간'!V16)/('연간'!V4),"") | K55: =IFERROR(('연간'!W16)/('연간'!W4),"") | L55: =IFERROR(('연간'!X16)/('연간'!X4),"")
A56: 순이익률 | B56: 10%↑ | C56: =IFERROR((IF(COUNT('연간'!G43:J43)<4,"",SUM('연간'!G43:J43)))/(IF(COUNT('연간'!G4:J4)<4,"",SUM('연간'!G4:J4))),"") | D56: =IFERROR((IF(COUNT('연간'!H43:K43)<4,"",SUM('연간'!H43:K43)))/(IF(COUNT('연간'!H4:K4)<4,"",SUM('연간'!H4:K4))),"") | E56: =IFERROR((IF(COUNT('연간'!I43:L43)<4,"",SUM('연간'!I43:L43)))/(IF(COUNT('연간'!I4:L4)<4,"",SUM('연간'!I4:L4))),"") | F56: =IFERROR((IF(COUNT('연간'!J43:M43)<4,"",SUM('연간'!J43:M43)))/(IF(COUNT('연간'!J4:M4)<4,"",SUM('연간'!J4:M4))),"") | G56: =IFERROR((IF(COUNT('연간'!K43:N43)<4,"",SUM('연간'!K43:N43)))/(IF(COUNT('연간'!K4:N4)<4,"",SUM('연간'!K4:N4))),"") | H56: =IFERROR(('연간'!T43)/('연간'!T4),"") | I56: =IFERROR(('연간'!U43)/('연간'!U4),"") | J56: =IFERROR(('연간'!V43)/('연간'!V4),"") | K56: =IFERROR(('연간'!W43)/('연간'!W4),"") | L56: =IFERROR(('연간'!X43)/('연간'!X4),"")
A57: 효율성 (회전율)
A58: 총자산회전율 | B58: 높을수록↑ | C58: =IFERROR((IF(COUNT('연간'!G4:J4)<4,"",SUM('연간'!G4:J4)))/C16,"") | D58: =IFERROR((IF(COUNT('연간'!H4:K4)<4,"",SUM('연간'!H4:K4)))/D16,"") | E58: =IFERROR((IF(COUNT('연간'!I4:L4)<4,"",SUM('연간'!I4:L4)))/E16,"") | F58: =IFERROR((IF(COUNT('연간'!J4:M4)<4,"",SUM('연간'!J4:M4)))/F16,"") | G58: =IFERROR((IF(COUNT('연간'!K4:N4)<4,"",SUM('연간'!K4:N4)))/G16,"") | H58: =IFERROR(('연간'!T4)/H16,"") | I58: =IFERROR(('연간'!U4)/I16,"") | J58: =IFERROR(('연간'!V4)/J16,"") | K58: =IFERROR(('연간'!W4)/K16,"") | L58: =IFERROR(('연간'!X4)/L16,"")
A59: 매출채권회전일수 | B59: 짧을수록↑ | C59: =IFERROR(C8/(IF(COUNT('연간'!G4:J4)<4,"",SUM('연간'!G4:J4)))*365,"") | D59: =IFERROR(D8/(IF(COUNT('연간'!H4:K4)<4,"",SUM('연간'!H4:K4)))*365,"") | E59: =IFERROR(E8/(IF(COUNT('연간'!I4:L4)<4,"",SUM('연간'!I4:L4)))*365,"") | F59: =IFERROR(F8/(IF(COUNT('연간'!J4:M4)<4,"",SUM('연간'!J4:M4)))*365,"") | G59: =IFERROR(G8/(IF(COUNT('연간'!K4:N4)<4,"",SUM('연간'!K4:N4)))*365,"") | H59: =IFERROR(H8/('연간'!T4)*365,"") | I59: =IFERROR(I8/('연간'!U4)*365,"") | J59: =IFERROR(J8/('연간'!V4)*365,"") | K59: =IFERROR(K8/('연간'!W4)*365,"") | L59: =IFERROR(L8/('연간'!X4)*365,"")
A60: 재고자산회전일수 | B60: 짧을수록↑ | C60: =IFERROR(C9/(IF(COUNT('연간'!G11:J11)<4,"",SUM('연간'!G11:J11)))*365,"") | D60: =IFERROR(D9/(IF(COUNT('연간'!H11:K11)<4,"",SUM('연간'!H11:K11)))*365,"") | E60: =IFERROR(E9/(IF(COUNT('연간'!I11:L11)<4,"",SUM('연간'!I11:L11)))*365,"") | F60: =IFERROR(F9/(IF(COUNT('연간'!J11:M11)<4,"",SUM('연간'!J11:M11)))*365,"") | G60: =IFERROR(G9/(IF(COUNT('연간'!K11:N11)<4,"",SUM('연간'!K11:N11)))*365,"") | H60: =IFERROR(H9/('연간'!T11)*365,"") | I60: =IFERROR(I9/('연간'!U11)*365,"") | J60: =IFERROR(J9/('연간'!V11)*365,"") | K60: =IFERROR(K9/('연간'!W11)*365,"") | L60: =IFERROR(L9/('연간'!X11)*365,"")
A61: 매입채무회전일수 | B61: 길수록 유리 | C61: =IFERROR(C19/(IF(COUNT('연간'!G11:J11)<4,"",SUM('연간'!G11:J11)))*365,"") | D61: =IFERROR(D19/(IF(COUNT('연간'!H11:K11)<4,"",SUM('연간'!H11:K11)))*365,"") | E61: =IFERROR(E19/(IF(COUNT('연간'!I11:L11)<4,"",SUM('연간'!I11:L11)))*365,"") | F61: =IFERROR(F19/(IF(COUNT('연간'!J11:M11)<4,"",SUM('연간'!J11:M11)))*365,"") | G61: =IFERROR(G19/(IF(COUNT('연간'!K11:N11)<4,"",SUM('연간'!K11:N11)))*365,"") | H61: =IFERROR(H19/('연간'!T11)*365,"") | I61: =IFERROR(I19/('연간'!U11)*365,"") | J61: =IFERROR(J19/('연간'!V11)*365,"") | K61: =IFERROR(K19/('연간'!W11)*365,"") | L61: =IFERROR(L19/('연간'!X11)*365,"")
A62: 현금전환주기 (CCC) | B62: 짧을수록↑ | C62: =IF(OR(C59="",C60="",C61=""),"",IFERROR(C59+C60-C61,"")) | D62: =IF(OR(D59="",D60="",D61=""),"",IFERROR(D59+D60-D61,"")) | E62: =IF(OR(E59="",E60="",E61=""),"",IFERROR(E59+E60-E61,"")) | F62: =IF(OR(F59="",F60="",F61=""),"",IFERROR(F59+F60-F61,"")) | G62: =IF(OR(G59="",G60="",G61=""),"",IFERROR(G59+G60-G61,"")) | H62: =IF(OR(H59="",H60="",H61=""),"",IFERROR(H59+H60-H61,"")) | I62: =IF(OR(I59="",I60="",I61=""),"",IFERROR(I59+I60-I61,"")) | J62: =IF(OR(J59="",J60="",J61=""),"",IFERROR(J59+J60-J61,"")) | ... L62: =IF(OR(L59="",L60="",L61=""),"",IFERROR(L59+L60-L61,""))
A63: 현금흐름
A64: 영업현금흐름 / 순이익 | B64: 1x↑ (이익의 질) | C64: =IF(C37="","",IFERROR(C37/(IF(COUNT('연간'!G43:J43)<4,"",SUM('연간'!G43:J43))),"")) | D64: =IF(D37="","",IFERROR(D37/(IF(COUNT('연간'!H43:K43)<4,"",SUM('연간'!H43:K43))),"")) | E64: =IF(E37="","",IFERROR(E37/(IF(COUNT('연간'!I43:L43)<4,"",SUM('연간'!I43:L43))),"")) | F64: =IF(F37="","",IFERROR(F37/(IF(COUNT('연간'!J43:M43)<4,"",SUM('연간'!J43:M43))),"")) | G64: =IF(G37="","",IFERROR(G37/(IF(COUNT('연간'!K43:N43)<4,"",SUM('연간'!K43:N43))),"")) | H64: =IF(H37="","",IFERROR(H37/('연간'!T43),"")) | I64: =IF(I37="","",IFERROR(I37/('연간'!U43),"")) | J64: =IF(J37="","",IFERROR(J37/('연간'!V43),"")) | K64: =IF(K37="","",IFERROR(K37/('연간'!W43),"")) | L64: =IF(L37="","",IFERROR(L37/('연간'!X43),""))
A65: FCF 마진 | B65: 5%↑ | C65: =IF(C39="","",IFERROR(C39/(IF(COUNT('연간'!G4:J4)<4,"",SUM('연간'!G4:J4))),"")) | D65: =IF(D39="","",IFERROR(D39/(IF(COUNT('연간'!H4:K4)<4,"",SUM('연간'!H4:K4))),"")) | E65: =IF(E39="","",IFERROR(E39/(IF(COUNT('연간'!I4:L4)<4,"",SUM('연간'!I4:L4))),"")) | F65: =IF(F39="","",IFERROR(F39/(IF(COUNT('연간'!J4:M4)<4,"",SUM('연간'!J4:M4))),"")) | G65: =IF(G39="","",IFERROR(G39/(IF(COUNT('연간'!K4:N4)<4,"",SUM('연간'!K4:N4))),"")) | H65: =IF(H39="","",IFERROR(H39/('연간'!T4),"")) | I65: =IF(I39="","",IFERROR(I39/('연간'!U4),"")) | J65: =IF(J39="","",IFERROR(J39/('연간'!V4),"")) | K65: =IF(K39="","",IFERROR(K39/('연간'!W4),"")) | L65: =IF(L39="","",IFERROR(L39/('연간'!X4),""))
A66: CAPEX / 매출 | B66: 낮을수록↑ (자본 가벼움) | C66: =IF(C38="","",IFERROR(C38/(IF(COUNT('연간'!G4:J4)<4,"",SUM('연간'!G4:J4))),"")) | D66: =IF(D38="","",IFERROR(D38/(IF(COUNT('연간'!H4:K4)<4,"",SUM('연간'!H4:K4))),"")) | E66: =IF(E38="","",IFERROR(E38/(IF(COUNT('연간'!I4:L4)<4,"",SUM('연간'!I4:L4))),"")) | F66: =IF(F38="","",IFERROR(F38/(IF(COUNT('연간'!J4:M4)<4,"",SUM('연간'!J4:M4))),"")) | G66: =IF(G38="","",IFERROR(G38/(IF(COUNT('연간'!K4:N4)<4,"",SUM('연간'!K4:N4))),"")) | H66: =IF(H38="","",IFERROR(H38/('연간'!T4),"")) | I66: =IF(I38="","",IFERROR(I38/('연간'!U4),"")) | J66: =IF(J38="","",IFERROR(J38/('연간'!V4),"")) | K66: =IF(K38="","",IFERROR(K38/('연간'!W4),"")) | L66: =IF(L38="","",IFERROR(L38/('연간'!X4),""))
A67: 배당성향 | B67: 참고 | C67: =IF(C40="","",IFERROR(C40/(IF(COUNT('연간'!G44:J44)<4,"",SUM('연간'!G44:J44))),"")) | D67: =IF(D40="","",IFERROR(D40/(IF(COUNT('연간'!H44:K44)<4,"",SUM('연간'!H44:K44))),"")) | E67: =IF(E40="","",IFERROR(E40/(IF(COUNT('연간'!I44:L44)<4,"",SUM('연간'!I44:L44))),"")) | F67: =IF(F40="","",IFERROR(F40/(IF(COUNT('연간'!J44:M44)<4,"",SUM('연간'!J44:M44))),"")) | G67: =IF(G40="","",IFERROR(G40/(IF(COUNT('연간'!K44:N44)<4,"",SUM('연간'!K44:N44))),"")) | H67: =IF(H40="","",IFERROR(H40/('연간'!T44),"")) | I67: =IF(I40="","",IFERROR(I40/('연간'!U44),"")) | J67: =IF(J40="","",IFERROR(J40/('연간'!V44),"")) | K67: =IF(K40="","",IFERROR(K40/('연간'!W44),"")) | L67: =IF(L40="","",IFERROR(L40/('연간'!X44),""))
A69: 재무상태표 · 전 항목 | B69: 분기 말 잔액
A70: 항목 | B70: 참고 | C70: 2026.1Q | D70: 2026.2Q | E70: 2026.3Q | F70: 2026.4Q | G70: 2027.1Q | H70: 2022 | I70: 2023 | J70: 2024 | K70: 2025 | L70: 2026
A71: 현금 및 예금 | C71: 24254.781 | D71: 10780.435 | E71: 12242.841 | F71: 15391.081 | G71: 17271.165 | H71: 5452.592 | I71: 4810.628 | J71: 5257.805 | K71: 29489.223 | L71: 15391.081
A72: 매출채권 | H72: 2700.19 | I72: 2392.419
A73: 받을어음·매출채권·계약자산 | C73: 2838.646 | D73: 2737.055 | E73: 3209.464 | F73: 4813.239 | G73: 4876.587 | I73: 2392.419 | J73: 3241.165 | K73: 7577.863 | L73: 4813.239
A74: 상품·제품 | C74: 30.244 | D74: 34.058 | E74: 461.792 | F74: 408.039 | G74: 16.057 | H74: 17.179 | I74: 13.384 | J74: 16.747 | K74: 30.845 | L74: 408.039
A75: 재공품 | C75: 18.31 | D75: 5.557 | E75: 37.509 | F75: 59.243 | G75: 31.401 | H75: 32.455 | I75: 0 | J75: 0 | K75: 33.278 | L75: 59.243
A76: 저장품 | C76: 468.821 | D76: 402.06 | E76: 523.094 | F76: 554.6 | G76: 457.962 | H76: 652.393 | I76: 526.641 | J76: 508.314 | K76: 468.449 | L76: 554.6
A77: 기타 | C77: 6105.545 | D77: 5753.726 | E77: 5636.488 | F77: 5051.385 | G77: 6443.651 | H77: 934.809 | I77: 1201.459 | J77: 1564.39 | K77: 4161.356 | L77: 5051.385
A78: 대손충당금 | C78: -18.46 | D78: -18.267 | E78: -21.892 | F78: -22.274 | G78: -22.365 | H78: -13.46 | I78: -13.545 | J78: -14.223 | K78: -16.423 | L78: -22.274
A79: 유동자산 합계 | C79: 33697.89 | D79: 19694.627 | E79: 22089.296 | F79: 26255.316 | G79: 29074.46 | H79: 9776.159 | I79: 8930.987 | J79: 10574.2 | K79: 41744.592 | L79: 26255.316
A80: 건물·구축물(순액) | C80: 9104.167 | D80: 8955.968 | E80: 8816.782 | F80: 9862.442 | G80: 12121.905 | H80: 7457.911 | I80: 6899.139 | J80: 6369.459 | K80: 6282.028 | L80: 9862.442
A81: 공구·기구·비품(순액) | C81: 14404.453 | D81: 26716.302 | E81: 26662.788 | F81: 17950.309 | G81: 16741.156 | H81: 2578.257 | I81: 1981.395 | J81: 2764.895 | K81: 16456.644 | L81: 17950.309
A82: 토지 | F82: 644.731 | H82: 640.139 | I82: 640.139 | J82: 644.731 | K82: 644.731 | L82: 644.731
A83: 리스자산(순액) | C83: 11054.526 | D83: 11894.061 | E83: 12185.318 | F83: 13097.016 | G83: 15167.649 | H83: 5049.248 | I83: 5176.95 | J83: 6841.909 | K83: 7727.951 | L83: 13097.016
A84: 건설중인자산 | F84: 5168.003 | J84: 35.698 | K84: 2358.189 | L84: 5168.003
A85: 기타(순액) | C85: 3317.475 | D85: 3624.613 | E85: 3549.686 | F85: 5812.735 | G85: 4863.616 | H85: 0 | I85: 18.477 | J85: 680.429 | K85: 3002.921 | L85: 5812.735
A86: 유형자산 합계 | C86: 37880.622 | D86: 51190.946 | E86: 51214.577 | F86: 46722.502 | G86: 48894.327 | H86: 15725.557 | I86: 14716.102 | J86: 16656.693 | K86: 33469.545 | L86: 46722.502
A87: 기타 | C87: 1403.956 | D87: 1565.479 | E87: 1831.062 | F87: 2018.177 | G87: 2109.37 | H87: 426.342 | I87: 508.025 | J87: 505.262 | K87: 1259.893 | L87: 2018.177
A88: 무형자산 합계 | C88: 1403.956 | D88: 1565.479 | E88: 1831.062 | F88: 2018.177 | G88: 2109.37 | H88: 426.342 | I88: 508.025 | J88: 505.262 | K88: 1259.893 | L88: 2018.177
A89: 투자유가증권 | F89: 820.74 | H89: 514.835 | I89: 517.935 | J89: 705.099 | K89: 682.27 | L89: 820.74
A90: 장기선급비용 | F90: 4822.678 | K90: 2902.618 | L90: 4822.678
A91: 이연법인세자산 | F91: 1313.522 | H91: 423.199 | I91: 364.355 | J91: 389.653 | K91: 846.556 | L91: 1313.522
A92: 기타 | C92: 8023.827 | D92: 7814.185 | E92: 7489.1 | F92: 7460.084 | G92: 7472.912 | H92: 1536.196 | I92: 1224.427 | J92: 1399.022 | K92: 519.325 | L92: 7460.084
A93: 대손충당금 | C93: -5.272 | D93: -5.212 | E93: -5.172 | F93: -5.004 | G93: -4.944 | H93: -5.964 | I93: -5.724 | J93: -5.484 | K93: -5.332 | L93: -5.004
A94: 투자 및 기타자산 합계 | C94: 8018.554 | D94: 7808.973 | E94: 7483.928 | F94: 7455.08 | G94: 7467.968 | H94: 2468.267 | I94: 2100.994 | J94: 2488.291 | K94: 4945.438 | L94: 7455.08
A95: 비유동자산 합계 | C95: 47303.133 | D95: 60565.398 | E95: 60529.567 | F95: 56195.76 | G95: 58471.666 | H95: 18620.168 | I95: 17325.122 | J95: 19650.247 | K95: 39674.878 | L95: 56195.76
A96: 자산 합계 | C96: 81001.024 | D96: 80260.025 | E96: 82618.864 | F96: 82451.076 | G96: 87546.127 | H96: 28396.327 | I96: 26256.109 | J96: 30224.447 | K96: 81419.47 | L96: 82451.076
A97: 매입채무 | C97: 607.006 | D97: 660.93 | E97: 816.725 | F97: 1245.523 | G97: 554.71 | H97: 1613.404 | I97: 917.034 | J97: 628.323 | K97: 1675.464 | L97: 1245.523
A98: 설비관련 미지급금 | F98: 206.704 | J98: 288.329 | K98: 8920.873 | L98: 206.704
A99: 단기차입금 | C99: 6741.667 | D99: 10675.668 | E99: 8255 | F99: 10687 | G99: 14742 | H99: 1451 | I99: 320 | J99: 417.668 | K99: 9261.668 | L99: 10687
A100: 1년 내 상환 장기차입금 | C100: 2668.38 | D100: 3657.66 | E100: 5323.383 | F100: 4796.832 | G100: 4242.518 | H100: 918.082 | I100: 813.183 | J100: 740.21 | K100: 2649.408 | L100: 4796.832
A101: 리스부채 | F101: 3101.105 | H101: 1196.356 | I101: 1225.371 | J101: 1686.876 | K101: 1928.797 | L101: 3101.105
...

Sheet 출처
A1: 출처 · 쓴 결산단신
A3: 공시일 | B3: 문서 | C3: PDF
A4: 2026-07-28 | B4: 2027년 3월 결산기 1분기 결산단신 | C4: https://www2.jpx.co.jp/disc/37780/140120260728500696.pdf
A5: 2026-04-27 | B5: 2026년 3월 결산기 연간 결산단신 | C5: https://www2.jpx.co.jp/disc/37780/140120260427511113.pdf
A6: 2026-01-30 | B6: 2026년 3월 결산기 3분기 결산단신 | C6: https://www2.jpx.co.jp/disc/37780/140120260129541884.pdf
A7: 2025-10-28 | B7: 2026년 3월 결산기 2분기 결산단신 | C7: https://www2.jpx.co.jp/disc/37780/140120251027579530.pdf
A8: 2025-07-28 | B8: 2026년 3월 결산기 1분기 결산단신 | C8: https://www2.jpx.co.jp/disc/37780/140120250728521679.pdf
A9: 2025-04-28 | B9: 2025년 3월 결산기 연간 결산단신 | C9: https://www2.jpx.co.jp/disc/37780/140120250425523471.pdf
A10: 2025-01-31 | B10: 2025년 3월 결산기 3분기 결산단신 | C10: https://www2.jpx.co.jp/disc/37780/140120250131559289.pdf
A11: 2024-10-28 | B11: 2025년 3월 결산기 2분기 결산단신 | C11: https://www2.jpx.co.jp/disc/37780/140120241028503689.pdf
A12: 2024-07-29 | B12: 2025년 3월 결산기 1분기 결산단신 | C12: https://www2.jpx.co.jp/disc/37780/140120240704544618.pdf
A13: 2024-04-26 | B13: 2024년 3월 결산기 연간 결산단신 | C13: https://www2.jpx.co.jp/disc/37780/140120240416571384.pdf
A14: 2024-01-31 | B14: 2024년 3월 결산기 3분기 결산단신 | C14: https://www2.jpx.co.jp/disc/37780/140120240105511512.pdf
... A24: 2018-04-26 | B24: 연간 결산단신 | C24: https://www2.jpx.co.jp/disc/37780/140120180403404220.pdf
