Workbook

Sheet 연간
A1: 4307 Model
A2: 모를 땐 보수적으로 | B2: (단위: 백만엔) | C2: 3월 결산 · IFRS · 2026.4Q = 2026년 3월 결산기 4분기 | Y2: (추정: 파란 글씨 = 직접 입력)
A3: 항목 | B3: 참고 | C3: 2024.1Q | D3: 2024.2Q | E3: 2024.3Q | F3: 2024.4Q | G3: 2025.1Q | H3: 2025.2Q | I3: 2025.3Q | J3: 2025.4Q | K3: 2026.1Q | L3: 2026.2Q | M3: 2026.3Q | N3: 2026.4Q | O3: 2017 | P3: 2018 | Q3: 2019 | R3: 2020 | S3: 2021 | T3: 2022 | U3: 2023 | V3: 2024 | W3: 2025 | X3: 2026 | Y3: 2027(MW) | Z3: 2028(MW) | AA3: 2029(MW) | AB3: 2030(MW) | AC3: 2031(MW)
A4: 매출액 | B4: MW = 제품 합계 | O4: 424548 | P4: 471488 | Q4: 501243 | R4: 528873 | S4: 550337 | T4: 611634 | U4: 692165 | V4: 736556 | W4: 764813 | X4: 814708 | Y4: =IF(COUNT(Y7,Y10,Y13,Y16)=0,"",SUM(Y7,Y10,Y13,Y16)) | Z4: =IF(COUNT(Z7,Z10,Z13,Z16)=0,"",SUM(Z7,Z10,Z13,Z16)) | AA4: =IF(COUNT(AA7,AA10,AA13,AA16)=0,"",SUM(AA7,AA10,AA13,AA16)) | AB4: =IF(COUNT(AB7,AB10,AB13,AB16)=0,"",SUM(AB7,AB10,AB13,AB16)) | AC4: =IF(COUNT(AC7,AC10,AC13,AC16)=0,"",SUM(AC7,AC10,AC13,AC16))
A5: YoY | G5: =IF(OR(G4="",C4=""),"",IFERROR(G4/C4-1,"")) | H5: =IF(OR(H4="",D4=""),"",IFERROR(H4/D4-1,"")) | I5: =IF(OR(I4="",E4=""),"",IFERROR(I4/E4-1,"")) | J5: =IF(OR(J4="",F4=""),"",IFERROR(J4/F4-1,"")) | K5: =IF(OR(K4="",G4=""),"",IFERROR(K4/G4-1,"")) | L5: =IF(OR(L4="",H4=""),"",IFERROR(L4/H4-1,"")) | M5: =IF(OR(M4="",I4=""),"",IFERROR(M4/I4-1,"")) | N5: =IF(OR(N4="",J4=""),"",IFERROR(N4/J4-1,"")) | P5: =IF(OR(P4="",O4=""),"",IFERROR(P4/O4-1,"")) | Q5: =IF(OR(Q4="",P4=""),"",IFERROR(Q4/P4-1,"")) | R5: =IF(OR(R4="",Q4=""),"",IFERROR(R4/Q4-1,"")) | S5: =IF(OR(S4="",R4=""),"",IFERROR(S4/R4-1,"")) | T5: =IF(OR(T4="",S4=""),"",IFERROR(T4/S4-1,"")) | U5: =IF(OR(U4="",T4=""),"",IFERROR(U4/T4-1,"")) | V5: =IF(OR(V4="",U4=""),"",IFERROR(V4/U4-1,"")) | W5: =IF(OR(W4="",V4=""),"",IFERROR(W4/V4-1,"")) | ... AC5: =IF(OR(AC4="",AB4=""),"",IFERROR(AC4/AB4-1,""))
A6: 제품별 매출 분류 | B6: 사업보고서 매출실적
A7: Consulting | C7: 10655 | D7: 13092 | E7: 13609 | F7: 14603 | G7: 12579 | H7: 14866 | I7: 16189 | J7: 16699 | K7: 13404 | L7: 15917 | M7: 17154 | N7: 17081 | V7: 51959 | W7: 60333 | X7: 63556
A8: 비중 | C8: =IF(OR(C7="",C4=""),"",IFERROR(C7/C4,"")) | D8: =IF(OR(D7="",D4=""),"",IFERROR(D7/D4,"")) | E8: =IF(OR(E7="",E4=""),"",IFERROR(E7/E4,"")) | F8: =IF(OR(F7="",F4=""),"",IFERROR(F7/F4,"")) | G8: =IF(OR(G7="",G4=""),"",IFERROR(G7/G4,"")) | H8: =IF(OR(H7="",H4=""),"",IFERROR(H7/H4,"")) | I8: =IF(OR(I7="",I4=""),"",IFERROR(I7/I4,"")) | J8: =IF(OR(J7="",J4=""),"",IFERROR(J7/J4,"")) | ... AC8: =IF(OR(AC7="",AC4=""),"",IFERROR(AC7/AC4,""))
A9: YoY | G9: =IF(OR(G7="",C7=""),"",IFERROR(G7/C7-1,"")) | H9: =IF(OR(H7="",D7=""),"",IFERROR(H7/D7-1,"")) | I9: =IF(OR(I7="",E7=""),"",IFERROR(I7/E7-1,"")) | J9: =IF(OR(J7="",F7=""),"",IFERROR(J7/F7-1,"")) | K9: =IF(OR(K7="",G7=""),"",IFERROR(K7/G7-1,"")) | L9: =IF(OR(L7="",H7=""),"",IFERROR(L7/H7-1,"")) | M9: =IF(OR(M7="",I7=""),"",IFERROR(M7/I7-1,"")) | N9: =IF(OR(N7="",J7=""),"",IFERROR(N7/J7-1,"")) | P9: =IF(OR(P7="",O7=""),"",IFERROR(P7/O7-1,"")) | Q9: =IF(OR(Q7="",P7=""),"",IFERROR(Q7/P7-1,"")) | R9: =IF(OR(R7="",Q7=""),"",IFERROR(R7/Q7-1,"")) | S9: =IF(OR(S7="",R7=""),"",IFERROR(S7/R7-1,"")) | T9: =IF(OR(T7="",S7=""),"",IFERROR(T7/S7-1,"")) | U9: =IF(OR(U7="",T7=""),"",IFERROR(U7/T7-1,"")) | V9: =IF(OR(V7="",U7=""),"",IFERROR(V7/U7-1,"")) | W9: =IF(OR(W7="",V7=""),"",IFERROR(W7/V7-1,"")) | ... AC9: =IF(OR(AC7="",AB7=""),"",IFERROR(AC7/AB7-1,""))
A10: Financial ITSolutions | C10: 83408 | D10: 87511 | E10: 89458 | F10: 89495 | G10: 89313 | H10: 90639 | I10: 93066 | J10: 93587 | K10: 109443 | L10: 84104 | M10: 101903 | N10: 104342 | V10: 349872 | W10: 366605 | X10: 399792
A11: 비중 | C11: =IF(OR(C10="",C4=""),"",IFERROR(C10/C4,"")) | D11: =IF(OR(D10="",D4=""),"",IFERROR(D10/D4,"")) | E11: =IF(OR(E10="",E4=""),"",IFERROR(E10/E4,"")) | F11: =IF(OR(F10="",F4=""),"",IFERROR(F10/F4,"")) | G11: =IF(OR(G10="",G4=""),"",IFERROR(G10/G4,"")) | H11: =IF(OR(H10="",H4=""),"",IFERROR(H10/H4,"")) | I11: =IF(OR(I10="",I4=""),"",IFERROR(I10/I4,"")) | J11: =IF(OR(J10="",J4=""),"",IFERROR(J10/J4,"")) | ... AC11: =IF(OR(AC10="",AC4=""),"",IFERROR(AC10/AC4,""))
A12: YoY | G12: =IF(OR(G10="",C10=""),"",IFERROR(G10/C10-1,"")) | H12: =IF(OR(H10="",D10=""),"",IFERROR(H10/D10-1,"")) | I12: =IF(OR(I10="",E10=""),"",IFERROR(I10/E10-1,"")) | J12: =IF(OR(J10="",F10=""),"",IFERROR(J10/F10-1,"")) | K12: =IF(OR(K10="",G10=""),"",IFERROR(K10/G10-1,"")) | L12: =IF(OR(L10="",H10=""),"",IFERROR(L10/H10-1,"")) | M12: =IF(OR(M10="",I10=""),"",IFERROR(M10/I10-1,"")) | N12: =IF(OR(N10="",J10=""),"",IFERROR(N10/J10-1,"")) | P12: =IF(OR(P10="",O10=""),"",IFERROR(P10/O10-1,"")) | Q12: =IF(OR(Q10="",P10=""),"",IFERROR(Q10/P10-1,"")) | R12: =IF(OR(R10="",Q10=""),"",IFERROR(R10/Q10-1,"")) | S12: =IF(OR(S10="",R10=""),"",IFERROR(S10/R10-1,"")) | T12: =IF(OR(T10="",S10=""),"",IFERROR(T10/S10-1,"")) | U12: =IF(OR(U10="",T10=""),"",IFERROR(U10/T10-1,"")) | V12: =IF(OR(V10="",U10=""),"",IFERROR(V10/U10-1,"")) | W12: =IF(OR(W10="",V10=""),"",IFERROR(W10/V10-1,"")) | ... AC12: =IF(OR(AC10="",AB10=""),"",IFERROR(AC10/AB10-1,""))
A13: Industrial ITSolutions | C13: 69426 | D13: 70631 | E13: 69295 | F13: 66571 | G13: 70599 | H13: 67175 | I13: 64674 | J13: 65039 | K13: 54550 | L13: 82486 | M13: 66210 | N13: 67995 | V13: 275923 | W13: 267487 | X13: 271241
A14: 비중 | C14: =IF(OR(C13="",C4=""),"",IFERROR(C13/C4,"")) | D14: =IF(OR(D13="",D4=""),"",IFERROR(D13/D4,"")) | E14: =IF(OR(E13="",E4=""),"",IFERROR(E13/E4,"")) | F14: =IF(OR(F13="",F4=""),"",IFERROR(F13/F4,"")) | G14: =IF(OR(G13="",G4=""),"",IFERROR(G13/G4,"")) | H14: =IF(OR(H13="",H4=""),"",IFERROR(H13/H4,"")) | I14: =IF(OR(I13="",I4=""),"",IFERROR(I13/I4,"")) | J14: =IF(OR(J13="",J4=""),"",IFERROR(J13/J4,"")) | ... AC14: =IF(OR(AC13="",AC4=""),"",IFERROR(AC13/AC4,""))
A15: YoY | G15: =IF(OR(G13="",C13=""),"",IFERROR(G13/C13-1,"")) | H15: =IF(OR(H13="",D13=""),"",IFERROR(H13/D13-1,"")) | I15: =IF(OR(I13="",E13=""),"",IFERROR(I13/E13-1,"")) | J15: =IF(OR(J13="",F13=""),"",IFERROR(J13/F13-1,"")) | K15: =IF(OR(K13="",G13=""),"",IFERROR(K13/G13-1,"")) | L15: =IF(OR(L13="",H13=""),"",IFERROR(L13/H13-1,"")) | M15: =IF(OR(M13="",I13=""),"",IFERROR(M13/I13-1,"")) | N15: =IF(OR(N13="",J13=""),"",IFERROR(N13/J13-1,"")) | P15: =IF(OR(P13="",O13=""),"",IFERROR(P13/O13-1,"")) | Q15: =IF(OR(Q13="",P13=""),"",IFERROR(Q13/P13-1,"")) | R15: =IF(OR(R13="",Q13=""),"",IFERROR(R13/Q13-1,"")) | S15: =IF(OR(S13="",R13=""),"",IFERROR(S13/R13-1,"")) | T15: =IF(OR(T13="",S13=""),"",IFERROR(T13/S13-1,"")) | U15: =IF(OR(U13="",T13=""),"",IFERROR(U13/T13-1,"")) | V15: =IF(OR(V13="",U13=""),"",IFERROR(V13/U13-1,"")) | W15: =IF(OR(W13="",V13=""),"",IFERROR(W13/V13-1,"")) | ... AC15: =IF(OR(AC13="",AB13=""),"",IFERROR(AC13/AB13-1,""))
A16: ITPlatform Services | C16: 12489 | D16: 13339 | E16: 14805 | F16: 14995 | G16: 14745 | H16: 15147 | I16: 16725 | J16: 20424 | K16: 17648 | L16: 18037 | M16: 19216 | N16: 22138 | V16: 55628 | W16: 67041 | X16: 77039
A17: 비중 | C17: =IF(OR(C16="",C4=""),"",IFERROR(C16/C4,"")) | D17: =IF(OR(D16="",D4=""),"",IFERROR(D16/D4,"")) | E17: =IF(OR(E16="",E4=""),"",IFERROR(E16/E4,"")) | F17: =IF(OR(F16="",F4=""),"",IFERROR(F16/F4,"")) | G17: =IF(OR(G16="",G4=""),"",IFERROR(G16/G4,"")) | H17: =IF(OR(H16="",H4=""),"",IFERROR(H16/H4,"")) | I17: =IF(OR(I16="",I4=""),"",IFERROR(I16/I4,"")) | J17: =IF(OR(J16="",J4=""),"",IFERROR(J16/J4,"")) | ... AC17: =IF(OR(AC16="",AC4=""),"",IFERROR(AC16/AC4,""))
A18: YoY | G18: =IF(OR(G16="",C16=""),"",IFERROR(G16/C16-1,"")) | H18: =IF(OR(H16="",D16=""),"",IFERROR(H16/D16-1,"")) | I18: =IF(OR(I16="",E16=""),"",IFERROR(I16/E16-1,"")) | J18: =IF(OR(J16="",F16=""),"",IFERROR(J16/F16-1,"")) | K18: =IF(OR(K16="",G16=""),"",IFERROR(K16/G16-1,"")) | L18: =IF(OR(L16="",H16=""),"",IFERROR(L16/H16-1,"")) | M18: =IF(OR(M16="",I16=""),"",IFERROR(M16/I16-1,"")) | N18: =IF(OR(N16="",J16=""),"",IFERROR(N16/J16-1,"")) | P18: =IF(OR(P16="",O16=""),"",IFERROR(P16/O16-1,"")) | Q18: =IF(OR(Q16="",P16=""),"",IFERROR(Q16/P16-1,"")) | R18: =IF(OR(R16="",Q16=""),"",IFERROR(R16/Q16-1,"")) | S18: =IF(OR(S16="",R16=""),"",IFERROR(S16/R16-1,"")) | T18: =IF(OR(T16="",S16=""),"",IFERROR(T16/S16-1,"")) | U18: =IF(OR(U16="",T16=""),"",IFERROR(U16/T16-1,"")) | V18: =IF(OR(V16="",U16=""),"",IFERROR(V16/U16-1,"")) | W18: =IF(OR(W16="",V16=""),"",IFERROR(W16/V16-1,"")) | ... AC18: =IF(OR(AC16="",AB16=""),"",IFERROR(AC16/AB16-1,""))
A19: 매출원가
A20: 전체 매출원가 | O20: 280761 | P20: 311868 | Q20: 336508 | R20: 348006 | S20: 364539 | T20: 395562 | U20: 452336 | V20: 475549 | W20: 489517 | X20: 514556
A21: YoY | G21: =IF(OR(G20="",C20=""),"",IF(C20<=0,"",IFERROR(G20/C20-1,""))) | H21: =IF(OR(H20="",D20=""),"",IF(D20<=0,"",IFERROR(H20/D20-1,""))) | I21: =IF(OR(I20="",E20=""),"",IF(E20<=0,"",IFERROR(I20/E20-1,""))) | J21: =IF(OR(J20="",F20=""),"",IF(F20<=0,"",IFERROR(J20/F20-1,""))) | K21: =IF(OR(K20="",G20=""),"",IF(G20<=0,"",IFERROR(K20/G20-1,""))) | L21: =IF(OR(L20="",H20=""),"",IF(H20<=0,"",IFERROR(L20/H20-1,""))) | M21: =IF(OR(M20="",I20=""),"",IF(I20<=0,"",IFERROR(M20/I20-1,""))) | N21: =IF(OR(N20="",J20=""),"",IF(J20<=0,"",IFERROR(N20/J20-1,""))) | P21: =IF(OR(P20="",O20=""),"",IF(O20<=0,"",IFERROR(P20/O20-1,""))) | Q21: =IF(OR(Q20="",P20=""),"",IF(P20<=0,"",IFERROR(Q20/P20-1,""))) | R21: =IF(OR(R20="",Q20=""),"",IF(Q20<=0,"",IFERROR(R20/Q20-1,""))) | S21: =IF(OR(S20="",R20=""),"",IF(R20<=0,"",IFERROR(S20/R20-1,""))) | T21: =IF(OR(T20="",S20=""),"",IF(S20<=0,"",IFERROR(T20/S20-1,""))) | U21: =IF(OR(U20="",T20=""),"",IF(T20<=0,"",IFERROR(U20/T20-1,""))) | V21: =IF(OR(V20="",U20=""),"",IF(U20<=0,"",IFERROR(V20/U20-1,""))) | W21: =IF(OR(W20="",V20=""),"",IF(V20<=0,"",IFERROR(W20/V20-1,""))) | ... AC21: =IF(OR(AC20="",AB20=""),"",IF(AB20<=0,"",IFERROR(AC20/AB20-1,"")))
A22: 매출총이익 | C22: =IF(OR(C4="",C20=""),"",IFERROR(C4-C20,"")) | D22: =IF(OR(D4="",D20=""),"",IFERROR(D4-D20,"")) | E22: =IF(OR(E4="",E20=""),"",IFERROR(E4-E20,"")) | F22: =IF(OR(F4="",F20=""),"",IFERROR(F4-F20,"")) | G22: =IF(OR(G4="",G20=""),"",IFERROR(G4-G20,"")) | H22: =IF(OR(H4="",H20=""),"",IFERROR(H4-H20,"")) | I22: =IF(OR(I4="",I20=""),"",IFERROR(I4-I20,"")) | J22: =IF(OR(J4="",J20=""),"",IFERROR(J4-J20,"")) | ... X22: =IF(OR(X4="",X20=""),"",IFERROR(X4-X20,""))
A23: GPM | C23: =IF(OR(C22="",C4=""),"",IFERROR(C22/C4,"")) | D23: =IF(OR(D22="",D4=""),"",IFERROR(D22/D4,"")) | E23: =IF(OR(E22="",E4=""),"",IFERROR(E22/E4,"")) | F23: =IF(OR(F22="",F4=""),"",IFERROR(F22/F4,"")) | G23: =IF(OR(G22="",G4=""),"",IFERROR(G22/G4,"")) | H23: =IF(OR(H22="",H4=""),"",IFERROR(H22/H4,"")) | I23: =IF(OR(I22="",I4=""),"",IFERROR(I22/I4,"")) | J23: =IF(OR(J22="",J4=""),"",IFERROR(J22/J4,"")) | ... AC23: =IF(OR(AC22="",AC4=""),"",IFERROR(AC22/AC4,""))
A24: YoY | G24: =IF(OR(G22="",C22=""),"",IF(C22<=0,"",IFERROR(G22/C22-1,""))) | H24: =IF(OR(H22="",D22=""),"",IF(D22<=0,"",IFERROR(H22/D22-1,""))) | I24: =IF(OR(I22="",E22=""),"",IF(E22<=0,"",IFERROR(I22/E22-1,""))) | J24: =IF(OR(J22="",F22=""),"",IF(F22<=0,"",IFERROR(J22/F22-1,""))) | K24: =IF(OR(K22="",G22=""),"",IF(G22<=0,"",IFERROR(K22/G22-1,""))) | L24: =IF(OR(L22="",H22=""),"",IF(H22<=0,"",IFERROR(L22/H22-1,""))) | M24: =IF(OR(M22="",I22=""),"",IF(I22<=0,"",IFERROR(M22/I22-1,""))) | N24: =IF(OR(N22="",J22=""),"",IF(J22<=0,"",IFERROR(N22/J22-1,""))) | P24: =IF(OR(P22="",O22=""),"",IF(O22<=0,"",IFERROR(P22/O22-1,""))) | Q24: =IF(OR(Q22="",P22=""),"",IF(P22<=0,"",IFERROR(Q22/P22-1,""))) | R24: =IF(OR(R22="",Q22=""),"",IF(Q22<=0,"",IFERROR(R22/Q22-1,""))) | S24: =IF(OR(S22="",R22=""),"",IF(R22<=0,"",IFERROR(S22/R22-1,""))) | T24: =IF(OR(T22="",S22=""),"",IF(S22<=0,"",IFERROR(T22/S22-1,""))) | U24: =IF(OR(U22="",T22=""),"",IF(T22<=0,"",IFERROR(U22/T22-1,""))) | V24: =IF(OR(V22="",U22=""),"",IF(U22<=0,"",IFERROR(V22/U22-1,""))) | W24: =IF(OR(W22="",V22=""),"",IF(V22<=0,"",IFERROR(W22/V22-1,""))) | ... AC24: =IF(OR(AC22="",AB22=""),"",IF(AB22<=0,"",IFERROR(AC22/AB22-1,"")))
A25: 판매관리비
A26: 전체 판관비 | O26: 85272 | P26: 94481 | Q26: 93293 | R26: 97688 | S26: 98366 | T26: 113536 | U26: 131580 | V26: 142353 | W26: 144071 | X26: 145642
A27: YoY | G27: =IF(OR(G26="",C26=""),"",IF(C26<=0,"",IFERROR(G26/C26-1,""))) | H27: =IF(OR(H26="",D26=""),"",IF(D26<=0,"",IFERROR(H26/D26-1,""))) | I27: =IF(OR(I26="",E26=""),"",IF(E26<=0,"",IFERROR(I26/E26-1,""))) | J27: =IF(OR(J26="",F26=""),"",IF(F26<=0,"",IFERROR(J26/F26-1,""))) | K27: =IF(OR(K26="",G26=""),"",IF(G26<=0,"",IFERROR(K26/G26-1,""))) | L27: =IF(OR(L26="",H26=""),"",IF(H26<=0,"",IFERROR(L26/H26-1,""))) | M27: =IF(OR(M26="",I26=""),"",IF(I26<=0,"",IFERROR(M26/I26-1,""))) | N27: =IF(OR(N26="",J26=""),"",IF(J26<=0,"",IFERROR(N26/J26-1,""))) | P27: =IF(OR(P26="",O26=""),"",IF(O26<=0,"",IFERROR(P26/O26-1,""))) | Q27: =IF(OR(Q26="",P26=""),"",IF(P26<=0,"",IFERROR(Q26/P26-1,""))) | R27: =IF(OR(R26="",Q26=""),"",IF(Q26<=0,"",IFERROR(R26/Q26-1,""))) | S27: =IF(OR(S26="",R26=""),"",IF(R26<=0,"",IFERROR(S26/R26-1,""))) | T27: =IF(OR(T26="",S26=""),"",IF(S26<=0,"",IFERROR(T26/S26-1,""))) | U27: =IF(OR(U26="",T26=""),"",IF(T26<=0,"",IFERROR(U26/T26-1,""))) | V27: =IF(OR(V26="",U26=""),"",IF(U26<=0,"",IFERROR(V26/U26-1,""))) | W27: =IF(OR(W26="",V26=""),"",IF(V26<=0,"",IFERROR(W26/V26-1,""))) | ... AC27: =IF(OR(AC26="",AB26=""),"",IF(AB26<=0,"",IFERROR(AC26/AB26-1,"")))
A28: 영업이익 | B28: MW = 매출 × OPM | O28: 58514 | P28: 65138 | Q28: 71442 | R28: 83178 | S28: 80748 | T28: 106218 | U28: 111832 | V28: 120411 | W28: 134907 | X28: 58273 | Y28: =IF(OR(Y4="",Y29=""),"",IFERROR(Y4*Y29,"")) | Z28: =IF(OR(Z4="",Z29=""),"",IFERROR(Z4*Z29,"")) | AA28: =IF(OR(AA4="",AA29=""),"",IFERROR(AA4*AA29,"")) | AB28: =IF(OR(AB4="",AB29=""),"",IFERROR(AB4*AB29,"")) | AC28: =IF(OR(AC4="",AC29=""),"",IFERROR(AC4*AC29,""))
A29: OPM | B29: MW 입력 | C29: =IF(OR(C28="",C4=""),"",IFERROR(C28/C4,"")) | D29: =IF(OR(D28="",D4=""),"",IFERROR(D28/D4,"")) | E29: =IF(OR(E28="",E4=""),"",IFERROR(E28/E4,"")) | F29: =IF(OR(F28="",F4=""),"",IFERROR(F28/F4,"")) | G29: =IF(OR(G28="",G4=""),"",IFERROR(G28/G4,"")) | H29: =IF(OR(H28="",H4=""),"",IFERROR(H28/H4,"")) | I29: =IF(OR(I28="",I4=""),"",IFERROR(I28/I4,"")) | J29: =IF(OR(J28="",J4=""),"",IFERROR(J28/J4,"")) | ... X29: =IF(OR(X28="",X4=""),"",IFERROR(X28/X4,""))
A30: 증가율 | G30: =IF(OR(G28="",C28=""),"",IFERROR(G28/C28-1,"")) | H30: =IF(OR(H28="",D28=""),"",IFERROR(H28/D28-1,"")) | I30: =IF(OR(I28="",E28=""),"",IFERROR(I28/E28-1,"")) | J30: =IF(OR(J28="",F28=""),"",IFERROR(J28/F28-1,"")) | K30: =IF(OR(K28="",G28=""),"",IFERROR(K28/G28-1,"")) | L30: =IF(OR(L28="",H28=""),"",IFERROR(L28/H28-1,"")) | M30: =IF(OR(M28="",I28=""),"",IFERROR(M28/I28-1,"")) | N30: =IF(OR(N28="",J28=""),"",IFERROR(N28/J28-1,"")) | P30: =IF(OR(P28="",O28=""),"",IFERROR(P28/O28-1,"")) | Q30: =IF(OR(Q28="",P28=""),"",IFERROR(Q28/P28-1,"")) | R30: =IF(OR(R28="",Q28=""),"",IFERROR(R28/Q28-1,"")) | S30: =IF(OR(S28="",R28=""),"",IFERROR(S28/R28-1,"")) | T30: =IF(OR(T28="",S28=""),"",IFERROR(T28/S28-1,"")) | U30: =IF(OR(U28="",T28=""),"",IFERROR(U28/T28-1,"")) | V30: =IF(OR(V28="",U28=""),"",IFERROR(V28/U28-1,"")) | W30: =IF(OR(W28="",V28=""),"",IFERROR(W28/V28-1,"")) | ... AC30: =IF(OR(AC28="",AB28=""),"",IFERROR(AC28/AB28-1,""))
A31: 비용의 성격별 분류 | B31: 참고 데이터
A32: 총 판관비 | O32: =IF(O26="","",O26) | P32: =IF(P26="","",P26) | Q32: =IF(Q26="","",Q26) | R32: =IF(R26="","",R26) | S32: =IF(S26="","",S26) | T32: =IF(T26="","",T26) | U32: =IF(U26="","",U26) | V32: =IF(V26="","",V26) | ... X32: =IF(X26="","",X26)
A33: 급여 | B33: 고정비
A34: % of Sales | O34: =IF(OR(O33="",O4=""),"",IFERROR(O33/O4,"")) | P34: =IF(OR(P33="",P4=""),"",IFERROR(P33/P4,"")) | Q34: =IF(OR(Q33="",Q4=""),"",IFERROR(Q33/Q4,"")) | R34: =IF(OR(R33="",R4=""),"",IFERROR(R33/R4,"")) | S34: =IF(OR(S33="",S4=""),"",IFERROR(S33/S4,"")) | T34: =IF(OR(T33="",T4=""),"",IFERROR(T33/T4,"")) | U34: =IF(OR(U33="",U4=""),"",IFERROR(U33/U4,"")) | V34: =IF(OR(V33="",V4=""),"",IFERROR(V33/V4,"")) | ... X34: =IF(OR(X33="",X4=""),"",IFERROR(X33/X4,""))
A35: 감가상각비 | B35: 고정비
A36: % of Sales | O36: =IF(OR(O35="",O4=""),"",IFERROR(O35/O4,"")) | P36: =IF(OR(P35="",P4=""),"",IFERROR(P35/P4,"")) | Q36: =IF(OR(Q35="",Q4=""),"",IFERROR(Q35/Q4,"")) | R36: =IF(OR(R35="",R4=""),"",IFERROR(R35/R4,"")) | S36: =IF(OR(S35="",S4=""),"",IFERROR(S35/S4,"")) | T36: =IF(OR(T35="",T4=""),"",IFERROR(T35/T4,"")) | U36: =IF(OR(U35="",U4=""),"",IFERROR(U35/U4,"")) | V36: =IF(OR(V35="",V4=""),"",IFERROR(V35/V4,"")) | ... X36: =IF(OR(X35="",X4=""),"",IFERROR(X35/X4,""))
A37: 지급수수료 | B37: 고정비
A38: % of Sales | O38: =IF(OR(O37="",O4=""),"",IFERROR(O37/O4,"")) | P38: =IF(OR(P37="",P4=""),"",IFERROR(P37/P4,"")) | Q38: =IF(OR(Q37="",Q4=""),"",IFERROR(Q37/Q4,"")) | R38: =IF(OR(R37="",R4=""),"",IFERROR(R37/R4,"")) | S38: =IF(OR(S37="",S4=""),"",IFERROR(S37/S4,"")) | T38: =IF(OR(T37="",T4=""),"",IFERROR(T37/T4,"")) | U38: =IF(OR(U37="",U4=""),"",IFERROR(U37/U4,"")) | V38: =IF(OR(V37="",V4=""),"",IFERROR(V37/V4,"")) | ... X38: =IF(OR(X37="",X4=""),"",IFERROR(X37/X4,""))
A39: 연구개발비 | B39: 변동비
A40: % of Sales | O40: =IF(OR(O39="",O4=""),"",IFERROR(O39/O4,"")) | P40: =IF(OR(P39="",P4=""),"",IFERROR(P39/P4,"")) | Q40: =IF(OR(Q39="",Q4=""),"",IFERROR(Q39/Q4,"")) | R40: =IF(OR(R39="",R4=""),"",IFERROR(R39/R4,"")) | S40: =IF(OR(S39="",S4=""),"",IFERROR(S39/S4,"")) | T40: =IF(OR(T39="",T4=""),"",IFERROR(T39/T4,"")) | U40: =IF(OR(U39="",U4=""),"",IFERROR(U39/U4,"")) | V40: =IF(OR(V39="",V4=""),"",IFERROR(V39/V4,"")) | ... X40: =IF(OR(X39="",X4=""),"",IFERROR(X39/X4,""))
A41: 기타비용 | B41: 변동비 | O41: =IF(OR(O32="",O33="",O35="",O37="",O39=""),"",IFERROR(O32-O33-O35-O37-O39,"")) | P41: =IF(OR(P32="",P33="",P35="",P37="",P39=""),"",IFERROR(P32-P33-P35-P37-P39,"")) | Q41: =IF(OR(Q32="",Q33="",Q35="",Q37="",Q39=""),"",IFERROR(Q32-Q33-Q35-Q37-Q39,"")) | R41: =IF(OR(R32="",R33="",R35="",R37="",R39=""),"",IFERROR(R32-R33-R35-R37-R39,"")) | S41: =IF(OR(S32="",S33="",S35="",S37="",S39=""),"",IFERROR(S32-S33-S35-S37-S39,"")) | T41: =IF(OR(T32="",T33="",T35="",T37="",T39=""),"",IFERROR(T32-T33-T35-T37-T39,"")) | U41: =IF(OR(U32="",U33="",U35="",U37="",U39=""),"",IFERROR(U32-U33-U35-U37-U39,"")) | V41: =IF(OR(V32="",V33="",V35="",V37="",V39=""),"",IFERROR(V32-V33-V35-V37-V39,"")) | ... X41: =IF(OR(X32="",X33="",X35="",X37="",X39=""),"",IFERROR(X32-X33-X35-X37-X39,""))
A42: % of Sales | O42: =IF(OR(O41="",O4=""),"",IFERROR(O41/O4,"")) | P42: =IF(OR(P41="",P4=""),"",IFERROR(P41/P4,"")) | Q42: =IF(OR(Q41="",Q4=""),"",IFERROR(Q41/Q4,"")) | R42: =IF(OR(R41="",R4=""),"",IFERROR(R41/R4,"")) | S42: =IF(OR(S41="",S4=""),"",IFERROR(S41/S4,"")) | T42: =IF(OR(T41="",T4=""),"",IFERROR(T41/T4,"")) | U42: =IF(OR(U41="",U4=""),"",IFERROR(U41/U4,"")) | V42: =IF(OR(V41="",V4=""),"",IFERROR(V41/V4,"")) | ... X42: =IF(OR(X41="",X4=""),"",IFERROR(X41/X4,""))
A43: 당기순이익 추정
A44: 기타이익 | O44: 13234 | P44: 22104 | Q44: 9385 | R44: 20873 | S44: 1880 | T44: 3754 | U44: 3779 | V44: 2748 | W44: 3249 | X44: 1396 | Y44: =IF(OR(Y4="",Y45=""),"",IFERROR(Y4*Y45,"")) | Z44: =IF(OR(Z4="",Z45=""),"",IFERROR(Z4*Z45,"")) | AA44: =IF(OR(AA4="",AA45=""),"",IFERROR(AA4*AA45,"")) | AB44: =IF(OR(AB4="",AB45=""),"",IFERROR(AB4*AB45,"")) | AC44: =IF(OR(AC4="",AC45=""),"",IFERROR(AC4*AC45,""))
A45: % of Sales | B45: MW = 최근 3년 평균 | C45: =IF(OR(C44="",C4=""),"",IFERROR(C44/C4,"")) | D45: =IF(OR(D44="",D4=""),"",IFERROR(D44/D4,"")) | E45: =IF(OR(E44="",E4=""),"",IFERROR(E44/E4,"")) | F45: =IF(OR(F44="",F4=""),"",IFERROR(F44/F4,"")) | G45: =IF(OR(G44="",G4=""),"",IFERROR(G44/G4,"")) | H45: =IF(OR(H44="",H4=""),"",IFERROR(H44/H4,"")) | I45: =IF(OR(I44="",I4=""),"",IFERROR(I44/I4,"")) | J45: =IF(OR(J44="",J4=""),"",IFERROR(J44/J4,"")) | ... X45: =IF(OR(X44="",X4=""),"",IFERROR(X44/X4,"")) | Y45: =IFERROR(AVERAGE(V45,W45,X45),"") | Z45: =Y45 | AA45: =Z45 | AB45: =AA45 | AC45: =AB45
A46: 기타손실 | O46: 8596 | P46: 5738 | Q46: 5044 | R46: 2905 | S46: 8626 | T46: 275 | U46: 647 | V46: 1771 | W46: 468 | X46: 98735 | Y46: =IF(OR(Y4="",Y47=""),"",IFERROR(Y4*Y47,"")) | Z46: =IF(OR(Z4="",Z47=""),"",IFERROR(Z4*Z47,"")) | AA46: =IF(OR(AA4="",AA47=""),"",IFERROR(AA4*AA47,"")) | AB46: =IF(OR(AB4="",AB47=""),"",IFERROR(AB4*AB47,"")) | AC46: =IF(OR(AC4="",AC47=""),"",IFERROR(AC4*AC47,""))
A47: % of Sales | C47: =IF(OR(C46="",C4=""),"",IFERROR(C46/C4,"")) | D47: =IF(OR(D46="",D4=""),"",IFERROR(D46/D4,"")) | E47: =IF(OR(E46="",E4=""),"",IFERROR(E46/E4,"")) | F47: =IF(OR(F46="",F4=""),"",IFERROR(F46/F4,"")) | G47: =IF(OR(G46="",G4=""),"",IFERROR(G46/G4,"")) | H47: =IF(OR(H46="",H4=""),"",IFERROR(H46/H4,"")) | I47: =IF(OR(I46="",I4=""),"",IFERROR(I46/I4,"")) | J47: =IF(OR(J46="",J4=""),"",IFERROR(J46/J4,"")) | ... X47: =IF(OR(X46="",X4=""),"",IFERROR(X46/X4,"")) | Y47: =IFERROR(AVERAGE(V47,W47,X47),"") | Z47: =Y47 | AA47: =Z47 | AB47: =AA47 | AC47: =AB47
A48: 금융수익 | O48: 2112 | P48: 2004 | Q48: 1743 | R48: 2068 | S48: 1841 | T48: 1971 | U48: 2218 | V48: 3472 | W48: 5057 | X48: 5173 | Y48: =IF(OR(Y4="",Y49=""),"",IFERROR(Y4*Y49,"")) | Z48: =IF(OR(Z4="",Z49=""),"",IFERROR(Z4*Z49,"")) | AA48: =IF(OR(AA4="",AA49=""),"",IFERROR(AA4*AA49,"")) | AB48: =IF(OR(AB4="",AB49=""),"",IFERROR(AB4*AB49,"")) | AC48: =IF(OR(AC4="",AC49=""),"",IFERROR(AC4*AC49,""))
A49: % of Sales | C49: =IF(OR(C48="",C4=""),"",IFERROR(C48/C4,"")) | D49: =IF(OR(D48="",D4=""),"",IFERROR(D48/D4,"")) | E49: =IF(OR(E48="",E4=""),"",IFERROR(E48/E4,"")) | F49: =IF(OR(F48="",F4=""),"",IFERROR(F48/F4,"")) | G49: =IF(OR(G48="",G4=""),"",IFERROR(G48/G4,"")) | H49: =IF(OR(H48="",H4=""),"",IFERROR(H48/H4,"")) | I49: =IF(OR(I48="",I4=""),"",IFERROR(I48/I4,"")) | J49: =IF(OR(J48="",J4=""),"",IFERROR(J48/J4,"")) | ... X49: =IF(OR(X48="",X4=""),"",IFERROR(X48/X4,"")) | Y49: =IFERROR(AVERAGE(V49,W49,X49),"") | Z49: =Y49 | AA49: =Z49 | AB49: =AA49 | AC49: =AB49
A50: 금융원가 | O50: 272 | P50: 981 | Q50: 776 | R50: 718 | S50: 11514 | T50: 3518 | U50: 5551 | V50: 6658 | W50: 5803 | X50: 4595 | Y50: =IF(OR(Y4="",Y51=""),"",IFERROR(Y4*Y51,"")) | Z50: =IF(OR(Z4="",Z51=""),"",IFERROR(Z4*Z51,"")) | AA50: =IF(OR(AA4="",AA51=""),"",IFERROR(AA4*AA51,"")) | AB50: =IF(OR(AB4="",AB51=""),"",IFERROR(AB4*AB51,"")) | AC50: =IF(OR(AC4="",AC51=""),"",IFERROR(AC4*AC51,""))
A51: % of Sales | C51: =IF(OR(C50="",C4=""),"",IFERROR(C50/C4,"")) | D51: =IF(OR(D50="",D4=""),"",IFERROR(D50/D4,"")) | E51: =IF(OR(E50="",E4=""),"",IFERROR(E50/E4,"")) | F51: =IF(OR(F50="",F4=""),"",IFERROR(F50/F4,"")) | G51: =IF(OR(G50="",G4=""),"",IFERROR(G50/G4,"")) | H51: =IF(OR(H50="",H4=""),"",IFERROR(H50/H4,"")) | I51: =IF(OR(I50="",I4=""),"",IFERROR(I50/I4,"")) | J51: =IF(OR(J50="",J4=""),"",IFERROR(J50/J4,"")) | ... X51: =IF(OR(X50="",X4=""),"",IFERROR(X50/X4,"")) | Y51: =IFERROR(AVERAGE(V51,W51,X51),"") | Z51: =Y51 | AA51: =Z51 | AB51: =AA51 | AC51: =AB51
A52: 법인세비용차감전순이익(손실) | O52: 64992 | P52: 82527 | Q52: 76749 | R52: 102496 | S52: 71075 | T52: 104671 | U52: 108499 | V52: 117224 | W52: 134161 | X52: 58851 | Y52: =IF(OR(Y28=""),"",IFERROR(Y28+N(Y44)-N(Y46)+N(Y48)-N(Y50),"")) | Z52: =IF(OR(Z28=""),"",IFERROR(Z28+N(Z44)-N(Z46)+N(Z48)-N(Z50),"")) | AA52: =IF(OR(AA28=""),"",IFERROR(AA28+N(AA44)-N(AA46)+N(AA48)-N(AA50),"")) | AB52: =IF(OR(AB28=""),"",IFERROR(AB28+N(AB44)-N(AB46)+N(AB48)-N(AB50),"")) | AC52: =IF(OR(AC28=""),"",IFERROR(AC28+N(AC44)-N(AC46)+N(AC48)-N(AC50),""))
A53: YoY | G53: =IF(OR(G52="",C52=""),"",IF(C52<=0,"",IFERROR(G52/C52-1,""))) | H53: =IF(OR(H52="",D52=""),"",IF(D52<=0,"",IFERROR(H52/D52-1,""))) | I53: =IF(OR(I52="",E52=""),"",IF(E52<=0,"",IFERROR(I52/E52-1,""))) | J53: =IF(OR(J52="",F52=""),"",IF(F52<=0,"",IFERROR(J52/F52-1,""))) | K53: =IF(OR(K52="",G52=""),"",IF(G52<=0,"",IFERROR(K52/G52-1,""))) | L53: =IF(OR(L52="",H52=""),"",IF(H52<=0,"",IFERROR(L52/H52-1,""))) | M53: =IF(OR(M52="",I52=""),"",IF(I52<=0,"",IFERROR(M52/I52-1,""))) | N53: =IF(OR(N52="",J52=""),"",IF(J52<=0,"",IFERROR(N52/J52-1,""))) | P53: =IF(OR(P52="",O52=""),"",IF(O52<=0,"",IFERROR(P52/O52-1,""))) | Q53: =IF(OR(Q52="",P52=""),"",IF(P52<=0,"",IFERROR(Q52/P52-1,""))) | R53: =IF(OR(R52="",Q52=""),"",IF(Q52<=0,"",IFERROR(R52/Q52-1,""))) | S53: =IF(OR(S52="",R52=""),"",IF(R52<=0,"",IFERROR(S52/R52-1,""))) | T53: =IF(OR(T52="",S52=""),"",IF(S52<=0,"",IFERROR(T52/S52-1,""))) | U53: =IF(OR(U52="",T52=""),"",IF(T52<=0,"",IFERROR(U52/T52-1,""))) | V53: =IF(OR(V52="",U52=""),"",IF(U52<=0,"",IFERROR(V52/U52-1,""))) | W53: =IF(OR(W52="",V52=""),"",IF(V52<=0,"",IFERROR(W52/V52-1,""))) | ... AC53: =IF(OR(AC52="",AB52=""),"",IF(AB52<=0,"",IFERROR(AC52/AB52-1,"")))
A54: 법인세비용(수익) | O54: 21042 | P54: 26356 | Q54: 25213 | R54: 32288 | S54: 18497 | T54: 32878 | U54: 32002 | V54: 37062 | W54: 39778 | X54: 43067 | Y54: =IF(OR(Y52="",Y55=""),"",IFERROR(MAX(Y52,0)*Y55,"")) | Z54: =IF(OR(Z52="",Z55=""),"",IFERROR(MAX(Z52,0)*Z55,"")) | AA54: =IF(OR(AA52="",AA55=""),"",IFERROR(MAX(AA52,0)*AA55,"")) | AB54: =IF(OR(AB52="",AB55=""),"",IFERROR(MAX(AB52,0)*AB55,"")) | AC54: =IF(OR(AC52="",AC55=""),"",IFERROR(MAX(AC52,0)*AC55,""))
A55: 법인세율 | B55: MW 기본 30% | C55: =IF(OR(C54="",C52=""),"",IFERROR(C54/C52,"")) | D55: =IF(OR(D54="",D52=""),"",IFERROR(D54/D52,"")) | E55: =IF(OR(E54="",E52=""),"",IFERROR(E54/E52,"")) | F55: =IF(OR(F54="",F52=""),"",IFERROR(F54/F52,"")) | G55: =IF(OR(G54="",G52=""),"",IFERROR(G54/G52,"")) | H55: =IF(OR(H54="",H52=""),"",IFERROR(H54/H52,"")) | I55: =IF(OR(I54="",I52=""),"",IFERROR(I54/I52,"")) | J55: =IF(OR(J54="",J52=""),"",IFERROR(J54/J52,"")) | ... X55: =IF(OR(X54="",X52=""),"",IFERROR(X54/X52,"")) | Y55: 0.3 | Z55: 0.3 | AA55: 0.3 | AB55: 0.3 | AC55: 0.3
A56: 당기순이익(손실) | O56: 43950 | P56: 56171 | Q56: 51535 | R56: 70208 | S56: 52578 | T56: 71792 | U56: 76496 | V56: 80162 | W56: 94382 | X56: 15783 | Y56: =IF(OR(Y52=""),"",IFERROR(Y52-Y54,"")) | Z56: =IF(OR(Z52=""),"",IFERROR(Z52-Z54,"")) | AA56: =IF(OR(AA52=""),"",IFERROR(AA52-AA54,"")) | AB56: =IF(OR(AB52=""),"",IFERROR(AB52-AB54,"")) | AC56: =IF(OR(AC52=""),"",IFERROR(AC52-AC54,""))
A57: YoY | G57: =IF(OR(G56="",C56=""),"",IF(C56<=0,"",IFERROR(G56/C56-1,""))) | H57: =IF(OR(H56="",D56=""),"",IF(D56<=0,"",IFERROR(H56/D56-1,""))) | I57: =IF(OR(I56="",E56=""),"",IF(E56<=0,"",IFERROR(I56/E56-1,""))) | J57: =IF(OR(J56="",F56=""),"",IF(F56<=0,"",IFERROR(J56/F56-1,""))) | K57: =IF(OR(K56="",G56=""),"",IF(G56<=0,"",IFERROR(K56/G56-1,""))) | L57: =IF(OR(L56="",H56=""),"",IF(H56<=0,"",IFERROR(L56/H56-1,""))) | M57: =IF(OR(M56="",I56=""),"",IF(I56<=0,"",IFERROR(M56/I56-1,""))) | N57: =IF(OR(N56="",J56=""),"",IF(J56<=0,"",IFERROR(N56/J56-1,""))) | P57: =IF(OR(P56="",O56=""),"",IF(O56<=0,"",IFERROR(P56/O56-1,""))) | Q57: =IF(OR(Q56="",P56=""),"",IF(P56<=0,"",IFERROR(Q56/P56-1,""))) | R57: =IF(OR(R56="",Q56=""),"",IF(Q56<=0,"",IFERROR(R56/Q56-1,""))) | S57: =IF(OR(S56="",R56=""),"",IF(R56<=0,"",IFERROR(S56/R56-1,""))) | T57: =IF(OR(T56="",S56=""),"",IF(S56<=0,"",IFERROR(T56/S56-1,""))) | U57: =IF(OR(U56="",T56=""),"",IF(T56<=0,"",IFERROR(U56/T56-1,""))) | V57: =IF(OR(V56="",U56=""),"",IF(U56<=0,"",IFERROR(V56/U56-1,""))) | W57: =IF(OR(W56="",V56=""),"",IF(V56<=0,"",IFERROR(W56/V56-1,""))) | ... AC57: =IF(OR(AC56="",AB56=""),"",IF(AB56<=0,"",IFERROR(AC56/AB56-1,"")))
A58: 지배주주 순이익 | O58: 45064 | P58: 55145 | Q58: 50931 | R58: 69276 | S58: 52867 | T58: 71445 | U58: 76307 | V58: 79643 | W58: 93762 | X58: 15257 | Y58: =IF(OR(Y56="",Y59=""),"",IFERROR(Y56*Y59,"")) | Z58: =IF(OR(Z56="",Z59=""),"",IFERROR(Z56*Z59,"")) | AA58: =IF(OR(AA56="",AA59=""),"",IFERROR(AA56*AA59,"")) | AB58: =IF(OR(AB56="",AB59=""),"",IFERROR(AB56*AB59,"")) | AC58: =IF(OR(AC56="",AC59=""),"",IFERROR(AC56*AC59,""))
A59: 지배주주 순이익률 | B59: MW 기본 100% | C59: =IF(OR(C58="",C56=""),"",IFERROR(C58/C56,"")) | D59: =IF(OR(D58="",D56=""),"",IFERROR(D58/D56,"")) | E59: =IF(OR(E58="",E56=""),"",IFERROR(E58/E56,"")) | F59: =IF(OR(F58="",F56=""),"",IFERROR(F58/F56,"")) | G59: =IF(OR(G58="",G56=""),"",IFERROR(G58/G56,"")) | H59: =IF(OR(H58="",H56=""),"",IFERROR(H58/H56,"")) | I59: =IF(OR(I58="",I56=""),"",IFERROR(I58/I56,"")) | J59: =IF(OR(J58="",J56=""),"",IFERROR(J58/J56,"")) | ... X59: =IF(OR(X58="",X56=""),"",IFERROR(X58/X56,"")) | Y59: 1 | Z59: 1 | AA59: 1 | AB59: 1 | AC59: 1
A60: 지배주주 순이익 YoY | G60: =IF(OR(G58="",C58=""),"",IF(C58<=0,"",IFERROR(G58/C58-1,""))) | H60: =IF(OR(H58="",D58=""),"",IF(D58<=0,"",IFERROR(H58/D58-1,""))) | I60: =IF(OR(I58="",E58=""),"",IF(E58<=0,"",IFERROR(I58/E58-1,""))) | J60: =IF(OR(J58="",F58=""),"",IF(F58<=0,"",IFERROR(J58/F58-1,""))) | K60: =IF(OR(K58="",G58=""),"",IF(G58<=0,"",IFERROR(K58/G58-1,""))) | L60: =IF(OR(L58="",H58=""),"",IF(H58<=0,"",IFERROR(L58/H58-1,""))) | M60: =IF(OR(M58="",I58=""),"",IF(I58<=0,"",IFERROR(M58/I58-1,""))) | N60: =IF(OR(N58="",J58=""),"",IF(J58<=0,"",IFERROR(N58/J58-1,""))) | P60: =IF(OR(P58="",O58=""),"",IF(O58<=0,"",IFERROR(P58/O58-1,""))) | Q60: =IF(OR(Q58="",P58=""),"",IF(P58<=0,"",IFERROR(Q58/P58-1,""))) | R60: =IF(OR(R58="",Q58=""),"",IF(Q58<=0,"",IFERROR(R58/Q58-1,""))) | S60: =IF(OR(S58="",R58=""),"",IF(R58<=0,"",IFERROR(S58/R58-1,""))) | T60: =IF(OR(T58="",S58=""),"",IF(S58<=0,"",IFERROR(T58/S58-1,""))) | U60: =IF(OR(U58="",T58=""),"",IF(T58<=0,"",IFERROR(U58/T58-1,""))) | V60: =IF(OR(V58="",U58=""),"",IF(U58<=0,"",IFERROR(V58/U58-1,""))) | W60: =IF(OR(W58="",V58=""),"",IF(V58<=0,"",IFERROR(W58/V58-1,""))) | ... AC60: =IF(OR(AC58="",AB58=""),"",IF(AB58<=0,"",IFERROR(AC58/AB58-1,"")))
A61: 목표주가 산출
A62: 현재 주가 (2026.10.28) | B62: 6137
A63: 발행주식수 (보통주) | B63: 561197409
A64: 시가총액 (백만엔) | B64: =IF(OR(B62="",B63=""),"",B62*B63/1000000.0)
A65: OPM | O65: =IF(O29="","",O29) | P65: =IF(P29="","",P29) | Q65: =IF(Q29="","",Q29) | R65: =IF(R29="","",R29) | S65: =IF(S29="","",S29) | T65: =IF(T29="","",T29) | U65: =IF(U29="","",U29) | V65: =IF(V29="","",V29) | ... AC65: =IF(AC29="","",AC29)
A66: 지배주주 순이익 증가율 | P66: =IF(OR(P58="",O58=""),"",IFERROR(P58/O58-1,"")) | Q66: =IF(OR(Q58="",P58=""),"",IFERROR(Q58/P58-1,"")) | R66: =IF(OR(R58="",Q58=""),"",IFERROR(R58/Q58-1,"")) | S66: =IF(OR(S58="",R58=""),"",IFERROR(S58/R58-1,"")) | T66: =IF(OR(T58="",S58=""),"",IFERROR(T58/S58-1,"")) | U66: =IF(OR(U58="",T58=""),"",IFERROR(U58/T58-1,"")) | V66: =IF(OR(V58="",U58=""),"",IFERROR(V58/U58-1,"")) | W66: =IF(OR(W58="",V58=""),"",IFERROR(W58/V58-1,"")) | ... AC66: =IF(OR(AC58="",AB58=""),"",IFERROR(AC58/AB58-1,""))
A67: P/E (현재 주가) | B67: 시총 ÷ 지배순이익 | X67: =IF(OR($B$64="",X58=""),"",IFERROR($B$64/X58,"")) | Y67: =IF(OR($B$64="",Y58=""),"",IFERROR($B$64/Y58,"")) | Z67: =IF(OR($B$64="",Z58=""),"",IFERROR($B$64/Z58,"")) | AA67: =IF(OR($B$64="",AA58=""),"",IFERROR($B$64/AA58,"")) | AB67: =IF(OR($B$64="",AB58=""),"",IFERROR($B$64/AB58,"")) | AC67: =IF(OR($B$64="",AC58=""),"",IFERROR($B$64/AC58,""))
A68: Target P/E | B68: 직접 입력
A69: EPS | B69: 지배순이익 ÷ 주식수 | O69: =IF(OR(O58="",$B$63=""),"",IFERROR(O58*1000000.0/$B$63,"")) | P69: =IF(OR(P58="",$B$63=""),"",IFERROR(P58*1000000.0/$B$63,"")) | Q69: =IF(OR(Q58="",$B$63=""),"",IFERROR(Q58*1000000.0/$B$63,"")) | R69: =IF(OR(R58="",$B$63=""),"",IFERROR(R58*1000000.0/$B$63,"")) | S69: =IF(OR(S58="",$B$63=""),"",IFERROR(S58*1000000.0/$B$63,"")) | T69: =IF(OR(T58="",$B$63=""),"",IFERROR(T58*1000000.0/$B$63,"")) | U69: =IF(OR(U58="",$B$63=""),"",IFERROR(U58*1000000.0/$B$63,"")) | V69: =IF(OR(V58="",$B$63=""),"",IFERROR(V58*1000000.0/$B$63,"")) | ... AC69: =IF(OR(AC58="",$B$63=""),"",IFERROR(AC58*1000000.0/$B$63,""))
A70: 목표주가 | Y70: =IF(OR(Y69="",Y68=""),"",IFERROR(Y69*Y68,"")) | Z70: =IF(OR(Z69="",Z68=""),"",IFERROR(Z69*Z68,"")) | AA70: =IF(OR(AA69="",AA68=""),"",IFERROR(AA69*AA68,"")) | AB70: =IF(OR(AB69="",AB68=""),"",IFERROR(AB69*AB68,"")) | AC70: =IF(OR(AC69="",AC68=""),"",IFERROR(AC69*AC68,""))
A71: 상승여력 | Y71: =IF(OR(Y70="",$B$62=""),"",IFERROR(Y70/$B$62-1,"")) | Z71: =IF(OR(Z70="",$B$62=""),"",IFERROR(Z70/$B$62-1,"")) | AA71: =IF(OR(AA70="",$B$62=""),"",IFERROR(AA70/$B$62-1,"")) | AB71: =IF(OR(AB70="",$B$62=""),"",IFERROR(AB70/$B$62-1,"")) | AC71: =IF(OR(AC70="",$B$62=""),"",IFERROR(AC70/$B$62-1,""))
A72: 자산가치 산출 | B72: 최신 분기 BS
A73: 현금및현금성자산 | X73: ='재무상태표'!G6 | Y73: ='재무상태표'!G6 | Z73: ='재무상태표'!G6 | AA73: ='재무상태표'!G6 | AB73: ='재무상태표'!G6 | AC73: ='재무상태표'!G6
A74: 단기금융상품 | X74: ='재무상태표'!G7 | Y74: ='재무상태표'!G7 | Z74: ='재무상태표'!G7 | AA74: ='재무상태표'!G7 | AB74: ='재무상태표'!G7 | AC74: ='재무상태표'!G7
A75: 투자부동산 | X75: ='재무상태표'!G14 | Y75: ='재무상태표'!G14 | Z75: ='재무상태표'!G14 | AA75: ='재무상태표'!G14 | AB75: ='재무상태표'!G14 | AC75: ='재무상태표'!G14
A76: 지배자본 | X76: ='재무상태표'!G31 | Y76: ='재무상태표'!G31 | Z76: ='재무상태표'!G31 | AA76: ='재무상태표'!G31 | AB76: ='재무상태표'!G31 | AC76: ='재무상태표'!G31
A77: 부채 | X77: ='재무상태표'!G27 | Y77: ='재무상태표'!G27 | Z77: ='재무상태표'!G27 | AA77: ='재무상태표'!G27 | AB77: ='재무상태표'!G27 | AC77: ='재무상태표'!G27
A78: 부채비율 | X78: =IF(OR(X77="",X76=""),"",IFERROR(X77/X76,"")) | Y78: =IF(OR(Y77="",Y76=""),"",IFERROR(Y77/Y76,"")) | Z78: =IF(OR(Z77="",Z76=""),"",IFERROR(Z77/Z76,"")) | AA78: =IF(OR(AA77="",AA76=""),"",IFERROR(AA77/AA76,"")) | AB78: =IF(OR(AB77="",AB76=""),"",IFERROR(AB77/AB76,"")) | AC78: =IF(OR(AC77="",AC76=""),"",IFERROR(AC77/AC76,""))
A79: 자산가치 | B79: 현금+단기금융+투자부동산 | X79: =SUM(X73,X74,X75) | Y79: =SUM(Y73,Y74,Y75) | Z79: =SUM(Z73,Z74,Z75) | AA79: =SUM(AA73,AA74,AA75) | AB79: =SUM(AB73,AB74,AB75) | AC79: =SUM(AC73,AC74,AC75)
A80: 기업가치 산출
A81: 목표 시가총액 (P/E) | B81: 지배순이익 × Target P/E | Y81: =IF(OR(Y58="",Y68=""),"",IFERROR(Y58*Y68,"")) | Z81: =IF(OR(Z58="",Z68=""),"",IFERROR(Z58*Z68,"")) | AA81: =IF(OR(AA58="",AA68=""),"",IFERROR(AA58*AA68,"")) | AB81: =IF(OR(AB58="",AB68=""),"",IFERROR(AB58*AB68,"")) | AC81: =IF(OR(AC58="",AC68=""),"",IFERROR(AC58*AC68,""))
A82: 기업가치 | B82: 목표시총 + 자산가치 | Y82: =IF(OR(Y81=""),"",IFERROR(Y81+Y79,"")) | Z82: =IF(OR(Z81=""),"",IFERROR(Z81+Z79,"")) | AA82: =IF(OR(AA81=""),"",IFERROR(AA81+AA79,"")) | AB82: =IF(OR(AB81=""),"",IFERROR(AB81+AB79,"")) | AC82: =IF(OR(AC81=""),"",IFERROR(AC81+AC79,""))
A83: 현재 시가총액 | Y83: =$B$64 | Z83: =$B$64 | AA83: =$B$64 | AB83: =$B$64 | AC83: =$B$64
A84: 상승여력 | Y84: =IF(OR(Y82="",Y83=""),"",IFERROR(Y82/Y83-1,"")) | Z84: =IF(OR(Z82="",Z83=""),"",IFERROR(Z82/Z83-1,"")) | AA84: =IF(OR(AA82="",AA83=""),"",IFERROR(AA82/AA83-1,"")) | AB84: =IF(OR(AB82="",AB83=""),"",IFERROR(AB82/AB83-1,"")) | AC84: =IF(OR(AC82="",AC83=""),"",IFERROR(AC82/AC83-1,""))
A86: 출처
A87: 결산단신 XBRL(TDnet·JPX 보관소) — 쓴 문서는 '출처' 시트
A88: 분기 = 누계에서 앞 분기를 뺀 3개월 값
A89: 주가: 야후 파이낸스 일봉 2026.10.28
A91: 포괄손익 · 전 항목 | B91: 분기 = 3개월 단독
A92: 항목 | B92: 참고 | C92: 2024.1Q | D92: 2024.2Q | E92: 2024.3Q | F92: 2024.4Q | G92: 2025.1Q | H92: 2025.2Q | I92: 2025.3Q | J92: 2025.4Q | K92: 2026.1Q | L92: 2026.2Q | M92: 2026.3Q | N92: 2026.4Q | O92: 2017 | P92: 2018 | Q92: 2019 | R92: 2020 | S92: 2021 | T92: 2022 | U92: 2023 | V92: 2024 | W92: 2025 | X92: 2026 | Y92: 2027(MW) | Z92: 2028(MW) | AA92: 2029(MW) | AB92: 2030(MW) | AC92: 2031(MW)
A93: 매출수익 | C93: 176709 | D93: 185356 | E93: 187954 | G93: 188110 | K93: 195770
A94: 매출원가 | C94: 113538 | D94: 120154 | E94: 121346 | G94: 120450 | K94: 124198
A95: 매출총이익 | C95: 63170 | D95: 65203 | E95: 66607 | G95: 67660 | K95: 71571
A96: 판매비와 관리비 | C96: 35342 | D96: 33803 | E96: 36198 | G96: 36470 | K96: 34864
A97: Share Of Profit Loss Of Investments Accounted For Using Equity Method | C97: 147 | D97: 142 | E97: 331 | G97: 152 | K97: 285
A98: 기타수익 | C98: 90 | D98: 259 | E98: 1620 | G98: 1322 | K98: 312
A99: 기타비용 | C99: 1039 | D99: -37 | E99: -14 | G99: 21 | K99: 58
A100: 영업이익 | C100: 27027 | D100: 31838 | E100: 32374 | G100: 32643 | K100: 37246
A101: 금융수익 | C101: 1032 | D101: 756 | E101: 991 | G101: 1339 | K101: 2008
A102: 금융비용 | C102: 1479 | D102: 1635 | E102: 1630 | G102: 1933 | K102: 1275
...

Sheet 재무상태표
A1: 4307 재무상태표
A2: 재무비율은 기말 잔액 기준 · 분기 손익은 최근 4분기 합산(TTM) | B2: (단위: 백만엔)
A3: 항목 | B3: 참고 | C3: 2026.1Q | D3: 2026.2Q | E3: 2026.3Q | F3: 2026.4Q | G3: 2027.1Q | H3: 2022 | I3: 2023 | J3: 2024 | K3: 2025 | L3: 2026
A4: 자산
A5: 유동자산 | C5: 413613 | D5: 466465 | E5: 401200 | F5: 501060 | G5: 444936 | H5: 333645 | I5: 349102 | J5: 405178 | K5: 419424 | L5: 501060
A6: 현금및현금성자산 | C6: 176277 | D6: 152852 | E6: 108663 | F6: 132620 | G6: 131784 | H6: 115610 | I6: 129257 | J6: 173935 | K6: 168597 | L6: 132620
A7: 단기금융상품 | C7: 20058 | D7: 44412 | E7: 57966 | F7: 61975 | G7: 14964 | H7: 14015 | I7: 14201 | J7: 13982 | K7: 15622 | L7: 61975
A8: 매출채권 | C8: 117324 | D8: 155666 | E8: 110112 | F8: 146189 | G8: 88879 | H8: 135678 | I8: 131592 | J8: 141870 | K8: 158295 | L8: 146189
A9: 재고자산
A10: 기타유동자산 | B10: 총계 − 위 항목 | C10: =IF(OR(C5=""),"",IFERROR(C5-SUM(C6,C7,C8,C9),"")) | D10: =IF(OR(D5=""),"",IFERROR(D5-SUM(D6,D7,D8,D9),"")) | E10: =IF(OR(E5=""),"",IFERROR(E5-SUM(E6,E7,E8,E9),"")) | F10: =IF(OR(F5=""),"",IFERROR(F5-SUM(F6,F7,F8,F9),"")) | G10: =IF(OR(G5=""),"",IFERROR(G5-SUM(G6,G7,G8,G9),"")) | H10: =IF(OR(H5=""),"",IFERROR(H5-SUM(H6,H7,H8,H9),"")) | I10: =IF(OR(I5=""),"",IFERROR(I5-SUM(I6,I7,I8,I9),"")) | J10: =IF(OR(J5=""),"",IFERROR(J5-SUM(J6,J7,J8,J9),"")) | ... L10: =IF(OR(L5=""),"",IFERROR(L5-SUM(L6,L7,L8,L9),""))
A11: 비유동자산 | C11: 512587 | D11: 528048 | E11: 547339 | F11: 458733 | G11: 461453 | H11: 456010 | I11: 489122 | J11: 517595 | K11: 509077 | L11: 458733
A12: 유형자산 | C12: 37244 | D12: 36900 | E12: 38341 | F12: 46748 | G12: 45807 | H12: 37482 | I12: 42114 | J12: 40245 | K12: 38032 | L12: 46748
A13: 무형자산
A14: 투자부동산
A15: 기타비유동자산 | B15: 총계 − 위 항목 | C15: =IF(OR(C11=""),"",IFERROR(C11-SUM(C12,C13,C14),"")) | D15: =IF(OR(D11=""),"",IFERROR(D11-SUM(D12,D13,D14),"")) | E15: =IF(OR(E11=""),"",IFERROR(E11-SUM(E12,E13,E14),"")) | F15: =IF(OR(F11=""),"",IFERROR(F11-SUM(F12,F13,F14),"")) | G15: =IF(OR(G11=""),"",IFERROR(G11-SUM(G12,G13,G14),"")) | H15: =IF(OR(H11=""),"",IFERROR(H11-SUM(H12,H13,H14),"")) | I15: =IF(OR(I11=""),"",IFERROR(I11-SUM(I12,I13,I14),"")) | J15: =IF(OR(J11=""),"",IFERROR(J11-SUM(J12,J13,J14),"")) | ... L15: =IF(OR(L11=""),"",IFERROR(L11-SUM(L12,L13,L14),""))
A16: 자산총계 | C16: 926201 | D16: 994514 | E16: 948539 | F16: 959794 | G16: 906390 | H16: 789655 | I16: 838224 | J16: 922773 | K16: 928501 | L16: 959794
A17: 부채
A18: 유동부채 | C18: 224650 | D18: 270664 | E18: 192746 | F18: 273021 | G18: 275000 | H18: 298342 | I18: 198247 | J18: 214642 | K18: 239482 | L18: 273021
A19: 매입채무 | C19: 63800 | D19: 79896 | E19: 53776 | F19: 36911 | G19: 30939 | H19: 53800 | I19: 52129 | J19: 53038 | K19: 58146 | L19: 36911
A20: 단기차입금
A21: 유동성장기부채
A22: 기타유동부채 | B22: 총계 − 위 항목 | C22: =IF(OR(C18=""),"",IFERROR(C18-SUM(C19,C20,C21),"")) | D22: =IF(OR(D18=""),"",IFERROR(D18-SUM(D19,D20,D21),"")) | E22: =IF(OR(E18=""),"",IFERROR(E18-SUM(E19,E20,E21),"")) | F22: =IF(OR(F18=""),"",IFERROR(F18-SUM(F19,F20,F21),"")) | G22: =IF(OR(G18=""),"",IFERROR(G18-SUM(G19,G20,G21),"")) | H22: =IF(OR(H18=""),"",IFERROR(H18-SUM(H19,H20,H21),"")) | I22: =IF(OR(I18=""),"",IFERROR(I18-SUM(I19,I20,I21),"")) | J22: =IF(OR(J18=""),"",IFERROR(J18-SUM(J19,J20,J21),"")) | ... L22: =IF(OR(L18=""),"",IFERROR(L18-SUM(L19,L20,L21),""))
A23: 비유동부채 | C23: 254324 | D23: 242710 | E23: 250227 | F23: 248770 | G23: 254189 | H23: 148826 | I23: 237570 | J23: 305109 | K23: 251059 | L23: 248770
A24: 장기차입금
A25: 사채 | C25: 208418 | D25: 190089 | E25: 191378 | F25: 192245 | G25: 192471 | H25: 91275 | I25: 182725 | J25: 253864 | K25: 208654 | L25: 192245
A26: 기타비유동부채 | B26: 총계 − 위 항목 | C26: =IF(OR(C23=""),"",IFERROR(C23-SUM(C24,C25),"")) | D26: =IF(OR(D23=""),"",IFERROR(D23-SUM(D24,D25),"")) | E26: =IF(OR(E23=""),"",IFERROR(E23-SUM(E24,E25),"")) | F26: =IF(OR(F23=""),"",IFERROR(F23-SUM(F24,F25),"")) | G26: =IF(OR(G23=""),"",IFERROR(G23-SUM(G24,G25),"")) | H26: =IF(OR(H23=""),"",IFERROR(H23-SUM(H24,H25),"")) | I26: =IF(OR(I23=""),"",IFERROR(I23-SUM(I24,I25),"")) | J26: =IF(OR(J23=""),"",IFERROR(J23-SUM(J24,J25),"")) | ... L26: =IF(OR(L23=""),"",IFERROR(L23-SUM(L24,L25),""))
A27: 부채총계 | C27: 478974 | D27: 513374 | E27: 442974 | F27: 521791 | G27: 529189 | H27: 447168 | I27: 435817 | J27: 519752 | K27: 490542 | L27: 521791
A28: 총차입금 | B28: 단기+유동성장기+장기+사채 | C28: =SUM(C20,C21,C24,C25) | D28: =SUM(D20,D21,D24,D25) | E28: =SUM(E20,E21,E24,E25) | F28: =SUM(F20,F21,F24,F25) | G28: =SUM(G20,G21,G24,G25) | H28: =SUM(H20,H21,H24,H25) | I28: =SUM(I20,I21,I24,I25) | J28: =SUM(J20,J21,J24,J25) | ... L28: =SUM(L20,L21,L24,L25)
A29: 순차입금 | B29: 음수 = 순현금 | C29: =C28-C6-N(C7) | D29: =D28-D6-N(D7) | E29: =E28-E6-N(E7) | F29: =F28-F6-N(F7) | G29: =G28-G6-N(G7) | H29: =H28-H6-N(H7) | I29: =I28-I6-N(I7) | J29: =J28-J6-N(J7) | ... L29: =L28-L6-N(L7)
A30: 자본
A31: 지배주주지분 | C31: 443603 | D31: 477384 | E31: 501656 | F31: 433905 | G31: 373424 | H31: 339360 | I31: 399006 | J31: 399532 | K31: 434040 | L31: 433905
A32: 자본금 | C32: 25655 | D32: 25655 | E32: 25655 | F32: 25655 | G32: 25655 | H32: 22414 | I32: 23644 | J32: 24701 | K32: 25655 | L32: 25655
A33: 이익잉여금 | C33: 385184 | D33: 412742 | E33: 422302 | F33: 354056 | G33: 265808 | H33: 328830 | I33: 321676 | J33: 320320 | K33: 378659 | L33: 354056
A34: 비지배지분 | C34: 3622 | D34: 3754 | E34: 3908 | F34: 4097 | G34: 3775 | H34: 3126 | I34: 3399 | J34: 3489 | K34: 3918 | L34: 4097
A35: 자본총계 | C35: 447226 | D35: 481139 | E35: 505565 | F35: 438002 | G35: 377200 | H35: 342486 | I35: 402406 | J35: 403021 | K35: 437959 | L35: 438002
A36: 현금흐름 요약 | B36: 분기 = TTM (있을 때만)
A37: 영업활동현금흐름 | C37: 147245 | D37: 145208 | E37: 143423 | F37: 147641 | G37: 160201 | H37: 98137 | I37: 118899 | J37: 142277 | K37: 130196 | L37: 147641
A38: CAPEX (유·무형 취득) | B38: 양수로 입력 | C38: 50179 | D38: 50383 | E38: 48208 | F38: 46311 | G38: 45330 | H38: 42977 | I38: 54701 | J38: 49797 | K38: 49602 | L38: 46311
A39: FCF | C39: =IF(OR(C37="",C38=""),"",IFERROR(C37-C38,"")) | D39: =IF(OR(D37="",D38=""),"",IFERROR(D37-D38,"")) | E39: =IF(OR(E37="",E38=""),"",IFERROR(E37-E38,"")) | F39: =IF(OR(F37="",F38=""),"",IFERROR(F37-F38,"")) | G39: =IF(OR(G37="",G38=""),"",IFERROR(G37-G38,"")) | H39: =IF(OR(H37="",H38=""),"",IFERROR(H37-H38,"")) | I39: =IF(OR(I37="",I38=""),"",IFERROR(I37-I38,"")) | J39: =IF(OR(J37="",J38=""),"",IFERROR(J37-J38,"")) | ... L39: =IF(OR(L37="",L38=""),"",IFERROR(L37-L38,""))
A40: 배당금 지급 | B40: 양수로 입력 | C40: 36057 | D40: 36053 | E40: 39519 | F40: 39516 | G40: 44182 | H40: 22647 | I40: 25372 | J40: 27583 | K40: 33313 | L40: 39516
A41: 주요 재무 비율 | B41: 기준 (빨간 글씨 = 미달)
A42: 안정성
A43: 부채비율 | B43: 100%↓ | C43: =IF(OR(C27="",C35=""),"",IFERROR(C27/C35,"")) | D43: =IF(OR(D27="",D35=""),"",IFERROR(D27/D35,"")) | E43: =IF(OR(E27="",E35=""),"",IFERROR(E27/E35,"")) | F43: =IF(OR(F27="",F35=""),"",IFERROR(F27/F35,"")) | G43: =IF(OR(G27="",G35=""),"",IFERROR(G27/G35,"")) | H43: =IF(OR(H27="",H35=""),"",IFERROR(H27/H35,"")) | I43: =IF(OR(I27="",I35=""),"",IFERROR(I27/I35,"")) | J43: =IF(OR(J27="",J35=""),"",IFERROR(J27/J35,"")) | ... L43: =IF(OR(L27="",L35=""),"",IFERROR(L27/L35,""))
A44: 순차입금비율 | B44: 0%↓ 순현금 | C44: =IF(OR(C29="",C35=""),"",IFERROR(C29/C35,"")) | D44: =IF(OR(D29="",D35=""),"",IFERROR(D29/D35,"")) | E44: =IF(OR(E29="",E35=""),"",IFERROR(E29/E35,"")) | F44: =IF(OR(F29="",F35=""),"",IFERROR(F29/F35,"")) | G44: =IF(OR(G29="",G35=""),"",IFERROR(G29/G35,"")) | H44: =IF(OR(H29="",H35=""),"",IFERROR(H29/H35,"")) | I44: =IF(OR(I29="",I35=""),"",IFERROR(I29/I35,"")) | J44: =IF(OR(J29="",J35=""),"",IFERROR(J29/J35,"")) | ... L44: =IF(OR(L29="",L35=""),"",IFERROR(L29/L35,""))
A45: 자기자본비율 | B45: 50%↑ | C45: =IF(OR(C35="",C16=""),"",IFERROR(C35/C16,"")) | D45: =IF(OR(D35="",D16=""),"",IFERROR(D35/D16,"")) | E45: =IF(OR(E35="",E16=""),"",IFERROR(E35/E16,"")) | F45: =IF(OR(F35="",F16=""),"",IFERROR(F35/F16,"")) | G45: =IF(OR(G35="",G16=""),"",IFERROR(G35/G16,"")) | H45: =IF(OR(H35="",H16=""),"",IFERROR(H35/H16,"")) | I45: =IF(OR(I35="",I16=""),"",IFERROR(I35/I16,"")) | J45: =IF(OR(J35="",J16=""),"",IFERROR(J35/J16,"")) | ... L45: =IF(OR(L35="",L16=""),"",IFERROR(L35/L16,""))
A46: 유동비율 | B46: 150%↑ | C46: =IF(OR(C5="",C18=""),"",IFERROR(C5/C18,"")) | D46: =IF(OR(D5="",D18=""),"",IFERROR(D5/D18,"")) | E46: =IF(OR(E5="",E18=""),"",IFERROR(E5/E18,"")) | F46: =IF(OR(F5="",F18=""),"",IFERROR(F5/F18,"")) | G46: =IF(OR(G5="",G18=""),"",IFERROR(G5/G18,"")) | H46: =IF(OR(H5="",H18=""),"",IFERROR(H5/H18,"")) | I46: =IF(OR(I5="",I18=""),"",IFERROR(I5/I18,"")) | J46: =IF(OR(J5="",J18=""),"",IFERROR(J5/J18,"")) | ... L46: =IF(OR(L5="",L18=""),"",IFERROR(L5/L18,""))
A47: 당좌비율 | B47: 100%↑ | C47: =IF(OR(C5="",C18=""),"",IFERROR((C5-N(C9))/C18,"")) | D47: =IF(OR(D5="",D18=""),"",IFERROR((D5-N(D9))/D18,"")) | E47: =IF(OR(E5="",E18=""),"",IFERROR((E5-N(E9))/E18,"")) | F47: =IF(OR(F5="",F18=""),"",IFERROR((F5-N(F9))/F18,"")) | G47: =IF(OR(G5="",G18=""),"",IFERROR((G5-N(G9))/G18,"")) | H47: =IF(OR(H5="",H18=""),"",IFERROR((H5-N(H9))/H18,"")) | I47: =IF(OR(I5="",I18=""),"",IFERROR((I5-N(I9))/I18,"")) | J47: =IF(OR(J5="",J18=""),"",IFERROR((J5-N(J9))/J18,"")) | ... L47: =IF(OR(L5="",L18=""),"",IFERROR((L5-N(L9))/L18,""))
A48: 이자보상배율 | B48: 5x↑ (금융원가 기준) | C48: =IFERROR((IF(COUNT('연간'!H28:K28)<4,"",SUM('연간'!H28:K28)))/(IF(COUNT('연간'!H50:K50)<4,"",SUM('연간'!H50:K50))),"") | D48: =IFERROR((IF(COUNT('연간'!I28:L28)<4,"",SUM('연간'!I28:L28)))/(IF(COUNT('연간'!I50:L50)<4,"",SUM('연간'!I50:L50))),"") | E48: =IFERROR((IF(COUNT('연간'!J28:M28)<4,"",SUM('연간'!J28:M28)))/(IF(COUNT('연간'!J50:M50)<4,"",SUM('연간'!J50:M50))),"") | F48: =IFERROR((IF(COUNT('연간'!K28:N28)<4,"",SUM('연간'!K28:N28)))/(IF(COUNT('연간'!K50:N50)<4,"",SUM('연간'!K50:N50))),"") | H48: =IFERROR(('연간'!T28)/('연간'!T50),"") | I48: =IFERROR(('연간'!U28)/('연간'!U50),"") | J48: =IFERROR(('연간'!V28)/('연간'!V50),"") | K48: =IFERROR(('연간'!W28)/('연간'!W50),"") | L48: =IFERROR(('연간'!X28)/('연간'!X50),"")
A49: 차입금 상환연수 | B49: 4년↓ (버핏) | C49: =IFERROR(IF((IF(COUNT('연간'!H58:K58)<4,"",SUM('연간'!H58:K58)))<=0,"적자",C28/(IF(COUNT('연간'!H58:K58)<4,"",SUM('연간'!H58:K58)))),"") | D49: =IFERROR(IF((IF(COUNT('연간'!I58:L58)<4,"",SUM('연간'!I58:L58)))<=0,"적자",D28/(IF(COUNT('연간'!I58:L58)<4,"",SUM('연간'!I58:L58)))),"") | E49: =IFERROR(IF((IF(COUNT('연간'!J58:M58)<4,"",SUM('연간'!J58:M58)))<=0,"적자",E28/(IF(COUNT('연간'!J58:M58)<4,"",SUM('연간'!J58:M58)))),"") | F49: =IFERROR(IF((IF(COUNT('연간'!K58:N58)<4,"",SUM('연간'!K58:N58)))<=0,"적자",F28/(IF(COUNT('연간'!K58:N58)<4,"",SUM('연간'!K58:N58)))),"") | H49: =IFERROR(IF(('연간'!T58)<=0,"적자",H28/('연간'!T58)),"") | I49: =IFERROR(IF(('연간'!U58)<=0,"적자",I28/('연간'!U58)),"") | J49: =IFERROR(IF(('연간'!V58)<=0,"적자",J28/('연간'!V58)),"") | K49: =IFERROR(IF(('연간'!W58)<=0,"적자",K28/('연간'!W58)),"") | L49: =IFERROR(IF(('연간'!X58)<=0,"적자",L28/('연간'!X58)),"")
A50: 수익성
A51: ROE | B51: 15%↑ (버핏) | C51: =IFERROR((IF(COUNT('연간'!H58:K58)<4,"",SUM('연간'!H58:K58)))/C31,"") | D51: =IFERROR((IF(COUNT('연간'!I58:L58)<4,"",SUM('연간'!I58:L58)))/D31,"") | E51: =IFERROR((IF(COUNT('연간'!J58:M58)<4,"",SUM('연간'!J58:M58)))/E31,"") | F51: =IFERROR((IF(COUNT('연간'!K58:N58)<4,"",SUM('연간'!K58:N58)))/F31,"") | H51: =IFERROR(('연간'!T58)/H31,"") | I51: =IFERROR(('연간'!U58)/I31,"") | J51: =IFERROR(('연간'!V58)/J31,"") | K51: =IFERROR(('연간'!W58)/K31,"") | L51: =IFERROR(('연간'!X58)/L31,"")
A52: ROA | B52: 5%↑ | C52: =IFERROR((IF(COUNT('연간'!H56:K56)<4,"",SUM('연간'!H56:K56)))/C16,"") | D52: =IFERROR((IF(COUNT('연간'!I56:L56)<4,"",SUM('연간'!I56:L56)))/D16,"") | E52: =IFERROR((IF(COUNT('연간'!J56:M56)<4,"",SUM('연간'!J56:M56)))/E16,"") | F52: =IFERROR((IF(COUNT('연간'!K56:N56)<4,"",SUM('연간'!K56:N56)))/F16,"") | H52: =IFERROR(('연간'!T56)/H16,"") | I52: =IFERROR(('연간'!U56)/I16,"") | J52: =IFERROR(('연간'!V56)/J16,"") | K52: =IFERROR(('연간'!W56)/K16,"") | L52: =IFERROR(('연간'!X56)/L16,"")
A53: ROIC | B53: 10%↑ (세후영업이익 기준) | C53: =IFERROR((IF(COUNT('연간'!H28:K28)<4,"",SUM('연간'!H28:K28)))*(1-0.3)/(C35+C29),"") | D53: =IFERROR((IF(COUNT('연간'!I28:L28)<4,"",SUM('연간'!I28:L28)))*(1-0.3)/(D35+D29),"") | E53: =IFERROR((IF(COUNT('연간'!J28:M28)<4,"",SUM('연간'!J28:M28)))*(1-0.3)/(E35+E29),"") | F53: =IFERROR((IF(COUNT('연간'!K28:N28)<4,"",SUM('연간'!K28:N28)))*(1-0.3)/(F35+F29),"") | H53: =IFERROR(('연간'!T28)*(1-0.3)/(H35+H29),"") | I53: =IFERROR(('연간'!U28)*(1-0.3)/(I35+I29),"") | J53: =IFERROR(('연간'!V28)*(1-0.3)/(J35+J29),"") | K53: =IFERROR(('연간'!W28)*(1-0.3)/(K35+K29),"") | L53: =IFERROR(('연간'!X28)*(1-0.3)/(L35+L29),"")
A54: 매출총이익률 (GPM) | B54: 40%↑ (해자 신호) | C54: =IFERROR((IF(COUNT('연간'!H22:K22)<4,"",SUM('연간'!H22:K22)))/(IF(COUNT('연간'!H4:K4)<4,"",SUM('연간'!H4:K4))),"") | D54: =IFERROR((IF(COUNT('연간'!I22:L22)<4,"",SUM('연간'!I22:L22)))/(IF(COUNT('연간'!I4:L4)<4,"",SUM('연간'!I4:L4))),"") | E54: =IFERROR((IF(COUNT('연간'!J22:M22)<4,"",SUM('연간'!J22:M22)))/(IF(COUNT('연간'!J4:M4)<4,"",SUM('연간'!J4:M4))),"") | F54: =IFERROR((IF(COUNT('연간'!K22:N22)<4,"",SUM('연간'!K22:N22)))/(IF(COUNT('연간'!K4:N4)<4,"",SUM('연간'!K4:N4))),"") | H54: =IFERROR(('연간'!T22)/('연간'!T4),"") | I54: =IFERROR(('연간'!U22)/('연간'!U4),"") | J54: =IFERROR(('연간'!V22)/('연간'!V4),"") | K54: =IFERROR(('연간'!W22)/('연간'!W4),"") | L54: =IFERROR(('연간'!X22)/('연간'!X4),"")
A55: 영업이익률 (OPM) | B55: 15%↑ | C55: =IFERROR((IF(COUNT('연간'!H28:K28)<4,"",SUM('연간'!H28:K28)))/(IF(COUNT('연간'!H4:K4)<4,"",SUM('연간'!H4:K4))),"") | D55: =IFERROR((IF(COUNT('연간'!I28:L28)<4,"",SUM('연간'!I28:L28)))/(IF(COUNT('연간'!I4:L4)<4,"",SUM('연간'!I4:L4))),"") | E55: =IFERROR((IF(COUNT('연간'!J28:M28)<4,"",SUM('연간'!J28:M28)))/(IF(COUNT('연간'!J4:M4)<4,"",SUM('연간'!J4:M4))),"") | F55: =IFERROR((IF(COUNT('연간'!K28:N28)<4,"",SUM('연간'!K28:N28)))/(IF(COUNT('연간'!K4:N4)<4,"",SUM('연간'!K4:N4))),"") | H55: =IFERROR(('연간'!T28)/('연간'!T4),"") | I55: =IFERROR(('연간'!U28)/('연간'!U4),"") | J55: =IFERROR(('연간'!V28)/('연간'!V4),"") | K55: =IFERROR(('연간'!W28)/('연간'!W4),"") | L55: =IFERROR(('연간'!X28)/('연간'!X4),"")
A56: 순이익률 | B56: 10%↑ | C56: =IFERROR((IF(COUNT('연간'!H56:K56)<4,"",SUM('연간'!H56:K56)))/(IF(COUNT('연간'!H4:K4)<4,"",SUM('연간'!H4:K4))),"") | D56: =IFERROR((IF(COUNT('연간'!I56:L56)<4,"",SUM('연간'!I56:L56)))/(IF(COUNT('연간'!I4:L4)<4,"",SUM('연간'!I4:L4))),"") | E56: =IFERROR((IF(COUNT('연간'!J56:M56)<4,"",SUM('연간'!J56:M56)))/(IF(COUNT('연간'!J4:M4)<4,"",SUM('연간'!J4:M4))),"") | F56: =IFERROR((IF(COUNT('연간'!K56:N56)<4,"",SUM('연간'!K56:N56)))/(IF(COUNT('연간'!K4:N4)<4,"",SUM('연간'!K4:N4))),"") | H56: =IFERROR(('연간'!T56)/('연간'!T4),"") | I56: =IFERROR(('연간'!U56)/('연간'!U4),"") | J56: =IFERROR(('연간'!V56)/('연간'!V4),"") | K56: =IFERROR(('연간'!W56)/('연간'!W4),"") | L56: =IFERROR(('연간'!X56)/('연간'!X4),"")
A57: 효율성 (회전율)
A58: 총자산회전율 | B58: 높을수록↑ | C58: =IFERROR((IF(COUNT('연간'!H4:K4)<4,"",SUM('연간'!H4:K4)))/C16,"") | D58: =IFERROR((IF(COUNT('연간'!I4:L4)<4,"",SUM('연간'!I4:L4)))/D16,"") | E58: =IFERROR((IF(COUNT('연간'!J4:M4)<4,"",SUM('연간'!J4:M4)))/E16,"") | F58: =IFERROR((IF(COUNT('연간'!K4:N4)<4,"",SUM('연간'!K4:N4)))/F16,"") | H58: =IFERROR(('연간'!T4)/H16,"") | I58: =IFERROR(('연간'!U4)/I16,"") | J58: =IFERROR(('연간'!V4)/J16,"") | K58: =IFERROR(('연간'!W4)/K16,"") | L58: =IFERROR(('연간'!X4)/L16,"")
A59: 매출채권회전일수 | B59: 짧을수록↑ | C59: =IFERROR(C8/(IF(COUNT('연간'!H4:K4)<4,"",SUM('연간'!H4:K4)))*365,"") | D59: =IFERROR(D8/(IF(COUNT('연간'!I4:L4)<4,"",SUM('연간'!I4:L4)))*365,"") | E59: =IFERROR(E8/(IF(COUNT('연간'!J4:M4)<4,"",SUM('연간'!J4:M4)))*365,"") | F59: =IFERROR(F8/(IF(COUNT('연간'!K4:N4)<4,"",SUM('연간'!K4:N4)))*365,"") | H59: =IFERROR(H8/('연간'!T4)*365,"") | I59: =IFERROR(I8/('연간'!U4)*365,"") | J59: =IFERROR(J8/('연간'!V4)*365,"") | K59: =IFERROR(K8/('연간'!W4)*365,"") | L59: =IFERROR(L8/('연간'!X4)*365,"")
A60: 재고자산회전일수 | B60: 짧을수록↑ | C60: =IFERROR(C9/(IF(COUNT('연간'!H20:K20)<4,"",SUM('연간'!H20:K20)))*365,"") | D60: =IFERROR(D9/(IF(COUNT('연간'!I20:L20)<4,"",SUM('연간'!I20:L20)))*365,"") | E60: =IFERROR(E9/(IF(COUNT('연간'!J20:M20)<4,"",SUM('연간'!J20:M20)))*365,"") | F60: =IFERROR(F9/(IF(COUNT('연간'!K20:N20)<4,"",SUM('연간'!K20:N20)))*365,"") | H60: =IFERROR(H9/('연간'!T20)*365,"") | I60: =IFERROR(I9/('연간'!U20)*365,"") | J60: =IFERROR(J9/('연간'!V20)*365,"") | K60: =IFERROR(K9/('연간'!W20)*365,"") | L60: =IFERROR(L9/('연간'!X20)*365,"")
A61: 매입채무회전일수 | B61: 길수록 유리 | C61: =IFERROR(C19/(IF(COUNT('연간'!H20:K20)<4,"",SUM('연간'!H20:K20)))*365,"") | D61: =IFERROR(D19/(IF(COUNT('연간'!I20:L20)<4,"",SUM('연간'!I20:L20)))*365,"") | E61: =IFERROR(E19/(IF(COUNT('연간'!J20:M20)<4,"",SUM('연간'!J20:M20)))*365,"") | F61: =IFERROR(F19/(IF(COUNT('연간'!K20:N20)<4,"",SUM('연간'!K20:N20)))*365,"") | H61: =IFERROR(H19/('연간'!T20)*365,"") | I61: =IFERROR(I19/('연간'!U20)*365,"") | J61: =IFERROR(J19/('연간'!V20)*365,"") | K61: =IFERROR(K19/('연간'!W20)*365,"") | L61: =IFERROR(L19/('연간'!X20)*365,"")
A62: 현금전환주기 (CCC) | B62: 짧을수록↑ | C62: =IF(OR(C59="",C60="",C61=""),"",IFERROR(C59+C60-C61,"")) | D62: =IF(OR(D59="",D60="",D61=""),"",IFERROR(D59+D60-D61,"")) | E62: =IF(OR(E59="",E60="",E61=""),"",IFERROR(E59+E60-E61,"")) | F62: =IF(OR(F59="",F60="",F61=""),"",IFERROR(F59+F60-F61,"")) | G62: =IF(OR(G59="",G60="",G61=""),"",IFERROR(G59+G60-G61,"")) | H62: =IF(OR(H59="",H60="",H61=""),"",IFERROR(H59+H60-H61,"")) | I62: =IF(OR(I59="",I60="",I61=""),"",IFERROR(I59+I60-I61,"")) | J62: =IF(OR(J59="",J60="",J61=""),"",IFERROR(J59+J60-J61,"")) | ... L62: =IF(OR(L59="",L60="",L61=""),"",IFERROR(L59+L60-L61,""))
A63: 현금흐름
A64: 영업현금흐름 / 순이익 | B64: 1x↑ (이익의 질) | C64: =IF(C37="","",IFERROR(C37/(IF(COUNT('연간'!H56:K56)<4,"",SUM('연간'!H56:K56))),"")) | D64: =IF(D37="","",IFERROR(D37/(IF(COUNT('연간'!I56:L56)<4,"",SUM('연간'!I56:L56))),"")) | E64: =IF(E37="","",IFERROR(E37/(IF(COUNT('연간'!J56:M56)<4,"",SUM('연간'!J56:M56))),"")) | F64: =IF(F37="","",IFERROR(F37/(IF(COUNT('연간'!K56:N56)<4,"",SUM('연간'!K56:N56))),"")) | H64: =IF(H37="","",IFERROR(H37/('연간'!T56),"")) | I64: =IF(I37="","",IFERROR(I37/('연간'!U56),"")) | J64: =IF(J37="","",IFERROR(J37/('연간'!V56),"")) | K64: =IF(K37="","",IFERROR(K37/('연간'!W56),"")) | L64: =IF(L37="","",IFERROR(L37/('연간'!X56),""))
A65: FCF 마진 | B65: 5%↑ | C65: =IF(C39="","",IFERROR(C39/(IF(COUNT('연간'!H4:K4)<4,"",SUM('연간'!H4:K4))),"")) | D65: =IF(D39="","",IFERROR(D39/(IF(COUNT('연간'!I4:L4)<4,"",SUM('연간'!I4:L4))),"")) | E65: =IF(E39="","",IFERROR(E39/(IF(COUNT('연간'!J4:M4)<4,"",SUM('연간'!J4:M4))),"")) | F65: =IF(F39="","",IFERROR(F39/(IF(COUNT('연간'!K4:N4)<4,"",SUM('연간'!K4:N4))),"")) | H65: =IF(H39="","",IFERROR(H39/('연간'!T4),"")) | I65: =IF(I39="","",IFERROR(I39/('연간'!U4),"")) | J65: =IF(J39="","",IFERROR(J39/('연간'!V4),"")) | K65: =IF(K39="","",IFERROR(K39/('연간'!W4),"")) | L65: =IF(L39="","",IFERROR(L39/('연간'!X4),""))
A66: CAPEX / 매출 | B66: 낮을수록↑ (자본 가벼움) | C66: =IF(C38="","",IFERROR(C38/(IF(COUNT('연간'!H4:K4)<4,"",SUM('연간'!H4:K4))),"")) | D66: =IF(D38="","",IFERROR(D38/(IF(COUNT('연간'!I4:L4)<4,"",SUM('연간'!I4:L4))),"")) | E66: =IF(E38="","",IFERROR(E38/(IF(COUNT('연간'!J4:M4)<4,"",SUM('연간'!J4:M4))),"")) | F66: =IF(F38="","",IFERROR(F38/(IF(COUNT('연간'!K4:N4)<4,"",SUM('연간'!K4:N4))),"")) | H66: =IF(H38="","",IFERROR(H38/('연간'!T4),"")) | I66: =IF(I38="","",IFERROR(I38/('연간'!U4),"")) | J66: =IF(J38="","",IFERROR(J38/('연간'!V4),"")) | K66: =IF(K38="","",IFERROR(K38/('연간'!W4),"")) | L66: =IF(L38="","",IFERROR(L38/('연간'!X4),""))
A67: 배당성향 | B67: 참고 | C67: =IF(C40="","",IFERROR(C40/(IF(COUNT('연간'!H58:K58)<4,"",SUM('연간'!H58:K58))),"")) | D67: =IF(D40="","",IFERROR(D40/(IF(COUNT('연간'!I58:L58)<4,"",SUM('연간'!I58:L58))),"")) | E67: =IF(E40="","",IFERROR(E40/(IF(COUNT('연간'!J58:M58)<4,"",SUM('연간'!J58:M58))),"")) | F67: =IF(F40="","",IFERROR(F40/(IF(COUNT('연간'!K58:N58)<4,"",SUM('연간'!K58:N58))),"")) | H67: =IF(H40="","",IFERROR(H40/('연간'!T58),"")) | I67: =IF(I40="","",IFERROR(I40/('연간'!U58),"")) | J67: =IF(J40="","",IFERROR(J40/('연간'!V58),"")) | K67: =IF(K40="","",IFERROR(K40/('연간'!W58),"")) | L67: =IF(L40="","",IFERROR(L40/('연간'!X58),""))
A69: 재무상태표 · 전 항목 | B69: 분기 말 잔액
A70: 항목 | B70: 참고 | C70: 2026.1Q | D70: 2026.2Q | E70: 2026.3Q | F70: 2026.4Q | G70: 2027.1Q | H70: 2022 | I70: 2023 | J70: 2024 | K70: 2025 | L70: 2026
A71: 현금및현금성자산 | C71: 176277 | D71: 152852 | E71: 108663 | F71: 132620 | G71: 131784 | H71: 115610 | I71: 129257 | J71: 173935 | K71: 168597 | L71: 132620
A72: 영업채권 및 기타채권 | C72: 117324 | D72: 155666 | E72: 110112 | F72: 146189 | G72: 88879 | H72: 135678 | I72: 131592 | J72: 141870 | K72: 158295 | L72: 146189
A73: 계약자산 | C73: 71898 | D73: 81737 | E73: 97291 | F73: 65428 | G73: 74075 | H73: 50666 | I73: 55980 | J73: 56066 | K73: 58437 | L73: 65428
A74: Assets Related To Securities Transaction CA | F74: 68200 | G74: 103424 | L74: 68200
A75: 기타금융자산 | C75: 20058 | D75: 44412 | E75: 57966 | F75: 61975 | G75: 14964 | H75: 14015 | I75: 14201 | J75: 13982 | K75: 15622 | L75: 61975
A76: 기타유동자산 | C76: 28054 | D76: 31797 | E76: 27165 | F76: 26646 | G76: 31808 | H76: 13246 | I76: 18070 | J76: 19323 | K76: 18471 | L76: 26646
A77: 소계 | H77: 329217 | I77: 349102
A78: 매각예정 자산 | H78: 4428 | I78: 0
A79: 유동자산 합계 | C79: 413613 | D79: 466465 | E79: 401200 | F79: 501060 | G79: 444936 | H79: 333645 | I79: 349102 | J79: 405178 | K79: 419424 | L79: 501060
A80: 유형자산 | C80: 37244 | D80: 36900 | E80: 38341 | F80: 46748 | G80: 45807 | H80: 37482 | I80: 42114 | J80: 40245 | K80: 38032 | L80: 46748
A81: 사용권자산 | C81: 20687 | D81: 31249 | E81: 30903 | F81: 28042 | G81: 27078 | H81: 38969 | I81: 31877 | J81: 28851 | K81: 22630 | L81: 28042
A82: 영업권 및 무형자산 | C82: 276137 | D82: 284103 | E82: 294246 | F82: 201988 | G82: 202545 | H82: 210744 | I82: 237283 | J82: 265334 | K82: 268232 | L82: 201988
A83: 지분법 투자 | C83: 10286 | D83: 10409 | E83: 11026 | F83: 11352 | G83: 11018 | H83: 6427 | I83: 9527 | J83: 9796 | K83: 10689 | L83: 11352
A84: 퇴직급여자산 | C84: 80491 | D84: 81583 | E84: 82620 | F84: 81902 | G84: 83381 | H84: 85383 | I84: 89710 | J84: 82553 | K84: 79405 | L84: 81902
A85: 기타금융자산 | C85: 78671 | D85: 74697 | E85: 81590 | F85: 78897 | G85: 77388 | H85: 69219 | I85: 70838 | J85: 80792 | K85: 80969 | L85: 78897
A86: 이연법인세자산 | C86: 5513 | D86: 5562 | E86: 5572 | F86: 8411 | G86: 8403 | H86: 5426 | I86: 5671 | J86: 6102 | K86: 5541 | L86: 8411
A87: 기타비유동자산 | C87: 3556 | D87: 3542 | E87: 3038 | F87: 1389 | G87: 5831 | H87: 2356 | I87: 2098 | J87: 3919 | K87: 3577 | L87: 1389
A88: 비유동자산 합계 | C88: 512587 | D88: 528048 | E88: 547339 | F88: 458733 | G88: 461453 | H88: 456010 | I88: 489122 | J88: 517595 | K88: 509077 | L88: 458733
A89: 자산 합계 | C89: 926201 | D89: 994514 | E89: 948539 | F89: 959794 | G89: 906390 | H89: 789655 | I89: 838224 | J89: 922773 | K89: 928501 | L89: 959794
A90: 영업채무 및 기타채무 | C90: 63800 | D90: 79896 | E90: 53776 | F90: 36911 | G90: 30939 | H90: 53800 | I90: 52129 | J90: 53038 | K90: 58146 | L90: 36911
... A93: 리스부채 | C93: 10678 | D93: 10638 | E93: 10791 | F93: 10867 | G93: 10090 | H93: 12250 | I93: 9364 | J93: 11023 | K93: 11020 | L93: 10867
A94: Liabilities Related To Securities Transaction CL | F94: 66200 | G94: 100759 | L94: 66200
A95: 기타금융부채 | C95: 40777 | D95: 30004 | E95: 36376 | F95: 33881 | G95: 40921 | H95: 27675 | I95: 31294 | J95: 33530 | K95: 31900 | L95: 33881
A96: 미지급법인세 | C96: 7910 | D96: 24973 | E96: 11469 | F96: 26428 | G96: 9161 | H96: 20648 | I96: 13093 | J96: 23874 | K96: 23363 | L96: 26428
A97: 충당금 | C97: 459 | D97: 827 | E97: 667 | F97: 661 | G97: 717 | H97: 2646 | I97: 1027 | J97: 526 | K97: 585 | L97: 661
A98: 기타유동부채 | C98: 43763 | D98: 54378 | E98: 44879 | F98: 60231 | G98: 45769 | H98: 47294 | I98: 53979 | J98: 60546 | K98: 55173 | L98: 60231
A99: 유동부채 합계 | C99: 224650 | D99: 270664 | E99: 192746 | F99: 273021 | G99: 275000 | H99: 298342 | I99: 198247 | J99: 214642 | K99: 239482 | L99: 273021
A100: 사채 및 차입금 | C100: 208418 | D100: 190089 | E100: 191378 | F100: 192245 | G100: 192471 | H100: 91275 | I100: 182725 | J100: 253864 | K100: 208654 | L100: 192245
A101: 리스부채 | C101: 12094 | D101: 22601 | E101: 22183 | F101: 20869 | G101: 20454 | H101: 29952 | I101: 25420 | J101: 20436 | K101: 14060 | L101: 20869
A102: 기타금융부채 | C102: 1757 | D102: 983 | E102: 1347 | F102: 1513 | G102: 1487 | H102: 3313 | I102: 1615 | J102: 1253 | K102: 1303 | L102: 1513
A103: 퇴직급여부채 | C103: 5378 | D103: 5622 | E103: 5877 | F103: 4114 | G103: 4313 | H103: 7561 | I103: 7086 | J103: 6146 | K103: 5194 | L103: 4114
...

Sheet 출처
A1: 출처 · 쓴 결산단신
A3: 공시일 | B3: 문서 | C3: PDF
A4: 2026-07-30 | B4: 2027년 3월 결산기 1분기 결산단신 | C4: https://www2.jpx.co.jp/disc/43070/140120260729501398.pdf
A5: 2026-04-24 | B5: 2026년 3월 결산기 연간 결산단신 | C5: https://www2.jpx.co.jp/disc/43070/140120260423509100.pdf
A6: 2026-01-29 | B6: 2026년 3월 결산기 3분기 결산단신 | C6: https://www2.jpx.co.jp/disc/43070/140120260126538339.pdf
A7: 2025-10-30 | B7: 2026년 3월 결산기 2분기 결산단신 | C7: https://www2.jpx.co.jp/disc/43070/140120251027579313.pdf
A8: 2025-07-28 | B8: 2026년 3월 결산기 1분기 결산단신 | C8: https://www2.jpx.co.jp/disc/43070/140120250724519337.pdf
A9: 2025-04-24 | B9: 2025년 3월 결산기 연간 결산단신 | C9: https://www2.jpx.co.jp/disc/43070/140120250422519942.pdf
A10: 2025-01-30 | B10: 2025년 3월 결산기 3분기 결산단신 | C10: https://www2.jpx.co.jp/disc/43070/140120250127555598.pdf
A11: 2024-10-30 | B11: 2025년 3월 결산기 2분기 결산단신 | C11: https://www2.jpx.co.jp/disc/43070/140120241028504098.pdf
A12: 2024-07-25 | B12: 2025년 3월 결산기 1분기 결산단신 | C12: https://www2.jpx.co.jp/disc/43070/140120240723552972.pdf
A13: 2024-04-25 | B13: 2024년 3월 결산기 연간 결산단신 | C13: https://www2.jpx.co.jp/disc/43070/140120240422573620.pdf
A14: 2024-01-31 | B14: 2024년 3월 결산기 3분기 결산단신 | C14: https://www2.jpx.co.jp/disc/43070/140120240129520393.pdf
... A24: 2018-04-26 | B24: 연간 결산단신 | C24: https://www2.jpx.co.jp/disc/43070/140120180426421152.pdf
