Workbook

Sheet 연간
A1: 4368 Model
A2: 모를 땐 보수적으로 | B2: (단위: 백만엔) | C2: 3월 결산 · 일본 기준 · 2027.2Q = 2027년 3월 결산기 2분기 | Y2: (추정: 파란 글씨 = 직접 입력)
A3: 항목 | B3: 참고 | C3: 2024.3Q | D3: 2024.4Q | E3: 2025.1Q | F3: 2025.2Q | G3: 2025.3Q | H3: 2025.4Q | I3: 2026.1Q | J3: 2026.2Q | K3: 2026.3Q | L3: 2026.4Q | M3: 2027.1Q | N3: 2027.2Q | O3: 2017 | P3: 2018 | Q3: 2019 | R3: 2020 | S3: 2021 | T3: 2022 | U3: 2023 | V3: 2024 | W3: 2025 | X3: 2026 | Y3: 2027(MW) | Z3: 2028(MW) | AA3: 2029(MW) | AB3: 2030(MW) | AC3: 2031(MW)
A4: 매출액 | B4: MW = 제품 합계 | C4: 15999.892 | D4: 15835.24 | E4: 17431.688 | F4: 17324.665 | G4: 17664.282 | H4: 5030.191 | I4: 18658.089 | J4: 19047.799 | K4: 20223.08 | L4: 6170.108 | M4: 22819.442 | N4: 22777.177 | O4: 36224.356 | P4: 40221.619 | Q4: 34504.967 | R4: 41310.689 | S4: 42209.38 | T4: 46166.438 | U4: 68459.392 | V4: 58970.273 | W4: 57450.826 | X4: 64099.076 | Y4: =IF(COUNT(Y7,Y10,Y13,Y16,Y19)=0,"",SUM(Y7,Y10,Y13,Y16,Y19)) | Z4: =IF(COUNT(Z7,Z10,Z13,Z16,Z19)=0,"",SUM(Z7,Z10,Z13,Z16,Z19)) | AA4: =IF(COUNT(AA7,AA10,AA13,AA16,AA19)=0,"",SUM(AA7,AA10,AA13,AA16,AA19)) | AB4: =IF(COUNT(AB7,AB10,AB13,AB16,AB19)=0,"",SUM(AB7,AB10,AB13,AB16,AB19)) | AC4: =IF(COUNT(AC7,AC10,AC13,AC16,AC19)=0,"",SUM(AC7,AC10,AC13,AC16,AC19))
A5: YoY | G5: =IF(OR(G4="",C4=""),"",IFERROR(G4/C4-1,"")) | H5: =IF(OR(H4="",D4=""),"",IFERROR(H4/D4-1,"")) | I5: =IF(OR(I4="",E4=""),"",IFERROR(I4/E4-1,"")) | J5: =IF(OR(J4="",F4=""),"",IFERROR(J4/F4-1,"")) | K5: =IF(OR(K4="",G4=""),"",IFERROR(K4/G4-1,"")) | L5: =IF(OR(L4="",H4=""),"",IFERROR(L4/H4-1,"")) | M5: =IF(OR(M4="",I4=""),"",IFERROR(M4/I4-1,"")) | N5: =IF(OR(N4="",J4=""),"",IFERROR(N4/J4-1,"")) | P5: =IF(OR(P4="",O4=""),"",IFERROR(P4/O4-1,"")) | Q5: =IF(OR(Q4="",P4=""),"",IFERROR(Q4/P4-1,"")) | R5: =IF(OR(R4="",Q4=""),"",IFERROR(R4/Q4-1,"")) | S5: =IF(OR(S4="",R4=""),"",IFERROR(S4/R4-1,"")) | T5: =IF(OR(T4="",S4=""),"",IFERROR(T4/S4-1,"")) | U5: =IF(OR(U4="",T4=""),"",IFERROR(U4/T4-1,"")) | V5: =IF(OR(V4="",U4=""),"",IFERROR(V4/U4-1,"")) | W5: =IF(OR(W4="",V4=""),"",IFERROR(W4/V4-1,"")) | ... AC5: =IF(OR(AC4="",AB4=""),"",IFERROR(AC4/AB4-1,""))
A6: 제품별 매출 분류 | B6: 사업보고서 매출실적
A7: 생명과학 사업 | C7: 8868.972 | E7: 9389.278 | F7: 9279.262 | G7: 8836.409 | I7: 8955.786 | J7: 8827.664 | K7: 8613.153 | M7: 9845.598 | N7: 9981.59
A8: 비중 | C8: =IF(OR(C7="",C4=""),"",IFERROR(C7/C4,"")) | D8: =IF(OR(D7="",D4=""),"",IFERROR(D7/D4,"")) | E8: =IF(OR(E7="",E4=""),"",IFERROR(E7/E4,"")) | F8: =IF(OR(F7="",F4=""),"",IFERROR(F7/F4,"")) | G8: =IF(OR(G7="",G4=""),"",IFERROR(G7/G4,"")) | H8: =IF(OR(H7="",H4=""),"",IFERROR(H7/H4,"")) | I8: =IF(OR(I7="",I4=""),"",IFERROR(I7/I4,"")) | J8: =IF(OR(J7="",J4=""),"",IFERROR(J7/J4,"")) | ... AC8: =IF(OR(AC7="",AC4=""),"",IFERROR(AC7/AC4,""))
A9: YoY | G9: =IF(OR(G7="",C7=""),"",IFERROR(G7/C7-1,"")) | H9: =IF(OR(H7="",D7=""),"",IFERROR(H7/D7-1,"")) | I9: =IF(OR(I7="",E7=""),"",IFERROR(I7/E7-1,"")) | J9: =IF(OR(J7="",F7=""),"",IFERROR(J7/F7-1,"")) | K9: =IF(OR(K7="",G7=""),"",IFERROR(K7/G7-1,"")) | L9: =IF(OR(L7="",H7=""),"",IFERROR(L7/H7-1,"")) | M9: =IF(OR(M7="",I7=""),"",IFERROR(M7/I7-1,"")) | N9: =IF(OR(N7="",J7=""),"",IFERROR(N7/J7-1,"")) | P9: =IF(OR(P7="",O7=""),"",IFERROR(P7/O7-1,"")) | Q9: =IF(OR(Q7="",P7=""),"",IFERROR(Q7/P7-1,"")) | R9: =IF(OR(R7="",Q7=""),"",IFERROR(R7/Q7-1,"")) | S9: =IF(OR(S7="",R7=""),"",IFERROR(S7/R7-1,"")) | T9: =IF(OR(T7="",S7=""),"",IFERROR(T7/S7-1,"")) | U9: =IF(OR(U7="",T7=""),"",IFERROR(U7/T7-1,"")) | V9: =IF(OR(V7="",U7=""),"",IFERROR(V7/U7-1,"")) | W9: =IF(OR(W7="",V7=""),"",IFERROR(W7/V7-1,"")) | ... AC9: =IF(OR(AC7="",AB7=""),"",IFERROR(AC7/AB7-1,""))
A10: 전자재료 사업 | C10: 7130.921 | E10: 8042.41 | F10: 8045.403 | G10: 8827.873 | I10: 9702.302 | J10: 10220.136 | K10: 11609.926 | M10: 12973.844 | N10: 12795.586
A11: 비중 | C11: =IF(OR(C10="",C4=""),"",IFERROR(C10/C4,"")) | D11: =IF(OR(D10="",D4=""),"",IFERROR(D10/D4,"")) | E11: =IF(OR(E10="",E4=""),"",IFERROR(E10/E4,"")) | F11: =IF(OR(F10="",F4=""),"",IFERROR(F10/F4,"")) | G11: =IF(OR(G10="",G4=""),"",IFERROR(G10/G4,"")) | H11: =IF(OR(H10="",H4=""),"",IFERROR(H10/H4,"")) | I11: =IF(OR(I10="",I4=""),"",IFERROR(I10/I4,"")) | J11: =IF(OR(J10="",J4=""),"",IFERROR(J10/J4,"")) | ... AC11: =IF(OR(AC10="",AC4=""),"",IFERROR(AC10/AC4,""))
A12: YoY | G12: =IF(OR(G10="",C10=""),"",IFERROR(G10/C10-1,"")) | H12: =IF(OR(H10="",D10=""),"",IFERROR(H10/D10-1,"")) | I12: =IF(OR(I10="",E10=""),"",IFERROR(I10/E10-1,"")) | J12: =IF(OR(J10="",F10=""),"",IFERROR(J10/F10-1,"")) | K12: =IF(OR(K10="",G10=""),"",IFERROR(K10/G10-1,"")) | L12: =IF(OR(L10="",H10=""),"",IFERROR(L10/H10-1,"")) | M12: =IF(OR(M10="",I10=""),"",IFERROR(M10/I10-1,"")) | N12: =IF(OR(N10="",J10=""),"",IFERROR(N10/J10-1,"")) | P12: =IF(OR(P10="",O10=""),"",IFERROR(P10/O10-1,"")) | Q12: =IF(OR(Q10="",P10=""),"",IFERROR(Q10/P10-1,"")) | R12: =IF(OR(R10="",Q10=""),"",IFERROR(R10/Q10-1,"")) | S12: =IF(OR(S10="",R10=""),"",IFERROR(S10/R10-1,"")) | T12: =IF(OR(T10="",S10=""),"",IFERROR(T10/S10-1,"")) | U12: =IF(OR(U10="",T10=""),"",IFERROR(U10/T10-1,"")) | V12: =IF(OR(V10="",U10=""),"",IFERROR(V10/U10-1,"")) | W12: =IF(OR(W10="",V10=""),"",IFERROR(W10/V10-1,"")) | ... AC12: =IF(OR(AC10="",AB10=""),"",IFERROR(AC10/AB10-1,""))
A13: 생명과학 사업 | V13: 34142.983 | W13: 36287.718 | X13: 35411.14
A14: 비중 | C14: =IF(OR(C13="",C4=""),"",IFERROR(C13/C4,"")) | D14: =IF(OR(D13="",D4=""),"",IFERROR(D13/D4,"")) | E14: =IF(OR(E13="",E4=""),"",IFERROR(E13/E4,"")) | F14: =IF(OR(F13="",F4=""),"",IFERROR(F13/F4,"")) | G14: =IF(OR(G13="",G4=""),"",IFERROR(G13/G4,"")) | H14: =IF(OR(H13="",H4=""),"",IFERROR(H13/H4,"")) | I14: =IF(OR(I13="",I4=""),"",IFERROR(I13/I4,"")) | J14: =IF(OR(J13="",J4=""),"",IFERROR(J13/J4,"")) | ... AC14: =IF(OR(AC13="",AC4=""),"",IFERROR(AC13/AC4,""))
A15: YoY | G15: =IF(OR(G13="",C13=""),"",IFERROR(G13/C13-1,"")) | H15: =IF(OR(H13="",D13=""),"",IFERROR(H13/D13-1,"")) | I15: =IF(OR(I13="",E13=""),"",IFERROR(I13/E13-1,"")) | J15: =IF(OR(J13="",F13=""),"",IFERROR(J13/F13-1,"")) | K15: =IF(OR(K13="",G13=""),"",IFERROR(K13/G13-1,"")) | L15: =IF(OR(L13="",H13=""),"",IFERROR(L13/H13-1,"")) | M15: =IF(OR(M13="",I13=""),"",IFERROR(M13/I13-1,"")) | N15: =IF(OR(N13="",J13=""),"",IFERROR(N13/J13-1,"")) | P15: =IF(OR(P13="",O13=""),"",IFERROR(P13/O13-1,"")) | Q15: =IF(OR(Q13="",P13=""),"",IFERROR(Q13/P13-1,"")) | R15: =IF(OR(R13="",Q13=""),"",IFERROR(R13/Q13-1,"")) | S15: =IF(OR(S13="",R13=""),"",IFERROR(S13/R13-1,"")) | T15: =IF(OR(T13="",S13=""),"",IFERROR(T13/S13-1,"")) | U15: =IF(OR(U13="",T13=""),"",IFERROR(U13/T13-1,"")) | V15: =IF(OR(V13="",U13=""),"",IFERROR(V13/U13-1,"")) | W15: =IF(OR(W13="",V13=""),"",IFERROR(W13/V13-1,"")) | ... AC15: =IF(OR(AC13="",AB13=""),"",IFERROR(AC13/AB13-1,""))
A16: 전자재료 및 기능성 화학품 사업 | V16: 24827.289 | W16: 33213.808
A17: 비중 | C17: =IF(OR(C16="",C4=""),"",IFERROR(C16/C4,"")) | D17: =IF(OR(D16="",D4=""),"",IFERROR(D16/D4,"")) | E17: =IF(OR(E16="",E4=""),"",IFERROR(E16/E4,"")) | F17: =IF(OR(F16="",F4=""),"",IFERROR(F16/F4,"")) | G17: =IF(OR(G16="",G4=""),"",IFERROR(G16/G4,"")) | H17: =IF(OR(H16="",H4=""),"",IFERROR(H16/H4,"")) | I17: =IF(OR(I16="",I4=""),"",IFERROR(I16/I4,"")) | J17: =IF(OR(J16="",J4=""),"",IFERROR(J16/J4,"")) | ... AC17: =IF(OR(AC16="",AC4=""),"",IFERROR(AC16/AC4,""))
A18: YoY | G18: =IF(OR(G16="",C16=""),"",IFERROR(G16/C16-1,"")) | H18: =IF(OR(H16="",D16=""),"",IFERROR(H16/D16-1,"")) | I18: =IF(OR(I16="",E16=""),"",IFERROR(I16/E16-1,"")) | J18: =IF(OR(J16="",F16=""),"",IFERROR(J16/F16-1,"")) | K18: =IF(OR(K16="",G16=""),"",IFERROR(K16/G16-1,"")) | L18: =IF(OR(L16="",H16=""),"",IFERROR(L16/H16-1,"")) | M18: =IF(OR(M16="",I16=""),"",IFERROR(M16/I16-1,"")) | N18: =IF(OR(N16="",J16=""),"",IFERROR(N16/J16-1,"")) | P18: =IF(OR(P16="",O16=""),"",IFERROR(P16/O16-1,"")) | Q18: =IF(OR(Q16="",P16=""),"",IFERROR(Q16/P16-1,"")) | R18: =IF(OR(R16="",Q16=""),"",IFERROR(R16/Q16-1,"")) | S18: =IF(OR(S16="",R16=""),"",IFERROR(S16/R16-1,"")) | T18: =IF(OR(T16="",S16=""),"",IFERROR(T16/S16-1,"")) | U18: =IF(OR(U16="",T16=""),"",IFERROR(U16/T16-1,"")) | V18: =IF(OR(V16="",U16=""),"",IFERROR(V16/U16-1,"")) | W18: =IF(OR(W16="",V16=""),"",IFERROR(W16/V16-1,"")) | ... AC18: =IF(OR(AC16="",AB16=""),"",IFERROR(AC16/AB16-1,""))
A19: 전자재료 사업 | W19: 33213.808 | X19: 41514.883
A20: 비중 | C20: =IF(OR(C19="",C4=""),"",IFERROR(C19/C4,"")) | D20: =IF(OR(D19="",D4=""),"",IFERROR(D19/D4,"")) | E20: =IF(OR(E19="",E4=""),"",IFERROR(E19/E4,"")) | F20: =IF(OR(F19="",F4=""),"",IFERROR(F19/F4,"")) | G20: =IF(OR(G19="",G4=""),"",IFERROR(G19/G4,"")) | H20: =IF(OR(H19="",H4=""),"",IFERROR(H19/H4,"")) | I20: =IF(OR(I19="",I4=""),"",IFERROR(I19/I4,"")) | J20: =IF(OR(J19="",J4=""),"",IFERROR(J19/J4,"")) | ... AC20: =IF(OR(AC19="",AC4=""),"",IFERROR(AC19/AC4,""))
A21: YoY | G21: =IF(OR(G19="",C19=""),"",IFERROR(G19/C19-1,"")) | H21: =IF(OR(H19="",D19=""),"",IFERROR(H19/D19-1,"")) | I21: =IF(OR(I19="",E19=""),"",IFERROR(I19/E19-1,"")) | J21: =IF(OR(J19="",F19=""),"",IFERROR(J19/F19-1,"")) | K21: =IF(OR(K19="",G19=""),"",IFERROR(K19/G19-1,"")) | L21: =IF(OR(L19="",H19=""),"",IFERROR(L19/H19-1,"")) | M21: =IF(OR(M19="",I19=""),"",IFERROR(M19/I19-1,"")) | N21: =IF(OR(N19="",J19=""),"",IFERROR(N19/J19-1,"")) | P21: =IF(OR(P19="",O19=""),"",IFERROR(P19/O19-1,"")) | Q21: =IF(OR(Q19="",P19=""),"",IFERROR(Q19/P19-1,"")) | R21: =IF(OR(R19="",Q19=""),"",IFERROR(R19/Q19-1,"")) | S21: =IF(OR(S19="",R19=""),"",IFERROR(S19/R19-1,"")) | T21: =IF(OR(T19="",S19=""),"",IFERROR(T19/S19-1,"")) | U21: =IF(OR(U19="",T19=""),"",IFERROR(U19/T19-1,"")) | V21: =IF(OR(V19="",U19=""),"",IFERROR(V19/U19-1,"")) | W21: =IF(OR(W19="",V19=""),"",IFERROR(W19/V19-1,"")) | ... AC21: =IF(OR(AC19="",AB19=""),"",IFERROR(AC19/AB19-1,""))
A22: 매출원가
A23: 전체 매출원가 | C23: 10986.496 | D23: 10595.549 | E23: 11188.897 | F23: 10651.915 | G23: 10602.786 | H23: 4173.666 | I23: 11444.179 | J23: 11429.835 | K23: 12735.021 | L23: 4555.643 | M23: 13714.233 | N23: 12667.61 | O23: 19965.499 | P23: 22980.128 | Q23: 21451.597 | R23: 25896.348 | S23: 25861.584 | T23: 27225.691 | U23: 40048.359 | V23: 38396.998 | W23: 36617.264 | X23: 40164.678
A24: YoY | G24: =IF(OR(G23="",C23=""),"",IF(C23<=0,"",IFERROR(G23/C23-1,""))) | H24: =IF(OR(H23="",D23=""),"",IF(D23<=0,"",IFERROR(H23/D23-1,""))) | I24: =IF(OR(I23="",E23=""),"",IF(E23<=0,"",IFERROR(I23/E23-1,""))) | J24: =IF(OR(J23="",F23=""),"",IF(F23<=0,"",IFERROR(J23/F23-1,""))) | K24: =IF(OR(K23="",G23=""),"",IF(G23<=0,"",IFERROR(K23/G23-1,""))) | L24: =IF(OR(L23="",H23=""),"",IF(H23<=0,"",IFERROR(L23/H23-1,""))) | M24: =IF(OR(M23="",I23=""),"",IF(I23<=0,"",IFERROR(M23/I23-1,""))) | N24: =IF(OR(N23="",J23=""),"",IF(J23<=0,"",IFERROR(N23/J23-1,""))) | P24: =IF(OR(P23="",O23=""),"",IF(O23<=0,"",IFERROR(P23/O23-1,""))) | Q24: =IF(OR(Q23="",P23=""),"",IF(P23<=0,"",IFERROR(Q23/P23-1,""))) | R24: =IF(OR(R23="",Q23=""),"",IF(Q23<=0,"",IFERROR(R23/Q23-1,""))) | S24: =IF(OR(S23="",R23=""),"",IF(R23<=0,"",IFERROR(S23/R23-1,""))) | T24: =IF(OR(T23="",S23=""),"",IF(S23<=0,"",IFERROR(T23/S23-1,""))) | U24: =IF(OR(U23="",T23=""),"",IF(T23<=0,"",IFERROR(U23/T23-1,""))) | V24: =IF(OR(V23="",U23=""),"",IF(U23<=0,"",IFERROR(V23/U23-1,""))) | W24: =IF(OR(W23="",V23=""),"",IF(V23<=0,"",IFERROR(W23/V23-1,""))) | ... AC24: =IF(OR(AC23="",AB23=""),"",IF(AB23<=0,"",IFERROR(AC23/AB23-1,"")))
A25: 매출총이익 | C25: =IF(OR(C4="",C23=""),"",IFERROR(C4-C23,"")) | D25: =IF(OR(D4="",D23=""),"",IFERROR(D4-D23,"")) | E25: =IF(OR(E4="",E23=""),"",IFERROR(E4-E23,"")) | F25: =IF(OR(F4="",F23=""),"",IFERROR(F4-F23,"")) | G25: =IF(OR(G4="",G23=""),"",IFERROR(G4-G23,"")) | H25: =IF(OR(H4="",H23=""),"",IFERROR(H4-H23,"")) | I25: =IF(OR(I4="",I23=""),"",IFERROR(I4-I23,"")) | J25: =IF(OR(J4="",J23=""),"",IFERROR(J4-J23,"")) | ... X25: =IF(OR(X4="",X23=""),"",IFERROR(X4-X23,""))
A26: GPM | C26: =IF(OR(C25="",C4=""),"",IFERROR(C25/C4,"")) | D26: =IF(OR(D25="",D4=""),"",IFERROR(D25/D4,"")) | E26: =IF(OR(E25="",E4=""),"",IFERROR(E25/E4,"")) | F26: =IF(OR(F25="",F4=""),"",IFERROR(F25/F4,"")) | G26: =IF(OR(G25="",G4=""),"",IFERROR(G25/G4,"")) | H26: =IF(OR(H25="",H4=""),"",IFERROR(H25/H4,"")) | I26: =IF(OR(I25="",I4=""),"",IFERROR(I25/I4,"")) | J26: =IF(OR(J25="",J4=""),"",IFERROR(J25/J4,"")) | ... AC26: =IF(OR(AC25="",AC4=""),"",IFERROR(AC25/AC4,""))
A27: YoY | G27: =IF(OR(G25="",C25=""),"",IF(C25<=0,"",IFERROR(G25/C25-1,""))) | H27: =IF(OR(H25="",D25=""),"",IF(D25<=0,"",IFERROR(H25/D25-1,""))) | I27: =IF(OR(I25="",E25=""),"",IF(E25<=0,"",IFERROR(I25/E25-1,""))) | J27: =IF(OR(J25="",F25=""),"",IF(F25<=0,"",IFERROR(J25/F25-1,""))) | K27: =IF(OR(K25="",G25=""),"",IF(G25<=0,"",IFERROR(K25/G25-1,""))) | L27: =IF(OR(L25="",H25=""),"",IF(H25<=0,"",IFERROR(L25/H25-1,""))) | M27: =IF(OR(M25="",I25=""),"",IF(I25<=0,"",IFERROR(M25/I25-1,""))) | N27: =IF(OR(N25="",J25=""),"",IF(J25<=0,"",IFERROR(N25/J25-1,""))) | P27: =IF(OR(P25="",O25=""),"",IF(O25<=0,"",IFERROR(P25/O25-1,""))) | Q27: =IF(OR(Q25="",P25=""),"",IF(P25<=0,"",IFERROR(Q25/P25-1,""))) | R27: =IF(OR(R25="",Q25=""),"",IF(Q25<=0,"",IFERROR(R25/Q25-1,""))) | S27: =IF(OR(S25="",R25=""),"",IF(R25<=0,"",IFERROR(S25/R25-1,""))) | T27: =IF(OR(T25="",S25=""),"",IF(S25<=0,"",IFERROR(T25/S25-1,""))) | U27: =IF(OR(U25="",T25=""),"",IF(T25<=0,"",IFERROR(U25/T25-1,""))) | V27: =IF(OR(V25="",U25=""),"",IF(U25<=0,"",IFERROR(V25/U25-1,""))) | W27: =IF(OR(W25="",V25=""),"",IF(V25<=0,"",IFERROR(W25/V25-1,""))) | ... AC27: =IF(OR(AC25="",AB25=""),"",IF(AB25<=0,"",IFERROR(AC25/AB25-1,"")))
A28: 판매관리비
A29: 전체 판관비 | C29: 2368.088 | D29: 2382.11 | E29: 2332.019 | F29: 2438.478 | G29: 2610.778 | H29: 404.956 | I29: 2519.839 | J29: 2565.08 | K29: 2671.831 | L29: 819.333 | M29: 2932.925 | N29: 2987.518 | O29: 6391.02 | P29: 6704.344 | Q29: 5317.712 | R29: 6583.801 | S29: 6715.583 | T29: 6651.766 | U29: 9480.422 | V29: 9489.326 | W29: 7786.231 | X29: 8576.083
A30: YoY | G30: =IF(OR(G29="",C29=""),"",IF(C29<=0,"",IFERROR(G29/C29-1,""))) | H30: =IF(OR(H29="",D29=""),"",IF(D29<=0,"",IFERROR(H29/D29-1,""))) | I30: =IF(OR(I29="",E29=""),"",IF(E29<=0,"",IFERROR(I29/E29-1,""))) | J30: =IF(OR(J29="",F29=""),"",IF(F29<=0,"",IFERROR(J29/F29-1,""))) | K30: =IF(OR(K29="",G29=""),"",IF(G29<=0,"",IFERROR(K29/G29-1,""))) | L30: =IF(OR(L29="",H29=""),"",IF(H29<=0,"",IFERROR(L29/H29-1,""))) | M30: =IF(OR(M29="",I29=""),"",IF(I29<=0,"",IFERROR(M29/I29-1,""))) | N30: =IF(OR(N29="",J29=""),"",IF(J29<=0,"",IFERROR(N29/J29-1,""))) | P30: =IF(OR(P29="",O29=""),"",IF(O29<=0,"",IFERROR(P29/O29-1,""))) | Q30: =IF(OR(Q29="",P29=""),"",IF(P29<=0,"",IFERROR(Q29/P29-1,""))) | R30: =IF(OR(R29="",Q29=""),"",IF(Q29<=0,"",IFERROR(R29/Q29-1,""))) | S30: =IF(OR(S29="",R29=""),"",IF(R29<=0,"",IFERROR(S29/R29-1,""))) | T30: =IF(OR(T29="",S29=""),"",IF(S29<=0,"",IFERROR(T29/S29-1,""))) | U30: =IF(OR(U29="",T29=""),"",IF(T29<=0,"",IFERROR(U29/T29-1,""))) | V30: =IF(OR(V29="",U29=""),"",IF(U29<=0,"",IFERROR(V29/U29-1,""))) | W30: =IF(OR(W29="",V29=""),"",IF(V29<=0,"",IFERROR(W29/V29-1,""))) | ... AC30: =IF(OR(AC29="",AB29=""),"",IF(AB29<=0,"",IFERROR(AC29/AB29-1,"")))
A31: 영업이익 | B31: MW = 매출 × OPM | C31: 2645.307 | D31: 2857.581 | E31: 3910.771 | F31: 4234.273 | G31: 4450.716 | H31: 451.57 | I31: 4694.069 | J31: 5052.884 | K31: 4816.228 | L31: 795.133 | M31: 6172.283 | N31: 7122.049 | O31: 9867.835 | P31: 10537.146 | Q31: 7735.656 | R31: 8830.539 | S31: 9632.212 | T31: 12288.98 | U31: 18930.611 | V31: 11083.948 | W31: 13047.33 | X31: 15358.314 | Y31: =IF(OR(Y4="",Y32=""),"",IFERROR(Y4*Y32,"")) | Z31: =IF(OR(Z4="",Z32=""),"",IFERROR(Z4*Z32,"")) | AA31: =IF(OR(AA4="",AA32=""),"",IFERROR(AA4*AA32,"")) | AB31: =IF(OR(AB4="",AB32=""),"",IFERROR(AB4*AB32,"")) | AC31: =IF(OR(AC4="",AC32=""),"",IFERROR(AC4*AC32,""))
A32: OPM | B32: MW 입력 | C32: =IF(OR(C31="",C4=""),"",IFERROR(C31/C4,"")) | D32: =IF(OR(D31="",D4=""),"",IFERROR(D31/D4,"")) | E32: =IF(OR(E31="",E4=""),"",IFERROR(E31/E4,"")) | F32: =IF(OR(F31="",F4=""),"",IFERROR(F31/F4,"")) | G32: =IF(OR(G31="",G4=""),"",IFERROR(G31/G4,"")) | H32: =IF(OR(H31="",H4=""),"",IFERROR(H31/H4,"")) | I32: =IF(OR(I31="",I4=""),"",IFERROR(I31/I4,"")) | J32: =IF(OR(J31="",J4=""),"",IFERROR(J31/J4,"")) | ... X32: =IF(OR(X31="",X4=""),"",IFERROR(X31/X4,""))
A33: 증가율 | G33: =IF(OR(G31="",C31=""),"",IFERROR(G31/C31-1,"")) | H33: =IF(OR(H31="",D31=""),"",IFERROR(H31/D31-1,"")) | I33: =IF(OR(I31="",E31=""),"",IFERROR(I31/E31-1,"")) | J33: =IF(OR(J31="",F31=""),"",IFERROR(J31/F31-1,"")) | K33: =IF(OR(K31="",G31=""),"",IFERROR(K31/G31-1,"")) | L33: =IF(OR(L31="",H31=""),"",IFERROR(L31/H31-1,"")) | M33: =IF(OR(M31="",I31=""),"",IFERROR(M31/I31-1,"")) | N33: =IF(OR(N31="",J31=""),"",IFERROR(N31/J31-1,"")) | P33: =IF(OR(P31="",O31=""),"",IFERROR(P31/O31-1,"")) | Q33: =IF(OR(Q31="",P31=""),"",IFERROR(Q31/P31-1,"")) | R33: =IF(OR(R31="",Q31=""),"",IFERROR(R31/Q31-1,"")) | S33: =IF(OR(S31="",R31=""),"",IFERROR(S31/R31-1,"")) | T33: =IF(OR(T31="",S31=""),"",IFERROR(T31/S31-1,"")) | U33: =IF(OR(U31="",T31=""),"",IFERROR(U31/T31-1,"")) | V33: =IF(OR(V31="",U31=""),"",IFERROR(V31/U31-1,"")) | W33: =IF(OR(W31="",V31=""),"",IFERROR(W31/V31-1,"")) | ... AC33: =IF(OR(AC31="",AB31=""),"",IFERROR(AC31/AB31-1,""))
A34: 비용의 성격별 분류 | B34: 참고 데이터
A35: 총 판관비 | O35: =IF(O29="","",O29) | P35: =IF(P29="","",P29) | Q35: =IF(Q29="","",Q29) | R35: =IF(R29="","",R29) | S35: =IF(S29="","",S29) | T35: =IF(T29="","",T29) | U35: =IF(U29="","",U29) | V35: =IF(V29="","",V29) | ... X35: =IF(X29="","",X29)
A36: 급여 | B36: 고정비
A37: % of Sales | O37: =IF(OR(O36="",O4=""),"",IFERROR(O36/O4,"")) | P37: =IF(OR(P36="",P4=""),"",IFERROR(P36/P4,"")) | Q37: =IF(OR(Q36="",Q4=""),"",IFERROR(Q36/Q4,"")) | R37: =IF(OR(R36="",R4=""),"",IFERROR(R36/R4,"")) | S37: =IF(OR(S36="",S4=""),"",IFERROR(S36/S4,"")) | T37: =IF(OR(T36="",T4=""),"",IFERROR(T36/T4,"")) | U37: =IF(OR(U36="",U4=""),"",IFERROR(U36/U4,"")) | V37: =IF(OR(V36="",V4=""),"",IFERROR(V36/V4,"")) | ... X37: =IF(OR(X36="",X4=""),"",IFERROR(X36/X4,""))
A38: 감가상각비 | B38: 고정비
A39: % of Sales | O39: =IF(OR(O38="",O4=""),"",IFERROR(O38/O4,"")) | P39: =IF(OR(P38="",P4=""),"",IFERROR(P38/P4,"")) | Q39: =IF(OR(Q38="",Q4=""),"",IFERROR(Q38/Q4,"")) | R39: =IF(OR(R38="",R4=""),"",IFERROR(R38/R4,"")) | S39: =IF(OR(S38="",S4=""),"",IFERROR(S38/S4,"")) | T39: =IF(OR(T38="",T4=""),"",IFERROR(T38/T4,"")) | U39: =IF(OR(U38="",U4=""),"",IFERROR(U38/U4,"")) | V39: =IF(OR(V38="",V4=""),"",IFERROR(V38/V4,"")) | ... X39: =IF(OR(X38="",X4=""),"",IFERROR(X38/X4,""))
A40: 지급수수료 | B40: 고정비
A41: % of Sales | O41: =IF(OR(O40="",O4=""),"",IFERROR(O40/O4,"")) | P41: =IF(OR(P40="",P4=""),"",IFERROR(P40/P4,"")) | Q41: =IF(OR(Q40="",Q4=""),"",IFERROR(Q40/Q4,"")) | R41: =IF(OR(R40="",R4=""),"",IFERROR(R40/R4,"")) | S41: =IF(OR(S40="",S4=""),"",IFERROR(S40/S4,"")) | T41: =IF(OR(T40="",T4=""),"",IFERROR(T40/T4,"")) | U41: =IF(OR(U40="",U4=""),"",IFERROR(U40/U4,"")) | V41: =IF(OR(V40="",V4=""),"",IFERROR(V40/V4,"")) | ... X41: =IF(OR(X40="",X4=""),"",IFERROR(X40/X4,""))
A42: 연구개발비 | B42: 변동비
A43: % of Sales | O43: =IF(OR(O42="",O4=""),"",IFERROR(O42/O4,"")) | P43: =IF(OR(P42="",P4=""),"",IFERROR(P42/P4,"")) | Q43: =IF(OR(Q42="",Q4=""),"",IFERROR(Q42/Q4,"")) | R43: =IF(OR(R42="",R4=""),"",IFERROR(R42/R4,"")) | S43: =IF(OR(S42="",S4=""),"",IFERROR(S42/S4,"")) | T43: =IF(OR(T42="",T4=""),"",IFERROR(T42/T4,"")) | U43: =IF(OR(U42="",U4=""),"",IFERROR(U42/U4,"")) | V43: =IF(OR(V42="",V4=""),"",IFERROR(V42/V4,"")) | ... X43: =IF(OR(X42="",X4=""),"",IFERROR(X42/X4,""))
A44: 기타비용 | B44: 변동비 | O44: =IF(OR(O35="",O36="",O38="",O40="",O42=""),"",IFERROR(O35-O36-O38-O40-O42,"")) | P44: =IF(OR(P35="",P36="",P38="",P40="",P42=""),"",IFERROR(P35-P36-P38-P40-P42,"")) | Q44: =IF(OR(Q35="",Q36="",Q38="",Q40="",Q42=""),"",IFERROR(Q35-Q36-Q38-Q40-Q42,"")) | R44: =IF(OR(R35="",R36="",R38="",R40="",R42=""),"",IFERROR(R35-R36-R38-R40-R42,"")) | S44: =IF(OR(S35="",S36="",S38="",S40="",S42=""),"",IFERROR(S35-S36-S38-S40-S42,"")) | T44: =IF(OR(T35="",T36="",T38="",T40="",T42=""),"",IFERROR(T35-T36-T38-T40-T42,"")) | U44: =IF(OR(U35="",U36="",U38="",U40="",U42=""),"",IFERROR(U35-U36-U38-U40-U42,"")) | V44: =IF(OR(V35="",V36="",V38="",V40="",V42=""),"",IFERROR(V35-V36-V38-V40-V42,"")) | ... X44: =IF(OR(X35="",X36="",X38="",X40="",X42=""),"",IFERROR(X35-X36-X38-X40-X42,""))
A45: % of Sales | O45: =IF(OR(O44="",O4=""),"",IFERROR(O44/O4,"")) | P45: =IF(OR(P44="",P4=""),"",IFERROR(P44/P4,"")) | Q45: =IF(OR(Q44="",Q4=""),"",IFERROR(Q44/Q4,"")) | R45: =IF(OR(R44="",R4=""),"",IFERROR(R44/R4,"")) | S45: =IF(OR(S44="",S4=""),"",IFERROR(S44/S4,"")) | T45: =IF(OR(T44="",T4=""),"",IFERROR(T44/T4,"")) | U45: =IF(OR(U44="",U4=""),"",IFERROR(U44/U4,"")) | V45: =IF(OR(V44="",V4=""),"",IFERROR(V44/V4,"")) | ... X45: =IF(OR(X44="",X4=""),"",IFERROR(X44/X4,""))
A46: 당기순이익 추정
A47: 특별이익 | C47: 37.216 | D47: 141.456 | E47: 20.258 | F47: 60.927 | G47: 0 | H47: -45.078 | I47: 6.166 | J47: 2.236 | K47: 184.817 | L47: -0.515 | M47: 3703.86 | N47: 9.127 | O47: 1.811 | P47: 0.803 | Q47: 25.204 | R47: 78.944 | S47: 13.284 | T47: 227.403 | U47: 388.682 | V47: 192.369 | W47: 36.107 | X47: 192.704 | Y47: =IF(OR(Y4="",Y48=""),"",IFERROR(Y4*Y48,"")) | Z47: =IF(OR(Z4="",Z48=""),"",IFERROR(Z4*Z48,"")) | AA47: =IF(OR(AA4="",AA48=""),"",IFERROR(AA4*AA48,"")) | AB47: =IF(OR(AB4="",AB48=""),"",IFERROR(AB4*AB48,"")) | AC47: =IF(OR(AC4="",AC48=""),"",IFERROR(AC4*AC48,""))
A48: % of Sales | B48: MW = 최근 3년 평균 | C48: =IF(OR(C47="",C4=""),"",IFERROR(C47/C4,"")) | D48: =IF(OR(D47="",D4=""),"",IFERROR(D47/D4,"")) | E48: =IF(OR(E47="",E4=""),"",IFERROR(E47/E4,"")) | F48: =IF(OR(F47="",F4=""),"",IFERROR(F47/F4,"")) | G48: =IF(OR(G47="",G4=""),"",IFERROR(G47/G4,"")) | H48: =IF(OR(H47="",H4=""),"",IFERROR(H47/H4,"")) | I48: =IF(OR(I47="",I4=""),"",IFERROR(I47/I4,"")) | J48: =IF(OR(J47="",J4=""),"",IFERROR(J47/J4,"")) | ... X48: =IF(OR(X47="",X4=""),"",IFERROR(X47/X4,"")) | Y48: =IFERROR(AVERAGE(V48,W48,X48),"") | Z48: =Y48 | AA48: =Z48 | AB48: =AA48 | AC48: =AB48
A49: 특별손실 | C49: 15.758 | D49: 1.643 | E49: 12.232 | F49: 9.173 | G49: 18.862 | H49: 339.583 | I49: 4.066 | J49: 17.058 | K49: 10.117 | L49: 185.375 | M49: 95.385 | N49: 35.971 | O49: 51.445 | P49: 961.021 | Q49: 50.327 | R49: 157.649 | S49: 30.169 | T49: 20.055 | U49: 46.458 | V49: 69.257 | W49: 379.85 | X49: 216.616 | Y49: =IF(OR(Y4="",Y50=""),"",IFERROR(Y4*Y50,"")) | Z49: =IF(OR(Z4="",Z50=""),"",IFERROR(Z4*Z50,"")) | AA49: =IF(OR(AA4="",AA50=""),"",IFERROR(AA4*AA50,"")) | AB49: =IF(OR(AB4="",AB50=""),"",IFERROR(AB4*AB50,"")) | AC49: =IF(OR(AC4="",AC50=""),"",IFERROR(AC4*AC50,""))
A50: % of Sales | C50: =IF(OR(C49="",C4=""),"",IFERROR(C49/C4,"")) | D50: =IF(OR(D49="",D4=""),"",IFERROR(D49/D4,"")) | E50: =IF(OR(E49="",E4=""),"",IFERROR(E49/E4,"")) | F50: =IF(OR(F49="",F4=""),"",IFERROR(F49/F4,"")) | G50: =IF(OR(G49="",G4=""),"",IFERROR(G49/G4,"")) | H50: =IF(OR(H49="",H4=""),"",IFERROR(H49/H4,"")) | I50: =IF(OR(I49="",I4=""),"",IFERROR(I49/I4,"")) | J50: =IF(OR(J49="",J4=""),"",IFERROR(J49/J4,"")) | ... X50: =IF(OR(X49="",X4=""),"",IFERROR(X49/X4,"")) | Y50: =IFERROR(AVERAGE(V50,W50,X50),"") | Z50: =Y50 | AA50: =Z50 | AB50: =AA50 | AC50: =AB50
A51: 영업외수익 | C51: -158.719 | D51: 373.039 | E51: 429.097 | F51: -247.158 | G51: 492.168 | H51: 1154.459 | I51: 122.84 | J51: 114.515 | K51: 393.649 | L51: 3131.79 | M51: 220.727 | N51: 78.919 | O51: 186.652 | P51: 129.911 | Q51: 2119.172 | R51: 155.586 | S51: 123.804 | T51: 1686.007 | U51: 821.906 | V51: 952.398 | W51: 1828.566 | X51: 3762.794 | Y51: =IF(OR(Y4="",Y52=""),"",IFERROR(Y4*Y52,"")) | Z51: =IF(OR(Z4="",Z52=""),"",IFERROR(Z4*Z52,"")) | AA51: =IF(OR(AA4="",AA52=""),"",IFERROR(AA4*AA52,"")) | AB51: =IF(OR(AB4="",AB52=""),"",IFERROR(AB4*AB52,"")) | AC51: =IF(OR(AC4="",AC52=""),"",IFERROR(AC4*AC52,""))
A52: % of Sales | C52: =IF(OR(C51="",C4=""),"",IFERROR(C51/C4,"")) | D52: =IF(OR(D51="",D4=""),"",IFERROR(D51/D4,"")) | E52: =IF(OR(E51="",E4=""),"",IFERROR(E51/E4,"")) | F52: =IF(OR(F51="",F4=""),"",IFERROR(F51/F4,"")) | G52: =IF(OR(G51="",G4=""),"",IFERROR(G51/G4,"")) | H52: =IF(OR(H51="",H4=""),"",IFERROR(H51/H4,"")) | I52: =IF(OR(I51="",I4=""),"",IFERROR(I51/I4,"")) | J52: =IF(OR(J51="",J4=""),"",IFERROR(J51/J4,"")) | ... X52: =IF(OR(X51="",X4=""),"",IFERROR(X51/X4,"")) | Y52: =IFERROR(AVERAGE(V52,W52,X52),"") | Z52: =Y52 | AA52: =Z52 | AB52: =AA52 | AC52: =AB52
A53: 영업외비용 | C53: 33.603 | D53: 46.482 | E53: 49.19 | F53: 328.843 | G53: -264.658 | H53: 31.566 | I53: 284.229 | J53: -107.556 | K53: -56.682 | L53: 36.084 | M53: 29.552 | N53: 207.156 | O53: 15.809 | P53: 299.477 | Q53: 0.641 | R53: 31.645 | S53: 9.567 | T53: 4.222 | U53: 12.42 | V53: 153.263 | W53: 144.941 | X53: 156.075 | Y53: =IF(OR(Y4="",Y54=""),"",IFERROR(Y4*Y54,"")) | Z53: =IF(OR(Z4="",Z54=""),"",IFERROR(Z4*Z54,"")) | AA53: =IF(OR(AA4="",AA54=""),"",IFERROR(AA4*AA54,"")) | AB53: =IF(OR(AB4="",AB54=""),"",IFERROR(AB4*AB54,"")) | AC53: =IF(OR(AC4="",AC54=""),"",IFERROR(AC4*AC54,""))
A54: % of Sales | C54: =IF(OR(C53="",C4=""),"",IFERROR(C53/C4,"")) | D54: =IF(OR(D53="",D4=""),"",IFERROR(D53/D4,"")) | E54: =IF(OR(E53="",E4=""),"",IFERROR(E53/E4,"")) | F54: =IF(OR(F53="",F4=""),"",IFERROR(F53/F4,"")) | G54: =IF(OR(G53="",G4=""),"",IFERROR(G53/G4,"")) | H54: =IF(OR(H53="",H4=""),"",IFERROR(H53/H4,"")) | I54: =IF(OR(I53="",I4=""),"",IFERROR(I53/I4,"")) | J54: =IF(OR(J53="",J4=""),"",IFERROR(J53/J4,"")) | ... X54: =IF(OR(X53="",X4=""),"",IFERROR(X53/X4,"")) | Y54: =IFERROR(AVERAGE(V54,W54,X54),"") | Z54: =Y54 | AA54: =Z54 | AB54: =AA54 | AC54: =AB54
A55: 법인세비용차감전순이익(손실) | C55: 2474.442 | D55: 3323.951 | E55: 4298.705 | F55: 3710.025 | G55: 5188.68 | H55: 1189.802 | I55: 4534.78 | J55: 5260.133 | K55: 5441.26 | L55: 3704.949 | M55: 9971.934 | N55: 6966.967 | O55: 9989.044 | P55: 9407.362 | Q55: 9829.063 | R55: 8875.776 | S55: 9729.563 | T55: 14178.112 | U55: 20082.321 | V55: 12006.194 | W55: 14387.212 | X55: 18941.122 | Y55: =IF(OR(Y31=""),"",IFERROR(Y31+N(Y47)-N(Y49)+N(Y51)-N(Y53),"")) | Z55: =IF(OR(Z31=""),"",IFERROR(Z31+N(Z47)-N(Z49)+N(Z51)-N(Z53),"")) | AA55: =IF(OR(AA31=""),"",IFERROR(AA31+N(AA47)-N(AA49)+N(AA51)-N(AA53),"")) | AB55: =IF(OR(AB31=""),"",IFERROR(AB31+N(AB47)-N(AB49)+N(AB51)-N(AB53),"")) | AC55: =IF(OR(AC31=""),"",IFERROR(AC31+N(AC47)-N(AC49)+N(AC51)-N(AC53),""))
A56: YoY | G56: =IF(OR(G55="",C55=""),"",IF(C55<=0,"",IFERROR(G55/C55-1,""))) | H56: =IF(OR(H55="",D55=""),"",IF(D55<=0,"",IFERROR(H55/D55-1,""))) | I56: =IF(OR(I55="",E55=""),"",IF(E55<=0,"",IFERROR(I55/E55-1,""))) | J56: =IF(OR(J55="",F55=""),"",IF(F55<=0,"",IFERROR(J55/F55-1,""))) | K56: =IF(OR(K55="",G55=""),"",IF(G55<=0,"",IFERROR(K55/G55-1,""))) | L56: =IF(OR(L55="",H55=""),"",IF(H55<=0,"",IFERROR(L55/H55-1,""))) | M56: =IF(OR(M55="",I55=""),"",IF(I55<=0,"",IFERROR(M55/I55-1,""))) | N56: =IF(OR(N55="",J55=""),"",IF(J55<=0,"",IFERROR(N55/J55-1,""))) | P56: =IF(OR(P55="",O55=""),"",IF(O55<=0,"",IFERROR(P55/O55-1,""))) | Q56: =IF(OR(Q55="",P55=""),"",IF(P55<=0,"",IFERROR(Q55/P55-1,""))) | R56: =IF(OR(R55="",Q55=""),"",IF(Q55<=0,"",IFERROR(R55/Q55-1,""))) | S56: =IF(OR(S55="",R55=""),"",IF(R55<=0,"",IFERROR(S55/R55-1,""))) | T56: =IF(OR(T55="",S55=""),"",IF(S55<=0,"",IFERROR(T55/S55-1,""))) | U56: =IF(OR(U55="",T55=""),"",IF(T55<=0,"",IFERROR(U55/T55-1,""))) | V56: =IF(OR(V55="",U55=""),"",IF(U55<=0,"",IFERROR(V55/U55-1,""))) | W56: =IF(OR(W55="",V55=""),"",IF(V55<=0,"",IFERROR(W55/V55-1,""))) | ... AC56: =IF(OR(AC55="",AB55=""),"",IF(AB55<=0,"",IFERROR(AC55/AB55-1,"")))
A57: 법인세비용(수익) | C57: 654.999 | D57: 1087.332 | E57: 1414.142 | F57: 986.275 | G57: 1627.264 | H57: -490.681 | I57: 1429.602 | J57: 1485.386 | K57: 1632.005 | L57: -246.993 | M57: 3283.038 | N57: 1993.262 | O57: 3092.132 | P57: 2814.196 | Q57: 2460 | R57: 1861.453 | S57: 2921.483 | T57: 4016 | U57: 5952.861 | V57: 3662.894 | W57: 3537 | X57: 4300 | Y57: =IF(OR(Y55="",Y58=""),"",IFERROR(MAX(Y55,0)*Y58,"")) | Z57: =IF(OR(Z55="",Z58=""),"",IFERROR(MAX(Z55,0)*Z58,"")) | AA57: =IF(OR(AA55="",AA58=""),"",IFERROR(MAX(AA55,0)*AA58,"")) | AB57: =IF(OR(AB55="",AB58=""),"",IFERROR(MAX(AB55,0)*AB58,"")) | AC57: =IF(OR(AC55="",AC58=""),"",IFERROR(MAX(AC55,0)*AC58,""))
A58: 법인세율 | B58: MW 기본 30% | C58: =IF(OR(C57="",C55=""),"",IFERROR(C57/C55,"")) | D58: =IF(OR(D57="",D55=""),"",IFERROR(D57/D55,"")) | E58: =IF(OR(E57="",E55=""),"",IFERROR(E57/E55,"")) | F58: =IF(OR(F57="",F55=""),"",IFERROR(F57/F55,"")) | G58: =IF(OR(G57="",G55=""),"",IFERROR(G57/G55,"")) | H58: =IF(OR(H57="",H55=""),"",IFERROR(H57/H55,"")) | I58: =IF(OR(I57="",I55=""),"",IFERROR(I57/I55,"")) | J58: =IF(OR(J57="",J55=""),"",IFERROR(J57/J55,"")) | ... X58: =IF(OR(X57="",X55=""),"",IFERROR(X57/X55,"")) | Y58: 0.3 | Z58: 0.3 | AA58: 0.3 | AB58: 0.3 | AC58: 0.3
A59: 당기순이익(손실) | C59: 1819.443 | D59: 2236.618 | E59: 2884.562 | F59: 2723.751 | G59: 3561.416 | H59: 1680.483 | I59: 3105.177 | J59: 3774.747 | K59: 3809.256 | L59: 3951.942 | M59: 6688.896 | N59: 4973.704 | O59: 6896.911 | P59: 6593.165 | Q59: 7369.063 | R59: 7014.323 | S59: 6808.079 | T59: 10162.112 | U59: 14129.459 | V59: 8343.299 | W59: 10850.212 | X59: 14641.122 | Y59: =IF(OR(Y55=""),"",IFERROR(Y55-Y57,"")) | Z59: =IF(OR(Z55=""),"",IFERROR(Z55-Z57,"")) | AA59: =IF(OR(AA55=""),"",IFERROR(AA55-AA57,"")) | AB59: =IF(OR(AB55=""),"",IFERROR(AB55-AB57,"")) | AC59: =IF(OR(AC55=""),"",IFERROR(AC55-AC57,""))
A60: YoY | G60: =IF(OR(G59="",C59=""),"",IF(C59<=0,"",IFERROR(G59/C59-1,""))) | H60: =IF(OR(H59="",D59=""),"",IF(D59<=0,"",IFERROR(H59/D59-1,""))) | I60: =IF(OR(I59="",E59=""),"",IF(E59<=0,"",IFERROR(I59/E59-1,""))) | J60: =IF(OR(J59="",F59=""),"",IF(F59<=0,"",IFERROR(J59/F59-1,""))) | K60: =IF(OR(K59="",G59=""),"",IF(G59<=0,"",IFERROR(K59/G59-1,""))) | L60: =IF(OR(L59="",H59=""),"",IF(H59<=0,"",IFERROR(L59/H59-1,""))) | M60: =IF(OR(M59="",I59=""),"",IF(I59<=0,"",IFERROR(M59/I59-1,""))) | N60: =IF(OR(N59="",J59=""),"",IF(J59<=0,"",IFERROR(N59/J59-1,""))) | P60: =IF(OR(P59="",O59=""),"",IF(O59<=0,"",IFERROR(P59/O59-1,""))) | Q60: =IF(OR(Q59="",P59=""),"",IF(P59<=0,"",IFERROR(Q59/P59-1,""))) | R60: =IF(OR(R59="",Q59=""),"",IF(Q59<=0,"",IFERROR(R59/Q59-1,""))) | S60: =IF(OR(S59="",R59=""),"",IF(R59<=0,"",IFERROR(S59/R59-1,""))) | T60: =IF(OR(T59="",S59=""),"",IF(S59<=0,"",IFERROR(T59/S59-1,""))) | U60: =IF(OR(U59="",T59=""),"",IF(T59<=0,"",IFERROR(U59/T59-1,""))) | V60: =IF(OR(V59="",U59=""),"",IF(U59<=0,"",IFERROR(V59/U59-1,""))) | W60: =IF(OR(W59="",V59=""),"",IF(V59<=0,"",IFERROR(W59/V59-1,""))) | ... AC60: =IF(OR(AC59="",AB59=""),"",IF(AB59<=0,"",IFERROR(AC59/AB59-1,"")))
A61: 지배주주 순이익 | C61: 1819.443 | D61: 2236.618 | E61: 2884.562 | F61: 2723.751 | G61: 3561.416 | H61: 2453.056 | I61: 3105.177 | J61: 3774.747 | K61: 3809.256 | L61: 3622.402 | M61: 6688.896 | N61: 4973.704 | O61: 6895.594 | P61: 6592.287 | Q61: 6881.266 | R61: 7014.323 | S61: 6808.079 | T61: 10890.394 | U61: 14129.459 | V61: 8343.299 | W61: 11622.785 | X61: 14311.582 | Y61: =IF(OR(Y59="",Y62=""),"",IFERROR(Y59*Y62,"")) | Z61: =IF(OR(Z59="",Z62=""),"",IFERROR(Z59*Z62,"")) | AA61: =IF(OR(AA59="",AA62=""),"",IFERROR(AA59*AA62,"")) | AB61: =IF(OR(AB59="",AB62=""),"",IFERROR(AB59*AB62,"")) | AC61: =IF(OR(AC59="",AC62=""),"",IFERROR(AC59*AC62,""))
A62: 지배주주 순이익률 | B62: MW 기본 100% | C62: =IF(OR(C61="",C59=""),"",IFERROR(C61/C59,"")) | D62: =IF(OR(D61="",D59=""),"",IFERROR(D61/D59,"")) | E62: =IF(OR(E61="",E59=""),"",IFERROR(E61/E59,"")) | F62: =IF(OR(F61="",F59=""),"",IFERROR(F61/F59,"")) | G62: =IF(OR(G61="",G59=""),"",IFERROR(G61/G59,"")) | H62: =IF(OR(H61="",H59=""),"",IFERROR(H61/H59,"")) | I62: =IF(OR(I61="",I59=""),"",IFERROR(I61/I59,"")) | J62: =IF(OR(J61="",J59=""),"",IFERROR(J61/J59,"")) | ... X62: =IF(OR(X61="",X59=""),"",IFERROR(X61/X59,"")) | Y62: 1 | Z62: 1 | AA62: 1 | AB62: 1 | AC62: 1
A63: 지배주주 순이익 YoY | G63: =IF(OR(G61="",C61=""),"",IF(C61<=0,"",IFERROR(G61/C61-1,""))) | H63: =IF(OR(H61="",D61=""),"",IF(D61<=0,"",IFERROR(H61/D61-1,""))) | I63: =IF(OR(I61="",E61=""),"",IF(E61<=0,"",IFERROR(I61/E61-1,""))) | J63: =IF(OR(J61="",F61=""),"",IF(F61<=0,"",IFERROR(J61/F61-1,""))) | K63: =IF(OR(K61="",G61=""),"",IF(G61<=0,"",IFERROR(K61/G61-1,""))) | L63: =IF(OR(L61="",H61=""),"",IF(H61<=0,"",IFERROR(L61/H61-1,""))) | M63: =IF(OR(M61="",I61=""),"",IF(I61<=0,"",IFERROR(M61/I61-1,""))) | N63: =IF(OR(N61="",J61=""),"",IF(J61<=0,"",IFERROR(N61/J61-1,""))) | P63: =IF(OR(P61="",O61=""),"",IF(O61<=0,"",IFERROR(P61/O61-1,""))) | Q63: =IF(OR(Q61="",P61=""),"",IF(P61<=0,"",IFERROR(Q61/P61-1,""))) | R63: =IF(OR(R61="",Q61=""),"",IF(Q61<=0,"",IFERROR(R61/Q61-1,""))) | S63: =IF(OR(S61="",R61=""),"",IF(R61<=0,"",IFERROR(S61/R61-1,""))) | T63: =IF(OR(T61="",S61=""),"",IF(S61<=0,"",IFERROR(T61/S61-1,""))) | U63: =IF(OR(U61="",T61=""),"",IF(T61<=0,"",IFERROR(U61/T61-1,""))) | V63: =IF(OR(V61="",U61=""),"",IF(U61<=0,"",IFERROR(V61/U61-1,""))) | W63: =IF(OR(W61="",V61=""),"",IF(V61<=0,"",IFERROR(W61/V61-1,""))) | ... AC63: =IF(OR(AC61="",AB61=""),"",IF(AB61<=0,"",IFERROR(AC61/AB61-1,"")))
A64: 목표주가 산출
A65: 현재 주가 ()
A66: 발행주식수 (보통주)
A67: 시가총액 (백만엔) | B67: =IF(OR(B65="",B66=""),"",B65*B66/1000000.0)
A68: OPM | O68: =IF(O32="","",O32) | P68: =IF(P32="","",P32) | Q68: =IF(Q32="","",Q32) | R68: =IF(R32="","",R32) | S68: =IF(S32="","",S32) | T68: =IF(T32="","",T32) | U68: =IF(U32="","",U32) | V68: =IF(V32="","",V32) | ... AC68: =IF(AC32="","",AC32)
A69: 지배주주 순이익 증가율 | P69: =IF(OR(P61="",O61=""),"",IFERROR(P61/O61-1,"")) | Q69: =IF(OR(Q61="",P61=""),"",IFERROR(Q61/P61-1,"")) | R69: =IF(OR(R61="",Q61=""),"",IFERROR(R61/Q61-1,"")) | S69: =IF(OR(S61="",R61=""),"",IFERROR(S61/R61-1,"")) | T69: =IF(OR(T61="",S61=""),"",IFERROR(T61/S61-1,"")) | U69: =IF(OR(U61="",T61=""),"",IFERROR(U61/T61-1,"")) | V69: =IF(OR(V61="",U61=""),"",IFERROR(V61/U61-1,"")) | W69: =IF(OR(W61="",V61=""),"",IFERROR(W61/V61-1,"")) | ... AC69: =IF(OR(AC61="",AB61=""),"",IFERROR(AC61/AB61-1,""))
A70: P/E (현재 주가) | B70: 시총 ÷ 지배순이익 | X70: =IF(OR($B$67="",X61=""),"",IFERROR($B$67/X61,"")) | Y70: =IF(OR($B$67="",Y61=""),"",IFERROR($B$67/Y61,"")) | Z70: =IF(OR($B$67="",Z61=""),"",IFERROR($B$67/Z61,"")) | AA70: =IF(OR($B$67="",AA61=""),"",IFERROR($B$67/AA61,"")) | AB70: =IF(OR($B$67="",AB61=""),"",IFERROR($B$67/AB61,"")) | AC70: =IF(OR($B$67="",AC61=""),"",IFERROR($B$67/AC61,""))
A71: Target P/E | B71: 직접 입력
A72: EPS | B72: 지배순이익 ÷ 주식수 | O72: =IF(OR(O61="",$B$66=""),"",IFERROR(O61*1000000.0/$B$66,"")) | P72: =IF(OR(P61="",$B$66=""),"",IFERROR(P61*1000000.0/$B$66,"")) | Q72: =IF(OR(Q61="",$B$66=""),"",IFERROR(Q61*1000000.0/$B$66,"")) | R72: =IF(OR(R61="",$B$66=""),"",IFERROR(R61*1000000.0/$B$66,"")) | S72: =IF(OR(S61="",$B$66=""),"",IFERROR(S61*1000000.0/$B$66,"")) | T72: =IF(OR(T61="",$B$66=""),"",IFERROR(T61*1000000.0/$B$66,"")) | U72: =IF(OR(U61="",$B$66=""),"",IFERROR(U61*1000000.0/$B$66,"")) | V72: =IF(OR(V61="",$B$66=""),"",IFERROR(V61*1000000.0/$B$66,"")) | ... AC72: =IF(OR(AC61="",$B$66=""),"",IFERROR(AC61*1000000.0/$B$66,""))
A73: 목표주가 | Y73: =IF(OR(Y72="",Y71=""),"",IFERROR(Y72*Y71,"")) | Z73: =IF(OR(Z72="",Z71=""),"",IFERROR(Z72*Z71,"")) | AA73: =IF(OR(AA72="",AA71=""),"",IFERROR(AA72*AA71,"")) | AB73: =IF(OR(AB72="",AB71=""),"",IFERROR(AB72*AB71,"")) | AC73: =IF(OR(AC72="",AC71=""),"",IFERROR(AC72*AC71,""))
A74: 상승여력 | Y74: =IF(OR(Y73="",$B$65=""),"",IFERROR(Y73/$B$65-1,"")) | Z74: =IF(OR(Z73="",$B$65=""),"",IFERROR(Z73/$B$65-1,"")) | AA74: =IF(OR(AA73="",$B$65=""),"",IFERROR(AA73/$B$65-1,"")) | AB74: =IF(OR(AB73="",$B$65=""),"",IFERROR(AB73/$B$65-1,"")) | AC74: =IF(OR(AC73="",$B$65=""),"",IFERROR(AC73/$B$65-1,""))
A75: 자산가치 산출 | B75: 최신 분기 BS
A76: 현금및현금성자산 | X76: ='재무상태표'!G6 | Y76: ='재무상태표'!G6 | Z76: ='재무상태표'!G6 | AA76: ='재무상태표'!G6 | AB76: ='재무상태표'!G6 | AC76: ='재무상태표'!G6
A77: 단기금융상품 | X77: ='재무상태표'!G7 | Y77: ='재무상태표'!G7 | Z77: ='재무상태표'!G7 | AA77: ='재무상태표'!G7 | AB77: ='재무상태표'!G7 | AC77: ='재무상태표'!G7
A78: 투자부동산 | X78: ='재무상태표'!G14 | Y78: ='재무상태표'!G14 | Z78: ='재무상태표'!G14 | AA78: ='재무상태표'!G14 | AB78: ='재무상태표'!G14 | AC78: ='재무상태표'!G14
A79: 지배자본 | X79: ='재무상태표'!G31 | Y79: ='재무상태표'!G31 | Z79: ='재무상태표'!G31 | AA79: ='재무상태표'!G31 | AB79: ='재무상태표'!G31 | AC79: ='재무상태표'!G31
A80: 부채 | X80: ='재무상태표'!G27 | Y80: ='재무상태표'!G27 | Z80: ='재무상태표'!G27 | AA80: ='재무상태표'!G27 | AB80: ='재무상태표'!G27 | AC80: ='재무상태표'!G27
A81: 부채비율 | X81: =IF(OR(X80="",X79=""),"",IFERROR(X80/X79,"")) | Y81: =IF(OR(Y80="",Y79=""),"",IFERROR(Y80/Y79,"")) | Z81: =IF(OR(Z80="",Z79=""),"",IFERROR(Z80/Z79,"")) | AA81: =IF(OR(AA80="",AA79=""),"",IFERROR(AA80/AA79,"")) | AB81: =IF(OR(AB80="",AB79=""),"",IFERROR(AB80/AB79,"")) | AC81: =IF(OR(AC80="",AC79=""),"",IFERROR(AC80/AC79,""))
A82: 자산가치 | B82: 현금+단기금융+투자부동산 | X82: =SUM(X76,X77,X78) | Y82: =SUM(Y76,Y77,Y78) | Z82: =SUM(Z76,Z77,Z78) | AA82: =SUM(AA76,AA77,AA78) | AB82: =SUM(AB76,AB77,AB78) | AC82: =SUM(AC76,AC77,AC78)
A83: 기업가치 산출
A84: 목표 시가총액 (P/E) | B84: 지배순이익 × Target P/E | Y84: =IF(OR(Y61="",Y71=""),"",IFERROR(Y61*Y71,"")) | Z84: =IF(OR(Z61="",Z71=""),"",IFERROR(Z61*Z71,"")) | AA84: =IF(OR(AA61="",AA71=""),"",IFERROR(AA61*AA71,"")) | AB84: =IF(OR(AB61="",AB71=""),"",IFERROR(AB61*AB71,"")) | AC84: =IF(OR(AC61="",AC71=""),"",IFERROR(AC61*AC71,""))
A85: 기업가치 | B85: 목표시총 + 자산가치 | Y85: =IF(OR(Y84=""),"",IFERROR(Y84+Y82,"")) | Z85: =IF(OR(Z84=""),"",IFERROR(Z84+Z82,"")) | AA85: =IF(OR(AA84=""),"",IFERROR(AA84+AA82,"")) | AB85: =IF(OR(AB84=""),"",IFERROR(AB84+AB82,"")) | AC85: =IF(OR(AC84=""),"",IFERROR(AC84+AC82,""))
A86: 현재 시가총액 | Y86: =$B$67 | Z86: =$B$67 | AA86: =$B$67 | AB86: =$B$67 | AC86: =$B$67
A87: 상승여력 | Y87: =IF(OR(Y85="",Y86=""),"",IFERROR(Y85/Y86-1,"")) | Z87: =IF(OR(Z85="",Z86=""),"",IFERROR(Z85/Z86-1,"")) | AA87: =IF(OR(AA85="",AA86=""),"",IFERROR(AA85/AA86-1,"")) | AB87: =IF(OR(AB85="",AB86=""),"",IFERROR(AB85/AB86-1,"")) | AC87: =IF(OR(AC85="",AC86=""),"",IFERROR(AC85/AC86-1,""))
A89: 출처
A90: 결산단신 XBRL(TDnet·JPX 보관소) — 쓴 문서는 '출처' 시트
A91: 분기 = 누계에서 앞 분기를 뺀 3개월 값
A92: 주가: 야후 파이낸스 일봉
A94: 손익계산서 · 전 항목 | B94: 분기 = 3개월 단독
A95: 항목 | B95: 참고 | C95: 2024.3Q | D95: 2024.4Q | E95: 2025.1Q | F95: 2025.2Q | G95: 2025.3Q | H95: 2025.4Q | I95: 2026.1Q | J95: 2026.2Q | K95: 2026.3Q | L95: 2026.4Q | M95: 2027.1Q | N95: 2027.2Q | O95: 2017 | P95: 2018 | Q95: 2019 | R95: 2020 | S95: 2021 | T95: 2022 | U95: 2023 | V95: 2024 | W95: 2025 | X95: 2026 | Y95: 2027(MW) | Z95: 2028(MW) | AA95: 2029(MW) | AB95: 2030(MW) | AC95: 2031(MW)
A96: 매출액 | C96: 15999.892 | D96: 15835.24 | E96: 17431.688 | F96: 17324.665 | G96: 17664.282 | H96: 5030.191 | I96: 18658.089 | J96: 19047.799 | K96: 20223.08 | L96: 6170.108 | M96: 22819.442 | N96: 22777.177 | T96: 6510.031 | U96: 15825.273 | V96: 15835.24 | W96: 5030.191 | X96: 6170.108
A97: YoY | B97: 전년 같은 분기·전년 대비 | G97: =IF(OR(G96="",C96=""),"",IF(C96<=0,"",IFERROR(G96/C96-1,""))) | H97: =IF(OR(H96="",D96=""),"",IF(D96<=0,"",IFERROR(H96/D96-1,""))) | I97: =IF(OR(I96="",E96=""),"",IF(E96<=0,"",IFERROR(I96/E96-1,""))) | J97: =IF(OR(J96="",F96=""),"",IF(F96<=0,"",IFERROR(J96/F96-1,""))) | K97: =IF(OR(K96="",G96=""),"",IF(G96<=0,"",IFERROR(K96/G96-1,""))) | L97: =IF(OR(L96="",H96=""),"",IF(H96<=0,"",IFERROR(L96/H96-1,""))) | M97: =IF(OR(M96="",I96=""),"",IF(I96<=0,"",IFERROR(M96/I96-1,""))) | N97: =IF(OR(N96="",J96=""),"",IF(J96<=0,"",IFERROR(N96/J96-1,""))) | T97: =IF(OR(T96="",S96=""),"",IF(S96<=0,"",IFERROR(T96/S96-1,""))) | U97: =IF(OR(U96="",T96=""),"",IF(T96<=0,"",IFERROR(U96/T96-1,""))) | V97: =IF(OR(V96="",U96=""),"",IF(U96<=0,"",IFERROR(V96/U96-1,""))) | W97: =IF(OR(W96="",V96=""),"",IF(V96<=0,"",IFERROR(W96/V96-1,""))) | X97: =IF(OR(X96="",W96=""),"",IF(W96<=0,"",IFERROR(X96/W96-1,"")))
A98: 매출원가 | C98: 10986.496 | D98: 10595.549 | E98: 11188.897 | F98: 10651.915 | G98: 10602.786 | H98: 4173.666 | I98: 11444.179 | J98: 11429.835 | K98: 12735.021 | L98: 4555.643 | M98: 13714.233 | N98: 12667.61 | T98: 3533.159 | U98: 9208.561 | V98: 10595.549 | W98: 4173.666 | X98: 4555.643
A99: YoY | B99: 전년 같은 분기·전년 대비 | G99: =IF(OR(G98="",C98=""),"",IF(G98*C98<=0,"",IFERROR(G98/C98-1,""))) | H99: =IF(OR(H98="",D98=""),"",IF(H98*D98<=0,"",IFERROR(H98/D98-1,""))) | I99: =IF(OR(I98="",E98=""),"",IF(I98*E98<=0,"",IFERROR(I98/E98-1,""))) | J99: =IF(OR(J98="",F98=""),"",IF(J98*F98<=0,"",IFERROR(J98/F98-1,""))) | K99: =IF(OR(K98="",G98=""),"",IF(K98*G98<=0,"",IFERROR(K98/G98-1,""))) | L99: =IF(OR(L98="",H98=""),"",IF(L98*H98<=0,"",IFERROR(L98/H98-1,""))) | M99: =IF(OR(M98="",I98=""),"",IF(M98*I98<=0,"",IFERROR(M98/I98-1,""))) | N99: =IF(OR(N98="",J98=""),"",IF(N98*J98<=0,"",IFERROR(N98/J98-1,""))) | T99: =IF(OR(T98="",S98=""),"",IF(T98*S98<=0,"",IFERROR(T98/S98-1,""))) | U99: =IF(OR(U98="",T98=""),"",IF(U98*T98<=0,"",IFERROR(U98/T98-1,""))) | V99: =IF(OR(V98="",U98=""),"",IF(V98*U98<=0,"",IFERROR(V98/U98-1,""))) | W99: =IF(OR(W98="",V98=""),"",IF(W98*V98<=0,"",IFERROR(W98/V98-1,""))) | X99: =IF(OR(X98="",W98=""),"",IF(X98*W98<=0,"",IFERROR(X98/W98-1,"")))
A100: 매출총이익 | C100: 5013.396 | D100: 5239.691 | E100: 6242.79 | F100: 6672.751 | G100: 7061.495 | H100: 856.526 | I100: 7213.909 | J100: 7617.964 | K100: 7488.059 | L100: 1614.465 | M100: 9105.209 | N100: 10109.566 | T100: 2976.873 | U100: 6616.713 | V100: 5239.691 | W100: 856.526 | X100: 1614.465
A101: YoY | B101: 전년 같은 분기·전년 대비 | G101: =IF(OR(G100="",C100=""),"",IF(C100<=0,"",IFERROR(G100/C100-1,""))) | H101: =IF(OR(H100="",D100=""),"",IF(D100<=0,"",IFERROR(H100/D100-1,""))) | I101: =IF(OR(I100="",E100=""),"",IF(E100<=0,"",IFERROR(I100/E100-1,""))) | J101: =IF(OR(J100="",F100=""),"",IF(F100<=0,"",IFERROR(J100/F100-1,""))) | K101: =IF(OR(K100="",G100=""),"",IF(G100<=0,"",IFERROR(K100/G100-1,""))) | L101: =IF(OR(L100="",H100=""),"",IF(H100<=0,"",IFERROR(L100/H100-1,""))) | M101: =IF(OR(M100="",I100=""),"",IF(I100<=0,"",IFERROR(M100/I100-1,""))) | N101: =IF(OR(N100="",J100=""),"",IF(J100<=0,"",IFERROR(N100/J100-1,""))) | T101: =IF(OR(T100="",S100=""),"",IF(S100<=0,"",IFERROR(T100/S100-1,""))) | U101: =IF(OR(U100="",T100=""),"",IF(T100<=0,"",IFERROR(U100/T100-1,""))) | V101: =IF(OR(V100="",U100=""),"",IF(U100<=0,"",IFERROR(V100/U100-1,""))) | W101: =IF(OR(W100="",V100=""),"",IF(V100<=0,"",IFERROR(W100/V100-1,""))) | X101: =IF(OR(X100="",W100=""),"",IF(W100<=0,"",IFERROR(X100/W100-1,"")))
A102: 판매비와 관리비 | C102: 2368.088 | D102: 2382.11 | E102: 2332.019 | F102: 2438.478 | G102: 2610.778 | H102: 404.956 | I102: 2519.839 | J102: 2565.08 | K102: 2671.831 | L102: 819.333 | M102: 2932.925 | N102: 2987.518 | T102: 947.497 | U102: 2389.56 | V102: 2382.11 | W102: 404.956 | X102: 819.333
...

Sheet 재무상태표
A1: 4368 재무상태표
A2: 재무비율은 기말 잔액 기준 · 분기 손익은 최근 4분기 합산(TTM) | B2: (단위: 백만엔)
A3: 항목 | B3: 참고 | C3: 2026.2Q | D3: 2026.3Q | E3: 2026.4Q | F3: 2027.1Q | G3: 2027.2Q | H3: 2022 | I3: 2023 | J3: 2024 | K3: 2025 | L3: 2026
A4: 자산
A5: 유동자산 | C5: 70108.62 | D5: 75575.306 | E5: 78476.053 | F5: 82179.393 | G5: 89022.075 | H5: 43042.054 | I5: 55344.047 | J5: 55843.033 | K5: 67052.435 | L5: 78476.053
A6: 현금및현금성자산 | C6: 33464.723 | D6: 36726.14 | E6: 41006.795 | F6: 38292.068 | G6: 48452.787 | H6: 20007.336 | I6: 23412.586 | J6: 25247.778 | K6: 31295.73 | L6: 41006.795
A7: 단기금융상품 | H7: 123.756 | I7: 0
A8: 매출채권 | C8: 17296.107 | D8: 18315.013 | E8: 16626.358 | F8: 19621.452 | G8: 19739.931 | H8: 14886.764 | I8: 14968.781 | J8: 16457.71 | K8: 16046.056 | L8: 16626.358
A9: 재고자산 | C9: 18475.747 | D9: 17851.683 | E9: 18409.068 | F9: 18276.103 | G9: 20056.558 | H9: 8894.884 | I9: 16040.657 | J9: 13312.248 | K9: 18153.76 | L9: 18409.068
A10: 기타유동자산 | B10: 총계 − 위 항목 | C10: =IF(OR(C5=""),"",IFERROR(C5-SUM(C6,C7,C8,C9),"")) | D10: =IF(OR(D5=""),"",IFERROR(D5-SUM(D6,D7,D8,D9),"")) | E10: =IF(OR(E5=""),"",IFERROR(E5-SUM(E6,E7,E8,E9),"")) | F10: =IF(OR(F5=""),"",IFERROR(F5-SUM(F6,F7,F8,F9),"")) | G10: =IF(OR(G5=""),"",IFERROR(G5-SUM(G6,G7,G8,G9),"")) | H10: =IF(OR(H5=""),"",IFERROR(H5-SUM(H6,H7,H8,H9),"")) | I10: =IF(OR(I5=""),"",IFERROR(I5-SUM(I6,I7,I8,I9),"")) | J10: =IF(OR(J5=""),"",IFERROR(J5-SUM(J6,J7,J8,J9),"")) | ... L10: =IF(OR(L5=""),"",IFERROR(L5-SUM(L6,L7,L8,L9),""))
A11: 비유동자산 | C11: 74341.252 | D11: 73847.389 | E11: 73780.224 | F11: 84650.243 | G11: 82788.284 | H11: 40969.475 | I11: 58184.824 | J11: 65661.627 | K11: 74449.636 | L11: 73780.224
A12: 유형자산 | C12: 67053.077 | D12: 64719.999 | E12: 64540.33 | F12: 75667.07 | G12: 74392.106 | H12: 32662.44 | I12: 54301.501 | J12: 55305.885 | K12: 66982.585 | L12: 64540.33
A13: 무형자산 | C13: 3751.406 | D13: 5875.494 | E13: 5490.989 | F13: 5147.19 | G13: 4751.72 | H13: 1714.606 | I13: 1346.426 | J13: 2940.678 | K13: 4006.424 | L13: 5490.989
A14: 투자부동산
A15: 기타비유동자산 | B15: 총계 − 위 항목 | C15: =IF(OR(C11=""),"",IFERROR(C11-SUM(C12,C13,C14),"")) | D15: =IF(OR(D11=""),"",IFERROR(D11-SUM(D12,D13,D14),"")) | E15: =IF(OR(E11=""),"",IFERROR(E11-SUM(E12,E13,E14),"")) | F15: =IF(OR(F11=""),"",IFERROR(F11-SUM(F12,F13,F14),"")) | G15: =IF(OR(G11=""),"",IFERROR(G11-SUM(G12,G13,G14),"")) | H15: =IF(OR(H11=""),"",IFERROR(H11-SUM(H12,H13,H14),"")) | I15: =IF(OR(I11=""),"",IFERROR(I11-SUM(I12,I13,I14),"")) | J15: =IF(OR(J11=""),"",IFERROR(J11-SUM(J12,J13,J14),"")) | ... L15: =IF(OR(L11=""),"",IFERROR(L11-SUM(L12,L13,L14),""))
A16: 자산총계 | C16: 144449.87 | D16: 149422.7 | E16: 152256.28 | F16: 166829.64 | G16: 171810.36 | H16: 84011.529 | I16: 113528.87 | J16: 121504.66 | K16: 141502.07 | L16: 152256.28
A17: 부채
A18: 유동부채 | C18: 17719.952 | D18: 20221.903 | E18: 19844.13 | F18: 29631.79 | G18: 31159.777 | H18: 14735.91 | I18: 23908.669 | J18: 15904.377 | K18: 18489.603 | L18: 19844.13
A19: 매입채무 | C19: 2968.632 | D19: 2641.505 | E19: 2836.663 | F19: 3304.236 | G19: 3655.977 | H19: 3859.611 | I19: 3190.61 | J19: 2375.457 | K19: 3073.443 | L19: 2836.663
A20: 단기차입금
A21: 유동성장기부채 | C21: 4000 | D21: 4000 | E21: 4000 | F21: 4000 | G21: 4000 | J21: 0 | K21: 3100 | L21: 4000
A22: 기타유동부채 | B22: 총계 − 위 항목 | C22: =IF(OR(C18=""),"",IFERROR(C18-SUM(C19,C20,C21),"")) | D22: =IF(OR(D18=""),"",IFERROR(D18-SUM(D19,D20,D21),"")) | E22: =IF(OR(E18=""),"",IFERROR(E18-SUM(E19,E20,E21),"")) | F22: =IF(OR(F18=""),"",IFERROR(F18-SUM(F19,F20,F21),"")) | G22: =IF(OR(G18=""),"",IFERROR(G18-SUM(G19,G20,G21),"")) | H22: =IF(OR(H18=""),"",IFERROR(H18-SUM(H19,H20,H21),"")) | I22: =IF(OR(I18=""),"",IFERROR(I18-SUM(I19,I20,I21),"")) | J22: =IF(OR(J18=""),"",IFERROR(J18-SUM(J19,J20,J21),"")) | ... L22: =IF(OR(L18=""),"",IFERROR(L18-SUM(L19,L20,L21),""))
A23: 비유동부채 | C23: 16941.762 | D23: 16058.143 | E23: 15195.224 | F23: 14193.227 | G23: 13181.904 | H23: 1848.497 | I23: 2117.377 | J23: 21951.925 | K23: 18963.49 | L23: 15195.224
A24: 장기차입금 | C24: 14900 | D24: 14000 | E24: 12900 | F24: 11900 | G24: 10900 | I24: 0 | J24: 20000 | K24: 16900 | L24: 12900
A25: 사채
A26: 기타비유동부채 | B26: 총계 − 위 항목 | C26: =IF(OR(C23=""),"",IFERROR(C23-SUM(C24,C25),"")) | D26: =IF(OR(D23=""),"",IFERROR(D23-SUM(D24,D25),"")) | E26: =IF(OR(E23=""),"",IFERROR(E23-SUM(E24,E25),"")) | F26: =IF(OR(F23=""),"",IFERROR(F23-SUM(F24,F25),"")) | G26: =IF(OR(G23=""),"",IFERROR(G23-SUM(G24,G25),"")) | H26: =IF(OR(H23=""),"",IFERROR(H23-SUM(H24,H25),"")) | I26: =IF(OR(I23=""),"",IFERROR(I23-SUM(I24,I25),"")) | J26: =IF(OR(J23=""),"",IFERROR(J23-SUM(J24,J25),"")) | ... L26: =IF(OR(L23=""),"",IFERROR(L23-SUM(L24,L25),""))
A27: 부채총계 | C27: 34661.714 | D27: 36280.047 | E27: 35039.354 | F27: 43825.017 | G27: 44341.682 | H27: 16584.408 | I27: 26026.047 | J27: 37856.303 | K27: 37453.093 | L27: 35039.354
A28: 총차입금 | B28: 단기+유동성장기+장기+사채 | C28: =SUM(C20,C21,C24,C25) | D28: =SUM(D20,D21,D24,D25) | E28: =SUM(E20,E21,E24,E25) | F28: =SUM(F20,F21,F24,F25) | G28: =SUM(G20,G21,G24,G25) | H28: =SUM(H20,H21,H24,H25) | I28: =SUM(I20,I21,I24,I25) | J28: =SUM(J20,J21,J24,J25) | ... L28: =SUM(L20,L21,L24,L25)
A29: 순차입금 | B29: 음수 = 순현금 | C29: =C28-C6-N(C7) | D29: =D28-D6-N(D7) | E29: =E28-E6-N(E7) | F29: =F28-F6-N(F7) | G29: =G28-G6-N(G7) | H29: =H28-H6-N(H7) | I29: =I28-I6-N(I7) | J29: =J28-J6-N(J7) | ... L29: =L28-L6-N(L7)
A30: 자본
A31: 지배주주지분 | C31: 109788.16 | D31: 113142.65 | E31: 117216.92 | F31: 123004.62 | G31: 127468.68 | H31: 67427.121 | I31: 87502.824 | J31: 83648.357 | K31: 104048.98 | L31: 117216.92
A32: 자본금 | C32: 4334.047 | D32: 4334.047 | E32: 4334.047 | F32: 4334.047 | G32: 4334.047 | H32: 4334.047 | I32: 4334.047 | J32: 4334.047 | K32: 4334.047 | L32: 4334.047
A33: 이익잉여금 | C33: 96927.074 | D33: 99298.047 | E33: 102917.63 | F33: 108160.64 | G33: 113134.35 | H33: 58941.095 | I33: 76183.899 | J33: 75275.034 | K33: 91405.565 | L33: 102917.63
A34: 비지배지분
A35: 자본총계 | C35: 109788.16 | D35: 113142.65 | E35: 117216.92 | F35: 123004.62 | G35: 127468.68 | H35: 67427.121 | I35: 87502.824 | J35: 83648.357 | K35: 104048.98 | L35: 117216.92
A36: 현금흐름 요약 | B36: 분기 = TTM (있을 때만)
A37: 영업활동현금흐름 | C37: 19734.078 | D37: 21780.773 | E37: 24793.525 | F37: 25249.398 | G37: 31166.35 | H37: 10199.062 | I37: 13925.984 | J37: 7061.38 | K37: 22701.537 | L37: 24793.525
A38: CAPEX (유·무형 취득) | B38: 양수로 입력 | C38: 14601.445 | D38: 8166.968 | E38: 10109.93 | F38: 9230.36 | G38: 10139.343 | H38: 9621.672 | I38: 13634.807 | J38: 17587.579 | K38: 20138.778 | L38: 10109.93
A39: FCF | C39: =IF(OR(C37="",C38=""),"",IFERROR(C37-C38,"")) | D39: =IF(OR(D37="",D38=""),"",IFERROR(D37-D38,"")) | E39: =IF(OR(E37="",E38=""),"",IFERROR(E37-E38,"")) | F39: =IF(OR(F37="",F38=""),"",IFERROR(F37-F38,"")) | G39: =IF(OR(G37="",G38=""),"",IFERROR(G37-G38,"")) | H39: =IF(OR(H37="",H38=""),"",IFERROR(H37-H38,"")) | I39: =IF(OR(I37="",I38=""),"",IFERROR(I37-I38,"")) | J39: =IF(OR(J37="",J38=""),"",IFERROR(J37-J38,"")) | ... L39: =IF(OR(L37="",L38=""),"",IFERROR(L37-L38,""))
A40: 배당금 지급 | B40: 양수로 입력 | C40: 2572.589 | D40: 2784.337 | E40: 2784.923 | F40: 2892.173 | G40: 2889.396 | H40: 1768.811 | I40: 2114.417 | J40: 2325.355 | K40: 2396.208 | L40: 2784.923
A41: 주요 재무 비율 | B41: 기준 (빨간 글씨 = 미달)
A42: 안정성
A43: 부채비율 | B43: 100%↓ | C43: =IF(OR(C27="",C35=""),"",IFERROR(C27/C35,"")) | D43: =IF(OR(D27="",D35=""),"",IFERROR(D27/D35,"")) | E43: =IF(OR(E27="",E35=""),"",IFERROR(E27/E35,"")) | F43: =IF(OR(F27="",F35=""),"",IFERROR(F27/F35,"")) | G43: =IF(OR(G27="",G35=""),"",IFERROR(G27/G35,"")) | H43: =IF(OR(H27="",H35=""),"",IFERROR(H27/H35,"")) | I43: =IF(OR(I27="",I35=""),"",IFERROR(I27/I35,"")) | J43: =IF(OR(J27="",J35=""),"",IFERROR(J27/J35,"")) | ... L43: =IF(OR(L27="",L35=""),"",IFERROR(L27/L35,""))
A44: 순차입금비율 | B44: 0%↓ 순현금 | C44: =IF(OR(C29="",C35=""),"",IFERROR(C29/C35,"")) | D44: =IF(OR(D29="",D35=""),"",IFERROR(D29/D35,"")) | E44: =IF(OR(E29="",E35=""),"",IFERROR(E29/E35,"")) | F44: =IF(OR(F29="",F35=""),"",IFERROR(F29/F35,"")) | G44: =IF(OR(G29="",G35=""),"",IFERROR(G29/G35,"")) | H44: =IF(OR(H29="",H35=""),"",IFERROR(H29/H35,"")) | I44: =IF(OR(I29="",I35=""),"",IFERROR(I29/I35,"")) | J44: =IF(OR(J29="",J35=""),"",IFERROR(J29/J35,"")) | ... L44: =IF(OR(L29="",L35=""),"",IFERROR(L29/L35,""))
A45: 자기자본비율 | B45: 50%↑ | C45: =IF(OR(C35="",C16=""),"",IFERROR(C35/C16,"")) | D45: =IF(OR(D35="",D16=""),"",IFERROR(D35/D16,"")) | E45: =IF(OR(E35="",E16=""),"",IFERROR(E35/E16,"")) | F45: =IF(OR(F35="",F16=""),"",IFERROR(F35/F16,"")) | G45: =IF(OR(G35="",G16=""),"",IFERROR(G35/G16,"")) | H45: =IF(OR(H35="",H16=""),"",IFERROR(H35/H16,"")) | I45: =IF(OR(I35="",I16=""),"",IFERROR(I35/I16,"")) | J45: =IF(OR(J35="",J16=""),"",IFERROR(J35/J16,"")) | ... L45: =IF(OR(L35="",L16=""),"",IFERROR(L35/L16,""))
A46: 유동비율 | B46: 150%↑ | C46: =IF(OR(C5="",C18=""),"",IFERROR(C5/C18,"")) | D46: =IF(OR(D5="",D18=""),"",IFERROR(D5/D18,"")) | E46: =IF(OR(E5="",E18=""),"",IFERROR(E5/E18,"")) | F46: =IF(OR(F5="",F18=""),"",IFERROR(F5/F18,"")) | G46: =IF(OR(G5="",G18=""),"",IFERROR(G5/G18,"")) | H46: =IF(OR(H5="",H18=""),"",IFERROR(H5/H18,"")) | I46: =IF(OR(I5="",I18=""),"",IFERROR(I5/I18,"")) | J46: =IF(OR(J5="",J18=""),"",IFERROR(J5/J18,"")) | ... L46: =IF(OR(L5="",L18=""),"",IFERROR(L5/L18,""))
A47: 당좌비율 | B47: 100%↑ | C47: =IF(OR(C5="",C18=""),"",IFERROR((C5-N(C9))/C18,"")) | D47: =IF(OR(D5="",D18=""),"",IFERROR((D5-N(D9))/D18,"")) | E47: =IF(OR(E5="",E18=""),"",IFERROR((E5-N(E9))/E18,"")) | F47: =IF(OR(F5="",F18=""),"",IFERROR((F5-N(F9))/F18,"")) | G47: =IF(OR(G5="",G18=""),"",IFERROR((G5-N(G9))/G18,"")) | H47: =IF(OR(H5="",H18=""),"",IFERROR((H5-N(H9))/H18,"")) | I47: =IF(OR(I5="",I18=""),"",IFERROR((I5-N(I9))/I18,"")) | J47: =IF(OR(J5="",J18=""),"",IFERROR((J5-N(J9))/J18,"")) | ... L47: =IF(OR(L5="",L18=""),"",IFERROR((L5-N(L9))/L18,""))
A48: 이자보상배율 | B48: 5x↑ (금융원가 기준) | C48: =IFERROR((IF(COUNT('연간'!G31:J31)<4,"",SUM('연간'!G31:J31)))/(IF(COUNT('연간'!G53:J53)<4,"",SUM('연간'!G53:J53))),"") | D48: =IFERROR((IF(COUNT('연간'!H31:K31)<4,"",SUM('연간'!H31:K31)))/(IF(COUNT('연간'!H53:K53)<4,"",SUM('연간'!H53:K53))),"") | E48: =IFERROR((IF(COUNT('연간'!I31:L31)<4,"",SUM('연간'!I31:L31)))/(IF(COUNT('연간'!I53:L53)<4,"",SUM('연간'!I53:L53))),"") | F48: =IFERROR((IF(COUNT('연간'!J31:M31)<4,"",SUM('연간'!J31:M31)))/(IF(COUNT('연간'!J53:M53)<4,"",SUM('연간'!J53:M53))),"") | G48: =IFERROR((IF(COUNT('연간'!K31:N31)<4,"",SUM('연간'!K31:N31)))/(IF(COUNT('연간'!K53:N53)<4,"",SUM('연간'!K53:N53))),"") | H48: =IFERROR(('연간'!T31)/('연간'!T53),"") | I48: =IFERROR(('연간'!U31)/('연간'!U53),"") | J48: =IFERROR(('연간'!V31)/('연간'!V53),"") | K48: =IFERROR(('연간'!W31)/('연간'!W53),"") | L48: =IFERROR(('연간'!X31)/('연간'!X53),"")
A49: 차입금 상환연수 | B49: 4년↓ (버핏) | C49: =IFERROR(IF((IF(COUNT('연간'!G61:J61)<4,"",SUM('연간'!G61:J61)))<=0,"적자",C28/(IF(COUNT('연간'!G61:J61)<4,"",SUM('연간'!G61:J61)))),"") | D49: =IFERROR(IF((IF(COUNT('연간'!H61:K61)<4,"",SUM('연간'!H61:K61)))<=0,"적자",D28/(IF(COUNT('연간'!H61:K61)<4,"",SUM('연간'!H61:K61)))),"") | E49: =IFERROR(IF((IF(COUNT('연간'!I61:L61)<4,"",SUM('연간'!I61:L61)))<=0,"적자",E28/(IF(COUNT('연간'!I61:L61)<4,"",SUM('연간'!I61:L61)))),"") | F49: =IFERROR(IF((IF(COUNT('연간'!J61:M61)<4,"",SUM('연간'!J61:M61)))<=0,"적자",F28/(IF(COUNT('연간'!J61:M61)<4,"",SUM('연간'!J61:M61)))),"") | G49: =IFERROR(IF((IF(COUNT('연간'!K61:N61)<4,"",SUM('연간'!K61:N61)))<=0,"적자",G28/(IF(COUNT('연간'!K61:N61)<4,"",SUM('연간'!K61:N61)))),"") | H49: =IFERROR(IF(('연간'!T61)<=0,"적자",H28/('연간'!T61)),"") | I49: =IFERROR(IF(('연간'!U61)<=0,"적자",I28/('연간'!U61)),"") | J49: =IFERROR(IF(('연간'!V61)<=0,"적자",J28/('연간'!V61)),"") | K49: =IFERROR(IF(('연간'!W61)<=0,"적자",K28/('연간'!W61)),"") | L49: =IFERROR(IF(('연간'!X61)<=0,"적자",L28/('연간'!X61)),"")
A50: 수익성
A51: ROE | B51: 15%↑ (버핏) | C51: =IFERROR((IF(COUNT('연간'!G61:J61)<4,"",SUM('연간'!G61:J61)))/C31,"") | D51: =IFERROR((IF(COUNT('연간'!H61:K61)<4,"",SUM('연간'!H61:K61)))/D31,"") | E51: =IFERROR((IF(COUNT('연간'!I61:L61)<4,"",SUM('연간'!I61:L61)))/E31,"") | F51: =IFERROR((IF(COUNT('연간'!J61:M61)<4,"",SUM('연간'!J61:M61)))/F31,"") | G51: =IFERROR((IF(COUNT('연간'!K61:N61)<4,"",SUM('연간'!K61:N61)))/G31,"") | H51: =IFERROR(('연간'!T61)/H31,"") | I51: =IFERROR(('연간'!U61)/I31,"") | J51: =IFERROR(('연간'!V61)/J31,"") | K51: =IFERROR(('연간'!W61)/K31,"") | L51: =IFERROR(('연간'!X61)/L31,"")
A52: ROA | B52: 5%↑ | C52: =IFERROR((IF(COUNT('연간'!G59:J59)<4,"",SUM('연간'!G59:J59)))/C16,"") | D52: =IFERROR((IF(COUNT('연간'!H59:K59)<4,"",SUM('연간'!H59:K59)))/D16,"") | E52: =IFERROR((IF(COUNT('연간'!I59:L59)<4,"",SUM('연간'!I59:L59)))/E16,"") | F52: =IFERROR((IF(COUNT('연간'!J59:M59)<4,"",SUM('연간'!J59:M59)))/F16,"") | G52: =IFERROR((IF(COUNT('연간'!K59:N59)<4,"",SUM('연간'!K59:N59)))/G16,"") | H52: =IFERROR(('연간'!T59)/H16,"") | I52: =IFERROR(('연간'!U59)/I16,"") | J52: =IFERROR(('연간'!V59)/J16,"") | K52: =IFERROR(('연간'!W59)/K16,"") | L52: =IFERROR(('연간'!X59)/L16,"")
A53: ROIC | B53: 10%↑ (세후영업이익 기준) | C53: =IFERROR((IF(COUNT('연간'!G31:J31)<4,"",SUM('연간'!G31:J31)))*(1-0.3)/(C35+C29),"") | D53: =IFERROR((IF(COUNT('연간'!H31:K31)<4,"",SUM('연간'!H31:K31)))*(1-0.3)/(D35+D29),"") | E53: =IFERROR((IF(COUNT('연간'!I31:L31)<4,"",SUM('연간'!I31:L31)))*(1-0.3)/(E35+E29),"") | F53: =IFERROR((IF(COUNT('연간'!J31:M31)<4,"",SUM('연간'!J31:M31)))*(1-0.3)/(F35+F29),"") | G53: =IFERROR((IF(COUNT('연간'!K31:N31)<4,"",SUM('연간'!K31:N31)))*(1-0.3)/(G35+G29),"") | H53: =IFERROR(('연간'!T31)*(1-0.3)/(H35+H29),"") | I53: =IFERROR(('연간'!U31)*(1-0.3)/(I35+I29),"") | J53: =IFERROR(('연간'!V31)*(1-0.3)/(J35+J29),"") | K53: =IFERROR(('연간'!W31)*(1-0.3)/(K35+K29),"") | L53: =IFERROR(('연간'!X31)*(1-0.3)/(L35+L29),"")
A54: 매출총이익률 (GPM) | B54: 40%↑ (해자 신호) | C54: =IFERROR((IF(COUNT('연간'!G25:J25)<4,"",SUM('연간'!G25:J25)))/(IF(COUNT('연간'!G4:J4)<4,"",SUM('연간'!G4:J4))),"") | D54: =IFERROR((IF(COUNT('연간'!H25:K25)<4,"",SUM('연간'!H25:K25)))/(IF(COUNT('연간'!H4:K4)<4,"",SUM('연간'!H4:K4))),"") | E54: =IFERROR((IF(COUNT('연간'!I25:L25)<4,"",SUM('연간'!I25:L25)))/(IF(COUNT('연간'!I4:L4)<4,"",SUM('연간'!I4:L4))),"") | F54: =IFERROR((IF(COUNT('연간'!J25:M25)<4,"",SUM('연간'!J25:M25)))/(IF(COUNT('연간'!J4:M4)<4,"",SUM('연간'!J4:M4))),"") | G54: =IFERROR((IF(COUNT('연간'!K25:N25)<4,"",SUM('연간'!K25:N25)))/(IF(COUNT('연간'!K4:N4)<4,"",SUM('연간'!K4:N4))),"") | H54: =IFERROR(('연간'!T25)/('연간'!T4),"") | I54: =IFERROR(('연간'!U25)/('연간'!U4),"") | J54: =IFERROR(('연간'!V25)/('연간'!V4),"") | K54: =IFERROR(('연간'!W25)/('연간'!W4),"") | L54: =IFERROR(('연간'!X25)/('연간'!X4),"")
A55: 영업이익률 (OPM) | B55: 15%↑ | C55: =IFERROR((IF(COUNT('연간'!G31:J31)<4,"",SUM('연간'!G31:J31)))/(IF(COUNT('연간'!G4:J4)<4,"",SUM('연간'!G4:J4))),"") | D55: =IFERROR((IF(COUNT('연간'!H31:K31)<4,"",SUM('연간'!H31:K31)))/(IF(COUNT('연간'!H4:K4)<4,"",SUM('연간'!H4:K4))),"") | E55: =IFERROR((IF(COUNT('연간'!I31:L31)<4,"",SUM('연간'!I31:L31)))/(IF(COUNT('연간'!I4:L4)<4,"",SUM('연간'!I4:L4))),"") | F55: =IFERROR((IF(COUNT('연간'!J31:M31)<4,"",SUM('연간'!J31:M31)))/(IF(COUNT('연간'!J4:M4)<4,"",SUM('연간'!J4:M4))),"") | G55: =IFERROR((IF(COUNT('연간'!K31:N31)<4,"",SUM('연간'!K31:N31)))/(IF(COUNT('연간'!K4:N4)<4,"",SUM('연간'!K4:N4))),"") | H55: =IFERROR(('연간'!T31)/('연간'!T4),"") | I55: =IFERROR(('연간'!U31)/('연간'!U4),"") | J55: =IFERROR(('연간'!V31)/('연간'!V4),"") | K55: =IFERROR(('연간'!W31)/('연간'!W4),"") | L55: =IFERROR(('연간'!X31)/('연간'!X4),"")
A56: 순이익률 | B56: 10%↑ | C56: =IFERROR((IF(COUNT('연간'!G59:J59)<4,"",SUM('연간'!G59:J59)))/(IF(COUNT('연간'!G4:J4)<4,"",SUM('연간'!G4:J4))),"") | D56: =IFERROR((IF(COUNT('연간'!H59:K59)<4,"",SUM('연간'!H59:K59)))/(IF(COUNT('연간'!H4:K4)<4,"",SUM('연간'!H4:K4))),"") | E56: =IFERROR((IF(COUNT('연간'!I59:L59)<4,"",SUM('연간'!I59:L59)))/(IF(COUNT('연간'!I4:L4)<4,"",SUM('연간'!I4:L4))),"") | F56: =IFERROR((IF(COUNT('연간'!J59:M59)<4,"",SUM('연간'!J59:M59)))/(IF(COUNT('연간'!J4:M4)<4,"",SUM('연간'!J4:M4))),"") | G56: =IFERROR((IF(COUNT('연간'!K59:N59)<4,"",SUM('연간'!K59:N59)))/(IF(COUNT('연간'!K4:N4)<4,"",SUM('연간'!K4:N4))),"") | H56: =IFERROR(('연간'!T59)/('연간'!T4),"") | I56: =IFERROR(('연간'!U59)/('연간'!U4),"") | J56: =IFERROR(('연간'!V59)/('연간'!V4),"") | K56: =IFERROR(('연간'!W59)/('연간'!W4),"") | L56: =IFERROR(('연간'!X59)/('연간'!X4),"")
A57: 효율성 (회전율)
A58: 총자산회전율 | B58: 높을수록↑ | C58: =IFERROR((IF(COUNT('연간'!G4:J4)<4,"",SUM('연간'!G4:J4)))/C16,"") | D58: =IFERROR((IF(COUNT('연간'!H4:K4)<4,"",SUM('연간'!H4:K4)))/D16,"") | E58: =IFERROR((IF(COUNT('연간'!I4:L4)<4,"",SUM('연간'!I4:L4)))/E16,"") | F58: =IFERROR((IF(COUNT('연간'!J4:M4)<4,"",SUM('연간'!J4:M4)))/F16,"") | G58: =IFERROR((IF(COUNT('연간'!K4:N4)<4,"",SUM('연간'!K4:N4)))/G16,"") | H58: =IFERROR(('연간'!T4)/H16,"") | I58: =IFERROR(('연간'!U4)/I16,"") | J58: =IFERROR(('연간'!V4)/J16,"") | K58: =IFERROR(('연간'!W4)/K16,"") | L58: =IFERROR(('연간'!X4)/L16,"")
A59: 매출채권회전일수 | B59: 짧을수록↑ | C59: =IFERROR(C8/(IF(COUNT('연간'!G4:J4)<4,"",SUM('연간'!G4:J4)))*365,"") | D59: =IFERROR(D8/(IF(COUNT('연간'!H4:K4)<4,"",SUM('연간'!H4:K4)))*365,"") | E59: =IFERROR(E8/(IF(COUNT('연간'!I4:L4)<4,"",SUM('연간'!I4:L4)))*365,"") | F59: =IFERROR(F8/(IF(COUNT('연간'!J4:M4)<4,"",SUM('연간'!J4:M4)))*365,"") | G59: =IFERROR(G8/(IF(COUNT('연간'!K4:N4)<4,"",SUM('연간'!K4:N4)))*365,"") | H59: =IFERROR(H8/('연간'!T4)*365,"") | I59: =IFERROR(I8/('연간'!U4)*365,"") | J59: =IFERROR(J8/('연간'!V4)*365,"") | K59: =IFERROR(K8/('연간'!W4)*365,"") | L59: =IFERROR(L8/('연간'!X4)*365,"")
A60: 재고자산회전일수 | B60: 짧을수록↑ | C60: =IFERROR(C9/(IF(COUNT('연간'!G23:J23)<4,"",SUM('연간'!G23:J23)))*365,"") | D60: =IFERROR(D9/(IF(COUNT('연간'!H23:K23)<4,"",SUM('연간'!H23:K23)))*365,"") | E60: =IFERROR(E9/(IF(COUNT('연간'!I23:L23)<4,"",SUM('연간'!I23:L23)))*365,"") | F60: =IFERROR(F9/(IF(COUNT('연간'!J23:M23)<4,"",SUM('연간'!J23:M23)))*365,"") | G60: =IFERROR(G9/(IF(COUNT('연간'!K23:N23)<4,"",SUM('연간'!K23:N23)))*365,"") | H60: =IFERROR(H9/('연간'!T23)*365,"") | I60: =IFERROR(I9/('연간'!U23)*365,"") | J60: =IFERROR(J9/('연간'!V23)*365,"") | K60: =IFERROR(K9/('연간'!W23)*365,"") | L60: =IFERROR(L9/('연간'!X23)*365,"")
A61: 매입채무회전일수 | B61: 길수록 유리 | C61: =IFERROR(C19/(IF(COUNT('연간'!G23:J23)<4,"",SUM('연간'!G23:J23)))*365,"") | D61: =IFERROR(D19/(IF(COUNT('연간'!H23:K23)<4,"",SUM('연간'!H23:K23)))*365,"") | E61: =IFERROR(E19/(IF(COUNT('연간'!I23:L23)<4,"",SUM('연간'!I23:L23)))*365,"") | F61: =IFERROR(F19/(IF(COUNT('연간'!J23:M23)<4,"",SUM('연간'!J23:M23)))*365,"") | G61: =IFERROR(G19/(IF(COUNT('연간'!K23:N23)<4,"",SUM('연간'!K23:N23)))*365,"") | H61: =IFERROR(H19/('연간'!T23)*365,"") | I61: =IFERROR(I19/('연간'!U23)*365,"") | J61: =IFERROR(J19/('연간'!V23)*365,"") | K61: =IFERROR(K19/('연간'!W23)*365,"") | L61: =IFERROR(L19/('연간'!X23)*365,"")
A62: 현금전환주기 (CCC) | B62: 짧을수록↑ | C62: =IF(OR(C59="",C60="",C61=""),"",IFERROR(C59+C60-C61,"")) | D62: =IF(OR(D59="",D60="",D61=""),"",IFERROR(D59+D60-D61,"")) | E62: =IF(OR(E59="",E60="",E61=""),"",IFERROR(E59+E60-E61,"")) | F62: =IF(OR(F59="",F60="",F61=""),"",IFERROR(F59+F60-F61,"")) | G62: =IF(OR(G59="",G60="",G61=""),"",IFERROR(G59+G60-G61,"")) | H62: =IF(OR(H59="",H60="",H61=""),"",IFERROR(H59+H60-H61,"")) | I62: =IF(OR(I59="",I60="",I61=""),"",IFERROR(I59+I60-I61,"")) | J62: =IF(OR(J59="",J60="",J61=""),"",IFERROR(J59+J60-J61,"")) | ... L62: =IF(OR(L59="",L60="",L61=""),"",IFERROR(L59+L60-L61,""))
A63: 현금흐름
A64: 영업현금흐름 / 순이익 | B64: 1x↑ (이익의 질) | C64: =IF(C37="","",IFERROR(C37/(IF(COUNT('연간'!G59:J59)<4,"",SUM('연간'!G59:J59))),"")) | D64: =IF(D37="","",IFERROR(D37/(IF(COUNT('연간'!H59:K59)<4,"",SUM('연간'!H59:K59))),"")) | E64: =IF(E37="","",IFERROR(E37/(IF(COUNT('연간'!I59:L59)<4,"",SUM('연간'!I59:L59))),"")) | F64: =IF(F37="","",IFERROR(F37/(IF(COUNT('연간'!J59:M59)<4,"",SUM('연간'!J59:M59))),"")) | G64: =IF(G37="","",IFERROR(G37/(IF(COUNT('연간'!K59:N59)<4,"",SUM('연간'!K59:N59))),"")) | H64: =IF(H37="","",IFERROR(H37/('연간'!T59),"")) | I64: =IF(I37="","",IFERROR(I37/('연간'!U59),"")) | J64: =IF(J37="","",IFERROR(J37/('연간'!V59),"")) | K64: =IF(K37="","",IFERROR(K37/('연간'!W59),"")) | L64: =IF(L37="","",IFERROR(L37/('연간'!X59),""))
A65: FCF 마진 | B65: 5%↑ | C65: =IF(C39="","",IFERROR(C39/(IF(COUNT('연간'!G4:J4)<4,"",SUM('연간'!G4:J4))),"")) | D65: =IF(D39="","",IFERROR(D39/(IF(COUNT('연간'!H4:K4)<4,"",SUM('연간'!H4:K4))),"")) | E65: =IF(E39="","",IFERROR(E39/(IF(COUNT('연간'!I4:L4)<4,"",SUM('연간'!I4:L4))),"")) | F65: =IF(F39="","",IFERROR(F39/(IF(COUNT('연간'!J4:M4)<4,"",SUM('연간'!J4:M4))),"")) | G65: =IF(G39="","",IFERROR(G39/(IF(COUNT('연간'!K4:N4)<4,"",SUM('연간'!K4:N4))),"")) | H65: =IF(H39="","",IFERROR(H39/('연간'!T4),"")) | I65: =IF(I39="","",IFERROR(I39/('연간'!U4),"")) | J65: =IF(J39="","",IFERROR(J39/('연간'!V4),"")) | K65: =IF(K39="","",IFERROR(K39/('연간'!W4),"")) | L65: =IF(L39="","",IFERROR(L39/('연간'!X4),""))
A66: CAPEX / 매출 | B66: 낮을수록↑ (자본 가벼움) | C66: =IF(C38="","",IFERROR(C38/(IF(COUNT('연간'!G4:J4)<4,"",SUM('연간'!G4:J4))),"")) | D66: =IF(D38="","",IFERROR(D38/(IF(COUNT('연간'!H4:K4)<4,"",SUM('연간'!H4:K4))),"")) | E66: =IF(E38="","",IFERROR(E38/(IF(COUNT('연간'!I4:L4)<4,"",SUM('연간'!I4:L4))),"")) | F66: =IF(F38="","",IFERROR(F38/(IF(COUNT('연간'!J4:M4)<4,"",SUM('연간'!J4:M4))),"")) | G66: =IF(G38="","",IFERROR(G38/(IF(COUNT('연간'!K4:N4)<4,"",SUM('연간'!K4:N4))),"")) | H66: =IF(H38="","",IFERROR(H38/('연간'!T4),"")) | I66: =IF(I38="","",IFERROR(I38/('연간'!U4),"")) | J66: =IF(J38="","",IFERROR(J38/('연간'!V4),"")) | K66: =IF(K38="","",IFERROR(K38/('연간'!W4),"")) | L66: =IF(L38="","",IFERROR(L38/('연간'!X4),""))
A67: 배당성향 | B67: 참고 | C67: =IF(C40="","",IFERROR(C40/(IF(COUNT('연간'!G61:J61)<4,"",SUM('연간'!G61:J61))),"")) | D67: =IF(D40="","",IFERROR(D40/(IF(COUNT('연간'!H61:K61)<4,"",SUM('연간'!H61:K61))),"")) | E67: =IF(E40="","",IFERROR(E40/(IF(COUNT('연간'!I61:L61)<4,"",SUM('연간'!I61:L61))),"")) | F67: =IF(F40="","",IFERROR(F40/(IF(COUNT('연간'!J61:M61)<4,"",SUM('연간'!J61:M61))),"")) | G67: =IF(G40="","",IFERROR(G40/(IF(COUNT('연간'!K61:N61)<4,"",SUM('연간'!K61:N61))),"")) | H67: =IF(H40="","",IFERROR(H40/('연간'!T61),"")) | I67: =IF(I40="","",IFERROR(I40/('연간'!U61),"")) | J67: =IF(J40="","",IFERROR(J40/('연간'!V61),"")) | K67: =IF(K40="","",IFERROR(K40/('연간'!W61),"")) | L67: =IF(L40="","",IFERROR(L40/('연간'!X61),""))
A69: 재무상태표 · 전 항목 | B69: 분기 말 잔액
A70: 항목 | B70: 참고 | C70: 2026.2Q | D70: 2026.3Q | E70: 2026.4Q | F70: 2027.1Q | G70: 2027.2Q | H70: 2022 | I70: 2023 | J70: 2024 | K70: 2025 | L70: 2026
A71: 현금 및 예금 | C71: 33464.723 | D71: 36726.14 | E71: 41006.795 | F71: 38292.068 | G71: 48452.787 | H71: 20007.336 | I71: 23412.586 | J71: 25247.778 | K71: 31295.73 | L71: 41006.795
A72: 매출채권 | E72: 14551.07 | H72: 13027.869 | I72: 13296.144 | J72: 14661.399 | K72: 14205.014 | L72: 14551.07
A73: 받을어음·매출채권 | C73: 17296.107 | D73: 18315.013 | E73: 16626.358 | F73: 19621.452 | G73: 19739.931 | H73: 14886.764 | I73: 14968.781 | J73: 16457.71 | K73: 16046.056 | L73: 16626.358
A74: 유가증권 | H74: 123.756 | I74: 0
A75: 상품·제품 | C75: 14409.922 | D75: 13581.04 | E75: 14205.343 | F75: 13100.192 | G75: 14902.014 | H75: 6575.026 | I75: 11880.482 | J75: 10627.481 | K75: 14058.439 | L75: 14205.343
A76: 재공품 | C76: 656.335 | D76: 602.813 | E76: 703.343 | F76: 1017.971 | G76: 785.791 | H76: 630.342 | I76: 691.534 | J76: 686.143 | K76: 675.979 | L76: 703.343
A77: 원재료·저장품 | C77: 3409.49 | D77: 3667.83 | E77: 3500.382 | F77: 4157.94 | G77: 4368.753 | H77: 1689.516 | I77: 3468.641 | J77: 1998.624 | K77: 3419.342 | L77: 3500.382
A78: 미수 소비세 | E78: 1622.623 | K78: 1028.736 | L78: 1622.623
A79: 기타 | C79: 887.486 | D79: 2696.875 | E79: 2450.191 | F79: 6006.849 | G79: 790.799 | H79: 1113.285 | I79: 936.534 | J79: 2623.395 | K79: 543.001 | L79: 2450.191
A80: 대손충당금 | C80: -15.446 | D80: -14.407 | E80: -16.363 | F80: -17.08 | G80: -18.002 | H80: -1.321 | I80: -14.513 | J80: -1.79 | K80: -14.851 | L80: -16.363
A81: 유동자산 합계 | C81: 70108.62 | D81: 75575.306 | E81: 78476.053 | F81: 82179.393 | G81: 89022.075 | H81: 43042.054 | I81: 55344.047 | J81: 55843.033 | K81: 67052.435 | L81: 78476.053
A82: 건물 | E82: 19251.658 | H82: 7392.104 | I82: 7301.688 | J82: 11616.793 | K82: 14848.438 | L82: 19251.658
A83: 구축물 | E83: 5040.061 | H83: 1077.908 | I83: 919.145 | J83: 2973.08 | K83: 3425.724 | L83: 5040.061
A84: 기계장치 | E84: 23102.368 | H84: 5919.047 | I84: 5099.255 | J84: 13339.703 | K84: 16252.021 | L84: 23102.368
A85: 차량운반구 | E85: 8.927 | H85: 11.416 | I85: 43.117 | J85: 27.889 | K85: 17.778 | L85: 8.927
A86: 공구·기구·비품 | E86: 758.299 | H86: 287.578 | I86: 630.186 | J86: 868.13 | K86: 838.95 | L86: 758.299
A87: 건물·구축물 | E87: 41983.664 | H87: 20788.477 | I87: 21392.69 | J87: 29139.532 | K87: 33948.274 | L87: 41983.664
A88: 감가상각누계액 | E88: -16491.484 | H88: -11137.413 | I88: -11974.615 | J88: -13320.922 | K88: -14513.262 | L88: -16491.484
A89: 건물·구축물(순액) | C89: 18913.246 | D89: 24245.286 | E89: 25492.18 | F89: 25019.74 | G89: 24874.576 | H89: 9651.063 | I89: 9418.074 | J89: 15818.609 | K89: 19435.011 | L89: 25492.18
A90: 기계장치·운반구 | E90: 69551.102 | H90: 34369.808 | I90: 35741.898 | J90: 48985.504 | K90: 55532.435 | L90: 69551.102
A91: 감가상각누계액 | E91: -44147.326 | H91: -27320.329 | I91: -29501.284 | J91: -33895.026 | K91: -37040.7 | L91: -44147.326
A92: 기계장치·운반구(순액) | C92: 17719.557 | D92: 27122.361 | E92: 25403.776 | F92: 23899.142 | G92: 22172.937 | H92: 7049.478 | I92: 6240.614 | J92: 15090.477 | K92: 18491.734 | L92: 25403.776
A93: 토지 | C93: 8432.429 | D93: 8439.662 | E93: 8442.867 | F93: 8445.249 | G93: 8440.408 | H93: 6787.206 | I93: 6913.458 | J93: 6787.206 | K93: 8433.034 | L93: 8442.867
A94: 리스자산 | E94: 65.977 | H94: 18.702 | I94: 11.958 | J94: 6.768 | K94: 53.99 | L94: 65.977
A95: 건설중인자산 | C95: 21045.936 | D95: 3963.222 | E95: 4188.076 | F95: 17328.242 | G95: 17919.401 | H95: 11168.474 | I95: 30938.084 | J95: 19686.313 | K95: 19567.556 | L95: 4188.076
A96: 기타 | E96: 5318.982 | H96: 3272.118 | I96: 3831.573 | J96: 4505.891 | K96: 4899.55 | L96: 5318.982
A97: 감가상각누계액 | E97: -4305.552 | H97: -2832.696 | I97: -3040.303 | J97: -3463.787 | K97: -3844.302 | L97: -4305.552
A98: 기타(순액) | C98: 941.907 | D98: 949.466 | E98: 1013.429 | F98: 974.695 | G98: 984.781 | H98: 439.421 | I98: 791.27 | J98: 1042.104 | K98: 1055.247 | L98: 1013.429
A99: 유형자산 합계 | C99: 67053.077 | D99: 64719.999 | E99: 64540.33 | F99: 75667.07 | G99: 74392.106 | H99: 32662.44 | I99: 54301.501 | J99: 55305.885 | K99: 66982.585 | L99: 64540.33
A100: 무형자산 | C100: 3751.406 | D100: 5875.494 | E100: 5490.989 | F100: 5147.19 | G100: 4751.72 | H100: 1714.606 | I100: 1346.426 | J100: 2940.678 | K100: 4006.424 | L100: 5490.989
A101: 투자유가증권 | C101: 805.008 | D101: 602.915 | E101: 679.817 | F101: 894.644 | G101: 764.804 | H101: 1030.246 | I101: 691.304 | J101: 885.432 | K101: 714.487 | L101: 679.817
...

Sheet 섹터 데이터
A1: 4368 섹터·사업 데이터
A2: 2단계 보고서를 만들 때 모은 자료 · 월차 · 출처는 맨 오른쪽
A4: current filing · 상반기
A5: 항목 | B5: 값 | N5: 출처
A6: 매출 | B6: 456 | N6: 2단계 보고서 자료(회사 설명회 자료·공시)
A7: 매출 YoY | B7: 20.9
A8: 영업이익 | B8: 132.9
A9: 영업이익 YoY | B9: 36.4
A10: ord | B10: 133.6
A11: 순이익 | B11: 116.6
A12: 순이익 YoY | B12: 69.5
A13: EPS | B13: 110.23
A15: current filing · 2Q
A16: 항목 | B16: 값 | N16: 출처
A17: 매출 | B17: 227.8 | N17: 2단계 보고서 자료(회사 설명회 자료·공시)
A18: 영업이익 | B18: 71.2
A19: ord | B19: 69.9
A20: 순이익 | B20: 49.7
A21: gp | B21: 101.1
A22: sga | B22: 29.9
A24: current filing · 상반기 pl
A25: 항목 | B25: 값 | N25: 출처
A26: 매출원가 | B26: 263.8 | N26: 2단계 보고서 자료(회사 설명회 자료·공시)
A27: 매출총이익 | B27: 192.1
A28: 판관비 | B28: 59.2
A29: 영업외수익 | B29: 3
A30: 수취이자 | B30: 2.8
A31: 영업외비용 | B31: 2.4
A32: 지급이자 | B32: 0.5
A33: 환차손 | B33: 1.6
A34: 보조금수입(특별이익) | B34: 37
A35: 고정자산제각손(특별손실) | B35: 1.3
A36: 세전 | B36: 169.4
A37: 법인세 | B37: 52.8
A38: 감가상각비 | B38: 61.1
A40: current filing · 상반기 직전 pl
A41: 항목 | B41: 값 | N41: 출처
A42: 매출원가 | B42: 228.7 | N42: 2단계 보고서 자료(회사 설명회 자료·공시)
A43: 매출총이익 | B43: 148.3
A44: 판관비 | B44: 50.8
A45: 보조금 | B45: 0.06
A46: 세전 | B46: 97.9
A47: 감가상각비 | B47: 45.8
A49: current filing · seg 2Q 매출
A50: 항목 | B50: 값 | N50: 출처
A51: 라이프사이언스 | B51: 99.8 | N51: 2단계 보고서 자료(회사 설명회 자료·공시)
A52: 전자재료 | B52: 128
A54: current filing · 가이던스 new
A55: 항목 | B55: 값 | N55: 출처
A56: 매출 | B56: 930 | N56: 2단계 보고서 자료(회사 설명회 자료·공시)
A57: 영업이익 | B57: 280
A58: ord | B58: 281
A59: 순이익 | B59: 219
A60: EPS | B60: 206.99
A61: ebitda | B61: 407
A63: current filing · implied 2h
A64: 항목 | B64: 값 | N64: 출처
A65: 매출 | B65: 474 | N65: 2단계 보고서 자료(회사 설명회 자료·공시)
A66: 영업이익 | B66: 147.1
A67: 순이익 | B67: 102.4
A69: current filing · bs
A70: 항목 | B70: 값 | N70: 출처
A71: 총자산 | B71: 1718.1 | N71: 2단계 보고서 자료(회사 설명회 자료·공시)
A72: 순자산 | B72: 1274.7
A73: 자기자본비율 | B73: 74.2
A74: 현금 | B74: 484.5
A75: 장기차입(1년내 포함) | B75: 149
A76: 건설가계정 | B76: 179.2
A77: 설비관계미지급금 | B77: 138
A79: current filing · cf 상반기
A80: 항목 | B80: 값 | N80: 출처
A81: 영업CF | B81: 179.7 | N81: 2단계 보고서 자료(회사 설명회 자료·공시)
A82: 유형자산취득 | B82: -67.3
A83: 배당 | B83: -14.4
A85: current filing · shares
A86: 항목 | B86: 값 | N86: 출처
A87: issued | B87: 106533000 | N87: 2단계 보고서 자료(회사 설명회 자료·공시)
A88: treasury | B88: 728179
A89: out | B89: 105804821
A91: 부문별 quarterly
A92: 항목 | B92: 2024.3Q | C92: 2024.4Q | D92: 2025.1Q | E92: 2025.2Q | F92: 2025.3Q | G92: 2025.4Q | H92: 2026.1Q | I92: 2026.2Q | J92: 2026.3Q | K92: 2026.4Q | L92: 2027.1Q | M92: 2027.2Q | N92: 출처
A93: 라이프사이언스 | B93: 88.7 | D93: 93.9 | E93: 92.8 | F93: 88.4 | H93: 89.6 | I93: 88.3 | J93: 86.1 | L93: 98.5 | M93: 99.8 | N93: 부문 매출(외부 고객, prep XBRL). 4Q는 연간−3Q누계로 계산. 부문이익 분기값은 prep에 없음 — 결산단신 부문표에서.
A94: 전자재료 | B94: 71.3 | D94: 80.4 | E94: 80.5 | F94: 88.3 | H94: 97 | I94: 102.2 | J94: 116.1 | L94: 129.7 | M94: 128
A96: bs annual
A97: 항목 | B97: 2022 | C97: 2023 | D97: 2024 | E97: 2025 | F97: 2026 | N97: 출처
A98: labels | B98: 2022 | C98: 2023 | D98: 2024 | E98: 2025 | F98: 2026 | N98: 2단계 보고서 자료(회사 설명회 자료·공시)
A99: current assets | B99: 430.4 | C99: 553.4 | D99: 558.4 | E99: 670.5 | F99: 784.8
A100: cash | B100: 200.1 | C100: 234.1 | D100: 252.5 | E100: 313 | F100: 410.1
A101: st fin | B101: 1.2 | C101: 0
A102: receivables | B102: 148.9 | C102: 149.7 | D102: 164.6 | E102: 160.5 | F102: 166.3
A103: inventory | B103: 88.9 | C103: 160.4 | D103: 133.1 | E103: 181.5 | F103: 184.1
A104: noncurrent assets | B104: 409.7 | C104: 581.8 | D104: 656.6 | E104: 744.5 | F104: 737.8
A105: ppe | B105: 326.6 | C105: 543 | D105: 553.1 | E105: 669.8 | F105: 645.4
A106: intangibles | B106: 17.1 | C106: 13.5 | D106: 29.4 | E106: 40.1 | F106: 54.9
A107: inv property
A108: 합계 assets | B108: 840.1 | C108: 1135.3 | D108: 1215 | E108: 1415 | F108: 1522.6
A109: current liab | B109: 147.4 | C109: 239.1 | D109: 159 | E109: 184.9 | F109: 198.4
A110: payables | B110: 38.6 | C110: 31.9 | D110: 23.8 | E110: 30.7 | F110: 28.4
A111: st debt
A112: noncurrent liab | B112: 18.5 | C112: 21.2 | D112: 219.5 | E112: 189.6 | F112: 152
...

Sheet 출처
A1: 출처 · 쓴 결산단신
A3: 공시일 | B3: 문서 | C3: PDF
A4: 2026-10-30 | B4: 2027년 3월 결산기 2분기 결산단신 | C4: https://www2.jpx.co.jp/disc/43680/140120261030561153.pdf
A5: 2026-08-07 | B5: 2027년 3월 결산기 1분기 결산단신 | C5: https://www2.jpx.co.jp/disc/43680/140120260807515047.pdf
A6: 2026-05-11 | B6: 2026년 3월 결산기 연간 결산단신 | C6: https://www2.jpx.co.jp/disc/43680/140120260511522373.pdf
A7: 2026-02-06 | B7: 2026년 3월 결산기 3분기 결산단신 | C7: https://www2.jpx.co.jp/disc/43680/140120260206550192.pdf
A8: 2025-10-31 | B8: 2026년 3월 결산기 2분기 결산단신 | C8: https://www2.jpx.co.jp/disc/43680/140120251031584140.pdf
A9: 2025-08-08 | B9: 2026년 3월 결산기 1분기 결산단신 | C9: https://www2.jpx.co.jp/disc/43680/140120250808537713.pdf
A10: 2025-05-12 | B10: 2025년 3월 결산기 연간 결산단신 | C10: https://www2.jpx.co.jp/disc/43680/140120250512541966.pdf
A11: 2025-02-07 | B11: 2025년 3월 결산기 3분기 결산단신 | C11: https://www2.jpx.co.jp/disc/43680/140120250207566816.pdf
A12: 2024-10-31 | B12: 2025년 3월 결산기 2분기 결산단신 | C12: https://www2.jpx.co.jp/disc/43680/140120241031507360.pdf
A13: 2024-08-07 | B13: 2025년 3월 결산기 1분기 결산단신 | C13: https://www2.jpx.co.jp/disc/43680/140120240807565315.pdf
A14: 2024-05-10 | B14: 2024년 3월 결산기 연간 결산단신 | C14: https://www2.jpx.co.jp/disc/43680/140120240510589535.pdf
... A24: 2018-05-07 | B24: 연간 결산단신 | C24: https://www2.jpx.co.jp/disc/43680/140120180507428121.pdf

Sheet 재무제표 한눈에 보기
A1: 4368 재무제표 한눈에 보기 — 최근 40개 분기(달력 분기, 3Q26 = 26.7~9) · 단위 억 엔
A2: 출처: 매출·영업이익 결산단신 XBRL · 재무상태표 등 결산단신 XBRL 36건(2018-01-31~2026-10-30). 부문·지역·수주·수출은 있을 때만(출처는 줄 끝). 총 차입금 = 이자 붙는 부채 전부(단기·장기 차입금, CP, 사채·전환사채, 리스부채)
A4: 항목 | B4: 4Q16 | C4: 1Q17 | D4: 2Q17 | E4: 3Q17 | F4: 4Q17 | G4: 1Q18 | H4: 2Q18 | I4: 3Q18 | J4: 4Q18 | K4: 1Q19 | L4: 2Q19 | M4: 3Q19 | N4: 4Q19 | O4: 1Q20 | P4: 2Q20 | Q4: 3Q20 | R4: 4Q20 | S4: 1Q21 | T4: 2Q21 | U4: 3Q21 | V4: 4Q21 | W4: 1Q22 | X4: 2Q22 | Y4: 3Q22 | Z4: 4Q22 | AA4: 1Q23 | AB4: 2Q23 | AC4: 3Q23 | AD4: 4Q23 | AE4: 1Q24 | AF4: 2Q24 | AG4: 3Q24 | AH4: 4Q24 | AI4: 1Q25 | AJ4: 2Q25 | AK4: 3Q25 | AL4: 4Q25 | AM4: 1Q26 | AN4: 2Q26 | AO4: 3Q26 | AP4: 출처
A5: 매출액 | C5: 94.5 | D5: 98.1 | E5: 97.7 | F5: 107.2 | G5: 99.3 | H5: 106.8 | I5: 106.3 | J5: 110.9 | K5: 21 | L5: 99.8 | M5: 103.6 | N5: 109.3 | O5: 100.5 | P5: 102 | Q5: 101.4 | R5: 108.4 | S5: 110.3 | T5: 128.3 | U5: 123.4 | V5: 144.9 | W5: 65.1 | X5: 175.4 | Y5: 178.2 | Z5: 172.7 | AA5: 158.3 | AB5: 136.4 | AC5: 134.9 | AD5: 160 | AE5: 158.4 | AF5: 174.3 | AG5: 173.2 | AH5: 176.6 | AI5: 50.3 | AJ5: 186.6 | AK5: 190.5 | AL5: 202.2 | AM5: 61.7 | AN5: 228.2 | AO5: 227.8
A6: 매출액 YoY | G6: 5.1 | H6: 8.9 | I6: 8.8 | J6: 3.5 | K6: -78.9 | L6: -6.6 | M6: -2.5 | N6: -1.4 | O6: 378.6 | P6: 2.2 | Q6: -2.1 | R6: -0.8 | S6: 9.8 | T6: 25.8 | U6: 21.7 | V6: 33.7 | W6: -41 | X6: 36.7 | Y6: 44.4 | Z6: 19.2 | AA6: 143.2 | AB6: -22.2 | AC6: -24.3 | AD6: -7.4 | AE6: 0.1 | AF6: 27.8 | AG6: 28.4 | AH6: 10.4 | AI6: -68.2 | AJ6: 7.1 | AK6: 10 | AL6: 14.5 | AM6: 22.7 | AN6: 22.3 | AO6: 19.6
A7: 영업이익 | C7: 25.1 | D7: 28.8 | E7: 25.5 | F7: 27.4 | G7: 23.7 | H7: 26.5 | I7: 25.9 | J7: 22.4 | K7: 2.5 | L7: 21.3 | M7: 22.4 | N7: 25.7 | O7: 19 | P7: 23.5 | Q7: 22.8 | R7: 25.6 | S7: 24.4 | T7: 33.7 | U7: 30.5 | V7: 38.3 | W7: 20.3 | X7: 46.9 | Y7: 48.9 | Z7: 51.2 | AA7: 42.3 | AB7: 31.9 | AC7: 23.9 | AD7: 26.5 | AE7: 28.6 | AF7: 39.1 | AG7: 42.3 | AH7: 44.5 | AI7: 4.5 | AJ7: 46.9 | AK7: 50.5 | AL7: 48.2 | AM7: 8 | AN7: 61.7 | AO7: 71.2
A8: 영업이익률 | C8: 26.6 | D8: 29.4 | E8: 26.1 | F8: 25.6 | G8: 23.9 | H8: 24.8 | I8: 24.4 | J8: 20.2 | K8: 11.9 | L8: 21.3 | M8: 21.6 | N8: 23.5 | O8: 18.9 | P8: 23 | Q8: 22.5 | R8: 23.6 | S8: 22.1 | T8: 26.3 | U8: 24.7 | V8: 26.4 | W8: 31.2 | X8: 26.7 | Y8: 27.4 | Z8: 29.6 | AA8: 26.7 | AB8: 23.4 | AC8: 17.7 | AD8: 16.6 | AE8: 18.1 | AF8: 22.4 | AG8: 24.4 | AH8: 25.2 | AI8: 8.9 | AJ8: 25.1 | AK8: 26.5 | AL8: 23.8 | AM8: 13 | AN8: 27 | AO8: 31.3
A9: 영업이익 YoY | G9: -5.6 | H9: -8 | I9: 1.6 | J9: -18.2 | K9: -89.5 | L9: -19.6 | M9: -13.5 | N9: 14.7 | O9: 660 | P9: 10.3 | Q9: 1.8 | R9: -0.4 | S9: 28.4 | T9: 43.4 | U9: 33.8 | V9: 49.6 | W9: -16.8 | X9: 39.2 | Y9: 60.3 | Z9: 33.7 | AA9: 108.4 | AB9: -32 | AC9: -51.1 | AD9: -48.2 | AE9: -32.4 | AF9: 22.6 | AG9: 77 | AH9: 67.9 | AI9: -84.3 | AJ9: 19.9 | AK9: 19.4 | AL9: 8.3 | AM9: 77.8 | AN9: 31.6 | AO9: 41
A10: 유동자산 | C10: 413.5 | F10: 410.3 | G10: 394.7 | H10: 370.5 | I10: 383.2 | J10: 311 | K10: 239 | L10: 309.3 | M10: 327.9 | N10: 341.9 | O10: 289.4 | P10: 365.5 | Q10: 388.6 | R10: 404.4 | S10: 376.8 | T10: 463.1 | U10: 484.8 | V10: 448 | W10: 430.4 | X10: 509.9 | Y10: 524.8 | Z10: 501.1 | AA10: 553.4 | AB10: 632.4 | AC10: 663.1 | AD10: 630.3 | AE10: 558.4 | AF10: 685.4 | AG10: 654.8 | AH10: 648.8 | AI10: 670.5 | AJ10: 642.3 | AK10: 701.1 | AL10: 755.8 | AM10: 784.8 | AN10: 821.8 | AO10: 890.2
A11: 유동부채 | C11: 93 | F11: 118.3 | G11: 122.7 | H11: 118.7 | I11: 134.7 | J11: 85.2 | K11: 69.5 | L11: 64.8 | M11: 81.9 | N11: 75.7 | O11: 68.7 | P11: 68.5 | Q11: 65.6 | R11: 63 | S11: 75.9 | T11: 80.7 | U11: 149.2 | V11: 88.5 | W11: 147.4 | X11: 167.9 | Y11: 138.9 | Z11: 214 | AA11: 239.1 | AB11: 126 | AC11: 136.7 | AD11: 110.8 | AE11: 159 | AF11: 163.5 | AG11: 148.7 | AH11: 123.7 | AI11: 184.9 | AJ11: 137.5 | AK11: 177.2 | AL11: 202.2 | AM11: 198.4 | AN11: 296.3 | AO11: 311.6
A12: 부채총계 | C12: 114.3 | F12: 140.5 | G12: 140.8 | H12: 136.4 | I12: 152.4 | J12: 103.2 | K12: 87 | L12: 83.1 | M12: 99.5 | N12: 93.7 | O12: 85.9 | P12: 86.5 | Q12: 85.6 | R12: 83 | S12: 94.3 | T12: 100.7 | U12: 169.3 | V12: 108.8 | W12: 165.8 | X12: 188.7 | Y12: 160.2 | Z12: 234.8 | AA12: 260.3 | AB12: 347.5 | AC12: 358.4 | AD12: 332.3 | AE12: 378.6 | AF12: 385.3 | AG12: 360.3 | AH12: 326.8 | AI12: 374.5 | AJ12: 317.1 | AK12: 346.6 | AL12: 362.8 | AM12: 350.4 | AN12: 438.3 | AO12: 443.4
A13: 자기자본 | C13: 451.6 | F13: 497.1 | G13: 501.5 | H13: 512.7 | I13: 533.9 | J13: 538.4 | K13: 499 | L13: 554.8 | M13: 570.7 | N13: 584.3 | O13: 549.5 | P13: 610 | Q13: 626 | R13: 635.4 | S13: 602.5 | T13: 675.2 | U13: 688.3 | V13: 711.3 | W13: 674.3 | X13: 788.1 | Y13: 829.5 | Z13: 841.9 | AA13: 875 | AB13: 896.1 | AC13: 918.2 | AD13: 918.9 | AE13: 836.5 | AF13: 976.4 | AG13: 988.7 | AH13: 1025.4 | AI13: 1040.5 | AJ13: 1054.5 | AK13: 1097.9 | AL13: 1131.4 | AM13: 1172.2 | AN13: 1230 | AO13: 1274.7
A14: 유동비율 | C14: 444.6 | F14: 346.8 | G14: 321.7 | H14: 312.1 | I14: 284.5 | J14: 365 | K14: 343.9 | L14: 477.3 | M14: 400.4 | N14: 451.7 | O14: 421.3 | P14: 533.6 | Q14: 592.4 | R14: 641.9 | S14: 496.4 | T14: 573.9 | U14: 324.9 | V14: 506.2 | W14: 292 | X14: 303.7 | Y14: 377.8 | Z14: 234.2 | AA14: 231.5 | AB14: 501.9 | AC14: 485.1 | AD14: 568.9 | AE14: 351.2 | AF14: 419.2 | AG14: 440.3 | AH14: 524.5 | AI14: 362.6 | AJ14: 467.1 | AK14: 395.7 | AL14: 373.8 | AM14: 395.6 | AN14: 277.4 | AO14: 285.7
A15: 부채비율 | C15: 25.3 | F15: 28.3 | G15: 28.1 | H15: 26.6 | I15: 28.5 | J15: 19.2 | K15: 17.4 | L15: 15 | M15: 17.4 | N15: 16 | O15: 15.6 | P15: 14.2 | Q15: 13.7 | R15: 13.1 | S15: 15.7 | T15: 14.9 | U15: 24.6 | V15: 15.3 | W15: 24.6 | X15: 23.9 | Y15: 19.3 | Z15: 27.9 | AA15: 29.7 | AB15: 38.8 | AC15: 39 | AD15: 36.2 | AE15: 45.3 | AF15: 39.5 | AG15: 36.4 | AH15: 31.9 | AI15: 36 | AJ15: 30.1 | AK15: 31.6 | AL15: 32.1 | AM15: 29.9 | AN15: 35.6 | AO15: 34.8
A16: 순차입금/자기자본 | C16: -54.2 | F16: -40.9 | G16: -37.8 | H16: -32.7 | I16: -33.1 | J16: -18.4 | K16: -15.1 | L16: -21.2 | M16: -24 | N16: -24.2 | O16: -23.1 | P16: -29.2 | Q16: -32 | R16: -32.2 | S16: -36.3 | T16: -38.4 | U16: -38.9 | V16: -28.3 | W16: -29.7 | X16: -25.4 | Y16: -25.7 | Z16: -20.8 | AA16: -26.8 | AB16: -11.6 | AC16: -10.2 | AD16: -6 | AE16: -6.3 | AF16: -12.8 | AG16: -12.1 | AH16: -7.5 | AI16: -10.9 | AJ16: -7.6 | AK16: -13.3 | AL16: -16.6 | AM16: -20.6 | AN16: -18.2 | AO16: -26.3
A17: 재고자산 | C17: 59.1 | F17: 68.8 | G17: 80.1 | H17: 81.2 | I17: 81.1 | J17: 81.3 | K17: 60.4 | L17: 78.1 | M17: 79.1 | N17: 80.3 | O17: 61.2 | P17: 81.9 | Q17: 86.2 | R17: 83.3 | S17: 61.5 | T17: 79.7 | U17: 89.8 | V17: 100.7 | W17: 89 | X17: 134.3 | Y17: 138.9 | Z17: 149.3 | AA17: 160.4 | AB17: 180.8 | AC17: 193.1 | AD17: 181.5 | AE17: 133.2 | AF17: 158.7 | AG17: 164.1 | AH17: 176.5 | AI17: 181.6 | AJ17: 179.2 | AK17: 184.8 | AL17: 178.5 | AM17: 184.1 | AN17: 182.8 | AO17: 200.6
A18: 재고자산 회전일수 | C18: 103 | F18: 100 | G18: 125 | H18: 117 | I18: 118 | J18: 104 | K18: 314 | L18: 114 | M18: 111 | N18: 110 | O18: 86 | P18: 119 | Q18: 127 | R18: 115 | S18: 81 | T18: 94 | U18: 110 | V18: 107 | W18: 229 | X18: 116 | Y18: 120 | Z18: 139 | AA18: 158 | AB18: 204 | AC18: 201 | AD18: 150 | AE18: 114 | AF18: 129 | AG18: 140 | AH18: 152 | AI18: 396 | AJ18: 143 | AK18: 147 | AL18: 127 | AM18: 367 | AN18: 121 | AO18: 144
A19: 매출채권 회전일수 | C19: 94 | F19: 101 | G19: 103 | H19: 97 | I19: 99 | J19: 98 | K19: 472 | L19: 98 | M19: 92 | N19: 96 | O19: 93 | P19: 90 | Q19: 88 | R19: 93 | S19: 87 | T19: 84 | U19: 88 | V19: 87 | W19: 208 | X19: 84 | Y19: 83 | Z19: 87 | AA19: 86 | AB19: 89 | AC19: 100 | AD19: 90 | AE19: 95 | AF19: 89 | AG19: 85 | AH19: 94 | AI19: 290 | AJ19: 83 | AK19: 83 | AL19: 82 | AM19: 245 | AN19: 78 | AO19: 79
A20: 매입채무 회전일수 | C20: 49 | F20: 41 | G20: 40 | H20: 32 | I20: 37 | J20: 28 | K20: 95 | L20: 24 | M20: 28 | N20: 27 | O20: 30 | P20: 27 | Q20: 27 | R20: 24 | S20: 29 | T20: 20 | U20: 28 | V20: 27 | W20: 100 | X20: 28 | Y20: 25 | Z20: 27 | AA20: 32 | AB20: 40 | AC20: 34 | AD20: 21 | AE20: 20 | AF20: 26 | AG20: 28 | AH20: 28 | AI20: 67 | AJ20: 24 | AK20: 24 | AL20: 19 | AM20: 57 | AN20: 22 | AO20: 26
A21: 현금전환주기(CCC) | C21: 148 | F21: 160 | G21: 188 | H21: 182 | I21: 180 | J21: 174 | K21: 691 | L21: 188 | M21: 175 | N21: 179 | O21: 149 | P21: 182 | Q21: 188 | R21: 184 | S21: 139 | T21: 158 | U21: 170 | V21: 167 | W21: 337 | X21: 172 | Y21: 178 | Z21: 199 | AA21: 212 | AB21: 253 | AC21: 267 | AD21: 219 | AE21: 189 | AF21: 192 | AG21: 197 | AH21: 218 | AI21: 619 | AJ21: 202 | AK21: 206 | AL21: 190 | AM21: 555 | AN21: 177 | AO21: 197
... A23: 현금 | C23: 244.7 | F23: 203.5 | G23: 189.4 | H23: 167.5 | I23: 176.6 | J23: 98.8 | K23: 75.4 | L23: 117.8 | M23: 136.8 | N23: 141.6 | O23: 127.2 | P23: 178 | Q23: 200.2 | R23: 204.3 | S23: 218.7 | T23: 259 | U23: 268 | V23: 201.1 | W23: 200.1 | X23: 200.5 | Y23: 213.5 | Z23: 174.9 | AA23: 234.1 | AB23: 303.9 | AC23: 293.8 | AD23: 255.3 | AE23: 252.5 | AF23: 325.3 | AG23: 319.2 | AH23: 277.3 | AI23: 313 | AJ23: 278.7 | AK23: 334.6 | AL23: 367.3 | AM23: 410.1 | AN23: 382.9 | AO23: 484.5
A24: 부문별 매출 · ライフサイエンス事業、報告セグメント [メンバー] | AB24: 85.3 | AC24: 84.5 | AD24: 88.7 | AF24: 93.9 | AG24: 92.8 | AH24: 88.4 | AJ24: 89.6 | AK24: 88.3 | AL24: 86.1 | AN24: 98.5 | AO24: 99.8 | AP24: 결산단신 부문 정보(외부 고객 매출)
A25: 부문별 매출 · 電子材料事業、報告セグメント [メンバー] | AB25: 51.1 | AC25: 50.5 | AD25: 71.3 | AF25: 80.4 | AG25: 80.5 | AH25: 88.3 | AJ25: 97 | AK25: 102.2 | AL25: 116.1 | AN25: 129.7 | AO25: 128 | AP25: 결산단신 부문 정보(외부 고객 매출)
