Workbook

Sheet 연간
A1: 4507 Model
A2: 모를 땐 보수적으로 | B2: (단위: 백만엔) | C2: 3월 결산 · IFRS · 2027.1Q = 2027년 3월 결산기 1분기 | Y2: (추정: 파란 글씨 = 직접 입력)
A3: 항목 | B3: 참고 | C3: 2024.2Q | D3: 2024.3Q | E3: 2024.4Q | F3: 2025.1Q | G3: 2025.2Q | H3: 2025.3Q | I3: 2025.4Q | J3: 2026.1Q | K3: 2026.2Q | L3: 2026.3Q | M3: 2026.4Q | N3: 2027.1Q | O3: 2017 | P3: 2018 | Q3: 2019 | R3: 2020 | S3: 2021 | T3: 2022 | U3: 2023 | V3: 2024 | W3: 2025 | X3: 2026 | Y3: 2027(MW) | Z3: 2028(MW) | AA3: 2029(MW) | AB3: 2030(MW) | AC3: 2031(MW)
A4: 매출액 | B4: MW 직접 입력 | C4: 121230 | D4: 106279 | E4: 98261 | F4: 97586 | G4: 116384 | H4: 119630 | I4: 104668 | J4: 99781 | K4: 113184 | L4: 147719 | M4: 138993 | N4: 163310 | Q4: 367960 | R4: 333371 | S4: 297177 | T4: 335138 | U4: 426684 | V4: 410073 | W4: 438268 | X4: 499677 | Y4: =IF(COUNT(Y7)=0,"",SUM(Y7)) | Z4: =IF(COUNT(Z7)=0,"",SUM(Z7)) | AA4: =IF(COUNT(AA7)=0,"",SUM(AA7)) | AB4: =IF(COUNT(AB7)=0,"",SUM(AB7)) | AC4: =IF(COUNT(AC7)=0,"",SUM(AC7))
A5: YoY | G5: =IF(OR(G4="",C4=""),"",IFERROR(G4/C4-1,"")) | H5: =IF(OR(H4="",D4=""),"",IFERROR(H4/D4-1,"")) | I5: =IF(OR(I4="",E4=""),"",IFERROR(I4/E4-1,"")) | J5: =IF(OR(J4="",F4=""),"",IFERROR(J4/F4-1,"")) | K5: =IF(OR(K4="",G4=""),"",IFERROR(K4/G4-1,"")) | L5: =IF(OR(L4="",H4=""),"",IFERROR(L4/H4-1,"")) | M5: =IF(OR(M4="",I4=""),"",IFERROR(M4/I4-1,"")) | N5: =IF(OR(N4="",J4=""),"",IFERROR(N4/J4-1,"")) | P5: =IF(OR(P4="",O4=""),"",IFERROR(P4/O4-1,"")) | Q5: =IF(OR(Q4="",P4=""),"",IFERROR(Q4/P4-1,"")) | R5: =IF(OR(R4="",Q4=""),"",IFERROR(R4/Q4-1,"")) | S5: =IF(OR(S4="",R4=""),"",IFERROR(S4/R4-1,"")) | T5: =IF(OR(T4="",S4=""),"",IFERROR(T4/S4-1,"")) | U5: =IF(OR(U4="",T4=""),"",IFERROR(U4/T4-1,"")) | V5: =IF(OR(V4="",U4=""),"",IFERROR(V4/U4-1,"")) | W5: =IF(OR(W4="",V4=""),"",IFERROR(W4/V4-1,"")) | ... AC5: =IF(OR(AC4="",AB4=""),"",IFERROR(AC4/AB4-1,""))
A6: 제품별 매출 분류 | B6: 사업보고서 매출실적
A7: (제품별 매출 미공시 — 직접 입력)
A8: 비중 | C8: =IF(OR(C7="",C4=""),"",IFERROR(C7/C4,"")) | D8: =IF(OR(D7="",D4=""),"",IFERROR(D7/D4,"")) | E8: =IF(OR(E7="",E4=""),"",IFERROR(E7/E4,"")) | F8: =IF(OR(F7="",F4=""),"",IFERROR(F7/F4,"")) | G8: =IF(OR(G7="",G4=""),"",IFERROR(G7/G4,"")) | H8: =IF(OR(H7="",H4=""),"",IFERROR(H7/H4,"")) | I8: =IF(OR(I7="",I4=""),"",IFERROR(I7/I4,"")) | J8: =IF(OR(J7="",J4=""),"",IFERROR(J7/J4,"")) | ... AC8: =IF(OR(AC7="",AC4=""),"",IFERROR(AC7/AC4,""))
A9: YoY | G9: =IF(OR(G7="",C7=""),"",IFERROR(G7/C7-1,"")) | H9: =IF(OR(H7="",D7=""),"",IFERROR(H7/D7-1,"")) | I9: =IF(OR(I7="",E7=""),"",IFERROR(I7/E7-1,"")) | J9: =IF(OR(J7="",F7=""),"",IFERROR(J7/F7-1,"")) | K9: =IF(OR(K7="",G7=""),"",IFERROR(K7/G7-1,"")) | L9: =IF(OR(L7="",H7=""),"",IFERROR(L7/H7-1,"")) | M9: =IF(OR(M7="",I7=""),"",IFERROR(M7/I7-1,"")) | N9: =IF(OR(N7="",J7=""),"",IFERROR(N7/J7-1,"")) | P9: =IF(OR(P7="",O7=""),"",IFERROR(P7/O7-1,"")) | Q9: =IF(OR(Q7="",P7=""),"",IFERROR(Q7/P7-1,"")) | R9: =IF(OR(R7="",Q7=""),"",IFERROR(R7/Q7-1,"")) | S9: =IF(OR(S7="",R7=""),"",IFERROR(S7/R7-1,"")) | T9: =IF(OR(T7="",S7=""),"",IFERROR(T7/S7-1,"")) | U9: =IF(OR(U7="",T7=""),"",IFERROR(U7/T7-1,"")) | V9: =IF(OR(V7="",U7=""),"",IFERROR(V7/U7-1,"")) | W9: =IF(OR(W7="",V7=""),"",IFERROR(W7/V7-1,"")) | ... AC9: =IF(OR(AC7="",AB7=""),"",IFERROR(AC7/AB7-1,""))
A10: 매출원가
A11: 전체 매출원가 | C11: 14766 | D11: 14517 | E11: 15200 | F11: 14442 | G11: 15695 | H11: 15898 | I11: 17791 | J11: 12317 | K11: 16940 | L11: 25090 | M11: 28103 | N11: 30795 | Q11: 55591 | R11: 56782 | S11: 52523 | T11: 55415 | U11: 62246 | V11: 57602 | W11: 63826 | X11: 82450
A12: 매출총이익 | C12: =IF(OR(C4="",C11=""),"",IFERROR(C4-C11,"")) | D12: =IF(OR(D4="",D11=""),"",IFERROR(D4-D11,"")) | E12: =IF(OR(E4="",E11=""),"",IFERROR(E4-E11,"")) | F12: =IF(OR(F4="",F11=""),"",IFERROR(F4-F11,"")) | G12: =IF(OR(G4="",G11=""),"",IFERROR(G4-G11,"")) | H12: =IF(OR(H4="",H11=""),"",IFERROR(H4-H11,"")) | I12: =IF(OR(I4="",I11=""),"",IFERROR(I4-I11,"")) | J12: =IF(OR(J4="",J11=""),"",IFERROR(J4-J11,"")) | ... X12: =IF(OR(X4="",X11=""),"",IFERROR(X4-X11,""))
A13: GPM | C13: =IF(OR(C12="",C4=""),"",IFERROR(C12/C4,"")) | D13: =IF(OR(D12="",D4=""),"",IFERROR(D12/D4,"")) | E13: =IF(OR(E12="",E4=""),"",IFERROR(E12/E4,"")) | F13: =IF(OR(F12="",F4=""),"",IFERROR(F12/F4,"")) | G13: =IF(OR(G12="",G4=""),"",IFERROR(G12/G4,"")) | H13: =IF(OR(H12="",H4=""),"",IFERROR(H12/H4,"")) | I13: =IF(OR(I12="",I4=""),"",IFERROR(I12/I4,"")) | J13: =IF(OR(J12="",J4=""),"",IFERROR(J12/J4,"")) | ... AC13: =IF(OR(AC12="",AC4=""),"",IFERROR(AC12/AC4,""))
A14: 판매관리비
A15: 전체 판관비 | C15: 24326 | D15: 24143 | E15: 27991 | F15: 24042 | G15: 23692 | H15: 25451 | I15: 28688 | J15: 25820 | K15: 27558 | L15: 35484 | M15: 38043 | N15: 45150 | Q15: 87668 | R15: 95094 | S15: 91902 | T15: 91771 | U15: 97775 | V15: 99651 | W15: 101873 | X15: 126905
A16: 영업이익 | B16: MW = 매출 × OPM | C16: 51521 | D16: 40631 | E16: 14573 | F16: 28110 | G16: 47759 | H16: 53355 | I16: 27379 | J16: 35097 | K16: 39674 | L16: 73968 | M16: 17986 | N16: 66911 | Q16: 145081 | R16: 130628 | S16: 117438 | T16: 110312 | U16: 149003 | V16: 153310 | W16: 156603 | X16: 166725 | Y16: =IF(OR(Y4="",Y17=""),"",IFERROR(Y4*Y17,"")) | Z16: =IF(OR(Z4="",Z17=""),"",IFERROR(Z4*Z17,"")) | AA16: =IF(OR(AA4="",AA17=""),"",IFERROR(AA4*AA17,"")) | AB16: =IF(OR(AB4="",AB17=""),"",IFERROR(AB4*AB17,"")) | AC16: =IF(OR(AC4="",AC17=""),"",IFERROR(AC4*AC17,""))
A17: OPM | B17: MW 입력 | C17: =IF(OR(C16="",C4=""),"",IFERROR(C16/C4,"")) | D17: =IF(OR(D16="",D4=""),"",IFERROR(D16/D4,"")) | E17: =IF(OR(E16="",E4=""),"",IFERROR(E16/E4,"")) | F17: =IF(OR(F16="",F4=""),"",IFERROR(F16/F4,"")) | G17: =IF(OR(G16="",G4=""),"",IFERROR(G16/G4,"")) | H17: =IF(OR(H16="",H4=""),"",IFERROR(H16/H4,"")) | I17: =IF(OR(I16="",I4=""),"",IFERROR(I16/I4,"")) | J17: =IF(OR(J16="",J4=""),"",IFERROR(J16/J4,"")) | ... X17: =IF(OR(X16="",X4=""),"",IFERROR(X16/X4,""))
A18: 증가율 | G18: =IF(OR(G16="",C16=""),"",IFERROR(G16/C16-1,"")) | H18: =IF(OR(H16="",D16=""),"",IFERROR(H16/D16-1,"")) | I18: =IF(OR(I16="",E16=""),"",IFERROR(I16/E16-1,"")) | J18: =IF(OR(J16="",F16=""),"",IFERROR(J16/F16-1,"")) | K18: =IF(OR(K16="",G16=""),"",IFERROR(K16/G16-1,"")) | L18: =IF(OR(L16="",H16=""),"",IFERROR(L16/H16-1,"")) | M18: =IF(OR(M16="",I16=""),"",IFERROR(M16/I16-1,"")) | N18: =IF(OR(N16="",J16=""),"",IFERROR(N16/J16-1,"")) | P18: =IF(OR(P16="",O16=""),"",IFERROR(P16/O16-1,"")) | Q18: =IF(OR(Q16="",P16=""),"",IFERROR(Q16/P16-1,"")) | R18: =IF(OR(R16="",Q16=""),"",IFERROR(R16/Q16-1,"")) | S18: =IF(OR(S16="",R16=""),"",IFERROR(S16/R16-1,"")) | T18: =IF(OR(T16="",S16=""),"",IFERROR(T16/S16-1,"")) | U18: =IF(OR(U16="",T16=""),"",IFERROR(U16/T16-1,"")) | V18: =IF(OR(V16="",U16=""),"",IFERROR(V16/U16-1,"")) | W18: =IF(OR(W16="",V16=""),"",IFERROR(W16/V16-1,"")) | ... AC18: =IF(OR(AC16="",AB16=""),"",IFERROR(AC16/AB16-1,""))
A19: 비용의 성격별 분류 | B19: 참고 데이터
A20: 총 판관비 | O20: =IF(O15="","",O15) | P20: =IF(P15="","",P15) | Q20: =IF(Q15="","",Q15) | R20: =IF(R15="","",R15) | S20: =IF(S15="","",S15) | T20: =IF(T15="","",T15) | U20: =IF(U15="","",U15) | V20: =IF(V15="","",V15) | ... X20: =IF(X15="","",X15)
A21: 급여 | B21: 고정비
A22: % of Sales | O22: =IF(OR(O21="",O4=""),"",IFERROR(O21/O4,"")) | P22: =IF(OR(P21="",P4=""),"",IFERROR(P21/P4,"")) | Q22: =IF(OR(Q21="",Q4=""),"",IFERROR(Q21/Q4,"")) | R22: =IF(OR(R21="",R4=""),"",IFERROR(R21/R4,"")) | S22: =IF(OR(S21="",S4=""),"",IFERROR(S21/S4,"")) | T22: =IF(OR(T21="",T4=""),"",IFERROR(T21/T4,"")) | U22: =IF(OR(U21="",U4=""),"",IFERROR(U21/U4,"")) | V22: =IF(OR(V21="",V4=""),"",IFERROR(V21/V4,"")) | ... X22: =IF(OR(X21="",X4=""),"",IFERROR(X21/X4,""))
A23: 감가상각비 | B23: 고정비
A24: % of Sales | O24: =IF(OR(O23="",O4=""),"",IFERROR(O23/O4,"")) | P24: =IF(OR(P23="",P4=""),"",IFERROR(P23/P4,"")) | Q24: =IF(OR(Q23="",Q4=""),"",IFERROR(Q23/Q4,"")) | R24: =IF(OR(R23="",R4=""),"",IFERROR(R23/R4,"")) | S24: =IF(OR(S23="",S4=""),"",IFERROR(S23/S4,"")) | T24: =IF(OR(T23="",T4=""),"",IFERROR(T23/T4,"")) | U24: =IF(OR(U23="",U4=""),"",IFERROR(U23/U4,"")) | V24: =IF(OR(V23="",V4=""),"",IFERROR(V23/V4,"")) | ... X24: =IF(OR(X23="",X4=""),"",IFERROR(X23/X4,""))
A25: 지급수수료 | B25: 고정비
A26: % of Sales | O26: =IF(OR(O25="",O4=""),"",IFERROR(O25/O4,"")) | P26: =IF(OR(P25="",P4=""),"",IFERROR(P25/P4,"")) | Q26: =IF(OR(Q25="",Q4=""),"",IFERROR(Q25/Q4,"")) | R26: =IF(OR(R25="",R4=""),"",IFERROR(R25/R4,"")) | S26: =IF(OR(S25="",S4=""),"",IFERROR(S25/S4,"")) | T26: =IF(OR(T25="",T4=""),"",IFERROR(T25/T4,"")) | U26: =IF(OR(U25="",U4=""),"",IFERROR(U25/U4,"")) | V26: =IF(OR(V25="",V4=""),"",IFERROR(V25/V4,"")) | ... X26: =IF(OR(X25="",X4=""),"",IFERROR(X25/X4,""))
A27: 연구개발비 | B27: 변동비
A28: % of Sales | O28: =IF(OR(O27="",O4=""),"",IFERROR(O27/O4,"")) | P28: =IF(OR(P27="",P4=""),"",IFERROR(P27/P4,"")) | Q28: =IF(OR(Q27="",Q4=""),"",IFERROR(Q27/Q4,"")) | R28: =IF(OR(R27="",R4=""),"",IFERROR(R27/R4,"")) | S28: =IF(OR(S27="",S4=""),"",IFERROR(S27/S4,"")) | T28: =IF(OR(T27="",T4=""),"",IFERROR(T27/T4,"")) | U28: =IF(OR(U27="",U4=""),"",IFERROR(U27/U4,"")) | V28: =IF(OR(V27="",V4=""),"",IFERROR(V27/V4,"")) | ... X28: =IF(OR(X27="",X4=""),"",IFERROR(X27/X4,""))
A29: 기타비용 | B29: 변동비 | O29: =IF(OR(O20="",O21="",O23="",O25="",O27=""),"",IFERROR(O20-O21-O23-O25-O27,"")) | P29: =IF(OR(P20="",P21="",P23="",P25="",P27=""),"",IFERROR(P20-P21-P23-P25-P27,"")) | Q29: =IF(OR(Q20="",Q21="",Q23="",Q25="",Q27=""),"",IFERROR(Q20-Q21-Q23-Q25-Q27,"")) | R29: =IF(OR(R20="",R21="",R23="",R25="",R27=""),"",IFERROR(R20-R21-R23-R25-R27,"")) | S29: =IF(OR(S20="",S21="",S23="",S25="",S27=""),"",IFERROR(S20-S21-S23-S25-S27,"")) | T29: =IF(OR(T20="",T21="",T23="",T25="",T27=""),"",IFERROR(T20-T21-T23-T25-T27,"")) | U29: =IF(OR(U20="",U21="",U23="",U25="",U27=""),"",IFERROR(U20-U21-U23-U25-U27,"")) | V29: =IF(OR(V20="",V21="",V23="",V25="",V27=""),"",IFERROR(V20-V21-V23-V25-V27,"")) | ... X29: =IF(OR(X20="",X21="",X23="",X25="",X27=""),"",IFERROR(X20-X21-X23-X25-X27,""))
A30: % of Sales | O30: =IF(OR(O29="",O4=""),"",IFERROR(O29/O4,"")) | P30: =IF(OR(P29="",P4=""),"",IFERROR(P29/P4,"")) | Q30: =IF(OR(Q29="",Q4=""),"",IFERROR(Q29/Q4,"")) | R30: =IF(OR(R29="",R4=""),"",IFERROR(R29/R4,"")) | S30: =IF(OR(S29="",S4=""),"",IFERROR(S29/S4,"")) | T30: =IF(OR(T29="",T4=""),"",IFERROR(T29/T4,"")) | U30: =IF(OR(U29="",U4=""),"",IFERROR(U29/U4,"")) | V30: =IF(OR(V29="",V4=""),"",IFERROR(V29/V4,"")) | ... X30: =IF(OR(X29="",X4=""),"",IFERROR(X29/X4,""))
A31: 당기순이익 추정
A32: 기타이익 | C32: 95 | D32: 171 | E32: 5836 | F32: 77 | G32: 408 | H32: 16 | I32: 27 | J32: 85 | K32: 366 | L32: 20442 | M32: 26258 | N32: 27772 | Q32: 1394 | R32: 4291 | S32: 26403 | T32: 3384 | U32: 3899 | V32: 6194 | W32: 528 | X32: 47151 | Y32: =IF(OR(Y4="",Y33=""),"",IFERROR(Y4*Y33,"")) | Z32: =IF(OR(Z4="",Z33=""),"",IFERROR(Z4*Z33,"")) | AA32: =IF(OR(AA4="",AA33=""),"",IFERROR(AA4*AA33,"")) | AB32: =IF(OR(AB4="",AB33=""),"",IFERROR(AB4*AB33,"")) | AC32: =IF(OR(AC4="",AC33=""),"",IFERROR(AC4*AC33,""))
A33: % of Sales | B33: MW = 최근 3년 평균 | C33: =IF(OR(C32="",C4=""),"",IFERROR(C32/C4,"")) | D33: =IF(OR(D32="",D4=""),"",IFERROR(D32/D4,"")) | E33: =IF(OR(E32="",E4=""),"",IFERROR(E32/E4,"")) | F33: =IF(OR(F32="",F4=""),"",IFERROR(F32/F4,"")) | G33: =IF(OR(G32="",G4=""),"",IFERROR(G32/G4,"")) | H33: =IF(OR(H32="",H4=""),"",IFERROR(H32/H4,"")) | I33: =IF(OR(I32="",I4=""),"",IFERROR(I32/I4,"")) | J33: =IF(OR(J32="",J4=""),"",IFERROR(J32/J4,"")) | ... X33: =IF(OR(X32="",X4=""),"",IFERROR(X32/X4,"")) | Y33: =IFERROR(AVERAGE(V33,W33,X33),"") | Z33: =Y33 | AA33: =Z33 | AB33: =AA33 | AC33: =AB33
A34: 기타손실 | C34: 7623 | D34: 839 | E34: 15220 | F34: 540 | G34: 1181 | H34: 1231 | I34: 750 | J34: 1258 | K34: 1345 | L34: 3189 | M34: 36013 | N34: 611 | Q34: 24680 | R34: 3951 | S34: 4257 | T34: 4551 | U34: 15445 | V34: 24342 | W34: 3702 | X34: 41805 | Y34: =IF(OR(Y4="",Y35=""),"",IFERROR(Y4*Y35,"")) | Z34: =IF(OR(Z4="",Z35=""),"",IFERROR(Z4*Z35,"")) | AA34: =IF(OR(AA4="",AA35=""),"",IFERROR(AA4*AA35,"")) | AB34: =IF(OR(AB4="",AB35=""),"",IFERROR(AB4*AB35,"")) | AC34: =IF(OR(AC4="",AC35=""),"",IFERROR(AC4*AC35,""))
A35: % of Sales | C35: =IF(OR(C34="",C4=""),"",IFERROR(C34/C4,"")) | D35: =IF(OR(D34="",D4=""),"",IFERROR(D34/D4,"")) | E35: =IF(OR(E34="",E4=""),"",IFERROR(E34/E4,"")) | F35: =IF(OR(F34="",F4=""),"",IFERROR(F34/F4,"")) | G35: =IF(OR(G34="",G4=""),"",IFERROR(G34/G4,"")) | H35: =IF(OR(H34="",H4=""),"",IFERROR(H34/H4,"")) | I35: =IF(OR(I34="",I4=""),"",IFERROR(I34/I4,"")) | J35: =IF(OR(J34="",J4=""),"",IFERROR(J34/J4,"")) | ... X35: =IF(OR(X34="",X4=""),"",IFERROR(X34/X4,"")) | Y35: =IFERROR(AVERAGE(V35,W35,X35),"") | Z35: =Y35 | AA35: =Z35 | AB35: =AA35 | AC35: =AB35
A36: 금융수익 | C36: 10038 | D36: 9639 | E36: 21924 | F36: 11254 | G36: 12317 | H36: 9440 | I36: 20163 | J36: 13562 | K36: 14208 | L36: 20529 | M36: 32497 | N36: 12147 | Q36: 32371 | R36: 30504 | S36: 26522 | T36: 16797 | U36: 75829 | V36: 51674 | W36: 53174 | X36: 80796 | Y36: =IF(OR(Y4="",Y37=""),"",IFERROR(Y4*Y37,"")) | Z36: =IF(OR(Z4="",Z37=""),"",IFERROR(Z4*Z37,"")) | AA36: =IF(OR(AA4="",AA37=""),"",IFERROR(AA4*AA37,"")) | AB36: =IF(OR(AB4="",AB37=""),"",IFERROR(AB4*AB37,"")) | AC36: =IF(OR(AC4="",AC37=""),"",IFERROR(AC4*AC37,""))
A37: % of Sales | C37: =IF(OR(C36="",C4=""),"",IFERROR(C36/C4,"")) | D37: =IF(OR(D36="",D4=""),"",IFERROR(D36/D4,"")) | E37: =IF(OR(E36="",E4=""),"",IFERROR(E36/E4,"")) | F37: =IF(OR(F36="",F4=""),"",IFERROR(F36/F4,"")) | G37: =IF(OR(G36="",G4=""),"",IFERROR(G36/G4,"")) | H37: =IF(OR(H36="",H4=""),"",IFERROR(H36/H4,"")) | I37: =IF(OR(I36="",I4=""),"",IFERROR(I36/I4,"")) | J37: =IF(OR(J36="",J4=""),"",IFERROR(J36/J4,"")) | ... X37: =IF(OR(X36="",X4=""),"",IFERROR(X36/X4,"")) | Y37: =IFERROR(AVERAGE(V37,W37,X37),"") | Z37: =Y37 | AA37: =Z37 | AB37: =AA37 | AC37: =AB37
A38: 금융원가 | C38: 1660 | D38: 1386 | E38: 2701 | F38: 2839 | G38: 2768 | H38: 751 | I38: 2669 | J38: 2331 | K38: 1825 | L38: 1611 | M38: 2838 | N38: 5322 | Q38: 3409 | R38: 2616 | S38: 941 | T38: 841 | U38: 4500 | V38: 6701 | W38: 9027 | X38: 8605 | Y38: =IF(OR(Y4="",Y39=""),"",IFERROR(Y4*Y39,"")) | Z38: =IF(OR(Z4="",Z39=""),"",IFERROR(Z4*Z39,"")) | AA38: =IF(OR(AA4="",AA39=""),"",IFERROR(AA4*AA39,"")) | AB38: =IF(OR(AB4="",AB39=""),"",IFERROR(AB4*AB39,"")) | AC38: =IF(OR(AC4="",AC39=""),"",IFERROR(AC4*AC39,""))
A39: % of Sales | C39: =IF(OR(C38="",C4=""),"",IFERROR(C38/C4,"")) | D39: =IF(OR(D38="",D4=""),"",IFERROR(D38/D4,"")) | E39: =IF(OR(E38="",E4=""),"",IFERROR(E38/E4,"")) | F39: =IF(OR(F38="",F4=""),"",IFERROR(F38/F4,"")) | G39: =IF(OR(G38="",G4=""),"",IFERROR(G38/G4,"")) | H39: =IF(OR(H38="",H4=""),"",IFERROR(H38/H4,"")) | I39: =IF(OR(I38="",I4=""),"",IFERROR(I38/I4,"")) | J39: =IF(OR(J38="",J4=""),"",IFERROR(J38/J4,"")) | ... X39: =IF(OR(X38="",X4=""),"",IFERROR(X38/X4,"")) | Y39: =IFERROR(AVERAGE(V39,W39,X39),"") | Z39: =Y39 | AA39: =Z39 | AB39: =AA39 | AC39: =AB39
A40: 법인세비용차감전순이익(손실) | C40: 59899 | D40: 48884 | E40: 33796 | F40: 36525 | G40: 57308 | H40: 62044 | I40: 44873 | J40: 46328 | K40: 52056 | L40: 92886 | M40: 47646 | N40: 73736 | Q40: 174043 | R40: 158516 | S40: 143018 | T40: 126268 | U40: 220332 | V40: 198283 | W40: 200750 | X40: 238916 | Y40: =IF(OR(Y16=""),"",IFERROR(Y16+N(Y32)-N(Y34)+N(Y36)-N(Y38),"")) | Z40: =IF(OR(Z16=""),"",IFERROR(Z16+N(Z32)-N(Z34)+N(Z36)-N(Z38),"")) | AA40: =IF(OR(AA16=""),"",IFERROR(AA16+N(AA32)-N(AA34)+N(AA36)-N(AA38),"")) | AB40: =IF(OR(AB16=""),"",IFERROR(AB16+N(AB32)-N(AB34)+N(AB36)-N(AB38),"")) | AC40: =IF(OR(AC16=""),"",IFERROR(AC16+N(AC32)-N(AC34)+N(AC36)-N(AC38),""))
A41: 법인세비용(수익) | C41: 11915 | D41: 12643 | E41: -340 | F41: 6218 | G41: 4743 | H41: 11579 | I41: 8675 | J41: 6980 | K41: 7872 | L41: 18206 | M41: -56 | N41: -23982 | Q41: 37124 | R41: 36322 | S41: 30956 | T41: 12829 | U41: 35836 | V41: 37708 | W41: 31215 | X41: 33002 | Y41: =IF(OR(Y40="",Y42=""),"",IFERROR(MAX(Y40,0)*Y42,"")) | Z41: =IF(OR(Z40="",Z42=""),"",IFERROR(MAX(Z40,0)*Z42,"")) | AA41: =IF(OR(AA40="",AA42=""),"",IFERROR(MAX(AA40,0)*AA42,"")) | AB41: =IF(OR(AB40="",AB42=""),"",IFERROR(MAX(AB40,0)*AB42,"")) | AC41: =IF(OR(AC40="",AC42=""),"",IFERROR(MAX(AC40,0)*AC42,""))
A42: 법인세율 | B42: MW 기본 30% | C42: =IF(OR(C41="",C40=""),"",IFERROR(C41/C40,"")) | D42: =IF(OR(D41="",D40=""),"",IFERROR(D41/D40,"")) | E42: =IF(OR(E41="",E40=""),"",IFERROR(E41/E40,"")) | F42: =IF(OR(F41="",F40=""),"",IFERROR(F41/F40,"")) | G42: =IF(OR(G41="",G40=""),"",IFERROR(G41/G40,"")) | H42: =IF(OR(H41="",H40=""),"",IFERROR(H41/H40,"")) | I42: =IF(OR(I41="",I40=""),"",IFERROR(I41/I40,"")) | J42: =IF(OR(J41="",J40=""),"",IFERROR(J41/J40,"")) | ... X42: =IF(OR(X41="",X40=""),"",IFERROR(X41/X40,"")) | Y42: 0.3 | Z42: 0.3 | AA42: 0.3 | AB42: 0.3 | AC42: 0.3
A43: 당기순이익(손실) | C43: 47984 | D43: 36241 | E43: 34136 | F43: 30307 | G43: 52565 | H43: 50464 | I43: 36198 | J43: 39348 | K43: 44184 | L43: 74680 | M43: 47702 | N43: 97718 | Q43: 136918 | R43: 122194 | S43: 112061 | T43: 113439 | U43: 184496 | V43: 160575 | W43: 169534 | X43: 205914 | Y43: =IF(OR(Y40=""),"",IFERROR(Y40-Y41,"")) | Z43: =IF(OR(Z40=""),"",IFERROR(Z40-Z41,"")) | AA43: =IF(OR(AA40=""),"",IFERROR(AA40-AA41,"")) | AB43: =IF(OR(AB40=""),"",IFERROR(AB40-AB41,"")) | AC43: =IF(OR(AC40=""),"",IFERROR(AC40-AC41,""))
A44: 지배주주 순이익 | C44: 48031 | D44: 36629 | E44: 34808 | F44: 30637 | G44: 52496 | H44: 50670 | I44: 36632 | J44: 39355 | K44: 44187 | L44: 74683 | M44: 46934 | N44: 97696 | Q44: 137191 | R44: 122193 | S44: 111858 | T44: 114185 | U44: 184965 | V44: 162030 | W44: 170435 | X44: 205159 | Y44: =IF(OR(Y43="",Y45=""),"",IFERROR(Y43*Y45,"")) | Z44: =IF(OR(Z43="",Z45=""),"",IFERROR(Z43*Z45,"")) | AA44: =IF(OR(AA43="",AA45=""),"",IFERROR(AA43*AA45,"")) | AB44: =IF(OR(AB43="",AB45=""),"",IFERROR(AB43*AB45,"")) | AC44: =IF(OR(AC43="",AC45=""),"",IFERROR(AC43*AC45,""))
A45: 지배주주 순이익률 | B45: MW 기본 100% | C45: =IF(OR(C44="",C43=""),"",IFERROR(C44/C43,"")) | D45: =IF(OR(D44="",D43=""),"",IFERROR(D44/D43,"")) | E45: =IF(OR(E44="",E43=""),"",IFERROR(E44/E43,"")) | F45: =IF(OR(F44="",F43=""),"",IFERROR(F44/F43,"")) | G45: =IF(OR(G44="",G43=""),"",IFERROR(G44/G43,"")) | H45: =IF(OR(H44="",H43=""),"",IFERROR(H44/H43,"")) | I45: =IF(OR(I44="",I43=""),"",IFERROR(I44/I43,"")) | J45: =IF(OR(J44="",J43=""),"",IFERROR(J44/J43,"")) | ... X45: =IF(OR(X44="",X43=""),"",IFERROR(X44/X43,"")) | Y45: 1 | Z45: 1 | AA45: 1 | AB45: 1 | AC45: 1
A46: 목표주가 산출
A47: 현재 주가 ()
A48: 발행주식수 (보통주)
A49: 시가총액 (백만엔) | B49: =IF(OR(B47="",B48=""),"",B47*B48/1000000.0)
A50: OPM | O50: =IF(O17="","",O17) | P50: =IF(P17="","",P17) | Q50: =IF(Q17="","",Q17) | R50: =IF(R17="","",R17) | S50: =IF(S17="","",S17) | T50: =IF(T17="","",T17) | U50: =IF(U17="","",U17) | V50: =IF(V17="","",V17) | ... AC50: =IF(AC17="","",AC17)
A51: 지배주주 순이익 증가율 | P51: =IF(OR(P44="",O44=""),"",IFERROR(P44/O44-1,"")) | Q51: =IF(OR(Q44="",P44=""),"",IFERROR(Q44/P44-1,"")) | R51: =IF(OR(R44="",Q44=""),"",IFERROR(R44/Q44-1,"")) | S51: =IF(OR(S44="",R44=""),"",IFERROR(S44/R44-1,"")) | T51: =IF(OR(T44="",S44=""),"",IFERROR(T44/S44-1,"")) | U51: =IF(OR(U44="",T44=""),"",IFERROR(U44/T44-1,"")) | V51: =IF(OR(V44="",U44=""),"",IFERROR(V44/U44-1,"")) | W51: =IF(OR(W44="",V44=""),"",IFERROR(W44/V44-1,"")) | ... AC51: =IF(OR(AC44="",AB44=""),"",IFERROR(AC44/AB44-1,""))
A52: P/E (현재 주가) | B52: 시총 ÷ 지배순이익 | X52: =IF(OR($B$49="",X44=""),"",IFERROR($B$49/X44,"")) | Y52: =IF(OR($B$49="",Y44=""),"",IFERROR($B$49/Y44,"")) | Z52: =IF(OR($B$49="",Z44=""),"",IFERROR($B$49/Z44,"")) | AA52: =IF(OR($B$49="",AA44=""),"",IFERROR($B$49/AA44,"")) | AB52: =IF(OR($B$49="",AB44=""),"",IFERROR($B$49/AB44,"")) | AC52: =IF(OR($B$49="",AC44=""),"",IFERROR($B$49/AC44,""))
A53: Target P/E | B53: 직접 입력
A54: EPS | B54: 지배순이익 ÷ 주식수 | O54: =IF(OR(O44="",$B$48=""),"",IFERROR(O44*1000000.0/$B$48,"")) | P54: =IF(OR(P44="",$B$48=""),"",IFERROR(P44*1000000.0/$B$48,"")) | Q54: =IF(OR(Q44="",$B$48=""),"",IFERROR(Q44*1000000.0/$B$48,"")) | R54: =IF(OR(R44="",$B$48=""),"",IFERROR(R44*1000000.0/$B$48,"")) | S54: =IF(OR(S44="",$B$48=""),"",IFERROR(S44*1000000.0/$B$48,"")) | T54: =IF(OR(T44="",$B$48=""),"",IFERROR(T44*1000000.0/$B$48,"")) | U54: =IF(OR(U44="",$B$48=""),"",IFERROR(U44*1000000.0/$B$48,"")) | V54: =IF(OR(V44="",$B$48=""),"",IFERROR(V44*1000000.0/$B$48,"")) | ... AC54: =IF(OR(AC44="",$B$48=""),"",IFERROR(AC44*1000000.0/$B$48,""))
A55: 목표주가 | Y55: =IF(OR(Y54="",Y53=""),"",IFERROR(Y54*Y53,"")) | Z55: =IF(OR(Z54="",Z53=""),"",IFERROR(Z54*Z53,"")) | AA55: =IF(OR(AA54="",AA53=""),"",IFERROR(AA54*AA53,"")) | AB55: =IF(OR(AB54="",AB53=""),"",IFERROR(AB54*AB53,"")) | AC55: =IF(OR(AC54="",AC53=""),"",IFERROR(AC54*AC53,""))
A56: 상승여력 | Y56: =IF(OR(Y55="",$B$47=""),"",IFERROR(Y55/$B$47-1,"")) | Z56: =IF(OR(Z55="",$B$47=""),"",IFERROR(Z55/$B$47-1,"")) | AA56: =IF(OR(AA55="",$B$47=""),"",IFERROR(AA55/$B$47-1,"")) | AB56: =IF(OR(AB55="",$B$47=""),"",IFERROR(AB55/$B$47-1,"")) | AC56: =IF(OR(AC55="",$B$47=""),"",IFERROR(AC55/$B$47-1,""))
A57: 자산가치 산출 | B57: 최신 분기 BS
A58: 현금및현금성자산 | X58: ='재무상태표'!G6 | Y58: ='재무상태표'!G6 | Z58: ='재무상태표'!G6 | AA58: ='재무상태표'!G6 | AB58: ='재무상태표'!G6 | AC58: ='재무상태표'!G6
A59: 단기금융상품 | X59: ='재무상태표'!G7 | Y59: ='재무상태표'!G7 | Z59: ='재무상태표'!G7 | AA59: ='재무상태표'!G7 | AB59: ='재무상태표'!G7 | AC59: ='재무상태표'!G7
A60: 투자부동산 | X60: ='재무상태표'!G14 | Y60: ='재무상태표'!G14 | Z60: ='재무상태표'!G14 | AA60: ='재무상태표'!G14 | AB60: ='재무상태표'!G14 | AC60: ='재무상태표'!G14
A61: 지배자본 | X61: ='재무상태표'!G31 | Y61: ='재무상태표'!G31 | Z61: ='재무상태표'!G31 | AA61: ='재무상태표'!G31 | AB61: ='재무상태표'!G31 | AC61: ='재무상태표'!G31
A62: 부채 | X62: ='재무상태표'!G27 | Y62: ='재무상태표'!G27 | Z62: ='재무상태표'!G27 | AA62: ='재무상태표'!G27 | AB62: ='재무상태표'!G27 | AC62: ='재무상태표'!G27
A63: 부채비율 | X63: =IF(OR(X62="",X61=""),"",IFERROR(X62/X61,"")) | Y63: =IF(OR(Y62="",Y61=""),"",IFERROR(Y62/Y61,"")) | Z63: =IF(OR(Z62="",Z61=""),"",IFERROR(Z62/Z61,"")) | AA63: =IF(OR(AA62="",AA61=""),"",IFERROR(AA62/AA61,"")) | AB63: =IF(OR(AB62="",AB61=""),"",IFERROR(AB62/AB61,"")) | AC63: =IF(OR(AC62="",AC61=""),"",IFERROR(AC62/AC61,""))
A64: 자산가치 | B64: 현금+단기금융+투자부동산 | X64: =SUM(X58,X59,X60) | Y64: =SUM(Y58,Y59,Y60) | Z64: =SUM(Z58,Z59,Z60) | AA64: =SUM(AA58,AA59,AA60) | AB64: =SUM(AB58,AB59,AB60) | AC64: =SUM(AC58,AC59,AC60)
A65: 기업가치 산출
A66: 목표 시가총액 (P/E) | B66: 지배순이익 × Target P/E | Y66: =IF(OR(Y44="",Y53=""),"",IFERROR(Y44*Y53,"")) | Z66: =IF(OR(Z44="",Z53=""),"",IFERROR(Z44*Z53,"")) | AA66: =IF(OR(AA44="",AA53=""),"",IFERROR(AA44*AA53,"")) | AB66: =IF(OR(AB44="",AB53=""),"",IFERROR(AB44*AB53,"")) | AC66: =IF(OR(AC44="",AC53=""),"",IFERROR(AC44*AC53,""))
A67: 기업가치 | B67: 목표시총 + 자산가치 | Y67: =IF(OR(Y66=""),"",IFERROR(Y66+Y64,"")) | Z67: =IF(OR(Z66=""),"",IFERROR(Z66+Z64,"")) | AA67: =IF(OR(AA66=""),"",IFERROR(AA66+AA64,"")) | AB67: =IF(OR(AB66=""),"",IFERROR(AB66+AB64,"")) | AC67: =IF(OR(AC66=""),"",IFERROR(AC66+AC64,""))
A68: 현재 시가총액 | Y68: =$B$49 | Z68: =$B$49 | AA68: =$B$49 | AB68: =$B$49 | AC68: =$B$49
A69: 상승여력 | Y69: =IF(OR(Y67="",Y68=""),"",IFERROR(Y67/Y68-1,"")) | Z69: =IF(OR(Z67="",Z68=""),"",IFERROR(Z67/Z68-1,"")) | AA69: =IF(OR(AA67="",AA68=""),"",IFERROR(AA67/AA68-1,"")) | AB69: =IF(OR(AB67="",AB68=""),"",IFERROR(AB67/AB68-1,"")) | AC69: =IF(OR(AC67="",AC68=""),"",IFERROR(AC67/AC68-1,""))
A71: 출처
A72: 결산단신 XBRL(TDnet·JPX 보관소) — 쓴 문서는 '출처' 시트
A73: 분기 = 누계에서 앞 분기를 뺀 3개월 값
A74: 주가: 야후 파이낸스 일봉
A76: 손익계산서 · 전 항목 | B76: 분기 = 3개월 단독
A77: 항목 | B77: 참고 | C77: 2024.2Q | D77: 2024.3Q | E77: 2024.4Q | F77: 2025.1Q | G77: 2025.2Q | H77: 2025.3Q | I77: 2025.4Q | J77: 2026.1Q | K77: 2026.2Q | L77: 2026.3Q | M77: 2026.4Q | N77: 2027.1Q | O77: 2017 | P77: 2018 | Q77: 2019 | R77: 2020 | S77: 2021 | T77: 2022 | U77: 2023 | V77: 2024 | W77: 2025 | X77: 2026 | Y77: 2027(MW) | Z77: 2028(MW) | AA77: 2029(MW) | AB77: 2030(MW) | AC77: 2031(MW)
A78: 매출수익 | C78: 121230 | D78: 106279 | E78: 98261 | F78: 97586 | G78: 116384 | H78: 119630 | I78: 104668 | J78: 99781 | K78: 113184 | L78: 147719 | M78: 138993 | N78: 163310 | T78: 115512 | U78: 88337 | V78: 98261 | W78: 104668 | X78: 138993
A79: License Transfer Profit Profit | F79: 0
A80: License Transfer Profit Revenue | D80: 0 | E80: 0 | H80: 0 | I80: 0 | U80: 0 | V80: 0 | W80: 0
A81: 매출원가 | C81: 14766 | D81: 14517 | E81: 15200 | F81: 14442 | G81: 15695 | H81: 15898 | I81: 17791 | J81: 12317 | K81: 16940 | L81: 25090 | M81: 28103 | N81: 30795 | T81: 15562 | U81: 17680 | V81: 15200 | W81: 17791 | X81: 28103
A82: 매출총이익 | C82: 106464 | D82: 91762 | E82: 83061 | F82: 83144 | G82: 100688 | H82: 103732 | I82: 86877 | J82: 87464 | K82: 96244 | L82: 122628 | M82: 110890 | N82: 132515 | T82: 99950 | U82: 70656 | V82: 83061 | W82: 86877 | X82: 110890
A83: 판매비와 관리비 | C83: 24326 | D83: 24143 | E83: 27991 | F83: 24042 | G83: 23692 | H83: 25451 | I83: 28688 | J83: 25820 | K83: 27558 | L83: 35484 | M83: 38043 | N83: 45150 | T83: 25229 | U83: 27089 | V83: 27991 | W83: 28688 | X83: 38043
A84: 연구개발비 | C84: 22208 | D84: 25428 | E84: 30007 | F84: 29432 | G84: 27394 | H84: 22621 | I84: 29165 | J84: 24888 | K84: 27549 | L84: 29867 | M84: 40539 | N84: 31789 | T84: 24777 | U84: 27584 | V84: 30007 | W84: 29165 | X84: 40539
A85: Amortization On Intangible Assets Associated With Products | C85: 881 | D85: 893 | E85: 1105 | F85: 1095 | G85: 1070 | H85: 1091 | I85: 922 | J85: 485 | K85: 485 | L85: 562 | M85: 4567 | N85: 15824 | T85: 997 | U85: 846 | V85: 1105 | W85: 922 | X85: 4567
A86: Other Income | C86: 95 | D86: 171 | E86: 5836 | F86: 77 | G86: 408 | H86: 16 | I86: 27 | J86: 85 | K86: 366 | L86: 20442 | M86: 26258 | N86: 27772 | T86: 1643 | U86: 267 | V86: 5836 | W86: 27 | X86: 26258
A87: 기타비용 | C87: 7623 | D87: 839 | E87: 15220 | F87: 540 | G87: 1181 | H87: 1231 | I87: 750 | J87: 1258 | K87: 1345 | L87: 3189 | M87: 36013 | N87: 611 | T87: 701 | U87: 12875 | V87: 15220 | W87: 750 | X87: 36013
A88: 영업이익 | C88: 51521 | D88: 40631 | E88: 14573 | F88: 28110 | G88: 47759 | H88: 53355 | I88: 27379 | J88: 35097 | K88: 39674 | L88: 73968 | M88: 17986 | N88: 66911 | T88: 49890 | U88: 2530 | V88: 14573 | W88: 27379 | X88: 17986
A89: 금융수익 | C89: 10038 | D89: 9639 | E89: 21924 | F89: 11254 | G89: 12317 | H89: 9440 | I89: 20163 | J89: 13562 | K89: 14208 | L89: 20529 | M89: 32497 | N89: 12147 | T89: 1780 | U89: 22689 | V89: 21924 | W89: 20163 | X89: 32497
A90: 금융비용 | C90: 1660 | D90: 1386 | E90: 2701 | F90: 2839 | G90: 2768 | H90: 751 | I90: 2669 | J90: 2331 | K90: 1825 | L90: 1611 | M90: 2838 | N90: 5322 | T90: 186 | U90: 3673 | V90: 2701 | W90: 2669 | X90: 2838
A91: 법인세비용차감전 중간이익 | C91: 59899 | D91: 48884 | E91: 33796 | F91: 36525 | G91: 57308 | H91: 62044 | I91: 44873 | J91: 46328 | K91: 52056 | L91: 92886 | M91: 47646 | N91: 73736 | T91: 51484 | U91: 21546 | V91: 33796 | W91: 44873 | X91: 47646
A92: Income Tax Expense | C92: 11915 | D92: 12643 | E92: -340 | F92: 6218 | G92: 4743 | H92: 11579 | I92: 8675 | J92: 6980 | K92: 7872 | L92: 18206 | M92: -56 | N92: -23982 | T92: 8777 | U92: -5177 | V92: -340 | W92: 8675 | X92: -56
... A97: 비지배지분 | C97: -48 | D97: -388 | E97: -672 | F97: -330 | G97: 69 | H97: -205 | I97: -434 | J97: -7 | K97: -3 | L97: -3 | M97: 767 | N97: 22 | T97: -477 | U97: -512 | V97: -672 | W97: -434 | X97: 767
A99: 포괄손익 · 전 항목 | B99: 분기 = 3개월 단독
A100: 항목 | B100: 참고 | C100: 2024.2Q | D100: 2024.3Q | E100: 2024.4Q | F100: 2025.1Q | G100: 2025.2Q | H100: 2025.3Q | I100: 2025.4Q | J100: 2026.1Q | K100: 2026.2Q | L100: 2026.3Q | M100: 2026.4Q | N100: 2027.1Q | O100: 2017 | P100: 2018 | Q100: 2019 | R100: 2020 | S100: 2021 | T100: 2022 | U100: 2023 | V100: 2024 | W100: 2025 | X100: 2026 | Y100: 2027(MW) | Z100: 2028(MW) | AA100: 2029(MW) | AB100: 2030(MW) | AC100: 2031(MW)
A101: 중간이익 | C101: 47984 | D101: 36241 | E101: 34136 | F101: 30307 | G101: 52565 | H101: 50464 | I101: 36198 | J101: 39348 | K101: 44184 | L101: 74680 | M101: 47702 | N101: 97718 | T101: 42708 | U101: 26723 | V101: 34136 | W101: 36198 | X101: 47702
A102: Net Change In Fair Value Of Equity Instruments Designated As Measured At Fair Value Through Other Comprehensive Income Net Of Tax Items That Will Not Be Reclassified To Profit Or Loss OCI | C102: 3776 | D102: -1807 | E102: 9715 | F102: 2391 | G102: -1065 | H102: 1397 | I102: -7313 | J102: 44 | K102: 3767 | L102: 965 | M102: 102300 | N102: 1344 | T102: 23952 | U102: 3591 | V102: 9715 | W102: -7313 | X102: 102300
A103: 확정급여제도 재측정 | C103: 486 | D103: -637 | E103: 1167 | F103: -301 | G103: -312 | H103: -79 | I103: 371 | J103: -138 | K103: 60 | L103: 12 | M103: 403 | N103: 313 | T103: -1161 | U103: 2251 | V103: 1167 | W103: 371 | X103: 403
A104: Total Of Items That Will Not Be Reclassified To Profit Or Loss OCI | C104: 4261 | D104: -2444 | E104: 10882 | F104: 2089 | G104: -1377 | H104: 1319 | I104: -6942 | J104: -93 | K104: 3826 | L104: 977 | M104: 102704 | N104: 1657 | T104: 22791 | U104: 5843 | V104: 10882 | W104: -6942 | X104: 102704
A105: Exchange Differences On Translation Of Foreign Operations Net Of Tax Items That May Be Reclassified To Profit Or Loss OCI | C105: 3275 | D105: -4140 | E105: 25387 | F105: 32962 | G105: -36065 | H105: 24933 | I105: -15902 | J105: 7571 | K105: 5196 | L105: 33752 | M105: 19844 | N105: 17892 | T105: 17293 | U105: 11923 | V105: 25387 | W105: -15902 | X105: 19844
A106: Effective Portion Of Cash Flow Hedges Net Of Tax Items That May Be Reclassified To Profit Or Loss OCI | C106: 2976 | D106: 2685 | E106: 179 | F106: -2893 | G106: 4960 | H106: -1350 | I106: 77 | J106: -2241 | K106: 657 | L106: -519 | M106: 2158 | N106: -1688 | T106: -1813 | U106: -1071 | V106: 179 | W106: 77 | X106: 2158
A107: Share Of Other Comprehensive Income Of Investments Accounted For Using Equity Method Net Of Tax Items That May Be Reclassified To Profit Or Loss OCI | C107: 0 | D107: 0 | E107: 112 | F107: 357 | G107: -661 | H107: 545 | I107: -294 | J107: -145 | K107: 253 | L107: 478 | M107: -586 | N107: -139 | V107: 112 | W107: -294 | X107: -586
...

Sheet 재무상태표
A1: 4507 재무상태표
A2: 재무비율은 기말 잔액 기준 · 분기 손익은 최근 4분기 합산(TTM) | B2: (단위: 백만엔)
A3: 항목 | B3: 참고 | C3: 2025.4Q | D3: 2026.1Q | E3: 2026.2Q | F3: 2026.3Q | G3: 2026.4Q | H3: 2022 | I3: 2023 | J3: 2024 | K3: 2025 | L3: 2026
A4: 자산
A5: 유동자산 | C5: 858504 | G5: 1310335 | H5: 659205 | I5: 784192 | J5: 784205 | K5: 858504 | L5: 1310335
A6: 현금및현금성자산 | C6: 374795 | G6: 711397 | H6: 254420 | I6: 309224 | J6: 358090 | K6: 374795 | L6: 711397
A7: 단기금융상품 | C7: 270024 | G7: 310748 | H7: 210757 | I7: 254131 | J7: 215761 | K7: 270024 | L7: 310748
A8: 매출채권
A9: 재고자산 | C9: 65477 | G9: 99396 | H9: 45892 | I9: 57919 | J9: 64916 | K9: 65477 | L9: 99396
A10: 기타유동자산 | B10: 총계 − 위 항목 | C10: =IF(OR(C5=""),"",IFERROR(C5-SUM(C6,C7,C8,C9),"")) | D10: =IF(OR(D5=""),"",IFERROR(D5-SUM(D6,D7,D8,D9),"")) | E10: =IF(OR(E5=""),"",IFERROR(E5-SUM(E6,E7,E8,E9),"")) | F10: =IF(OR(F5=""),"",IFERROR(F5-SUM(F6,F7,F8,F9),"")) | G10: =IF(OR(G5=""),"",IFERROR(G5-SUM(G6,G7,G8,G9),"")) | H10: =IF(OR(H5=""),"",IFERROR(H5-SUM(H6,H7,H8,H9),"")) | I10: =IF(OR(I5=""),"",IFERROR(I5-SUM(I6,I7,I8,I9),"")) | J10: =IF(OR(J5=""),"",IFERROR(J5-SUM(J6,J7,J8,J9),"")) | ... L10: =IF(OR(L5=""),"",IFERROR(L5-SUM(L6,L7,L8,L9),""))
A11: 비유동자산 | C11: 676844 | G11: 1266535 | H11: 491396 | I11: 527607 | J11: 632712 | K11: 676844 | L11: 1266535
A12: 유형자산 | C12: 115412 | G12: 156519 | H12: 108893 | I12: 112085 | J12: 114586 | K12: 115412 | L12: 156519
A13: 무형자산 | C13: 143652 | G13: 173553 | H13: 81223 | I13: 96309 | J13: 117621 | K13: 143652 | L13: 173553
A14: 투자부동산 | C14: 27722 | G14: 27337 | H14: 26672 | I14: 26382 | J14: 27768 | K14: 27722 | L14: 27337
A15: 기타비유동자산 | B15: 총계 − 위 항목 | C15: =IF(OR(C11=""),"",IFERROR(C11-SUM(C12,C13,C14),"")) | D15: =IF(OR(D11=""),"",IFERROR(D11-SUM(D12,D13,D14),"")) | E15: =IF(OR(E11=""),"",IFERROR(E11-SUM(E12,E13,E14),"")) | F15: =IF(OR(F11=""),"",IFERROR(F11-SUM(F12,F13,F14),"")) | G15: =IF(OR(G11=""),"",IFERROR(G11-SUM(G12,G13,G14),"")) | H15: =IF(OR(H11=""),"",IFERROR(H11-SUM(H12,H13,H14),"")) | I15: =IF(OR(I11=""),"",IFERROR(I11-SUM(I12,I13,I14),"")) | J15: =IF(OR(J11=""),"",IFERROR(J11-SUM(J12,J13,J14),"")) | ... L15: =IF(OR(L11=""),"",IFERROR(L11-SUM(L12,L13,L14),""))
A16: 자산총계 | C16: 1535349 | G16: 2576870 | H16: 1150601 | I16: 1311800 | J16: 1416918 | K16: 1535349 | L16: 2576870
A17: 부채
A18: 유동부채 | C18: 129392 | G18: 827430 | H18: 124396 | I18: 158552 | J18: 133907 | K18: 129392 | L18: 827430
A19: 매입채무
A20: 단기차입금
A21: 유동성장기부채
A22: 기타유동부채 | B22: 총계 − 위 항목 | C22: =IF(OR(C18=""),"",IFERROR(C18-SUM(C19,C20,C21),"")) | D22: =IF(OR(D18=""),"",IFERROR(D18-SUM(D19,D20,D21),"")) | E22: =IF(OR(E18=""),"",IFERROR(E18-SUM(E19,E20,E21),"")) | F22: =IF(OR(F18=""),"",IFERROR(F18-SUM(F19,F20,F21),"")) | G22: =IF(OR(G18=""),"",IFERROR(G18-SUM(G19,G20,G21),"")) | H22: =IF(OR(H18=""),"",IFERROR(H18-SUM(H19,H20,H21),"")) | I22: =IF(OR(I18=""),"",IFERROR(I18-SUM(I19,I20,I21),"")) | J22: =IF(OR(J18=""),"",IFERROR(J18-SUM(J19,J20,J21),"")) | ... L22: =IF(OR(L18=""),"",IFERROR(L18-SUM(L19,L20,L21),""))
A23: 비유동부채 | C23: 43459 | G23: 63235 | H23: 32920 | I23: 31369 | J23: 30448 | K23: 43459 | L23: 63235
A24: 장기차입금
A25: 사채
A26: 기타비유동부채 | B26: 총계 − 위 항목 | C26: =IF(OR(C23=""),"",IFERROR(C23-SUM(C24,C25),"")) | D26: =IF(OR(D23=""),"",IFERROR(D23-SUM(D24,D25),"")) | E26: =IF(OR(E23=""),"",IFERROR(E23-SUM(E24,E25),"")) | F26: =IF(OR(F23=""),"",IFERROR(F23-SUM(F24,F25),"")) | G26: =IF(OR(G23=""),"",IFERROR(G23-SUM(G24,G25),"")) | H26: =IF(OR(H23=""),"",IFERROR(H23-SUM(H24,H25),"")) | I26: =IF(OR(I23=""),"",IFERROR(I23-SUM(I24,I25),"")) | J26: =IF(OR(J23=""),"",IFERROR(J23-SUM(J24,J25),"")) | ... L26: =IF(OR(L23=""),"",IFERROR(L23-SUM(L24,L25),""))
A27: 부채총계 | C27: 172852 | G27: 890665 | H27: 157316 | I27: 189921 | J27: 164355 | K27: 172852 | L27: 890665
A28: 총차입금 | B28: 단기+유동성장기+장기+사채 | C28: =SUM(C20,C21,C24,C25) | D28: =SUM(D20,D21,D24,D25) | E28: =SUM(E20,E21,E24,E25) | F28: =SUM(F20,F21,F24,F25) | G28: =SUM(G20,G21,G24,G25) | H28: =SUM(H20,H21,H24,H25) | I28: =SUM(I20,I21,I24,I25) | J28: =SUM(J20,J21,J24,J25) | ... L28: =SUM(L20,L21,L24,L25)
A29: 순차입금 | B29: 음수 = 순현금 | C29: =C28-C6-N(C7) | D29: =D28-D6-N(D7) | E29: =E28-E6-N(E7) | F29: =F28-F6-N(F7) | G29: =G28-G6-N(G7) | H29: =H28-H6-N(H7) | I29: =I28-I6-N(I7) | J29: =J28-J6-N(J7) | ... L29: =L28-L6-N(L7)
A30: 자본
A31: 지배주주지분 | C31: 1361924 | G31: 1685215 | H31: 975661 | I31: 1100046 | J31: 1235325 | K31: 1361924 | L31: 1685215
A32: 자본금 | C32: 21279 | G32: 21279 | H32: 21279 | I32: 21279 | J32: 21279 | K32: 21279 | L32: 21279
A33: 이익잉여금 | C33: 1115729 | G33: 1492697 | H33: 832958 | I33: 940606 | J33: 1065913 | K33: 1115729 | L33: 1492697
A34: 비지배지분 | C34: 572 | G34: 989 | H34: 17624 | I34: 21832 | J34: 17236 | K34: 572 | L34: 989
A35: 자본총계 | C35: 1362497 | G35: 1686205 | H35: 993285 | I35: 1121878 | J35: 1252562 | K35: 1362497 | L35: 1686205
A36: 현금흐름 요약 | B36: 분기 = TTM (있을 때만)
A37: 영업활동현금흐름 | C37: 195460 | D37: 203003 | E37: 208154 | F37: 199390 | G37: 213572 | H37: 102068 | I37: 177867 | J37: 154284 | K37: 195460 | L37: 213572
A38: CAPEX (유·무형 취득) | B38: 양수로 입력 | C38: 52103 | D38: 27056 | E38: 26913 | F38: 24983 | G38: 31304 | H38: 31564 | I38: 37187 | J38: 28267 | K38: 52103 | L38: 31304
A39: FCF | C39: =IF(OR(C37="",C38=""),"",IFERROR(C37-C38,"")) | D39: =IF(OR(D37="",D38=""),"",IFERROR(D37-D38,"")) | E39: =IF(OR(E37="",E38=""),"",IFERROR(E37-E38,"")) | F39: =IF(OR(F37="",F38=""),"",IFERROR(F37-F38,"")) | G39: =IF(OR(G37="",G38=""),"",IFERROR(G37-G38,"")) | H39: =IF(OR(H37="",H38=""),"",IFERROR(H37-H38,"")) | I39: =IF(OR(I37="",I38=""),"",IFERROR(I37-I38,"")) | J39: =IF(OR(J37="",J38=""),"",IFERROR(J37-J38,"")) | ... L39: =IF(OR(L37="",L38=""),"",IFERROR(L37-L38,""))
A40: 배당금 지급 | B40: 양수로 입력 | C40: 48698 | D40: 52845 | E40: 52456 | F40: 56430 | G40: 56175 | H40: 33146 | I40: 36142 | J40: 43876 | K40: 48698 | L40: 56175
A41: 주요 재무 비율 | B41: 기준 (빨간 글씨 = 미달)
A42: 안정성
A43: 부채비율 | B43: 100%↓ | C43: =IF(OR(C27="",C35=""),"",IFERROR(C27/C35,"")) | D43: =IF(OR(D27="",D35=""),"",IFERROR(D27/D35,"")) | E43: =IF(OR(E27="",E35=""),"",IFERROR(E27/E35,"")) | F43: =IF(OR(F27="",F35=""),"",IFERROR(F27/F35,"")) | G43: =IF(OR(G27="",G35=""),"",IFERROR(G27/G35,"")) | H43: =IF(OR(H27="",H35=""),"",IFERROR(H27/H35,"")) | I43: =IF(OR(I27="",I35=""),"",IFERROR(I27/I35,"")) | J43: =IF(OR(J27="",J35=""),"",IFERROR(J27/J35,"")) | ... L43: =IF(OR(L27="",L35=""),"",IFERROR(L27/L35,""))
A44: 순차입금비율 | B44: 0%↓ 순현금 | C44: =IF(OR(C29="",C35=""),"",IFERROR(C29/C35,"")) | D44: =IF(OR(D29="",D35=""),"",IFERROR(D29/D35,"")) | E44: =IF(OR(E29="",E35=""),"",IFERROR(E29/E35,"")) | F44: =IF(OR(F29="",F35=""),"",IFERROR(F29/F35,"")) | G44: =IF(OR(G29="",G35=""),"",IFERROR(G29/G35,"")) | H44: =IF(OR(H29="",H35=""),"",IFERROR(H29/H35,"")) | I44: =IF(OR(I29="",I35=""),"",IFERROR(I29/I35,"")) | J44: =IF(OR(J29="",J35=""),"",IFERROR(J29/J35,"")) | ... L44: =IF(OR(L29="",L35=""),"",IFERROR(L29/L35,""))
A45: 자기자본비율 | B45: 50%↑ | C45: =IF(OR(C35="",C16=""),"",IFERROR(C35/C16,"")) | D45: =IF(OR(D35="",D16=""),"",IFERROR(D35/D16,"")) | E45: =IF(OR(E35="",E16=""),"",IFERROR(E35/E16,"")) | F45: =IF(OR(F35="",F16=""),"",IFERROR(F35/F16,"")) | G45: =IF(OR(G35="",G16=""),"",IFERROR(G35/G16,"")) | H45: =IF(OR(H35="",H16=""),"",IFERROR(H35/H16,"")) | I45: =IF(OR(I35="",I16=""),"",IFERROR(I35/I16,"")) | J45: =IF(OR(J35="",J16=""),"",IFERROR(J35/J16,"")) | ... L45: =IF(OR(L35="",L16=""),"",IFERROR(L35/L16,""))
A46: 유동비율 | B46: 150%↑ | C46: =IF(OR(C5="",C18=""),"",IFERROR(C5/C18,"")) | D46: =IF(OR(D5="",D18=""),"",IFERROR(D5/D18,"")) | E46: =IF(OR(E5="",E18=""),"",IFERROR(E5/E18,"")) | F46: =IF(OR(F5="",F18=""),"",IFERROR(F5/F18,"")) | G46: =IF(OR(G5="",G18=""),"",IFERROR(G5/G18,"")) | H46: =IF(OR(H5="",H18=""),"",IFERROR(H5/H18,"")) | I46: =IF(OR(I5="",I18=""),"",IFERROR(I5/I18,"")) | J46: =IF(OR(J5="",J18=""),"",IFERROR(J5/J18,"")) | ... L46: =IF(OR(L5="",L18=""),"",IFERROR(L5/L18,""))
A47: 당좌비율 | B47: 100%↑ | C47: =IF(OR(C5="",C18=""),"",IFERROR((C5-N(C9))/C18,"")) | D47: =IF(OR(D5="",D18=""),"",IFERROR((D5-N(D9))/D18,"")) | E47: =IF(OR(E5="",E18=""),"",IFERROR((E5-N(E9))/E18,"")) | F47: =IF(OR(F5="",F18=""),"",IFERROR((F5-N(F9))/F18,"")) | G47: =IF(OR(G5="",G18=""),"",IFERROR((G5-N(G9))/G18,"")) | H47: =IF(OR(H5="",H18=""),"",IFERROR((H5-N(H9))/H18,"")) | I47: =IF(OR(I5="",I18=""),"",IFERROR((I5-N(I9))/I18,"")) | J47: =IF(OR(J5="",J18=""),"",IFERROR((J5-N(J9))/J18,"")) | ... L47: =IF(OR(L5="",L18=""),"",IFERROR((L5-N(L9))/L18,""))
A48: 이자보상배율 | B48: 5x↑ (금융원가 기준) | C48: =IFERROR((IF(COUNT('연간'!F16:I16)<4,"",SUM('연간'!F16:I16)))/(IF(COUNT('연간'!F38:I38)<4,"",SUM('연간'!F38:I38))),"") | D48: =IFERROR((IF(COUNT('연간'!G16:J16)<4,"",SUM('연간'!G16:J16)))/(IF(COUNT('연간'!G38:J38)<4,"",SUM('연간'!G38:J38))),"") | E48: =IFERROR((IF(COUNT('연간'!H16:K16)<4,"",SUM('연간'!H16:K16)))/(IF(COUNT('연간'!H38:K38)<4,"",SUM('연간'!H38:K38))),"") | F48: =IFERROR((IF(COUNT('연간'!I16:L16)<4,"",SUM('연간'!I16:L16)))/(IF(COUNT('연간'!I38:L38)<4,"",SUM('연간'!I38:L38))),"") | G48: =IFERROR((IF(COUNT('연간'!J16:M16)<4,"",SUM('연간'!J16:M16)))/(IF(COUNT('연간'!J38:M38)<4,"",SUM('연간'!J38:M38))),"") | H48: =IFERROR(('연간'!T16)/('연간'!T38),"") | I48: =IFERROR(('연간'!U16)/('연간'!U38),"") | J48: =IFERROR(('연간'!V16)/('연간'!V38),"") | K48: =IFERROR(('연간'!W16)/('연간'!W38),"") | L48: =IFERROR(('연간'!X16)/('연간'!X38),"")
A49: 차입금 상환연수 | B49: 4년↓ (버핏) | C49: =IFERROR(IF((IF(COUNT('연간'!F44:I44)<4,"",SUM('연간'!F44:I44)))<=0,"적자",C28/(IF(COUNT('연간'!F44:I44)<4,"",SUM('연간'!F44:I44)))),"") | D49: =IFERROR(IF((IF(COUNT('연간'!G44:J44)<4,"",SUM('연간'!G44:J44)))<=0,"적자",D28/(IF(COUNT('연간'!G44:J44)<4,"",SUM('연간'!G44:J44)))),"") | E49: =IFERROR(IF((IF(COUNT('연간'!H44:K44)<4,"",SUM('연간'!H44:K44)))<=0,"적자",E28/(IF(COUNT('연간'!H44:K44)<4,"",SUM('연간'!H44:K44)))),"") | F49: =IFERROR(IF((IF(COUNT('연간'!I44:L44)<4,"",SUM('연간'!I44:L44)))<=0,"적자",F28/(IF(COUNT('연간'!I44:L44)<4,"",SUM('연간'!I44:L44)))),"") | G49: =IFERROR(IF((IF(COUNT('연간'!J44:M44)<4,"",SUM('연간'!J44:M44)))<=0,"적자",G28/(IF(COUNT('연간'!J44:M44)<4,"",SUM('연간'!J44:M44)))),"") | H49: =IFERROR(IF(('연간'!T44)<=0,"적자",H28/('연간'!T44)),"") | I49: =IFERROR(IF(('연간'!U44)<=0,"적자",I28/('연간'!U44)),"") | J49: =IFERROR(IF(('연간'!V44)<=0,"적자",J28/('연간'!V44)),"") | K49: =IFERROR(IF(('연간'!W44)<=0,"적자",K28/('연간'!W44)),"") | L49: =IFERROR(IF(('연간'!X44)<=0,"적자",L28/('연간'!X44)),"")
A50: 수익성
A51: ROE | B51: 15%↑ (버핏) | C51: =IFERROR((IF(COUNT('연간'!F44:I44)<4,"",SUM('연간'!F44:I44)))/C31,"") | D51: =IFERROR((IF(COUNT('연간'!G44:J44)<4,"",SUM('연간'!G44:J44)))/D31,"") | E51: =IFERROR((IF(COUNT('연간'!H44:K44)<4,"",SUM('연간'!H44:K44)))/E31,"") | F51: =IFERROR((IF(COUNT('연간'!I44:L44)<4,"",SUM('연간'!I44:L44)))/F31,"") | G51: =IFERROR((IF(COUNT('연간'!J44:M44)<4,"",SUM('연간'!J44:M44)))/G31,"") | H51: =IFERROR(('연간'!T44)/H31,"") | I51: =IFERROR(('연간'!U44)/I31,"") | J51: =IFERROR(('연간'!V44)/J31,"") | K51: =IFERROR(('연간'!W44)/K31,"") | L51: =IFERROR(('연간'!X44)/L31,"")
A52: ROA | B52: 5%↑ | C52: =IFERROR((IF(COUNT('연간'!F43:I43)<4,"",SUM('연간'!F43:I43)))/C16,"") | D52: =IFERROR((IF(COUNT('연간'!G43:J43)<4,"",SUM('연간'!G43:J43)))/D16,"") | E52: =IFERROR((IF(COUNT('연간'!H43:K43)<4,"",SUM('연간'!H43:K43)))/E16,"") | F52: =IFERROR((IF(COUNT('연간'!I43:L43)<4,"",SUM('연간'!I43:L43)))/F16,"") | G52: =IFERROR((IF(COUNT('연간'!J43:M43)<4,"",SUM('연간'!J43:M43)))/G16,"") | H52: =IFERROR(('연간'!T43)/H16,"") | I52: =IFERROR(('연간'!U43)/I16,"") | J52: =IFERROR(('연간'!V43)/J16,"") | K52: =IFERROR(('연간'!W43)/K16,"") | L52: =IFERROR(('연간'!X43)/L16,"")
A53: ROIC | B53: 10%↑ (세후영업이익 기준) | C53: =IFERROR((IF(COUNT('연간'!F16:I16)<4,"",SUM('연간'!F16:I16)))*(1-0.3)/(C35+C29),"") | D53: =IFERROR((IF(COUNT('연간'!G16:J16)<4,"",SUM('연간'!G16:J16)))*(1-0.3)/(D35+D29),"") | E53: =IFERROR((IF(COUNT('연간'!H16:K16)<4,"",SUM('연간'!H16:K16)))*(1-0.3)/(E35+E29),"") | F53: =IFERROR((IF(COUNT('연간'!I16:L16)<4,"",SUM('연간'!I16:L16)))*(1-0.3)/(F35+F29),"") | G53: =IFERROR((IF(COUNT('연간'!J16:M16)<4,"",SUM('연간'!J16:M16)))*(1-0.3)/(G35+G29),"") | H53: =IFERROR(('연간'!T16)*(1-0.3)/(H35+H29),"") | I53: =IFERROR(('연간'!U16)*(1-0.3)/(I35+I29),"") | J53: =IFERROR(('연간'!V16)*(1-0.3)/(J35+J29),"") | K53: =IFERROR(('연간'!W16)*(1-0.3)/(K35+K29),"") | L53: =IFERROR(('연간'!X16)*(1-0.3)/(L35+L29),"")
A54: 매출총이익률 (GPM) | B54: 40%↑ (해자 신호) | C54: =IFERROR((IF(COUNT('연간'!F12:I12)<4,"",SUM('연간'!F12:I12)))/(IF(COUNT('연간'!F4:I4)<4,"",SUM('연간'!F4:I4))),"") | D54: =IFERROR((IF(COUNT('연간'!G12:J12)<4,"",SUM('연간'!G12:J12)))/(IF(COUNT('연간'!G4:J4)<4,"",SUM('연간'!G4:J4))),"") | E54: =IFERROR((IF(COUNT('연간'!H12:K12)<4,"",SUM('연간'!H12:K12)))/(IF(COUNT('연간'!H4:K4)<4,"",SUM('연간'!H4:K4))),"") | F54: =IFERROR((IF(COUNT('연간'!I12:L12)<4,"",SUM('연간'!I12:L12)))/(IF(COUNT('연간'!I4:L4)<4,"",SUM('연간'!I4:L4))),"") | G54: =IFERROR((IF(COUNT('연간'!J12:M12)<4,"",SUM('연간'!J12:M12)))/(IF(COUNT('연간'!J4:M4)<4,"",SUM('연간'!J4:M4))),"") | H54: =IFERROR(('연간'!T12)/('연간'!T4),"") | I54: =IFERROR(('연간'!U12)/('연간'!U4),"") | J54: =IFERROR(('연간'!V12)/('연간'!V4),"") | K54: =IFERROR(('연간'!W12)/('연간'!W4),"") | L54: =IFERROR(('연간'!X12)/('연간'!X4),"")
A55: 영업이익률 (OPM) | B55: 15%↑ | C55: =IFERROR((IF(COUNT('연간'!F16:I16)<4,"",SUM('연간'!F16:I16)))/(IF(COUNT('연간'!F4:I4)<4,"",SUM('연간'!F4:I4))),"") | D55: =IFERROR((IF(COUNT('연간'!G16:J16)<4,"",SUM('연간'!G16:J16)))/(IF(COUNT('연간'!G4:J4)<4,"",SUM('연간'!G4:J4))),"") | E55: =IFERROR((IF(COUNT('연간'!H16:K16)<4,"",SUM('연간'!H16:K16)))/(IF(COUNT('연간'!H4:K4)<4,"",SUM('연간'!H4:K4))),"") | F55: =IFERROR((IF(COUNT('연간'!I16:L16)<4,"",SUM('연간'!I16:L16)))/(IF(COUNT('연간'!I4:L4)<4,"",SUM('연간'!I4:L4))),"") | G55: =IFERROR((IF(COUNT('연간'!J16:M16)<4,"",SUM('연간'!J16:M16)))/(IF(COUNT('연간'!J4:M4)<4,"",SUM('연간'!J4:M4))),"") | H55: =IFERROR(('연간'!T16)/('연간'!T4),"") | I55: =IFERROR(('연간'!U16)/('연간'!U4),"") | J55: =IFERROR(('연간'!V16)/('연간'!V4),"") | K55: =IFERROR(('연간'!W16)/('연간'!W4),"") | L55: =IFERROR(('연간'!X16)/('연간'!X4),"")
A56: 순이익률 | B56: 10%↑ | C56: =IFERROR((IF(COUNT('연간'!F43:I43)<4,"",SUM('연간'!F43:I43)))/(IF(COUNT('연간'!F4:I4)<4,"",SUM('연간'!F4:I4))),"") | D56: =IFERROR((IF(COUNT('연간'!G43:J43)<4,"",SUM('연간'!G43:J43)))/(IF(COUNT('연간'!G4:J4)<4,"",SUM('연간'!G4:J4))),"") | E56: =IFERROR((IF(COUNT('연간'!H43:K43)<4,"",SUM('연간'!H43:K43)))/(IF(COUNT('연간'!H4:K4)<4,"",SUM('연간'!H4:K4))),"") | F56: =IFERROR((IF(COUNT('연간'!I43:L43)<4,"",SUM('연간'!I43:L43)))/(IF(COUNT('연간'!I4:L4)<4,"",SUM('연간'!I4:L4))),"") | G56: =IFERROR((IF(COUNT('연간'!J43:M43)<4,"",SUM('연간'!J43:M43)))/(IF(COUNT('연간'!J4:M4)<4,"",SUM('연간'!J4:M4))),"") | H56: =IFERROR(('연간'!T43)/('연간'!T4),"") | I56: =IFERROR(('연간'!U43)/('연간'!U4),"") | J56: =IFERROR(('연간'!V43)/('연간'!V4),"") | K56: =IFERROR(('연간'!W43)/('연간'!W4),"") | L56: =IFERROR(('연간'!X43)/('연간'!X4),"")
A57: 효율성 (회전율)
A58: 총자산회전율 | B58: 높을수록↑ | C58: =IFERROR((IF(COUNT('연간'!F4:I4)<4,"",SUM('연간'!F4:I4)))/C16,"") | D58: =IFERROR((IF(COUNT('연간'!G4:J4)<4,"",SUM('연간'!G4:J4)))/D16,"") | E58: =IFERROR((IF(COUNT('연간'!H4:K4)<4,"",SUM('연간'!H4:K4)))/E16,"") | F58: =IFERROR((IF(COUNT('연간'!I4:L4)<4,"",SUM('연간'!I4:L4)))/F16,"") | G58: =IFERROR((IF(COUNT('연간'!J4:M4)<4,"",SUM('연간'!J4:M4)))/G16,"") | H58: =IFERROR(('연간'!T4)/H16,"") | I58: =IFERROR(('연간'!U4)/I16,"") | J58: =IFERROR(('연간'!V4)/J16,"") | K58: =IFERROR(('연간'!W4)/K16,"") | L58: =IFERROR(('연간'!X4)/L16,"")
A59: 매출채권회전일수 | B59: 짧을수록↑ | C59: =IFERROR(C8/(IF(COUNT('연간'!F4:I4)<4,"",SUM('연간'!F4:I4)))*365,"") | D59: =IFERROR(D8/(IF(COUNT('연간'!G4:J4)<4,"",SUM('연간'!G4:J4)))*365,"") | E59: =IFERROR(E8/(IF(COUNT('연간'!H4:K4)<4,"",SUM('연간'!H4:K4)))*365,"") | F59: =IFERROR(F8/(IF(COUNT('연간'!I4:L4)<4,"",SUM('연간'!I4:L4)))*365,"") | G59: =IFERROR(G8/(IF(COUNT('연간'!J4:M4)<4,"",SUM('연간'!J4:M4)))*365,"") | H59: =IFERROR(H8/('연간'!T4)*365,"") | I59: =IFERROR(I8/('연간'!U4)*365,"") | J59: =IFERROR(J8/('연간'!V4)*365,"") | K59: =IFERROR(K8/('연간'!W4)*365,"") | L59: =IFERROR(L8/('연간'!X4)*365,"")
A60: 재고자산회전일수 | B60: 짧을수록↑ | C60: =IFERROR(C9/(IF(COUNT('연간'!F11:I11)<4,"",SUM('연간'!F11:I11)))*365,"") | D60: =IFERROR(D9/(IF(COUNT('연간'!G11:J11)<4,"",SUM('연간'!G11:J11)))*365,"") | E60: =IFERROR(E9/(IF(COUNT('연간'!H11:K11)<4,"",SUM('연간'!H11:K11)))*365,"") | F60: =IFERROR(F9/(IF(COUNT('연간'!I11:L11)<4,"",SUM('연간'!I11:L11)))*365,"") | G60: =IFERROR(G9/(IF(COUNT('연간'!J11:M11)<4,"",SUM('연간'!J11:M11)))*365,"") | H60: =IFERROR(H9/('연간'!T11)*365,"") | I60: =IFERROR(I9/('연간'!U11)*365,"") | J60: =IFERROR(J9/('연간'!V11)*365,"") | K60: =IFERROR(K9/('연간'!W11)*365,"") | L60: =IFERROR(L9/('연간'!X11)*365,"")
A61: 매입채무회전일수 | B61: 길수록 유리 | C61: =IFERROR(C19/(IF(COUNT('연간'!F11:I11)<4,"",SUM('연간'!F11:I11)))*365,"") | D61: =IFERROR(D19/(IF(COUNT('연간'!G11:J11)<4,"",SUM('연간'!G11:J11)))*365,"") | E61: =IFERROR(E19/(IF(COUNT('연간'!H11:K11)<4,"",SUM('연간'!H11:K11)))*365,"") | F61: =IFERROR(F19/(IF(COUNT('연간'!I11:L11)<4,"",SUM('연간'!I11:L11)))*365,"") | G61: =IFERROR(G19/(IF(COUNT('연간'!J11:M11)<4,"",SUM('연간'!J11:M11)))*365,"") | H61: =IFERROR(H19/('연간'!T11)*365,"") | I61: =IFERROR(I19/('연간'!U11)*365,"") | J61: =IFERROR(J19/('연간'!V11)*365,"") | K61: =IFERROR(K19/('연간'!W11)*365,"") | L61: =IFERROR(L19/('연간'!X11)*365,"")
A62: 현금전환주기 (CCC) | B62: 짧을수록↑ | C62: =IF(OR(C59="",C60="",C61=""),"",IFERROR(C59+C60-C61,"")) | D62: =IF(OR(D59="",D60="",D61=""),"",IFERROR(D59+D60-D61,"")) | E62: =IF(OR(E59="",E60="",E61=""),"",IFERROR(E59+E60-E61,"")) | F62: =IF(OR(F59="",F60="",F61=""),"",IFERROR(F59+F60-F61,"")) | G62: =IF(OR(G59="",G60="",G61=""),"",IFERROR(G59+G60-G61,"")) | H62: =IF(OR(H59="",H60="",H61=""),"",IFERROR(H59+H60-H61,"")) | I62: =IF(OR(I59="",I60="",I61=""),"",IFERROR(I59+I60-I61,"")) | J62: =IF(OR(J59="",J60="",J61=""),"",IFERROR(J59+J60-J61,"")) | ... L62: =IF(OR(L59="",L60="",L61=""),"",IFERROR(L59+L60-L61,""))
A63: 현금흐름
A64: 영업현금흐름 / 순이익 | B64: 1x↑ (이익의 질) | C64: =IF(C37="","",IFERROR(C37/(IF(COUNT('연간'!F43:I43)<4,"",SUM('연간'!F43:I43))),"")) | D64: =IF(D37="","",IFERROR(D37/(IF(COUNT('연간'!G43:J43)<4,"",SUM('연간'!G43:J43))),"")) | E64: =IF(E37="","",IFERROR(E37/(IF(COUNT('연간'!H43:K43)<4,"",SUM('연간'!H43:K43))),"")) | F64: =IF(F37="","",IFERROR(F37/(IF(COUNT('연간'!I43:L43)<4,"",SUM('연간'!I43:L43))),"")) | G64: =IF(G37="","",IFERROR(G37/(IF(COUNT('연간'!J43:M43)<4,"",SUM('연간'!J43:M43))),"")) | H64: =IF(H37="","",IFERROR(H37/('연간'!T43),"")) | I64: =IF(I37="","",IFERROR(I37/('연간'!U43),"")) | J64: =IF(J37="","",IFERROR(J37/('연간'!V43),"")) | K64: =IF(K37="","",IFERROR(K37/('연간'!W43),"")) | L64: =IF(L37="","",IFERROR(L37/('연간'!X43),""))
A65: FCF 마진 | B65: 5%↑ | C65: =IF(C39="","",IFERROR(C39/(IF(COUNT('연간'!F4:I4)<4,"",SUM('연간'!F4:I4))),"")) | D65: =IF(D39="","",IFERROR(D39/(IF(COUNT('연간'!G4:J4)<4,"",SUM('연간'!G4:J4))),"")) | E65: =IF(E39="","",IFERROR(E39/(IF(COUNT('연간'!H4:K4)<4,"",SUM('연간'!H4:K4))),"")) | F65: =IF(F39="","",IFERROR(F39/(IF(COUNT('연간'!I4:L4)<4,"",SUM('연간'!I4:L4))),"")) | G65: =IF(G39="","",IFERROR(G39/(IF(COUNT('연간'!J4:M4)<4,"",SUM('연간'!J4:M4))),"")) | H65: =IF(H39="","",IFERROR(H39/('연간'!T4),"")) | I65: =IF(I39="","",IFERROR(I39/('연간'!U4),"")) | J65: =IF(J39="","",IFERROR(J39/('연간'!V4),"")) | K65: =IF(K39="","",IFERROR(K39/('연간'!W4),"")) | L65: =IF(L39="","",IFERROR(L39/('연간'!X4),""))
A66: CAPEX / 매출 | B66: 낮을수록↑ (자본 가벼움) | C66: =IF(C38="","",IFERROR(C38/(IF(COUNT('연간'!F4:I4)<4,"",SUM('연간'!F4:I4))),"")) | D66: =IF(D38="","",IFERROR(D38/(IF(COUNT('연간'!G4:J4)<4,"",SUM('연간'!G4:J4))),"")) | E66: =IF(E38="","",IFERROR(E38/(IF(COUNT('연간'!H4:K4)<4,"",SUM('연간'!H4:K4))),"")) | F66: =IF(F38="","",IFERROR(F38/(IF(COUNT('연간'!I4:L4)<4,"",SUM('연간'!I4:L4))),"")) | G66: =IF(G38="","",IFERROR(G38/(IF(COUNT('연간'!J4:M4)<4,"",SUM('연간'!J4:M4))),"")) | H66: =IF(H38="","",IFERROR(H38/('연간'!T4),"")) | I66: =IF(I38="","",IFERROR(I38/('연간'!U4),"")) | J66: =IF(J38="","",IFERROR(J38/('연간'!V4),"")) | K66: =IF(K38="","",IFERROR(K38/('연간'!W4),"")) | L66: =IF(L38="","",IFERROR(L38/('연간'!X4),""))
A67: 배당성향 | B67: 참고 | C67: =IF(C40="","",IFERROR(C40/(IF(COUNT('연간'!F44:I44)<4,"",SUM('연간'!F44:I44))),"")) | D67: =IF(D40="","",IFERROR(D40/(IF(COUNT('연간'!G44:J44)<4,"",SUM('연간'!G44:J44))),"")) | E67: =IF(E40="","",IFERROR(E40/(IF(COUNT('연간'!H44:K44)<4,"",SUM('연간'!H44:K44))),"")) | F67: =IF(F40="","",IFERROR(F40/(IF(COUNT('연간'!I44:L44)<4,"",SUM('연간'!I44:L44))),"")) | G67: =IF(G40="","",IFERROR(G40/(IF(COUNT('연간'!J44:M44)<4,"",SUM('연간'!J44:M44))),"")) | H67: =IF(H40="","",IFERROR(H40/('연간'!T44),"")) | I67: =IF(I40="","",IFERROR(I40/('연간'!U44),"")) | J67: =IF(J40="","",IFERROR(J40/('연간'!V44),"")) | K67: =IF(K40="","",IFERROR(K40/('연간'!W44),"")) | L67: =IF(L40="","",IFERROR(L40/('연간'!X44),""))
A69: 재무상태표 · 전 항목 | B69: 분기 말 잔액
A70: 항목 | B70: 참고 | C70: 2025.4Q | D70: 2026.1Q | E70: 2026.2Q | F70: 2026.3Q | G70: 2026.4Q | H70: 2022 | I70: 2023 | J70: 2024 | K70: 2025 | L70: 2026
A71: 유형자산 | C71: 115412 | G71: 156519 | H71: 108893 | I71: 112085 | J71: 114586 | K71: 115412 | L71: 156519
A72: 영업권 | C72: 15748 | G72: 35061 | H72: 9638 | I72: 9819 | J72: 15287 | K72: 15748 | L72: 35061
A73: 무형자산 | C73: 143652 | G73: 173553 | H73: 81223 | I73: 96309 | J73: 117621 | K73: 143652 | L73: 173553
A74: 사용권자산 | C74: 19395 | G74: 22789 | H74: 3524 | I74: 6482 | J74: 9440 | K74: 19395 | L74: 22789
A75: Investment Property | C75: 27722 | G75: 27337 | H75: 26672 | I75: 26382 | J75: 27768 | K75: 27722 | L75: 27337
A76: 지분법 투자 | C76: 10429 | G76: 710751 | K76: 10429 | L76: 710751
A77: 기타금융자산 | C77: 299799 | G77: 107518 | H77: 242479 | I77: 247711 | J77: 292321 | K77: 299799 | L77: 107518
A78: 이연법인세자산 | C78: 13244 | G78: 4344 | H78: 12907 | I78: 22100 | J78: 13526 | K78: 13244 | L78: 4344
A79: 기타비유동자산 | C79: 31440 | G79: 28660 | H79: 6055 | I79: 6716 | J79: 42158 | K79: 31440 | L79: 28660
A80: 비유동자산 합계 | C80: 676844 | G80: 1266535 | H80: 491396 | I80: 527607 | J80: 632712 | K80: 676844 | L80: 1266535
A81: 재고자산 | C81: 65477 | G81: 99396 | H81: 45892 | I81: 57919 | J81: 64916 | K81: 65477 | L81: 99396
A82: Trade Receivables CA | C82: 120553 | G82: 159773 | H82: 122965 | I82: 109774 | J82: 122830 | K82: 120553 | L82: 159773
A83: 기타금융자산 | C83: 270024 | G83: 310748 | H83: 210757 | I83: 254131 | J83: 215761 | K83: 270024 | L83: 310748
A84: 미수법인세 | H84: 51 | I84: 68
A85: 기타유동자산 | C85: 27653 | G85: 29020 | H85: 25117 | I85: 53142 | J85: 22607 | K85: 27653 | L85: 29020
A86: 현금및현금성자산 | C86: 374795 | G86: 711397 | H86: 254420 | I86: 309224 | J86: 358090 | K86: 374795 | L86: 711397
A87: 유동자산 합계 | C87: 858504 | G87: 1310335 | H87: 659205 | I87: 784192 | J87: 784205 | K87: 858504 | L87: 1310335
A88: 자산 합계 | C88: 1535349 | G88: 2576870 | H88: 1150601 | I88: 1311800 | J88: 1416918 | K88: 1535349 | L88: 2576870
A89: 자본금 | C89: 21279 | G89: 21279 | H89: 21279 | I89: 21279 | J89: 21279 | K89: 21279 | L89: 21279
A90: 자본잉여금 | C90: 17845 | G90: 17824 | H90: 14455 | I90: 15204 | J90: 14242 | K90: 17845 | L90: 17824
A91: 자기주식 | C91: -65855 | G91: -65189 | H91: -57857 | I91: -63074 | J91: -137889 | K91: -65855 | L91: -65189
A92: 이익잉여금 | C92: 1115729 | G92: 1492697 | H92: 832958 | I92: 940606 | J92: 1065913 | K92: 1115729 | L92: 1492697
A93: 기타자본구성요소 | C93: 272924 | G93: 218603 | H93: 164824 | I93: 186030 | J93: 271778 | K93: 272924 | L93: 218603
A94: Equity Attributable To Owners Of Parent | C94: 1361924 | G94: 1685215 | H94: 975661 | I94: 1100046 | J94: 1235325 | K94: 1361924 | L94: 1685215
A95: 비지배지분 | C95: 572 | G95: 989 | H95: 17624 | I95: 21832 | J95: 17236 | K95: 572 | L95: 989
A96: 자본 합계 | C96: 1362497 | G96: 1686205 | H96: 993285 | I96: 1121878 | J96: 1252562 | K96: 1362497 | L96: 1686205
... A100: 이연법인세부채 | C100: 4401 | G100: 17476 | H100: 7807 | I100: 5916 | J100: 4360 | K100: 4401 | L100: 17476
A101: 충당금 | C101: 0 | G101: 2526 | K101: 0 | L101: 2526
A102: 기타비유동부채 | C102: 4363 | G102: 3626 | H102: 354 | I102: 1343 | J102: 1691 | K102: 4363 | L102: 3626
A103: 비유동부채 합계 | C103: 43459 | G103: 63235 | H103: 32920 | I103: 31369 | J103: 30448 | K103: 43459 | L103: 63235
A104: 사채 및 차입금 | C104: 0 | G104: 660000 | K104: 0 | L104: 660000
...

Sheet 출처
A1: 출처 · 쓴 결산단신
A3: 공시일 | B3: 문서 | C3: PDF
A4: 2026-08-03 | B4: 2027년 3월 결산기 １분기 결산단신 | C4: https://www2.jpx.co.jp/disc/45070/140120260803506986.pdf
A5: 2026-05-12 | B5: 2026년 3월 결산기 연간 결산단신 | C5: https://www2.jpx.co.jp/disc/45070/140120260512525603.pdf
A6: 2026-01-30 | B6: 2026년 3월 결산기 3분기 결산단신 | C6: https://www2.jpx.co.jp/disc/45070/140120260130542826.pdf
A7: 2025-10-27 | B7: 2026년 3월 결산기 2분기 결산단신 | C7: https://www2.jpx.co.jp/disc/45070/140120251027579144.pdf
A8: 2025-07-28 | B8: 2026년 3월 결산기 1분기 결산단신 | C8: https://www2.jpx.co.jp/disc/45070/140120250728521233.pdf
A9: 2025-05-12 | B9: 2025년 3월 결산기 연간 결산단신 | C9: https://www2.jpx.co.jp/disc/45070/140120250509538686.pdf
A10: 2025-01-31 | B10: 2025년 3월 결산기 3분기 결산단신 | C10: https://www2.jpx.co.jp/disc/45070/140120250130558067.pdf
A11: 2024-10-28 | B11: 2025년 3월 결산기 2분기 결산단신 | C11: https://www2.jpx.co.jp/disc/45070/140120241025503103.pdf
A12: 2024-07-29 | B12: 2025년 3월 결산기 1분기 결산단신 | C12: https://www2.jpx.co.jp/disc/45070/140120240726555510.pdf
A13: 2024-05-13 | B13: 2024년 3월 결산기 연간 결산단신 | C13: https://www2.jpx.co.jp/disc/45070/140120240513591454.pdf
A14: 2024-01-31 | B14: 2024년 3월 결산기 3분기 결산단신 | C14: https://www2.jpx.co.jp/disc/45070/140120240130522211.pdf
... A22: 2020-06-24 | B22: 2020년 3월 결산기 연간 결산단신 | C22: https://www2.jpx.co.jp/disc/45070/140120200624451077.pdf
