Workbook

Sheet 연간
A1: 5257 Model
A2: 모를 땐 보수적으로 | B2: (단위: 백만엔) | C2: 12월 결산 · 일본 기준 · 2026.3Q = 2026년 12월 결산기 3분기 | Y2: (추정: 파란 글씨 = 직접 입력)
A3: 항목 | B3: 참고 | C3: 2023.4Q | D3: 2024.1Q | E3: 2024.2Q | F3: 2024.3Q | G3: 2024.4Q | H3: 2025.1Q | I3: 2025.2Q | J3: 2025.3Q | K3: 2025.4Q | L3: 2026.1Q | M3: 2026.2Q | N3: 2026.3Q | O3: 2016 | P3: 2017 | Q3: 2018 | R3: 2019 | S3: 2020 | T3: 2021 | U3: 2022 | V3: 2023 | W3: 2024 | X3: 2025 | Y3: 2026(MW) | Z3: 2027(MW) | AA3: 2028(MW) | AB3: 2029(MW) | AC3: 2030(MW)
A4: 매출액 | B4: MW 직접 입력 | C4: 1426.668 | D4: 1584.021 | E4: 1511.883 | F4: 1648.352 | G4: 1717.573 | H4: 1676.977 | I4: 1617.122 | J4: 1690.535 | K4: 1731.555 | L4: 1718.008 | M4: 1797.601 | N4: 1859.032 | U4: 4626.211 | V4: 5422.716 | W4: 6461.829 | X4: 6716.189 | Y4: =IF(COUNT(Y7)=0,"",SUM(Y7)) | Z4: =IF(COUNT(Z7)=0,"",SUM(Z7)) | AA4: =IF(COUNT(AA7)=0,"",SUM(AA7)) | AB4: =IF(COUNT(AB7)=0,"",SUM(AB7)) | AC4: =IF(COUNT(AC7)=0,"",SUM(AC7))
A5: YoY | G5: =IF(OR(G4="",C4=""),"",IFERROR(G4/C4-1,"")) | H5: =IF(OR(H4="",D4=""),"",IFERROR(H4/D4-1,"")) | I5: =IF(OR(I4="",E4=""),"",IFERROR(I4/E4-1,"")) | J5: =IF(OR(J4="",F4=""),"",IFERROR(J4/F4-1,"")) | K5: =IF(OR(K4="",G4=""),"",IFERROR(K4/G4-1,"")) | L5: =IF(OR(L4="",H4=""),"",IFERROR(L4/H4-1,"")) | M5: =IF(OR(M4="",I4=""),"",IFERROR(M4/I4-1,"")) | N5: =IF(OR(N4="",J4=""),"",IFERROR(N4/J4-1,"")) | P5: =IF(OR(P4="",O4=""),"",IFERROR(P4/O4-1,"")) | Q5: =IF(OR(Q4="",P4=""),"",IFERROR(Q4/P4-1,"")) | R5: =IF(OR(R4="",Q4=""),"",IFERROR(R4/Q4-1,"")) | S5: =IF(OR(S4="",R4=""),"",IFERROR(S4/R4-1,"")) | T5: =IF(OR(T4="",S4=""),"",IFERROR(T4/S4-1,"")) | U5: =IF(OR(U4="",T4=""),"",IFERROR(U4/T4-1,"")) | V5: =IF(OR(V4="",U4=""),"",IFERROR(V4/U4-1,"")) | W5: =IF(OR(W4="",V4=""),"",IFERROR(W4/V4-1,"")) | ... AC5: =IF(OR(AC4="",AB4=""),"",IFERROR(AC4/AB4-1,""))
A6: 제품별 매출 분류 | B6: 사업보고서 매출실적
A7: (제품별 매출 미공시 — 직접 입력)
A8: 비중 | C8: =IF(OR(C7="",C4=""),"",IFERROR(C7/C4,"")) | D8: =IF(OR(D7="",D4=""),"",IFERROR(D7/D4,"")) | E8: =IF(OR(E7="",E4=""),"",IFERROR(E7/E4,"")) | F8: =IF(OR(F7="",F4=""),"",IFERROR(F7/F4,"")) | G8: =IF(OR(G7="",G4=""),"",IFERROR(G7/G4,"")) | H8: =IF(OR(H7="",H4=""),"",IFERROR(H7/H4,"")) | I8: =IF(OR(I7="",I4=""),"",IFERROR(I7/I4,"")) | J8: =IF(OR(J7="",J4=""),"",IFERROR(J7/J4,"")) | ... AC8: =IF(OR(AC7="",AC4=""),"",IFERROR(AC7/AC4,""))
A9: YoY | G9: =IF(OR(G7="",C7=""),"",IFERROR(G7/C7-1,"")) | H9: =IF(OR(H7="",D7=""),"",IFERROR(H7/D7-1,"")) | I9: =IF(OR(I7="",E7=""),"",IFERROR(I7/E7-1,"")) | J9: =IF(OR(J7="",F7=""),"",IFERROR(J7/F7-1,"")) | K9: =IF(OR(K7="",G7=""),"",IFERROR(K7/G7-1,"")) | L9: =IF(OR(L7="",H7=""),"",IFERROR(L7/H7-1,"")) | M9: =IF(OR(M7="",I7=""),"",IFERROR(M7/I7-1,"")) | N9: =IF(OR(N7="",J7=""),"",IFERROR(N7/J7-1,"")) | P9: =IF(OR(P7="",O7=""),"",IFERROR(P7/O7-1,"")) | Q9: =IF(OR(Q7="",P7=""),"",IFERROR(Q7/P7-1,"")) | R9: =IF(OR(R7="",Q7=""),"",IFERROR(R7/Q7-1,"")) | S9: =IF(OR(S7="",R7=""),"",IFERROR(S7/R7-1,"")) | T9: =IF(OR(T7="",S7=""),"",IFERROR(T7/S7-1,"")) | U9: =IF(OR(U7="",T7=""),"",IFERROR(U7/T7-1,"")) | V9: =IF(OR(V7="",U7=""),"",IFERROR(V7/U7-1,"")) | W9: =IF(OR(W7="",V7=""),"",IFERROR(W7/V7-1,"")) | ... AC9: =IF(OR(AC7="",AB7=""),"",IFERROR(AC7/AB7-1,""))
A10: 매출원가
A11: 전체 매출원가 | C11: 1109.397 | D11: 1213.005 | E11: 1202.67 | F11: 1316.258 | G11: 1305.314 | H11: 1355.062 | I11: 1343.012 | J11: 1396.342 | K11: 1324.905 | L11: 1342.983 | M11: 1336.124 | N11: 1429.576 | U11: 3598.047 | V11: 4088.889 | W11: 5037.247 | X11: 5419.321
A12: YoY | G12: =IF(OR(G11="",C11=""),"",IF(C11<=0,"",IFERROR(G11/C11-1,""))) | H12: =IF(OR(H11="",D11=""),"",IF(D11<=0,"",IFERROR(H11/D11-1,""))) | I12: =IF(OR(I11="",E11=""),"",IF(E11<=0,"",IFERROR(I11/E11-1,""))) | J12: =IF(OR(J11="",F11=""),"",IF(F11<=0,"",IFERROR(J11/F11-1,""))) | K12: =IF(OR(K11="",G11=""),"",IF(G11<=0,"",IFERROR(K11/G11-1,""))) | L12: =IF(OR(L11="",H11=""),"",IF(H11<=0,"",IFERROR(L11/H11-1,""))) | M12: =IF(OR(M11="",I11=""),"",IF(I11<=0,"",IFERROR(M11/I11-1,""))) | N12: =IF(OR(N11="",J11=""),"",IF(J11<=0,"",IFERROR(N11/J11-1,""))) | P12: =IF(OR(P11="",O11=""),"",IF(O11<=0,"",IFERROR(P11/O11-1,""))) | Q12: =IF(OR(Q11="",P11=""),"",IF(P11<=0,"",IFERROR(Q11/P11-1,""))) | R12: =IF(OR(R11="",Q11=""),"",IF(Q11<=0,"",IFERROR(R11/Q11-1,""))) | S12: =IF(OR(S11="",R11=""),"",IF(R11<=0,"",IFERROR(S11/R11-1,""))) | T12: =IF(OR(T11="",S11=""),"",IF(S11<=0,"",IFERROR(T11/S11-1,""))) | U12: =IF(OR(U11="",T11=""),"",IF(T11<=0,"",IFERROR(U11/T11-1,""))) | V12: =IF(OR(V11="",U11=""),"",IF(U11<=0,"",IFERROR(V11/U11-1,""))) | W12: =IF(OR(W11="",V11=""),"",IF(V11<=0,"",IFERROR(W11/V11-1,""))) | ... AC12: =IF(OR(AC11="",AB11=""),"",IF(AB11<=0,"",IFERROR(AC11/AB11-1,"")))
A13: 매출총이익 | C13: =IF(OR(C4="",C11=""),"",IFERROR(C4-C11,"")) | D13: =IF(OR(D4="",D11=""),"",IFERROR(D4-D11,"")) | E13: =IF(OR(E4="",E11=""),"",IFERROR(E4-E11,"")) | F13: =IF(OR(F4="",F11=""),"",IFERROR(F4-F11,"")) | G13: =IF(OR(G4="",G11=""),"",IFERROR(G4-G11,"")) | H13: =IF(OR(H4="",H11=""),"",IFERROR(H4-H11,"")) | I13: =IF(OR(I4="",I11=""),"",IFERROR(I4-I11,"")) | J13: =IF(OR(J4="",J11=""),"",IFERROR(J4-J11,"")) | ... X13: =IF(OR(X4="",X11=""),"",IFERROR(X4-X11,""))
A14: GPM | C14: =IF(OR(C13="",C4=""),"",IFERROR(C13/C4,"")) | D14: =IF(OR(D13="",D4=""),"",IFERROR(D13/D4,"")) | E14: =IF(OR(E13="",E4=""),"",IFERROR(E13/E4,"")) | F14: =IF(OR(F13="",F4=""),"",IFERROR(F13/F4,"")) | G14: =IF(OR(G13="",G4=""),"",IFERROR(G13/G4,"")) | H14: =IF(OR(H13="",H4=""),"",IFERROR(H13/H4,"")) | I14: =IF(OR(I13="",I4=""),"",IFERROR(I13/I4,"")) | J14: =IF(OR(J13="",J4=""),"",IFERROR(J13/J4,"")) | ... AC14: =IF(OR(AC13="",AC4=""),"",IFERROR(AC13/AC4,""))
A15: YoY | G15: =IF(OR(G13="",C13=""),"",IF(C13<=0,"",IFERROR(G13/C13-1,""))) | H15: =IF(OR(H13="",D13=""),"",IF(D13<=0,"",IFERROR(H13/D13-1,""))) | I15: =IF(OR(I13="",E13=""),"",IF(E13<=0,"",IFERROR(I13/E13-1,""))) | J15: =IF(OR(J13="",F13=""),"",IF(F13<=0,"",IFERROR(J13/F13-1,""))) | K15: =IF(OR(K13="",G13=""),"",IF(G13<=0,"",IFERROR(K13/G13-1,""))) | L15: =IF(OR(L13="",H13=""),"",IF(H13<=0,"",IFERROR(L13/H13-1,""))) | M15: =IF(OR(M13="",I13=""),"",IF(I13<=0,"",IFERROR(M13/I13-1,""))) | N15: =IF(OR(N13="",J13=""),"",IF(J13<=0,"",IFERROR(N13/J13-1,""))) | P15: =IF(OR(P13="",O13=""),"",IF(O13<=0,"",IFERROR(P13/O13-1,""))) | Q15: =IF(OR(Q13="",P13=""),"",IF(P13<=0,"",IFERROR(Q13/P13-1,""))) | R15: =IF(OR(R13="",Q13=""),"",IF(Q13<=0,"",IFERROR(R13/Q13-1,""))) | S15: =IF(OR(S13="",R13=""),"",IF(R13<=0,"",IFERROR(S13/R13-1,""))) | T15: =IF(OR(T13="",S13=""),"",IF(S13<=0,"",IFERROR(T13/S13-1,""))) | U15: =IF(OR(U13="",T13=""),"",IF(T13<=0,"",IFERROR(U13/T13-1,""))) | V15: =IF(OR(V13="",U13=""),"",IF(U13<=0,"",IFERROR(V13/U13-1,""))) | W15: =IF(OR(W13="",V13=""),"",IF(V13<=0,"",IFERROR(W13/V13-1,""))) | ... AC15: =IF(OR(AC13="",AB13=""),"",IF(AB13<=0,"",IFERROR(AC13/AB13-1,"")))
A16: 판매관리비
A17: 전체 판관비 | C17: 221.552 | D17: 212.357 | E17: 260.958 | F17: 209.522 | G17: 213.559 | H17: 226.234 | I17: 281.883 | J17: 221.582 | K17: 242.406 | L17: 253.926 | M17: 308.434 | N17: 269.497 | U17: 698.094 | V17: 843.051 | W17: 896.396 | X17: 972.105
A18: YoY | G18: =IF(OR(G17="",C17=""),"",IF(C17<=0,"",IFERROR(G17/C17-1,""))) | H18: =IF(OR(H17="",D17=""),"",IF(D17<=0,"",IFERROR(H17/D17-1,""))) | I18: =IF(OR(I17="",E17=""),"",IF(E17<=0,"",IFERROR(I17/E17-1,""))) | J18: =IF(OR(J17="",F17=""),"",IF(F17<=0,"",IFERROR(J17/F17-1,""))) | K18: =IF(OR(K17="",G17=""),"",IF(G17<=0,"",IFERROR(K17/G17-1,""))) | L18: =IF(OR(L17="",H17=""),"",IF(H17<=0,"",IFERROR(L17/H17-1,""))) | M18: =IF(OR(M17="",I17=""),"",IF(I17<=0,"",IFERROR(M17/I17-1,""))) | N18: =IF(OR(N17="",J17=""),"",IF(J17<=0,"",IFERROR(N17/J17-1,""))) | P18: =IF(OR(P17="",O17=""),"",IF(O17<=0,"",IFERROR(P17/O17-1,""))) | Q18: =IF(OR(Q17="",P17=""),"",IF(P17<=0,"",IFERROR(Q17/P17-1,""))) | R18: =IF(OR(R17="",Q17=""),"",IF(Q17<=0,"",IFERROR(R17/Q17-1,""))) | S18: =IF(OR(S17="",R17=""),"",IF(R17<=0,"",IFERROR(S17/R17-1,""))) | T18: =IF(OR(T17="",S17=""),"",IF(S17<=0,"",IFERROR(T17/S17-1,""))) | U18: =IF(OR(U17="",T17=""),"",IF(T17<=0,"",IFERROR(U17/T17-1,""))) | V18: =IF(OR(V17="",U17=""),"",IF(U17<=0,"",IFERROR(V17/U17-1,""))) | W18: =IF(OR(W17="",V17=""),"",IF(V17<=0,"",IFERROR(W17/V17-1,""))) | ... AC18: =IF(OR(AC17="",AB17=""),"",IF(AB17<=0,"",IFERROR(AC17/AB17-1,"")))
A19: 영업이익 | B19: MW = 매출 × OPM | C19: 95.72 | D19: 158.657 | E19: 48.256 | F19: 122.573 | G19: 198.7 | H19: 95.68 | I19: -7.773 | J19: 72.611 | K19: 164.244 | L19: 121.098 | M19: 153.043 | N19: 159.96 | U19: 330.07 | V19: 490.776 | W19: 528.186 | X19: 324.762 | Y19: =IF(OR(Y4="",Y20=""),"",IFERROR(Y4*Y20,"")) | Z19: =IF(OR(Z4="",Z20=""),"",IFERROR(Z4*Z20,"")) | AA19: =IF(OR(AA4="",AA20=""),"",IFERROR(AA4*AA20,"")) | AB19: =IF(OR(AB4="",AB20=""),"",IFERROR(AB4*AB20,"")) | AC19: =IF(OR(AC4="",AC20=""),"",IFERROR(AC4*AC20,""))
A20: OPM | B20: MW 입력 | C20: =IF(OR(C19="",C4=""),"",IFERROR(C19/C4,"")) | D20: =IF(OR(D19="",D4=""),"",IFERROR(D19/D4,"")) | E20: =IF(OR(E19="",E4=""),"",IFERROR(E19/E4,"")) | F20: =IF(OR(F19="",F4=""),"",IFERROR(F19/F4,"")) | G20: =IF(OR(G19="",G4=""),"",IFERROR(G19/G4,"")) | H20: =IF(OR(H19="",H4=""),"",IFERROR(H19/H4,"")) | I20: =IF(OR(I19="",I4=""),"",IFERROR(I19/I4,"")) | J20: =IF(OR(J19="",J4=""),"",IFERROR(J19/J4,"")) | ... X20: =IF(OR(X19="",X4=""),"",IFERROR(X19/X4,""))
A21: 증가율 | G21: =IF(OR(G19="",C19=""),"",IFERROR(G19/C19-1,"")) | H21: =IF(OR(H19="",D19=""),"",IFERROR(H19/D19-1,"")) | I21: =IF(OR(I19="",E19=""),"",IFERROR(I19/E19-1,"")) | J21: =IF(OR(J19="",F19=""),"",IFERROR(J19/F19-1,"")) | K21: =IF(OR(K19="",G19=""),"",IFERROR(K19/G19-1,"")) | L21: =IF(OR(L19="",H19=""),"",IFERROR(L19/H19-1,"")) | M21: =IF(OR(M19="",I19=""),"",IFERROR(M19/I19-1,"")) | N21: =IF(OR(N19="",J19=""),"",IFERROR(N19/J19-1,"")) | P21: =IF(OR(P19="",O19=""),"",IFERROR(P19/O19-1,"")) | Q21: =IF(OR(Q19="",P19=""),"",IFERROR(Q19/P19-1,"")) | R21: =IF(OR(R19="",Q19=""),"",IFERROR(R19/Q19-1,"")) | S21: =IF(OR(S19="",R19=""),"",IFERROR(S19/R19-1,"")) | T21: =IF(OR(T19="",S19=""),"",IFERROR(T19/S19-1,"")) | U21: =IF(OR(U19="",T19=""),"",IFERROR(U19/T19-1,"")) | V21: =IF(OR(V19="",U19=""),"",IFERROR(V19/U19-1,"")) | W21: =IF(OR(W19="",V19=""),"",IFERROR(W19/V19-1,"")) | ... AC21: =IF(OR(AC19="",AB19=""),"",IFERROR(AC19/AB19-1,""))
A22: 비용의 성격별 분류 | B22: 참고 데이터
A23: 총 판관비 | O23: =IF(O17="","",O17) | P23: =IF(P17="","",P17) | Q23: =IF(Q17="","",Q17) | R23: =IF(R17="","",R17) | S23: =IF(S17="","",S17) | T23: =IF(T17="","",T17) | U23: =IF(U17="","",U17) | V23: =IF(V17="","",V17) | ... X23: =IF(X17="","",X17)
A24: 급여 | B24: 고정비
A25: % of Sales | O25: =IF(OR(O24="",O4=""),"",IFERROR(O24/O4,"")) | P25: =IF(OR(P24="",P4=""),"",IFERROR(P24/P4,"")) | Q25: =IF(OR(Q24="",Q4=""),"",IFERROR(Q24/Q4,"")) | R25: =IF(OR(R24="",R4=""),"",IFERROR(R24/R4,"")) | S25: =IF(OR(S24="",S4=""),"",IFERROR(S24/S4,"")) | T25: =IF(OR(T24="",T4=""),"",IFERROR(T24/T4,"")) | U25: =IF(OR(U24="",U4=""),"",IFERROR(U24/U4,"")) | V25: =IF(OR(V24="",V4=""),"",IFERROR(V24/V4,"")) | ... X25: =IF(OR(X24="",X4=""),"",IFERROR(X24/X4,""))
A26: 감가상각비 | B26: 고정비
A27: % of Sales | O27: =IF(OR(O26="",O4=""),"",IFERROR(O26/O4,"")) | P27: =IF(OR(P26="",P4=""),"",IFERROR(P26/P4,"")) | Q27: =IF(OR(Q26="",Q4=""),"",IFERROR(Q26/Q4,"")) | R27: =IF(OR(R26="",R4=""),"",IFERROR(R26/R4,"")) | S27: =IF(OR(S26="",S4=""),"",IFERROR(S26/S4,"")) | T27: =IF(OR(T26="",T4=""),"",IFERROR(T26/T4,"")) | U27: =IF(OR(U26="",U4=""),"",IFERROR(U26/U4,"")) | V27: =IF(OR(V26="",V4=""),"",IFERROR(V26/V4,"")) | ... X27: =IF(OR(X26="",X4=""),"",IFERROR(X26/X4,""))
A28: 지급수수료 | B28: 고정비
A29: % of Sales | O29: =IF(OR(O28="",O4=""),"",IFERROR(O28/O4,"")) | P29: =IF(OR(P28="",P4=""),"",IFERROR(P28/P4,"")) | Q29: =IF(OR(Q28="",Q4=""),"",IFERROR(Q28/Q4,"")) | R29: =IF(OR(R28="",R4=""),"",IFERROR(R28/R4,"")) | S29: =IF(OR(S28="",S4=""),"",IFERROR(S28/S4,"")) | T29: =IF(OR(T28="",T4=""),"",IFERROR(T28/T4,"")) | U29: =IF(OR(U28="",U4=""),"",IFERROR(U28/U4,"")) | V29: =IF(OR(V28="",V4=""),"",IFERROR(V28/V4,"")) | ... X29: =IF(OR(X28="",X4=""),"",IFERROR(X28/X4,""))
A30: 연구개발비 | B30: 변동비
A31: % of Sales | O31: =IF(OR(O30="",O4=""),"",IFERROR(O30/O4,"")) | P31: =IF(OR(P30="",P4=""),"",IFERROR(P30/P4,"")) | Q31: =IF(OR(Q30="",Q4=""),"",IFERROR(Q30/Q4,"")) | R31: =IF(OR(R30="",R4=""),"",IFERROR(R30/R4,"")) | S31: =IF(OR(S30="",S4=""),"",IFERROR(S30/S4,"")) | T31: =IF(OR(T30="",T4=""),"",IFERROR(T30/T4,"")) | U31: =IF(OR(U30="",U4=""),"",IFERROR(U30/U4,"")) | V31: =IF(OR(V30="",V4=""),"",IFERROR(V30/V4,"")) | ... X31: =IF(OR(X30="",X4=""),"",IFERROR(X30/X4,""))
A32: 기타비용 | B32: 변동비 | O32: =IF(OR(O23="",O24="",O26="",O28="",O30=""),"",IFERROR(O23-O24-O26-O28-O30,"")) | P32: =IF(OR(P23="",P24="",P26="",P28="",P30=""),"",IFERROR(P23-P24-P26-P28-P30,"")) | Q32: =IF(OR(Q23="",Q24="",Q26="",Q28="",Q30=""),"",IFERROR(Q23-Q24-Q26-Q28-Q30,"")) | R32: =IF(OR(R23="",R24="",R26="",R28="",R30=""),"",IFERROR(R23-R24-R26-R28-R30,"")) | S32: =IF(OR(S23="",S24="",S26="",S28="",S30=""),"",IFERROR(S23-S24-S26-S28-S30,"")) | T32: =IF(OR(T23="",T24="",T26="",T28="",T30=""),"",IFERROR(T23-T24-T26-T28-T30,"")) | U32: =IF(OR(U23="",U24="",U26="",U28="",U30=""),"",IFERROR(U23-U24-U26-U28-U30,"")) | V32: =IF(OR(V23="",V24="",V26="",V28="",V30=""),"",IFERROR(V23-V24-V26-V28-V30,"")) | ... X32: =IF(OR(X23="",X24="",X26="",X28="",X30=""),"",IFERROR(X23-X24-X26-X28-X30,""))
A33: % of Sales | O33: =IF(OR(O32="",O4=""),"",IFERROR(O32/O4,"")) | P33: =IF(OR(P32="",P4=""),"",IFERROR(P32/P4,"")) | Q33: =IF(OR(Q32="",Q4=""),"",IFERROR(Q32/Q4,"")) | R33: =IF(OR(R32="",R4=""),"",IFERROR(R32/R4,"")) | S33: =IF(OR(S32="",S4=""),"",IFERROR(S32/S4,"")) | T33: =IF(OR(T32="",T4=""),"",IFERROR(T32/T4,"")) | U33: =IF(OR(U32="",U4=""),"",IFERROR(U32/U4,"")) | V33: =IF(OR(V32="",V4=""),"",IFERROR(V32/V4,"")) | ... X33: =IF(OR(X32="",X4=""),"",IFERROR(X32/X4,""))
A34: 당기순이익 추정
A35: 특별이익 | F35: 0 | G35: 0.909 | H35: 0 | I35: 0.378 | J35: 0 | K35: 0 | L35: 1.174 | M35: 0 | N35: 0 | U35: 0 | V35: 3.997 | W35: 0.909 | X35: 0.378 | Y35: =IF(OR(Y4="",Y36=""),"",IFERROR(Y4*Y36,"")) | Z35: =IF(OR(Z4="",Z36=""),"",IFERROR(Z4*Z36,"")) | AA35: =IF(OR(AA4="",AA36=""),"",IFERROR(AA4*AA36,"")) | AB35: =IF(OR(AB4="",AB36=""),"",IFERROR(AB4*AB36,"")) | AC35: =IF(OR(AC4="",AC36=""),"",IFERROR(AC4*AC36,""))
A36: % of Sales | B36: MW = 최근 3년 평균 | C36: =IF(OR(C35="",C4=""),"",IFERROR(C35/C4,"")) | D36: =IF(OR(D35="",D4=""),"",IFERROR(D35/D4,"")) | E36: =IF(OR(E35="",E4=""),"",IFERROR(E35/E4,"")) | F36: =IF(OR(F35="",F4=""),"",IFERROR(F35/F4,"")) | G36: =IF(OR(G35="",G4=""),"",IFERROR(G35/G4,"")) | H36: =IF(OR(H35="",H4=""),"",IFERROR(H35/H4,"")) | I36: =IF(OR(I35="",I4=""),"",IFERROR(I35/I4,"")) | J36: =IF(OR(J35="",J4=""),"",IFERROR(J35/J4,"")) | ... X36: =IF(OR(X35="",X4=""),"",IFERROR(X35/X4,"")) | Y36: =IFERROR(AVERAGE(V36,W36,X36),"") | Z36: =Y36 | AA36: =Z36 | AB36: =AA36 | AC36: =AB36
A37: 특별손실 | C37: 1.268 | H37: 0 | I37: 0 | J37: 0 | K37: 16.288 | L37: 22.5 | M37: 1.111 | N37: 4.282 | U37: 2.618 | V37: 1.268 | W37: 12.952 | X37: 16.288 | Y37: =IF(OR(Y4="",Y38=""),"",IFERROR(Y4*Y38,"")) | Z37: =IF(OR(Z4="",Z38=""),"",IFERROR(Z4*Z38,"")) | AA37: =IF(OR(AA4="",AA38=""),"",IFERROR(AA4*AA38,"")) | AB37: =IF(OR(AB4="",AB38=""),"",IFERROR(AB4*AB38,"")) | AC37: =IF(OR(AC4="",AC38=""),"",IFERROR(AC4*AC38,""))
A38: % of Sales | C38: =IF(OR(C37="",C4=""),"",IFERROR(C37/C4,"")) | D38: =IF(OR(D37="",D4=""),"",IFERROR(D37/D4,"")) | E38: =IF(OR(E37="",E4=""),"",IFERROR(E37/E4,"")) | F38: =IF(OR(F37="",F4=""),"",IFERROR(F37/F4,"")) | G38: =IF(OR(G37="",G4=""),"",IFERROR(G37/G4,"")) | H38: =IF(OR(H37="",H4=""),"",IFERROR(H37/H4,"")) | I38: =IF(OR(I37="",I4=""),"",IFERROR(I37/I4,"")) | J38: =IF(OR(J37="",J4=""),"",IFERROR(J37/J4,"")) | ... X38: =IF(OR(X37="",X4=""),"",IFERROR(X37/X4,"")) | Y38: =IFERROR(AVERAGE(V38,W38,X38),"") | Z38: =Y38 | AA38: =Z38 | AB38: =AA38 | AC38: =AB38
A39: 영업외수익 | C39: 5.814 | D39: 2.777 | E39: 7.217 | F39: 3.467 | G39: 14.365 | H39: 12.953 | I39: 7.225 | J39: 4.921 | K39: 25.524 | L39: 5.009 | M39: 8.797 | N39: 11.329 | U39: 18.577 | V39: 18.128 | W39: 27.826 | X39: 50.623 | Y39: =IF(OR(Y4="",Y40=""),"",IFERROR(Y4*Y40,"")) | Z39: =IF(OR(Z4="",Z40=""),"",IFERROR(Z4*Z40,"")) | AA39: =IF(OR(AA4="",AA40=""),"",IFERROR(AA4*AA40,"")) | AB39: =IF(OR(AB4="",AB40=""),"",IFERROR(AB4*AB40,"")) | AC39: =IF(OR(AC4="",AC40=""),"",IFERROR(AC4*AC40,""))
A40: % of Sales | C40: =IF(OR(C39="",C4=""),"",IFERROR(C39/C4,"")) | D40: =IF(OR(D39="",D4=""),"",IFERROR(D39/D4,"")) | E40: =IF(OR(E39="",E4=""),"",IFERROR(E39/E4,"")) | F40: =IF(OR(F39="",F4=""),"",IFERROR(F39/F4,"")) | G40: =IF(OR(G39="",G4=""),"",IFERROR(G39/G4,"")) | H40: =IF(OR(H39="",H4=""),"",IFERROR(H39/H4,"")) | I40: =IF(OR(I39="",I4=""),"",IFERROR(I39/I4,"")) | J40: =IF(OR(J39="",J4=""),"",IFERROR(J39/J4,"")) | ... X40: =IF(OR(X39="",X4=""),"",IFERROR(X39/X4,"")) | Y40: =IFERROR(AVERAGE(V40,W40,X40),"") | Z40: =Y40 | AA40: =Z40 | AB40: =AA40 | AC40: =AB40
A41: 영업외비용 | C41: 1.652 | D41: 1.238 | E41: 1.281 | F41: 1.324 | G41: 1.089 | H41: 1.59 | I41: 2.149 | J41: 1.938 | K41: 6.012 | L41: 3.56 | M41: 3.337 | N41: 3.673 | U41: 11.087 | V41: 25.49 | W41: 4.932 | X41: 11.689 | Y41: =IF(OR(Y4="",Y42=""),"",IFERROR(Y4*Y42,"")) | Z41: =IF(OR(Z4="",Z42=""),"",IFERROR(Z4*Z42,"")) | AA41: =IF(OR(AA4="",AA42=""),"",IFERROR(AA4*AA42,"")) | AB41: =IF(OR(AB4="",AB42=""),"",IFERROR(AB4*AB42,"")) | AC41: =IF(OR(AC4="",AC42=""),"",IFERROR(AC4*AC42,""))
A42: % of Sales | C42: =IF(OR(C41="",C4=""),"",IFERROR(C41/C4,"")) | D42: =IF(OR(D41="",D4=""),"",IFERROR(D41/D4,"")) | E42: =IF(OR(E41="",E4=""),"",IFERROR(E41/E4,"")) | F42: =IF(OR(F41="",F4=""),"",IFERROR(F41/F4,"")) | G42: =IF(OR(G41="",G4=""),"",IFERROR(G41/G4,"")) | H42: =IF(OR(H41="",H4=""),"",IFERROR(H41/H4,"")) | I42: =IF(OR(I41="",I4=""),"",IFERROR(I41/I4,"")) | J42: =IF(OR(J41="",J4=""),"",IFERROR(J41/J4,"")) | ... X42: =IF(OR(X41="",X4=""),"",IFERROR(X41/X4,"")) | Y42: =IFERROR(AVERAGE(V42,W42,X42),"") | Z42: =Y42 | AA42: =Z42 | AB42: =AA42 | AC42: =AB42
A43: 법인세비용차감전순이익(손실) | C43: 102.61 | D43: 160.196 | E43: 54.192 | F43: 124.715 | G43: 199.934 | H43: 107.043 | I43: -2.318 | J43: 75.594 | K43: 167.466 | L43: 101.221 | M43: 157.392 | N43: 163.333 | U43: 334.941 | V43: 486.142 | W43: 539.037 | X43: 347.785 | Y43: =IF(OR(Y19=""),"",IFERROR(Y19+N(Y35)-N(Y37)+N(Y39)-N(Y41),"")) | Z43: =IF(OR(Z19=""),"",IFERROR(Z19+N(Z35)-N(Z37)+N(Z39)-N(Z41),"")) | AA43: =IF(OR(AA19=""),"",IFERROR(AA19+N(AA35)-N(AA37)+N(AA39)-N(AA41),"")) | AB43: =IF(OR(AB19=""),"",IFERROR(AB19+N(AB35)-N(AB37)+N(AB39)-N(AB41),"")) | AC43: =IF(OR(AC19=""),"",IFERROR(AC19+N(AC35)-N(AC37)+N(AC39)-N(AC41),""))
A44: YoY | G44: =IF(OR(G43="",C43=""),"",IF(C43<=0,"",IFERROR(G43/C43-1,""))) | H44: =IF(OR(H43="",D43=""),"",IF(D43<=0,"",IFERROR(H43/D43-1,""))) | I44: =IF(OR(I43="",E43=""),"",IF(E43<=0,"",IFERROR(I43/E43-1,""))) | J44: =IF(OR(J43="",F43=""),"",IF(F43<=0,"",IFERROR(J43/F43-1,""))) | K44: =IF(OR(K43="",G43=""),"",IF(G43<=0,"",IFERROR(K43/G43-1,""))) | L44: =IF(OR(L43="",H43=""),"",IF(H43<=0,"",IFERROR(L43/H43-1,""))) | M44: =IF(OR(M43="",I43=""),"",IF(I43<=0,"",IFERROR(M43/I43-1,""))) | N44: =IF(OR(N43="",J43=""),"",IF(J43<=0,"",IFERROR(N43/J43-1,""))) | P44: =IF(OR(P43="",O43=""),"",IF(O43<=0,"",IFERROR(P43/O43-1,""))) | Q44: =IF(OR(Q43="",P43=""),"",IF(P43<=0,"",IFERROR(Q43/P43-1,""))) | R44: =IF(OR(R43="",Q43=""),"",IF(Q43<=0,"",IFERROR(R43/Q43-1,""))) | S44: =IF(OR(S43="",R43=""),"",IF(R43<=0,"",IFERROR(S43/R43-1,""))) | T44: =IF(OR(T43="",S43=""),"",IF(S43<=0,"",IFERROR(T43/S43-1,""))) | U44: =IF(OR(U43="",T43=""),"",IF(T43<=0,"",IFERROR(U43/T43-1,""))) | V44: =IF(OR(V43="",U43=""),"",IF(U43<=0,"",IFERROR(V43/U43-1,""))) | W44: =IF(OR(W43="",V43=""),"",IF(V43<=0,"",IFERROR(W43/V43-1,""))) | ... AC44: =IF(OR(AC43="",AB43=""),"",IF(AB43<=0,"",IFERROR(AC43/AB43-1,"")))
A45: 법인세비용(수익) | C45: 19.085 | D45: 51.051 | E45: 18.025 | F45: 39.604 | G45: 35.68 | H45: 34.178 | I45: 0.843 | J45: 25.216 | K45: 53.489 | L45: 31.433 | M45: 51.612 | N45: 51.353 | U45: 122.379 | V45: 143.907 | W45: 144.36 | X45: 113.726 | Y45: =IF(OR(Y43="",Y46=""),"",IFERROR(MAX(Y43,0)*Y46,"")) | Z45: =IF(OR(Z43="",Z46=""),"",IFERROR(MAX(Z43,0)*Z46,"")) | AA45: =IF(OR(AA43="",AA46=""),"",IFERROR(MAX(AA43,0)*AA46,"")) | AB45: =IF(OR(AB43="",AB46=""),"",IFERROR(MAX(AB43,0)*AB46,"")) | AC45: =IF(OR(AC43="",AC46=""),"",IFERROR(MAX(AC43,0)*AC46,""))
A46: 법인세율 | B46: MW 기본 30% | C46: =IF(OR(C45="",C43=""),"",IFERROR(C45/C43,"")) | D46: =IF(OR(D45="",D43=""),"",IFERROR(D45/D43,"")) | E46: =IF(OR(E45="",E43=""),"",IFERROR(E45/E43,"")) | F46: =IF(OR(F45="",F43=""),"",IFERROR(F45/F43,"")) | G46: =IF(OR(G45="",G43=""),"",IFERROR(G45/G43,"")) | H46: =IF(OR(H45="",H43=""),"",IFERROR(H45/H43,"")) | I46: =IF(OR(I45="",I43=""),"",IFERROR(I45/I43,"")) | J46: =IF(OR(J45="",J43=""),"",IFERROR(J45/J43,"")) | ... X46: =IF(OR(X45="",X43=""),"",IFERROR(X45/X43,"")) | Y46: 0.3 | Z46: 0.3 | AA46: 0.3 | AB46: 0.3 | AC46: 0.3
A47: 당기순이익(손실) | C47: 83.526 | D47: 109.145 | E47: 36.167 | F47: 85.111 | G47: 164.253 | H47: 72.864 | I47: -3.161 | J47: 50.379 | K47: 113.977 | L47: 69.787 | M47: 105.781 | N47: 111.98 | U47: 212.562 | V47: 342.235 | W47: 394.676 | X47: 234.059 | Y47: =IF(OR(Y43=""),"",IFERROR(Y43-Y45,"")) | Z47: =IF(OR(Z43=""),"",IFERROR(Z43-Z45,"")) | AA47: =IF(OR(AA43=""),"",IFERROR(AA43-AA45,"")) | AB47: =IF(OR(AB43=""),"",IFERROR(AB43-AB45,"")) | AC47: =IF(OR(AC43=""),"",IFERROR(AC43-AC45,""))
A48: YoY | G48: =IF(OR(G47="",C47=""),"",IF(C47<=0,"",IFERROR(G47/C47-1,""))) | H48: =IF(OR(H47="",D47=""),"",IF(D47<=0,"",IFERROR(H47/D47-1,""))) | I48: =IF(OR(I47="",E47=""),"",IF(E47<=0,"",IFERROR(I47/E47-1,""))) | J48: =IF(OR(J47="",F47=""),"",IF(F47<=0,"",IFERROR(J47/F47-1,""))) | K48: =IF(OR(K47="",G47=""),"",IF(G47<=0,"",IFERROR(K47/G47-1,""))) | L48: =IF(OR(L47="",H47=""),"",IF(H47<=0,"",IFERROR(L47/H47-1,""))) | M48: =IF(OR(M47="",I47=""),"",IF(I47<=0,"",IFERROR(M47/I47-1,""))) | N48: =IF(OR(N47="",J47=""),"",IF(J47<=0,"",IFERROR(N47/J47-1,""))) | P48: =IF(OR(P47="",O47=""),"",IF(O47<=0,"",IFERROR(P47/O47-1,""))) | Q48: =IF(OR(Q47="",P47=""),"",IF(P47<=0,"",IFERROR(Q47/P47-1,""))) | R48: =IF(OR(R47="",Q47=""),"",IF(Q47<=0,"",IFERROR(R47/Q47-1,""))) | S48: =IF(OR(S47="",R47=""),"",IF(R47<=0,"",IFERROR(S47/R47-1,""))) | T48: =IF(OR(T47="",S47=""),"",IF(S47<=0,"",IFERROR(T47/S47-1,""))) | U48: =IF(OR(U47="",T47=""),"",IF(T47<=0,"",IFERROR(U47/T47-1,""))) | V48: =IF(OR(V47="",U47=""),"",IF(U47<=0,"",IFERROR(V47/U47-1,""))) | W48: =IF(OR(W47="",V47=""),"",IF(V47<=0,"",IFERROR(W47/V47-1,""))) | ... AC48: =IF(OR(AC47="",AB47=""),"",IF(AB47<=0,"",IFERROR(AC47/AB47-1,"")))
A49: 지배주주 순이익 | C49: 83.526 | D49: 109.145 | E49: 36.167 | F49: 85.111 | G49: 164.253 | H49: 72.864 | I49: -3.161 | J49: 50.379 | K49: 113.977 | L49: 69.787 | M49: 105.781 | N49: 111.98 | U49: 212.562 | V49: 342.235 | W49: 394.676 | X49: 234.059 | Y49: =IF(OR(Y47="",Y50=""),"",IFERROR(Y47*Y50,"")) | Z49: =IF(OR(Z47="",Z50=""),"",IFERROR(Z47*Z50,"")) | AA49: =IF(OR(AA47="",AA50=""),"",IFERROR(AA47*AA50,"")) | AB49: =IF(OR(AB47="",AB50=""),"",IFERROR(AB47*AB50,"")) | AC49: =IF(OR(AC47="",AC50=""),"",IFERROR(AC47*AC50,""))
A50: 지배주주 순이익률 | B50: MW 기본 100% | C50: =IF(OR(C49="",C47=""),"",IFERROR(C49/C47,"")) | D50: =IF(OR(D49="",D47=""),"",IFERROR(D49/D47,"")) | E50: =IF(OR(E49="",E47=""),"",IFERROR(E49/E47,"")) | F50: =IF(OR(F49="",F47=""),"",IFERROR(F49/F47,"")) | G50: =IF(OR(G49="",G47=""),"",IFERROR(G49/G47,"")) | H50: =IF(OR(H49="",H47=""),"",IFERROR(H49/H47,"")) | I50: =IF(OR(I49="",I47=""),"",IFERROR(I49/I47,"")) | J50: =IF(OR(J49="",J47=""),"",IFERROR(J49/J47,"")) | ... X50: =IF(OR(X49="",X47=""),"",IFERROR(X49/X47,"")) | Y50: 1 | Z50: 1 | AA50: 1 | AB50: 1 | AC50: 1
A51: 지배주주 순이익 YoY | G51: =IF(OR(G49="",C49=""),"",IF(C49<=0,"",IFERROR(G49/C49-1,""))) | H51: =IF(OR(H49="",D49=""),"",IF(D49<=0,"",IFERROR(H49/D49-1,""))) | I51: =IF(OR(I49="",E49=""),"",IF(E49<=0,"",IFERROR(I49/E49-1,""))) | J51: =IF(OR(J49="",F49=""),"",IF(F49<=0,"",IFERROR(J49/F49-1,""))) | K51: =IF(OR(K49="",G49=""),"",IF(G49<=0,"",IFERROR(K49/G49-1,""))) | L51: =IF(OR(L49="",H49=""),"",IF(H49<=0,"",IFERROR(L49/H49-1,""))) | M51: =IF(OR(M49="",I49=""),"",IF(I49<=0,"",IFERROR(M49/I49-1,""))) | N51: =IF(OR(N49="",J49=""),"",IF(J49<=0,"",IFERROR(N49/J49-1,""))) | P51: =IF(OR(P49="",O49=""),"",IF(O49<=0,"",IFERROR(P49/O49-1,""))) | Q51: =IF(OR(Q49="",P49=""),"",IF(P49<=0,"",IFERROR(Q49/P49-1,""))) | R51: =IF(OR(R49="",Q49=""),"",IF(Q49<=0,"",IFERROR(R49/Q49-1,""))) | S51: =IF(OR(S49="",R49=""),"",IF(R49<=0,"",IFERROR(S49/R49-1,""))) | T51: =IF(OR(T49="",S49=""),"",IF(S49<=0,"",IFERROR(T49/S49-1,""))) | U51: =IF(OR(U49="",T49=""),"",IF(T49<=0,"",IFERROR(U49/T49-1,""))) | V51: =IF(OR(V49="",U49=""),"",IF(U49<=0,"",IFERROR(V49/U49-1,""))) | W51: =IF(OR(W49="",V49=""),"",IF(V49<=0,"",IFERROR(W49/V49-1,""))) | ... AC51: =IF(OR(AC49="",AB49=""),"",IF(AB49<=0,"",IFERROR(AC49/AB49-1,"")))
A52: 목표주가 산출
A53: 현재 주가 ()
A54: 발행주식수 (보통주)
A55: 시가총액 (백만엔) | B55: =IF(OR(B53="",B54=""),"",B53*B54/1000000.0)
A56: OPM | O56: =IF(O20="","",O20) | P56: =IF(P20="","",P20) | Q56: =IF(Q20="","",Q20) | R56: =IF(R20="","",R20) | S56: =IF(S20="","",S20) | T56: =IF(T20="","",T20) | U56: =IF(U20="","",U20) | V56: =IF(V20="","",V20) | ... AC56: =IF(AC20="","",AC20)
A57: 지배주주 순이익 증가율 | P57: =IF(OR(P49="",O49=""),"",IFERROR(P49/O49-1,"")) | Q57: =IF(OR(Q49="",P49=""),"",IFERROR(Q49/P49-1,"")) | R57: =IF(OR(R49="",Q49=""),"",IFERROR(R49/Q49-1,"")) | S57: =IF(OR(S49="",R49=""),"",IFERROR(S49/R49-1,"")) | T57: =IF(OR(T49="",S49=""),"",IFERROR(T49/S49-1,"")) | U57: =IF(OR(U49="",T49=""),"",IFERROR(U49/T49-1,"")) | V57: =IF(OR(V49="",U49=""),"",IFERROR(V49/U49-1,"")) | W57: =IF(OR(W49="",V49=""),"",IFERROR(W49/V49-1,"")) | ... AC57: =IF(OR(AC49="",AB49=""),"",IFERROR(AC49/AB49-1,""))
A58: P/E (현재 주가) | B58: 시총 ÷ 지배순이익 | X58: =IF(OR($B$55="",X49=""),"",IFERROR($B$55/X49,"")) | Y58: =IF(OR($B$55="",Y49=""),"",IFERROR($B$55/Y49,"")) | Z58: =IF(OR($B$55="",Z49=""),"",IFERROR($B$55/Z49,"")) | AA58: =IF(OR($B$55="",AA49=""),"",IFERROR($B$55/AA49,"")) | AB58: =IF(OR($B$55="",AB49=""),"",IFERROR($B$55/AB49,"")) | AC58: =IF(OR($B$55="",AC49=""),"",IFERROR($B$55/AC49,""))
A59: Target P/E | B59: 직접 입력
A60: EPS | B60: 지배순이익 ÷ 주식수 | O60: =IF(OR(O49="",$B$54=""),"",IFERROR(O49*1000000.0/$B$54,"")) | P60: =IF(OR(P49="",$B$54=""),"",IFERROR(P49*1000000.0/$B$54,"")) | Q60: =IF(OR(Q49="",$B$54=""),"",IFERROR(Q49*1000000.0/$B$54,"")) | R60: =IF(OR(R49="",$B$54=""),"",IFERROR(R49*1000000.0/$B$54,"")) | S60: =IF(OR(S49="",$B$54=""),"",IFERROR(S49*1000000.0/$B$54,"")) | T60: =IF(OR(T49="",$B$54=""),"",IFERROR(T49*1000000.0/$B$54,"")) | U60: =IF(OR(U49="",$B$54=""),"",IFERROR(U49*1000000.0/$B$54,"")) | V60: =IF(OR(V49="",$B$54=""),"",IFERROR(V49*1000000.0/$B$54,"")) | ... AC60: =IF(OR(AC49="",$B$54=""),"",IFERROR(AC49*1000000.0/$B$54,""))
A61: 목표주가 | Y61: =IF(OR(Y60="",Y59=""),"",IFERROR(Y60*Y59,"")) | Z61: =IF(OR(Z60="",Z59=""),"",IFERROR(Z60*Z59,"")) | AA61: =IF(OR(AA60="",AA59=""),"",IFERROR(AA60*AA59,"")) | AB61: =IF(OR(AB60="",AB59=""),"",IFERROR(AB60*AB59,"")) | AC61: =IF(OR(AC60="",AC59=""),"",IFERROR(AC60*AC59,""))
A62: 상승여력 | Y62: =IF(OR(Y61="",$B$53=""),"",IFERROR(Y61/$B$53-1,"")) | Z62: =IF(OR(Z61="",$B$53=""),"",IFERROR(Z61/$B$53-1,"")) | AA62: =IF(OR(AA61="",$B$53=""),"",IFERROR(AA61/$B$53-1,"")) | AB62: =IF(OR(AB61="",$B$53=""),"",IFERROR(AB61/$B$53-1,"")) | AC62: =IF(OR(AC61="",$B$53=""),"",IFERROR(AC61/$B$53-1,""))
A63: 자산가치 산출 | B63: 최신 분기 BS
A64: 현금및현금성자산 | X64: ='재무상태표'!G6 | Y64: ='재무상태표'!G6 | Z64: ='재무상태표'!G6 | AA64: ='재무상태표'!G6 | AB64: ='재무상태표'!G6 | AC64: ='재무상태표'!G6
A65: 단기금융상품 | X65: ='재무상태표'!G7 | Y65: ='재무상태표'!G7 | Z65: ='재무상태표'!G7 | AA65: ='재무상태표'!G7 | AB65: ='재무상태표'!G7 | AC65: ='재무상태표'!G7
A66: 투자부동산 | X66: ='재무상태표'!G14 | Y66: ='재무상태표'!G14 | Z66: ='재무상태표'!G14 | AA66: ='재무상태표'!G14 | AB66: ='재무상태표'!G14 | AC66: ='재무상태표'!G14
A67: 지배자본 | X67: ='재무상태표'!G31 | Y67: ='재무상태표'!G31 | Z67: ='재무상태표'!G31 | AA67: ='재무상태표'!G31 | AB67: ='재무상태표'!G31 | AC67: ='재무상태표'!G31
A68: 부채 | X68: ='재무상태표'!G27 | Y68: ='재무상태표'!G27 | Z68: ='재무상태표'!G27 | AA68: ='재무상태표'!G27 | AB68: ='재무상태표'!G27 | AC68: ='재무상태표'!G27
A69: 부채비율 | X69: =IF(OR(X68="",X67=""),"",IFERROR(X68/X67,"")) | Y69: =IF(OR(Y68="",Y67=""),"",IFERROR(Y68/Y67,"")) | Z69: =IF(OR(Z68="",Z67=""),"",IFERROR(Z68/Z67,"")) | AA69: =IF(OR(AA68="",AA67=""),"",IFERROR(AA68/AA67,"")) | AB69: =IF(OR(AB68="",AB67=""),"",IFERROR(AB68/AB67,"")) | AC69: =IF(OR(AC68="",AC67=""),"",IFERROR(AC68/AC67,""))
A70: 자산가치 | B70: 현금+단기금융+투자부동산 | X70: =SUM(X64,X65,X66) | Y70: =SUM(Y64,Y65,Y66) | Z70: =SUM(Z64,Z65,Z66) | AA70: =SUM(AA64,AA65,AA66) | AB70: =SUM(AB64,AB65,AB66) | AC70: =SUM(AC64,AC65,AC66)
A71: 기업가치 산출
A72: 목표 시가총액 (P/E) | B72: 지배순이익 × Target P/E | Y72: =IF(OR(Y49="",Y59=""),"",IFERROR(Y49*Y59,"")) | Z72: =IF(OR(Z49="",Z59=""),"",IFERROR(Z49*Z59,"")) | AA72: =IF(OR(AA49="",AA59=""),"",IFERROR(AA49*AA59,"")) | AB72: =IF(OR(AB49="",AB59=""),"",IFERROR(AB49*AB59,"")) | AC72: =IF(OR(AC49="",AC59=""),"",IFERROR(AC49*AC59,""))
A73: 기업가치 | B73: 목표시총 + 자산가치 | Y73: =IF(OR(Y72=""),"",IFERROR(Y72+Y70,"")) | Z73: =IF(OR(Z72=""),"",IFERROR(Z72+Z70,"")) | AA73: =IF(OR(AA72=""),"",IFERROR(AA72+AA70,"")) | AB73: =IF(OR(AB72=""),"",IFERROR(AB72+AB70,"")) | AC73: =IF(OR(AC72=""),"",IFERROR(AC72+AC70,""))
A74: 현재 시가총액 | Y74: =$B$55 | Z74: =$B$55 | AA74: =$B$55 | AB74: =$B$55 | AC74: =$B$55
A75: 상승여력 | Y75: =IF(OR(Y73="",Y74=""),"",IFERROR(Y73/Y74-1,"")) | Z75: =IF(OR(Z73="",Z74=""),"",IFERROR(Z73/Z74-1,"")) | AA75: =IF(OR(AA73="",AA74=""),"",IFERROR(AA73/AA74-1,"")) | AB75: =IF(OR(AB73="",AB74=""),"",IFERROR(AB73/AB74-1,"")) | AC75: =IF(OR(AC73="",AC74=""),"",IFERROR(AC73/AC74-1,""))
A77: 출처
A78: 결산단신 XBRL(TDnet·JPX 보관소) — 쓴 문서는 '출처' 시트
A79: 분기 = 누계에서 앞 분기를 뺀 3개월 값
A80: 주가: 야후 파이낸스 일봉
A82: 손익계산서 · 전 항목 | B82: 분기 = 3개월 단독
A83: 항목 | B83: 참고 | C83: 2023.4Q | D83: 2024.1Q | E83: 2024.2Q | F83: 2024.3Q | G83: 2024.4Q | H83: 2025.1Q | I83: 2025.2Q | J83: 2025.3Q | K83: 2025.4Q | L83: 2026.1Q | M83: 2026.2Q | N83: 2026.3Q | O83: 2016 | P83: 2017 | Q83: 2018 | R83: 2019 | S83: 2020 | T83: 2021 | U83: 2022 | V83: 2023 | W83: 2024 | X83: 2025 | Y83: 2026(MW) | Z83: 2027(MW) | AA83: 2028(MW) | AB83: 2029(MW) | AC83: 2030(MW)
A84: 매출액 | C84: 1426.668 | D84: 1584.021 | E84: 1511.883 | F84: 1648.352 | G84: 1717.573 | H84: 1676.977 | I84: 1617.122 | J84: 1690.535 | K84: 1731.555 | L84: 1718.008 | M84: 1797.601 | N84: 1859.032 | U84: 1284.041 | V84: 1426.668 | W84: 1717.573 | X84: 1731.555
A85: YoY | B85: 전년 같은 분기·전년 대비 | G85: =IF(OR(G84="",C84=""),"",IF(C84<=0,"",IFERROR(G84/C84-1,""))) | H85: =IF(OR(H84="",D84=""),"",IF(D84<=0,"",IFERROR(H84/D84-1,""))) | I85: =IF(OR(I84="",E84=""),"",IF(E84<=0,"",IFERROR(I84/E84-1,""))) | J85: =IF(OR(J84="",F84=""),"",IF(F84<=0,"",IFERROR(J84/F84-1,""))) | K85: =IF(OR(K84="",G84=""),"",IF(G84<=0,"",IFERROR(K84/G84-1,""))) | L85: =IF(OR(L84="",H84=""),"",IF(H84<=0,"",IFERROR(L84/H84-1,""))) | M85: =IF(OR(M84="",I84=""),"",IF(I84<=0,"",IFERROR(M84/I84-1,""))) | N85: =IF(OR(N84="",J84=""),"",IF(J84<=0,"",IFERROR(N84/J84-1,""))) | U85: =IF(OR(U84="",T84=""),"",IF(T84<=0,"",IFERROR(U84/T84-1,""))) | V85: =IF(OR(V84="",U84=""),"",IF(U84<=0,"",IFERROR(V84/U84-1,""))) | W85: =IF(OR(W84="",V84=""),"",IF(V84<=0,"",IFERROR(W84/V84-1,""))) | X85: =IF(OR(X84="",W84=""),"",IF(W84<=0,"",IFERROR(X84/W84-1,"")))
A86: 매출원가 | C86: 1109.397 | D86: 1213.005 | E86: 1202.67 | F86: 1316.258 | G86: 1305.314 | H86: 1355.062 | I86: 1343.012 | J86: 1396.342 | K86: 1324.905 | L86: 1342.983 | M86: 1336.124 | N86: 1429.576 | U86: 965.249 | V86: 1109.397 | W86: 1305.314 | X86: 1324.905
A87: YoY | B87: 전년 같은 분기·전년 대비 | G87: =IF(OR(G86="",C86=""),"",IF(G86*C86<=0,"",IFERROR(G86/C86-1,""))) | H87: =IF(OR(H86="",D86=""),"",IF(H86*D86<=0,"",IFERROR(H86/D86-1,""))) | I87: =IF(OR(I86="",E86=""),"",IF(I86*E86<=0,"",IFERROR(I86/E86-1,""))) | J87: =IF(OR(J86="",F86=""),"",IF(J86*F86<=0,"",IFERROR(J86/F86-1,""))) | K87: =IF(OR(K86="",G86=""),"",IF(K86*G86<=0,"",IFERROR(K86/G86-1,""))) | L87: =IF(OR(L86="",H86=""),"",IF(L86*H86<=0,"",IFERROR(L86/H86-1,""))) | M87: =IF(OR(M86="",I86=""),"",IF(M86*I86<=0,"",IFERROR(M86/I86-1,""))) | N87: =IF(OR(N86="",J86=""),"",IF(N86*J86<=0,"",IFERROR(N86/J86-1,""))) | U87: =IF(OR(U86="",T86=""),"",IF(U86*T86<=0,"",IFERROR(U86/T86-1,""))) | V87: =IF(OR(V86="",U86=""),"",IF(V86*U86<=0,"",IFERROR(V86/U86-1,""))) | W87: =IF(OR(W86="",V86=""),"",IF(W86*V86<=0,"",IFERROR(W86/V86-1,""))) | X87: =IF(OR(X86="",W86=""),"",IF(X86*W86<=0,"",IFERROR(X86/W86-1,"")))
A88: 매출총이익 | C88: 317.271 | D88: 371.015 | E88: 309.214 | F88: 332.094 | G88: 412.259 | H88: 321.914 | I88: 274.11 | J88: 294.193 | K88: 406.65 | L88: 375.024 | M88: 461.478 | N88: 429.456 | U88: 318.793 | V88: 317.271 | W88: 412.259 | X88: 406.65
A89: YoY | B89: 전년 같은 분기·전년 대비 | G89: =IF(OR(G88="",C88=""),"",IF(C88<=0,"",IFERROR(G88/C88-1,""))) | H89: =IF(OR(H88="",D88=""),"",IF(D88<=0,"",IFERROR(H88/D88-1,""))) | I89: =IF(OR(I88="",E88=""),"",IF(E88<=0,"",IFERROR(I88/E88-1,""))) | J89: =IF(OR(J88="",F88=""),"",IF(F88<=0,"",IFERROR(J88/F88-1,""))) | K89: =IF(OR(K88="",G88=""),"",IF(G88<=0,"",IFERROR(K88/G88-1,""))) | L89: =IF(OR(L88="",H88=""),"",IF(H88<=0,"",IFERROR(L88/H88-1,""))) | M89: =IF(OR(M88="",I88=""),"",IF(I88<=0,"",IFERROR(M88/I88-1,""))) | N89: =IF(OR(N88="",J88=""),"",IF(J88<=0,"",IFERROR(N88/J88-1,""))) | U89: =IF(OR(U88="",T88=""),"",IF(T88<=0,"",IFERROR(U88/T88-1,""))) | V89: =IF(OR(V88="",U88=""),"",IF(U88<=0,"",IFERROR(V88/U88-1,""))) | W89: =IF(OR(W88="",V88=""),"",IF(V88<=0,"",IFERROR(W88/V88-1,""))) | X89: =IF(OR(X88="",W88=""),"",IF(W88<=0,"",IFERROR(X88/W88-1,"")))
A90: 판매비와 관리비 | C90: 221.552 | D90: 212.357 | E90: 260.958 | F90: 209.522 | G90: 213.559 | H90: 226.234 | I90: 281.883 | J90: 221.582 | K90: 242.406 | L90: 253.926 | M90: 308.434 | N90: 269.497 | U90: 182.958 | V90: 221.552 | W90: 213.559 | X90: 242.406
A91: YoY | B91: 전년 같은 분기·전년 대비 | G91: =IF(OR(G90="",C90=""),"",IF(G90*C90<=0,"",IFERROR(G90/C90-1,""))) | H91: =IF(OR(H90="",D90=""),"",IF(H90*D90<=0,"",IFERROR(H90/D90-1,""))) | I91: =IF(OR(I90="",E90=""),"",IF(I90*E90<=0,"",IFERROR(I90/E90-1,""))) | J91: =IF(OR(J90="",F90=""),"",IF(J90*F90<=0,"",IFERROR(J90/F90-1,""))) | K91: =IF(OR(K90="",G90=""),"",IF(K90*G90<=0,"",IFERROR(K90/G90-1,""))) | L91: =IF(OR(L90="",H90=""),"",IF(L90*H90<=0,"",IFERROR(L90/H90-1,""))) | M91: =IF(OR(M90="",I90=""),"",IF(M90*I90<=0,"",IFERROR(M90/I90-1,""))) | N91: =IF(OR(N90="",J90=""),"",IF(N90*J90<=0,"",IFERROR(N90/J90-1,""))) | U91: =IF(OR(U90="",T90=""),"",IF(U90*T90<=0,"",IFERROR(U90/T90-1,""))) | V91: =IF(OR(V90="",U90=""),"",IF(V90*U90<=0,"",IFERROR(V90/U90-1,""))) | W91: =IF(OR(W90="",V90=""),"",IF(W90*V90<=0,"",IFERROR(W90/V90-1,""))) | X91: =IF(OR(X90="",W90=""),"",IF(X90*W90<=0,"",IFERROR(X90/W90-1,"")))
A92: 영업이익 | C92: 95.72 | D92: 158.657 | E92: 48.256 | F92: 122.573 | G92: 198.7 | H92: 95.68 | I92: -7.773 | J92: 72.611 | K92: 164.244 | L92: 121.098 | M92: 153.043 | N92: 159.96 | U92: 135.835 | V92: 95.72 | W92: 198.7 | X92: 164.244
A93: OPM | B93: 영업이익 ÷ 매출 | C93: =IF(OR(C92="",C84=""),"",IF(C84<=0,"",IFERROR(C92/C84,""))) | D93: =IF(OR(D92="",D84=""),"",IF(D84<=0,"",IFERROR(D92/D84,""))) | E93: =IF(OR(E92="",E84=""),"",IF(E84<=0,"",IFERROR(E92/E84,""))) | F93: =IF(OR(F92="",F84=""),"",IF(F84<=0,"",IFERROR(F92/F84,""))) | G93: =IF(OR(G92="",G84=""),"",IF(G84<=0,"",IFERROR(G92/G84,""))) | H93: =IF(OR(H92="",H84=""),"",IF(H84<=0,"",IFERROR(H92/H84,""))) | I93: =IF(OR(I92="",I84=""),"",IF(I84<=0,"",IFERROR(I92/I84,""))) | J93: =IF(OR(J92="",J84=""),"",IF(J84<=0,"",IFERROR(J92/J84,""))) | ... N93: =IF(OR(N92="",N84=""),"",IF(N84<=0,"",IFERROR(N92/N84,""))) | U93: =IF(OR(U92="",U84=""),"",IF(U84<=0,"",IFERROR(U92/U84,""))) | V93: =IF(OR(V92="",V84=""),"",IF(V84<=0,"",IFERROR(V92/V84,""))) | W93: =IF(OR(W92="",W84=""),"",IF(W84<=0,"",IFERROR(W92/W84,""))) | X93: =IF(OR(X92="",X84=""),"",IF(X84<=0,"",IFERROR(X92/X84,"")))
A94: YoY | B94: 전년 같은 분기·전년 대비 | G94: =IF(OR(G92="",C92=""),"",IF(C92<=0,"",IFERROR(G92/C92-1,""))) | H94: =IF(OR(H92="",D92=""),"",IF(D92<=0,"",IFERROR(H92/D92-1,""))) | I94: =IF(OR(I92="",E92=""),"",IF(E92<=0,"",IFERROR(I92/E92-1,""))) | J94: =IF(OR(J92="",F92=""),"",IF(F92<=0,"",IFERROR(J92/F92-1,""))) | K94: =IF(OR(K92="",G92=""),"",IF(G92<=0,"",IFERROR(K92/G92-1,""))) | L94: =IF(OR(L92="",H92=""),"",IF(H92<=0,"",IFERROR(L92/H92-1,""))) | M94: =IF(OR(M92="",I92=""),"",IF(I92<=0,"",IFERROR(M92/I92-1,""))) | N94: =IF(OR(N92="",J92=""),"",IF(J92<=0,"",IFERROR(N92/J92-1,""))) | U94: =IF(OR(U92="",T92=""),"",IF(T92<=0,"",IFERROR(U92/T92-1,""))) | V94: =IF(OR(V92="",U92=""),"",IF(U92<=0,"",IFERROR(V92/U92-1,""))) | W94: =IF(OR(W92="",V92=""),"",IF(V92<=0,"",IFERROR(W92/V92-1,""))) | X94: =IF(OR(X92="",W92=""),"",IF(W92<=0,"",IFERROR(X92/W92-1,"")))
A95: 배당금수익 | C95: 1.625 | F95: 0 | G95: 3.282 | J95: 0 | K95: 3.678 | N95: 0 | U95: 1.42 | V95: 1.625 | W95: 3.282 | X95: 3.678
A96: 임대료 수익 | C96: 2.145 | D96: 1.967 | E96: 2.081 | F96: 2.161 | G96: 1.918 | H96: 2.133 | I96: 2.438 | J96: 3.072 | K96: 3.867 | L96: 3.962 | M96: 3.985 | N96: 4.315 | U96: 2.33 | V96: 2.145 | W96: 1.918 | X96: 3.867
A97: 보조금 수입 | D97: 0 | E97: 0.733 | F97: 0 | G97: 7.926 | H97: 7.926 | I97: 0 | J97: 0 | K97: 17.264 | L97: 0 | M97: 0 | N97: 5.022 | W97: 7.926 | X97: 17.264
A98: 기타 | C98: -1.162 | D98: 0.809 | E98: 0.66 | F98: 1.306 | G98: -0.361 | H98: 2.894 | I98: 1.298 | J98: 1.849 | K98: -1.796 | L98: 1.046 | M98: 0.747 | N98: 1.992 | U98: -0.668 | V98: -1.162 | W98: -0.361 | X98: -1.796
A99: 영업외수익 합계 | C99: 5.814 | D99: 2.777 | E99: 7.217 | F99: 3.467 | G99: 14.365 | H99: 12.953 | I99: 7.225 | J99: 4.921 | K99: 25.524 | L99: 5.009 | M99: 8.797 | N99: 11.329 | U99: 5.301 | V99: 5.814 | W99: 14.365 | X99: 25.524
A100: YoY | B100: 전년 같은 분기·전년 대비 | G100: =IF(OR(G99="",C99=""),"",IF(G99*C99<=0,"",IFERROR(G99/C99-1,""))) | H100: =IF(OR(H99="",D99=""),"",IF(H99*D99<=0,"",IFERROR(H99/D99-1,""))) | I100: =IF(OR(I99="",E99=""),"",IF(I99*E99<=0,"",IFERROR(I99/E99-1,""))) | J100: =IF(OR(J99="",F99=""),"",IF(J99*F99<=0,"",IFERROR(J99/F99-1,""))) | K100: =IF(OR(K99="",G99=""),"",IF(K99*G99<=0,"",IFERROR(K99/G99-1,""))) | L100: =IF(OR(L99="",H99=""),"",IF(L99*H99<=0,"",IFERROR(L99/H99-1,""))) | M100: =IF(OR(M99="",I99=""),"",IF(M99*I99<=0,"",IFERROR(M99/I99-1,""))) | N100: =IF(OR(N99="",J99=""),"",IF(N99*J99<=0,"",IFERROR(N99/J99-1,""))) | U100: =IF(OR(U99="",T99=""),"",IF(U99*T99<=0,"",IFERROR(U99/T99-1,""))) | V100: =IF(OR(V99="",U99=""),"",IF(V99*U99<=0,"",IFERROR(V99/U99-1,""))) | W100: =IF(OR(W99="",V99=""),"",IF(W99*V99<=0,"",IFERROR(W99/V99-1,""))) | X100: =IF(OR(X99="",W99=""),"",IF(X99*W99<=0,"",IFERROR(X99/W99-1,"")))
A101: 이자비용 | C101: 1.526 | D101: 1.115 | E101: 1.247 | F101: 1.135 | G101: 1.086 | H101: 1.435 | I101: 2.13 | J101: 1.938 | K101: 1.696 | L101: 2.347 | M101: 3.066 | N101: 3.111 | U101: 1.766 | V101: 1.526 | W101: 1.086 | X101: 1.696
A102: 상장 관련 비용 | C102: 0 | D102: 0 | E102: 0 | F102: 0 | G102: 0 | U102: 3 | V102: 0 | W102: 0
...

Sheet 재무상태표
A1: 5257 재무상태표
A2: 재무비율은 기말 잔액 기준 · 분기 손익은 최근 4분기 합산(TTM) | B2: (단위: 백만엔)
A3: 항목 | B3: 참고 | C3: 2025.3Q | D3: 2025.4Q | E3: 2026.1Q | F3: 2026.2Q | G3: 2026.3Q | H3: 2022 | I3: 2023 | J3: 2024 | K3: 2025
A4: 자산
A5: 유동자산 | C5: 1929.203 | D5: 1994.664 | E5: 2229.164 | F5: 2053.709 | G5: 2025.228 | H5: 1487.786 | I5: 1981.817 | J5: 2189.405 | K5: 1994.664
A6: 현금및현금성자산 | C6: 721.249 | D6: 732.866 | E6: 1110.658 | F6: 896.554 | G6: 737.719 | H6: 633.554 | I6: 898.688 | J6: 758.979 | K6: 732.866
A7: 단기금융상품
A8: 매출채권 | C8: 1127.434 | D8: 1198.613 | E8: 1052.535 | F8: 1078.045 | G8: 1188.498 | H8: 782.733 | I8: 1016.396 | J8: 1374.371 | K8: 1198.613
A9: 재고자산 | C9: 15.878 | D9: 21.071 | E9: 25.046 | F9: 26.11 | G9: 26.536 | H9: 38.918 | I9: 28.185 | J9: 14.743 | K9: 21.071
A10: 기타유동자산 | B10: 총계 − 위 항목 | C10: =IF(OR(C5=""),"",IFERROR(C5-SUM(C6,C7,C8,C9),"")) | D10: =IF(OR(D5=""),"",IFERROR(D5-SUM(D6,D7,D8,D9),"")) | E10: =IF(OR(E5=""),"",IFERROR(E5-SUM(E6,E7,E8,E9),"")) | F10: =IF(OR(F5=""),"",IFERROR(F5-SUM(F6,F7,F8,F9),"")) | G10: =IF(OR(G5=""),"",IFERROR(G5-SUM(G6,G7,G8,G9),"")) | H10: =IF(OR(H5=""),"",IFERROR(H5-SUM(H6,H7,H8,H9),"")) | I10: =IF(OR(I5=""),"",IFERROR(I5-SUM(I6,I7,I8,I9),"")) | J10: =IF(OR(J5=""),"",IFERROR(J5-SUM(J6,J7,J8,J9),"")) | K10: =IF(OR(K5=""),"",IFERROR(K5-SUM(K6,K7,K8,K9),""))
A11: 비유동자산 | C11: 2056.76 | D11: 2093.009 | E11: 2005.244 | F11: 2124.31 | G11: 2174.179 | H11: 1299.173 | I11: 1400.702 | J11: 1541.072 | K11: 2093.009
A12: 유형자산 | C12: 1352.109 | D12: 1353.908 | E12: 1459.674 | F12: 1461.624 | G12: 1441.524 | H12: 863.192 | I12: 1003.389 | J12: 966.751 | K12: 1353.908
A13: 무형자산 | C13: 7.252 | D13: 6.532 | E13: 5.839 | F13: 5.197 | G13: 4.556 | H13: 19.218 | I13: 15.733 | J13: 10.574 | K13: 6.532
A14: 투자부동산
A15: 기타비유동자산 | B15: 총계 − 위 항목 | C15: =IF(OR(C11=""),"",IFERROR(C11-SUM(C12,C13,C14),"")) | D15: =IF(OR(D11=""),"",IFERROR(D11-SUM(D12,D13,D14),"")) | E15: =IF(OR(E11=""),"",IFERROR(E11-SUM(E12,E13,E14),"")) | F15: =IF(OR(F11=""),"",IFERROR(F11-SUM(F12,F13,F14),"")) | G15: =IF(OR(G11=""),"",IFERROR(G11-SUM(G12,G13,G14),"")) | H15: =IF(OR(H11=""),"",IFERROR(H11-SUM(H12,H13,H14),"")) | I15: =IF(OR(I11=""),"",IFERROR(I11-SUM(I12,I13,I14),"")) | J15: =IF(OR(J11=""),"",IFERROR(J11-SUM(J12,J13,J14),"")) | K15: =IF(OR(K11=""),"",IFERROR(K11-SUM(K12,K13,K14),""))
A16: 자산총계 | C16: 3985.963 | D16: 4087.674 | E16: 4234.409 | F16: 4178.02 | G16: 4199.407 | H16: 2786.959 | I16: 3382.52 | J16: 3730.478 | K16: 4087.674
A17: 부채
A18: 유동부채 | C18: 1058.283 | D18: 1042.954 | E18: 1233.554 | F18: 1140.273 | G18: 1198.055 | H18: 1059.296 | I18: 980.647 | J18: 1043.657 | K18: 1042.954
A19: 매입채무 | C19: 192.584 | D19: 193.018 | E19: 182.861 | F19: 192.448 | G19: 207.13 | H19: 117.475 | I19: 157.643 | J19: 211.777 | K19: 193.018
A20: 단기차입금
A21: 유동성장기부채 | C21: 400.232 | D21: 376.923 | E21: 521.318 | F21: 494.573 | G21: 465.079 | H21: 465.292 | I21: 411.946 | J21: 308.202 | K21: 376.923
A22: 기타유동부채 | B22: 총계 − 위 항목 | C22: =IF(OR(C18=""),"",IFERROR(C18-SUM(C19,C20,C21),"")) | D22: =IF(OR(D18=""),"",IFERROR(D18-SUM(D19,D20,D21),"")) | E22: =IF(OR(E18=""),"",IFERROR(E18-SUM(E19,E20,E21),"")) | F22: =IF(OR(F18=""),"",IFERROR(F18-SUM(F19,F20,F21),"")) | G22: =IF(OR(G18=""),"",IFERROR(G18-SUM(G19,G20,G21),"")) | H22: =IF(OR(H18=""),"",IFERROR(H18-SUM(H19,H20,H21),"")) | I22: =IF(OR(I18=""),"",IFERROR(I18-SUM(I19,I20,I21),"")) | J22: =IF(OR(J18=""),"",IFERROR(J18-SUM(J19,J20,J21),"")) | K22: =IF(OR(K18=""),"",IFERROR(K18-SUM(K19,K20,K21),""))
A23: 비유동부채 | C23: 518.229 | D23: 492.787 | E23: 653.538 | F23: 603.102 | G23: 478.229 | H23: 564.641 | I23: 604.7 | J23: 452.836 | K23: 492.787
A24: 장기차입금 | C24: 390.97 | D24: 307.026 | E24: 539.209 | F24: 432.571 | G24: 328.682 | H24: 387.359 | I24: 482.124 | J24: 320.032 | K24: 307.026
A25: 사채 | H25: 50 | I25: 0
A26: 기타비유동부채 | B26: 총계 − 위 항목 | C26: =IF(OR(C23=""),"",IFERROR(C23-SUM(C24,C25),"")) | D26: =IF(OR(D23=""),"",IFERROR(D23-SUM(D24,D25),"")) | E26: =IF(OR(E23=""),"",IFERROR(E23-SUM(E24,E25),"")) | F26: =IF(OR(F23=""),"",IFERROR(F23-SUM(F24,F25),"")) | G26: =IF(OR(G23=""),"",IFERROR(G23-SUM(G24,G25),"")) | H26: =IF(OR(H23=""),"",IFERROR(H23-SUM(H24,H25),"")) | I26: =IF(OR(I23=""),"",IFERROR(I23-SUM(I24,I25),"")) | J26: =IF(OR(J23=""),"",IFERROR(J23-SUM(J24,J25),"")) | K26: =IF(OR(K23=""),"",IFERROR(K23-SUM(K24,K25),""))
A27: 부채총계 | C27: 1576.513 | D27: 1535.742 | E27: 1887.093 | F27: 1743.375 | G27: 1676.285 | H27: 1623.937 | I27: 1585.347 | J27: 1496.493 | K27: 1535.742
A28: 총차입금 | B28: 단기+유동성장기+장기+사채 | C28: =SUM(C20,C21,C24,C25) | D28: =SUM(D20,D21,D24,D25) | E28: =SUM(E20,E21,E24,E25) | F28: =SUM(F20,F21,F24,F25) | G28: =SUM(G20,G21,G24,G25) | H28: =SUM(H20,H21,H24,H25) | I28: =SUM(I20,I21,I24,I25) | J28: =SUM(J20,J21,J24,J25) | K28: =SUM(K20,K21,K24,K25)
A29: 순차입금 | B29: 음수 = 순현금 | C29: =C28-C6-N(C7) | D29: =D28-D6-N(D7) | E29: =E28-E6-N(E7) | F29: =F28-F6-N(F7) | G29: =G28-G6-N(G7) | H29: =H28-H6-N(H7) | I29: =I28-I6-N(I7) | J29: =J28-J6-N(J7) | K29: =K28-K6-N(K7)
A30: 자본
A31: 지배주주지분 | C31: 2409.45 | D31: 2551.931 | E31: 2347.315 | F31: 2434.644 | G31: 2523.122 | H31: 1163.022 | I31: 1797.172 | J31: 2233.984 | K31: 2551.931
A32: 자본금 | C32: 298.105 | D32: 298.105 | E32: 298.105 | F32: 298.105 | G32: 298.105 | H32: 139.75 | I32: 298.105 | J32: 298.105 | K32: 298.105
A33: 이익잉여금 | C33: 1559.008 | D33: 1661.604 | E33: 1584.359 | F33: 1689.896 | G33: 1791.997 | H33: 702.498 | I33: 1044.734 | J33: 1439.41 | K33: 1661.604
A34: 비지배지분
A35: 자본총계 | C35: 2409.45 | D35: 2551.931 | E35: 2347.315 | F35: 2434.644 | G35: 2523.122 | H35: 1163.022 | I35: 1797.172 | J35: 2233.984 | K35: 2551.931
A36: 현금흐름 요약 | B36: 분기 = TTM (있을 때만)
A37: 영업활동현금흐름 | D37: 401.199 | F37: 690.335 | H37: 80.143 | I37: 145.01 | J37: 253.242 | K37: 401.199
A38: CAPEX (유·무형 취득) | B38: 양수로 입력 | D38: 440.458 | F38: 130.117 | H38: 390.63 | I38: 211.208 | J38: 18.511 | K38: 440.458
A39: FCF | C39: =IF(OR(C37="",C38=""),"",IFERROR(C37-C38,"")) | D39: =IF(OR(D37="",D38=""),"",IFERROR(D37-D38,"")) | E39: =IF(OR(E37="",E38=""),"",IFERROR(E37-E38,"")) | F39: =IF(OR(F37="",F38=""),"",IFERROR(F37-F38,"")) | G39: =IF(OR(G37="",G38=""),"",IFERROR(G37-G38,"")) | H39: =IF(OR(H37="",H38=""),"",IFERROR(H37-H38,"")) | I39: =IF(OR(I37="",I38=""),"",IFERROR(I37-I38,"")) | J39: =IF(OR(J37="",J38=""),"",IFERROR(J37-J38,"")) | K39: =IF(OR(K37="",K38=""),"",IFERROR(K37-K38,""))
A40: 배당금 지급 | B40: 양수로 입력
A41: 주요 재무 비율 | B41: 기준 (빨간 글씨 = 미달)
A42: 안정성
A43: 부채비율 | B43: 100%↓ | C43: =IF(OR(C27="",C35=""),"",IFERROR(C27/C35,"")) | D43: =IF(OR(D27="",D35=""),"",IFERROR(D27/D35,"")) | E43: =IF(OR(E27="",E35=""),"",IFERROR(E27/E35,"")) | F43: =IF(OR(F27="",F35=""),"",IFERROR(F27/F35,"")) | G43: =IF(OR(G27="",G35=""),"",IFERROR(G27/G35,"")) | H43: =IF(OR(H27="",H35=""),"",IFERROR(H27/H35,"")) | I43: =IF(OR(I27="",I35=""),"",IFERROR(I27/I35,"")) | J43: =IF(OR(J27="",J35=""),"",IFERROR(J27/J35,"")) | K43: =IF(OR(K27="",K35=""),"",IFERROR(K27/K35,""))
A44: 순차입금비율 | B44: 0%↓ 순현금 | C44: =IF(OR(C29="",C35=""),"",IFERROR(C29/C35,"")) | D44: =IF(OR(D29="",D35=""),"",IFERROR(D29/D35,"")) | E44: =IF(OR(E29="",E35=""),"",IFERROR(E29/E35,"")) | F44: =IF(OR(F29="",F35=""),"",IFERROR(F29/F35,"")) | G44: =IF(OR(G29="",G35=""),"",IFERROR(G29/G35,"")) | H44: =IF(OR(H29="",H35=""),"",IFERROR(H29/H35,"")) | I44: =IF(OR(I29="",I35=""),"",IFERROR(I29/I35,"")) | J44: =IF(OR(J29="",J35=""),"",IFERROR(J29/J35,"")) | K44: =IF(OR(K29="",K35=""),"",IFERROR(K29/K35,""))
A45: 자기자본비율 | B45: 50%↑ | C45: =IF(OR(C35="",C16=""),"",IFERROR(C35/C16,"")) | D45: =IF(OR(D35="",D16=""),"",IFERROR(D35/D16,"")) | E45: =IF(OR(E35="",E16=""),"",IFERROR(E35/E16,"")) | F45: =IF(OR(F35="",F16=""),"",IFERROR(F35/F16,"")) | G45: =IF(OR(G35="",G16=""),"",IFERROR(G35/G16,"")) | H45: =IF(OR(H35="",H16=""),"",IFERROR(H35/H16,"")) | I45: =IF(OR(I35="",I16=""),"",IFERROR(I35/I16,"")) | J45: =IF(OR(J35="",J16=""),"",IFERROR(J35/J16,"")) | K45: =IF(OR(K35="",K16=""),"",IFERROR(K35/K16,""))
A46: 유동비율 | B46: 150%↑ | C46: =IF(OR(C5="",C18=""),"",IFERROR(C5/C18,"")) | D46: =IF(OR(D5="",D18=""),"",IFERROR(D5/D18,"")) | E46: =IF(OR(E5="",E18=""),"",IFERROR(E5/E18,"")) | F46: =IF(OR(F5="",F18=""),"",IFERROR(F5/F18,"")) | G46: =IF(OR(G5="",G18=""),"",IFERROR(G5/G18,"")) | H46: =IF(OR(H5="",H18=""),"",IFERROR(H5/H18,"")) | I46: =IF(OR(I5="",I18=""),"",IFERROR(I5/I18,"")) | J46: =IF(OR(J5="",J18=""),"",IFERROR(J5/J18,"")) | K46: =IF(OR(K5="",K18=""),"",IFERROR(K5/K18,""))
A47: 당좌비율 | B47: 100%↑ | C47: =IF(OR(C5="",C18=""),"",IFERROR((C5-N(C9))/C18,"")) | D47: =IF(OR(D5="",D18=""),"",IFERROR((D5-N(D9))/D18,"")) | E47: =IF(OR(E5="",E18=""),"",IFERROR((E5-N(E9))/E18,"")) | F47: =IF(OR(F5="",F18=""),"",IFERROR((F5-N(F9))/F18,"")) | G47: =IF(OR(G5="",G18=""),"",IFERROR((G5-N(G9))/G18,"")) | H47: =IF(OR(H5="",H18=""),"",IFERROR((H5-N(H9))/H18,"")) | I47: =IF(OR(I5="",I18=""),"",IFERROR((I5-N(I9))/I18,"")) | J47: =IF(OR(J5="",J18=""),"",IFERROR((J5-N(J9))/J18,"")) | K47: =IF(OR(K5="",K18=""),"",IFERROR((K5-N(K9))/K18,""))
A48: 이자보상배율 | B48: 5x↑ (금융원가 기준) | C48: =IFERROR((IF(COUNT('연간'!G19:J19)<4,"",SUM('연간'!G19:J19)))/(IF(COUNT('연간'!G41:J41)<4,"",SUM('연간'!G41:J41))),"") | D48: =IFERROR((IF(COUNT('연간'!H19:K19)<4,"",SUM('연간'!H19:K19)))/(IF(COUNT('연간'!H41:K41)<4,"",SUM('연간'!H41:K41))),"") | E48: =IFERROR((IF(COUNT('연간'!I19:L19)<4,"",SUM('연간'!I19:L19)))/(IF(COUNT('연간'!I41:L41)<4,"",SUM('연간'!I41:L41))),"") | F48: =IFERROR((IF(COUNT('연간'!J19:M19)<4,"",SUM('연간'!J19:M19)))/(IF(COUNT('연간'!J41:M41)<4,"",SUM('연간'!J41:M41))),"") | G48: =IFERROR((IF(COUNT('연간'!K19:N19)<4,"",SUM('연간'!K19:N19)))/(IF(COUNT('연간'!K41:N41)<4,"",SUM('연간'!K41:N41))),"") | H48: =IFERROR(('연간'!U19)/('연간'!U41),"") | I48: =IFERROR(('연간'!V19)/('연간'!V41),"") | J48: =IFERROR(('연간'!W19)/('연간'!W41),"") | K48: =IFERROR(('연간'!X19)/('연간'!X41),"")
A49: 차입금 상환연수 | B49: 4년↓ (버핏) | C49: =IFERROR(IF((IF(COUNT('연간'!G49:J49)<4,"",SUM('연간'!G49:J49)))<=0,"적자",C28/(IF(COUNT('연간'!G49:J49)<4,"",SUM('연간'!G49:J49)))),"") | D49: =IFERROR(IF((IF(COUNT('연간'!H49:K49)<4,"",SUM('연간'!H49:K49)))<=0,"적자",D28/(IF(COUNT('연간'!H49:K49)<4,"",SUM('연간'!H49:K49)))),"") | E49: =IFERROR(IF((IF(COUNT('연간'!I49:L49)<4,"",SUM('연간'!I49:L49)))<=0,"적자",E28/(IF(COUNT('연간'!I49:L49)<4,"",SUM('연간'!I49:L49)))),"") | F49: =IFERROR(IF((IF(COUNT('연간'!J49:M49)<4,"",SUM('연간'!J49:M49)))<=0,"적자",F28/(IF(COUNT('연간'!J49:M49)<4,"",SUM('연간'!J49:M49)))),"") | G49: =IFERROR(IF((IF(COUNT('연간'!K49:N49)<4,"",SUM('연간'!K49:N49)))<=0,"적자",G28/(IF(COUNT('연간'!K49:N49)<4,"",SUM('연간'!K49:N49)))),"") | H49: =IFERROR(IF(('연간'!U49)<=0,"적자",H28/('연간'!U49)),"") | I49: =IFERROR(IF(('연간'!V49)<=0,"적자",I28/('연간'!V49)),"") | J49: =IFERROR(IF(('연간'!W49)<=0,"적자",J28/('연간'!W49)),"") | K49: =IFERROR(IF(('연간'!X49)<=0,"적자",K28/('연간'!X49)),"")
A50: 수익성
A51: ROE | B51: 15%↑ (버핏) | C51: =IFERROR((IF(COUNT('연간'!G49:J49)<4,"",SUM('연간'!G49:J49)))/C31,"") | D51: =IFERROR((IF(COUNT('연간'!H49:K49)<4,"",SUM('연간'!H49:K49)))/D31,"") | E51: =IFERROR((IF(COUNT('연간'!I49:L49)<4,"",SUM('연간'!I49:L49)))/E31,"") | F51: =IFERROR((IF(COUNT('연간'!J49:M49)<4,"",SUM('연간'!J49:M49)))/F31,"") | G51: =IFERROR((IF(COUNT('연간'!K49:N49)<4,"",SUM('연간'!K49:N49)))/G31,"") | H51: =IFERROR(('연간'!U49)/H31,"") | I51: =IFERROR(('연간'!V49)/I31,"") | J51: =IFERROR(('연간'!W49)/J31,"") | K51: =IFERROR(('연간'!X49)/K31,"")
A52: ROA | B52: 5%↑ | C52: =IFERROR((IF(COUNT('연간'!G47:J47)<4,"",SUM('연간'!G47:J47)))/C16,"") | D52: =IFERROR((IF(COUNT('연간'!H47:K47)<4,"",SUM('연간'!H47:K47)))/D16,"") | E52: =IFERROR((IF(COUNT('연간'!I47:L47)<4,"",SUM('연간'!I47:L47)))/E16,"") | F52: =IFERROR((IF(COUNT('연간'!J47:M47)<4,"",SUM('연간'!J47:M47)))/F16,"") | G52: =IFERROR((IF(COUNT('연간'!K47:N47)<4,"",SUM('연간'!K47:N47)))/G16,"") | H52: =IFERROR(('연간'!U47)/H16,"") | I52: =IFERROR(('연간'!V47)/I16,"") | J52: =IFERROR(('연간'!W47)/J16,"") | K52: =IFERROR(('연간'!X47)/K16,"")
A53: ROIC | B53: 10%↑ (세후영업이익 기준) | C53: =IFERROR((IF(COUNT('연간'!G19:J19)<4,"",SUM('연간'!G19:J19)))*(1-0.3)/(C35+C29),"") | D53: =IFERROR((IF(COUNT('연간'!H19:K19)<4,"",SUM('연간'!H19:K19)))*(1-0.3)/(D35+D29),"") | E53: =IFERROR((IF(COUNT('연간'!I19:L19)<4,"",SUM('연간'!I19:L19)))*(1-0.3)/(E35+E29),"") | F53: =IFERROR((IF(COUNT('연간'!J19:M19)<4,"",SUM('연간'!J19:M19)))*(1-0.3)/(F35+F29),"") | G53: =IFERROR((IF(COUNT('연간'!K19:N19)<4,"",SUM('연간'!K19:N19)))*(1-0.3)/(G35+G29),"") | H53: =IFERROR(('연간'!U19)*(1-0.3)/(H35+H29),"") | I53: =IFERROR(('연간'!V19)*(1-0.3)/(I35+I29),"") | J53: =IFERROR(('연간'!W19)*(1-0.3)/(J35+J29),"") | K53: =IFERROR(('연간'!X19)*(1-0.3)/(K35+K29),"")
A54: 매출총이익률 (GPM) | B54: 40%↑ (해자 신호) | C54: =IFERROR((IF(COUNT('연간'!G13:J13)<4,"",SUM('연간'!G13:J13)))/(IF(COUNT('연간'!G4:J4)<4,"",SUM('연간'!G4:J4))),"") | D54: =IFERROR((IF(COUNT('연간'!H13:K13)<4,"",SUM('연간'!H13:K13)))/(IF(COUNT('연간'!H4:K4)<4,"",SUM('연간'!H4:K4))),"") | E54: =IFERROR((IF(COUNT('연간'!I13:L13)<4,"",SUM('연간'!I13:L13)))/(IF(COUNT('연간'!I4:L4)<4,"",SUM('연간'!I4:L4))),"") | F54: =IFERROR((IF(COUNT('연간'!J13:M13)<4,"",SUM('연간'!J13:M13)))/(IF(COUNT('연간'!J4:M4)<4,"",SUM('연간'!J4:M4))),"") | G54: =IFERROR((IF(COUNT('연간'!K13:N13)<4,"",SUM('연간'!K13:N13)))/(IF(COUNT('연간'!K4:N4)<4,"",SUM('연간'!K4:N4))),"") | H54: =IFERROR(('연간'!U13)/('연간'!U4),"") | I54: =IFERROR(('연간'!V13)/('연간'!V4),"") | J54: =IFERROR(('연간'!W13)/('연간'!W4),"") | K54: =IFERROR(('연간'!X13)/('연간'!X4),"")
A55: 영업이익률 (OPM) | B55: 15%↑ | C55: =IFERROR((IF(COUNT('연간'!G19:J19)<4,"",SUM('연간'!G19:J19)))/(IF(COUNT('연간'!G4:J4)<4,"",SUM('연간'!G4:J4))),"") | D55: =IFERROR((IF(COUNT('연간'!H19:K19)<4,"",SUM('연간'!H19:K19)))/(IF(COUNT('연간'!H4:K4)<4,"",SUM('연간'!H4:K4))),"") | E55: =IFERROR((IF(COUNT('연간'!I19:L19)<4,"",SUM('연간'!I19:L19)))/(IF(COUNT('연간'!I4:L4)<4,"",SUM('연간'!I4:L4))),"") | F55: =IFERROR((IF(COUNT('연간'!J19:M19)<4,"",SUM('연간'!J19:M19)))/(IF(COUNT('연간'!J4:M4)<4,"",SUM('연간'!J4:M4))),"") | G55: =IFERROR((IF(COUNT('연간'!K19:N19)<4,"",SUM('연간'!K19:N19)))/(IF(COUNT('연간'!K4:N4)<4,"",SUM('연간'!K4:N4))),"") | H55: =IFERROR(('연간'!U19)/('연간'!U4),"") | I55: =IFERROR(('연간'!V19)/('연간'!V4),"") | J55: =IFERROR(('연간'!W19)/('연간'!W4),"") | K55: =IFERROR(('연간'!X19)/('연간'!X4),"")
A56: 순이익률 | B56: 10%↑ | C56: =IFERROR((IF(COUNT('연간'!G47:J47)<4,"",SUM('연간'!G47:J47)))/(IF(COUNT('연간'!G4:J4)<4,"",SUM('연간'!G4:J4))),"") | D56: =IFERROR((IF(COUNT('연간'!H47:K47)<4,"",SUM('연간'!H47:K47)))/(IF(COUNT('연간'!H4:K4)<4,"",SUM('연간'!H4:K4))),"") | E56: =IFERROR((IF(COUNT('연간'!I47:L47)<4,"",SUM('연간'!I47:L47)))/(IF(COUNT('연간'!I4:L4)<4,"",SUM('연간'!I4:L4))),"") | F56: =IFERROR((IF(COUNT('연간'!J47:M47)<4,"",SUM('연간'!J47:M47)))/(IF(COUNT('연간'!J4:M4)<4,"",SUM('연간'!J4:M4))),"") | G56: =IFERROR((IF(COUNT('연간'!K47:N47)<4,"",SUM('연간'!K47:N47)))/(IF(COUNT('연간'!K4:N4)<4,"",SUM('연간'!K4:N4))),"") | H56: =IFERROR(('연간'!U47)/('연간'!U4),"") | I56: =IFERROR(('연간'!V47)/('연간'!V4),"") | J56: =IFERROR(('연간'!W47)/('연간'!W4),"") | K56: =IFERROR(('연간'!X47)/('연간'!X4),"")
A57: 효율성 (회전율)
A58: 총자산회전율 | B58: 높을수록↑ | C58: =IFERROR((IF(COUNT('연간'!G4:J4)<4,"",SUM('연간'!G4:J4)))/C16,"") | D58: =IFERROR((IF(COUNT('연간'!H4:K4)<4,"",SUM('연간'!H4:K4)))/D16,"") | E58: =IFERROR((IF(COUNT('연간'!I4:L4)<4,"",SUM('연간'!I4:L4)))/E16,"") | F58: =IFERROR((IF(COUNT('연간'!J4:M4)<4,"",SUM('연간'!J4:M4)))/F16,"") | G58: =IFERROR((IF(COUNT('연간'!K4:N4)<4,"",SUM('연간'!K4:N4)))/G16,"") | H58: =IFERROR(('연간'!U4)/H16,"") | I58: =IFERROR(('연간'!V4)/I16,"") | J58: =IFERROR(('연간'!W4)/J16,"") | K58: =IFERROR(('연간'!X4)/K16,"")
A59: 매출채권회전일수 | B59: 짧을수록↑ | C59: =IFERROR(C8/(IF(COUNT('연간'!G4:J4)<4,"",SUM('연간'!G4:J4)))*365,"") | D59: =IFERROR(D8/(IF(COUNT('연간'!H4:K4)<4,"",SUM('연간'!H4:K4)))*365,"") | E59: =IFERROR(E8/(IF(COUNT('연간'!I4:L4)<4,"",SUM('연간'!I4:L4)))*365,"") | F59: =IFERROR(F8/(IF(COUNT('연간'!J4:M4)<4,"",SUM('연간'!J4:M4)))*365,"") | G59: =IFERROR(G8/(IF(COUNT('연간'!K4:N4)<4,"",SUM('연간'!K4:N4)))*365,"") | H59: =IFERROR(H8/('연간'!U4)*365,"") | I59: =IFERROR(I8/('연간'!V4)*365,"") | J59: =IFERROR(J8/('연간'!W4)*365,"") | K59: =IFERROR(K8/('연간'!X4)*365,"")
A60: 재고자산회전일수 | B60: 짧을수록↑ | C60: =IFERROR(C9/(IF(COUNT('연간'!G11:J11)<4,"",SUM('연간'!G11:J11)))*365,"") | D60: =IFERROR(D9/(IF(COUNT('연간'!H11:K11)<4,"",SUM('연간'!H11:K11)))*365,"") | E60: =IFERROR(E9/(IF(COUNT('연간'!I11:L11)<4,"",SUM('연간'!I11:L11)))*365,"") | F60: =IFERROR(F9/(IF(COUNT('연간'!J11:M11)<4,"",SUM('연간'!J11:M11)))*365,"") | G60: =IFERROR(G9/(IF(COUNT('연간'!K11:N11)<4,"",SUM('연간'!K11:N11)))*365,"") | H60: =IFERROR(H9/('연간'!U11)*365,"") | I60: =IFERROR(I9/('연간'!V11)*365,"") | J60: =IFERROR(J9/('연간'!W11)*365,"") | K60: =IFERROR(K9/('연간'!X11)*365,"")
A61: 매입채무회전일수 | B61: 길수록 유리 | C61: =IFERROR(C19/(IF(COUNT('연간'!G11:J11)<4,"",SUM('연간'!G11:J11)))*365,"") | D61: =IFERROR(D19/(IF(COUNT('연간'!H11:K11)<4,"",SUM('연간'!H11:K11)))*365,"") | E61: =IFERROR(E19/(IF(COUNT('연간'!I11:L11)<4,"",SUM('연간'!I11:L11)))*365,"") | F61: =IFERROR(F19/(IF(COUNT('연간'!J11:M11)<4,"",SUM('연간'!J11:M11)))*365,"") | G61: =IFERROR(G19/(IF(COUNT('연간'!K11:N11)<4,"",SUM('연간'!K11:N11)))*365,"") | H61: =IFERROR(H19/('연간'!U11)*365,"") | I61: =IFERROR(I19/('연간'!V11)*365,"") | J61: =IFERROR(J19/('연간'!W11)*365,"") | K61: =IFERROR(K19/('연간'!X11)*365,"")
A62: 현금전환주기 (CCC) | B62: 짧을수록↑ | C62: =IF(OR(C59="",C60="",C61=""),"",IFERROR(C59+C60-C61,"")) | D62: =IF(OR(D59="",D60="",D61=""),"",IFERROR(D59+D60-D61,"")) | E62: =IF(OR(E59="",E60="",E61=""),"",IFERROR(E59+E60-E61,"")) | F62: =IF(OR(F59="",F60="",F61=""),"",IFERROR(F59+F60-F61,"")) | G62: =IF(OR(G59="",G60="",G61=""),"",IFERROR(G59+G60-G61,"")) | H62: =IF(OR(H59="",H60="",H61=""),"",IFERROR(H59+H60-H61,"")) | I62: =IF(OR(I59="",I60="",I61=""),"",IFERROR(I59+I60-I61,"")) | J62: =IF(OR(J59="",J60="",J61=""),"",IFERROR(J59+J60-J61,"")) | K62: =IF(OR(K59="",K60="",K61=""),"",IFERROR(K59+K60-K61,""))
A63: 현금흐름
A64: 영업현금흐름 / 순이익 | B64: 1x↑ (이익의 질) | C64: =IF(C37="","",IFERROR(C37/(IF(COUNT('연간'!G47:J47)<4,"",SUM('연간'!G47:J47))),"")) | D64: =IF(D37="","",IFERROR(D37/(IF(COUNT('연간'!H47:K47)<4,"",SUM('연간'!H47:K47))),"")) | E64: =IF(E37="","",IFERROR(E37/(IF(COUNT('연간'!I47:L47)<4,"",SUM('연간'!I47:L47))),"")) | F64: =IF(F37="","",IFERROR(F37/(IF(COUNT('연간'!J47:M47)<4,"",SUM('연간'!J47:M47))),"")) | G64: =IF(G37="","",IFERROR(G37/(IF(COUNT('연간'!K47:N47)<4,"",SUM('연간'!K47:N47))),"")) | H64: =IF(H37="","",IFERROR(H37/('연간'!U47),"")) | I64: =IF(I37="","",IFERROR(I37/('연간'!V47),"")) | J64: =IF(J37="","",IFERROR(J37/('연간'!W47),"")) | K64: =IF(K37="","",IFERROR(K37/('연간'!X47),""))
A65: FCF 마진 | B65: 5%↑ | C65: =IF(C39="","",IFERROR(C39/(IF(COUNT('연간'!G4:J4)<4,"",SUM('연간'!G4:J4))),"")) | D65: =IF(D39="","",IFERROR(D39/(IF(COUNT('연간'!H4:K4)<4,"",SUM('연간'!H4:K4))),"")) | E65: =IF(E39="","",IFERROR(E39/(IF(COUNT('연간'!I4:L4)<4,"",SUM('연간'!I4:L4))),"")) | F65: =IF(F39="","",IFERROR(F39/(IF(COUNT('연간'!J4:M4)<4,"",SUM('연간'!J4:M4))),"")) | G65: =IF(G39="","",IFERROR(G39/(IF(COUNT('연간'!K4:N4)<4,"",SUM('연간'!K4:N4))),"")) | H65: =IF(H39="","",IFERROR(H39/('연간'!U4),"")) | I65: =IF(I39="","",IFERROR(I39/('연간'!V4),"")) | J65: =IF(J39="","",IFERROR(J39/('연간'!W4),"")) | K65: =IF(K39="","",IFERROR(K39/('연간'!X4),""))
A66: CAPEX / 매출 | B66: 낮을수록↑ (자본 가벼움) | C66: =IF(C38="","",IFERROR(C38/(IF(COUNT('연간'!G4:J4)<4,"",SUM('연간'!G4:J4))),"")) | D66: =IF(D38="","",IFERROR(D38/(IF(COUNT('연간'!H4:K4)<4,"",SUM('연간'!H4:K4))),"")) | E66: =IF(E38="","",IFERROR(E38/(IF(COUNT('연간'!I4:L4)<4,"",SUM('연간'!I4:L4))),"")) | F66: =IF(F38="","",IFERROR(F38/(IF(COUNT('연간'!J4:M4)<4,"",SUM('연간'!J4:M4))),"")) | G66: =IF(G38="","",IFERROR(G38/(IF(COUNT('연간'!K4:N4)<4,"",SUM('연간'!K4:N4))),"")) | H66: =IF(H38="","",IFERROR(H38/('연간'!U4),"")) | I66: =IF(I38="","",IFERROR(I38/('연간'!V4),"")) | J66: =IF(J38="","",IFERROR(J38/('연간'!W4),"")) | K66: =IF(K38="","",IFERROR(K38/('연간'!X4),""))
A67: 배당성향 | B67: 참고 | C67: =IF(C40="","",IFERROR(C40/(IF(COUNT('연간'!G49:J49)<4,"",SUM('연간'!G49:J49))),"")) | D67: =IF(D40="","",IFERROR(D40/(IF(COUNT('연간'!H49:K49)<4,"",SUM('연간'!H49:K49))),"")) | E67: =IF(E40="","",IFERROR(E40/(IF(COUNT('연간'!I49:L49)<4,"",SUM('연간'!I49:L49))),"")) | F67: =IF(F40="","",IFERROR(F40/(IF(COUNT('연간'!J49:M49)<4,"",SUM('연간'!J49:M49))),"")) | G67: =IF(G40="","",IFERROR(G40/(IF(COUNT('연간'!K49:N49)<4,"",SUM('연간'!K49:N49))),"")) | H67: =IF(H40="","",IFERROR(H40/('연간'!U49),"")) | I67: =IF(I40="","",IFERROR(I40/('연간'!V49),"")) | J67: =IF(J40="","",IFERROR(J40/('연간'!W49),"")) | K67: =IF(K40="","",IFERROR(K40/('연간'!X49),""))
A69: 재무상태표 · 전 항목 | B69: 분기 말 잔액
A70: 항목 | B70: 참고 | C70: 2025.3Q | D70: 2025.4Q | E70: 2026.1Q | F70: 2026.2Q | G70: 2026.3Q | H70: 2022 | I70: 2023 | J70: 2024 | K70: 2025
A71: 현금 및 예금 | C71: 721.249 | D71: 732.866 | E71: 1110.658 | F71: 896.554 | G71: 737.719 | H71: 633.554 | I71: 898.688 | J71: 758.979 | K71: 732.866
A72: 매출채권·계약자산 | H72: 782.733 | I72: 1016.396
A73: 매출채권·계약자산 | H73: 782.733 | I73: 1016.396
A74: 매출채권·계약자산 | C74: 1127.434 | D74: 1198.613 | E74: 1052.535 | F74: 1078.045 | G74: 1188.498 | I74: 1016.396 | J74: 1374.371 | K74: 1198.613
A75: 저장품 | C75: 15.878 | D75: 21.071 | E75: 25.046 | F75: 26.11 | G75: 26.536 | H75: 38.918 | I75: 28.185 | J75: 14.743 | K75: 21.071
A76: 선급금 | D76: 0.424 | H76: 1.477 | I76: 0.714 | J76: 1.734 | K76: 0.424
A77: 선급비용 | D77: 26.455 | H77: 28.74 | I77: 22.856 | J77: 22.787 | K77: 26.455
A78: 미수금 | D78: 13.464 | H78: 0.717 | I78: 12.529 | J78: 14.606 | K78: 13.464
A79: 기타 | C79: 64.719 | D79: 42.421 | E79: 43.409 | F79: 55.308 | G79: 74.556 | H79: 1.722 | I79: 2.524 | J79: 2.261 | K79: 42.421
A80: 대손충당금 | C80: -0.078 | D80: -0.307 | E80: -2.484 | F80: -2.31 | G80: -2.082 | H80: -0.078 | I80: -0.078 | J80: -0.078 | K80: -0.307
A81: 유동자산 합계 | C81: 1929.203 | D81: 1994.664 | E81: 2229.164 | F81: 2053.709 | G81: 2025.228 | H81: 1487.786 | I81: 1981.817 | J81: 2189.405 | K81: 1994.664
A82: 건물(순액) | C82: 778.936 | D82: 779.336 | E82: 867.938 | F82: 876.246 | G82: 863.077 | H82: 284.278 | I82: 599.847 | J82: 568.095 | K82: 779.336
A83: 구축물(순액) | C83: 121.994 | D83: 120.245 | E83: 118.497 | F83: 116.749 | G83: 115 | H83: 1.378 | I83: 134.232 | J83: 127.239 | K83: 120.245
A84: 기계장치(순액) | C84: 2.756 | D84: 2.537 | E84: 2.32 | F84: 0.991 | G84: 0.96 | H84: 4.369 | I84: 3.119 | J84: 2.227 | K84: 2.537
A85: 차량운반구(순액) | C85: 4.729 | D85: 9.951 | E85: 9.123 | F85: 8.294 | G85: 7.466 | H85: 0.241 | I85: 0 | J85: 6.303 | K85: 9.951
A86: 공구·기구·비품(순액) | C86: 32.672 | D86: 30.816 | E86: 50.773 | F86: 48.321 | G86: 43.999 | H86: 22.235 | I86: 43.726 | J86: 30.423 | K86: 30.816
A87: 토지 | C87: 411.02 | D87: 411.02 | E87: 411.02 | F87: 411.02 | G87: 411.02 | H87: 191.817 | I87: 222.462 | J87: 222.462 | K87: 411.02
A88: 건설중인자산 | C88: 0 | D88: 0 | H88: 358.872 | I88: 0 | J88: 10 | K88: 0
A89: 유형자산 합계 | C89: 1352.109 | D89: 1353.908 | E89: 1459.674 | F89: 1461.624 | G89: 1441.524 | H89: 863.192 | I89: 1003.389 | J89: 966.751 | K89: 1353.908
A90: 소프트웨어 | C90: 5.304 | D90: 4.604 | E90: 3.93 | F90: 3.308 | G90: 2.686 | H90: 16.462 | I90: 11.873 | J90: 8.568 | K90: 4.604
A91: 기타 | C91: 1.947 | D91: 1.928 | E91: 1.909 | F91: 1.889 | G91: 1.87 | H91: 2.755 | I91: 3.859 | J91: 2.006 | K91: 1.928
A92: 무형자산 합계 | C92: 7.252 | D92: 6.532 | E92: 5.839 | F92: 5.197 | G92: 4.556 | H92: 19.218 | I92: 15.733 | J92: 10.574 | K92: 6.532
A93: 투자유가증권 | C93: 472.771 | D93: 508.877 | E93: 332.777 | F93: 452.728 | G93: 511.826 | H93: 330.293 | I93: 297.864 | J93: 362.099 | K93: 508.877
A94: 관계회사 주식 | D94: 13.519 | H94: 3.339 | I94: 3.339 | J94: 3.339 | K94: 13.519
A95: 출자금 | D95: 0.01 | H95: 5.601 | I95: 0 | J95: 0 | K95: 0.01
A96: 장기선급비용 | D96: 3.477 | H96: 0.702 | I96: 1.855 | J96: 5.828 | K96: 3.477
A97: 임차보증금·보증금 | D97: 205.527 | I97: 77.366 | J97: 191.323 | K97: 205.527
A98: 기타 | C98: 224.626 | D98: 223.69 | E98: 206.953 | F98: 204.76 | G98: 216.272 | H98: 76.826 | I98: 1.155 | J98: 1.155 | K98: 223.69
A99: 투자 및 기타자산 합계 | C99: 697.397 | D99: 732.567 | E99: 539.731 | F99: 657.488 | G99: 728.098 | H99: 416.761 | I99: 381.58 | J99: 563.746 | K99: 732.567
A100: 비유동자산 합계 | C100: 2056.76 | D100: 2093.009 | E100: 2005.244 | F100: 2124.31 | G100: 2174.179 | H100: 1299.173 | I100: 1400.702 | J100: 1541.072 | K100: 2093.009
A101: 자산 합계 | C101: 3985.963 | D101: 4087.674 | E101: 4234.409 | F101: 4178.02 | G101: 4199.407 | H101: 2786.959 | I101: 3382.52 | J101: 3730.478 | K101: 4087.674
...

Sheet 섹터 데이터
A1: 5257 섹터·사업 데이터
A2: 2단계 보고서를 만들 때 모은 자료 · 월차 · 출처는 맨 오른쪽
A4: this_results · q3_standalone_억엔
A5: 항목 | B5: 값 | N5: 출처
A6: 매출 | B6: 18.59 | N6: 2단계 보고서 자료(회사 설명회 자료·공시)
A7: 영업이익 | B7: 1.6
A8: 경상이익 | B8: 1.67
A9: 순이익 | B9: 1.12
A10: EPS_엔 | B10: 80.96
A11: OPM_% | B11: 8.6
A12: YoY_매출_% | B12: 10
A14: this_results · ytd_9m_백만엔
A15: 항목 | B15: 값 | N15: 출처
A16: 매출 | B16: 5374.6 | N16: 2단계 보고서 자료(회사 설명회 자료·공시)
A17: YoY | B17: 7.8
A18: SI매출 | B18: 5285.2
A19: SI YoY | B19: 7.8
A20: 클라우드매출 | B20: 89.5
A21: 클라우드_YoY | B21: 6.7
A22: 매출원가 | B22: 4108.7
A23: 매출총이익 | B23: 1266
A24: GP YoY | B24: 42.2
A25: 판관비 | B25: 831.9
A26: 판관비_YoY | B26: 14
A27: 영업이익 | B27: 434.1
A28: 영업이익 YoY | B28: 170.4
... A36: 감가상각비 | B36: 61.5
A38: this_results · ytd_prev_9m_백만엔
A39: 항목 | B39: 값 | N39: 출처
A40: 매출 | B40: 4984.6 | N40: 2단계 보고서 자료(회사 설명회 자료·공시)
A41: 매출원가 | B41: 4094.4
A42: 매출총이익 | B42: 890.2
A43: 판관비 | B43: 729.7
A44: 영업이익 | B44: 160.5
A45: 경상이익 | B45: 179.9
A46: 특별이익 | B46: 0.4
A47: 세전 | B47: 180.3
A48: 법인세등 | B48: 60.2
A49: 순이익 | B49: 120.1
A51: this_results · guidance_FY26_백만엔
A52: 항목 | B52: 값 | N52: 출처
A53: 매출 | B53: 7535 | N53: 2단계 보고서 자료(회사 설명회 자료·공시)
A54: SI | B54: 7405
A55: 클라우드 | B55: 130
A56: 매출총이익 | B56: 1715
A57: 영업이익 | B57: 617
A58: 영업이익률 | B58: 8.2
A59: 경상 | B59: 660
A60: 순이익 | B60: 442
A61: EPS | B61: 315.44
A62: DPS | B62: 105
A64: this_results · BS_3Q말_백만엔
A65: 항목 | B65: 값 | N65: 출처
A66: 현금 | B66: 737.7 | N66: 2단계 보고서 자료(회사 설명회 자료·공시)
A67: 매출채권·계약자산 | B67: 1188.5
A68: 유형자산 | B68: 1441.5
A69: 투자유가증권 | B69: 511.8
A70: 총자산 | B70: 4199.4
A71: 차입금(1년내+장기) | B71: 793.8
A72: 순자산 | B72: 2523.1
A73: 자기자본비율 | B73: 60.1
A75: this results · shares
A76: 항목 | B76: 값 | N76: 출처
A77: 발행 | B77: 1402500 | N77: 2단계 보고서 자료(회사 설명회 자료·공시)
A78: 자사주 | B78: 30811
A79: 유통 | B79: 1371689
A80: 평균9M | B80: 1391787
A82: quarterly_억엔
A83: 항목 | B83: 2023.4Q | C83: 2024.1Q | D83: 2024.2Q | E83: 2024.3Q | F83: 2024.4Q | G83: 2025.1Q | H83: 2025.2Q | I83: 2025.3Q | J83: 2025.4Q | K83: 2026.1Q | L83: 2026.2Q | M83: 2026.3Q | N83: 출처
A84: 매출 | B84: 14.3 | C84: 15.8 | D84: 15.1 | E84: 16.5 | F84: 17.2 | G84: 16.8 | H84: 16.2 | I84: 16.9 | J84: 17.3 | K84: 17.2 | L84: 18 | M84: 18.6 | N84: 2단계 보고서 자료(회사 설명회 자료·공시)
A85: gp | B85: 3.2 | C85: 3.7 | D85: 3.1 | E85: 3.3 | F85: 4.1 | G85: 3.2 | H85: 2.7 | I85: 2.9 | J85: 4.1 | K85: 3.8 | L85: 4.6 | M85: 4.3
A86: sga | B86: 2.2 | C86: 2.1 | D86: 2.6 | E86: 2.1 | F86: 2.1 | G86: 2.3 | H86: 2.8 | I86: 2.2 | J86: 2.4 | K86: 2.5 | L86: 3.1 | M86: 2.7
A87: 영업이익 | B87: 1 | C87: 1.6 | D87: 0.5 | E87: 1.2 | F87: 2 | G87: 1 | H87: -0.1 | I87: 0.7 | J87: 1.6 | K87: 1.2 | L87: 1.5 | M87: 1.6
A88: pbt | B88: 1 | C88: 1.6 | D88: 0.5 | E88: 1.2 | F88: 2 | G88: 1.1 | H88: 0 | I88: 0.8 | J88: 1.7 | K88: 1 | L88: 1.6 | M88: 1.6
A89: 순이익 owner | B89: 0.8 | C89: 1.1 | D89: 0.4 | E89: 0.9 | F89: 1.6 | G89: 0.7 | H89: 0 | I89: 0.5 | J89: 1.1 | K89: 0.7 | L89: 1.1 | M89: 1.1
A91: annual_억엔
A92: 항목 | B92: 2016 | C92: 2017 | D92: 2018 | E92: 2019 | F92: 2020 | G92: 2021 | H92: 2022 | I92: 2023 | J92: 2024 | K92: 2025 | N92: 출처
A93: labels | B93: 2016 | C93: 2017 | D93: 2018 | E93: 2019 | F93: 2020 | G93: 2021 | H93: 2022 | I93: 2023 | J93: 2024 | K93: 2025 | N93: 2단계 보고서 자료(회사 설명회 자료·공시)
A94: 매출 | H94: 46.3 | I94: 54.2 | J94: 64.6 | K94: 67.2
A95: gp | H95: 10.3 | I95: 13.3 | J95: 14.2 | K95: 13
A96: sga | H96: 7 | I96: 8.4 | J96: 9 | K96: 9.7
A97: 영업이익 | H97: 3.3 | I97: 4.9 | J97: 5.3 | K97: 3.2
A98: pbt | H98: 3.3 | I98: 4.9 | J98: 5.4 | K98: 3.5
A99: 순이익 owner | H99: 2.1 | I99: 3.4 | J99: 3.9 | K99: 2.3
A101: bs annual
A102: 항목 | B102: 2022 | C102: 2023 | D102: 2024 | E102: 2025 | N102: 출처
A103: labels | B103: 2022 | C103: 2023 | D103: 2024 | E103: 2025 | N103: 2단계 보고서 자료(회사 설명회 자료·공시)
A104: current assets | B104: 14.9 | C104: 19.8 | D104: 21.9 | E104: 19.9
A105: cash | B105: 6.3 | C105: 9 | D105: 7.6 | E105: 7.3
A106: st fin
A107: receivables | B107: 7.8 | C107: 10.2 | D107: 13.7 | E107: 12
A108: inventory | B108: 0.4 | C108: 0.3 | D108: 0.1 | E108: 0.2
A109: noncurrent assets | B109: 13 | C109: 14 | D109: 15.4 | E109: 20.9
A110: ppe | B110: 8.6 | C110: 10 | D110: 9.7 | E110: 13.5
A111: intangibles | B111: 0.2 | C111: 0.2 | D111: 0.1 | E111: 0.1
A112: inv property
A113: 합계 assets | B113: 27.9 | C113: 33.8 | D113: 37.3 | E113: 40.9
A114: current liab | B114: 10.6 | C114: 9.8 | D114: 10.4 | E114: 10.4
A115: payables | B115: 1.2 | C115: 1.6 | D115: 2.1 | E115: 1.9
A116: st debt
...

Sheet 출처
A1: 출처 · 쓴 결산단신
A3: 공시일 | B3: 문서 | C3: PDF
A4: 2026-10-30 | B4: 2026년 12월 결산기 ３분기 결산단신 | C4: https://www2.jpx.co.jp/disc/52570/140120261029558756.pdf
A5: 2026-07-31 | B5: 2026년 12월 결산기 ２분기 결산단신 | C5: https://www2.jpx.co.jp/disc/52570/140120260731504310.pdf
A6: 2026-04-30 | B6: 2026년 12월 결산기 １분기 결산단신 | C6: https://www2.jpx.co.jp/disc/52570/140120260428513795.pdf
A7: 2026-02-13 | B7: 2025년 12월 결산기 연간 결산단신 | C7: https://www2.jpx.co.jp/disc/52570/140120260213559062.pdf
A8: 2025-10-31 | B8: 2025년 12월 결산기 ３분기 결산단신 | C8: https://www2.jpx.co.jp/disc/52570/140120251030582916.pdf
A9: 2025-07-31 | B9: 2025년 12월 결산기 ２분기 결산단신 | C9: https://www2.jpx.co.jp/disc/52570/140120250730524474.pdf
A10: 2025-05-02 | B10: 2025년 12월 결산기 １분기 결산단신 | C10: https://www2.jpx.co.jp/disc/52570/140120250501529021.pdf
A11: 2025-04-30 | B11: 2025년 12월 결산기 １분기 결산단신 | C11: https://www2.jpx.co.jp/disc/52570/140120250425524884.pdf
A12: 2025-02-13 | B12: 2024년 12월 결산기 연간 결산단신 | C12: https://www2.jpx.co.jp/disc/52570/140120250213572288.pdf
A13: 2024-10-31 | B13: 2024년 12월 결산기 ３분기 결산단신 | C13: https://www2.jpx.co.jp/disc/52570/140120241030506335.pdf
A14: 2024-07-31 | B14: 2024년 12월 결산기 ２분기 결산단신 | C14: https://www2.jpx.co.jp/disc/52570/140120240730557856.pdf
... A19: 2023-04-28 | B19: 2023년 12월 결산기 １분기 결산단신 | C19: https://www2.jpx.co.jp/disc/52570/140120230426553659.pdf

Sheet 재무제표 한눈에 보기
A1: 5257 재무제표 한눈에 보기 — 최근 40개 분기(달력 분기, 3Q26 = 26.7~9) · 단위 억 엔
A2: 출처: 매출·영업이익 결산단신 XBRL · 재무상태표 등 결산단신 XBRL 16건(2023-04-28~2026-10-30). 부문·지역·수주·수출은 있을 때만(출처는 줄 끝). 총 차입금 = 이자 붙는 부채 전부(단기·장기 차입금, CP, 사채·전환사채, 리스부채)
A4: 항목 | B4: 4Q16 | C4: 1Q17 | D4: 2Q17 | E4: 3Q17 | F4: 4Q17 | G4: 1Q18 | H4: 2Q18 | I4: 3Q18 | J4: 4Q18 | K4: 1Q19 | L4: 2Q19 | M4: 3Q19 | N4: 4Q19 | O4: 1Q20 | P4: 2Q20 | Q4: 3Q20 | R4: 4Q20 | S4: 1Q21 | T4: 2Q21 | U4: 3Q21 | V4: 4Q21 | W4: 1Q22 | X4: 2Q22 | Y4: 3Q22 | Z4: 4Q22 | AA4: 1Q23 | AB4: 2Q23 | AC4: 3Q23 | AD4: 4Q23 | AE4: 1Q24 | AF4: 2Q24 | AG4: 3Q24 | AH4: 4Q24 | AI4: 1Q25 | AJ4: 2Q25 | AK4: 3Q25 | AL4: 4Q25 | AM4: 1Q26 | AN4: 2Q26 | AO4: 3Q26 | AP4: 출처
A5: 매출액 | Z5: 12.8 | AA5: 13.3 | AB5: 12.6 | AC5: 14.1 | AD5: 14.3 | AE5: 15.8 | AF5: 15.1 | AG5: 16.5 | AH5: 17.2 | AI5: 16.8 | AJ5: 16.2 | AK5: 16.9 | AL5: 17.3 | AM5: 17.2 | AN5: 18 | AO5: 18.6
A6: 매출액 YoY | AD6: 11.7 | AE6: 18.8 | AF6: 19.8 | AG6: 17 | AH6: 20.3 | AI6: 6.3 | AJ6: 7.3 | AK6: 2.4 | AL6: 0.6 | AM6: 2.4 | AN6: 11.1 | AO6: 10.1
A7: 영업이익 | Z7: 1.4 | AA7: 1.7 | AB7: 0.7 | AC7: 1.6 | AD7: 1 | AE7: 1.6 | AF7: 0.5 | AG7: 1.2 | AH7: 2 | AI7: 1 | AJ7: -0.1 | AK7: 0.7 | AL7: 1.6 | AM7: 1.2 | AN7: 1.5 | AO7: 1.6
A8: 영업이익률 | Z8: 10.9 | AA8: 12.8 | AB8: 5.6 | AC8: 11.3 | AD8: 7 | AE8: 10.1 | AF8: 3.3 | AG8: 7.3 | AH8: 11.6 | AI8: 6 | AJ8: -0.6 | AK8: 4.1 | AL8: 9.2 | AM8: 7 | AN8: 8.3 | AO8: 8.6
A9: 영업이익 YoY | AD9: -28.6 | AE9: -5.9 | AF9: -28.6 | AG9: -25 | AH9: 100 | AI9: -37.5 | AJ9: -120 | AK9: -41.7 | AL9: -20 | AM9: 20 | AO9: 128.6
A10: 유동자산 | Z10: 14.9 | AA10: 19.5 | AB10: 18.4 | AC10: 19.3 | AD10: 19.8 | AE10: 22.4 | AF10: 21.8 | AG10: 21.2 | AH10: 21.9 | AI10: 24.5 | AJ10: 19.8 | AK10: 19.3 | AL10: 19.9 | AM10: 22.3 | AN10: 20.5 | AO10: 20.3
A11: 유동부채 | Z11: 10.6 | AA11: 9.9 | AB11: 8.8 | AC11: 10 | AD11: 9.8 | AE11: 11 | AF11: 10.5 | AG11: 9.9 | AH11: 10.4 | AI11: 11.1 | AJ11: 10.3 | AK11: 10.6 | AL11: 10.4 | AM11: 12.3 | AN11: 11.4 | AO11: 12
A12: 부채총계 | Z12: 16.2 | AA12: 18.4 | AB12: 16.8 | AC12: 16.6 | AD12: 15.9 | AE12: 17.3 | AF12: 16.1 | AG12: 14.7 | AH12: 15 | AI12: 17.3 | AJ12: 16.8 | AK12: 15.8 | AL12: 15.4 | AM12: 18.9 | AN12: 17.4 | AO12: 16.8
A13: 자기자본 | Z13: 11.6 | AA13: 15 | AB13: 16.4 | AC13: 17.3 | AD13: 18 | AE13: 19.2 | AF13: 19.4 | AG13: 20.6 | AH13: 22.3 | AI13: 23.1 | AJ13: 23.6 | AK13: 24.1 | AL13: 25.5 | AM13: 23.5 | AN13: 24.3 | AO13: 25.2
A14: 유동비율 | Z14: 140.6 | AA14: 197 | AB14: 209.1 | AC14: 193 | AD14: 202 | AE14: 203.6 | AF14: 207.6 | AG14: 214.1 | AH14: 210.6 | AI14: 220.7 | AJ14: 192.2 | AK14: 182.1 | AL14: 191.3 | AM14: 181.3 | AN14: 179.8 | AO14: 169.2
A15: 부채비율 | Z15: 139.7 | AA15: 122.7 | AB15: 102.4 | AC15: 96 | AD15: 88.3 | AE15: 90.1 | AF15: 83 | AG15: 71.4 | AH15: 67.3 | AI15: 74.9 | AJ15: 71.2 | AK15: 65.6 | AL15: 60.4 | AM15: 80.4 | AN15: 71.6 | AO15: 66.7
A16: 순차입금/자기자본 | Z16: 23.3 | AA16: 8 | AB16: 10.4 | AC16: 4 | AD16: -0.6 | AE16: -2.6 | AF16: -4.6 | AG16: -7.8 | AH16: -5.8 | AI16: -14.7 | AJ16: 13.6 | AK16: 2.9 | AL16: -1.6 | AM16: -2.1 | AN16: 0.8 | AO16: 2.4
A17: 재고자산 | Z17: 0.4 | AA17: 0.3 | AB17: 0.4 | AC17: 0.4 | AD17: 0.3 | AE17: 0.3 | AF17: 0.2 | AG17: 0.2 | AH17: 0.1 | AI17: 0.1 | AJ17: 0.1 | AK17: 0.2 | AL17: 0.2 | AM17: 0.3 | AN17: 0.3 | AO17: 0.3
A18: 재고자산 회전일수 | Z18: 4 | AA18: 3 | AB18: 4 | AC18: 3 | AD18: 2 | AE18: 2 | AF18: 2 | AG18: 1 | AH18: 1 | AI18: 1 | AJ18: 1 | AK18: 1 | AL18: 1 | AM18: 2 | AN18: 2 | AO18: 2
A19: 매출채권 회전일수 | Z19: 55 | AA19: 55 | AB19: 61 | AC19: 61 | AD19: 65 | AE19: 69 | AF19: 72 | AG19: 67 | AH19: 72 | AI19: 61 | AJ19: 75 | AK19: 61 | AL19: 63 | AM19: 56 | AN19: 55 | AO19: 58
A20: 매입채무 회전일수 | Z20: 11 | AA20: 13 | AB20: 12 | AC20: 12 | AD20: 13 | AE20: 17 | AF20: 15 | AG20: 14 | AH20: 15 | AI20: 14 | AJ20: 15 | AK20: 12 | AL20: 13 | AM20: 12 | AN20: 13 | AO20: 13
A21: 현금전환주기(CCC) | Z21: 48 | AA21: 45 | AB21: 53 | AC21: 52 | AD21: 54 | AE21: 54 | AF21: 59 | AG21: 54 | AH21: 58 | AI21: 48 | AJ21: 61 | AK21: 50 | AL21: 51 | AM21: 46 | AN21: 44 | AO21: 47
... A23: 현금 | Z23: 6.3 | AA23: 10.7 | AB23: 9.3 | AC23: 9.2 | AD23: 9 | AE23: 10 | AF23: 9.3 | AG23: 8.7 | AH23: 7.6 | AI23: 12.6 | AJ23: 5.9 | AK23: 7.2 | AL23: 7.3 | AM23: 11.1 | AN23: 9 | AO23: 7.4
