Workbook

Sheet 연간
A1: 5532 Model
A2: 모를 땐 보수적으로 | B2: (단위: 백만엔) | C2: 9월 결산 · 일본 기준 · 2026.3Q = 2026년 9월 결산기 3분기 | Y2: (추정: 파란 글씨 = 직접 입력)
A3: 항목 | B3: 참고 | C3: 2023.4Q | D3: 2024.1Q | E3: 2024.2Q | F3: 2024.3Q | G3: 2024.4Q | H3: 2025.1Q | I3: 2025.2Q | J3: 2025.3Q | K3: 2025.4Q | L3: 2026.1Q | M3: 2026.2Q | N3: 2026.3Q | O3: 2016 | P3: 2017 | Q3: 2018 | R3: 2019 | S3: 2020 | T3: 2021 | U3: 2022 | V3: 2023 | W3: 2024 | X3: 2025 | Y3: 2026(MW) | Z3: 2027(MW) | AA3: 2028(MW) | AB3: 2029(MW) | AC3: 2030(MW)
A4: 매출액 | B4: MW 직접 입력 | C4: 1757.173 | D4: 2588.383 | E4: 2425.441 | F4: 1457.637 | G4: 1477.025 | H4: 2816.632 | I4: 3569.23 | J4: 1774.488 | K4: 1631.648 | L4: 3951.287 | M4: 1721.978 | N4: 2036.119 | U4: 5843.209 | V4: 6972.224 | W4: 7948.486 | X4: 9791.998 | Y4: =IF(COUNT(Y7)=0,"",SUM(Y7)) | Z4: =IF(COUNT(Z7)=0,"",SUM(Z7)) | AA4: =IF(COUNT(AA7)=0,"",SUM(AA7)) | AB4: =IF(COUNT(AB7)=0,"",SUM(AB7)) | AC4: =IF(COUNT(AC7)=0,"",SUM(AC7))
A5: YoY | G5: =IF(OR(G4="",C4=""),"",IFERROR(G4/C4-1,"")) | H5: =IF(OR(H4="",D4=""),"",IFERROR(H4/D4-1,"")) | I5: =IF(OR(I4="",E4=""),"",IFERROR(I4/E4-1,"")) | J5: =IF(OR(J4="",F4=""),"",IFERROR(J4/F4-1,"")) | K5: =IF(OR(K4="",G4=""),"",IFERROR(K4/G4-1,"")) | L5: =IF(OR(L4="",H4=""),"",IFERROR(L4/H4-1,"")) | M5: =IF(OR(M4="",I4=""),"",IFERROR(M4/I4-1,"")) | N5: =IF(OR(N4="",J4=""),"",IFERROR(N4/J4-1,"")) | P5: =IF(OR(P4="",O4=""),"",IFERROR(P4/O4-1,"")) | Q5: =IF(OR(Q4="",P4=""),"",IFERROR(Q4/P4-1,"")) | R5: =IF(OR(R4="",Q4=""),"",IFERROR(R4/Q4-1,"")) | S5: =IF(OR(S4="",R4=""),"",IFERROR(S4/R4-1,"")) | T5: =IF(OR(T4="",S4=""),"",IFERROR(T4/S4-1,"")) | U5: =IF(OR(U4="",T4=""),"",IFERROR(U4/T4-1,"")) | V5: =IF(OR(V4="",U4=""),"",IFERROR(V4/U4-1,"")) | W5: =IF(OR(W4="",V4=""),"",IFERROR(W4/V4-1,"")) | ... AC5: =IF(OR(AC4="",AB4=""),"",IFERROR(AC4/AB4-1,""))
A6: 제품별 매출 분류 | B6: 사업보고서 매출실적
A7: (제품별 매출 미공시 — 직접 입력)
A8: 비중 | C8: =IF(OR(C7="",C4=""),"",IFERROR(C7/C4,"")) | D8: =IF(OR(D7="",D4=""),"",IFERROR(D7/D4,"")) | E8: =IF(OR(E7="",E4=""),"",IFERROR(E7/E4,"")) | F8: =IF(OR(F7="",F4=""),"",IFERROR(F7/F4,"")) | G8: =IF(OR(G7="",G4=""),"",IFERROR(G7/G4,"")) | H8: =IF(OR(H7="",H4=""),"",IFERROR(H7/H4,"")) | I8: =IF(OR(I7="",I4=""),"",IFERROR(I7/I4,"")) | J8: =IF(OR(J7="",J4=""),"",IFERROR(J7/J4,"")) | ... AC8: =IF(OR(AC7="",AC4=""),"",IFERROR(AC7/AC4,""))
A9: YoY | G9: =IF(OR(G7="",C7=""),"",IFERROR(G7/C7-1,"")) | H9: =IF(OR(H7="",D7=""),"",IFERROR(H7/D7-1,"")) | I9: =IF(OR(I7="",E7=""),"",IFERROR(I7/E7-1,"")) | J9: =IF(OR(J7="",F7=""),"",IFERROR(J7/F7-1,"")) | K9: =IF(OR(K7="",G7=""),"",IFERROR(K7/G7-1,"")) | L9: =IF(OR(L7="",H7=""),"",IFERROR(L7/H7-1,"")) | M9: =IF(OR(M7="",I7=""),"",IFERROR(M7/I7-1,"")) | N9: =IF(OR(N7="",J7=""),"",IFERROR(N7/J7-1,"")) | P9: =IF(OR(P7="",O7=""),"",IFERROR(P7/O7-1,"")) | Q9: =IF(OR(Q7="",P7=""),"",IFERROR(Q7/P7-1,"")) | R9: =IF(OR(R7="",Q7=""),"",IFERROR(R7/Q7-1,"")) | S9: =IF(OR(S7="",R7=""),"",IFERROR(S7/R7-1,"")) | T9: =IF(OR(T7="",S7=""),"",IFERROR(T7/S7-1,"")) | U9: =IF(OR(U7="",T7=""),"",IFERROR(U7/T7-1,"")) | V9: =IF(OR(V7="",U7=""),"",IFERROR(V7/U7-1,"")) | W9: =IF(OR(W7="",V7=""),"",IFERROR(W7/V7-1,"")) | ... AC9: =IF(OR(AC7="",AB7=""),"",IFERROR(AC7/AB7-1,""))
A10: 매출원가
A11: 전체 매출원가 | C11: 1591.928 | D11: 2201.369 | E11: 1847.602 | F11: 1286.301 | G11: 1320.913 | H11: 2410.547 | I11: 2861.804 | J11: 1429.712 | K11: 1412.849 | L11: 2837.032 | M11: 1414.472 | N11: 1720.312 | U11: 5054.53 | V11: 5988.986 | W11: 6656.185 | X11: 8114.912
A12: 매출총이익 | C12: =IF(OR(C4="",C11=""),"",IFERROR(C4-C11,"")) | D12: =IF(OR(D4="",D11=""),"",IFERROR(D4-D11,"")) | E12: =IF(OR(E4="",E11=""),"",IFERROR(E4-E11,"")) | F12: =IF(OR(F4="",F11=""),"",IFERROR(F4-F11,"")) | G12: =IF(OR(G4="",G11=""),"",IFERROR(G4-G11,"")) | H12: =IF(OR(H4="",H11=""),"",IFERROR(H4-H11,"")) | I12: =IF(OR(I4="",I11=""),"",IFERROR(I4-I11,"")) | J12: =IF(OR(J4="",J11=""),"",IFERROR(J4-J11,"")) | ... X12: =IF(OR(X4="",X11=""),"",IFERROR(X4-X11,""))
A13: GPM | C13: =IF(OR(C12="",C4=""),"",IFERROR(C12/C4,"")) | D13: =IF(OR(D12="",D4=""),"",IFERROR(D12/D4,"")) | E13: =IF(OR(E12="",E4=""),"",IFERROR(E12/E4,"")) | F13: =IF(OR(F12="",F4=""),"",IFERROR(F12/F4,"")) | G13: =IF(OR(G12="",G4=""),"",IFERROR(G12/G4,"")) | H13: =IF(OR(H12="",H4=""),"",IFERROR(H12/H4,"")) | I13: =IF(OR(I12="",I4=""),"",IFERROR(I12/I4,"")) | J13: =IF(OR(J12="",J4=""),"",IFERROR(J12/J4,"")) | ... AC13: =IF(OR(AC12="",AC4=""),"",IFERROR(AC12/AC4,""))
A14: 판매관리비
A15: 전체 판관비 | C15: 107.555 | D15: 126.462 | E15: 135.414 | F15: 126.925 | G15: 136.726 | H15: 168.756 | I15: 162.153 | J15: 147.934 | K15: 155.063 | L15: 201.594 | M15: 176.52 | N15: 198.919 | U15: 359.373 | V15: 434.334 | W15: 525.527 | X15: 633.906
A16: 영업이익 | B16: MW = 매출 × OPM | C16: 57.689 | D16: 260.55 | E16: 442.426 | F16: 44.411 | G16: 19.386 | H16: 237.328 | I16: 545.273 | J16: 196.842 | K16: 63.736 | L16: 912.659 | M16: 130.987 | N16: 116.887 | U16: 429.306 | V16: 548.902 | W16: 766.773 | X16: 1043.179 | Y16: =IF(OR(Y4="",Y17=""),"",IFERROR(Y4*Y17,"")) | Z16: =IF(OR(Z4="",Z17=""),"",IFERROR(Z4*Z17,"")) | AA16: =IF(OR(AA4="",AA17=""),"",IFERROR(AA4*AA17,"")) | AB16: =IF(OR(AB4="",AB17=""),"",IFERROR(AB4*AB17,"")) | AC16: =IF(OR(AC4="",AC17=""),"",IFERROR(AC4*AC17,""))
A17: OPM | B17: MW 입력 | C17: =IF(OR(C16="",C4=""),"",IFERROR(C16/C4,"")) | D17: =IF(OR(D16="",D4=""),"",IFERROR(D16/D4,"")) | E17: =IF(OR(E16="",E4=""),"",IFERROR(E16/E4,"")) | F17: =IF(OR(F16="",F4=""),"",IFERROR(F16/F4,"")) | G17: =IF(OR(G16="",G4=""),"",IFERROR(G16/G4,"")) | H17: =IF(OR(H16="",H4=""),"",IFERROR(H16/H4,"")) | I17: =IF(OR(I16="",I4=""),"",IFERROR(I16/I4,"")) | J17: =IF(OR(J16="",J4=""),"",IFERROR(J16/J4,"")) | ... X17: =IF(OR(X16="",X4=""),"",IFERROR(X16/X4,""))
A18: 증가율 | G18: =IF(OR(G16="",C16=""),"",IFERROR(G16/C16-1,"")) | H18: =IF(OR(H16="",D16=""),"",IFERROR(H16/D16-1,"")) | I18: =IF(OR(I16="",E16=""),"",IFERROR(I16/E16-1,"")) | J18: =IF(OR(J16="",F16=""),"",IFERROR(J16/F16-1,"")) | K18: =IF(OR(K16="",G16=""),"",IFERROR(K16/G16-1,"")) | L18: =IF(OR(L16="",H16=""),"",IFERROR(L16/H16-1,"")) | M18: =IF(OR(M16="",I16=""),"",IFERROR(M16/I16-1,"")) | N18: =IF(OR(N16="",J16=""),"",IFERROR(N16/J16-1,"")) | P18: =IF(OR(P16="",O16=""),"",IFERROR(P16/O16-1,"")) | Q18: =IF(OR(Q16="",P16=""),"",IFERROR(Q16/P16-1,"")) | R18: =IF(OR(R16="",Q16=""),"",IFERROR(R16/Q16-1,"")) | S18: =IF(OR(S16="",R16=""),"",IFERROR(S16/R16-1,"")) | T18: =IF(OR(T16="",S16=""),"",IFERROR(T16/S16-1,"")) | U18: =IF(OR(U16="",T16=""),"",IFERROR(U16/T16-1,"")) | V18: =IF(OR(V16="",U16=""),"",IFERROR(V16/U16-1,"")) | W18: =IF(OR(W16="",V16=""),"",IFERROR(W16/V16-1,"")) | ... AC18: =IF(OR(AC16="",AB16=""),"",IFERROR(AC16/AB16-1,""))
A19: 비용의 성격별 분류 | B19: 참고 데이터
A20: 총 판관비 | O20: =IF(O15="","",O15) | P20: =IF(P15="","",P15) | Q20: =IF(Q15="","",Q15) | R20: =IF(R15="","",R15) | S20: =IF(S15="","",S15) | T20: =IF(T15="","",T15) | U20: =IF(U15="","",U15) | V20: =IF(V15="","",V15) | ... X20: =IF(X15="","",X15)
A21: 급여 | B21: 고정비
A22: % of Sales | O22: =IF(OR(O21="",O4=""),"",IFERROR(O21/O4,"")) | P22: =IF(OR(P21="",P4=""),"",IFERROR(P21/P4,"")) | Q22: =IF(OR(Q21="",Q4=""),"",IFERROR(Q21/Q4,"")) | R22: =IF(OR(R21="",R4=""),"",IFERROR(R21/R4,"")) | S22: =IF(OR(S21="",S4=""),"",IFERROR(S21/S4,"")) | T22: =IF(OR(T21="",T4=""),"",IFERROR(T21/T4,"")) | U22: =IF(OR(U21="",U4=""),"",IFERROR(U21/U4,"")) | V22: =IF(OR(V21="",V4=""),"",IFERROR(V21/V4,"")) | ... X22: =IF(OR(X21="",X4=""),"",IFERROR(X21/X4,""))
A23: 감가상각비 | B23: 고정비
A24: % of Sales | O24: =IF(OR(O23="",O4=""),"",IFERROR(O23/O4,"")) | P24: =IF(OR(P23="",P4=""),"",IFERROR(P23/P4,"")) | Q24: =IF(OR(Q23="",Q4=""),"",IFERROR(Q23/Q4,"")) | R24: =IF(OR(R23="",R4=""),"",IFERROR(R23/R4,"")) | S24: =IF(OR(S23="",S4=""),"",IFERROR(S23/S4,"")) | T24: =IF(OR(T23="",T4=""),"",IFERROR(T23/T4,"")) | U24: =IF(OR(U23="",U4=""),"",IFERROR(U23/U4,"")) | V24: =IF(OR(V23="",V4=""),"",IFERROR(V23/V4,"")) | ... X24: =IF(OR(X23="",X4=""),"",IFERROR(X23/X4,""))
A25: 지급수수료 | B25: 고정비
A26: % of Sales | O26: =IF(OR(O25="",O4=""),"",IFERROR(O25/O4,"")) | P26: =IF(OR(P25="",P4=""),"",IFERROR(P25/P4,"")) | Q26: =IF(OR(Q25="",Q4=""),"",IFERROR(Q25/Q4,"")) | R26: =IF(OR(R25="",R4=""),"",IFERROR(R25/R4,"")) | S26: =IF(OR(S25="",S4=""),"",IFERROR(S25/S4,"")) | T26: =IF(OR(T25="",T4=""),"",IFERROR(T25/T4,"")) | U26: =IF(OR(U25="",U4=""),"",IFERROR(U25/U4,"")) | V26: =IF(OR(V25="",V4=""),"",IFERROR(V25/V4,"")) | ... X26: =IF(OR(X25="",X4=""),"",IFERROR(X25/X4,""))
A27: 연구개발비 | B27: 변동비
A28: % of Sales | O28: =IF(OR(O27="",O4=""),"",IFERROR(O27/O4,"")) | P28: =IF(OR(P27="",P4=""),"",IFERROR(P27/P4,"")) | Q28: =IF(OR(Q27="",Q4=""),"",IFERROR(Q27/Q4,"")) | R28: =IF(OR(R27="",R4=""),"",IFERROR(R27/R4,"")) | S28: =IF(OR(S27="",S4=""),"",IFERROR(S27/S4,"")) | T28: =IF(OR(T27="",T4=""),"",IFERROR(T27/T4,"")) | U28: =IF(OR(U27="",U4=""),"",IFERROR(U27/U4,"")) | V28: =IF(OR(V27="",V4=""),"",IFERROR(V27/V4,"")) | ... X28: =IF(OR(X27="",X4=""),"",IFERROR(X27/X4,""))
A29: 기타비용 | B29: 변동비 | O29: =IF(OR(O20="",O21="",O23="",O25="",O27=""),"",IFERROR(O20-O21-O23-O25-O27,"")) | P29: =IF(OR(P20="",P21="",P23="",P25="",P27=""),"",IFERROR(P20-P21-P23-P25-P27,"")) | Q29: =IF(OR(Q20="",Q21="",Q23="",Q25="",Q27=""),"",IFERROR(Q20-Q21-Q23-Q25-Q27,"")) | R29: =IF(OR(R20="",R21="",R23="",R25="",R27=""),"",IFERROR(R20-R21-R23-R25-R27,"")) | S29: =IF(OR(S20="",S21="",S23="",S25="",S27=""),"",IFERROR(S20-S21-S23-S25-S27,"")) | T29: =IF(OR(T20="",T21="",T23="",T25="",T27=""),"",IFERROR(T20-T21-T23-T25-T27,"")) | U29: =IF(OR(U20="",U21="",U23="",U25="",U27=""),"",IFERROR(U20-U21-U23-U25-U27,"")) | V29: =IF(OR(V20="",V21="",V23="",V25="",V27=""),"",IFERROR(V20-V21-V23-V25-V27,"")) | ... X29: =IF(OR(X20="",X21="",X23="",X25="",X27=""),"",IFERROR(X20-X21-X23-X25-X27,""))
A30: % of Sales | O30: =IF(OR(O29="",O4=""),"",IFERROR(O29/O4,"")) | P30: =IF(OR(P29="",P4=""),"",IFERROR(P29/P4,"")) | Q30: =IF(OR(Q29="",Q4=""),"",IFERROR(Q29/Q4,"")) | R30: =IF(OR(R29="",R4=""),"",IFERROR(R29/R4,"")) | S30: =IF(OR(S29="",S4=""),"",IFERROR(S29/S4,"")) | T30: =IF(OR(T29="",T4=""),"",IFERROR(T29/T4,"")) | U30: =IF(OR(U29="",U4=""),"",IFERROR(U29/U4,"")) | V30: =IF(OR(V29="",V4=""),"",IFERROR(V29/V4,"")) | ... X30: =IF(OR(X29="",X4=""),"",IFERROR(X29/X4,""))
A31: 당기순이익 추정
A32: 특별이익 | C32: 5.338 | F32: 0 | G32: 0 | J32: 0 | K32: 0.617 | U32: 0.497 | V32: 5.338 | W32: 9.5 | X32: 0.617 | Y32: =IF(OR(Y4="",Y33=""),"",IFERROR(Y4*Y33,"")) | Z32: =IF(OR(Z4="",Z33=""),"",IFERROR(Z4*Z33,"")) | AA32: =IF(OR(AA4="",AA33=""),"",IFERROR(AA4*AA33,"")) | AB32: =IF(OR(AB4="",AB33=""),"",IFERROR(AB4*AB33,"")) | AC32: =IF(OR(AC4="",AC33=""),"",IFERROR(AC4*AC33,""))
A33: % of Sales | B33: MW = 최근 3년 평균 | C33: =IF(OR(C32="",C4=""),"",IFERROR(C32/C4,"")) | D33: =IF(OR(D32="",D4=""),"",IFERROR(D32/D4,"")) | E33: =IF(OR(E32="",E4=""),"",IFERROR(E32/E4,"")) | F33: =IF(OR(F32="",F4=""),"",IFERROR(F32/F4,"")) | G33: =IF(OR(G32="",G4=""),"",IFERROR(G32/G4,"")) | H33: =IF(OR(H32="",H4=""),"",IFERROR(H32/H4,"")) | I33: =IF(OR(I32="",I4=""),"",IFERROR(I32/I4,"")) | J33: =IF(OR(J32="",J4=""),"",IFERROR(J32/J4,"")) | ... X33: =IF(OR(X32="",X4=""),"",IFERROR(X32/X4,"")) | Y33: =IFERROR(AVERAGE(V33,W33,X33),"") | Z33: =Y33 | AA33: =Z33 | AB33: =AA33 | AC33: =AB33
A34: 특별손실 | C34: 50.757 | F34: 0 | G34: 87.858 | K34: 30.75 | U34: 347.911 | V34: 64.108 | W34: 87.858 | X34: 30.75 | Y34: =IF(OR(Y4="",Y35=""),"",IFERROR(Y4*Y35,"")) | Z34: =IF(OR(Z4="",Z35=""),"",IFERROR(Z4*Z35,"")) | AA34: =IF(OR(AA4="",AA35=""),"",IFERROR(AA4*AA35,"")) | AB34: =IF(OR(AB4="",AB35=""),"",IFERROR(AB4*AB35,"")) | AC34: =IF(OR(AC4="",AC35=""),"",IFERROR(AC4*AC35,""))
A35: % of Sales | C35: =IF(OR(C34="",C4=""),"",IFERROR(C34/C4,"")) | D35: =IF(OR(D34="",D4=""),"",IFERROR(D34/D4,"")) | E35: =IF(OR(E34="",E4=""),"",IFERROR(E34/E4,"")) | F35: =IF(OR(F34="",F4=""),"",IFERROR(F34/F4,"")) | G35: =IF(OR(G34="",G4=""),"",IFERROR(G34/G4,"")) | H35: =IF(OR(H34="",H4=""),"",IFERROR(H34/H4,"")) | I35: =IF(OR(I34="",I4=""),"",IFERROR(I34/I4,"")) | J35: =IF(OR(J34="",J4=""),"",IFERROR(J34/J4,"")) | ... X35: =IF(OR(X34="",X4=""),"",IFERROR(X34/X4,"")) | Y35: =IFERROR(AVERAGE(V35,W35,X35),"") | Z35: =Y35 | AA35: =Z35 | AB35: =AA35 | AC35: =AB35
A36: 영업외수익 | C36: 0.015 | D36: 0 | E36: 0.408 | F36: 1.248 | G36: 0.422 | H36: 0.304 | I36: 1.399 | J36: 1.303 | K36: 3.525 | L36: 0.843 | M36: 1.938 | N36: 0.644 | U36: 0.664 | V36: 1.503 | W36: 2.078 | X36: 6.531 | Y36: =IF(OR(Y4="",Y37=""),"",IFERROR(Y4*Y37,"")) | Z36: =IF(OR(Z4="",Z37=""),"",IFERROR(Z4*Z37,"")) | AA36: =IF(OR(AA4="",AA37=""),"",IFERROR(AA4*AA37,"")) | AB36: =IF(OR(AB4="",AB37=""),"",IFERROR(AB4*AB37,"")) | AC36: =IF(OR(AC4="",AC37=""),"",IFERROR(AC4*AC37,""))
A37: % of Sales | C37: =IF(OR(C36="",C4=""),"",IFERROR(C36/C4,"")) | D37: =IF(OR(D36="",D4=""),"",IFERROR(D36/D4,"")) | E37: =IF(OR(E36="",E4=""),"",IFERROR(E36/E4,"")) | F37: =IF(OR(F36="",F4=""),"",IFERROR(F36/F4,"")) | G37: =IF(OR(G36="",G4=""),"",IFERROR(G36/G4,"")) | H37: =IF(OR(H36="",H4=""),"",IFERROR(H36/H4,"")) | I37: =IF(OR(I36="",I4=""),"",IFERROR(I36/I4,"")) | J37: =IF(OR(J36="",J4=""),"",IFERROR(J36/J4,"")) | ... X37: =IF(OR(X36="",X4=""),"",IFERROR(X36/X4,"")) | Y37: =IFERROR(AVERAGE(V37,W37,X37),"") | Z37: =Y37 | AA37: =Z37 | AB37: =AA37 | AC37: =AB37
A38: 영업외비용 | C38: 15.815 | D38: 13.254 | E38: 42.187 | F38: 54.383 | G38: 29.092 | H38: 50.915 | I38: 40.482 | J38: 45.743 | K38: 85.531 | L38: 75.77 | M38: 95.849 | N38: 121.531 | U38: 42.375 | V38: 65.763 | W38: 138.916 | X38: 222.671 | Y38: =IF(OR(Y4="",Y39=""),"",IFERROR(Y4*Y39,"")) | Z38: =IF(OR(Z4="",Z39=""),"",IFERROR(Z4*Z39,"")) | AA38: =IF(OR(AA4="",AA39=""),"",IFERROR(AA4*AA39,"")) | AB38: =IF(OR(AB4="",AB39=""),"",IFERROR(AB4*AB39,"")) | AC38: =IF(OR(AC4="",AC39=""),"",IFERROR(AC4*AC39,""))
A39: % of Sales | C39: =IF(OR(C38="",C4=""),"",IFERROR(C38/C4,"")) | D39: =IF(OR(D38="",D4=""),"",IFERROR(D38/D4,"")) | E39: =IF(OR(E38="",E4=""),"",IFERROR(E38/E4,"")) | F39: =IF(OR(F38="",F4=""),"",IFERROR(F38/F4,"")) | G39: =IF(OR(G38="",G4=""),"",IFERROR(G38/G4,"")) | H39: =IF(OR(H38="",H4=""),"",IFERROR(H38/H4,"")) | I39: =IF(OR(I38="",I4=""),"",IFERROR(I38/I4,"")) | J39: =IF(OR(J38="",J4=""),"",IFERROR(J38/J4,"")) | ... X39: =IF(OR(X38="",X4=""),"",IFERROR(X38/X4,"")) | Y39: =IFERROR(AVERAGE(V39,W39,X39),"") | Z39: =Y39 | AA39: =Z39 | AB39: =AA39 | AC39: =AB39
A40: 법인세비용차감전순이익(손실) | C40: -3.53 | D40: 247.296 | E40: 410.147 | F40: -8.725 | G40: -97.141 | H40: 186.718 | I40: 506.189 | J40: 152.402 | K40: -48.403 | L40: 837.732 | M40: 37.077 | N40: -24.739 | U40: 40.18 | V40: 425.872 | W40: 551.577 | X40: 796.906 | Y40: =IF(OR(Y16=""),"",IFERROR(Y16+N(Y32)-N(Y34)+N(Y36)-N(Y38),"")) | Z40: =IF(OR(Z16=""),"",IFERROR(Z16+N(Z32)-N(Z34)+N(Z36)-N(Z38),"")) | AA40: =IF(OR(AA16=""),"",IFERROR(AA16+N(AA32)-N(AA34)+N(AA36)-N(AA38),"")) | AB40: =IF(OR(AB16=""),"",IFERROR(AB16+N(AB32)-N(AB34)+N(AB36)-N(AB38),"")) | AC40: =IF(OR(AC16=""),"",IFERROR(AC16+N(AC32)-N(AC34)+N(AC36)-N(AC38),""))
A41: 법인세비용(수익) | C41: -15.159 | D41: 77.654 | E41: 135.715 | F41: -8.12 | G41: -34.041 | H41: 61.89 | I41: 153.608 | J41: 50.889 | K41: -28.702 | L41: 261.47 | M41: 19.365 | N41: 1.284 | U41: 4.08 | V41: 147.278 | W41: 171.208 | X41: 237.685 | Y41: =IF(OR(Y40="",Y42=""),"",IFERROR(MAX(Y40,0)*Y42,"")) | Z41: =IF(OR(Z40="",Z42=""),"",IFERROR(MAX(Z40,0)*Z42,"")) | AA41: =IF(OR(AA40="",AA42=""),"",IFERROR(MAX(AA40,0)*AA42,"")) | AB41: =IF(OR(AB40="",AB42=""),"",IFERROR(MAX(AB40,0)*AB42,"")) | AC41: =IF(OR(AC40="",AC42=""),"",IFERROR(MAX(AC40,0)*AC42,""))
A42: 법인세율 | B42: MW 기본 30% | C42: =IF(OR(C41="",C40=""),"",IFERROR(C41/C40,"")) | D42: =IF(OR(D41="",D40=""),"",IFERROR(D41/D40,"")) | E42: =IF(OR(E41="",E40=""),"",IFERROR(E41/E40,"")) | F42: =IF(OR(F41="",F40=""),"",IFERROR(F41/F40,"")) | G42: =IF(OR(G41="",G40=""),"",IFERROR(G41/G40,"")) | H42: =IF(OR(H41="",H40=""),"",IFERROR(H41/H40,"")) | I42: =IF(OR(I41="",I40=""),"",IFERROR(I41/I40,"")) | J42: =IF(OR(J41="",J40=""),"",IFERROR(J41/J40,"")) | ... X42: =IF(OR(X41="",X40=""),"",IFERROR(X41/X40,"")) | Y42: 0.3 | Z42: 0.3 | AA42: 0.3 | AB42: 0.3 | AC42: 0.3
A43: 당기순이익(손실) | C43: 11.629 | D43: 169.642 | E43: 274.431 | F43: -0.604 | G43: -63.101 | H43: 124.827 | I43: 352.581 | J43: 101.514 | K43: -19.702 | L43: 576.261 | M43: 17.712 | N43: -26.023 | U43: 36.099 | V43: 278.593 | W43: 380.368 | X43: 559.22 | Y43: =IF(OR(Y40=""),"",IFERROR(Y40-Y41,"")) | Z43: =IF(OR(Z40=""),"",IFERROR(Z40-Z41,"")) | AA43: =IF(OR(AA40=""),"",IFERROR(AA40-AA41,"")) | AB43: =IF(OR(AB40=""),"",IFERROR(AB40-AB41,"")) | AC43: =IF(OR(AC40=""),"",IFERROR(AC40-AC41,""))
A44: 지배주주 순이익 | C44: 11.629 | D44: 169.642 | E44: 274.431 | F44: -0.604 | G44: -63.101 | H44: 124.827 | I44: 352.581 | J44: 101.514 | K44: -19.702 | L44: 576.261 | M44: 17.712 | N44: -26.023 | U44: 36.099 | V44: 278.593 | W44: 380.368 | X44: 559.22 | Y44: =IF(OR(Y43="",Y45=""),"",IFERROR(Y43*Y45,"")) | Z44: =IF(OR(Z43="",Z45=""),"",IFERROR(Z43*Z45,"")) | AA44: =IF(OR(AA43="",AA45=""),"",IFERROR(AA43*AA45,"")) | AB44: =IF(OR(AB43="",AB45=""),"",IFERROR(AB43*AB45,"")) | AC44: =IF(OR(AC43="",AC45=""),"",IFERROR(AC43*AC45,""))
A45: 지배주주 순이익률 | B45: MW 기본 100% | C45: =IF(OR(C44="",C43=""),"",IFERROR(C44/C43,"")) | D45: =IF(OR(D44="",D43=""),"",IFERROR(D44/D43,"")) | E45: =IF(OR(E44="",E43=""),"",IFERROR(E44/E43,"")) | F45: =IF(OR(F44="",F43=""),"",IFERROR(F44/F43,"")) | G45: =IF(OR(G44="",G43=""),"",IFERROR(G44/G43,"")) | H45: =IF(OR(H44="",H43=""),"",IFERROR(H44/H43,"")) | I45: =IF(OR(I44="",I43=""),"",IFERROR(I44/I43,"")) | J45: =IF(OR(J44="",J43=""),"",IFERROR(J44/J43,"")) | ... X45: =IF(OR(X44="",X43=""),"",IFERROR(X44/X43,"")) | Y45: 1 | Z45: 1 | AA45: 1 | AB45: 1 | AC45: 1
A46: 목표주가 산출
A47: 현재 주가 ()
A48: 발행주식수 (보통주)
A49: 시가총액 (백만엔) | B49: =IF(OR(B47="",B48=""),"",B47*B48/1000000.0)
A50: OPM | O50: =IF(O17="","",O17) | P50: =IF(P17="","",P17) | Q50: =IF(Q17="","",Q17) | R50: =IF(R17="","",R17) | S50: =IF(S17="","",S17) | T50: =IF(T17="","",T17) | U50: =IF(U17="","",U17) | V50: =IF(V17="","",V17) | ... AC50: =IF(AC17="","",AC17)
A51: 지배주주 순이익 증가율 | P51: =IF(OR(P44="",O44=""),"",IFERROR(P44/O44-1,"")) | Q51: =IF(OR(Q44="",P44=""),"",IFERROR(Q44/P44-1,"")) | R51: =IF(OR(R44="",Q44=""),"",IFERROR(R44/Q44-1,"")) | S51: =IF(OR(S44="",R44=""),"",IFERROR(S44/R44-1,"")) | T51: =IF(OR(T44="",S44=""),"",IFERROR(T44/S44-1,"")) | U51: =IF(OR(U44="",T44=""),"",IFERROR(U44/T44-1,"")) | V51: =IF(OR(V44="",U44=""),"",IFERROR(V44/U44-1,"")) | W51: =IF(OR(W44="",V44=""),"",IFERROR(W44/V44-1,"")) | ... AC51: =IF(OR(AC44="",AB44=""),"",IFERROR(AC44/AB44-1,""))
A52: P/E (현재 주가) | B52: 시총 ÷ 지배순이익 | X52: =IF(OR($B$49="",X44=""),"",IFERROR($B$49/X44,"")) | Y52: =IF(OR($B$49="",Y44=""),"",IFERROR($B$49/Y44,"")) | Z52: =IF(OR($B$49="",Z44=""),"",IFERROR($B$49/Z44,"")) | AA52: =IF(OR($B$49="",AA44=""),"",IFERROR($B$49/AA44,"")) | AB52: =IF(OR($B$49="",AB44=""),"",IFERROR($B$49/AB44,"")) | AC52: =IF(OR($B$49="",AC44=""),"",IFERROR($B$49/AC44,""))
A53: Target P/E | B53: 직접 입력
A54: EPS | B54: 지배순이익 ÷ 주식수 | O54: =IF(OR(O44="",$B$48=""),"",IFERROR(O44*1000000.0/$B$48,"")) | P54: =IF(OR(P44="",$B$48=""),"",IFERROR(P44*1000000.0/$B$48,"")) | Q54: =IF(OR(Q44="",$B$48=""),"",IFERROR(Q44*1000000.0/$B$48,"")) | R54: =IF(OR(R44="",$B$48=""),"",IFERROR(R44*1000000.0/$B$48,"")) | S54: =IF(OR(S44="",$B$48=""),"",IFERROR(S44*1000000.0/$B$48,"")) | T54: =IF(OR(T44="",$B$48=""),"",IFERROR(T44*1000000.0/$B$48,"")) | U54: =IF(OR(U44="",$B$48=""),"",IFERROR(U44*1000000.0/$B$48,"")) | V54: =IF(OR(V44="",$B$48=""),"",IFERROR(V44*1000000.0/$B$48,"")) | ... AC54: =IF(OR(AC44="",$B$48=""),"",IFERROR(AC44*1000000.0/$B$48,""))
A55: 목표주가 | Y55: =IF(OR(Y54="",Y53=""),"",IFERROR(Y54*Y53,"")) | Z55: =IF(OR(Z54="",Z53=""),"",IFERROR(Z54*Z53,"")) | AA55: =IF(OR(AA54="",AA53=""),"",IFERROR(AA54*AA53,"")) | AB55: =IF(OR(AB54="",AB53=""),"",IFERROR(AB54*AB53,"")) | AC55: =IF(OR(AC54="",AC53=""),"",IFERROR(AC54*AC53,""))
A56: 상승여력 | Y56: =IF(OR(Y55="",$B$47=""),"",IFERROR(Y55/$B$47-1,"")) | Z56: =IF(OR(Z55="",$B$47=""),"",IFERROR(Z55/$B$47-1,"")) | AA56: =IF(OR(AA55="",$B$47=""),"",IFERROR(AA55/$B$47-1,"")) | AB56: =IF(OR(AB55="",$B$47=""),"",IFERROR(AB55/$B$47-1,"")) | AC56: =IF(OR(AC55="",$B$47=""),"",IFERROR(AC55/$B$47-1,""))
A57: 자산가치 산출 | B57: 최신 분기 BS
A58: 현금및현금성자산 | X58: ='재무상태표'!G6 | Y58: ='재무상태표'!G6 | Z58: ='재무상태표'!G6 | AA58: ='재무상태표'!G6 | AB58: ='재무상태표'!G6 | AC58: ='재무상태표'!G6
A59: 단기금융상품 | X59: ='재무상태표'!G7 | Y59: ='재무상태표'!G7 | Z59: ='재무상태표'!G7 | AA59: ='재무상태표'!G7 | AB59: ='재무상태표'!G7 | AC59: ='재무상태표'!G7
A60: 투자부동산 | X60: ='재무상태표'!G14 | Y60: ='재무상태표'!G14 | Z60: ='재무상태표'!G14 | AA60: ='재무상태표'!G14 | AB60: ='재무상태표'!G14 | AC60: ='재무상태표'!G14
A61: 지배자본 | X61: ='재무상태표'!G31 | Y61: ='재무상태표'!G31 | Z61: ='재무상태표'!G31 | AA61: ='재무상태표'!G31 | AB61: ='재무상태표'!G31 | AC61: ='재무상태표'!G31
A62: 부채 | X62: ='재무상태표'!G27 | Y62: ='재무상태표'!G27 | Z62: ='재무상태표'!G27 | AA62: ='재무상태표'!G27 | AB62: ='재무상태표'!G27 | AC62: ='재무상태표'!G27
A63: 부채비율 | X63: =IF(OR(X62="",X61=""),"",IFERROR(X62/X61,"")) | Y63: =IF(OR(Y62="",Y61=""),"",IFERROR(Y62/Y61,"")) | Z63: =IF(OR(Z62="",Z61=""),"",IFERROR(Z62/Z61,"")) | AA63: =IF(OR(AA62="",AA61=""),"",IFERROR(AA62/AA61,"")) | AB63: =IF(OR(AB62="",AB61=""),"",IFERROR(AB62/AB61,"")) | AC63: =IF(OR(AC62="",AC61=""),"",IFERROR(AC62/AC61,""))
A64: 자산가치 | B64: 현금+단기금융+투자부동산 | X64: =SUM(X58,X59,X60) | Y64: =SUM(Y58,Y59,Y60) | Z64: =SUM(Z58,Z59,Z60) | AA64: =SUM(AA58,AA59,AA60) | AB64: =SUM(AB58,AB59,AB60) | AC64: =SUM(AC58,AC59,AC60)
A65: 기업가치 산출
A66: 목표 시가총액 (P/E) | B66: 지배순이익 × Target P/E | Y66: =IF(OR(Y44="",Y53=""),"",IFERROR(Y44*Y53,"")) | Z66: =IF(OR(Z44="",Z53=""),"",IFERROR(Z44*Z53,"")) | AA66: =IF(OR(AA44="",AA53=""),"",IFERROR(AA44*AA53,"")) | AB66: =IF(OR(AB44="",AB53=""),"",IFERROR(AB44*AB53,"")) | AC66: =IF(OR(AC44="",AC53=""),"",IFERROR(AC44*AC53,""))
A67: 기업가치 | B67: 목표시총 + 자산가치 | Y67: =IF(OR(Y66=""),"",IFERROR(Y66+Y64,"")) | Z67: =IF(OR(Z66=""),"",IFERROR(Z66+Z64,"")) | AA67: =IF(OR(AA66=""),"",IFERROR(AA66+AA64,"")) | AB67: =IF(OR(AB66=""),"",IFERROR(AB66+AB64,"")) | AC67: =IF(OR(AC66=""),"",IFERROR(AC66+AC64,""))
A68: 현재 시가총액 | Y68: =$B$49 | Z68: =$B$49 | AA68: =$B$49 | AB68: =$B$49 | AC68: =$B$49
A69: 상승여력 | Y69: =IF(OR(Y67="",Y68=""),"",IFERROR(Y67/Y68-1,"")) | Z69: =IF(OR(Z67="",Z68=""),"",IFERROR(Z67/Z68-1,"")) | AA69: =IF(OR(AA67="",AA68=""),"",IFERROR(AA67/AA68-1,"")) | AB69: =IF(OR(AB67="",AB68=""),"",IFERROR(AB67/AB68-1,"")) | AC69: =IF(OR(AC67="",AC68=""),"",IFERROR(AC67/AC68-1,""))
A71: 출처
A72: 결산단신 XBRL(TDnet·JPX 보관소) — 쓴 문서는 '출처' 시트
A73: 분기 = 누계에서 앞 분기를 뺀 3개월 값
A74: 주가: 야후 파이낸스 일봉
A76: 손익계산서 · 전 항목 | B76: 분기 = 3개월 단독
A77: 항목 | B77: 참고 | C77: 2023.4Q | D77: 2024.1Q | E77: 2024.2Q | F77: 2024.3Q | G77: 2024.4Q | H77: 2025.1Q | I77: 2025.2Q | J77: 2025.3Q | K77: 2025.4Q | L77: 2026.1Q | M77: 2026.2Q | N77: 2026.3Q | O77: 2016 | P77: 2017 | Q77: 2018 | R77: 2019 | S77: 2020 | T77: 2021 | U77: 2022 | V77: 2023 | W77: 2024 | X77: 2025 | Y77: 2026(MW) | Z77: 2027(MW) | AA77: 2028(MW) | AB77: 2029(MW) | AC77: 2030(MW)
A78: 매출액 | C78: 1757.173 | D78: 2588.383 | E78: 2425.441 | F78: 1457.637 | G78: 1477.025 | H78: 2816.632 | I78: 3569.23 | J78: 1774.488 | K78: 1631.648 | L78: 3951.287 | M78: 1721.978 | N78: 2036.119 | V78: 1757.173 | W78: 1477.025 | X78: 1631.648
A79: 매출원가 | C79: 1591.928 | D79: 2201.369 | E79: 1847.602 | F79: 1286.301 | G79: 1320.913 | H79: 2410.547 | I79: 2861.804 | J79: 1429.712 | K79: 1412.849 | L79: 2837.032 | M79: 1414.472 | N79: 1720.312 | V79: 1591.928 | W79: 1320.913 | X79: 1412.849
A80: 매출총이익 | C80: 165.244 | D80: 387.013 | E80: 577.839 | F80: 171.337 | G80: 156.112 | H80: 406.085 | I80: 707.425 | J80: 344.776 | K80: 218.8 | L80: 1114.254 | M80: 307.506 | N80: 315.807 | V80: 165.244 | W80: 156.112 | X80: 218.8
A81: 판매비와 관리비 | C81: 107.555 | D81: 126.462 | E81: 135.414 | F81: 126.925 | G81: 136.726 | H81: 168.756 | I81: 162.153 | J81: 147.934 | K81: 155.063 | L81: 201.594 | M81: 176.52 | N81: 198.919 | V81: 107.555 | W81: 136.726 | X81: 155.063
A82: 영업이익 | C82: 57.689 | D82: 260.55 | E82: 442.426 | F82: 44.411 | G82: 19.386 | H82: 237.328 | I82: 545.273 | J82: 196.842 | K82: 63.736 | L82: 912.659 | M82: 130.987 | N82: 116.887 | V82: 57.689 | W82: 19.386 | X82: 63.736
A83: 이자수익 | C83: 0.005 | D83: 0 | E83: 0.086 | F83: 0.368 | G83: 0.422 | H83: 0.304 | I83: 1.19 | J83: 0.523 | K83: 2.314 | L83: 0.403 | M83: 1.854 | N83: 0.407 | V83: 0.005 | W83: 0.422 | X83: 2.314
A84: 보조금 수입 | C84: 0 | F84: 0 | G84: 0 | V84: 0 | W84: 0
A85: 협찬금 수입 | C85: 0 | F85: 0.88 | G85: 0 | H85: 0 | I85: 0 | J85: 0.209 | K85: 0 | L85: 0.21 | M85: 0 | N85: 0 | V85: 0 | W85: 0 | X85: 0
A86: 기타 | C86: 0.01 | D86: 0 | E86: 0.025 | F86: 0 | G86: 0 | H86: 0 | I86: 0.208 | J86: 0.571 | K86: 0.04 | L86: 0.23 | M86: 0.083 | N86: 0.237 | V86: 0.01 | W86: 0 | X86: 0.04
A87: 영업외수익 합계 | C87: 0.015 | D87: 0 | E87: 0.408 | F87: 1.248 | G87: 0.422 | H87: 0.304 | I87: 1.399 | J87: 1.303 | K87: 3.525 | L87: 0.843 | M87: 1.938 | N87: 0.644 | V87: 0.015 | W87: 0.422 | X87: 3.525
A88: 이자비용 | C88: 14.346 | D88: 12.914 | E88: 11.626 | F88: 16.271 | G88: 24.822 | H88: 30.423 | I88: 38.329 | J88: 43.835 | K88: 47.266 | L88: 58.105 | M88: 68.033 | N88: 89.2 | V88: 14.346 | W88: 24.822 | X88: 47.266
A89: 지급수수료 | C89: 0 | D89: 0 | E89: 26.469 | F89: 28.878 | G89: 0.022 | H89: 16.035 | I89: 0.446 | J89: 0.036 | K89: 35.816 | L89: 12.739 | M89: 23.735 | N89: 2.555 | V89: 0 | W89: 0.022 | X89: 35.816
A90: 감가상각비 | D90: 0 | E90: 3.843 | F90: 8.749 | G90: 4.188 | H90: 2.791 | I90: 0.93 | J90: 1.872 | K90: 2.449 | L90: 4.554 | M90: 3.664 | N90: 4.772 | W90: 4.188 | X90: 2.449
A91: 상장 관련 비용 | C91: 0.212 | F91: 0 | G91: 0 | V91: 0.212 | W91: 0
A92: 주식교부비 | C92: 1.19 | D92: 0.17 | E92: 0.153 | F92: 0.09 | G92: 0.06 | H92: 0 | I92: 0 | J92: 0 | K92: 0 | V92: 1.19 | W92: 0.06 | X92: 0
A93: 기타 | C93: -0.111 | D93: 0.169 | E93: 0.094 | F93: 0.396 | G93: 0 | H93: 1.665 | I93: 0.777 | J93: 0 | K93: 0 | L93: 0.371 | M93: 0.416 | N93: 1.063 | V93: -0.111 | W93: 0 | X93: 0
A94: 영업외비용 합계 | C94: 15.815 | D94: 13.254 | E94: 42.187 | F94: 54.383 | G94: 29.092 | H94: 50.915 | I94: 40.482 | J94: 45.743 | K94: 85.531 | L94: 75.77 | M94: 95.849 | N94: 121.531 | V94: 15.815 | W94: 29.092 | X94: 85.531
A95: 경상이익 | C95: 41.889 | D95: 247.296 | E95: 400.647 | F95: -8.725 | G95: -9.283 | H95: 186.718 | I95: 506.189 | J95: 152.402 | K95: -18.27 | L95: 837.732 | M95: 37.077 | N95: -4.001 | V95: 41.889 | W95: -9.283 | X95: -18.27
A96: 보상금 수취 | C96: 0 | F96: 0 | G96: 0 | J96: 0 | K96: 0 | V96: 0 | W96: 0 | X96: 0
A97: 특별이익 합계 | C97: 5.338 | F97: 0 | G97: 0 | J97: 0 | K97: 0.617 | V97: 5.338 | W97: 0 | X97: 0.617
A98: 손상차손 | K98: 30.75 | X98: 30.75
A99: 고정자산 제각손실 | C99: 3.898 | F99: 0 | G99: 0 | V99: 3.898 | W99: 0
A100: 특별손실 합계 | C100: 50.757 | F100: 0 | G100: 87.858 | K100: 30.75 | V100: 50.757 | W100: 87.858 | X100: 30.75
A101: 법인세차감전 순이익 | C101: -3.53 | D101: 247.296 | E101: 410.147 | F101: -8.725 | G101: -97.141 | H101: 186.718 | I101: 506.189 | J101: 152.402 | K101: -48.403 | L101: 837.732 | M101: 37.077 | N101: -24.739 | V101: -3.53 | W101: -97.141 | X101: -48.403
A102: 법인세·주민세·사업세 | C102: 9.763 | D102: 63.778 | E102: 140.107 | F102: -0.879 | G102: 12.432 | H102: 47.052 | I102: 157.656 | J102: 34.658 | K102: 5.364 | L102: 248.161 | M102: 32.695 | N102: -6.329 | V102: 9.763 | W102: 12.432 | X102: 5.364
...

Sheet 재무상태표
A1: 5532 재무상태표
A2: 재무비율은 기말 잔액 기준 · 분기 손익은 최근 4분기 합산(TTM) | B2: (단위: 백만엔)
A3: 항목 | B3: 참고 | C3: 2025.3Q | D3: 2025.4Q | E3: 2026.1Q | F3: 2026.2Q | G3: 2026.3Q | H3: 2022 | I3: 2023 | J3: 2024 | K3: 2025
A4: 자산
A5: 유동자산 | C5: 4347.558 | D5: 4472.266 | E5: 3903.33 | F5: 3192.709 | G5: 5320.596 | H5: 2043.317 | I5: 4007.328 | J5: 5526.633 | K5: 4472.266
A6: 현금및현금성자산 | C6: 2051.601 | D6: 947.147 | E6: 1368.944 | F6: 551.492 | G6: 2170.351 | H6: 642.939 | I6: 1962.754 | J6: 1130.352 | K6: 947.147
A7: 단기금융상품
A8: 매출채권
A9: 재고자산 | C9: 948.17 | D9: 2372.776 | E9: 1325.957 | F9: 1323.187 | G9: 1694.953 | H9: 589.453 | I9: 1010.532 | J9: 3299.284 | K9: 2372.776
A10: 기타유동자산 | B10: 총계 − 위 항목 | C10: =IF(OR(C5=""),"",IFERROR(C5-SUM(C6,C7,C8,C9),"")) | D10: =IF(OR(D5=""),"",IFERROR(D5-SUM(D6,D7,D8,D9),"")) | E10: =IF(OR(E5=""),"",IFERROR(E5-SUM(E6,E7,E8,E9),"")) | F10: =IF(OR(F5=""),"",IFERROR(F5-SUM(F6,F7,F8,F9),"")) | G10: =IF(OR(G5=""),"",IFERROR(G5-SUM(G6,G7,G8,G9),"")) | H10: =IF(OR(H5=""),"",IFERROR(H5-SUM(H6,H7,H8,H9),"")) | I10: =IF(OR(I5=""),"",IFERROR(I5-SUM(I6,I7,I8,I9),"")) | J10: =IF(OR(J5=""),"",IFERROR(J5-SUM(J6,J7,J8,J9),"")) | K10: =IF(OR(K5=""),"",IFERROR(K5-SUM(K6,K7,K8,K9),""))
A11: 비유동자산 | C11: 14609.096 | D11: 16792.466 | E11: 18231.458 | F11: 22050.124 | G11: 23359.552 | H11: 5716.793 | I11: 7399.641 | J11: 10368.085 | K11: 16792.466
A12: 유형자산 | C12: 12290.623 | D12: 14440.749 | E12: 15890.711 | F12: 19477.626 | G12: 20826.975 | H12: 3799.943 | I12: 5393.194 | J12: 8153.064 | K12: 14440.749
A13: 무형자산 | C13: 59.53 | D13: 60.748 | E13: 55.764 | F13: 50.114 | G13: 44.594 | H13: 74.785 | I13: 70.524 | J13: 58.505 | K13: 60.748
A14: 투자부동산
A15: 기타비유동자산 | B15: 총계 − 위 항목 | C15: =IF(OR(C11=""),"",IFERROR(C11-SUM(C12,C13,C14),"")) | D15: =IF(OR(D11=""),"",IFERROR(D11-SUM(D12,D13,D14),"")) | E15: =IF(OR(E11=""),"",IFERROR(E11-SUM(E12,E13,E14),"")) | F15: =IF(OR(F11=""),"",IFERROR(F11-SUM(F12,F13,F14),"")) | G15: =IF(OR(G11=""),"",IFERROR(G11-SUM(G12,G13,G14),"")) | H15: =IF(OR(H11=""),"",IFERROR(H11-SUM(H12,H13,H14),"")) | I15: =IF(OR(I11=""),"",IFERROR(I11-SUM(I12,I13,I14),"")) | J15: =IF(OR(J11=""),"",IFERROR(J11-SUM(J12,J13,J14),"")) | K15: =IF(OR(K11=""),"",IFERROR(K11-SUM(K12,K13,K14),""))
A16: 자산총계 | C16: 18956.654 | D16: 21264.732 | E16: 22134.789 | F16: 25242.833 | G16: 28680.149 | H16: 7760.11 | I16: 11406.97 | J16: 15894.719 | K16: 21264.732
A17: 부채
A18: 유동부채 | C18: 3019.607 | D18: 3901.427 | E18: 3604.267 | F18: 5004.413 | G18: 5829.901 | H18: 1973.719 | I18: 4327.304 | J18: 5837.629 | K18: 3901.427
A19: 매입채무
A20: 단기차입금 | D20: 0 | E20: 180 | F20: 1490 | G20: 2000.45 | H20: 0 | I20: 1842 | J20: 0 | K20: 0
A21: 유동성장기부채 | C21: 1010.521 | D21: 1646.526 | E21: 1598.036 | F21: 1608.847 | G21: 1783.23 | H21: 594.61 | I21: 791.965 | J21: 4126.706 | K21: 1646.526
A22: 기타유동부채 | B22: 총계 − 위 항목 | C22: =IF(OR(C18=""),"",IFERROR(C18-SUM(C19,C20,C21),"")) | D22: =IF(OR(D18=""),"",IFERROR(D18-SUM(D19,D20,D21),"")) | E22: =IF(OR(E18=""),"",IFERROR(E18-SUM(E19,E20,E21),"")) | F22: =IF(OR(F18=""),"",IFERROR(F18-SUM(F19,F20,F21),"")) | G22: =IF(OR(G18=""),"",IFERROR(G18-SUM(G19,G20,G21),"")) | H22: =IF(OR(H18=""),"",IFERROR(H18-SUM(H19,H20,H21),"")) | I22: =IF(OR(I18=""),"",IFERROR(I18-SUM(I19,I20,I21),"")) | J22: =IF(OR(J18=""),"",IFERROR(J18-SUM(J19,J20,J21),"")) | K22: =IF(OR(K18=""),"",IFERROR(K18-SUM(K19,K20,K21),""))
A23: 비유동부채 | C23: 12573.825 | D23: 14011.697 | E23: 14585.997 | F23: 16174.586 | G23: 16348.8 | H23: 5049.475 | I23: 4798.113 | J23: 7345.438 | K23: 14011.697
A24: 장기차입금 | C24: 10744.795 | D24: 12291.17 | E24: 12850.796 | F24: 14355.744 | G24: 14482.994 | H24: 3563.687 | I24: 3137.216 | J24: 5580.105 | K24: 12291.17
A25: 사채
A26: 기타비유동부채 | B26: 총계 − 위 항목 | C26: =IF(OR(C23=""),"",IFERROR(C23-SUM(C24,C25),"")) | D26: =IF(OR(D23=""),"",IFERROR(D23-SUM(D24,D25),"")) | E26: =IF(OR(E23=""),"",IFERROR(E23-SUM(E24,E25),"")) | F26: =IF(OR(F23=""),"",IFERROR(F23-SUM(F24,F25),"")) | G26: =IF(OR(G23=""),"",IFERROR(G23-SUM(G24,G25),"")) | H26: =IF(OR(H23=""),"",IFERROR(H23-SUM(H24,H25),"")) | I26: =IF(OR(I23=""),"",IFERROR(I23-SUM(I24,I25),"")) | J26: =IF(OR(J23=""),"",IFERROR(J23-SUM(J24,J25),"")) | K26: =IF(OR(K23=""),"",IFERROR(K23-SUM(K24,K25),""))
A27: 부채총계 | C27: 15593.432 | D27: 17913.124 | E27: 18190.264 | F27: 21179 | G27: 22178.701 | H27: 7023.194 | I27: 9125.418 | J27: 13183.068 | K27: 17913.124
A28: 총차입금 | B28: 단기+유동성장기+장기+사채 | C28: =SUM(C20,C21,C24,C25) | D28: =SUM(D20,D21,D24,D25) | E28: =SUM(E20,E21,E24,E25) | F28: =SUM(F20,F21,F24,F25) | G28: =SUM(G20,G21,G24,G25) | H28: =SUM(H20,H21,H24,H25) | I28: =SUM(I20,I21,I24,I25) | J28: =SUM(J20,J21,J24,J25) | K28: =SUM(K20,K21,K24,K25)
A29: 순차입금 | B29: 음수 = 순현금 | C29: =C28-C6-N(C7) | D29: =D28-D6-N(D7) | E29: =E28-E6-N(E7) | F29: =F28-F6-N(F7) | G29: =G28-G6-N(G7) | H29: =H28-H6-N(H7) | I29: =I28-I6-N(I7) | J29: =J28-J6-N(J7) | K29: =K28-K6-N(K7)
A30: 자본
A31: 지배주주지분 | C31: 3319.475 | D31: 3300.088 | E31: 3876.214 | F31: 3976.246 | G31: 6392.464 | H31: 731.564 | I31: 2281.552 | J31: 2692.252 | K31: 3300.088
A32: 자본금 | C32: 705.121 | D32: 705.279 | E32: 705.279 | F32: 746.439 | G32: 1967.559 | H32: 30 | I32: 665.697 | J32: 680.971 | K32: 705.279
A33: 이익잉여금 | C33: 1939.45 | D33: 1919.747 | E33: 2496.009 | F33: 2513.721 | G33: 2487.698 | H33: 701.564 | I33: 980.158 | J33: 1360.527 | K33: 1919.747
A34: 비지배지분
A35: 자본총계 | C35: 3363.222 | D35: 3351.607 | E35: 3944.525 | F35: 4063.832 | G35: 6501.447 | H35: 736.915 | I35: 2281.552 | J35: 2711.65 | K35: 3351.607
A36: 현금흐름 요약 | B36: 분기 = TTM (있을 때만)
A37: 영업활동현금흐름 | D37: 3560.622 | F37: 1913.919 | H37: 410.604 | I37: 1505.901 | J37: -1332.824 | K37: 3560.622
A38: CAPEX (유·무형 취득) | B38: 양수로 입력 | D38: 7766.772 | F38: 8963.809 | H38: 2314.234 | I38: 2929.198 | J38: 3205.09 | K38: 7766.772
A39: FCF | C39: =IF(OR(C37="",C38=""),"",IFERROR(C37-C38,"")) | D39: =IF(OR(D37="",D38=""),"",IFERROR(D37-D38,"")) | E39: =IF(OR(E37="",E38=""),"",IFERROR(E37-E38,"")) | F39: =IF(OR(F37="",F38=""),"",IFERROR(F37-F38,"")) | G39: =IF(OR(G37="",G38=""),"",IFERROR(G37-G38,"")) | H39: =IF(OR(H37="",H38=""),"",IFERROR(H37-H38,"")) | I39: =IF(OR(I37="",I38=""),"",IFERROR(I37-I38,"")) | J39: =IF(OR(J37="",J38=""),"",IFERROR(J37-J38,"")) | K39: =IF(OR(K37="",K38=""),"",IFERROR(K37-K38,""))
A40: 배당금 지급 | B40: 양수로 입력
A41: 주요 재무 비율 | B41: 기준 (빨간 글씨 = 미달)
A42: 안정성
A43: 부채비율 | B43: 100%↓ | C43: =IF(OR(C27="",C35=""),"",IFERROR(C27/C35,"")) | D43: =IF(OR(D27="",D35=""),"",IFERROR(D27/D35,"")) | E43: =IF(OR(E27="",E35=""),"",IFERROR(E27/E35,"")) | F43: =IF(OR(F27="",F35=""),"",IFERROR(F27/F35,"")) | G43: =IF(OR(G27="",G35=""),"",IFERROR(G27/G35,"")) | H43: =IF(OR(H27="",H35=""),"",IFERROR(H27/H35,"")) | I43: =IF(OR(I27="",I35=""),"",IFERROR(I27/I35,"")) | J43: =IF(OR(J27="",J35=""),"",IFERROR(J27/J35,"")) | K43: =IF(OR(K27="",K35=""),"",IFERROR(K27/K35,""))
A44: 순차입금비율 | B44: 0%↓ 순현금 | C44: =IF(OR(C29="",C35=""),"",IFERROR(C29/C35,"")) | D44: =IF(OR(D29="",D35=""),"",IFERROR(D29/D35,"")) | E44: =IF(OR(E29="",E35=""),"",IFERROR(E29/E35,"")) | F44: =IF(OR(F29="",F35=""),"",IFERROR(F29/F35,"")) | G44: =IF(OR(G29="",G35=""),"",IFERROR(G29/G35,"")) | H44: =IF(OR(H29="",H35=""),"",IFERROR(H29/H35,"")) | I44: =IF(OR(I29="",I35=""),"",IFERROR(I29/I35,"")) | J44: =IF(OR(J29="",J35=""),"",IFERROR(J29/J35,"")) | K44: =IF(OR(K29="",K35=""),"",IFERROR(K29/K35,""))
A45: 자기자본비율 | B45: 50%↑ | C45: =IF(OR(C35="",C16=""),"",IFERROR(C35/C16,"")) | D45: =IF(OR(D35="",D16=""),"",IFERROR(D35/D16,"")) | E45: =IF(OR(E35="",E16=""),"",IFERROR(E35/E16,"")) | F45: =IF(OR(F35="",F16=""),"",IFERROR(F35/F16,"")) | G45: =IF(OR(G35="",G16=""),"",IFERROR(G35/G16,"")) | H45: =IF(OR(H35="",H16=""),"",IFERROR(H35/H16,"")) | I45: =IF(OR(I35="",I16=""),"",IFERROR(I35/I16,"")) | J45: =IF(OR(J35="",J16=""),"",IFERROR(J35/J16,"")) | K45: =IF(OR(K35="",K16=""),"",IFERROR(K35/K16,""))
A46: 유동비율 | B46: 150%↑ | C46: =IF(OR(C5="",C18=""),"",IFERROR(C5/C18,"")) | D46: =IF(OR(D5="",D18=""),"",IFERROR(D5/D18,"")) | E46: =IF(OR(E5="",E18=""),"",IFERROR(E5/E18,"")) | F46: =IF(OR(F5="",F18=""),"",IFERROR(F5/F18,"")) | G46: =IF(OR(G5="",G18=""),"",IFERROR(G5/G18,"")) | H46: =IF(OR(H5="",H18=""),"",IFERROR(H5/H18,"")) | I46: =IF(OR(I5="",I18=""),"",IFERROR(I5/I18,"")) | J46: =IF(OR(J5="",J18=""),"",IFERROR(J5/J18,"")) | K46: =IF(OR(K5="",K18=""),"",IFERROR(K5/K18,""))
A47: 당좌비율 | B47: 100%↑ | C47: =IF(OR(C5="",C18=""),"",IFERROR((C5-N(C9))/C18,"")) | D47: =IF(OR(D5="",D18=""),"",IFERROR((D5-N(D9))/D18,"")) | E47: =IF(OR(E5="",E18=""),"",IFERROR((E5-N(E9))/E18,"")) | F47: =IF(OR(F5="",F18=""),"",IFERROR((F5-N(F9))/F18,"")) | G47: =IF(OR(G5="",G18=""),"",IFERROR((G5-N(G9))/G18,"")) | H47: =IF(OR(H5="",H18=""),"",IFERROR((H5-N(H9))/H18,"")) | I47: =IF(OR(I5="",I18=""),"",IFERROR((I5-N(I9))/I18,"")) | J47: =IF(OR(J5="",J18=""),"",IFERROR((J5-N(J9))/J18,"")) | K47: =IF(OR(K5="",K18=""),"",IFERROR((K5-N(K9))/K18,""))
A48: 이자보상배율 | B48: 5x↑ (금융원가 기준) | C48: =IFERROR((IF(COUNT('연간'!G16:J16)<4,"",SUM('연간'!G16:J16)))/(IF(COUNT('연간'!G38:J38)<4,"",SUM('연간'!G38:J38))),"") | D48: =IFERROR((IF(COUNT('연간'!H16:K16)<4,"",SUM('연간'!H16:K16)))/(IF(COUNT('연간'!H38:K38)<4,"",SUM('연간'!H38:K38))),"") | E48: =IFERROR((IF(COUNT('연간'!I16:L16)<4,"",SUM('연간'!I16:L16)))/(IF(COUNT('연간'!I38:L38)<4,"",SUM('연간'!I38:L38))),"") | F48: =IFERROR((IF(COUNT('연간'!J16:M16)<4,"",SUM('연간'!J16:M16)))/(IF(COUNT('연간'!J38:M38)<4,"",SUM('연간'!J38:M38))),"") | G48: =IFERROR((IF(COUNT('연간'!K16:N16)<4,"",SUM('연간'!K16:N16)))/(IF(COUNT('연간'!K38:N38)<4,"",SUM('연간'!K38:N38))),"") | H48: =IFERROR(('연간'!U16)/('연간'!U38),"") | I48: =IFERROR(('연간'!V16)/('연간'!V38),"") | J48: =IFERROR(('연간'!W16)/('연간'!W38),"") | K48: =IFERROR(('연간'!X16)/('연간'!X38),"")
A49: 차입금 상환연수 | B49: 4년↓ (버핏) | C49: =IFERROR(IF((IF(COUNT('연간'!G44:J44)<4,"",SUM('연간'!G44:J44)))<=0,"적자",C28/(IF(COUNT('연간'!G44:J44)<4,"",SUM('연간'!G44:J44)))),"") | D49: =IFERROR(IF((IF(COUNT('연간'!H44:K44)<4,"",SUM('연간'!H44:K44)))<=0,"적자",D28/(IF(COUNT('연간'!H44:K44)<4,"",SUM('연간'!H44:K44)))),"") | E49: =IFERROR(IF((IF(COUNT('연간'!I44:L44)<4,"",SUM('연간'!I44:L44)))<=0,"적자",E28/(IF(COUNT('연간'!I44:L44)<4,"",SUM('연간'!I44:L44)))),"") | F49: =IFERROR(IF((IF(COUNT('연간'!J44:M44)<4,"",SUM('연간'!J44:M44)))<=0,"적자",F28/(IF(COUNT('연간'!J44:M44)<4,"",SUM('연간'!J44:M44)))),"") | G49: =IFERROR(IF((IF(COUNT('연간'!K44:N44)<4,"",SUM('연간'!K44:N44)))<=0,"적자",G28/(IF(COUNT('연간'!K44:N44)<4,"",SUM('연간'!K44:N44)))),"") | H49: =IFERROR(IF(('연간'!U44)<=0,"적자",H28/('연간'!U44)),"") | I49: =IFERROR(IF(('연간'!V44)<=0,"적자",I28/('연간'!V44)),"") | J49: =IFERROR(IF(('연간'!W44)<=0,"적자",J28/('연간'!W44)),"") | K49: =IFERROR(IF(('연간'!X44)<=0,"적자",K28/('연간'!X44)),"")
A50: 수익성
A51: ROE | B51: 15%↑ (버핏) | C51: =IFERROR((IF(COUNT('연간'!G44:J44)<4,"",SUM('연간'!G44:J44)))/C31,"") | D51: =IFERROR((IF(COUNT('연간'!H44:K44)<4,"",SUM('연간'!H44:K44)))/D31,"") | E51: =IFERROR((IF(COUNT('연간'!I44:L44)<4,"",SUM('연간'!I44:L44)))/E31,"") | F51: =IFERROR((IF(COUNT('연간'!J44:M44)<4,"",SUM('연간'!J44:M44)))/F31,"") | G51: =IFERROR((IF(COUNT('연간'!K44:N44)<4,"",SUM('연간'!K44:N44)))/G31,"") | H51: =IFERROR(('연간'!U44)/H31,"") | I51: =IFERROR(('연간'!V44)/I31,"") | J51: =IFERROR(('연간'!W44)/J31,"") | K51: =IFERROR(('연간'!X44)/K31,"")
A52: ROA | B52: 5%↑ | C52: =IFERROR((IF(COUNT('연간'!G43:J43)<4,"",SUM('연간'!G43:J43)))/C16,"") | D52: =IFERROR((IF(COUNT('연간'!H43:K43)<4,"",SUM('연간'!H43:K43)))/D16,"") | E52: =IFERROR((IF(COUNT('연간'!I43:L43)<4,"",SUM('연간'!I43:L43)))/E16,"") | F52: =IFERROR((IF(COUNT('연간'!J43:M43)<4,"",SUM('연간'!J43:M43)))/F16,"") | G52: =IFERROR((IF(COUNT('연간'!K43:N43)<4,"",SUM('연간'!K43:N43)))/G16,"") | H52: =IFERROR(('연간'!U43)/H16,"") | I52: =IFERROR(('연간'!V43)/I16,"") | J52: =IFERROR(('연간'!W43)/J16,"") | K52: =IFERROR(('연간'!X43)/K16,"")
A53: ROIC | B53: 10%↑ (세후영업이익 기준) | C53: =IFERROR((IF(COUNT('연간'!G16:J16)<4,"",SUM('연간'!G16:J16)))*(1-0.3)/(C35+C29),"") | D53: =IFERROR((IF(COUNT('연간'!H16:K16)<4,"",SUM('연간'!H16:K16)))*(1-0.3)/(D35+D29),"") | E53: =IFERROR((IF(COUNT('연간'!I16:L16)<4,"",SUM('연간'!I16:L16)))*(1-0.3)/(E35+E29),"") | F53: =IFERROR((IF(COUNT('연간'!J16:M16)<4,"",SUM('연간'!J16:M16)))*(1-0.3)/(F35+F29),"") | G53: =IFERROR((IF(COUNT('연간'!K16:N16)<4,"",SUM('연간'!K16:N16)))*(1-0.3)/(G35+G29),"") | H53: =IFERROR(('연간'!U16)*(1-0.3)/(H35+H29),"") | I53: =IFERROR(('연간'!V16)*(1-0.3)/(I35+I29),"") | J53: =IFERROR(('연간'!W16)*(1-0.3)/(J35+J29),"") | K53: =IFERROR(('연간'!X16)*(1-0.3)/(K35+K29),"")
A54: 매출총이익률 (GPM) | B54: 40%↑ (해자 신호) | C54: =IFERROR((IF(COUNT('연간'!G12:J12)<4,"",SUM('연간'!G12:J12)))/(IF(COUNT('연간'!G4:J4)<4,"",SUM('연간'!G4:J4))),"") | D54: =IFERROR((IF(COUNT('연간'!H12:K12)<4,"",SUM('연간'!H12:K12)))/(IF(COUNT('연간'!H4:K4)<4,"",SUM('연간'!H4:K4))),"") | E54: =IFERROR((IF(COUNT('연간'!I12:L12)<4,"",SUM('연간'!I12:L12)))/(IF(COUNT('연간'!I4:L4)<4,"",SUM('연간'!I4:L4))),"") | F54: =IFERROR((IF(COUNT('연간'!J12:M12)<4,"",SUM('연간'!J12:M12)))/(IF(COUNT('연간'!J4:M4)<4,"",SUM('연간'!J4:M4))),"") | G54: =IFERROR((IF(COUNT('연간'!K12:N12)<4,"",SUM('연간'!K12:N12)))/(IF(COUNT('연간'!K4:N4)<4,"",SUM('연간'!K4:N4))),"") | H54: =IFERROR(('연간'!U12)/('연간'!U4),"") | I54: =IFERROR(('연간'!V12)/('연간'!V4),"") | J54: =IFERROR(('연간'!W12)/('연간'!W4),"") | K54: =IFERROR(('연간'!X12)/('연간'!X4),"")
A55: 영업이익률 (OPM) | B55: 15%↑ | C55: =IFERROR((IF(COUNT('연간'!G16:J16)<4,"",SUM('연간'!G16:J16)))/(IF(COUNT('연간'!G4:J4)<4,"",SUM('연간'!G4:J4))),"") | D55: =IFERROR((IF(COUNT('연간'!H16:K16)<4,"",SUM('연간'!H16:K16)))/(IF(COUNT('연간'!H4:K4)<4,"",SUM('연간'!H4:K4))),"") | E55: =IFERROR((IF(COUNT('연간'!I16:L16)<4,"",SUM('연간'!I16:L16)))/(IF(COUNT('연간'!I4:L4)<4,"",SUM('연간'!I4:L4))),"") | F55: =IFERROR((IF(COUNT('연간'!J16:M16)<4,"",SUM('연간'!J16:M16)))/(IF(COUNT('연간'!J4:M4)<4,"",SUM('연간'!J4:M4))),"") | G55: =IFERROR((IF(COUNT('연간'!K16:N16)<4,"",SUM('연간'!K16:N16)))/(IF(COUNT('연간'!K4:N4)<4,"",SUM('연간'!K4:N4))),"") | H55: =IFERROR(('연간'!U16)/('연간'!U4),"") | I55: =IFERROR(('연간'!V16)/('연간'!V4),"") | J55: =IFERROR(('연간'!W16)/('연간'!W4),"") | K55: =IFERROR(('연간'!X16)/('연간'!X4),"")
A56: 순이익률 | B56: 10%↑ | C56: =IFERROR((IF(COUNT('연간'!G43:J43)<4,"",SUM('연간'!G43:J43)))/(IF(COUNT('연간'!G4:J4)<4,"",SUM('연간'!G4:J4))),"") | D56: =IFERROR((IF(COUNT('연간'!H43:K43)<4,"",SUM('연간'!H43:K43)))/(IF(COUNT('연간'!H4:K4)<4,"",SUM('연간'!H4:K4))),"") | E56: =IFERROR((IF(COUNT('연간'!I43:L43)<4,"",SUM('연간'!I43:L43)))/(IF(COUNT('연간'!I4:L4)<4,"",SUM('연간'!I4:L4))),"") | F56: =IFERROR((IF(COUNT('연간'!J43:M43)<4,"",SUM('연간'!J43:M43)))/(IF(COUNT('연간'!J4:M4)<4,"",SUM('연간'!J4:M4))),"") | G56: =IFERROR((IF(COUNT('연간'!K43:N43)<4,"",SUM('연간'!K43:N43)))/(IF(COUNT('연간'!K4:N4)<4,"",SUM('연간'!K4:N4))),"") | H56: =IFERROR(('연간'!U43)/('연간'!U4),"") | I56: =IFERROR(('연간'!V43)/('연간'!V4),"") | J56: =IFERROR(('연간'!W43)/('연간'!W4),"") | K56: =IFERROR(('연간'!X43)/('연간'!X4),"")
A57: 효율성 (회전율)
A58: 총자산회전율 | B58: 높을수록↑ | C58: =IFERROR((IF(COUNT('연간'!G4:J4)<4,"",SUM('연간'!G4:J4)))/C16,"") | D58: =IFERROR((IF(COUNT('연간'!H4:K4)<4,"",SUM('연간'!H4:K4)))/D16,"") | E58: =IFERROR((IF(COUNT('연간'!I4:L4)<4,"",SUM('연간'!I4:L4)))/E16,"") | F58: =IFERROR((IF(COUNT('연간'!J4:M4)<4,"",SUM('연간'!J4:M4)))/F16,"") | G58: =IFERROR((IF(COUNT('연간'!K4:N4)<4,"",SUM('연간'!K4:N4)))/G16,"") | H58: =IFERROR(('연간'!U4)/H16,"") | I58: =IFERROR(('연간'!V4)/I16,"") | J58: =IFERROR(('연간'!W4)/J16,"") | K58: =IFERROR(('연간'!X4)/K16,"")
A59: 매출채권회전일수 | B59: 짧을수록↑ | C59: =IFERROR(C8/(IF(COUNT('연간'!G4:J4)<4,"",SUM('연간'!G4:J4)))*365,"") | D59: =IFERROR(D8/(IF(COUNT('연간'!H4:K4)<4,"",SUM('연간'!H4:K4)))*365,"") | E59: =IFERROR(E8/(IF(COUNT('연간'!I4:L4)<4,"",SUM('연간'!I4:L4)))*365,"") | F59: =IFERROR(F8/(IF(COUNT('연간'!J4:M4)<4,"",SUM('연간'!J4:M4)))*365,"") | G59: =IFERROR(G8/(IF(COUNT('연간'!K4:N4)<4,"",SUM('연간'!K4:N4)))*365,"") | H59: =IFERROR(H8/('연간'!U4)*365,"") | I59: =IFERROR(I8/('연간'!V4)*365,"") | J59: =IFERROR(J8/('연간'!W4)*365,"") | K59: =IFERROR(K8/('연간'!X4)*365,"")
A60: 재고자산회전일수 | B60: 짧을수록↑ | C60: =IFERROR(C9/(IF(COUNT('연간'!G11:J11)<4,"",SUM('연간'!G11:J11)))*365,"") | D60: =IFERROR(D9/(IF(COUNT('연간'!H11:K11)<4,"",SUM('연간'!H11:K11)))*365,"") | E60: =IFERROR(E9/(IF(COUNT('연간'!I11:L11)<4,"",SUM('연간'!I11:L11)))*365,"") | F60: =IFERROR(F9/(IF(COUNT('연간'!J11:M11)<4,"",SUM('연간'!J11:M11)))*365,"") | G60: =IFERROR(G9/(IF(COUNT('연간'!K11:N11)<4,"",SUM('연간'!K11:N11)))*365,"") | H60: =IFERROR(H9/('연간'!U11)*365,"") | I60: =IFERROR(I9/('연간'!V11)*365,"") | J60: =IFERROR(J9/('연간'!W11)*365,"") | K60: =IFERROR(K9/('연간'!X11)*365,"")
A61: 매입채무회전일수 | B61: 길수록 유리 | C61: =IFERROR(C19/(IF(COUNT('연간'!G11:J11)<4,"",SUM('연간'!G11:J11)))*365,"") | D61: =IFERROR(D19/(IF(COUNT('연간'!H11:K11)<4,"",SUM('연간'!H11:K11)))*365,"") | E61: =IFERROR(E19/(IF(COUNT('연간'!I11:L11)<4,"",SUM('연간'!I11:L11)))*365,"") | F61: =IFERROR(F19/(IF(COUNT('연간'!J11:M11)<4,"",SUM('연간'!J11:M11)))*365,"") | G61: =IFERROR(G19/(IF(COUNT('연간'!K11:N11)<4,"",SUM('연간'!K11:N11)))*365,"") | H61: =IFERROR(H19/('연간'!U11)*365,"") | I61: =IFERROR(I19/('연간'!V11)*365,"") | J61: =IFERROR(J19/('연간'!W11)*365,"") | K61: =IFERROR(K19/('연간'!X11)*365,"")
A62: 현금전환주기 (CCC) | B62: 짧을수록↑ | C62: =IF(OR(C59="",C60="",C61=""),"",IFERROR(C59+C60-C61,"")) | D62: =IF(OR(D59="",D60="",D61=""),"",IFERROR(D59+D60-D61,"")) | E62: =IF(OR(E59="",E60="",E61=""),"",IFERROR(E59+E60-E61,"")) | F62: =IF(OR(F59="",F60="",F61=""),"",IFERROR(F59+F60-F61,"")) | G62: =IF(OR(G59="",G60="",G61=""),"",IFERROR(G59+G60-G61,"")) | H62: =IF(OR(H59="",H60="",H61=""),"",IFERROR(H59+H60-H61,"")) | I62: =IF(OR(I59="",I60="",I61=""),"",IFERROR(I59+I60-I61,"")) | J62: =IF(OR(J59="",J60="",J61=""),"",IFERROR(J59+J60-J61,"")) | K62: =IF(OR(K59="",K60="",K61=""),"",IFERROR(K59+K60-K61,""))
A63: 현금흐름
A64: 영업현금흐름 / 순이익 | B64: 1x↑ (이익의 질) | C64: =IF(C37="","",IFERROR(C37/(IF(COUNT('연간'!G43:J43)<4,"",SUM('연간'!G43:J43))),"")) | D64: =IF(D37="","",IFERROR(D37/(IF(COUNT('연간'!H43:K43)<4,"",SUM('연간'!H43:K43))),"")) | E64: =IF(E37="","",IFERROR(E37/(IF(COUNT('연간'!I43:L43)<4,"",SUM('연간'!I43:L43))),"")) | F64: =IF(F37="","",IFERROR(F37/(IF(COUNT('연간'!J43:M43)<4,"",SUM('연간'!J43:M43))),"")) | G64: =IF(G37="","",IFERROR(G37/(IF(COUNT('연간'!K43:N43)<4,"",SUM('연간'!K43:N43))),"")) | H64: =IF(H37="","",IFERROR(H37/('연간'!U43),"")) | I64: =IF(I37="","",IFERROR(I37/('연간'!V43),"")) | J64: =IF(J37="","",IFERROR(J37/('연간'!W43),"")) | K64: =IF(K37="","",IFERROR(K37/('연간'!X43),""))
A65: FCF 마진 | B65: 5%↑ | C65: =IF(C39="","",IFERROR(C39/(IF(COUNT('연간'!G4:J4)<4,"",SUM('연간'!G4:J4))),"")) | D65: =IF(D39="","",IFERROR(D39/(IF(COUNT('연간'!H4:K4)<4,"",SUM('연간'!H4:K4))),"")) | E65: =IF(E39="","",IFERROR(E39/(IF(COUNT('연간'!I4:L4)<4,"",SUM('연간'!I4:L4))),"")) | F65: =IF(F39="","",IFERROR(F39/(IF(COUNT('연간'!J4:M4)<4,"",SUM('연간'!J4:M4))),"")) | G65: =IF(G39="","",IFERROR(G39/(IF(COUNT('연간'!K4:N4)<4,"",SUM('연간'!K4:N4))),"")) | H65: =IF(H39="","",IFERROR(H39/('연간'!U4),"")) | I65: =IF(I39="","",IFERROR(I39/('연간'!V4),"")) | J65: =IF(J39="","",IFERROR(J39/('연간'!W4),"")) | K65: =IF(K39="","",IFERROR(K39/('연간'!X4),""))
A66: CAPEX / 매출 | B66: 낮을수록↑ (자본 가벼움) | C66: =IF(C38="","",IFERROR(C38/(IF(COUNT('연간'!G4:J4)<4,"",SUM('연간'!G4:J4))),"")) | D66: =IF(D38="","",IFERROR(D38/(IF(COUNT('연간'!H4:K4)<4,"",SUM('연간'!H4:K4))),"")) | E66: =IF(E38="","",IFERROR(E38/(IF(COUNT('연간'!I4:L4)<4,"",SUM('연간'!I4:L4))),"")) | F66: =IF(F38="","",IFERROR(F38/(IF(COUNT('연간'!J4:M4)<4,"",SUM('연간'!J4:M4))),"")) | G66: =IF(G38="","",IFERROR(G38/(IF(COUNT('연간'!K4:N4)<4,"",SUM('연간'!K4:N4))),"")) | H66: =IF(H38="","",IFERROR(H38/('연간'!U4),"")) | I66: =IF(I38="","",IFERROR(I38/('연간'!V4),"")) | J66: =IF(J38="","",IFERROR(J38/('연간'!W4),"")) | K66: =IF(K38="","",IFERROR(K38/('연간'!X4),""))
A67: 배당성향 | B67: 참고 | C67: =IF(C40="","",IFERROR(C40/(IF(COUNT('연간'!G44:J44)<4,"",SUM('연간'!G44:J44))),"")) | D67: =IF(D40="","",IFERROR(D40/(IF(COUNT('연간'!H44:K44)<4,"",SUM('연간'!H44:K44))),"")) | E67: =IF(E40="","",IFERROR(E40/(IF(COUNT('연간'!I44:L44)<4,"",SUM('연간'!I44:L44))),"")) | F67: =IF(F40="","",IFERROR(F40/(IF(COUNT('연간'!J44:M44)<4,"",SUM('연간'!J44:M44))),"")) | G67: =IF(G40="","",IFERROR(G40/(IF(COUNT('연간'!K44:N44)<4,"",SUM('연간'!K44:N44))),"")) | H67: =IF(H40="","",IFERROR(H40/('연간'!U44),"")) | I67: =IF(I40="","",IFERROR(I40/('연간'!V44),"")) | J67: =IF(J40="","",IFERROR(J40/('연간'!W44),"")) | K67: =IF(K40="","",IFERROR(K40/('연간'!X44),""))
A69: 재무상태표 · 전 항목 | B69: 분기 말 잔액
A70: 항목 | B70: 참고 | C70: 2025.3Q | D70: 2025.4Q | E70: 2026.1Q | F70: 2026.2Q | G70: 2026.3Q | H70: 2022 | I70: 2023 | J70: 2024 | K70: 2025
A71: 현금 및 예금 | C71: 2051.601 | D71: 947.147 | E71: 1368.944 | F71: 551.492 | G71: 2170.351 | H71: 642.939 | I71: 1962.754 | J71: 1130.352 | K71: 947.147
A72: Operating Accounts Receivable CA | C72: 706.207 | D72: 703.778 | E72: 661.831 | F72: 689.467 | G72: 698.467 | H72: 490.793 | I72: 601.902 | J72: 689.042 | K72: 703.778
A73: 완성공사 미수금 | C73: 106.294 | D73: 1.52 | E73: 0.09 | F73: 41.874 | G73: 16.012 | H73: 5.225 | I73: 72.344 | J73: 6.184 | K73: 1.52
A74: 계약자산 | C74: 0.51 | D74: 2.845 | E74: 96.767 | F74: 100.215 | G74: 54.794 | H74: 3.289 | I74: 20.636 | J74: 7.432 | K74: 2.845
A75: 판매용 부동산 | C75: 948.17 | D75: 2372.776 | E75: 1325.957 | F75: 1323.187 | G75: 1694.953 | H75: 589.453 | I75: 1010.532 | J75: 3299.284 | K75: 2372.776
A76: 미성공사 지출금 | C76: 0.02 | D76: 0.085 | E76: 0.112 | F76: 0.199 | G76: 0.221 | H76: 0.142 | I76: 0.143 | J76: 0 | K76: 0.085
A77: Costs On Uncompleted Services | H77: 0 | I77: 3.263 | J77: 0
A78: 선급비용 | C78: 329.548 | D78: 308.175 | E78: 309.831 | F78: 367.673 | G78: 343.862 | H78: 224.938 | I78: 252.387 | J78: 306.007 | K78: 308.175
A79: 기타 | C79: 205.626 | D79: 136.512 | E79: 140.335 | F79: 119.141 | G79: 342.393 | H79: 86.915 | I79: 83.549 | J79: 88.707 | K79: 136.512
A80: 대손충당금 | C80: -0.422 | D80: -0.576 | E80: -0.54 | F80: -0.541 | G80: -0.46 | H80: -0.38 | I80: -0.183 | J80: -0.377 | K80: -0.576
A81: 유동자산 합계 | C81: 4347.558 | D81: 4472.266 | E81: 3903.33 | F81: 3192.709 | G81: 5320.596 | H81: 2043.317 | I81: 4007.328 | J81: 5526.633 | K81: 4472.266
A82: 건물 | C82: 6473.784 | D82: 6103.713 | E82: 6716.119 | F82: 7127.26 | G82: 8677.472 | H82: 4096.053 | I82: 4678.921 | J82: 5607.411 | K82: 6103.713
A83: 구축물 | C83: 71.045 | D83: 71.045 | E83: 78.864 | F83: 79.117 | G83: 97.382 | H83: 36.625 | I83: 33.787 | J83: 45.858 | K83: 71.045
A84: 공구·기구·비품 | C84: 459.414 | D84: 437.437 | E84: 464.548 | F84: 487.922 | G84: 568.164 | H84: 325.897 | I84: 403.984 | J84: 431.527 | K84: 437.437
A85: 토지 | C85: 7708.328 | D85: 9983.653 | E85: 10964.721 | F85: 13793.534 | G85: 13794.04 | H85: 1044.473 | I85: 2228.506 | J85: 4405.596 | K85: 9983.653
A86: 리스자산 | C86: 3.018 | D86: 3.018 | E86: 3.018 | F86: 3.018 | G86: 3.018 | H86: 5.412 | I86: 0 | J86: 0 | K86: 3.018
A87: 건설중인자산 | C87: 212.006 | D87: 464.912 | E87: 379.537 | F87: 798.663 | G87: 605.779 | H87: 3.257 | I87: 2.704 | J87: 34.083 | K87: 464.912
A88: 기타 | C88: 0.381 | D88: 0.381 | E88: 0.381 | F88: 0.381 | G88: 0.381 | H88: 0.271 | I88: 0.271 | J88: 0.381 | K88: 0.381
A89: Accumulated Depreciation And Impairment Loss PPEBy Group | C89: -2637.355 | D89: -2623.412 | E89: -2716.478 | F89: -2812.269 | G89: -2919.264 | H89: -1712.047 | I89: -1954.981 | J89: -2371.794 | K89: -2623.412
... A91: 소프트웨어 | C91: 54.03 | D91: 60.748 | E91: 55.764 | F91: 50.114 | G91: 44.44 | H91: 74.785 | I91: 70.524 | J91: 58.505 | K91: 60.748
A92: 개발 중 소프트웨어 | C92: 5.5 | D92: 0 | G92: 0.154 | H92: 0 | I92: 0 | J92: 0 | K92: 0
A93: 무형자산 합계 | C93: 59.53 | D93: 60.748 | E93: 55.764 | F93: 50.114 | G93: 44.594 | H93: 74.785 | I93: 70.524 | J93: 58.505 | K93: 60.748
A94: 임차보증금·보증금 | C94: 1791.842 | D94: 1744.105 | E94: 1774.088 | F94: 1843.398 | G94: 1841.593 | H94: 1517.752 | I94: 1633.346 | J94: 1804.402 | K94: 1744.105
A95: 장기선급비용 | C95: 33.77 | D95: 31.324 | E95: 29.348 | F95: 38.621 | G95: 36.577 | H95: 0.704 | I95: 0.448 | J95: 24.453 | K95: 31.324
A96: 이연법인세자산 | C96: 232.761 | D96: 266.827 | E96: 253.518 | F96: 266.848 | G96: 259.235 | H96: 237.511 | I96: 215.552 | J96: 259.782 | K96: 266.827
A97: 기타 | C97: 200.719 | D97: 248.862 | E97: 228.177 | F97: 373.666 | G97: 350.728 | H97: 86.246 | I97: 86.726 | J97: 68.027 | K97: 248.862
A98: 대손충당금 | C98: -0.151 | D98: -0.151 | E98: -0.151 | F98: -0.151 | G98: -0.151 | H98: -0.151 | I98: -0.151 | J98: -0.151 | K98: -0.151
A99: 투자 및 기타자산 합계 | C99: 2258.943 | D99: 2290.969 | E99: 2284.982 | F99: 2522.382 | G99: 2487.982 | H99: 1842.063 | I99: 1935.922 | J99: 2156.515 | K99: 2290.969
A100: 비유동자산 합계 | C100: 14609.096 | D100: 16792.466 | E100: 18231.458 | F100: 22050.124 | G100: 23359.552 | H100: 5716.793 | I100: 7399.641 | J100: 10368.085 | K100: 16792.466
A101: 자산 합계 | C101: 18956.654 | D101: 21264.732 | E101: 22134.789 | F101: 25242.833 | G101: 28680.149 | H101: 7760.11 | I101: 11406.97 | J101: 15894.719 | K101: 21264.732
A102: Operating Accounts Payable | C102: 541.253 | D102: 625.426 | E102: 472.374 | F102: 558.884 | G102: 810.399 | H102: 435.131 | I102: 463.622 | J102: 503.097 | K102: 625.426
...

Sheet 출처
A1: 출처 · 쓴 결산단신
A3: 공시일 | B3: 문서 | C3: PDF
A4: 2026-07-28 | B4: 2026년 9월 결산기 3분기 결산단신 | C4: https://www2.jpx.co.jp/disc/55320/140120260728500659.pdf
A5: 2026-04-28 | B5: 2026년 9월 결산기 2분기 결산단신 | C5: https://www2.jpx.co.jp/disc/55320/140120260428512875.pdf
A6: 2026-01-27 | B6: 2026년 9월 결산기 1분기 결산단신 | C6: https://www2.jpx.co.jp/disc/55320/140120260127539012.pdf
A7: 2025-10-28 | B7: 2025년 9월 결산기 연간 결산단신 | C7: https://www2.jpx.co.jp/disc/55320/140120251028580040.pdf
A8: 2025-07-29 | B8: 2025년 9월 결산기 3분기 결산단신 | C8: https://www2.jpx.co.jp/disc/55320/140120250729522255.pdf
A9: 2025-04-22 | B9: 2025년 9월 결산기 2분기 결산단신 | C9: https://www2.jpx.co.jp/disc/55320/140120250422520002.pdf
A10: 2025-01-28 | B10: 2025년 9월 결산기 1분기 결산단신 | C10: https://www2.jpx.co.jp/disc/55320/140120250128556236.pdf
A11: 2024-10-29 | B11: 2024년 9월 결산기 연간 결산단신 | C11: https://www2.jpx.co.jp/disc/55320/140120241029504911.pdf
A12: 2024-07-30 | B12: 2024년 9월 결산기 3분기 결산단신 | C12: https://www2.jpx.co.jp/disc/55320/140120240730557600.pdf
A13: 2024-04-23 | B13: 2024년 9월 결산기 2분기 결산단신 | C13: https://www2.jpx.co.jp/disc/55320/140120240423574540.pdf
A14: 2024-01-30 | B14: 2024년 9월 결산기 1분기 결산단신 | C14: https://www2.jpx.co.jp/disc/55320/140120240130521750.pdf
... A16: 2023-07-25 | B16: 2023년 9월 결산기 3분기 결산단신 | C16: https://www2.jpx.co.jp/disc/55320/140120230725526381.pdf
