Workbook

Sheet 연간
A1: 6663 Model
A2: 모를 땐 보수적으로 | B2: (단위: 백만엔) | C2: 11월 결산 · 일본 기준 · 2026.4Q = 2026년 11월 결산기 4분기 | Y2: (추정: 파란 글씨 = 직접 입력)
A3: 항목 | B3: 참고 | C3: 2024.1Q | D3: 2024.2Q | E3: 2024.3Q | F3: 2024.4Q | G3: 2025.1Q | H3: 2025.2Q | I3: 2025.3Q | J3: 2025.4Q | K3: 2026.1Q | L3: 2026.2Q | M3: 2026.3Q | N3: 2026.4Q | O3: 2017 | P3: 2018 | Q3: 2019 | R3: 2020 | S3: 2021 | T3: 2022 | U3: 2023 | V3: 2024 | W3: 2025 | X3: 2026 | Y3: 2027(MW) | Z3: 2028(MW) | AA3: 2029(MW) | AB3: 2030(MW) | AC3: 2031(MW)
A4: 매출액 | B4: MW = 제품 합계 | C4: 865.849 | D4: 894.376 | E4: 997.932 | F4: 653.308 | G4: 783.899 | H4: 823.261 | I4: 1011.058 | J4: 901.082 | K4: 820.764 | L4: 961.948 | O4: 4979.906 | P4: 4238.765 | Q4: 4582.357 | R4: 3896.341 | S4: 3175.189 | T4: 3917.94 | U4: 3625.517 | V4: 3411.465 | W4: 3519.3 | X4: 3751.667 | Y4: =IF(COUNT(Y7,Y10,Y13,Y16)=0,"",SUM(Y7,Y10,Y13,Y16)) | Z4: =IF(COUNT(Z7,Z10,Z13,Z16)=0,"",SUM(Z7,Z10,Z13,Z16)) | AA4: =IF(COUNT(AA7,AA10,AA13,AA16)=0,"",SUM(AA7,AA10,AA13,AA16)) | AB4: =IF(COUNT(AB7,AB10,AB13,AB16)=0,"",SUM(AB7,AB10,AB13,AB16)) | AC4: =IF(COUNT(AC7,AC10,AC13,AC16)=0,"",SUM(AC7,AC10,AC13,AC16))
A5: YoY | G5: =IF(OR(G4="",C4=""),"",IFERROR(G4/C4-1,"")) | H5: =IF(OR(H4="",D4=""),"",IFERROR(H4/D4-1,"")) | I5: =IF(OR(I4="",E4=""),"",IFERROR(I4/E4-1,"")) | J5: =IF(OR(J4="",F4=""),"",IFERROR(J4/F4-1,"")) | K5: =IF(OR(K4="",G4=""),"",IFERROR(K4/G4-1,"")) | L5: =IF(OR(L4="",H4=""),"",IFERROR(L4/H4-1,"")) | M5: =IF(OR(M4="",I4=""),"",IFERROR(M4/I4-1,"")) | N5: =IF(OR(N4="",J4=""),"",IFERROR(N4/J4-1,"")) | P5: =IF(OR(P4="",O4=""),"",IFERROR(P4/O4-1,"")) | Q5: =IF(OR(Q4="",P4=""),"",IFERROR(Q4/P4-1,"")) | R5: =IF(OR(R4="",Q4=""),"",IFERROR(R4/Q4-1,"")) | S5: =IF(OR(S4="",R4=""),"",IFERROR(S4/R4-1,"")) | T5: =IF(OR(T4="",S4=""),"",IFERROR(T4/S4-1,"")) | U5: =IF(OR(U4="",T4=""),"",IFERROR(U4/T4-1,"")) | V5: =IF(OR(V4="",U4=""),"",IFERROR(V4/U4-1,"")) | W5: =IF(OR(W4="",V4=""),"",IFERROR(W4/V4-1,"")) | ... AC5: =IF(OR(AC4="",AB4=""),"",IFERROR(AC4/AB4-1,""))
A6: 제품별 매출 분류 | B6: 사업보고서 매출실적
A7: 부문 | C7: 572.255 | D7: 580.651 | E7: 564.595 | F7: 701.874 | G7: 574.353 | H7: 584.717 | I7: 548.37 | J7: 559.268 | K7: 649.97 | L7: 673.094 | V7: 2419.375 | W7: 2266.708 | X7: 2409.323
A8: 비중 | C8: =IF(OR(C7="",C4=""),"",IFERROR(C7/C4,"")) | D8: =IF(OR(D7="",D4=""),"",IFERROR(D7/D4,"")) | E8: =IF(OR(E7="",E4=""),"",IFERROR(E7/E4,"")) | F8: =IF(OR(F7="",F4=""),"",IFERROR(F7/F4,"")) | G8: =IF(OR(G7="",G4=""),"",IFERROR(G7/G4,"")) | H8: =IF(OR(H7="",H4=""),"",IFERROR(H7/H4,"")) | I8: =IF(OR(I7="",I4=""),"",IFERROR(I7/I4,"")) | J8: =IF(OR(J7="",J4=""),"",IFERROR(J7/J4,"")) | ... AC8: =IF(OR(AC7="",AC4=""),"",IFERROR(AC7/AC4,""))
A9: YoY | G9: =IF(OR(G7="",C7=""),"",IFERROR(G7/C7-1,"")) | H9: =IF(OR(H7="",D7=""),"",IFERROR(H7/D7-1,"")) | I9: =IF(OR(I7="",E7=""),"",IFERROR(I7/E7-1,"")) | J9: =IF(OR(J7="",F7=""),"",IFERROR(J7/F7-1,"")) | K9: =IF(OR(K7="",G7=""),"",IFERROR(K7/G7-1,"")) | L9: =IF(OR(L7="",H7=""),"",IFERROR(L7/H7-1,"")) | M9: =IF(OR(M7="",I7=""),"",IFERROR(M7/I7-1,"")) | N9: =IF(OR(N7="",J7=""),"",IFERROR(N7/J7-1,"")) | P9: =IF(OR(P7="",O7=""),"",IFERROR(P7/O7-1,"")) | Q9: =IF(OR(Q7="",P7=""),"",IFERROR(Q7/P7-1,"")) | R9: =IF(OR(R7="",Q7=""),"",IFERROR(R7/Q7-1,"")) | S9: =IF(OR(S7="",R7=""),"",IFERROR(S7/R7-1,"")) | T9: =IF(OR(T7="",S7=""),"",IFERROR(T7/S7-1,"")) | U9: =IF(OR(U7="",T7=""),"",IFERROR(U7/T7-1,"")) | V9: =IF(OR(V7="",U7=""),"",IFERROR(V7/U7-1,"")) | W9: =IF(OR(W7="",V7=""),"",IFERROR(W7/V7-1,"")) | ... AC9: =IF(OR(AC7="",AB7=""),"",IFERROR(AC7/AB7-1,""))
A10: 부문 | C10: 175.585 | D10: 173.913 | E10: 243.186 | F10: -171.931 | G10: 77.954 | H10: 61.254 | I10: 80.823 | J10: 477.705 | K10: 76.842 | L10: 116.365 | V10: 420.753 | W10: 697.736 | X10: 450.982
A11: 비중 | C11: =IF(OR(C10="",C4=""),"",IFERROR(C10/C4,"")) | D11: =IF(OR(D10="",D4=""),"",IFERROR(D10/D4,"")) | E11: =IF(OR(E10="",E4=""),"",IFERROR(E10/E4,"")) | F11: =IF(OR(F10="",F4=""),"",IFERROR(F10/F4,"")) | G11: =IF(OR(G10="",G4=""),"",IFERROR(G10/G4,"")) | H11: =IF(OR(H10="",H4=""),"",IFERROR(H10/H4,"")) | I11: =IF(OR(I10="",I4=""),"",IFERROR(I10/I4,"")) | J11: =IF(OR(J10="",J4=""),"",IFERROR(J10/J4,"")) | ... AC11: =IF(OR(AC10="",AC4=""),"",IFERROR(AC10/AC4,""))
A12: YoY | G12: =IF(OR(G10="",C10=""),"",IFERROR(G10/C10-1,"")) | H12: =IF(OR(H10="",D10=""),"",IFERROR(H10/D10-1,"")) | I12: =IF(OR(I10="",E10=""),"",IFERROR(I10/E10-1,"")) | J12: =IF(OR(J10="",F10=""),"",IFERROR(J10/F10-1,"")) | K12: =IF(OR(K10="",G10=""),"",IFERROR(K10/G10-1,"")) | L12: =IF(OR(L10="",H10=""),"",IFERROR(L10/H10-1,"")) | M12: =IF(OR(M10="",I10=""),"",IFERROR(M10/I10-1,"")) | N12: =IF(OR(N10="",J10=""),"",IFERROR(N10/J10-1,"")) | P12: =IF(OR(P10="",O10=""),"",IFERROR(P10/O10-1,"")) | Q12: =IF(OR(Q10="",P10=""),"",IFERROR(Q10/P10-1,"")) | R12: =IF(OR(R10="",Q10=""),"",IFERROR(R10/Q10-1,"")) | S12: =IF(OR(S10="",R10=""),"",IFERROR(S10/R10-1,"")) | T12: =IF(OR(T10="",S10=""),"",IFERROR(T10/S10-1,"")) | U12: =IF(OR(U10="",T10=""),"",IFERROR(U10/T10-1,"")) | V12: =IF(OR(V10="",U10=""),"",IFERROR(V10/U10-1,"")) | W12: =IF(OR(W10="",V10=""),"",IFERROR(W10/V10-1,"")) | ... AC12: =IF(OR(AC10="",AB10=""),"",IFERROR(AC10/AB10-1,""))
A13: 부문 | C13: 102.012 | D13: 90.459 | E13: 134.637 | F13: 69.611 | G13: 119.334 | H13: 97.19 | I13: 104.111 | J13: 101.201 | K13: 65.52 | L13: 133.173 | V13: 396.719 | W13: 421.836 | X13: 445.667
A14: 비중 | C14: =IF(OR(C13="",C4=""),"",IFERROR(C13/C4,"")) | D14: =IF(OR(D13="",D4=""),"",IFERROR(D13/D4,"")) | E14: =IF(OR(E13="",E4=""),"",IFERROR(E13/E4,"")) | F14: =IF(OR(F13="",F4=""),"",IFERROR(F13/F4,"")) | G14: =IF(OR(G13="",G4=""),"",IFERROR(G13/G4,"")) | H14: =IF(OR(H13="",H4=""),"",IFERROR(H13/H4,"")) | I14: =IF(OR(I13="",I4=""),"",IFERROR(I13/I4,"")) | J14: =IF(OR(J13="",J4=""),"",IFERROR(J13/J4,"")) | ... AC14: =IF(OR(AC13="",AC4=""),"",IFERROR(AC13/AC4,""))
A15: YoY | G15: =IF(OR(G13="",C13=""),"",IFERROR(G13/C13-1,"")) | H15: =IF(OR(H13="",D13=""),"",IFERROR(H13/D13-1,"")) | I15: =IF(OR(I13="",E13=""),"",IFERROR(I13/E13-1,"")) | J15: =IF(OR(J13="",F13=""),"",IFERROR(J13/F13-1,"")) | K15: =IF(OR(K13="",G13=""),"",IFERROR(K13/G13-1,"")) | L15: =IF(OR(L13="",H13=""),"",IFERROR(L13/H13-1,"")) | M15: =IF(OR(M13="",I13=""),"",IFERROR(M13/I13-1,"")) | N15: =IF(OR(N13="",J13=""),"",IFERROR(N13/J13-1,"")) | P15: =IF(OR(P13="",O13=""),"",IFERROR(P13/O13-1,"")) | Q15: =IF(OR(Q13="",P13=""),"",IFERROR(Q13/P13-1,"")) | R15: =IF(OR(R13="",Q13=""),"",IFERROR(R13/Q13-1,"")) | S15: =IF(OR(S13="",R13=""),"",IFERROR(S13/R13-1,"")) | T15: =IF(OR(T13="",S13=""),"",IFERROR(T13/S13-1,"")) | U15: =IF(OR(U13="",T13=""),"",IFERROR(U13/T13-1,"")) | V15: =IF(OR(V13="",U13=""),"",IFERROR(V13/U13-1,"")) | W15: =IF(OR(W13="",V13=""),"",IFERROR(W13/V13-1,"")) | ... AC15: =IF(OR(AC13="",AB13=""),"",IFERROR(AC13/AB13-1,""))
A16: 부문 | C16: 15.995 | D16: 49.354 | E16: 55.512 | F16: 53.756 | G16: 12.257 | H16: 80.099 | I16: 277.755 | J16: -237.092 | K16: 28.43 | L16: 39.316 | V16: 174.617 | W16: 133.019 | X16: 445.693
A17: 비중 | C17: =IF(OR(C16="",C4=""),"",IFERROR(C16/C4,"")) | D17: =IF(OR(D16="",D4=""),"",IFERROR(D16/D4,"")) | E17: =IF(OR(E16="",E4=""),"",IFERROR(E16/E4,"")) | F17: =IF(OR(F16="",F4=""),"",IFERROR(F16/F4,"")) | G17: =IF(OR(G16="",G4=""),"",IFERROR(G16/G4,"")) | H17: =IF(OR(H16="",H4=""),"",IFERROR(H16/H4,"")) | I17: =IF(OR(I16="",I4=""),"",IFERROR(I16/I4,"")) | J17: =IF(OR(J16="",J4=""),"",IFERROR(J16/J4,"")) | ... AC17: =IF(OR(AC16="",AC4=""),"",IFERROR(AC16/AC4,""))
A18: YoY | G18: =IF(OR(G16="",C16=""),"",IFERROR(G16/C16-1,"")) | H18: =IF(OR(H16="",D16=""),"",IFERROR(H16/D16-1,"")) | I18: =IF(OR(I16="",E16=""),"",IFERROR(I16/E16-1,"")) | J18: =IF(OR(J16="",F16=""),"",IFERROR(J16/F16-1,"")) | K18: =IF(OR(K16="",G16=""),"",IFERROR(K16/G16-1,"")) | L18: =IF(OR(L16="",H16=""),"",IFERROR(L16/H16-1,"")) | M18: =IF(OR(M16="",I16=""),"",IFERROR(M16/I16-1,"")) | N18: =IF(OR(N16="",J16=""),"",IFERROR(N16/J16-1,"")) | P18: =IF(OR(P16="",O16=""),"",IFERROR(P16/O16-1,"")) | Q18: =IF(OR(Q16="",P16=""),"",IFERROR(Q16/P16-1,"")) | R18: =IF(OR(R16="",Q16=""),"",IFERROR(R16/Q16-1,"")) | S18: =IF(OR(S16="",R16=""),"",IFERROR(S16/R16-1,"")) | T18: =IF(OR(T16="",S16=""),"",IFERROR(T16/S16-1,"")) | U18: =IF(OR(U16="",T16=""),"",IFERROR(U16/T16-1,"")) | V18: =IF(OR(V16="",U16=""),"",IFERROR(V16/U16-1,"")) | W18: =IF(OR(W16="",V16=""),"",IFERROR(W16/V16-1,"")) | ... AC18: =IF(OR(AC16="",AB16=""),"",IFERROR(AC16/AB16-1,""))
A19: 매출원가
A20: 전체 매출원가 | C20: 593.605 | D20: 670.452 | E20: 697.359 | F20: 505.74 | G20: 562.78 | H20: 583.814 | I20: 759.414 | J20: 603.213 | K20: 546.983 | L20: 652.153 | O20: 3747.426 | P20: 3095.518 | Q20: 3263.75 | R20: 2834.274 | S20: 2540.878 | T20: 2726.187 | U20: 2583.747 | V20: 2467.156 | W20: 2509.221 | X20: 2627.606
A21: 매출총이익 | C21: =IF(OR(C4="",C20=""),"",IFERROR(C4-C20,"")) | D21: =IF(OR(D4="",D20=""),"",IFERROR(D4-D20,"")) | E21: =IF(OR(E4="",E20=""),"",IFERROR(E4-E20,"")) | F21: =IF(OR(F4="",F20=""),"",IFERROR(F4-F20,"")) | G21: =IF(OR(G4="",G20=""),"",IFERROR(G4-G20,"")) | H21: =IF(OR(H4="",H20=""),"",IFERROR(H4-H20,"")) | I21: =IF(OR(I4="",I20=""),"",IFERROR(I4-I20,"")) | J21: =IF(OR(J4="",J20=""),"",IFERROR(J4-J20,"")) | ... X21: =IF(OR(X4="",X20=""),"",IFERROR(X4-X20,""))
A22: GPM | C22: =IF(OR(C21="",C4=""),"",IFERROR(C21/C4,"")) | D22: =IF(OR(D21="",D4=""),"",IFERROR(D21/D4,"")) | E22: =IF(OR(E21="",E4=""),"",IFERROR(E21/E4,"")) | F22: =IF(OR(F21="",F4=""),"",IFERROR(F21/F4,"")) | G22: =IF(OR(G21="",G4=""),"",IFERROR(G21/G4,"")) | H22: =IF(OR(H21="",H4=""),"",IFERROR(H21/H4,"")) | I22: =IF(OR(I21="",I4=""),"",IFERROR(I21/I4,"")) | J22: =IF(OR(J21="",J4=""),"",IFERROR(J21/J4,"")) | ... AC22: =IF(OR(AC21="",AC4=""),"",IFERROR(AC21/AC4,""))
A23: 판매관리비
A24: 전체 판관비 | C24: 270.476 | D24: 260.157 | E24: 269.416 | F24: 286.133 | G24: 280.648 | H24: 237.353 | I24: 227.358 | J24: 318.807 | K24: 249.62 | L24: 250.577 | O24: 1175.282 | P24: 1173.203 | Q24: 1196.519 | R24: 1175.836 | S24: 1060.003 | T24: 1070.503 | U24: 1069.554 | V24: 1086.182 | W24: 1064.166 | X24: 981.488
A25: 영업이익 | B25: MW = 매출 × OPM | C25: 1.767 | D25: -36.232 | E25: 31.156 | F25: -138.564 | G25: -59.528 | H25: 2.093 | I25: 24.286 | J25: -20.939 | K25: 24.16 | L25: 59.218 | O25: 57.197 | P25: -29.956 | Q25: 122.086 | R25: -113.769 | S25: -425.693 | T25: 121.249 | U25: -27.783 | V25: -141.873 | W25: -54.088 | X25: 142.572 | Y25: =IF(OR(Y4="",Y26=""),"",IFERROR(Y4*Y26,"")) | Z25: =IF(OR(Z4="",Z26=""),"",IFERROR(Z4*Z26,"")) | AA25: =IF(OR(AA4="",AA26=""),"",IFERROR(AA4*AA26,"")) | AB25: =IF(OR(AB4="",AB26=""),"",IFERROR(AB4*AB26,"")) | AC25: =IF(OR(AC4="",AC26=""),"",IFERROR(AC4*AC26,""))
A26: OPM | B26: MW 입력 | C26: =IF(OR(C25="",C4=""),"",IFERROR(C25/C4,"")) | D26: =IF(OR(D25="",D4=""),"",IFERROR(D25/D4,"")) | E26: =IF(OR(E25="",E4=""),"",IFERROR(E25/E4,"")) | F26: =IF(OR(F25="",F4=""),"",IFERROR(F25/F4,"")) | G26: =IF(OR(G25="",G4=""),"",IFERROR(G25/G4,"")) | H26: =IF(OR(H25="",H4=""),"",IFERROR(H25/H4,"")) | I26: =IF(OR(I25="",I4=""),"",IFERROR(I25/I4,"")) | J26: =IF(OR(J25="",J4=""),"",IFERROR(J25/J4,"")) | ... X26: =IF(OR(X25="",X4=""),"",IFERROR(X25/X4,""))
A27: 증가율 | G27: =IF(OR(G25="",C25=""),"",IFERROR(G25/C25-1,"")) | H27: =IF(OR(H25="",D25=""),"",IFERROR(H25/D25-1,"")) | I27: =IF(OR(I25="",E25=""),"",IFERROR(I25/E25-1,"")) | J27: =IF(OR(J25="",F25=""),"",IFERROR(J25/F25-1,"")) | K27: =IF(OR(K25="",G25=""),"",IFERROR(K25/G25-1,"")) | L27: =IF(OR(L25="",H25=""),"",IFERROR(L25/H25-1,"")) | M27: =IF(OR(M25="",I25=""),"",IFERROR(M25/I25-1,"")) | N27: =IF(OR(N25="",J25=""),"",IFERROR(N25/J25-1,"")) | P27: =IF(OR(P25="",O25=""),"",IFERROR(P25/O25-1,"")) | Q27: =IF(OR(Q25="",P25=""),"",IFERROR(Q25/P25-1,"")) | R27: =IF(OR(R25="",Q25=""),"",IFERROR(R25/Q25-1,"")) | S27: =IF(OR(S25="",R25=""),"",IFERROR(S25/R25-1,"")) | T27: =IF(OR(T25="",S25=""),"",IFERROR(T25/S25-1,"")) | U27: =IF(OR(U25="",T25=""),"",IFERROR(U25/T25-1,"")) | V27: =IF(OR(V25="",U25=""),"",IFERROR(V25/U25-1,"")) | W27: =IF(OR(W25="",V25=""),"",IFERROR(W25/V25-1,"")) | ... AC27: =IF(OR(AC25="",AB25=""),"",IFERROR(AC25/AB25-1,""))
A28: 비용의 성격별 분류 | B28: 참고 데이터
A29: 총 판관비 | O29: =IF(O24="","",O24) | P29: =IF(P24="","",P24) | Q29: =IF(Q24="","",Q24) | R29: =IF(R24="","",R24) | S29: =IF(S24="","",S24) | T29: =IF(T24="","",T24) | U29: =IF(U24="","",U24) | V29: =IF(V24="","",V24) | ... X29: =IF(X24="","",X24)
A30: 급여 | B30: 고정비
A31: % of Sales | O31: =IF(OR(O30="",O4=""),"",IFERROR(O30/O4,"")) | P31: =IF(OR(P30="",P4=""),"",IFERROR(P30/P4,"")) | Q31: =IF(OR(Q30="",Q4=""),"",IFERROR(Q30/Q4,"")) | R31: =IF(OR(R30="",R4=""),"",IFERROR(R30/R4,"")) | S31: =IF(OR(S30="",S4=""),"",IFERROR(S30/S4,"")) | T31: =IF(OR(T30="",T4=""),"",IFERROR(T30/T4,"")) | U31: =IF(OR(U30="",U4=""),"",IFERROR(U30/U4,"")) | V31: =IF(OR(V30="",V4=""),"",IFERROR(V30/V4,"")) | ... X31: =IF(OR(X30="",X4=""),"",IFERROR(X30/X4,""))
A32: 감가상각비 | B32: 고정비
A33: % of Sales | O33: =IF(OR(O32="",O4=""),"",IFERROR(O32/O4,"")) | P33: =IF(OR(P32="",P4=""),"",IFERROR(P32/P4,"")) | Q33: =IF(OR(Q32="",Q4=""),"",IFERROR(Q32/Q4,"")) | R33: =IF(OR(R32="",R4=""),"",IFERROR(R32/R4,"")) | S33: =IF(OR(S32="",S4=""),"",IFERROR(S32/S4,"")) | T33: =IF(OR(T32="",T4=""),"",IFERROR(T32/T4,"")) | U33: =IF(OR(U32="",U4=""),"",IFERROR(U32/U4,"")) | V33: =IF(OR(V32="",V4=""),"",IFERROR(V32/V4,"")) | ... X33: =IF(OR(X32="",X4=""),"",IFERROR(X32/X4,""))
A34: 지급수수료 | B34: 고정비
A35: % of Sales | O35: =IF(OR(O34="",O4=""),"",IFERROR(O34/O4,"")) | P35: =IF(OR(P34="",P4=""),"",IFERROR(P34/P4,"")) | Q35: =IF(OR(Q34="",Q4=""),"",IFERROR(Q34/Q4,"")) | R35: =IF(OR(R34="",R4=""),"",IFERROR(R34/R4,"")) | S35: =IF(OR(S34="",S4=""),"",IFERROR(S34/S4,"")) | T35: =IF(OR(T34="",T4=""),"",IFERROR(T34/T4,"")) | U35: =IF(OR(U34="",U4=""),"",IFERROR(U34/U4,"")) | V35: =IF(OR(V34="",V4=""),"",IFERROR(V34/V4,"")) | ... X35: =IF(OR(X34="",X4=""),"",IFERROR(X34/X4,""))
A36: 연구개발비 | B36: 변동비
A37: % of Sales | O37: =IF(OR(O36="",O4=""),"",IFERROR(O36/O4,"")) | P37: =IF(OR(P36="",P4=""),"",IFERROR(P36/P4,"")) | Q37: =IF(OR(Q36="",Q4=""),"",IFERROR(Q36/Q4,"")) | R37: =IF(OR(R36="",R4=""),"",IFERROR(R36/R4,"")) | S37: =IF(OR(S36="",S4=""),"",IFERROR(S36/S4,"")) | T37: =IF(OR(T36="",T4=""),"",IFERROR(T36/T4,"")) | U37: =IF(OR(U36="",U4=""),"",IFERROR(U36/U4,"")) | V37: =IF(OR(V36="",V4=""),"",IFERROR(V36/V4,"")) | ... X37: =IF(OR(X36="",X4=""),"",IFERROR(X36/X4,""))
A38: 기타비용 | B38: 변동비 | O38: =IF(OR(O29="",O30="",O32="",O34="",O36=""),"",IFERROR(O29-O30-O32-O34-O36,"")) | P38: =IF(OR(P29="",P30="",P32="",P34="",P36=""),"",IFERROR(P29-P30-P32-P34-P36,"")) | Q38: =IF(OR(Q29="",Q30="",Q32="",Q34="",Q36=""),"",IFERROR(Q29-Q30-Q32-Q34-Q36,"")) | R38: =IF(OR(R29="",R30="",R32="",R34="",R36=""),"",IFERROR(R29-R30-R32-R34-R36,"")) | S38: =IF(OR(S29="",S30="",S32="",S34="",S36=""),"",IFERROR(S29-S30-S32-S34-S36,"")) | T38: =IF(OR(T29="",T30="",T32="",T34="",T36=""),"",IFERROR(T29-T30-T32-T34-T36,"")) | U38: =IF(OR(U29="",U30="",U32="",U34="",U36=""),"",IFERROR(U29-U30-U32-U34-U36,"")) | V38: =IF(OR(V29="",V30="",V32="",V34="",V36=""),"",IFERROR(V29-V30-V32-V34-V36,"")) | ... X38: =IF(OR(X29="",X30="",X32="",X34="",X36=""),"",IFERROR(X29-X30-X32-X34-X36,""))
A39: % of Sales | O39: =IF(OR(O38="",O4=""),"",IFERROR(O38/O4,"")) | P39: =IF(OR(P38="",P4=""),"",IFERROR(P38/P4,"")) | Q39: =IF(OR(Q38="",Q4=""),"",IFERROR(Q38/Q4,"")) | R39: =IF(OR(R38="",R4=""),"",IFERROR(R38/R4,"")) | S39: =IF(OR(S38="",S4=""),"",IFERROR(S38/S4,"")) | T39: =IF(OR(T38="",T4=""),"",IFERROR(T38/T4,"")) | U39: =IF(OR(U38="",U4=""),"",IFERROR(U38/U4,"")) | V39: =IF(OR(V38="",V4=""),"",IFERROR(V38/V4,"")) | ... X39: =IF(OR(X38="",X4=""),"",IFERROR(X38/X4,""))
A40: 당기순이익 추정
A41: 특별이익 | C41: 8.366 | D41: 0 | E41: 0 | F41: 90.357 | G41: 44.754 | H41: 0 | I41: 14.29 | J41: -50.541 | K41: 0 | L41: 0 | O41: 0.033 | P41: 14.381 | Q41: 1.776 | R41: 43.855 | S41: 0 | T41: 9.982 | U41: 5.958 | V41: 98.723 | W41: 8.503 | X41: 59.169 | Y41: =IF(OR(Y4="",Y42=""),"",IFERROR(Y4*Y42,"")) | Z41: =IF(OR(Z4="",Z42=""),"",IFERROR(Z4*Z42,"")) | AA41: =IF(OR(AA4="",AA42=""),"",IFERROR(AA4*AA42,"")) | AB41: =IF(OR(AB4="",AB42=""),"",IFERROR(AB4*AB42,"")) | AC41: =IF(OR(AC4="",AC42=""),"",IFERROR(AC4*AC42,""))
A42: % of Sales | B42: MW = 최근 3년 평균 | C42: =IF(OR(C41="",C4=""),"",IFERROR(C41/C4,"")) | D42: =IF(OR(D41="",D4=""),"",IFERROR(D41/D4,"")) | E42: =IF(OR(E41="",E4=""),"",IFERROR(E41/E4,"")) | F42: =IF(OR(F41="",F4=""),"",IFERROR(F41/F4,"")) | G42: =IF(OR(G41="",G4=""),"",IFERROR(G41/G4,"")) | H42: =IF(OR(H41="",H4=""),"",IFERROR(H41/H4,"")) | I42: =IF(OR(I41="",I4=""),"",IFERROR(I41/I4,"")) | J42: =IF(OR(J41="",J4=""),"",IFERROR(J41/J4,"")) | ... X42: =IF(OR(X41="",X4=""),"",IFERROR(X41/X4,"")) | Y42: =IFERROR(AVERAGE(V42,W42,X42),"") | Z42: =Y42 | AA42: =Z42 | AB42: =AA42 | AC42: =AB42
A43: 특별손실 | C43: 8.366 | D43: 0.04 | E43: 0 | F43: 105.003 | G43: 0 | H43: 44.417 | I43: 0 | J43: -32.805 | K43: 8.57 | L43: 0.157 | O43: 107.946 | P43: 25.709 | Q43: 6.774 | R43: 16.732 | S43: 302.05 | T43: 5.281 | U43: 8.981 | V43: 113.409 | W43: 11.612 | X43: 48.386 | Y43: =IF(OR(Y4="",Y44=""),"",IFERROR(Y4*Y44,"")) | Z43: =IF(OR(Z4="",Z44=""),"",IFERROR(Z4*Z44,"")) | AA43: =IF(OR(AA4="",AA44=""),"",IFERROR(AA4*AA44,"")) | AB43: =IF(OR(AB4="",AB44=""),"",IFERROR(AB4*AB44,"")) | AC43: =IF(OR(AC4="",AC44=""),"",IFERROR(AC4*AC44,""))
A44: % of Sales | C44: =IF(OR(C43="",C4=""),"",IFERROR(C43/C4,"")) | D44: =IF(OR(D43="",D4=""),"",IFERROR(D43/D4,"")) | E44: =IF(OR(E43="",E4=""),"",IFERROR(E43/E4,"")) | F44: =IF(OR(F43="",F4=""),"",IFERROR(F43/F4,"")) | G44: =IF(OR(G43="",G4=""),"",IFERROR(G43/G4,"")) | H44: =IF(OR(H43="",H4=""),"",IFERROR(H43/H4,"")) | I44: =IF(OR(I43="",I4=""),"",IFERROR(I43/I4,"")) | J44: =IF(OR(J43="",J4=""),"",IFERROR(J43/J4,"")) | ... X44: =IF(OR(X43="",X4=""),"",IFERROR(X43/X4,"")) | Y44: =IFERROR(AVERAGE(V44,W44,X44),"") | Z44: =Y44 | AA44: =Z44 | AB44: =AA44 | AC44: =AB44
A45: 영업외수익 | C45: 5.244 | D45: 2.85 | E45: 7.246 | F45: 34.618 | G45: 3.628 | H45: 2.836 | I45: 10.154 | J45: 7.777 | K45: 3.561 | L45: 1.799 | O45: 66.099 | P45: 69.571 | Q45: 32.171 | R45: 47.923 | S45: 132.555 | T45: 147.987 | U45: 88.183 | V45: 49.958 | W45: 24.395 | X45: 32.946 | Y45: =IF(OR(Y4="",Y46=""),"",IFERROR(Y4*Y46,"")) | Z45: =IF(OR(Z4="",Z46=""),"",IFERROR(Z4*Z46,"")) | AA45: =IF(OR(AA4="",AA46=""),"",IFERROR(AA4*AA46,"")) | AB45: =IF(OR(AB4="",AB46=""),"",IFERROR(AB4*AB46,"")) | AC45: =IF(OR(AC4="",AC46=""),"",IFERROR(AC4*AC46,""))
A46: % of Sales | C46: =IF(OR(C45="",C4=""),"",IFERROR(C45/C4,"")) | D46: =IF(OR(D45="",D4=""),"",IFERROR(D45/D4,"")) | E46: =IF(OR(E45="",E4=""),"",IFERROR(E45/E4,"")) | F46: =IF(OR(F45="",F4=""),"",IFERROR(F45/F4,"")) | G46: =IF(OR(G45="",G4=""),"",IFERROR(G45/G4,"")) | H46: =IF(OR(H45="",H4=""),"",IFERROR(H45/H4,"")) | I46: =IF(OR(I45="",I4=""),"",IFERROR(I45/I4,"")) | J46: =IF(OR(J45="",J4=""),"",IFERROR(J45/J4,"")) | ... X46: =IF(OR(X45="",X4=""),"",IFERROR(X45/X4,"")) | Y46: =IFERROR(AVERAGE(V46,W46,X46),"") | Z46: =Y46 | AA46: =Z46 | AB46: =AA46 | AC46: =AB46
A47: 영업외비용 | C47: 3.143 | D47: 5.582 | E47: 6.459 | F47: 0.977 | G47: 4.895 | H47: 4.034 | I47: 6.238 | J47: 2.383 | K47: 5.193 | L47: 4.087 | O47: 29.313 | P47: 17.679 | Q47: 23.617 | R47: 22.001 | S47: 21.106 | T47: 15.591 | U47: 14.688 | V47: 16.161 | W47: 17.55 | X47: 17.177 | Y47: =IF(OR(Y4="",Y48=""),"",IFERROR(Y4*Y48,"")) | Z47: =IF(OR(Z4="",Z48=""),"",IFERROR(Z4*Z48,"")) | AA47: =IF(OR(AA4="",AA48=""),"",IFERROR(AA4*AA48,"")) | AB47: =IF(OR(AB4="",AB48=""),"",IFERROR(AB4*AB48,"")) | AC47: =IF(OR(AC4="",AC48=""),"",IFERROR(AC4*AC48,""))
A48: % of Sales | C48: =IF(OR(C47="",C4=""),"",IFERROR(C47/C4,"")) | D48: =IF(OR(D47="",D4=""),"",IFERROR(D47/D4,"")) | E48: =IF(OR(E47="",E4=""),"",IFERROR(E47/E4,"")) | F48: =IF(OR(F47="",F4=""),"",IFERROR(F47/F4,"")) | G48: =IF(OR(G47="",G4=""),"",IFERROR(G47/G4,"")) | H48: =IF(OR(H47="",H4=""),"",IFERROR(H47/H4,"")) | I48: =IF(OR(I47="",I4=""),"",IFERROR(I47/I4,"")) | J48: =IF(OR(J47="",J4=""),"",IFERROR(J47/J4,"")) | ... X48: =IF(OR(X47="",X4=""),"",IFERROR(X47/X4,"")) | Y48: =IFERROR(AVERAGE(V48,W48,X48),"") | Z48: =Y48 | AA48: =Z48 | AB48: =AA48 | AC48: =AB48
A49: 법인세비용차감전순이익(손실) | C49: 3.868 | D49: -39.004 | E49: 31.944 | F49: -119.57 | G49: -16.041 | H49: -43.522 | I49: 42.491 | J49: -33.28 | K49: 13.958 | L49: 56.773 | O49: -13.928 | P49: 10.607 | Q49: 125.642 | R49: -60.724 | S49: -616.295 | T49: 258.347 | U49: 42.687 | V49: -122.762 | W49: -50.352 | X49: 169.125 | Y49: =IF(OR(Y25=""),"",IFERROR(Y25+N(Y41)-N(Y43)+N(Y45)-N(Y47),"")) | Z49: =IF(OR(Z25=""),"",IFERROR(Z25+N(Z41)-N(Z43)+N(Z45)-N(Z47),"")) | AA49: =IF(OR(AA25=""),"",IFERROR(AA25+N(AA41)-N(AA43)+N(AA45)-N(AA47),"")) | AB49: =IF(OR(AB25=""),"",IFERROR(AB25+N(AB41)-N(AB43)+N(AB45)-N(AB47),"")) | AC49: =IF(OR(AC25=""),"",IFERROR(AC25+N(AC41)-N(AC43)+N(AC45)-N(AC47),""))
A50: 법인세비용(수익) | C50: -2.955 | D50: -6.702 | E50: 11.049 | F50: 2.46 | G50: 5.441 | H50: 2.487 | I50: 7.327 | J50: 15.714 | K50: 10.847 | L50: 18.318 | O50: -73.999 | P50: 8.608 | Q50: 42.068 | R50: 153.236 | S50: 19.111 | T50: 20.943 | U50: 9.534 | V50: 3.852 | W50: 30.969 | X50: 36.298 | Y50: =IF(OR(Y49="",Y51=""),"",IFERROR(MAX(Y49,0)*Y51,"")) | Z50: =IF(OR(Z49="",Z51=""),"",IFERROR(MAX(Z49,0)*Z51,"")) | AA50: =IF(OR(AA49="",AA51=""),"",IFERROR(MAX(AA49,0)*AA51,"")) | AB50: =IF(OR(AB49="",AB51=""),"",IFERROR(MAX(AB49,0)*AB51,"")) | AC50: =IF(OR(AC49="",AC51=""),"",IFERROR(MAX(AC49,0)*AC51,""))
A51: 법인세율 | B51: MW 기본 30% | C51: =IF(OR(C50="",C49=""),"",IFERROR(C50/C49,"")) | D51: =IF(OR(D50="",D49=""),"",IFERROR(D50/D49,"")) | E51: =IF(OR(E50="",E49=""),"",IFERROR(E50/E49,"")) | F51: =IF(OR(F50="",F49=""),"",IFERROR(F50/F49,"")) | G51: =IF(OR(G50="",G49=""),"",IFERROR(G50/G49,"")) | H51: =IF(OR(H50="",H49=""),"",IFERROR(H50/H49,"")) | I51: =IF(OR(I50="",I49=""),"",IFERROR(I50/I49,"")) | J51: =IF(OR(J50="",J49=""),"",IFERROR(J50/J49,"")) | ... X51: =IF(OR(X50="",X49=""),"",IFERROR(X50/X49,"")) | Y51: 0.3 | Z51: 0.3 | AA51: 0.3 | AB51: 0.3 | AC51: 0.3
A52: 당기순이익(손실) | C52: 6.824 | D52: -32.302 | E52: 20.893 | F52: -122.03 | G52: -21.483 | H52: -46.008 | I52: 35.164 | J52: -48.995 | K52: 3.111 | L52: 38.454 | O52: 60.07 | P52: 1.998 | Q52: 83.573 | R52: -213.961 | S52: -635.406 | T52: 237.403 | U52: 33.153 | V52: -126.615 | W52: -81.322 | X52: 132.827 | Y52: =IF(OR(Y49=""),"",IFERROR(Y49-Y50,"")) | Z52: =IF(OR(Z49=""),"",IFERROR(Z49-Z50,"")) | AA52: =IF(OR(AA49=""),"",IFERROR(AA49-AA50,"")) | AB52: =IF(OR(AB49=""),"",IFERROR(AB49-AB50,"")) | AC52: =IF(OR(AC49=""),"",IFERROR(AC49-AC50,""))
A53: 지배주주 순이익 | C53: 6.212 | D53: -32.363 | E53: 20.368 | F53: -120.753 | G53: -20.089 | H53: -45.145 | I53: 35.619 | J53: -50.165 | K53: 2.112 | L53: 37.012 | O53: 56.722 | P53: 5.366 | Q53: 69.341 | R53: -213.563 | S53: -630.016 | T53: 241.185 | U53: 39.764 | V53: -126.536 | W53: -79.78 | X53: 136.695 | Y53: =IF(OR(Y52="",Y54=""),"",IFERROR(Y52*Y54,"")) | Z53: =IF(OR(Z52="",Z54=""),"",IFERROR(Z52*Z54,"")) | AA53: =IF(OR(AA52="",AA54=""),"",IFERROR(AA52*AA54,"")) | AB53: =IF(OR(AB52="",AB54=""),"",IFERROR(AB52*AB54,"")) | AC53: =IF(OR(AC52="",AC54=""),"",IFERROR(AC52*AC54,""))
A54: 지배주주 순이익률 | B54: MW 기본 100% | C54: =IF(OR(C53="",C52=""),"",IFERROR(C53/C52,"")) | D54: =IF(OR(D53="",D52=""),"",IFERROR(D53/D52,"")) | E54: =IF(OR(E53="",E52=""),"",IFERROR(E53/E52,"")) | F54: =IF(OR(F53="",F52=""),"",IFERROR(F53/F52,"")) | G54: =IF(OR(G53="",G52=""),"",IFERROR(G53/G52,"")) | H54: =IF(OR(H53="",H52=""),"",IFERROR(H53/H52,"")) | I54: =IF(OR(I53="",I52=""),"",IFERROR(I53/I52,"")) | J54: =IF(OR(J53="",J52=""),"",IFERROR(J53/J52,"")) | ... X54: =IF(OR(X53="",X52=""),"",IFERROR(X53/X52,"")) | Y54: 1 | Z54: 1 | AA54: 1 | AB54: 1 | AC54: 1
A55: 목표주가 산출
A56: 현재 주가 ()
A57: 발행주식수 (보통주)
A58: 시가총액 (백만엔) | B58: =IF(OR(B56="",B57=""),"",B56*B57/1000000.0)
A59: OPM | O59: =IF(O26="","",O26) | P59: =IF(P26="","",P26) | Q59: =IF(Q26="","",Q26) | R59: =IF(R26="","",R26) | S59: =IF(S26="","",S26) | T59: =IF(T26="","",T26) | U59: =IF(U26="","",U26) | V59: =IF(V26="","",V26) | ... AC59: =IF(AC26="","",AC26)
A60: 지배주주 순이익 증가율 | P60: =IF(OR(P53="",O53=""),"",IFERROR(P53/O53-1,"")) | Q60: =IF(OR(Q53="",P53=""),"",IFERROR(Q53/P53-1,"")) | R60: =IF(OR(R53="",Q53=""),"",IFERROR(R53/Q53-1,"")) | S60: =IF(OR(S53="",R53=""),"",IFERROR(S53/R53-1,"")) | T60: =IF(OR(T53="",S53=""),"",IFERROR(T53/S53-1,"")) | U60: =IF(OR(U53="",T53=""),"",IFERROR(U53/T53-1,"")) | V60: =IF(OR(V53="",U53=""),"",IFERROR(V53/U53-1,"")) | W60: =IF(OR(W53="",V53=""),"",IFERROR(W53/V53-1,"")) | ... AC60: =IF(OR(AC53="",AB53=""),"",IFERROR(AC53/AB53-1,""))
A61: P/E (현재 주가) | B61: 시총 ÷ 지배순이익 | X61: =IF(OR($B$58="",X53=""),"",IFERROR($B$58/X53,"")) | Y61: =IF(OR($B$58="",Y53=""),"",IFERROR($B$58/Y53,"")) | Z61: =IF(OR($B$58="",Z53=""),"",IFERROR($B$58/Z53,"")) | AA61: =IF(OR($B$58="",AA53=""),"",IFERROR($B$58/AA53,"")) | AB61: =IF(OR($B$58="",AB53=""),"",IFERROR($B$58/AB53,"")) | AC61: =IF(OR($B$58="",AC53=""),"",IFERROR($B$58/AC53,""))
A62: Target P/E | B62: 직접 입력
A63: EPS | B63: 지배순이익 ÷ 주식수 | O63: =IF(OR(O53="",$B$57=""),"",IFERROR(O53*1000000.0/$B$57,"")) | P63: =IF(OR(P53="",$B$57=""),"",IFERROR(P53*1000000.0/$B$57,"")) | Q63: =IF(OR(Q53="",$B$57=""),"",IFERROR(Q53*1000000.0/$B$57,"")) | R63: =IF(OR(R53="",$B$57=""),"",IFERROR(R53*1000000.0/$B$57,"")) | S63: =IF(OR(S53="",$B$57=""),"",IFERROR(S53*1000000.0/$B$57,"")) | T63: =IF(OR(T53="",$B$57=""),"",IFERROR(T53*1000000.0/$B$57,"")) | U63: =IF(OR(U53="",$B$57=""),"",IFERROR(U53*1000000.0/$B$57,"")) | V63: =IF(OR(V53="",$B$57=""),"",IFERROR(V53*1000000.0/$B$57,"")) | ... AC63: =IF(OR(AC53="",$B$57=""),"",IFERROR(AC53*1000000.0/$B$57,""))
A64: 목표주가 | Y64: =IF(OR(Y63="",Y62=""),"",IFERROR(Y63*Y62,"")) | Z64: =IF(OR(Z63="",Z62=""),"",IFERROR(Z63*Z62,"")) | AA64: =IF(OR(AA63="",AA62=""),"",IFERROR(AA63*AA62,"")) | AB64: =IF(OR(AB63="",AB62=""),"",IFERROR(AB63*AB62,"")) | AC64: =IF(OR(AC63="",AC62=""),"",IFERROR(AC63*AC62,""))
A65: 상승여력 | Y65: =IF(OR(Y64="",$B$56=""),"",IFERROR(Y64/$B$56-1,"")) | Z65: =IF(OR(Z64="",$B$56=""),"",IFERROR(Z64/$B$56-1,"")) | AA65: =IF(OR(AA64="",$B$56=""),"",IFERROR(AA64/$B$56-1,"")) | AB65: =IF(OR(AB64="",$B$56=""),"",IFERROR(AB64/$B$56-1,"")) | AC65: =IF(OR(AC64="",$B$56=""),"",IFERROR(AC64/$B$56-1,""))
A66: 자산가치 산출 | B66: 최신 분기 BS
A67: 현금및현금성자산 | X67: ='재무상태표'!G6 | Y67: ='재무상태표'!G6 | Z67: ='재무상태표'!G6 | AA67: ='재무상태표'!G6 | AB67: ='재무상태표'!G6 | AC67: ='재무상태표'!G6
A68: 단기금융상품 | X68: ='재무상태표'!G7 | Y68: ='재무상태표'!G7 | Z68: ='재무상태표'!G7 | AA68: ='재무상태표'!G7 | AB68: ='재무상태표'!G7 | AC68: ='재무상태표'!G7
A69: 투자부동산 | X69: ='재무상태표'!G14 | Y69: ='재무상태표'!G14 | Z69: ='재무상태표'!G14 | AA69: ='재무상태표'!G14 | AB69: ='재무상태표'!G14 | AC69: ='재무상태표'!G14
A70: 지배자본 | X70: ='재무상태표'!G31 | Y70: ='재무상태표'!G31 | Z70: ='재무상태표'!G31 | AA70: ='재무상태표'!G31 | AB70: ='재무상태표'!G31 | AC70: ='재무상태표'!G31
A71: 부채 | X71: ='재무상태표'!G27 | Y71: ='재무상태표'!G27 | Z71: ='재무상태표'!G27 | AA71: ='재무상태표'!G27 | AB71: ='재무상태표'!G27 | AC71: ='재무상태표'!G27
A72: 부채비율 | X72: =IF(OR(X71="",X70=""),"",IFERROR(X71/X70,"")) | Y72: =IF(OR(Y71="",Y70=""),"",IFERROR(Y71/Y70,"")) | Z72: =IF(OR(Z71="",Z70=""),"",IFERROR(Z71/Z70,"")) | AA72: =IF(OR(AA71="",AA70=""),"",IFERROR(AA71/AA70,"")) | AB72: =IF(OR(AB71="",AB70=""),"",IFERROR(AB71/AB70,"")) | AC72: =IF(OR(AC71="",AC70=""),"",IFERROR(AC71/AC70,""))
A73: 자산가치 | B73: 현금+단기금융+투자부동산 | X73: =SUM(X67,X68,X69) | Y73: =SUM(Y67,Y68,Y69) | Z73: =SUM(Z67,Z68,Z69) | AA73: =SUM(AA67,AA68,AA69) | AB73: =SUM(AB67,AB68,AB69) | AC73: =SUM(AC67,AC68,AC69)
A74: 기업가치 산출
A75: 목표 시가총액 (P/E) | B75: 지배순이익 × Target P/E | Y75: =IF(OR(Y53="",Y62=""),"",IFERROR(Y53*Y62,"")) | Z75: =IF(OR(Z53="",Z62=""),"",IFERROR(Z53*Z62,"")) | AA75: =IF(OR(AA53="",AA62=""),"",IFERROR(AA53*AA62,"")) | AB75: =IF(OR(AB53="",AB62=""),"",IFERROR(AB53*AB62,"")) | AC75: =IF(OR(AC53="",AC62=""),"",IFERROR(AC53*AC62,""))
A76: 기업가치 | B76: 목표시총 + 자산가치 | Y76: =IF(OR(Y75=""),"",IFERROR(Y75+Y73,"")) | Z76: =IF(OR(Z75=""),"",IFERROR(Z75+Z73,"")) | AA76: =IF(OR(AA75=""),"",IFERROR(AA75+AA73,"")) | AB76: =IF(OR(AB75=""),"",IFERROR(AB75+AB73,"")) | AC76: =IF(OR(AC75=""),"",IFERROR(AC75+AC73,""))
A77: 현재 시가총액 | Y77: =$B$58 | Z77: =$B$58 | AA77: =$B$58 | AB77: =$B$58 | AC77: =$B$58
A78: 상승여력 | Y78: =IF(OR(Y76="",Y77=""),"",IFERROR(Y76/Y77-1,"")) | Z78: =IF(OR(Z76="",Z77=""),"",IFERROR(Z76/Z77-1,"")) | AA78: =IF(OR(AA76="",AA77=""),"",IFERROR(AA76/AA77-1,"")) | AB78: =IF(OR(AB76="",AB77=""),"",IFERROR(AB76/AB77-1,"")) | AC78: =IF(OR(AC76="",AC77=""),"",IFERROR(AC76/AC77-1,""))
A80: 출처
A81: 결산단신 XBRL(TDnet·JPX 보관소) — 쓴 문서는 '출처' 시트
A82: 분기 = 누계에서 앞 분기를 뺀 3개월 값
A83: 주가: 야후 파이낸스 일봉
A85: 손익계산서 · 전 항목 | B85: 분기 = 3개월 단독
A86: 항목 | B86: 참고 | C86: 2024.1Q | D86: 2024.2Q | E86: 2024.3Q | F86: 2024.4Q | G86: 2025.1Q | H86: 2025.2Q | I86: 2025.3Q | J86: 2025.4Q | K86: 2026.1Q | L86: 2026.2Q | M86: 2026.3Q | N86: 2026.4Q | O86: 2017 | P86: 2018 | Q86: 2019 | R86: 2020 | S86: 2021 | T86: 2022 | U86: 2023 | V86: 2024 | W86: 2025 | X86: 2026 | Y86: 2027(MW) | Z86: 2028(MW) | AA86: 2029(MW) | AB86: 2030(MW) | AC86: 2031(MW)
A87: 매출액 | C87: 865.849 | D87: 894.376 | E87: 997.932 | F87: 653.308 | G87: 783.899 | H87: 823.261 | I87: 1011.058 | J87: 901.082 | K87: 820.764 | L87: 961.948 | S87: 466.728 | T87: 1302.656 | U87: 1121.016 | V87: 653.308 | W87: 901.082
A88: 매출원가 | C88: 593.605 | D88: 670.452 | E88: 697.359 | F88: 505.74 | G88: 562.78 | H88: 583.814 | I88: 759.414 | J88: 603.213 | K88: 546.983 | L88: 652.153 | S88: 600.479 | T88: 850.837 | U88: 758.547 | V88: 505.74 | W88: 603.213
A89: 매출총이익 | C89: 272.244 | D89: 223.924 | E89: 300.572 | F89: 147.569 | G89: 221.119 | H89: 239.446 | I89: 251.645 | J89: 297.868 | K89: 273.78 | L89: 309.795 | S89: -133.752 | T89: 451.82 | U89: 362.469 | V89: 147.569 | W89: 297.868
A90: 판매비와 관리비 | C90: 270.476 | D90: 260.157 | E90: 269.416 | F90: 286.133 | G90: 280.648 | H90: 237.353 | I90: 227.358 | J90: 318.807 | K90: 249.62 | L90: 250.577 | S90: 274.263 | T90: 263.73 | U90: 251.488 | V90: 286.133 | W90: 318.807
A91: 영업이익(손실) | C91: 1.767 | D91: -36.232 | E91: 31.156 | F91: -138.564 | G91: -59.528 | H91: 2.093 | I91: 24.286 | J91: -20.939 | K91: 24.16 | L91: 59.218 | S91: -408.015 | T91: 188.088 | U91: 110.981 | V91: -138.564 | W91: -20.939
A92: 이자수익 | C92: 0.385 | D92: 0.36 | E92: 0.471 | F92: 0.344 | G92: 0.393 | H92: 0.27 | I92: 0.254 | J92: 0.664 | K92: 0.133 | L92: 0.429 | S92: 0.52 | T92: 0.366 | U92: 0.37 | V92: 0.344 | W92: 0.664
A93: 배당금수익 | E93: 3.145 | F93: 2.819 | I93: 7.541 | J93: 1.973 | S93: 0.486 | T93: 0.291 | U93: 4.986 | V93: 2.819 | W93: 1.973
A94: 외환차익 | G94: 0 | H94: 0 | K94: 1.754 | L94: 0.082 | S94: -6.06 | T94: -9.506 | U94: 11.658
A95: 보조금 수입 | C95: 2.515 | D95: 0 | E95: 0.508 | F95: 6.239 | G95: 1.475 | H95: 0 | K95: 0.9 | L95: 0.2 | S95: 9.893 | T95: 79.975 | U95: 32.162 | V95: 6.239
A96: 작업부산물 매각이익 | C96: 0.091 | D96: 0 | E96: 0 | F96: 22.596 | S96: 11.971 | T96: 1.512 | U96: -1.237 | V96: 22.596
A97: 기타 | C97: 2.344 | D97: 1.787 | E97: 6.146 | F97: -0.605 | G97: 1.759 | H97: 2.541 | I97: 3.835 | J97: 1.362 | K97: 0.774 | L97: 1.034 | S97: 5.786 | T97: 3.105 | U97: 0.701 | V97: -0.605 | W97: 1.362
A98: 영업외수익 합계 | C98: 5.244 | D98: 2.85 | E98: 7.246 | F98: 34.618 | G98: 3.628 | H98: 2.836 | I98: 10.154 | J98: 7.777 | K98: 3.561 | L98: 1.799 | S98: 22.596 | T98: 75.743 | U98: 48.641 | V98: 34.618 | W98: 7.777
A99: 이자비용 | C99: 2.412 | D99: 2.863 | E99: 2.891 | F99: 1.429 | G99: 3.184 | H99: 3.655 | I99: 3.385 | J99: 0.647 | K99: 3.385 | L99: 3.941 | S99: 2.004 | T99: 2.667 | U99: 2.327 | V99: 1.429 | W99: 0.647
A100: Loss On Transfer Of Receivables NOE | C100: 0.654 | D100: 1.356 | E100: 0.744 | F100: 0.841 | G100: 0.732 | H100: 1.108 | I100: 0.697 | J100: 0.997 | K100: 1.402 | L100: 0.124 | S100: 0.827 | T100: 0.61 | U100: 1.009 | V100: 0.841 | W100: 0.997
A101: Amortization Of Restricted Stock Compensation NOE | S101: -1.504 | T101: 1.504
A102: 외환차손 | C102: 0 | D102: 1.349 | E102: 2.522 | F102: -3.871 | J102: 0.358 | T102: 0 | V102: -3.871 | W102: 0.358
...

Sheet 재무상태표
A1: 6663 재무상태표
A2: 재무비율은 기말 잔액 기준 · 분기 손익은 최근 4분기 합산(TTM) | B2: (단위: 백만엔)
A3: 항목 | B3: 참고 | C3: 2025.3Q | D3: 2025.4Q | E3: 2026.1Q | F3: 2026.2Q | G3: 2026.3Q | H3: 2022 | I3: 2023 | J3: 2024 | K3: 2025
A4: 자산
A5: 유동자산 | C5: 2911.257 | D5: 2777.075 | E5: 2604.667 | F5: 2811.898 | G5: 2941.501 | H5: 3039.748 | I5: 2767.155 | J5: 2916.735 | K5: 2777.075
A6: 현금및현금성자산 | C6: 1872.416 | D6: 1650.048 | E6: 1257.565 | F6: 1707.71 | G6: 1942.751 | H6: 1758.992 | I6: 1665.094 | J6: 1769.981 | K6: 1650.048
A7: 단기금융상품 | C7: 0 | D7: 0 | E7: 0 | H7: 10 | I7: 0 | J7: 150 | K7: 0
A8: 매출채권 | C8: 584.847 | D8: 721.239 | E8: 1001.287 | F8: 701.593 | G8: 583.368 | H8: 686.654 | I8: 519.277 | J8: 580.887 | K8: 721.239
A9: 재고자산 | C9: 383.998 | D9: 376.169 | E9: 325.345 | F9: 389.142 | G9: 380.619 | H9: 532.542 | I9: 549.685 | J9: 379.4 | K9: 376.169
A10: 기타유동자산 | B10: 총계 − 위 항목 | C10: =IF(OR(C5=""),"",IFERROR(C5-SUM(C6,C7,C8,C9),"")) | D10: =IF(OR(D5=""),"",IFERROR(D5-SUM(D6,D7,D8,D9),"")) | E10: =IF(OR(E5=""),"",IFERROR(E5-SUM(E6,E7,E8,E9),"")) | F10: =IF(OR(F5=""),"",IFERROR(F5-SUM(F6,F7,F8,F9),"")) | G10: =IF(OR(G5=""),"",IFERROR(G5-SUM(G6,G7,G8,G9),"")) | H10: =IF(OR(H5=""),"",IFERROR(H5-SUM(H6,H7,H8,H9),"")) | I10: =IF(OR(I5=""),"",IFERROR(I5-SUM(I6,I7,I8,I9),"")) | J10: =IF(OR(J5=""),"",IFERROR(J5-SUM(J6,J7,J8,J9),"")) | K10: =IF(OR(K5=""),"",IFERROR(K5-SUM(K6,K7,K8,K9),""))
A11: 비유동자산 | C11: 1929.037 | D11: 1971.903 | E11: 1966.304 | F11: 2013.61 | G11: 2075.974 | H11: 2050.489 | I11: 2059.079 | J11: 2023.229 | K11: 1971.903
A12: 유형자산 | C12: 1381.958 | D12: 1380.279 | E12: 1356.225 | F12: 1335.302 | G12: 1332.055 | H12: 1418.311 | I12: 1412.807 | J12: 1439.542 | K12: 1380.279
A13: 무형자산 | C13: 51.158 | D13: 46.476 | E13: 41.841 | F13: 37.556 | G13: 33.567 | H13: 28.124 | I13: 63.814 | J13: 60.9 | K13: 46.476
A14: 투자부동산
A15: 기타비유동자산 | B15: 총계 − 위 항목 | C15: =IF(OR(C11=""),"",IFERROR(C11-SUM(C12,C13,C14),"")) | D15: =IF(OR(D11=""),"",IFERROR(D11-SUM(D12,D13,D14),"")) | E15: =IF(OR(E11=""),"",IFERROR(E11-SUM(E12,E13,E14),"")) | F15: =IF(OR(F11=""),"",IFERROR(F11-SUM(F12,F13,F14),"")) | G15: =IF(OR(G11=""),"",IFERROR(G11-SUM(G12,G13,G14),"")) | H15: =IF(OR(H11=""),"",IFERROR(H11-SUM(H12,H13,H14),"")) | I15: =IF(OR(I11=""),"",IFERROR(I11-SUM(I12,I13,I14),"")) | J15: =IF(OR(J11=""),"",IFERROR(J11-SUM(J12,J13,J14),"")) | K15: =IF(OR(K11=""),"",IFERROR(K11-SUM(K12,K13,K14),""))
A16: 자산총계 | C16: 4840.294 | D16: 4748.978 | E16: 4570.972 | F16: 4825.509 | G16: 5017.476 | H16: 5090.238 | I16: 4826.234 | J16: 4939.964 | K16: 4748.978
A17: 부채
A18: 유동부채 | C18: 1215.539 | D18: 1107.225 | E18: 784.061 | F18: 1021.765 | G18: 1024.752 | H18: 1157.769 | I18: 1051.918 | J18: 1144.982 | K18: 1107.225
A19: 매입채무 | C19: 100.747 | D19: 183.237 | E19: 135.614 | F19: 124.486 | G19: 127.169 | H19: 167.151 | I19: 97.028 | J19: 143.291 | K19: 183.237
A20: 단기차입금 | C20: 574.192 | D20: 562.165 | E20: 290.668 | F20: 510.689 | G20: 510.959 | H20: 599.197 | I20: 571.416 | J20: 598.676 | K20: 562.165
A21: 유동성장기부채
A22: 기타유동부채 | B22: 총계 − 위 항목 | C22: =IF(OR(C18=""),"",IFERROR(C18-SUM(C19,C20,C21),"")) | D22: =IF(OR(D18=""),"",IFERROR(D18-SUM(D19,D20,D21),"")) | E22: =IF(OR(E18=""),"",IFERROR(E18-SUM(E19,E20,E21),"")) | F22: =IF(OR(F18=""),"",IFERROR(F18-SUM(F19,F20,F21),"")) | G22: =IF(OR(G18=""),"",IFERROR(G18-SUM(G19,G20,G21),"")) | H22: =IF(OR(H18=""),"",IFERROR(H18-SUM(H19,H20,H21),"")) | I22: =IF(OR(I18=""),"",IFERROR(I18-SUM(I19,I20,I21),"")) | J22: =IF(OR(J18=""),"",IFERROR(J18-SUM(J19,J20,J21),"")) | K22: =IF(OR(K18=""),"",IFERROR(K18-SUM(K19,K20,K21),""))
A23: 비유동부채 | C23: 1180.433 | D23: 1137.966 | E23: 1088.5 | F23: 1088.554 | G23: 1173.526 | H23: 1302.884 | I23: 1234.38 | J23: 1225.434 | K23: 1137.966
A24: 장기차입금 | C24: 384.038 | D24: 331.575 | E24: 280.582 | F24: 268.76 | G24: 321.414 | H24: 517.808 | I24: 479.739 | J24: 394.737 | K24: 331.575
A25: 사채
A26: 기타비유동부채 | B26: 총계 − 위 항목 | C26: =IF(OR(C23=""),"",IFERROR(C23-SUM(C24,C25),"")) | D26: =IF(OR(D23=""),"",IFERROR(D23-SUM(D24,D25),"")) | E26: =IF(OR(E23=""),"",IFERROR(E23-SUM(E24,E25),"")) | F26: =IF(OR(F23=""),"",IFERROR(F23-SUM(F24,F25),"")) | G26: =IF(OR(G23=""),"",IFERROR(G23-SUM(G24,G25),"")) | H26: =IF(OR(H23=""),"",IFERROR(H23-SUM(H24,H25),"")) | I26: =IF(OR(I23=""),"",IFERROR(I23-SUM(I24,I25),"")) | J26: =IF(OR(J23=""),"",IFERROR(J23-SUM(J24,J25),"")) | K26: =IF(OR(K23=""),"",IFERROR(K23-SUM(K24,K25),""))
A27: 부채총계 | C27: 2395.973 | D27: 2245.191 | E27: 1872.562 | F27: 2110.319 | G27: 2198.279 | H27: 2460.654 | I27: 2286.298 | J27: 2370.417 | K27: 2245.191
A28: 총차입금 | B28: 단기+유동성장기+장기+사채 | C28: =SUM(C20,C21,C24,C25) | D28: =SUM(D20,D21,D24,D25) | E28: =SUM(E20,E21,E24,E25) | F28: =SUM(F20,F21,F24,F25) | G28: =SUM(G20,G21,G24,G25) | H28: =SUM(H20,H21,H24,H25) | I28: =SUM(I20,I21,I24,I25) | J28: =SUM(J20,J21,J24,J25) | K28: =SUM(K20,K21,K24,K25)
A29: 순차입금 | B29: 음수 = 순현금 | C29: =C28-C6-N(C7) | D29: =D28-D6-N(D7) | E29: =E28-E6-N(E7) | F29: =F28-F6-N(F7) | G29: =G28-G6-N(G7) | H29: =H28-H6-N(H7) | I29: =I28-I6-N(I7) | J29: =J28-J6-N(J7) | K29: =K28-K6-N(K7)
A30: 자본
A31: 지배주주지분 | C31: 2416.627 | D31: 2474.671 | E31: 2669.024 | F31: 2684.008 | G31: 2786.58 | H31: 2597.579 | I31: 2509.989 | J31: 2536.942 | K31: 2474.671
A32: 자본금 | C32: 822.195 | D32: 822.195 | E32: 822.195 | F32: 822.195 | G32: 833.535 | H32: 815.198 | I32: 815.198 | J32: 822.195 | K32: 822.195
A33: 이익잉여금 | C33: 476.169 | D33: 511.788 | E33: 678.098 | F33: 644.294 | G33: 681.306 | H33: 757.509 | I33: 648.872 | J33: 633.359 | K33: 511.788
A34: 비지배지분 | C34: 27.694 | D34: 29.115 | E34: 29.386 | F34: 31.181 | G34: 32.616 | H34: 32.005 | I34: 29.947 | J34: 32.605 | K34: 29.115
A35: 자본총계 | C35: 2444.321 | D35: 2503.786 | E35: 2698.41 | F35: 2715.189 | G35: 2819.196 | H35: 2629.584 | I35: 2539.936 | J35: 2569.547 | K35: 2503.786
A36: 현금흐름 요약 | B36: 분기 = TTM (있을 때만)
A37: 영업활동현금흐름 | D37: 248.699 | F37: 616.404 | H37: 165.18 | I37: 233.127 | J37: -27.472 | K37: 248.699
A38: CAPEX (유·무형 취득) | B38: 양수로 입력 | D38: 36.467 | F38: 24.074 | H38: 18.797 | I38: 87.276 | J38: 175.808 | K38: 36.467
A39: FCF | C39: =IF(OR(C37="",C38=""),"",IFERROR(C37-C38,"")) | D39: =IF(OR(D37="",D38=""),"",IFERROR(D37-D38,"")) | E39: =IF(OR(E37="",E38=""),"",IFERROR(E37-E38,"")) | F39: =IF(OR(F37="",F38=""),"",IFERROR(F37-F38,"")) | G39: =IF(OR(G37="",G38=""),"",IFERROR(G37-G38,"")) | H39: =IF(OR(H37="",H38=""),"",IFERROR(H37-H38,"")) | I39: =IF(OR(I37="",I38=""),"",IFERROR(I37-I38,"")) | J39: =IF(OR(J37="",J38=""),"",IFERROR(J37-J38,"")) | K39: =IF(OR(K37="",K38=""),"",IFERROR(K37-K38,""))
A40: 배당금 지급 | B40: 양수로 입력 | D40: 17.836 | F40: 35.795 | H40: 17.724 | I40: 29.519 | J40: 17.836 | K40: 17.836
A41: 주요 재무 비율 | B41: 기준 (빨간 글씨 = 미달)
A42: 안정성
A43: 부채비율 | B43: 100%↓ | C43: =IF(OR(C27="",C35=""),"",IFERROR(C27/C35,"")) | D43: =IF(OR(D27="",D35=""),"",IFERROR(D27/D35,"")) | E43: =IF(OR(E27="",E35=""),"",IFERROR(E27/E35,"")) | F43: =IF(OR(F27="",F35=""),"",IFERROR(F27/F35,"")) | G43: =IF(OR(G27="",G35=""),"",IFERROR(G27/G35,"")) | H43: =IF(OR(H27="",H35=""),"",IFERROR(H27/H35,"")) | I43: =IF(OR(I27="",I35=""),"",IFERROR(I27/I35,"")) | J43: =IF(OR(J27="",J35=""),"",IFERROR(J27/J35,"")) | K43: =IF(OR(K27="",K35=""),"",IFERROR(K27/K35,""))
A44: 순차입금비율 | B44: 0%↓ 순현금 | C44: =IF(OR(C29="",C35=""),"",IFERROR(C29/C35,"")) | D44: =IF(OR(D29="",D35=""),"",IFERROR(D29/D35,"")) | E44: =IF(OR(E29="",E35=""),"",IFERROR(E29/E35,"")) | F44: =IF(OR(F29="",F35=""),"",IFERROR(F29/F35,"")) | G44: =IF(OR(G29="",G35=""),"",IFERROR(G29/G35,"")) | H44: =IF(OR(H29="",H35=""),"",IFERROR(H29/H35,"")) | I44: =IF(OR(I29="",I35=""),"",IFERROR(I29/I35,"")) | J44: =IF(OR(J29="",J35=""),"",IFERROR(J29/J35,"")) | K44: =IF(OR(K29="",K35=""),"",IFERROR(K29/K35,""))
A45: 자기자본비율 | B45: 50%↑ | C45: =IF(OR(C35="",C16=""),"",IFERROR(C35/C16,"")) | D45: =IF(OR(D35="",D16=""),"",IFERROR(D35/D16,"")) | E45: =IF(OR(E35="",E16=""),"",IFERROR(E35/E16,"")) | F45: =IF(OR(F35="",F16=""),"",IFERROR(F35/F16,"")) | G45: =IF(OR(G35="",G16=""),"",IFERROR(G35/G16,"")) | H45: =IF(OR(H35="",H16=""),"",IFERROR(H35/H16,"")) | I45: =IF(OR(I35="",I16=""),"",IFERROR(I35/I16,"")) | J45: =IF(OR(J35="",J16=""),"",IFERROR(J35/J16,"")) | K45: =IF(OR(K35="",K16=""),"",IFERROR(K35/K16,""))
A46: 유동비율 | B46: 150%↑ | C46: =IF(OR(C5="",C18=""),"",IFERROR(C5/C18,"")) | D46: =IF(OR(D5="",D18=""),"",IFERROR(D5/D18,"")) | E46: =IF(OR(E5="",E18=""),"",IFERROR(E5/E18,"")) | F46: =IF(OR(F5="",F18=""),"",IFERROR(F5/F18,"")) | G46: =IF(OR(G5="",G18=""),"",IFERROR(G5/G18,"")) | H46: =IF(OR(H5="",H18=""),"",IFERROR(H5/H18,"")) | I46: =IF(OR(I5="",I18=""),"",IFERROR(I5/I18,"")) | J46: =IF(OR(J5="",J18=""),"",IFERROR(J5/J18,"")) | K46: =IF(OR(K5="",K18=""),"",IFERROR(K5/K18,""))
A47: 당좌비율 | B47: 100%↑ | C47: =IF(OR(C5="",C18=""),"",IFERROR((C5-N(C9))/C18,"")) | D47: =IF(OR(D5="",D18=""),"",IFERROR((D5-N(D9))/D18,"")) | E47: =IF(OR(E5="",E18=""),"",IFERROR((E5-N(E9))/E18,"")) | F47: =IF(OR(F5="",F18=""),"",IFERROR((F5-N(F9))/F18,"")) | G47: =IF(OR(G5="",G18=""),"",IFERROR((G5-N(G9))/G18,"")) | H47: =IF(OR(H5="",H18=""),"",IFERROR((H5-N(H9))/H18,"")) | I47: =IF(OR(I5="",I18=""),"",IFERROR((I5-N(I9))/I18,"")) | J47: =IF(OR(J5="",J18=""),"",IFERROR((J5-N(J9))/J18,"")) | K47: =IF(OR(K5="",K18=""),"",IFERROR((K5-N(K9))/K18,""))
A48: 이자보상배율 | B48: 5x↑ (금융원가 기준) | C48: =IFERROR((IF(COUNT('연간'!F25:I25)<4,"",SUM('연간'!F25:I25)))/(IF(COUNT('연간'!F47:I47)<4,"",SUM('연간'!F47:I47))),"") | D48: =IFERROR((IF(COUNT('연간'!G25:J25)<4,"",SUM('연간'!G25:J25)))/(IF(COUNT('연간'!G47:J47)<4,"",SUM('연간'!G47:J47))),"") | E48: =IFERROR((IF(COUNT('연간'!H25:K25)<4,"",SUM('연간'!H25:K25)))/(IF(COUNT('연간'!H47:K47)<4,"",SUM('연간'!H47:K47))),"") | F48: =IFERROR((IF(COUNT('연간'!I25:L25)<4,"",SUM('연간'!I25:L25)))/(IF(COUNT('연간'!I47:L47)<4,"",SUM('연간'!I47:L47))),"") | G48: =IFERROR((IF(COUNT('연간'!J25:M25)<4,"",SUM('연간'!J25:M25)))/(IF(COUNT('연간'!J47:M47)<4,"",SUM('연간'!J47:M47))),"") | H48: =IFERROR(('연간'!T25)/('연간'!T47),"") | I48: =IFERROR(('연간'!U25)/('연간'!U47),"") | J48: =IFERROR(('연간'!V25)/('연간'!V47),"") | K48: =IFERROR(('연간'!W25)/('연간'!W47),"")
A49: 차입금 상환연수 | B49: 4년↓ (버핏) | C49: =IFERROR(IF((IF(COUNT('연간'!F53:I53)<4,"",SUM('연간'!F53:I53)))<=0,"적자",C28/(IF(COUNT('연간'!F53:I53)<4,"",SUM('연간'!F53:I53)))),"") | D49: =IFERROR(IF((IF(COUNT('연간'!G53:J53)<4,"",SUM('연간'!G53:J53)))<=0,"적자",D28/(IF(COUNT('연간'!G53:J53)<4,"",SUM('연간'!G53:J53)))),"") | E49: =IFERROR(IF((IF(COUNT('연간'!H53:K53)<4,"",SUM('연간'!H53:K53)))<=0,"적자",E28/(IF(COUNT('연간'!H53:K53)<4,"",SUM('연간'!H53:K53)))),"") | F49: =IFERROR(IF((IF(COUNT('연간'!I53:L53)<4,"",SUM('연간'!I53:L53)))<=0,"적자",F28/(IF(COUNT('연간'!I53:L53)<4,"",SUM('연간'!I53:L53)))),"") | G49: =IFERROR(IF((IF(COUNT('연간'!J53:M53)<4,"",SUM('연간'!J53:M53)))<=0,"적자",G28/(IF(COUNT('연간'!J53:M53)<4,"",SUM('연간'!J53:M53)))),"") | H49: =IFERROR(IF(('연간'!T53)<=0,"적자",H28/('연간'!T53)),"") | I49: =IFERROR(IF(('연간'!U53)<=0,"적자",I28/('연간'!U53)),"") | J49: =IFERROR(IF(('연간'!V53)<=0,"적자",J28/('연간'!V53)),"") | K49: =IFERROR(IF(('연간'!W53)<=0,"적자",K28/('연간'!W53)),"")
A50: 수익성
A51: ROE | B51: 15%↑ (버핏) | C51: =IFERROR((IF(COUNT('연간'!F53:I53)<4,"",SUM('연간'!F53:I53)))/C31,"") | D51: =IFERROR((IF(COUNT('연간'!G53:J53)<4,"",SUM('연간'!G53:J53)))/D31,"") | E51: =IFERROR((IF(COUNT('연간'!H53:K53)<4,"",SUM('연간'!H53:K53)))/E31,"") | F51: =IFERROR((IF(COUNT('연간'!I53:L53)<4,"",SUM('연간'!I53:L53)))/F31,"") | G51: =IFERROR((IF(COUNT('연간'!J53:M53)<4,"",SUM('연간'!J53:M53)))/G31,"") | H51: =IFERROR(('연간'!T53)/H31,"") | I51: =IFERROR(('연간'!U53)/I31,"") | J51: =IFERROR(('연간'!V53)/J31,"") | K51: =IFERROR(('연간'!W53)/K31,"")
A52: ROA | B52: 5%↑ | C52: =IFERROR((IF(COUNT('연간'!F52:I52)<4,"",SUM('연간'!F52:I52)))/C16,"") | D52: =IFERROR((IF(COUNT('연간'!G52:J52)<4,"",SUM('연간'!G52:J52)))/D16,"") | E52: =IFERROR((IF(COUNT('연간'!H52:K52)<4,"",SUM('연간'!H52:K52)))/E16,"") | F52: =IFERROR((IF(COUNT('연간'!I52:L52)<4,"",SUM('연간'!I52:L52)))/F16,"") | G52: =IFERROR((IF(COUNT('연간'!J52:M52)<4,"",SUM('연간'!J52:M52)))/G16,"") | H52: =IFERROR(('연간'!T52)/H16,"") | I52: =IFERROR(('연간'!U52)/I16,"") | J52: =IFERROR(('연간'!V52)/J16,"") | K52: =IFERROR(('연간'!W52)/K16,"")
A53: ROIC | B53: 10%↑ (세후영업이익 기준) | C53: =IFERROR((IF(COUNT('연간'!F25:I25)<4,"",SUM('연간'!F25:I25)))*(1-0.3)/(C35+C29),"") | D53: =IFERROR((IF(COUNT('연간'!G25:J25)<4,"",SUM('연간'!G25:J25)))*(1-0.3)/(D35+D29),"") | E53: =IFERROR((IF(COUNT('연간'!H25:K25)<4,"",SUM('연간'!H25:K25)))*(1-0.3)/(E35+E29),"") | F53: =IFERROR((IF(COUNT('연간'!I25:L25)<4,"",SUM('연간'!I25:L25)))*(1-0.3)/(F35+F29),"") | G53: =IFERROR((IF(COUNT('연간'!J25:M25)<4,"",SUM('연간'!J25:M25)))*(1-0.3)/(G35+G29),"") | H53: =IFERROR(('연간'!T25)*(1-0.3)/(H35+H29),"") | I53: =IFERROR(('연간'!U25)*(1-0.3)/(I35+I29),"") | J53: =IFERROR(('연간'!V25)*(1-0.3)/(J35+J29),"") | K53: =IFERROR(('연간'!W25)*(1-0.3)/(K35+K29),"")
A54: 매출총이익률 (GPM) | B54: 40%↑ (해자 신호) | C54: =IFERROR((IF(COUNT('연간'!F21:I21)<4,"",SUM('연간'!F21:I21)))/(IF(COUNT('연간'!F4:I4)<4,"",SUM('연간'!F4:I4))),"") | D54: =IFERROR((IF(COUNT('연간'!G21:J21)<4,"",SUM('연간'!G21:J21)))/(IF(COUNT('연간'!G4:J4)<4,"",SUM('연간'!G4:J4))),"") | E54: =IFERROR((IF(COUNT('연간'!H21:K21)<4,"",SUM('연간'!H21:K21)))/(IF(COUNT('연간'!H4:K4)<4,"",SUM('연간'!H4:K4))),"") | F54: =IFERROR((IF(COUNT('연간'!I21:L21)<4,"",SUM('연간'!I21:L21)))/(IF(COUNT('연간'!I4:L4)<4,"",SUM('연간'!I4:L4))),"") | G54: =IFERROR((IF(COUNT('연간'!J21:M21)<4,"",SUM('연간'!J21:M21)))/(IF(COUNT('연간'!J4:M4)<4,"",SUM('연간'!J4:M4))),"") | H54: =IFERROR(('연간'!T21)/('연간'!T4),"") | I54: =IFERROR(('연간'!U21)/('연간'!U4),"") | J54: =IFERROR(('연간'!V21)/('연간'!V4),"") | K54: =IFERROR(('연간'!W21)/('연간'!W4),"")
A55: 영업이익률 (OPM) | B55: 15%↑ | C55: =IFERROR((IF(COUNT('연간'!F25:I25)<4,"",SUM('연간'!F25:I25)))/(IF(COUNT('연간'!F4:I4)<4,"",SUM('연간'!F4:I4))),"") | D55: =IFERROR((IF(COUNT('연간'!G25:J25)<4,"",SUM('연간'!G25:J25)))/(IF(COUNT('연간'!G4:J4)<4,"",SUM('연간'!G4:J4))),"") | E55: =IFERROR((IF(COUNT('연간'!H25:K25)<4,"",SUM('연간'!H25:K25)))/(IF(COUNT('연간'!H4:K4)<4,"",SUM('연간'!H4:K4))),"") | F55: =IFERROR((IF(COUNT('연간'!I25:L25)<4,"",SUM('연간'!I25:L25)))/(IF(COUNT('연간'!I4:L4)<4,"",SUM('연간'!I4:L4))),"") | G55: =IFERROR((IF(COUNT('연간'!J25:M25)<4,"",SUM('연간'!J25:M25)))/(IF(COUNT('연간'!J4:M4)<4,"",SUM('연간'!J4:M4))),"") | H55: =IFERROR(('연간'!T25)/('연간'!T4),"") | I55: =IFERROR(('연간'!U25)/('연간'!U4),"") | J55: =IFERROR(('연간'!V25)/('연간'!V4),"") | K55: =IFERROR(('연간'!W25)/('연간'!W4),"")
A56: 순이익률 | B56: 10%↑ | C56: =IFERROR((IF(COUNT('연간'!F52:I52)<4,"",SUM('연간'!F52:I52)))/(IF(COUNT('연간'!F4:I4)<4,"",SUM('연간'!F4:I4))),"") | D56: =IFERROR((IF(COUNT('연간'!G52:J52)<4,"",SUM('연간'!G52:J52)))/(IF(COUNT('연간'!G4:J4)<4,"",SUM('연간'!G4:J4))),"") | E56: =IFERROR((IF(COUNT('연간'!H52:K52)<4,"",SUM('연간'!H52:K52)))/(IF(COUNT('연간'!H4:K4)<4,"",SUM('연간'!H4:K4))),"") | F56: =IFERROR((IF(COUNT('연간'!I52:L52)<4,"",SUM('연간'!I52:L52)))/(IF(COUNT('연간'!I4:L4)<4,"",SUM('연간'!I4:L4))),"") | G56: =IFERROR((IF(COUNT('연간'!J52:M52)<4,"",SUM('연간'!J52:M52)))/(IF(COUNT('연간'!J4:M4)<4,"",SUM('연간'!J4:M4))),"") | H56: =IFERROR(('연간'!T52)/('연간'!T4),"") | I56: =IFERROR(('연간'!U52)/('연간'!U4),"") | J56: =IFERROR(('연간'!V52)/('연간'!V4),"") | K56: =IFERROR(('연간'!W52)/('연간'!W4),"")
A57: 효율성 (회전율)
A58: 총자산회전율 | B58: 높을수록↑ | C58: =IFERROR((IF(COUNT('연간'!F4:I4)<4,"",SUM('연간'!F4:I4)))/C16,"") | D58: =IFERROR((IF(COUNT('연간'!G4:J4)<4,"",SUM('연간'!G4:J4)))/D16,"") | E58: =IFERROR((IF(COUNT('연간'!H4:K4)<4,"",SUM('연간'!H4:K4)))/E16,"") | F58: =IFERROR((IF(COUNT('연간'!I4:L4)<4,"",SUM('연간'!I4:L4)))/F16,"") | G58: =IFERROR((IF(COUNT('연간'!J4:M4)<4,"",SUM('연간'!J4:M4)))/G16,"") | H58: =IFERROR(('연간'!T4)/H16,"") | I58: =IFERROR(('연간'!U4)/I16,"") | J58: =IFERROR(('연간'!V4)/J16,"") | K58: =IFERROR(('연간'!W4)/K16,"")
A59: 매출채권회전일수 | B59: 짧을수록↑ | C59: =IFERROR(C8/(IF(COUNT('연간'!F4:I4)<4,"",SUM('연간'!F4:I4)))*365,"") | D59: =IFERROR(D8/(IF(COUNT('연간'!G4:J4)<4,"",SUM('연간'!G4:J4)))*365,"") | E59: =IFERROR(E8/(IF(COUNT('연간'!H4:K4)<4,"",SUM('연간'!H4:K4)))*365,"") | F59: =IFERROR(F8/(IF(COUNT('연간'!I4:L4)<4,"",SUM('연간'!I4:L4)))*365,"") | G59: =IFERROR(G8/(IF(COUNT('연간'!J4:M4)<4,"",SUM('연간'!J4:M4)))*365,"") | H59: =IFERROR(H8/('연간'!T4)*365,"") | I59: =IFERROR(I8/('연간'!U4)*365,"") | J59: =IFERROR(J8/('연간'!V4)*365,"") | K59: =IFERROR(K8/('연간'!W4)*365,"")
A60: 재고자산회전일수 | B60: 짧을수록↑ | C60: =IFERROR(C9/(IF(COUNT('연간'!F20:I20)<4,"",SUM('연간'!F20:I20)))*365,"") | D60: =IFERROR(D9/(IF(COUNT('연간'!G20:J20)<4,"",SUM('연간'!G20:J20)))*365,"") | E60: =IFERROR(E9/(IF(COUNT('연간'!H20:K20)<4,"",SUM('연간'!H20:K20)))*365,"") | F60: =IFERROR(F9/(IF(COUNT('연간'!I20:L20)<4,"",SUM('연간'!I20:L20)))*365,"") | G60: =IFERROR(G9/(IF(COUNT('연간'!J20:M20)<4,"",SUM('연간'!J20:M20)))*365,"") | H60: =IFERROR(H9/('연간'!T20)*365,"") | I60: =IFERROR(I9/('연간'!U20)*365,"") | J60: =IFERROR(J9/('연간'!V20)*365,"") | K60: =IFERROR(K9/('연간'!W20)*365,"")
A61: 매입채무회전일수 | B61: 길수록 유리 | C61: =IFERROR(C19/(IF(COUNT('연간'!F20:I20)<4,"",SUM('연간'!F20:I20)))*365,"") | D61: =IFERROR(D19/(IF(COUNT('연간'!G20:J20)<4,"",SUM('연간'!G20:J20)))*365,"") | E61: =IFERROR(E19/(IF(COUNT('연간'!H20:K20)<4,"",SUM('연간'!H20:K20)))*365,"") | F61: =IFERROR(F19/(IF(COUNT('연간'!I20:L20)<4,"",SUM('연간'!I20:L20)))*365,"") | G61: =IFERROR(G19/(IF(COUNT('연간'!J20:M20)<4,"",SUM('연간'!J20:M20)))*365,"") | H61: =IFERROR(H19/('연간'!T20)*365,"") | I61: =IFERROR(I19/('연간'!U20)*365,"") | J61: =IFERROR(J19/('연간'!V20)*365,"") | K61: =IFERROR(K19/('연간'!W20)*365,"")
A62: 현금전환주기 (CCC) | B62: 짧을수록↑ | C62: =IF(OR(C59="",C60="",C61=""),"",IFERROR(C59+C60-C61,"")) | D62: =IF(OR(D59="",D60="",D61=""),"",IFERROR(D59+D60-D61,"")) | E62: =IF(OR(E59="",E60="",E61=""),"",IFERROR(E59+E60-E61,"")) | F62: =IF(OR(F59="",F60="",F61=""),"",IFERROR(F59+F60-F61,"")) | G62: =IF(OR(G59="",G60="",G61=""),"",IFERROR(G59+G60-G61,"")) | H62: =IF(OR(H59="",H60="",H61=""),"",IFERROR(H59+H60-H61,"")) | I62: =IF(OR(I59="",I60="",I61=""),"",IFERROR(I59+I60-I61,"")) | J62: =IF(OR(J59="",J60="",J61=""),"",IFERROR(J59+J60-J61,"")) | K62: =IF(OR(K59="",K60="",K61=""),"",IFERROR(K59+K60-K61,""))
A63: 현금흐름
A64: 영업현금흐름 / 순이익 | B64: 1x↑ (이익의 질) | C64: =IF(C37="","",IFERROR(C37/(IF(COUNT('연간'!F52:I52)<4,"",SUM('연간'!F52:I52))),"")) | D64: =IF(D37="","",IFERROR(D37/(IF(COUNT('연간'!G52:J52)<4,"",SUM('연간'!G52:J52))),"")) | E64: =IF(E37="","",IFERROR(E37/(IF(COUNT('연간'!H52:K52)<4,"",SUM('연간'!H52:K52))),"")) | F64: =IF(F37="","",IFERROR(F37/(IF(COUNT('연간'!I52:L52)<4,"",SUM('연간'!I52:L52))),"")) | G64: =IF(G37="","",IFERROR(G37/(IF(COUNT('연간'!J52:M52)<4,"",SUM('연간'!J52:M52))),"")) | H64: =IF(H37="","",IFERROR(H37/('연간'!T52),"")) | I64: =IF(I37="","",IFERROR(I37/('연간'!U52),"")) | J64: =IF(J37="","",IFERROR(J37/('연간'!V52),"")) | K64: =IF(K37="","",IFERROR(K37/('연간'!W52),""))
A65: FCF 마진 | B65: 5%↑ | C65: =IF(C39="","",IFERROR(C39/(IF(COUNT('연간'!F4:I4)<4,"",SUM('연간'!F4:I4))),"")) | D65: =IF(D39="","",IFERROR(D39/(IF(COUNT('연간'!G4:J4)<4,"",SUM('연간'!G4:J4))),"")) | E65: =IF(E39="","",IFERROR(E39/(IF(COUNT('연간'!H4:K4)<4,"",SUM('연간'!H4:K4))),"")) | F65: =IF(F39="","",IFERROR(F39/(IF(COUNT('연간'!I4:L4)<4,"",SUM('연간'!I4:L4))),"")) | G65: =IF(G39="","",IFERROR(G39/(IF(COUNT('연간'!J4:M4)<4,"",SUM('연간'!J4:M4))),"")) | H65: =IF(H39="","",IFERROR(H39/('연간'!T4),"")) | I65: =IF(I39="","",IFERROR(I39/('연간'!U4),"")) | J65: =IF(J39="","",IFERROR(J39/('연간'!V4),"")) | K65: =IF(K39="","",IFERROR(K39/('연간'!W4),""))
A66: CAPEX / 매출 | B66: 낮을수록↑ (자본 가벼움) | C66: =IF(C38="","",IFERROR(C38/(IF(COUNT('연간'!F4:I4)<4,"",SUM('연간'!F4:I4))),"")) | D66: =IF(D38="","",IFERROR(D38/(IF(COUNT('연간'!G4:J4)<4,"",SUM('연간'!G4:J4))),"")) | E66: =IF(E38="","",IFERROR(E38/(IF(COUNT('연간'!H4:K4)<4,"",SUM('연간'!H4:K4))),"")) | F66: =IF(F38="","",IFERROR(F38/(IF(COUNT('연간'!I4:L4)<4,"",SUM('연간'!I4:L4))),"")) | G66: =IF(G38="","",IFERROR(G38/(IF(COUNT('연간'!J4:M4)<4,"",SUM('연간'!J4:M4))),"")) | H66: =IF(H38="","",IFERROR(H38/('연간'!T4),"")) | I66: =IF(I38="","",IFERROR(I38/('연간'!U4),"")) | J66: =IF(J38="","",IFERROR(J38/('연간'!V4),"")) | K66: =IF(K38="","",IFERROR(K38/('연간'!W4),""))
A67: 배당성향 | B67: 참고 | C67: =IF(C40="","",IFERROR(C40/(IF(COUNT('연간'!F53:I53)<4,"",SUM('연간'!F53:I53))),"")) | D67: =IF(D40="","",IFERROR(D40/(IF(COUNT('연간'!G53:J53)<4,"",SUM('연간'!G53:J53))),"")) | E67: =IF(E40="","",IFERROR(E40/(IF(COUNT('연간'!H53:K53)<4,"",SUM('연간'!H53:K53))),"")) | F67: =IF(F40="","",IFERROR(F40/(IF(COUNT('연간'!I53:L53)<4,"",SUM('연간'!I53:L53))),"")) | G67: =IF(G40="","",IFERROR(G40/(IF(COUNT('연간'!J53:M53)<4,"",SUM('연간'!J53:M53))),"")) | H67: =IF(H40="","",IFERROR(H40/('연간'!T53),"")) | I67: =IF(I40="","",IFERROR(I40/('연간'!U53),"")) | J67: =IF(J40="","",IFERROR(J40/('연간'!V53),"")) | K67: =IF(K40="","",IFERROR(K40/('연간'!W53),""))
A69: 재무상태표 · 전 항목 | B69: 분기 말 잔액
A70: 항목 | B70: 참고 | C70: 2025.3Q | D70: 2025.4Q | E70: 2026.1Q | F70: 2026.2Q | G70: 2026.3Q | H70: 2022 | I70: 2023 | J70: 2024 | K70: 2025
A71: 현금 및 예금 | C71: 1872.416 | D71: 1650.048 | E71: 1257.565 | F71: 1707.71 | G71: 1942.751 | H71: 1758.992 | I71: 1665.094 | J71: 1769.981 | K71: 1650.048
A72: 받을어음 | E72: 70.181
A73: 매출채권 | E73: 931.106
A74: 유가증권 | C74: 0 | D74: 0 | E74: 0 | H74: 10 | I74: 0 | J74: 150 | K74: 0
A75: 받을어음·매출채권 | C75: 584.847 | D75: 721.239 | E75: 1001.287 | F75: 701.593 | G75: 583.368 | H75: 686.654 | I75: 519.277 | J75: 580.887 | K75: 721.239
A76: 상품·제품 | C76: 51.801 | D76: 30.292 | E76: 43.562 | F76: 106.195 | G76: 84.083 | H76: 87.831 | I76: 59.271 | J76: 64.167 | K76: 30.292
A77: 재공품 | C77: 216.299 | D77: 236.825 | E77: 167.599 | F77: 154.431 | G77: 176.987 | H77: 335.048 | I77: 359.059 | J77: 183.924 | K77: 236.825
A78: 원재료·저장품 | C78: 115.898 | D78: 109.052 | E78: 114.184 | F78: 128.516 | G78: 119.549 | H78: 109.663 | I78: 131.355 | J78: 131.309 | K78: 109.052
A79: 기타 | C79: 70.385 | D79: 30.108 | E79: 21.143 | F79: 13.931 | G79: 35.146 | H79: 52.069 | I79: 33.414 | J79: 36.846 | K79: 30.108
A80: 대손충당금 | C80: -0.391 | D80: -0.489 | E80: -0.674 | F80: -0.48 | G80: -0.385 | H80: -0.51 | I80: -0.318 | J80: -0.381 | K80: -0.489
A81: 유동자산 합계 | C81: 2911.257 | D81: 2777.075 | E81: 2604.667 | F81: 2811.898 | G81: 2941.501 | H81: 3039.748 | I81: 2767.155 | J81: 2916.735 | K81: 2777.075
A82: 건물·구축물(순액) | C82: 263.146 | D82: 259.827 | E82: 248.937 | F82: 243.392 | G82: 240.416 | H82: 318.382 | I82: 298.222 | J82: 280.888 | K82: 259.827
A83: 기계장치·운반구(순액) | C83: 188.266 | D83: 176.639 | E83: 160.447 | F83: 147.444 | G83: 147.226 | H83: 159.38 | I83: 176.698 | J83: 214.749 | K83: 176.639
A84: 토지 | C84: 903.724 | D84: 912.633 | E84: 914.686 | F84: 914.686 | G84: 914.686 | H84: 907.287 | I84: 912.019 | J84: 906.424 | K84: 912.633
A85: 기타(순액) | C85: 26.821 | D85: 31.179 | E85: 32.154 | F85: 29.779 | G85: 29.726 | H85: 33.261 | I85: 25.867 | J85: 37.481 | K85: 31.179
A86: 유형자산 합계 | C86: 1381.958 | D86: 1380.279 | E86: 1356.225 | F86: 1335.302 | G86: 1332.055 | H86: 1418.311 | I86: 1412.807 | J86: 1439.542 | K86: 1380.279
... A88: 무형자산 합계 | C88: 51.158 | D88: 46.476 | E88: 41.841 | F88: 37.556 | G88: 33.567 | H88: 28.124 | I88: 63.814 | J88: 60.9 | K88: 46.476
A89: 투자유가증권 | E89: 394.918 | G89: 526.788
A90: 보험적립금 | E90: 119.619
A91: 이연법인세자산 | E91: 2.476
A92: 기타 | C92: 499.393 | D92: 548.529 | E92: 176.61 | F92: 643.953 | G92: 186.675 | H92: 608.456 | I92: 586.56 | J92: 526.528 | K92: 548.529
A93: 대손충당금 | C93: -3.472 | D93: -3.382 | E93: -3.292 | F93: -3.202 | G93: -3.112 | H93: -4.402 | I93: -4.102 | J93: -3.742 | K93: -3.382
A94: 투자 및 기타자산 합계 | C94: 495.921 | D94: 545.147 | E94: 568.237 | F94: 640.751 | G94: 710.351 | H94: 604.053 | I94: 582.457 | J94: 522.785 | K94: 545.147
A95: 비유동자산 합계 | C95: 1929.037 | D95: 1971.903 | E95: 1966.304 | F95: 2013.61 | G95: 2075.974 | H95: 2050.489 | I95: 2059.079 | J95: 2023.229 | K95: 1971.903
A96: 자산 합계 | C96: 4840.294 | D96: 4748.978 | E96: 4570.972 | F96: 4825.509 | G96: 5017.476 | H96: 5090.238 | I96: 4826.234 | J96: 4939.964 | K96: 4748.978
A97: 지급어음·매입채무 | H97: 167.151
A98: 매입채무 | C98: 100.747 | D98: 183.237 | E98: 135.614 | F98: 124.486 | G98: 127.169 | I98: 97.028 | J98: 143.291 | K98: 183.237
A99: 단기차입금 | C99: 574.192 | D99: 562.165 | E99: 290.668 | F99: 510.689 | G99: 510.959 | H99: 599.197 | I99: 571.416 | J99: 598.676 | K99: 562.165
A100: 미지급법인세 | C100: 17.098 | D100: 13.967 | E100: 42.264 | F100: 16.693 | G100: 40.557 | H100: 0.044 | I100: 9.441 | J100: 15.618 | K100: 13.967
A101: 계약부채 | E101: 43.377
A102: 상여충당금 | D102: 33.999 | E102: 0 | F102: 42.999 | H102: 62.751 | I102: 48.249 | J102: 28.998 | K102: 33.999
...

Sheet 출처
A1: 출처 · 쓴 결산단신
A3: 공시일 | B3: 문서 | C3: PDF
A4: 2026-07-30 | B4: 2026년 12월 결산기 2분기 결산단신 | C4: https://www2.jpx.co.jp/disc/66630/140120260713592535.pdf
A5: 2026-04-24 | B5: 2026년 12월 결산기 1분기 결산단신 | C5: https://www2.jpx.co.jp/disc/66630/140120260406598632.pdf
A6: 2026-01-30 | B6: 2025년 12월 결산기 연간 결산단신 | C6: https://www2.jpx.co.jp/disc/66630/140120260115534361.pdf
A7: 2025-10-24 | B7: 2025년 12월 결산기 3분기 결산단신 | C7: https://www2.jpx.co.jp/disc/66630/140120251007569636.pdf
A8: 2025-07-30 | B8: 2025년 12월 결산기 2분기 결산단신 | C8: https://www2.jpx.co.jp/disc/66630/140120250618592901.pdf
A9: 2025-04-25 | B9: 2025년 12월 결산기 1분기 결산단신 | C9: https://www2.jpx.co.jp/disc/66630/140120250404509322.pdf
A10: 2025-01-31 | B10: 2024년 12월 결산기 연간 결산단신 | C10: https://www2.jpx.co.jp/disc/66630/140120241218540676.pdf
A11: 2024-10-25 | B11: 2024년 12월 결산기 3분기 결산단신 | C11: https://www2.jpx.co.jp/disc/66630/140120240912583995.pdf
A12: 2024-07-30 | B12: 2024년 12월 결산기 2분기 결산단신 | C12: https://www2.jpx.co.jp/disc/66630/140120240722552383.pdf
A13: 2024-04-26 | B13: 2024년 12월 결산기 1분기 결산단신 | C13: https://www2.jpx.co.jp/disc/66630/140120240401564224.pdf
A14: 2024-01-30 | B14: 2023년 12월 결산기 연간 결산단신 | C14: https://www2.jpx.co.jp/disc/66630/140120231221506600.pdf
... A24: 2018-01-30 | B24: 연간 결산단신 | C24: https://www2.jpx.co.jp/disc/66630/140120171227443538.pdf
