Workbook

Sheet 연간
A1: 6861 Model
A2: 모를 땐 보수적으로 | B2: (단위: 백만엔) | C2: 2월 결산 · 일본 기준 · 2027.4Q = 2027년 2월 결산기 4분기 | Y2: (추정: 파란 글씨 = 직접 입력)
A3: 항목 | B3: 참고 | C3: 2025.1Q | D3: 2025.2Q | E3: 2025.3Q | F3: 2025.4Q | G3: 2026.1Q | H3: 2026.2Q | I3: 2026.3Q | J3: 2026.4Q | K3: 2027.1Q | L3: 2027.2Q | M3: 2027.3Q | N3: 2027.4Q | O3: 2018 | P3: 2019 | Q3: 2020 | R3: 2021 | S3: 2022 | T3: 2023 | U3: 2024 | V3: 2025 | W3: 2026 | X3: 2027 | Y3: 2028(MW) | Z3: 2029(MW) | AA3: 2030(MW) | AB3: 2031(MW) | AC3: 2032(MW)
A4: 매출액 | B4: MW 직접 입력 | C4: 247223 | D4: 268327 | E4: 259640 | F4: 192098 | G4: 261076 | H4: 284224 | I4: 289305 | J4: 224540 | K4: 346621 | P4: 526847 | Q4: 587095 | R4: 551843 | S4: 538134 | T4: 755174 | U4: 922422 | V4: 967288 | W4: 1059145 | X4: 1169289 | Y4: =IF(COUNT(Y7)=0,"",SUM(Y7)) | Z4: =IF(COUNT(Z7)=0,"",SUM(Z7)) | AA4: =IF(COUNT(AA7)=0,"",SUM(AA7)) | AB4: =IF(COUNT(AB7)=0,"",SUM(AB7)) | AC4: =IF(COUNT(AC7)=0,"",SUM(AC7))
A5: YoY | G5: =IF(OR(G4="",C4=""),"",IFERROR(G4/C4-1,"")) | H5: =IF(OR(H4="",D4=""),"",IFERROR(H4/D4-1,"")) | I5: =IF(OR(I4="",E4=""),"",IFERROR(I4/E4-1,"")) | J5: =IF(OR(J4="",F4=""),"",IFERROR(J4/F4-1,"")) | K5: =IF(OR(K4="",G4=""),"",IFERROR(K4/G4-1,"")) | L5: =IF(OR(L4="",H4=""),"",IFERROR(L4/H4-1,"")) | M5: =IF(OR(M4="",I4=""),"",IFERROR(M4/I4-1,"")) | N5: =IF(OR(N4="",J4=""),"",IFERROR(N4/J4-1,"")) | P5: =IF(OR(P4="",O4=""),"",IFERROR(P4/O4-1,"")) | Q5: =IF(OR(Q4="",P4=""),"",IFERROR(Q4/P4-1,"")) | R5: =IF(OR(R4="",Q4=""),"",IFERROR(R4/Q4-1,"")) | S5: =IF(OR(S4="",R4=""),"",IFERROR(S4/R4-1,"")) | T5: =IF(OR(T4="",S4=""),"",IFERROR(T4/S4-1,"")) | U5: =IF(OR(U4="",T4=""),"",IFERROR(U4/T4-1,"")) | V5: =IF(OR(V4="",U4=""),"",IFERROR(V4/U4-1,"")) | W5: =IF(OR(W4="",V4=""),"",IFERROR(W4/V4-1,"")) | ... AC5: =IF(OR(AC4="",AB4=""),"",IFERROR(AC4/AB4-1,""))
A6: 제품별 매출 분류 | B6: 사업보고서 매출실적
A7: (제품별 매출 미공시 — 직접 입력)
A8: 비중 | C8: =IF(OR(C7="",C4=""),"",IFERROR(C7/C4,"")) | D8: =IF(OR(D7="",D4=""),"",IFERROR(D7/D4,"")) | E8: =IF(OR(E7="",E4=""),"",IFERROR(E7/E4,"")) | F8: =IF(OR(F7="",F4=""),"",IFERROR(F7/F4,"")) | G8: =IF(OR(G7="",G4=""),"",IFERROR(G7/G4,"")) | H8: =IF(OR(H7="",H4=""),"",IFERROR(H7/H4,"")) | I8: =IF(OR(I7="",I4=""),"",IFERROR(I7/I4,"")) | J8: =IF(OR(J7="",J4=""),"",IFERROR(J7/J4,"")) | ... AC8: =IF(OR(AC7="",AC4=""),"",IFERROR(AC7/AC4,""))
A9: YoY | G9: =IF(OR(G7="",C7=""),"",IFERROR(G7/C7-1,"")) | H9: =IF(OR(H7="",D7=""),"",IFERROR(H7/D7-1,"")) | I9: =IF(OR(I7="",E7=""),"",IFERROR(I7/E7-1,"")) | J9: =IF(OR(J7="",F7=""),"",IFERROR(J7/F7-1,"")) | K9: =IF(OR(K7="",G7=""),"",IFERROR(K7/G7-1,"")) | L9: =IF(OR(L7="",H7=""),"",IFERROR(L7/H7-1,"")) | M9: =IF(OR(M7="",I7=""),"",IFERROR(M7/I7-1,"")) | N9: =IF(OR(N7="",J7=""),"",IFERROR(N7/J7-1,"")) | P9: =IF(OR(P7="",O7=""),"",IFERROR(P7/O7-1,"")) | Q9: =IF(OR(Q7="",P7=""),"",IFERROR(Q7/P7-1,"")) | R9: =IF(OR(R7="",Q7=""),"",IFERROR(R7/Q7-1,"")) | S9: =IF(OR(S7="",R7=""),"",IFERROR(S7/R7-1,"")) | T9: =IF(OR(T7="",S7=""),"",IFERROR(T7/S7-1,"")) | U9: =IF(OR(U7="",T7=""),"",IFERROR(U7/T7-1,"")) | V9: =IF(OR(V7="",U7=""),"",IFERROR(V7/U7-1,"")) | W9: =IF(OR(W7="",V7=""),"",IFERROR(W7/V7-1,"")) | ... AC9: =IF(OR(AC7="",AB7=""),"",IFERROR(AC7/AB7-1,""))
A10: 매출원가
A11: 전체 매출원가 | C11: 39831 | D11: 42467 | E11: 42282 | F11: 40202 | G11: 45412 | H11: 49010 | I11: 48769 | J11: 28253 | K11: 51866 | P11: 94174 | Q11: 103623 | R11: 100406 | S11: 97250 | T11: 133984 | U11: 167690 | V11: 164782 | W11: 171444 | X11: 198552
A12: 매출총이익 | C12: =IF(OR(C4="",C11=""),"",IFERROR(C4-C11,"")) | D12: =IF(OR(D4="",D11=""),"",IFERROR(D4-D11,"")) | E12: =IF(OR(E4="",E11=""),"",IFERROR(E4-E11,"")) | F12: =IF(OR(F4="",F11=""),"",IFERROR(F4-F11,"")) | G12: =IF(OR(G4="",G11=""),"",IFERROR(G4-G11,"")) | H12: =IF(OR(H4="",H11=""),"",IFERROR(H4-H11,"")) | I12: =IF(OR(I4="",I11=""),"",IFERROR(I4-I11,"")) | J12: =IF(OR(J4="",J11=""),"",IFERROR(J4-J11,"")) | ... X12: =IF(OR(X4="",X11=""),"",IFERROR(X4-X11,""))
A13: GPM | C13: =IF(OR(C12="",C4=""),"",IFERROR(C12/C4,"")) | D13: =IF(OR(D12="",D4=""),"",IFERROR(D12/D4,"")) | E13: =IF(OR(E12="",E4=""),"",IFERROR(E12/E4,"")) | F13: =IF(OR(F12="",F4=""),"",IFERROR(F12/F4,"")) | G13: =IF(OR(G12="",G4=""),"",IFERROR(G12/G4,"")) | H13: =IF(OR(H12="",H4=""),"",IFERROR(H12/H4,"")) | I13: =IF(OR(I12="",I4=""),"",IFERROR(I12/I4,"")) | J13: =IF(OR(J12="",J4=""),"",IFERROR(J12/J4,"")) | ... AC13: =IF(OR(AC12="",AC4=""),"",IFERROR(AC12/AC4,""))
A14: 판매관리비
A15: 전체 판관비 | C15: 83986 | D15: 85301 | E15: 84288 | F15: 53916 | G15: 86363 | H15: 92335 | I15: 96334 | J15: 62893 | K15: 107679 | P15: 139781 | Q15: 165604 | R15: 173805 | S15: 164125 | T15: 203145 | U15: 255817 | V15: 307491 | W15: 337925 | X15: 374978
A16: 영업이익 | B16: MW = 매출 × OPM | C16: 123405 | D16: 140560 | E16: 133068 | F16: 97981 | G16: 129301 | H16: 142878 | I16: 144202 | J16: 133394 | K16: 187076 | P16: 292890 | Q16: 317868 | R16: 277631 | S16: 276758 | T16: 418045 | U16: 498914 | V16: 495014 | W16: 549775 | X16: 595759 | Y16: =IF(OR(Y4="",Y17=""),"",IFERROR(Y4*Y17,"")) | Z16: =IF(OR(Z4="",Z17=""),"",IFERROR(Z4*Z17,"")) | AA16: =IF(OR(AA4="",AA17=""),"",IFERROR(AA4*AA17,"")) | AB16: =IF(OR(AB4="",AB17=""),"",IFERROR(AB4*AB17,"")) | AC16: =IF(OR(AC4="",AC17=""),"",IFERROR(AC4*AC17,""))
A17: OPM | B17: MW 입력 | C17: =IF(OR(C16="",C4=""),"",IFERROR(C16/C4,"")) | D17: =IF(OR(D16="",D4=""),"",IFERROR(D16/D4,"")) | E17: =IF(OR(E16="",E4=""),"",IFERROR(E16/E4,"")) | F17: =IF(OR(F16="",F4=""),"",IFERROR(F16/F4,"")) | G17: =IF(OR(G16="",G4=""),"",IFERROR(G16/G4,"")) | H17: =IF(OR(H16="",H4=""),"",IFERROR(H16/H4,"")) | I17: =IF(OR(I16="",I4=""),"",IFERROR(I16/I4,"")) | J17: =IF(OR(J16="",J4=""),"",IFERROR(J16/J4,"")) | ... X17: =IF(OR(X16="",X4=""),"",IFERROR(X16/X4,""))
A18: 증가율 | G18: =IF(OR(G16="",C16=""),"",IFERROR(G16/C16-1,"")) | H18: =IF(OR(H16="",D16=""),"",IFERROR(H16/D16-1,"")) | I18: =IF(OR(I16="",E16=""),"",IFERROR(I16/E16-1,"")) | J18: =IF(OR(J16="",F16=""),"",IFERROR(J16/F16-1,"")) | K18: =IF(OR(K16="",G16=""),"",IFERROR(K16/G16-1,"")) | L18: =IF(OR(L16="",H16=""),"",IFERROR(L16/H16-1,"")) | M18: =IF(OR(M16="",I16=""),"",IFERROR(M16/I16-1,"")) | N18: =IF(OR(N16="",J16=""),"",IFERROR(N16/J16-1,"")) | P18: =IF(OR(P16="",O16=""),"",IFERROR(P16/O16-1,"")) | Q18: =IF(OR(Q16="",P16=""),"",IFERROR(Q16/P16-1,"")) | R18: =IF(OR(R16="",Q16=""),"",IFERROR(R16/Q16-1,"")) | S18: =IF(OR(S16="",R16=""),"",IFERROR(S16/R16-1,"")) | T18: =IF(OR(T16="",S16=""),"",IFERROR(T16/S16-1,"")) | U18: =IF(OR(U16="",T16=""),"",IFERROR(U16/T16-1,"")) | V18: =IF(OR(V16="",U16=""),"",IFERROR(V16/U16-1,"")) | W18: =IF(OR(W16="",V16=""),"",IFERROR(W16/V16-1,"")) | ... AC18: =IF(OR(AC16="",AB16=""),"",IFERROR(AC16/AB16-1,""))
A19: 비용의 성격별 분류 | B19: 참고 데이터
A20: 총 판관비 | O20: =IF(O15="","",O15) | P20: =IF(P15="","",P15) | Q20: =IF(Q15="","",Q15) | R20: =IF(R15="","",R15) | S20: =IF(S15="","",S15) | T20: =IF(T15="","",T15) | U20: =IF(U15="","",U15) | V20: =IF(V15="","",V15) | ... X20: =IF(X15="","",X15)
A21: 급여 | B21: 고정비
A22: % of Sales | O22: =IF(OR(O21="",O4=""),"",IFERROR(O21/O4,"")) | P22: =IF(OR(P21="",P4=""),"",IFERROR(P21/P4,"")) | Q22: =IF(OR(Q21="",Q4=""),"",IFERROR(Q21/Q4,"")) | R22: =IF(OR(R21="",R4=""),"",IFERROR(R21/R4,"")) | S22: =IF(OR(S21="",S4=""),"",IFERROR(S21/S4,"")) | T22: =IF(OR(T21="",T4=""),"",IFERROR(T21/T4,"")) | U22: =IF(OR(U21="",U4=""),"",IFERROR(U21/U4,"")) | V22: =IF(OR(V21="",V4=""),"",IFERROR(V21/V4,"")) | ... X22: =IF(OR(X21="",X4=""),"",IFERROR(X21/X4,""))
A23: 감가상각비 | B23: 고정비
A24: % of Sales | O24: =IF(OR(O23="",O4=""),"",IFERROR(O23/O4,"")) | P24: =IF(OR(P23="",P4=""),"",IFERROR(P23/P4,"")) | Q24: =IF(OR(Q23="",Q4=""),"",IFERROR(Q23/Q4,"")) | R24: =IF(OR(R23="",R4=""),"",IFERROR(R23/R4,"")) | S24: =IF(OR(S23="",S4=""),"",IFERROR(S23/S4,"")) | T24: =IF(OR(T23="",T4=""),"",IFERROR(T23/T4,"")) | U24: =IF(OR(U23="",U4=""),"",IFERROR(U23/U4,"")) | V24: =IF(OR(V23="",V4=""),"",IFERROR(V23/V4,"")) | ... X24: =IF(OR(X23="",X4=""),"",IFERROR(X23/X4,""))
A25: 지급수수료 | B25: 고정비
A26: % of Sales | O26: =IF(OR(O25="",O4=""),"",IFERROR(O25/O4,"")) | P26: =IF(OR(P25="",P4=""),"",IFERROR(P25/P4,"")) | Q26: =IF(OR(Q25="",Q4=""),"",IFERROR(Q25/Q4,"")) | R26: =IF(OR(R25="",R4=""),"",IFERROR(R25/R4,"")) | S26: =IF(OR(S25="",S4=""),"",IFERROR(S25/S4,"")) | T26: =IF(OR(T25="",T4=""),"",IFERROR(T25/T4,"")) | U26: =IF(OR(U25="",U4=""),"",IFERROR(U25/U4,"")) | V26: =IF(OR(V25="",V4=""),"",IFERROR(V25/V4,"")) | ... X26: =IF(OR(X25="",X4=""),"",IFERROR(X25/X4,""))
A27: 연구개발비 | B27: 변동비
A28: % of Sales | O28: =IF(OR(O27="",O4=""),"",IFERROR(O27/O4,"")) | P28: =IF(OR(P27="",P4=""),"",IFERROR(P27/P4,"")) | Q28: =IF(OR(Q27="",Q4=""),"",IFERROR(Q27/Q4,"")) | R28: =IF(OR(R27="",R4=""),"",IFERROR(R27/R4,"")) | S28: =IF(OR(S27="",S4=""),"",IFERROR(S27/S4,"")) | T28: =IF(OR(T27="",T4=""),"",IFERROR(T27/T4,"")) | U28: =IF(OR(U27="",U4=""),"",IFERROR(U27/U4,"")) | V28: =IF(OR(V27="",V4=""),"",IFERROR(V27/V4,"")) | ... X28: =IF(OR(X27="",X4=""),"",IFERROR(X27/X4,""))
A29: 기타비용 | B29: 변동비 | O29: =IF(OR(O20="",O21="",O23="",O25="",O27=""),"",IFERROR(O20-O21-O23-O25-O27,"")) | P29: =IF(OR(P20="",P21="",P23="",P25="",P27=""),"",IFERROR(P20-P21-P23-P25-P27,"")) | Q29: =IF(OR(Q20="",Q21="",Q23="",Q25="",Q27=""),"",IFERROR(Q20-Q21-Q23-Q25-Q27,"")) | R29: =IF(OR(R20="",R21="",R23="",R25="",R27=""),"",IFERROR(R20-R21-R23-R25-R27,"")) | S29: =IF(OR(S20="",S21="",S23="",S25="",S27=""),"",IFERROR(S20-S21-S23-S25-S27,"")) | T29: =IF(OR(T20="",T21="",T23="",T25="",T27=""),"",IFERROR(T20-T21-T23-T25-T27,"")) | U29: =IF(OR(U20="",U21="",U23="",U25="",U27=""),"",IFERROR(U20-U21-U23-U25-U27,"")) | V29: =IF(OR(V20="",V21="",V23="",V25="",V27=""),"",IFERROR(V20-V21-V23-V25-V27,"")) | ... X29: =IF(OR(X20="",X21="",X23="",X25="",X27=""),"",IFERROR(X20-X21-X23-X25-X27,""))
A30: % of Sales | O30: =IF(OR(O29="",O4=""),"",IFERROR(O29/O4,"")) | P30: =IF(OR(P29="",P4=""),"",IFERROR(P29/P4,"")) | Q30: =IF(OR(Q29="",Q4=""),"",IFERROR(Q29/Q4,"")) | R30: =IF(OR(R29="",R4=""),"",IFERROR(R29/R4,"")) | S30: =IF(OR(S29="",S4=""),"",IFERROR(S29/S4,"")) | T30: =IF(OR(T29="",T4=""),"",IFERROR(T29/T4,"")) | U30: =IF(OR(U29="",U4=""),"",IFERROR(U29/U4,"")) | V30: =IF(OR(V29="",V4=""),"",IFERROR(V29/V4,"")) | ... X30: =IF(OR(X29="",X4=""),"",IFERROR(X29/X4,""))
A31: 당기순이익 추정
A32: 특별이익 | Y32: =IF(OR(Y4="",Y33=""),"",IFERROR(Y4*Y33,"")) | Z32: =IF(OR(Z4="",Z33=""),"",IFERROR(Z4*Z33,"")) | AA32: =IF(OR(AA4="",AA33=""),"",IFERROR(AA4*AA33,"")) | AB32: =IF(OR(AB4="",AB33=""),"",IFERROR(AB4*AB33,"")) | AC32: =IF(OR(AC4="",AC33=""),"",IFERROR(AC4*AC33,""))
A33: % of Sales | B33: MW = 최근 3년 평균 | C33: =IF(OR(C32="",C4=""),"",IFERROR(C32/C4,"")) | D33: =IF(OR(D32="",D4=""),"",IFERROR(D32/D4,"")) | E33: =IF(OR(E32="",E4=""),"",IFERROR(E32/E4,"")) | F33: =IF(OR(F32="",F4=""),"",IFERROR(F32/F4,"")) | G33: =IF(OR(G32="",G4=""),"",IFERROR(G32/G4,"")) | H33: =IF(OR(H32="",H4=""),"",IFERROR(H32/H4,"")) | I33: =IF(OR(I32="",I4=""),"",IFERROR(I32/I4,"")) | J33: =IF(OR(J32="",J4=""),"",IFERROR(J32/J4,"")) | ... X33: =IF(OR(X32="",X4=""),"",IFERROR(X32/X4,"")) | Y33: =IFERROR(AVERAGE(V33,W33,X33),"") | Z33: =Y33 | AA33: =Z33 | AB33: =AA33 | AC33: =AB33
A34: 특별손실 | Y34: =IF(OR(Y4="",Y35=""),"",IFERROR(Y4*Y35,"")) | Z34: =IF(OR(Z4="",Z35=""),"",IFERROR(Z4*Z35,"")) | AA34: =IF(OR(AA4="",AA35=""),"",IFERROR(AA4*AA35,"")) | AB34: =IF(OR(AB4="",AB35=""),"",IFERROR(AB4*AB35,"")) | AC34: =IF(OR(AC4="",AC35=""),"",IFERROR(AC4*AC35,""))
A35: % of Sales | C35: =IF(OR(C34="",C4=""),"",IFERROR(C34/C4,"")) | D35: =IF(OR(D34="",D4=""),"",IFERROR(D34/D4,"")) | E35: =IF(OR(E34="",E4=""),"",IFERROR(E34/E4,"")) | F35: =IF(OR(F34="",F4=""),"",IFERROR(F34/F4,"")) | G35: =IF(OR(G34="",G4=""),"",IFERROR(G34/G4,"")) | H35: =IF(OR(H34="",H4=""),"",IFERROR(H34/H4,"")) | I35: =IF(OR(I34="",I4=""),"",IFERROR(I34/I4,"")) | J35: =IF(OR(J34="",J4=""),"",IFERROR(J34/J4,"")) | ... X35: =IF(OR(X34="",X4=""),"",IFERROR(X34/X4,"")) | Y35: =IFERROR(AVERAGE(V35,W35,X35),"") | Z35: =Y35 | AA35: =Z35 | AB35: =AA35 | AC35: =AB35
A36: 영업외수익 | C36: 8084 | D36: -1518 | E36: 6998 | F36: 11405 | G36: 4383 | H36: 8566 | I36: 14473 | J36: -11102 | K36: 9798 | P36: 6225 | Q36: 2743 | R36: 6587 | S36: 9954 | T36: 13356 | U36: 14166 | V36: 24969 | W36: 16320 | X36: 40491 | Y36: =IF(OR(Y4="",Y37=""),"",IFERROR(Y4*Y37,"")) | Z36: =IF(OR(Z4="",Z37=""),"",IFERROR(Z4*Z37,"")) | AA36: =IF(OR(AA4="",AA37=""),"",IFERROR(AA4*AA37,"")) | AB36: =IF(OR(AB4="",AB37=""),"",IFERROR(AB4*AB37,"")) | AC36: =IF(OR(AC4="",AC37=""),"",IFERROR(AC4*AC37,""))
A37: % of Sales | C37: =IF(OR(C36="",C4=""),"",IFERROR(C36/C4,"")) | D37: =IF(OR(D36="",D4=""),"",IFERROR(D36/D4,"")) | E37: =IF(OR(E36="",E4=""),"",IFERROR(E36/E4,"")) | F37: =IF(OR(F36="",F4=""),"",IFERROR(F36/F4,"")) | G37: =IF(OR(G36="",G4=""),"",IFERROR(G36/G4,"")) | H37: =IF(OR(H36="",H4=""),"",IFERROR(H36/H4,"")) | I37: =IF(OR(I36="",I4=""),"",IFERROR(I36/I4,"")) | J37: =IF(OR(J36="",J4=""),"",IFERROR(J36/J4,"")) | ... X37: =IF(OR(X36="",X4=""),"",IFERROR(X36/X4,"")) | Y37: =IFERROR(AVERAGE(V37,W37,X37),"") | Z37: =Y37 | AA37: =Z37 | AB37: =AA37 | AC37: =AB37
A38: 영업외비용 | C38: 44 | D38: 4770 | E38: -4553 | F38: 427 | G38: 2153 | H38: -2024 | I38: 60 | J38: 4896 | K38: 81 | P38: 256 | Q38: 751 | R38: 3965 | S38: 118 | T38: 161 | U38: 251 | V38: 688 | W38: 5085 | X38: 494 | Y38: =IF(OR(Y4="",Y39=""),"",IFERROR(Y4*Y39,"")) | Z38: =IF(OR(Z4="",Z39=""),"",IFERROR(Z4*Z39,"")) | AA38: =IF(OR(AA4="",AA39=""),"",IFERROR(AA4*AA39,"")) | AB38: =IF(OR(AB4="",AB39=""),"",IFERROR(AB4*AB39,"")) | AC38: =IF(OR(AC4="",AC39=""),"",IFERROR(AC4*AC39,""))
A39: % of Sales | C39: =IF(OR(C38="",C4=""),"",IFERROR(C38/C4,"")) | D39: =IF(OR(D38="",D4=""),"",IFERROR(D38/D4,"")) | E39: =IF(OR(E38="",E4=""),"",IFERROR(E38/E4,"")) | F39: =IF(OR(F38="",F4=""),"",IFERROR(F38/F4,"")) | G39: =IF(OR(G38="",G4=""),"",IFERROR(G38/G4,"")) | H39: =IF(OR(H38="",H4=""),"",IFERROR(H38/H4,"")) | I39: =IF(OR(I38="",I4=""),"",IFERROR(I38/I4,"")) | J39: =IF(OR(J38="",J4=""),"",IFERROR(J38/J4,"")) | ... X39: =IF(OR(X38="",X4=""),"",IFERROR(X38/X4,"")) | Y39: =IFERROR(AVERAGE(V39,W39,X39),"") | Z39: =Y39 | AA39: =Z39 | AB39: =AA39 | AC39: =AB39
A40: 법인세비용차감전순이익(손실) | C40: 131444 | D40: 134273 | E40: 144619 | F40: 108959 | G40: 131532 | H40: 153468 | I40: 158614 | J40: 117396 | K40: 196793 | P40: 298860 | Q40: 319860 | R40: 280253 | S40: 286594 | T40: 431240 | U40: 512830 | V40: 519295 | W40: 561010 | X40: 635756 | Y40: =IF(OR(Y16=""),"",IFERROR(Y16+N(Y32)-N(Y34)+N(Y36)-N(Y38),"")) | Z40: =IF(OR(Z16=""),"",IFERROR(Z16+N(Z32)-N(Z34)+N(Z36)-N(Z38),"")) | AA40: =IF(OR(AA16=""),"",IFERROR(AA16+N(AA32)-N(AA34)+N(AA36)-N(AA38),"")) | AB40: =IF(OR(AB16=""),"",IFERROR(AB16+N(AB32)-N(AB34)+N(AB36)-N(AB38),"")) | AC40: =IF(OR(AC16=""),"",IFERROR(AC16+N(AC32)-N(AC34)+N(AC36)-N(AC38),""))
A41: 법인세비용(수익) | C41: 37909 | D41: 38088 | E41: 42574 | F41: 31082 | G41: 39415 | H41: 45625 | I41: 47406 | J41: 29907 | K41: 57660 | P41: 88264 | Q41: 93713 | R41: 82129 | S41: 89305 | T41: 127880 | U41: 149866 | V41: 149653 | W41: 162353 | X41: 190570 | Y41: =IF(OR(Y40="",Y42=""),"",IFERROR(MAX(Y40,0)*Y42,"")) | Z41: =IF(OR(Z40="",Z42=""),"",IFERROR(MAX(Z40,0)*Z42,"")) | AA41: =IF(OR(AA40="",AA42=""),"",IFERROR(MAX(AA40,0)*AA42,"")) | AB41: =IF(OR(AB40="",AB42=""),"",IFERROR(MAX(AB40,0)*AB42,"")) | AC41: =IF(OR(AC40="",AC42=""),"",IFERROR(MAX(AC40,0)*AC42,""))
A42: 법인세율 | B42: MW 기본 30% | C42: =IF(OR(C41="",C40=""),"",IFERROR(C41/C40,"")) | D42: =IF(OR(D41="",D40=""),"",IFERROR(D41/D40,"")) | E42: =IF(OR(E41="",E40=""),"",IFERROR(E41/E40,"")) | F42: =IF(OR(F41="",F40=""),"",IFERROR(F41/F40,"")) | G42: =IF(OR(G41="",G40=""),"",IFERROR(G41/G40,"")) | H42: =IF(OR(H41="",H40=""),"",IFERROR(H41/H40,"")) | I42: =IF(OR(I41="",I40=""),"",IFERROR(I41/I40,"")) | J42: =IF(OR(J41="",J40=""),"",IFERROR(J41/J40,"")) | ... X42: =IF(OR(X41="",X40=""),"",IFERROR(X41/X40,"")) | Y42: 0.3 | Z42: 0.3 | AA42: 0.3 | AB42: 0.3 | AC42: 0.3
A43: 당기순이익(손실) | C43: 93534 | D43: 96186 | E43: 102045 | F43: 77877 | G43: 92116 | H43: 107843 | I43: 111208 | J43: 87489 | K43: 139133 | P43: 210595 | Q43: 226147 | R43: 198124 | S43: 197289 | T43: 303360 | U43: 362963 | V43: 369642 | W43: 398656 | X43: 445185 | Y43: =IF(OR(Y40=""),"",IFERROR(Y40-Y41,"")) | Z43: =IF(OR(Z40=""),"",IFERROR(Z40-Z41,"")) | AA43: =IF(OR(AA40=""),"",IFERROR(AA40-AA41,"")) | AB43: =IF(OR(AB40=""),"",IFERROR(AB40-AB41,"")) | AC43: =IF(OR(AC40=""),"",IFERROR(AC40-AC41,""))
A44: 지배주주 순이익 | C44: 93534 | D44: 96186 | E44: 102045 | F44: 77877 | G44: 92116 | H44: 107843 | I44: 111208 | J44: 87489 | K44: 139133 | P44: 210595 | Q44: 226147 | R44: 198124 | S44: 197289 | T44: 303360 | U44: 362963 | V44: 369642 | W44: 398656 | X44: 445185 | Y44: =IF(OR(Y43="",Y45=""),"",IFERROR(Y43*Y45,"")) | Z44: =IF(OR(Z43="",Z45=""),"",IFERROR(Z43*Z45,"")) | AA44: =IF(OR(AA43="",AA45=""),"",IFERROR(AA43*AA45,"")) | AB44: =IF(OR(AB43="",AB45=""),"",IFERROR(AB43*AB45,"")) | AC44: =IF(OR(AC43="",AC45=""),"",IFERROR(AC43*AC45,""))
A45: 지배주주 순이익률 | B45: MW 기본 100% | C45: =IF(OR(C44="",C43=""),"",IFERROR(C44/C43,"")) | D45: =IF(OR(D44="",D43=""),"",IFERROR(D44/D43,"")) | E45: =IF(OR(E44="",E43=""),"",IFERROR(E44/E43,"")) | F45: =IF(OR(F44="",F43=""),"",IFERROR(F44/F43,"")) | G45: =IF(OR(G44="",G43=""),"",IFERROR(G44/G43,"")) | H45: =IF(OR(H44="",H43=""),"",IFERROR(H44/H43,"")) | I45: =IF(OR(I44="",I43=""),"",IFERROR(I44/I43,"")) | J45: =IF(OR(J44="",J43=""),"",IFERROR(J44/J43,"")) | ... X45: =IF(OR(X44="",X43=""),"",IFERROR(X44/X43,"")) | Y45: 1 | Z45: 1 | AA45: 1 | AB45: 1 | AC45: 1
A46: 목표주가 산출
A47: 현재 주가 (2026.10.26) | B47: 77270
A48: 발행주식수 (보통주) | B48: 243207684
A49: 시가총액 (백만엔) | B49: =IF(OR(B47="",B48=""),"",B47*B48/1000000.0)
A50: OPM | O50: =IF(O17="","",O17) | P50: =IF(P17="","",P17) | Q50: =IF(Q17="","",Q17) | R50: =IF(R17="","",R17) | S50: =IF(S17="","",S17) | T50: =IF(T17="","",T17) | U50: =IF(U17="","",U17) | V50: =IF(V17="","",V17) | ... AC50: =IF(AC17="","",AC17)
A51: 지배주주 순이익 증가율 | P51: =IF(OR(P44="",O44=""),"",IFERROR(P44/O44-1,"")) | Q51: =IF(OR(Q44="",P44=""),"",IFERROR(Q44/P44-1,"")) | R51: =IF(OR(R44="",Q44=""),"",IFERROR(R44/Q44-1,"")) | S51: =IF(OR(S44="",R44=""),"",IFERROR(S44/R44-1,"")) | T51: =IF(OR(T44="",S44=""),"",IFERROR(T44/S44-1,"")) | U51: =IF(OR(U44="",T44=""),"",IFERROR(U44/T44-1,"")) | V51: =IF(OR(V44="",U44=""),"",IFERROR(V44/U44-1,"")) | W51: =IF(OR(W44="",V44=""),"",IFERROR(W44/V44-1,"")) | ... AC51: =IF(OR(AC44="",AB44=""),"",IFERROR(AC44/AB44-1,""))
A52: P/E (현재 주가) | B52: 시총 ÷ 지배순이익 | X52: =IF(OR($B$49="",X44=""),"",IFERROR($B$49/X44,"")) | Y52: =IF(OR($B$49="",Y44=""),"",IFERROR($B$49/Y44,"")) | Z52: =IF(OR($B$49="",Z44=""),"",IFERROR($B$49/Z44,"")) | AA52: =IF(OR($B$49="",AA44=""),"",IFERROR($B$49/AA44,"")) | AB52: =IF(OR($B$49="",AB44=""),"",IFERROR($B$49/AB44,"")) | AC52: =IF(OR($B$49="",AC44=""),"",IFERROR($B$49/AC44,""))
A53: Target P/E | B53: 직접 입력
A54: EPS | B54: 지배순이익 ÷ 주식수 | O54: =IF(OR(O44="",$B$48=""),"",IFERROR(O44*1000000.0/$B$48,"")) | P54: =IF(OR(P44="",$B$48=""),"",IFERROR(P44*1000000.0/$B$48,"")) | Q54: =IF(OR(Q44="",$B$48=""),"",IFERROR(Q44*1000000.0/$B$48,"")) | R54: =IF(OR(R44="",$B$48=""),"",IFERROR(R44*1000000.0/$B$48,"")) | S54: =IF(OR(S44="",$B$48=""),"",IFERROR(S44*1000000.0/$B$48,"")) | T54: =IF(OR(T44="",$B$48=""),"",IFERROR(T44*1000000.0/$B$48,"")) | U54: =IF(OR(U44="",$B$48=""),"",IFERROR(U44*1000000.0/$B$48,"")) | V54: =IF(OR(V44="",$B$48=""),"",IFERROR(V44*1000000.0/$B$48,"")) | ... AC54: =IF(OR(AC44="",$B$48=""),"",IFERROR(AC44*1000000.0/$B$48,""))
A55: 목표주가 | Y55: =IF(OR(Y54="",Y53=""),"",IFERROR(Y54*Y53,"")) | Z55: =IF(OR(Z54="",Z53=""),"",IFERROR(Z54*Z53,"")) | AA55: =IF(OR(AA54="",AA53=""),"",IFERROR(AA54*AA53,"")) | AB55: =IF(OR(AB54="",AB53=""),"",IFERROR(AB54*AB53,"")) | AC55: =IF(OR(AC54="",AC53=""),"",IFERROR(AC54*AC53,""))
A56: 상승여력 | Y56: =IF(OR(Y55="",$B$47=""),"",IFERROR(Y55/$B$47-1,"")) | Z56: =IF(OR(Z55="",$B$47=""),"",IFERROR(Z55/$B$47-1,"")) | AA56: =IF(OR(AA55="",$B$47=""),"",IFERROR(AA55/$B$47-1,"")) | AB56: =IF(OR(AB55="",$B$47=""),"",IFERROR(AB55/$B$47-1,"")) | AC56: =IF(OR(AC55="",$B$47=""),"",IFERROR(AC55/$B$47-1,""))
A57: 자산가치 산출 | B57: 최신 분기 BS
A58: 현금및현금성자산 | X58: ='재무상태표'!G6 | Y58: ='재무상태표'!G6 | Z58: ='재무상태표'!G6 | AA58: ='재무상태표'!G6 | AB58: ='재무상태표'!G6 | AC58: ='재무상태표'!G6
A59: 단기금융상품 | X59: ='재무상태표'!G7 | Y59: ='재무상태표'!G7 | Z59: ='재무상태표'!G7 | AA59: ='재무상태표'!G7 | AB59: ='재무상태표'!G7 | AC59: ='재무상태표'!G7
A60: 투자부동산 | X60: ='재무상태표'!G14 | Y60: ='재무상태표'!G14 | Z60: ='재무상태표'!G14 | AA60: ='재무상태표'!G14 | AB60: ='재무상태표'!G14 | AC60: ='재무상태표'!G14
A61: 지배자본 | X61: ='재무상태표'!G31 | Y61: ='재무상태표'!G31 | Z61: ='재무상태표'!G31 | AA61: ='재무상태표'!G31 | AB61: ='재무상태표'!G31 | AC61: ='재무상태표'!G31
A62: 부채 | X62: ='재무상태표'!G27 | Y62: ='재무상태표'!G27 | Z62: ='재무상태표'!G27 | AA62: ='재무상태표'!G27 | AB62: ='재무상태표'!G27 | AC62: ='재무상태표'!G27
A63: 부채비율 | X63: =IF(OR(X62="",X61=""),"",IFERROR(X62/X61,"")) | Y63: =IF(OR(Y62="",Y61=""),"",IFERROR(Y62/Y61,"")) | Z63: =IF(OR(Z62="",Z61=""),"",IFERROR(Z62/Z61,"")) | AA63: =IF(OR(AA62="",AA61=""),"",IFERROR(AA62/AA61,"")) | AB63: =IF(OR(AB62="",AB61=""),"",IFERROR(AB62/AB61,"")) | AC63: =IF(OR(AC62="",AC61=""),"",IFERROR(AC62/AC61,""))
A64: 자산가치 | B64: 현금+단기금융+투자부동산 | X64: =SUM(X58,X59,X60) | Y64: =SUM(Y58,Y59,Y60) | Z64: =SUM(Z58,Z59,Z60) | AA64: =SUM(AA58,AA59,AA60) | AB64: =SUM(AB58,AB59,AB60) | AC64: =SUM(AC58,AC59,AC60)
A65: 기업가치 산출
A66: 목표 시가총액 (P/E) | B66: 지배순이익 × Target P/E | Y66: =IF(OR(Y44="",Y53=""),"",IFERROR(Y44*Y53,"")) | Z66: =IF(OR(Z44="",Z53=""),"",IFERROR(Z44*Z53,"")) | AA66: =IF(OR(AA44="",AA53=""),"",IFERROR(AA44*AA53,"")) | AB66: =IF(OR(AB44="",AB53=""),"",IFERROR(AB44*AB53,"")) | AC66: =IF(OR(AC44="",AC53=""),"",IFERROR(AC44*AC53,""))
A67: 기업가치 | B67: 목표시총 + 자산가치 | Y67: =IF(OR(Y66=""),"",IFERROR(Y66+Y64,"")) | Z67: =IF(OR(Z66=""),"",IFERROR(Z66+Z64,"")) | AA67: =IF(OR(AA66=""),"",IFERROR(AA66+AA64,"")) | AB67: =IF(OR(AB66=""),"",IFERROR(AB66+AB64,"")) | AC67: =IF(OR(AC66=""),"",IFERROR(AC66+AC64,""))
A68: 현재 시가총액 | Y68: =$B$49 | Z68: =$B$49 | AA68: =$B$49 | AB68: =$B$49 | AC68: =$B$49
A69: 상승여력 | Y69: =IF(OR(Y67="",Y68=""),"",IFERROR(Y67/Y68-1,"")) | Z69: =IF(OR(Z67="",Z68=""),"",IFERROR(Z67/Z68-1,"")) | AA69: =IF(OR(AA67="",AA68=""),"",IFERROR(AA67/AA68-1,"")) | AB69: =IF(OR(AB67="",AB68=""),"",IFERROR(AB67/AB68-1,"")) | AC69: =IF(OR(AC67="",AC68=""),"",IFERROR(AC67/AC68-1,""))
A71: 출처
A72: 결산단신 XBRL(TDnet·JPX 보관소) — 쓴 문서는 '출처' 시트
A73: 분기 = 누계에서 앞 분기를 뺀 3개월 값
A74: 주가: 야후 파이낸스 일봉 2026.10.26
A76: 손익계산서 · 전 항목 | B76: 분기 = 3개월 단독
A77: 항목 | B77: 참고 | C77: 2025.1Q | D77: 2025.2Q | E77: 2025.3Q | F77: 2025.4Q | G77: 2026.1Q | H77: 2026.2Q | I77: 2026.3Q | J77: 2026.4Q | K77: 2027.1Q | L77: 2027.2Q | M77: 2027.3Q | N77: 2027.4Q | O77: 2018 | P77: 2019 | Q77: 2020 | R77: 2021 | S77: 2022 | T77: 2023 | U77: 2024 | V77: 2025 | W77: 2026 | X77: 2027 | Y77: 2028(MW) | Z77: 2029(MW) | AA77: 2030(MW) | AB77: 2031(MW) | AC77: 2032(MW)
A78: 매출액 | C78: 247223 | D78: 268327 | E78: 259640 | F78: 192098 | G78: 261076 | H78: 284224 | I78: 289305 | J78: 224540 | K78: 346621 | S78: -7198 | T78: 74556 | U78: 215233 | V78: 192098 | W78: 224540
A79: YoY | B79: 전년 같은 분기·전년 대비 | G79: =IF(OR(G78="",C78=""),"",IF(C78<=0,"",IFERROR(G78/C78-1,""))) | H79: =IF(OR(H78="",D78=""),"",IF(D78<=0,"",IFERROR(H78/D78-1,""))) | I79: =IF(OR(I78="",E78=""),"",IF(E78<=0,"",IFERROR(I78/E78-1,""))) | J79: =IF(OR(J78="",F78=""),"",IF(F78<=0,"",IFERROR(J78/F78-1,""))) | K79: =IF(OR(K78="",G78=""),"",IF(G78<=0,"",IFERROR(K78/G78-1,""))) | S79: =IF(OR(S78="",R78=""),"",IF(R78<=0,"",IFERROR(S78/R78-1,""))) | T79: =IF(OR(T78="",S78=""),"",IF(S78<=0,"",IFERROR(T78/S78-1,""))) | U79: =IF(OR(U78="",T78=""),"",IF(T78<=0,"",IFERROR(U78/T78-1,""))) | V79: =IF(OR(V78="",U78=""),"",IF(U78<=0,"",IFERROR(V78/U78-1,""))) | W79: =IF(OR(W78="",V78=""),"",IF(V78<=0,"",IFERROR(W78/V78-1,"")))
A80: 매출원가 | C80: 39831 | D80: 42467 | E80: 42282 | F80: 40202 | G80: 45412 | H80: 49010 | I80: 48769 | J80: 28253 | K80: 51866 | S80: 2048 | T80: 10573 | U80: 45309 | V80: 40202 | W80: 28253
A81: 매출총이익 | C81: 207391 | D81: 225861 | E81: 217357 | F81: 151896 | G81: 215664 | H81: 235214 | I81: 240535 | J81: 196287 | K81: 294755 | S81: -9246 | T81: 63984 | U81: 169924 | V81: 151896 | W81: 196287
A82: YoY | B82: 전년 같은 분기·전년 대비 | G82: =IF(OR(G81="",C81=""),"",IF(C81<=0,"",IFERROR(G81/C81-1,""))) | H82: =IF(OR(H81="",D81=""),"",IF(D81<=0,"",IFERROR(H81/D81-1,""))) | I82: =IF(OR(I81="",E81=""),"",IF(E81<=0,"",IFERROR(I81/E81-1,""))) | J82: =IF(OR(J81="",F81=""),"",IF(F81<=0,"",IFERROR(J81/F81-1,""))) | K82: =IF(OR(K81="",G81=""),"",IF(G81<=0,"",IFERROR(K81/G81-1,""))) | S82: =IF(OR(S81="",R81=""),"",IF(R81<=0,"",IFERROR(S81/R81-1,""))) | T82: =IF(OR(T81="",S81=""),"",IF(S81<=0,"",IFERROR(T81/S81-1,""))) | U82: =IF(OR(U81="",T81=""),"",IF(T81<=0,"",IFERROR(U81/T81-1,""))) | V82: =IF(OR(V81="",U81=""),"",IF(U81<=0,"",IFERROR(V81/U81-1,""))) | W82: =IF(OR(W81="",V81=""),"",IF(V81<=0,"",IFERROR(W81/V81-1,"")))
A83: 판매비와 관리비 | C83: 83986 | D83: 85301 | E83: 84288 | F83: 53916 | G83: 86363 | H83: 92335 | I83: 96334 | J83: 62893 | K83: 107679 | S83: 16406 | T83: 14970 | U83: 30525 | V83: 53916 | W83: 62893
A84: 영업이익 | C84: 123405 | D84: 140560 | E84: 133068 | F84: 97981 | G84: 129301 | H84: 142878 | I84: 144202 | J84: 133394 | K84: 187076 | S84: -25653 | T84: 49014 | U84: 139399 | V84: 97981 | W84: 133394
A85: OPM | B85: 영업이익 ÷ 매출 | C85: =IF(OR(C84="",C78=""),"",IF(C78<=0,"",IFERROR(C84/C78,""))) | D85: =IF(OR(D84="",D78=""),"",IF(D78<=0,"",IFERROR(D84/D78,""))) | E85: =IF(OR(E84="",E78=""),"",IF(E78<=0,"",IFERROR(E84/E78,""))) | F85: =IF(OR(F84="",F78=""),"",IF(F78<=0,"",IFERROR(F84/F78,""))) | G85: =IF(OR(G84="",G78=""),"",IF(G78<=0,"",IFERROR(G84/G78,""))) | H85: =IF(OR(H84="",H78=""),"",IF(H78<=0,"",IFERROR(H84/H78,""))) | I85: =IF(OR(I84="",I78=""),"",IF(I78<=0,"",IFERROR(I84/I78,""))) | J85: =IF(OR(J84="",J78=""),"",IF(J78<=0,"",IFERROR(J84/J78,""))) | K85: =IF(OR(K84="",K78=""),"",IF(K78<=0,"",IFERROR(K84/K78,""))) | S85: =IF(OR(S84="",S78=""),"",IF(S78<=0,"",IFERROR(S84/S78,""))) | T85: =IF(OR(T84="",T78=""),"",IF(T78<=0,"",IFERROR(T84/T78,""))) | U85: =IF(OR(U84="",U78=""),"",IF(U78<=0,"",IFERROR(U84/U78,""))) | V85: =IF(OR(V84="",V78=""),"",IF(V78<=0,"",IFERROR(V84/V78,""))) | W85: =IF(OR(W84="",W78=""),"",IF(W78<=0,"",IFERROR(W84/W78,"")))
A86: YoY | B86: 전년 같은 분기·전년 대비 | G86: =IF(OR(G84="",C84=""),"",IF(C84<=0,"",IFERROR(G84/C84-1,""))) | H86: =IF(OR(H84="",D84=""),"",IF(D84<=0,"",IFERROR(H84/D84-1,""))) | I86: =IF(OR(I84="",E84=""),"",IF(E84<=0,"",IFERROR(I84/E84-1,""))) | J86: =IF(OR(J84="",F84=""),"",IF(F84<=0,"",IFERROR(J84/F84-1,""))) | K86: =IF(OR(K84="",G84=""),"",IF(G84<=0,"",IFERROR(K84/G84-1,""))) | S86: =IF(OR(S84="",R84=""),"",IF(R84<=0,"",IFERROR(S84/R84-1,""))) | T86: =IF(OR(T84="",S84=""),"",IF(S84<=0,"",IFERROR(T84/S84-1,""))) | U86: =IF(OR(U84="",T84=""),"",IF(T84<=0,"",IFERROR(U84/T84-1,""))) | V86: =IF(OR(V84="",U84=""),"",IF(U84<=0,"",IFERROR(V84/U84-1,""))) | W86: =IF(OR(W84="",V84=""),"",IF(V84<=0,"",IFERROR(W84/V84-1,"")))
A87: 이자수익 | C87: 1677 | D87: 2228 | E87: 2176 | F87: -723 | G87: 3089 | H87: 3991 | I87: 3986 | J87: -2098 | K87: 6091 | S87: 342 | T87: -578 | U87: -1647 | V87: -723 | W87: -2098
A88: 지분법이익 | C88: 1012 | D88: 1455 | E88: 1453 | F88: 1451 | G88: 1121 | H88: 1776 | I88: 1869 | J88: 543 | K88: 1295 | S88: 794 | T88: 773 | U88: 1477 | V88: 1451 | W88: 543
A89: 외환차익 | C89: 5283 | D89: -5283 | E89: 2043 | F89: 10790 | G89: 0 | H89: 1644 | I89: 8512 | J89: -10156 | K89: 2243 | S89: 1173 | T89: 1579 | U89: -4158 | V89: 10790 | W89: -10156
A90: 잡이익 | C90: 111 | D90: 82 | E90: 1326 | F90: -114 | G90: 172 | H90: 1155 | I90: 106 | J90: 609 | K90: 168 | S90: 81 | T90: 185 | U90: 322 | V90: -114 | W90: 609
A91: 영업외수익 합계 | C91: 8084 | D91: -1518 | E91: 6998 | F91: 11405 | G91: 4383 | H91: 8566 | I91: 14473 | J91: -11102 | K91: 9798 | S91: 2391 | T91: 1957 | U91: -4005 | V91: 11405 | W91: -11102
A92: 외환차손 | C92: 0 | D92: 4705 | G92: 2070 | H92: -2070 | K92: 0
A93: 잡손실 | C93: 44 | D93: 64 | E93: 153 | F93: 427 | G93: 82 | H93: 47 | I93: 60 | J93: 675 | K93: 81 | S93: -8 | T93: 25 | U93: 125 | V93: 427 | W93: 675
A94: 영업외비용 합계 | C94: 44 | D94: 4770 | E94: -4553 | F94: 427 | G94: 2153 | H94: -2024 | I94: 60 | J94: 4896 | K94: 81 | S94: -8 | T94: 25 | U94: 125 | V94: 427 | W94: 4896
A95: 경상이익 | C95: 131444 | D95: 134273 | E95: 144619 | F95: 108959 | G95: 131532 | H95: 153468 | I95: 158614 | J95: 117396 | K95: 196793 | S95: -23254 | T95: 50946 | U95: 135270 | V95: 108959 | W95: 117396
A96: YoY | B96: 전년 같은 분기·전년 대비 | G96: =IF(OR(G95="",C95=""),"",IF(C95<=0,"",IFERROR(G95/C95-1,""))) | H96: =IF(OR(H95="",D95=""),"",IF(D95<=0,"",IFERROR(H95/D95-1,""))) | I96: =IF(OR(I95="",E95=""),"",IF(E95<=0,"",IFERROR(I95/E95-1,""))) | J96: =IF(OR(J95="",F95=""),"",IF(F95<=0,"",IFERROR(J95/F95-1,""))) | K96: =IF(OR(K95="",G95=""),"",IF(G95<=0,"",IFERROR(K95/G95-1,""))) | S96: =IF(OR(S95="",R95=""),"",IF(R95<=0,"",IFERROR(S95/R95-1,""))) | T96: =IF(OR(T95="",S95=""),"",IF(S95<=0,"",IFERROR(T95/S95-1,""))) | U96: =IF(OR(U95="",T95=""),"",IF(T95<=0,"",IFERROR(U95/T95-1,""))) | V96: =IF(OR(V95="",U95=""),"",IF(U95<=0,"",IFERROR(V95/U95-1,""))) | W96: =IF(OR(W95="",V95=""),"",IF(V95<=0,"",IFERROR(W95/V95-1,"")))
A97: 법인세차감전 순이익 | C97: 131444 | D97: 134273 | E97: 144619 | F97: 108959 | G97: 131532 | H97: 153468 | I97: 158614 | J97: 117396 | K97: 196793 | S97: -23254 | T97: 50946 | U97: 135270 | V97: 108959 | W97: 117396
A98: 법인세 등 | C98: 37909 | D98: 38088 | E98: 42574 | F98: 31082 | G98: 39415 | H98: 45625 | I98: 47406 | J98: 29907 | K98: 57660 | S98: -2138 | T98: 15609 | U98: 38733 | V98: 31082 | W98: 29907
A99: 순이익 | C99: 93534 | D99: 96186 | E99: 102045 | F99: 77877 | G99: 92116 | H99: 107843 | I99: 111208 | J99: 87489 | K99: 139133 | S99: -21116 | T99: 35338 | U99: 96537 | V99: 77877 | W99: 87489
A100: YoY | B100: 전년 같은 분기·전년 대비 | G100: =IF(OR(G99="",C99=""),"",IF(C99<=0,"",IFERROR(G99/C99-1,""))) | H100: =IF(OR(H99="",D99=""),"",IF(D99<=0,"",IFERROR(H99/D99-1,""))) | I100: =IF(OR(I99="",E99=""),"",IF(E99<=0,"",IFERROR(I99/E99-1,""))) | J100: =IF(OR(J99="",F99=""),"",IF(F99<=0,"",IFERROR(J99/F99-1,""))) | K100: =IF(OR(K99="",G99=""),"",IF(G99<=0,"",IFERROR(K99/G99-1,""))) | S100: =IF(OR(S99="",R99=""),"",IF(R99<=0,"",IFERROR(S99/R99-1,""))) | T100: =IF(OR(T99="",S99=""),"",IF(S99<=0,"",IFERROR(T99/S99-1,""))) | U100: =IF(OR(U99="",T99=""),"",IF(T99<=0,"",IFERROR(U99/T99-1,""))) | V100: =IF(OR(V99="",U99=""),"",IF(U99<=0,"",IFERROR(V99/U99-1,""))) | W100: =IF(OR(W99="",V99=""),"",IF(V99<=0,"",IFERROR(W99/V99-1,"")))
A101: 지배주주 순이익 | C101: 93534 | D101: 96186 | E101: 102045 | F101: 77877 | G101: 92116 | H101: 107843 | I101: 111208 | J101: 87489 | K101: 139133 | S101: -21116 | T101: 35338 | U101: 96537 | V101: 77877 | W101: 87489
A102: YoY | B102: 전년 같은 분기·전년 대비 | G102: =IF(OR(G101="",C101=""),"",IF(C101<=0,"",IFERROR(G101/C101-1,""))) | H102: =IF(OR(H101="",D101=""),"",IF(D101<=0,"",IFERROR(H101/D101-1,""))) | I102: =IF(OR(I101="",E101=""),"",IF(E101<=0,"",IFERROR(I101/E101-1,""))) | J102: =IF(OR(J101="",F101=""),"",IF(F101<=0,"",IFERROR(J101/F101-1,""))) | K102: =IF(OR(K101="",G101=""),"",IF(G101<=0,"",IFERROR(K101/G101-1,""))) | S102: =IF(OR(S101="",R101=""),"",IF(R101<=0,"",IFERROR(S101/R101-1,""))) | T102: =IF(OR(T101="",S101=""),"",IF(S101<=0,"",IFERROR(T101/S101-1,""))) | U102: =IF(OR(U101="",T101=""),"",IF(T101<=0,"",IFERROR(U101/T101-1,""))) | V102: =IF(OR(V101="",U101=""),"",IF(U101<=0,"",IFERROR(V101/U101-1,""))) | W102: =IF(OR(W101="",V101=""),"",IF(V101<=0,"",IFERROR(W101/V101-1,"")))
...

Sheet 재무상태표
A1: 6861 재무상태표
A2: 재무비율은 기말 잔액 기준 · 분기 손익은 최근 4분기 합산(TTM) | B2: (단위: 백만엔)
A3: 항목 | B3: 참고 | C3: 2026.2Q | D3: 2026.3Q | E3: 2026.4Q | F3: 2027.1Q | G3: 2027.2Q | H3: 2018 | I3: 2023 | J3: 2024 | K3: 2025 | L3: 2026
A4: 자산
A5: 유동자산 | C5: 1568423 | D5: 1741736 | E5: 1782006 | F5: 1979505 | G5: 1945636 | H5: 1023426 | I5: 1371399 | J5: 1357010 | K5: 1573043 | L5: 1782006
A6: 현금및현금성자산 | C6: 489078 | D6: 583276 | E6: 507115 | F6: 596976 | G6: 564751 | H6: 437675 | I6: 424998 | J6: 451518 | K6: 513402 | L6: 507115
A7: 단기금융상품 | C7: 675242 | D7: 734575 | E7: 826897 | F7: 896913 | G7: 861843 | H7: 370055 | I7: 556796 | J7: 520290 | K7: 660659 | L7: 826897
A8: 매출채권 | C8: 305063 | D8: 324817 | E8: 342170 | F8: 379590 | G8: 397626 | H8: 160276 | I8: 283733 | J8: 285099 | K8: 302441 | L8: 342170
A9: 재고자산 | C9: 84903 | D9: 83805 | E9: 87875 | F9: 85273 | G9: 101073 | H9: 34847 | I9: 92207 | J9: 87454 | K9: 82340 | L9: 87875
A10: 기타유동자산 | B10: 총계 − 위 항목 | C10: =IF(OR(C5=""),"",IFERROR(C5-SUM(C6,C7,C8,C9),"")) | D10: =IF(OR(D5=""),"",IFERROR(D5-SUM(D6,D7,D8,D9),"")) | E10: =IF(OR(E5=""),"",IFERROR(E5-SUM(E6,E7,E8,E9),"")) | F10: =IF(OR(F5=""),"",IFERROR(F5-SUM(F6,F7,F8,F9),"")) | G10: =IF(OR(G5=""),"",IFERROR(G5-SUM(G6,G7,G8,G9),"")) | H10: =IF(OR(H5=""),"",IFERROR(H5-SUM(H6,H7,H8,H9),"")) | I10: =IF(OR(I5=""),"",IFERROR(I5-SUM(I6,I7,I8,I9),"")) | J10: =IF(OR(J5=""),"",IFERROR(J5-SUM(J6,J7,J8,J9),"")) | ... L10: =IF(OR(L5=""),"",IFERROR(L5-SUM(L6,L7,L8,L9),""))
A11: 비유동자산 | C11: 1721430 | D11: 1705655 | E11: 1696638 | F11: 1691149 | G11: 1779255 | H11: 462796 | I11: 1146329 | J11: 1462367 | K11: 1574665 | L11: 1696638
A12: 유형자산 | C12: 81515 | D12: 82187 | E12: 84511 | F12: 94718 | G12: 98828 | H12: 21426 | I12: 31242 | J12: 73819 | K12: 77403 | L12: 84511
A13: 무형자산 | C13: 36111 | D13: 33535 | E13: 31360 | F13: 29181 | G13: 26932 | H13: 5204 | I13: 3538 | J13: 4568 | K13: 6311 | L13: 31360
A14: 투자부동산
A15: 기타비유동자산 | B15: 총계 − 위 항목 | C15: =IF(OR(C11=""),"",IFERROR(C11-SUM(C12,C13,C14),"")) | D15: =IF(OR(D11=""),"",IFERROR(D11-SUM(D12,D13,D14),"")) | E15: =IF(OR(E11=""),"",IFERROR(E11-SUM(E12,E13,E14),"")) | F15: =IF(OR(F11=""),"",IFERROR(F11-SUM(F12,F13,F14),"")) | G15: =IF(OR(G11=""),"",IFERROR(G11-SUM(G12,G13,G14),"")) | H15: =IF(OR(H11=""),"",IFERROR(H11-SUM(H12,H13,H14),"")) | I15: =IF(OR(I11=""),"",IFERROR(I11-SUM(I12,I13,I14),"")) | J15: =IF(OR(J11=""),"",IFERROR(J11-SUM(J12,J13,J14),"")) | ... L15: =IF(OR(L11=""),"",IFERROR(L11-SUM(L12,L13,L14),""))
A16: 자산총계 | C16: 3289853 | D16: 3447391 | E16: 3478645 | F16: 3670655 | G16: 3724891 | H16: 1486222 | I16: 2517729 | J16: 2819378 | K16: 3147709 | L16: 3478645
A17: 부채
A18: 유동부채 | C18: 114986 | D18: 160696 | E18: 131496 | F18: 187831 | G18: 163958 | H18: 97558 | I18: 116838 | J18: 107328 | K18: 124028 | L18: 131496
A19: 매입채무 | C19: 15760 | D19: 15091 | E19: 16653 | F19: 10890 | G19: 23600 | H19: 10645 | I19: 21225 | J19: 19208 | K19: 16095 | L19: 16653
A20: 단기차입금
A21: 유동성장기부채
A22: 기타유동부채 | B22: 총계 − 위 항목 | C22: =IF(OR(C18=""),"",IFERROR(C18-SUM(C19,C20,C21),"")) | D22: =IF(OR(D18=""),"",IFERROR(D18-SUM(D19,D20,D21),"")) | E22: =IF(OR(E18=""),"",IFERROR(E18-SUM(E19,E20,E21),"")) | F22: =IF(OR(F18=""),"",IFERROR(F18-SUM(F19,F20,F21),"")) | G22: =IF(OR(G18=""),"",IFERROR(G18-SUM(G19,G20,G21),"")) | H22: =IF(OR(H18=""),"",IFERROR(H18-SUM(H19,H20,H21),"")) | I22: =IF(OR(I18=""),"",IFERROR(I18-SUM(I19,I20,I21),"")) | J22: =IF(OR(J18=""),"",IFERROR(J18-SUM(J19,J20,J21),"")) | ... L22: =IF(OR(L18=""),"",IFERROR(L18-SUM(L19,L20,L21),""))
A23: 비유동부채 | C23: 12015 | D23: 11099 | E23: 11756 | F23: 11351 | G23: 12192 | H23: 7606 | I23: 4874 | J23: 11088 | K23: 12705 | L23: 11756
A24: 장기차입금
A25: 사채
A26: 기타비유동부채 | B26: 총계 − 위 항목 | C26: =IF(OR(C23=""),"",IFERROR(C23-SUM(C24,C25),"")) | D26: =IF(OR(D23=""),"",IFERROR(D23-SUM(D24,D25),"")) | E26: =IF(OR(E23=""),"",IFERROR(E23-SUM(E24,E25),"")) | F26: =IF(OR(F23=""),"",IFERROR(F23-SUM(F24,F25),"")) | G26: =IF(OR(G23=""),"",IFERROR(G23-SUM(G24,G25),"")) | H26: =IF(OR(H23=""),"",IFERROR(H23-SUM(H24,H25),"")) | I26: =IF(OR(I23=""),"",IFERROR(I23-SUM(I24,I25),"")) | J26: =IF(OR(J23=""),"",IFERROR(J23-SUM(J24,J25),"")) | ... L26: =IF(OR(L23=""),"",IFERROR(L23-SUM(L24,L25),""))
A27: 부채총계 | C27: 127001 | D27: 171795 | E27: 143253 | F27: 199183 | G27: 176150 | H27: 105164 | I27: 121713 | J27: 118416 | K27: 136733 | L27: 143253
A28: 총차입금 | B28: 단기+유동성장기+장기+사채 | C28: =SUM(C20,C21,C24,C25) | D28: =SUM(D20,D21,D24,D25) | E28: =SUM(E20,E21,E24,E25) | F28: =SUM(F20,F21,F24,F25) | G28: =SUM(G20,G21,G24,G25) | H28: =SUM(H20,H21,H24,H25) | I28: =SUM(I20,I21,I24,I25) | J28: =SUM(J20,J21,J24,J25) | ... L28: =SUM(L20,L21,L24,L25)
A29: 순차입금 | B29: 음수 = 순현금 | C29: =C28-C6-N(C7) | D29: =D28-D6-N(D7) | E29: =E28-E6-N(E7) | F29: =F28-F6-N(F7) | G29: =G28-G6-N(G7) | H29: =H28-H6-N(H7) | I29: =I28-I6-N(I7) | J29: =J28-J6-N(J7) | ... L29: =L28-L6-N(L7)
A30: 자본
A31: 지배주주지분 | C31: 3162851 | D31: 3275596 | E31: 3335392 | F31: 3471472 | G31: 3548740 | H31: 1381057 | I31: 2396016 | J31: 2700961 | K31: 3010975 | L31: 3335392
A32: 자본금 | C32: 30637 | D32: 30637 | E32: 30637 | F32: 30637 | G32: 30637 | H32: 30637 | I32: 30637 | J32: 30637 | K32: 30637 | L32: 30637
A33: 이익잉여금 | C33: 3070209 | D33: 3178052 | E33: 3222567 | F33: 3356584 | G33: 3429023 | H33: 1316311 | I33: 2308874 | J33: 2597483 | K33: 2913644 | L33: 3222567
A34: 비지배지분
A35: 자본총계 | C35: 3162851 | D35: 3275596 | E35: 3335392 | F35: 3471472 | G35: 3548740 | H35: 1381057 | I35: 2396016 | J35: 2700961 | K35: 3010975 | L35: 3335392
A36: 현금흐름 요약 | B36: 분기 = TTM (있을 때만)
A37: 영업활동현금흐름 | E37: 409522 | I37: 271476 | J37: 302628 | K37: 387916 | L37: 409522
A38: CAPEX (유·무형 취득) | B38: 양수로 입력 | E38: 14342 | I38: 6162 | J38: 39345 | K38: 12492 | L38: 14342
A39: FCF | C39: =IF(OR(C37="",C38=""),"",IFERROR(C37-C38,"")) | D39: =IF(OR(D37="",D38=""),"",IFERROR(D37-D38,"")) | E39: =IF(OR(E37="",E38=""),"",IFERROR(E37-E38,"")) | F39: =IF(OR(F37="",F38=""),"",IFERROR(F37-F38,"")) | G39: =IF(OR(G37="",G38=""),"",IFERROR(G37-G38,"")) | H39: =IF(OR(H37="",H38=""),"",IFERROR(H37-H38,"")) | I39: =IF(OR(I37="",I38=""),"",IFERROR(I37-I38,"")) | J39: =IF(OR(J37="",J38=""),"",IFERROR(J37-J38,"")) | ... L39: =IF(OR(L37="",L38=""),"",IFERROR(L37-L38,""))
A40: 배당금 지급 | B40: 양수로 입력 | E40: 78820 | I40: 48505 | J40: 60631 | K40: 72757 | L40: 78820
A41: 주요 재무 비율 | B41: 기준 (빨간 글씨 = 미달)
A42: 안정성
A43: 부채비율 | B43: 100%↓ | C43: =IF(OR(C27="",C35=""),"",IFERROR(C27/C35,"")) | D43: =IF(OR(D27="",D35=""),"",IFERROR(D27/D35,"")) | E43: =IF(OR(E27="",E35=""),"",IFERROR(E27/E35,"")) | F43: =IF(OR(F27="",F35=""),"",IFERROR(F27/F35,"")) | G43: =IF(OR(G27="",G35=""),"",IFERROR(G27/G35,"")) | H43: =IF(OR(H27="",H35=""),"",IFERROR(H27/H35,"")) | I43: =IF(OR(I27="",I35=""),"",IFERROR(I27/I35,"")) | J43: =IF(OR(J27="",J35=""),"",IFERROR(J27/J35,"")) | ... L43: =IF(OR(L27="",L35=""),"",IFERROR(L27/L35,""))
A44: 순차입금비율 | B44: 0%↓ 순현금 | C44: =IF(OR(C29="",C35=""),"",IFERROR(C29/C35,"")) | D44: =IF(OR(D29="",D35=""),"",IFERROR(D29/D35,"")) | E44: =IF(OR(E29="",E35=""),"",IFERROR(E29/E35,"")) | F44: =IF(OR(F29="",F35=""),"",IFERROR(F29/F35,"")) | G44: =IF(OR(G29="",G35=""),"",IFERROR(G29/G35,"")) | H44: =IF(OR(H29="",H35=""),"",IFERROR(H29/H35,"")) | I44: =IF(OR(I29="",I35=""),"",IFERROR(I29/I35,"")) | J44: =IF(OR(J29="",J35=""),"",IFERROR(J29/J35,"")) | ... L44: =IF(OR(L29="",L35=""),"",IFERROR(L29/L35,""))
A45: 자기자본비율 | B45: 50%↑ | C45: =IF(OR(C35="",C16=""),"",IFERROR(C35/C16,"")) | D45: =IF(OR(D35="",D16=""),"",IFERROR(D35/D16,"")) | E45: =IF(OR(E35="",E16=""),"",IFERROR(E35/E16,"")) | F45: =IF(OR(F35="",F16=""),"",IFERROR(F35/F16,"")) | G45: =IF(OR(G35="",G16=""),"",IFERROR(G35/G16,"")) | H45: =IF(OR(H35="",H16=""),"",IFERROR(H35/H16,"")) | I45: =IF(OR(I35="",I16=""),"",IFERROR(I35/I16,"")) | J45: =IF(OR(J35="",J16=""),"",IFERROR(J35/J16,"")) | ... L45: =IF(OR(L35="",L16=""),"",IFERROR(L35/L16,""))
A46: 유동비율 | B46: 150%↑ | C46: =IF(OR(C5="",C18=""),"",IFERROR(C5/C18,"")) | D46: =IF(OR(D5="",D18=""),"",IFERROR(D5/D18,"")) | E46: =IF(OR(E5="",E18=""),"",IFERROR(E5/E18,"")) | F46: =IF(OR(F5="",F18=""),"",IFERROR(F5/F18,"")) | G46: =IF(OR(G5="",G18=""),"",IFERROR(G5/G18,"")) | H46: =IF(OR(H5="",H18=""),"",IFERROR(H5/H18,"")) | I46: =IF(OR(I5="",I18=""),"",IFERROR(I5/I18,"")) | J46: =IF(OR(J5="",J18=""),"",IFERROR(J5/J18,"")) | ... L46: =IF(OR(L5="",L18=""),"",IFERROR(L5/L18,""))
A47: 당좌비율 | B47: 100%↑ | C47: =IF(OR(C5="",C18=""),"",IFERROR((C5-N(C9))/C18,"")) | D47: =IF(OR(D5="",D18=""),"",IFERROR((D5-N(D9))/D18,"")) | E47: =IF(OR(E5="",E18=""),"",IFERROR((E5-N(E9))/E18,"")) | F47: =IF(OR(F5="",F18=""),"",IFERROR((F5-N(F9))/F18,"")) | G47: =IF(OR(G5="",G18=""),"",IFERROR((G5-N(G9))/G18,"")) | H47: =IF(OR(H5="",H18=""),"",IFERROR((H5-N(H9))/H18,"")) | I47: =IF(OR(I5="",I18=""),"",IFERROR((I5-N(I9))/I18,"")) | J47: =IF(OR(J5="",J18=""),"",IFERROR((J5-N(J9))/J18,"")) | ... L47: =IF(OR(L5="",L18=""),"",IFERROR((L5-N(L9))/L18,""))
A48: 이자보상배율 | B48: 5x↑ (금융원가 기준) | C48: =IFERROR((IF(COUNT('연간'!E16:H16)<4,"",SUM('연간'!E16:H16)))/(IF(COUNT('연간'!E38:H38)<4,"",SUM('연간'!E38:H38))),"") | D48: =IFERROR((IF(COUNT('연간'!F16:I16)<4,"",SUM('연간'!F16:I16)))/(IF(COUNT('연간'!F38:I38)<4,"",SUM('연간'!F38:I38))),"") | E48: =IFERROR((IF(COUNT('연간'!G16:J16)<4,"",SUM('연간'!G16:J16)))/(IF(COUNT('연간'!G38:J38)<4,"",SUM('연간'!G38:J38))),"") | F48: =IFERROR((IF(COUNT('연간'!H16:K16)<4,"",SUM('연간'!H16:K16)))/(IF(COUNT('연간'!H38:K38)<4,"",SUM('연간'!H38:K38))),"") | G48: =IFERROR((IF(COUNT('연간'!I16:L16)<4,"",SUM('연간'!I16:L16)))/(IF(COUNT('연간'!I38:L38)<4,"",SUM('연간'!I38:L38))),"") | H48: =IFERROR(('연간'!O16)/('연간'!O38),"") | I48: =IFERROR(('연간'!T16)/('연간'!T38),"") | J48: =IFERROR(('연간'!U16)/('연간'!U38),"") | K48: =IFERROR(('연간'!V16)/('연간'!V38),"") | L48: =IFERROR(('연간'!W16)/('연간'!W38),"")
A49: 차입금 상환연수 | B49: 4년↓ (버핏) | C49: =IFERROR(IF((IF(COUNT('연간'!E44:H44)<4,"",SUM('연간'!E44:H44)))<=0,"적자",C28/(IF(COUNT('연간'!E44:H44)<4,"",SUM('연간'!E44:H44)))),"") | D49: =IFERROR(IF((IF(COUNT('연간'!F44:I44)<4,"",SUM('연간'!F44:I44)))<=0,"적자",D28/(IF(COUNT('연간'!F44:I44)<4,"",SUM('연간'!F44:I44)))),"") | E49: =IFERROR(IF((IF(COUNT('연간'!G44:J44)<4,"",SUM('연간'!G44:J44)))<=0,"적자",E28/(IF(COUNT('연간'!G44:J44)<4,"",SUM('연간'!G44:J44)))),"") | F49: =IFERROR(IF((IF(COUNT('연간'!H44:K44)<4,"",SUM('연간'!H44:K44)))<=0,"적자",F28/(IF(COUNT('연간'!H44:K44)<4,"",SUM('연간'!H44:K44)))),"") | G49: =IFERROR(IF((IF(COUNT('연간'!I44:L44)<4,"",SUM('연간'!I44:L44)))<=0,"적자",G28/(IF(COUNT('연간'!I44:L44)<4,"",SUM('연간'!I44:L44)))),"") | H49: =IFERROR(IF(('연간'!O44)<=0,"적자",H28/('연간'!O44)),"") | I49: =IFERROR(IF(('연간'!T44)<=0,"적자",I28/('연간'!T44)),"") | J49: =IFERROR(IF(('연간'!U44)<=0,"적자",J28/('연간'!U44)),"") | K49: =IFERROR(IF(('연간'!V44)<=0,"적자",K28/('연간'!V44)),"") | L49: =IFERROR(IF(('연간'!W44)<=0,"적자",L28/('연간'!W44)),"")
A50: 수익성
A51: ROE | B51: 15%↑ (버핏) | C51: =IFERROR((IF(COUNT('연간'!E44:H44)<4,"",SUM('연간'!E44:H44)))/C31,"") | D51: =IFERROR((IF(COUNT('연간'!F44:I44)<4,"",SUM('연간'!F44:I44)))/D31,"") | E51: =IFERROR((IF(COUNT('연간'!G44:J44)<4,"",SUM('연간'!G44:J44)))/E31,"") | F51: =IFERROR((IF(COUNT('연간'!H44:K44)<4,"",SUM('연간'!H44:K44)))/F31,"") | G51: =IFERROR((IF(COUNT('연간'!I44:L44)<4,"",SUM('연간'!I44:L44)))/G31,"") | H51: =IFERROR(('연간'!O44)/H31,"") | I51: =IFERROR(('연간'!T44)/I31,"") | J51: =IFERROR(('연간'!U44)/J31,"") | K51: =IFERROR(('연간'!V44)/K31,"") | L51: =IFERROR(('연간'!W44)/L31,"")
A52: ROA | B52: 5%↑ | C52: =IFERROR((IF(COUNT('연간'!E43:H43)<4,"",SUM('연간'!E43:H43)))/C16,"") | D52: =IFERROR((IF(COUNT('연간'!F43:I43)<4,"",SUM('연간'!F43:I43)))/D16,"") | E52: =IFERROR((IF(COUNT('연간'!G43:J43)<4,"",SUM('연간'!G43:J43)))/E16,"") | F52: =IFERROR((IF(COUNT('연간'!H43:K43)<4,"",SUM('연간'!H43:K43)))/F16,"") | G52: =IFERROR((IF(COUNT('연간'!I43:L43)<4,"",SUM('연간'!I43:L43)))/G16,"") | H52: =IFERROR(('연간'!O43)/H16,"") | I52: =IFERROR(('연간'!T43)/I16,"") | J52: =IFERROR(('연간'!U43)/J16,"") | K52: =IFERROR(('연간'!V43)/K16,"") | L52: =IFERROR(('연간'!W43)/L16,"")
A53: ROIC | B53: 10%↑ (세후영업이익 기준) | C53: =IFERROR((IF(COUNT('연간'!E16:H16)<4,"",SUM('연간'!E16:H16)))*(1-0.3)/(C35+C29),"") | D53: =IFERROR((IF(COUNT('연간'!F16:I16)<4,"",SUM('연간'!F16:I16)))*(1-0.3)/(D35+D29),"") | E53: =IFERROR((IF(COUNT('연간'!G16:J16)<4,"",SUM('연간'!G16:J16)))*(1-0.3)/(E35+E29),"") | F53: =IFERROR((IF(COUNT('연간'!H16:K16)<4,"",SUM('연간'!H16:K16)))*(1-0.3)/(F35+F29),"") | G53: =IFERROR((IF(COUNT('연간'!I16:L16)<4,"",SUM('연간'!I16:L16)))*(1-0.3)/(G35+G29),"") | H53: =IFERROR(('연간'!O16)*(1-0.3)/(H35+H29),"") | I53: =IFERROR(('연간'!T16)*(1-0.3)/(I35+I29),"") | J53: =IFERROR(('연간'!U16)*(1-0.3)/(J35+J29),"") | K53: =IFERROR(('연간'!V16)*(1-0.3)/(K35+K29),"") | L53: =IFERROR(('연간'!W16)*(1-0.3)/(L35+L29),"")
A54: 매출총이익률 (GPM) | B54: 40%↑ (해자 신호) | C54: =IFERROR((IF(COUNT('연간'!E12:H12)<4,"",SUM('연간'!E12:H12)))/(IF(COUNT('연간'!E4:H4)<4,"",SUM('연간'!E4:H4))),"") | D54: =IFERROR((IF(COUNT('연간'!F12:I12)<4,"",SUM('연간'!F12:I12)))/(IF(COUNT('연간'!F4:I4)<4,"",SUM('연간'!F4:I4))),"") | E54: =IFERROR((IF(COUNT('연간'!G12:J12)<4,"",SUM('연간'!G12:J12)))/(IF(COUNT('연간'!G4:J4)<4,"",SUM('연간'!G4:J4))),"") | F54: =IFERROR((IF(COUNT('연간'!H12:K12)<4,"",SUM('연간'!H12:K12)))/(IF(COUNT('연간'!H4:K4)<4,"",SUM('연간'!H4:K4))),"") | G54: =IFERROR((IF(COUNT('연간'!I12:L12)<4,"",SUM('연간'!I12:L12)))/(IF(COUNT('연간'!I4:L4)<4,"",SUM('연간'!I4:L4))),"") | H54: =IFERROR(('연간'!O12)/('연간'!O4),"") | I54: =IFERROR(('연간'!T12)/('연간'!T4),"") | J54: =IFERROR(('연간'!U12)/('연간'!U4),"") | K54: =IFERROR(('연간'!V12)/('연간'!V4),"") | L54: =IFERROR(('연간'!W12)/('연간'!W4),"")
A55: 영업이익률 (OPM) | B55: 15%↑ | C55: =IFERROR((IF(COUNT('연간'!E16:H16)<4,"",SUM('연간'!E16:H16)))/(IF(COUNT('연간'!E4:H4)<4,"",SUM('연간'!E4:H4))),"") | D55: =IFERROR((IF(COUNT('연간'!F16:I16)<4,"",SUM('연간'!F16:I16)))/(IF(COUNT('연간'!F4:I4)<4,"",SUM('연간'!F4:I4))),"") | E55: =IFERROR((IF(COUNT('연간'!G16:J16)<4,"",SUM('연간'!G16:J16)))/(IF(COUNT('연간'!G4:J4)<4,"",SUM('연간'!G4:J4))),"") | F55: =IFERROR((IF(COUNT('연간'!H16:K16)<4,"",SUM('연간'!H16:K16)))/(IF(COUNT('연간'!H4:K4)<4,"",SUM('연간'!H4:K4))),"") | G55: =IFERROR((IF(COUNT('연간'!I16:L16)<4,"",SUM('연간'!I16:L16)))/(IF(COUNT('연간'!I4:L4)<4,"",SUM('연간'!I4:L4))),"") | H55: =IFERROR(('연간'!O16)/('연간'!O4),"") | I55: =IFERROR(('연간'!T16)/('연간'!T4),"") | J55: =IFERROR(('연간'!U16)/('연간'!U4),"") | K55: =IFERROR(('연간'!V16)/('연간'!V4),"") | L55: =IFERROR(('연간'!W16)/('연간'!W4),"")
A56: 순이익률 | B56: 10%↑ | C56: =IFERROR((IF(COUNT('연간'!E43:H43)<4,"",SUM('연간'!E43:H43)))/(IF(COUNT('연간'!E4:H4)<4,"",SUM('연간'!E4:H4))),"") | D56: =IFERROR((IF(COUNT('연간'!F43:I43)<4,"",SUM('연간'!F43:I43)))/(IF(COUNT('연간'!F4:I4)<4,"",SUM('연간'!F4:I4))),"") | E56: =IFERROR((IF(COUNT('연간'!G43:J43)<4,"",SUM('연간'!G43:J43)))/(IF(COUNT('연간'!G4:J4)<4,"",SUM('연간'!G4:J4))),"") | F56: =IFERROR((IF(COUNT('연간'!H43:K43)<4,"",SUM('연간'!H43:K43)))/(IF(COUNT('연간'!H4:K4)<4,"",SUM('연간'!H4:K4))),"") | G56: =IFERROR((IF(COUNT('연간'!I43:L43)<4,"",SUM('연간'!I43:L43)))/(IF(COUNT('연간'!I4:L4)<4,"",SUM('연간'!I4:L4))),"") | H56: =IFERROR(('연간'!O43)/('연간'!O4),"") | I56: =IFERROR(('연간'!T43)/('연간'!T4),"") | J56: =IFERROR(('연간'!U43)/('연간'!U4),"") | K56: =IFERROR(('연간'!V43)/('연간'!V4),"") | L56: =IFERROR(('연간'!W43)/('연간'!W4),"")
A57: 효율성 (회전율)
A58: 총자산회전율 | B58: 높을수록↑ | C58: =IFERROR((IF(COUNT('연간'!E4:H4)<4,"",SUM('연간'!E4:H4)))/C16,"") | D58: =IFERROR((IF(COUNT('연간'!F4:I4)<4,"",SUM('연간'!F4:I4)))/D16,"") | E58: =IFERROR((IF(COUNT('연간'!G4:J4)<4,"",SUM('연간'!G4:J4)))/E16,"") | F58: =IFERROR((IF(COUNT('연간'!H4:K4)<4,"",SUM('연간'!H4:K4)))/F16,"") | G58: =IFERROR((IF(COUNT('연간'!I4:L4)<4,"",SUM('연간'!I4:L4)))/G16,"") | H58: =IFERROR(('연간'!O4)/H16,"") | I58: =IFERROR(('연간'!T4)/I16,"") | J58: =IFERROR(('연간'!U4)/J16,"") | K58: =IFERROR(('연간'!V4)/K16,"") | L58: =IFERROR(('연간'!W4)/L16,"")
A59: 매출채권회전일수 | B59: 짧을수록↑ | C59: =IFERROR(C8/(IF(COUNT('연간'!E4:H4)<4,"",SUM('연간'!E4:H4)))*365,"") | D59: =IFERROR(D8/(IF(COUNT('연간'!F4:I4)<4,"",SUM('연간'!F4:I4)))*365,"") | E59: =IFERROR(E8/(IF(COUNT('연간'!G4:J4)<4,"",SUM('연간'!G4:J4)))*365,"") | F59: =IFERROR(F8/(IF(COUNT('연간'!H4:K4)<4,"",SUM('연간'!H4:K4)))*365,"") | G59: =IFERROR(G8/(IF(COUNT('연간'!I4:L4)<4,"",SUM('연간'!I4:L4)))*365,"") | H59: =IFERROR(H8/('연간'!O4)*365,"") | I59: =IFERROR(I8/('연간'!T4)*365,"") | J59: =IFERROR(J8/('연간'!U4)*365,"") | K59: =IFERROR(K8/('연간'!V4)*365,"") | L59: =IFERROR(L8/('연간'!W4)*365,"")
A60: 재고자산회전일수 | B60: 짧을수록↑ | C60: =IFERROR(C9/(IF(COUNT('연간'!E11:H11)<4,"",SUM('연간'!E11:H11)))*365,"") | D60: =IFERROR(D9/(IF(COUNT('연간'!F11:I11)<4,"",SUM('연간'!F11:I11)))*365,"") | E60: =IFERROR(E9/(IF(COUNT('연간'!G11:J11)<4,"",SUM('연간'!G11:J11)))*365,"") | F60: =IFERROR(F9/(IF(COUNT('연간'!H11:K11)<4,"",SUM('연간'!H11:K11)))*365,"") | G60: =IFERROR(G9/(IF(COUNT('연간'!I11:L11)<4,"",SUM('연간'!I11:L11)))*365,"") | H60: =IFERROR(H9/('연간'!O11)*365,"") | I60: =IFERROR(I9/('연간'!T11)*365,"") | J60: =IFERROR(J9/('연간'!U11)*365,"") | K60: =IFERROR(K9/('연간'!V11)*365,"") | L60: =IFERROR(L9/('연간'!W11)*365,"")
A61: 매입채무회전일수 | B61: 길수록 유리 | C61: =IFERROR(C19/(IF(COUNT('연간'!E11:H11)<4,"",SUM('연간'!E11:H11)))*365,"") | D61: =IFERROR(D19/(IF(COUNT('연간'!F11:I11)<4,"",SUM('연간'!F11:I11)))*365,"") | E61: =IFERROR(E19/(IF(COUNT('연간'!G11:J11)<4,"",SUM('연간'!G11:J11)))*365,"") | F61: =IFERROR(F19/(IF(COUNT('연간'!H11:K11)<4,"",SUM('연간'!H11:K11)))*365,"") | G61: =IFERROR(G19/(IF(COUNT('연간'!I11:L11)<4,"",SUM('연간'!I11:L11)))*365,"") | H61: =IFERROR(H19/('연간'!O11)*365,"") | I61: =IFERROR(I19/('연간'!T11)*365,"") | J61: =IFERROR(J19/('연간'!U11)*365,"") | K61: =IFERROR(K19/('연간'!V11)*365,"") | L61: =IFERROR(L19/('연간'!W11)*365,"")
A62: 현금전환주기 (CCC) | B62: 짧을수록↑ | C62: =IF(OR(C59="",C60="",C61=""),"",IFERROR(C59+C60-C61,"")) | D62: =IF(OR(D59="",D60="",D61=""),"",IFERROR(D59+D60-D61,"")) | E62: =IF(OR(E59="",E60="",E61=""),"",IFERROR(E59+E60-E61,"")) | F62: =IF(OR(F59="",F60="",F61=""),"",IFERROR(F59+F60-F61,"")) | G62: =IF(OR(G59="",G60="",G61=""),"",IFERROR(G59+G60-G61,"")) | H62: =IF(OR(H59="",H60="",H61=""),"",IFERROR(H59+H60-H61,"")) | I62: =IF(OR(I59="",I60="",I61=""),"",IFERROR(I59+I60-I61,"")) | J62: =IF(OR(J59="",J60="",J61=""),"",IFERROR(J59+J60-J61,"")) | ... L62: =IF(OR(L59="",L60="",L61=""),"",IFERROR(L59+L60-L61,""))
A63: 현금흐름
A64: 영업현금흐름 / 순이익 | B64: 1x↑ (이익의 질) | C64: =IF(C37="","",IFERROR(C37/(IF(COUNT('연간'!E43:H43)<4,"",SUM('연간'!E43:H43))),"")) | D64: =IF(D37="","",IFERROR(D37/(IF(COUNT('연간'!F43:I43)<4,"",SUM('연간'!F43:I43))),"")) | E64: =IF(E37="","",IFERROR(E37/(IF(COUNT('연간'!G43:J43)<4,"",SUM('연간'!G43:J43))),"")) | F64: =IF(F37="","",IFERROR(F37/(IF(COUNT('연간'!H43:K43)<4,"",SUM('연간'!H43:K43))),"")) | G64: =IF(G37="","",IFERROR(G37/(IF(COUNT('연간'!I43:L43)<4,"",SUM('연간'!I43:L43))),"")) | H64: =IF(H37="","",IFERROR(H37/('연간'!O43),"")) | I64: =IF(I37="","",IFERROR(I37/('연간'!T43),"")) | J64: =IF(J37="","",IFERROR(J37/('연간'!U43),"")) | K64: =IF(K37="","",IFERROR(K37/('연간'!V43),"")) | L64: =IF(L37="","",IFERROR(L37/('연간'!W43),""))
A65: FCF 마진 | B65: 5%↑ | C65: =IF(C39="","",IFERROR(C39/(IF(COUNT('연간'!E4:H4)<4,"",SUM('연간'!E4:H4))),"")) | D65: =IF(D39="","",IFERROR(D39/(IF(COUNT('연간'!F4:I4)<4,"",SUM('연간'!F4:I4))),"")) | E65: =IF(E39="","",IFERROR(E39/(IF(COUNT('연간'!G4:J4)<4,"",SUM('연간'!G4:J4))),"")) | F65: =IF(F39="","",IFERROR(F39/(IF(COUNT('연간'!H4:K4)<4,"",SUM('연간'!H4:K4))),"")) | G65: =IF(G39="","",IFERROR(G39/(IF(COUNT('연간'!I4:L4)<4,"",SUM('연간'!I4:L4))),"")) | H65: =IF(H39="","",IFERROR(H39/('연간'!O4),"")) | I65: =IF(I39="","",IFERROR(I39/('연간'!T4),"")) | J65: =IF(J39="","",IFERROR(J39/('연간'!U4),"")) | K65: =IF(K39="","",IFERROR(K39/('연간'!V4),"")) | L65: =IF(L39="","",IFERROR(L39/('연간'!W4),""))
A66: CAPEX / 매출 | B66: 낮을수록↑ (자본 가벼움) | C66: =IF(C38="","",IFERROR(C38/(IF(COUNT('연간'!E4:H4)<4,"",SUM('연간'!E4:H4))),"")) | D66: =IF(D38="","",IFERROR(D38/(IF(COUNT('연간'!F4:I4)<4,"",SUM('연간'!F4:I4))),"")) | E66: =IF(E38="","",IFERROR(E38/(IF(COUNT('연간'!G4:J4)<4,"",SUM('연간'!G4:J4))),"")) | F66: =IF(F38="","",IFERROR(F38/(IF(COUNT('연간'!H4:K4)<4,"",SUM('연간'!H4:K4))),"")) | G66: =IF(G38="","",IFERROR(G38/(IF(COUNT('연간'!I4:L4)<4,"",SUM('연간'!I4:L4))),"")) | H66: =IF(H38="","",IFERROR(H38/('연간'!O4),"")) | I66: =IF(I38="","",IFERROR(I38/('연간'!T4),"")) | J66: =IF(J38="","",IFERROR(J38/('연간'!U4),"")) | K66: =IF(K38="","",IFERROR(K38/('연간'!V4),"")) | L66: =IF(L38="","",IFERROR(L38/('연간'!W4),""))
A67: 배당성향 | B67: 참고 | C67: =IF(C40="","",IFERROR(C40/(IF(COUNT('연간'!E44:H44)<4,"",SUM('연간'!E44:H44))),"")) | D67: =IF(D40="","",IFERROR(D40/(IF(COUNT('연간'!F44:I44)<4,"",SUM('연간'!F44:I44))),"")) | E67: =IF(E40="","",IFERROR(E40/(IF(COUNT('연간'!G44:J44)<4,"",SUM('연간'!G44:J44))),"")) | F67: =IF(F40="","",IFERROR(F40/(IF(COUNT('연간'!H44:K44)<4,"",SUM('연간'!H44:K44))),"")) | G67: =IF(G40="","",IFERROR(G40/(IF(COUNT('연간'!I44:L44)<4,"",SUM('연간'!I44:L44))),"")) | H67: =IF(H40="","",IFERROR(H40/('연간'!O44),"")) | I67: =IF(I40="","",IFERROR(I40/('연간'!T44),"")) | J67: =IF(J40="","",IFERROR(J40/('연간'!U44),"")) | K67: =IF(K40="","",IFERROR(K40/('연간'!V44),"")) | L67: =IF(L40="","",IFERROR(L40/('연간'!W44),""))
A69: 재무상태표 · 전 항목 | B69: 분기 말 잔액
A70: 항목 | B70: 참고 | C70: 2026.2Q | D70: 2026.3Q | E70: 2026.4Q | F70: 2027.1Q | G70: 2027.2Q | H70: 2018 | I70: 2023 | J70: 2024 | K70: 2025 | L70: 2026
A71: 현금 및 예금 | C71: 489078 | D71: 583276 | E71: 507115 | F71: 596976 | G71: 564751 | H71: 437675 | I71: 424998 | J71: 451518 | K71: 513402 | L71: 507115
A72: 받을어음·매출채권 | C72: 305063 | D72: 324817 | E72: 342170 | F72: 379590 | G72: 397626 | H72: 160276 | I72: 283733 | J72: 285099 | K72: 302441 | L72: 342170
A73: 유가증권 | C73: 675242 | D73: 734575 | E73: 826897 | F73: 896913 | G73: 861843 | H73: 370055 | I73: 556796 | J73: 520290 | K73: 660659 | L73: 826897
A74: 재고자산 | C74: 84903 | D74: 83805 | E74: 87875 | F74: 85273 | G74: 101073 | H74: 34847 | I74: 92207 | J74: 87454 | K74: 82340 | L74: 87875
A75: 이연법인세자산 | H75: 14395
A76: 기타 | C76: 15866 | D76: 17052 | E76: 19855 | F76: 22887 | G76: 22783 | H76: 6543 | I76: 14387 | J76: 13886 | K76: 15529 | L76: 19855
A77: 대손충당금 | C77: -1731 | D77: -1791 | E77: -1907 | F77: -2135 | G77: -2441 | H77: -366 | I77: -724 | J77: -1238 | K77: -1329 | L77: -1907
A78: 유동자산 합계 | C78: 1568423 | D78: 1741736 | E78: 1782006 | F78: 1979505 | G78: 1945636 | H78: 1023426 | I78: 1371399 | J78: 1357010 | K78: 1573043 | L78: 1782006
A79: 건물·구축물 | F79: 34915 | H79: 21363
A80: 감가상각누계액 | F80: -22804 | H80: -14276
A81: 건물·구축물(순액) | F81: 12110 | H81: 7086
A82: 공구·기구·비품 | F82: 75596 | H82: 30744
A83: 감가상각누계액 | F83: -61193 | H83: -25015
A84: 공구·기구·비품(순액) | F84: 14403 | H84: 5728
A85: 토지 | F85: 32971 | H85: 7021
A86: 기타 | F86: 55809 | H86: 2964
A87: 감가상각누계액 | F87: -20576 | H87: -1375
A88: 기타(순액) | F88: 35232 | H88: 1589
A89: 유형자산 | C89: 81515 | D89: 82187 | E89: 84511 | F89: 94718 | G89: 98828 | H89: 21426 | I89: 31242 | J89: 73819 | K89: 77403 | L89: 84511
A90: 기타 | F90: 29181 | H90: 5204
A91: 무형자산 | C91: 36111 | D91: 33535 | E91: 31360 | F91: 29181 | G91: 26932 | H91: 5204 | I91: 3538 | J91: 4568 | K91: 6311 | L91: 31360
A92: 투자유가증권 | C92: 1559662 | D92: 1544666 | E92: 1531075 | F92: 1514304 | G92: 1598277 | H92: 432981 | I92: 1073228 | J92: 1345412 | K92: 1447884 | L92: 1531075
A93: 이연법인세자산 | H93: 456
A94: Long Term Time Deposits IOA | C94: 17992 | D94: 18861 | E94: 19976 | F94: 20220 | G94: 20422 | I94: 15793 | J94: 17766 | K94: 17512 | L94: 19976
A95: 이연법인세자산 | F95: 20515
A96: 기타 | C96: 26208 | D96: 26465 | E96: 29775 | F96: 32786 | G96: 34854 | H96: 2790 | I96: 22588 | J96: 20860 | K96: 25615 | L96: 29775
A97: 대손충당금 | C97: -60 | D97: -60 | E97: -60 | F97: -60 | G97: -60 | H97: -61 | I97: -61 | J97: -60 | K97: -60 | L97: -60
A98: 투자 및 기타자산 합계 | C98: 1603803 | D98: 1589932 | E98: 1580766 | F98: 1567250 | G98: 1653494 | H98: 436165 | I98: 1111548 | J98: 1383979 | K98: 1490950 | L98: 1580766
A99: 비유동자산 합계 | C99: 1721430 | D99: 1705655 | E99: 1696638 | F99: 1691149 | G99: 1779255 | H99: 462796 | I99: 1146329 | J99: 1462367 | K99: 1574665 | L99: 1696638
A100: 자산 합계 | C100: 3289853 | D100: 3447391 | E100: 3478645 | F100: 3670655 | G100: 3724891 | H100: 1486222 | I100: 2517729 | J100: 2819378 | K100: 3147709 | L100: 3478645
A101: 지급어음·매입채무 | C101: 15760 | D101: 15091 | E101: 16653 | F101: 10890 | G101: 23600 | H101: 10645 | I101: 21225 | J101: 19208 | K101: 16095 | L101: 16653
...

Sheet 출처
A1: 출처 · 쓴 결산단신
A3: 공시일 | B3: 문서 | C3: PDF
A4: 2026-07-28 | B4: 2027년 3월 결산기 1분기 결산단신 | C4: https://www2.jpx.co.jp/disc/68610/140120260717595564.pdf
A5: 2026-04-24 | B5: 2026년 3월 결산기 연간 결산단신 | C5: https://www2.jpx.co.jp/disc/68610/140120260418506301.pdf
A6: 2026-01-29 | B6: 2026년 3월 결산기 3분기 결산단신 | C6: https://www2.jpx.co.jp/disc/68610/140120260123537908.pdf
A7: 2025-10-29 | B7: 2026년 3월 결산기 2분기 결산단신 | C7: https://www2.jpx.co.jp/disc/68610/140120251026578934.pdf
A8: 2025-07-29 | B8: 2026년 3월 결산기 1분기 결산단신 | C8: https://www2.jpx.co.jp/disc/68610/140120250724520054.pdf
A9: 2025-04-25 | B9: 2025년 3월 결산기 연간 결산단신 | C9: https://www2.jpx.co.jp/disc/68610/140120250422520237.pdf
A10: 2025-01-31 | B10: 2025년 3월 결산기 3분기 결산단신 | C10: https://www2.jpx.co.jp/disc/68610/140120241218540581.pdf
A11: 2024-10-29 | B11: 2025년 3월 결산기 2분기 결산단신 | C11: https://www2.jpx.co.jp/disc/68610/140120241025503102.pdf
A12: 2024-07-26 | B12: 2025년 3월 결산기 1분기 결산단신 | C12: https://www2.jpx.co.jp/disc/68610/140120240724554357.pdf
A13: 2024-04-25 | B13: 2024년 3월 결산기 연간 결산단신 | C13: https://www2.jpx.co.jp/disc/68610/140120240422574265.pdf
A14: 2024-02-02 | B14: 2024년 3월 결산기 3분기 결산단신 | C14: https://www2.jpx.co.jp/disc/68610/140120240130522378.pdf
... A24: 2018-04-26 | B24: 연간 결산단신 | C24: https://www2.jpx.co.jp/disc/68610/140120180416412789.pdf
