Workbook

Sheet 연간
A1: 7962 Model
A2: 모를 땐 보수적으로 | B2: (단위: 백만엔) | C2: 5월 결산 · 일본 기준 · 2027.4Q = 2027년 5월 결산기 4분기 | Y2: (추정: 파란 글씨 = 직접 입력)
A3: 항목 | B3: 참고 | C3: 2025.1Q | D3: 2025.2Q | E3: 2025.3Q | F3: 2025.4Q | G3: 2026.1Q | H3: 2026.2Q | I3: 2026.3Q | J3: 2026.4Q | K3: 2027.1Q | L3: 2027.2Q | M3: 2027.3Q | N3: 2027.4Q | O3: 2018 | P3: 2019 | Q3: 2020 | R3: 2021 | S3: 2022 | T3: 2023 | U3: 2024 | V3: 2025 | W3: 2026 | X3: 2027 | Y3: 2028(MW) | Z3: 2029(MW) | AA3: 2030(MW) | AB3: 2031(MW) | AC3: 2032(MW)
A4: 매출액 | B4: MW = 제품 합계 | C4: 8785.176 | D4: 9734.881 | E4: 10261.756 | F4: 10771.256 | G4: 8251.473 | H4: 9715.757 | I4: 9934.631 | J4: 11737.639 | O4: 34627.821 | P4: 34788.058 | Q4: 34329.544 | R4: 33455.274 | S4: 36319.071 | T4: 36636.516 | U4: 39393.899 | V4: 39553.069 | W4: 39639.5 | X4: 39134.788 | Y4: =IF(COUNT(Y7,Y10,Y13,Y16,Y19)=0,"",SUM(Y7,Y10,Y13,Y16,Y19)) | Z4: =IF(COUNT(Z7,Z10,Z13,Z16,Z19)=0,"",SUM(Z7,Z10,Z13,Z16,Z19)) | AA4: =IF(COUNT(AA7,AA10,AA13,AA16,AA19)=0,"",SUM(AA7,AA10,AA13,AA16,AA19)) | AB4: =IF(COUNT(AB7,AB10,AB13,AB16,AB19)=0,"",SUM(AB7,AB10,AB13,AB16,AB19)) | AC4: =IF(COUNT(AC7,AC10,AC13,AC16,AC19)=0,"",SUM(AC7,AC10,AC13,AC16,AC19))
A5: YoY | G5: =IF(OR(G4="",C4=""),"",IFERROR(G4/C4-1,"")) | H5: =IF(OR(H4="",D4=""),"",IFERROR(H4/D4-1,"")) | I5: =IF(OR(I4="",E4=""),"",IFERROR(I4/E4-1,"")) | J5: =IF(OR(J4="",F4=""),"",IFERROR(J4/F4-1,"")) | K5: =IF(OR(K4="",G4=""),"",IFERROR(K4/G4-1,"")) | L5: =IF(OR(L4="",H4=""),"",IFERROR(L4/H4-1,"")) | M5: =IF(OR(M4="",I4=""),"",IFERROR(M4/I4-1,"")) | N5: =IF(OR(N4="",J4=""),"",IFERROR(N4/J4-1,"")) | P5: =IF(OR(P4="",O4=""),"",IFERROR(P4/O4-1,"")) | Q5: =IF(OR(Q4="",P4=""),"",IFERROR(Q4/P4-1,"")) | R5: =IF(OR(R4="",Q4=""),"",IFERROR(R4/Q4-1,"")) | S5: =IF(OR(S4="",R4=""),"",IFERROR(S4/R4-1,"")) | T5: =IF(OR(T4="",S4=""),"",IFERROR(T4/S4-1,"")) | U5: =IF(OR(U4="",T4=""),"",IFERROR(U4/T4-1,"")) | V5: =IF(OR(V4="",U4=""),"",IFERROR(V4/U4-1,"")) | W5: =IF(OR(W4="",V4=""),"",IFERROR(W4/V4-1,"")) | ... AC5: =IF(OR(AC4="",AB4=""),"",IFERROR(AC4/AB4-1,""))
A6: 제품별 매출 분류 | B6: 사업보고서 매출실적
A7: StationeryAndOfficeSupplyReportableSegmentsMember | C7: 5183.236 | D7: 6189.249 | E7: 6839.502 | F7: 7122.651 | G7: 4922.836 | H7: 6096.275 | I7: 6846.367 | J7: 7312.615 | V7: 25334.638 | W7: 25178.093 | X7: 24902.916
A8: 비중 | C8: =IF(OR(C7="",C4=""),"",IFERROR(C7/C4,"")) | D8: =IF(OR(D7="",D4=""),"",IFERROR(D7/D4,"")) | E8: =IF(OR(E7="",E4=""),"",IFERROR(E7/E4,"")) | F8: =IF(OR(F7="",F4=""),"",IFERROR(F7/F4,"")) | G8: =IF(OR(G7="",G4=""),"",IFERROR(G7/G4,"")) | H8: =IF(OR(H7="",H4=""),"",IFERROR(H7/H4,"")) | I8: =IF(OR(I7="",I4=""),"",IFERROR(I7/I4,"")) | J8: =IF(OR(J7="",J4=""),"",IFERROR(J7/J4,"")) | ... AC8: =IF(OR(AC7="",AC4=""),"",IFERROR(AC7/AC4,""))
A9: YoY | G9: =IF(OR(G7="",C7=""),"",IFERROR(G7/C7-1,"")) | H9: =IF(OR(H7="",D7=""),"",IFERROR(H7/D7-1,"")) | I9: =IF(OR(I7="",E7=""),"",IFERROR(I7/E7-1,"")) | J9: =IF(OR(J7="",F7=""),"",IFERROR(J7/F7-1,"")) | K9: =IF(OR(K7="",G7=""),"",IFERROR(K7/G7-1,"")) | L9: =IF(OR(L7="",H7=""),"",IFERROR(L7/H7-1,"")) | M9: =IF(OR(M7="",I7=""),"",IFERROR(M7/I7-1,"")) | N9: =IF(OR(N7="",J7=""),"",IFERROR(N7/J7-1,"")) | P9: =IF(OR(P7="",O7=""),"",IFERROR(P7/O7-1,"")) | Q9: =IF(OR(Q7="",P7=""),"",IFERROR(Q7/P7-1,"")) | R9: =IF(OR(R7="",Q7=""),"",IFERROR(R7/Q7-1,"")) | S9: =IF(OR(S7="",R7=""),"",IFERROR(S7/R7-1,"")) | T9: =IF(OR(T7="",S7=""),"",IFERROR(T7/S7-1,"")) | U9: =IF(OR(U7="",T7=""),"",IFERROR(U7/T7-1,"")) | V9: =IF(OR(V7="",U7=""),"",IFERROR(V7/U7-1,"")) | W9: =IF(OR(W7="",V7=""),"",IFERROR(W7/V7-1,"")) | ... AC9: =IF(OR(AC7="",AB7=""),"",IFERROR(AC7/AB7-1,""))
A10: LifestyleProductsReportableSegmentMember | C10: 3601.94 | G10: 3328.637
A11: 비중 | C11: =IF(OR(C10="",C4=""),"",IFERROR(C10/C4,"")) | D11: =IF(OR(D10="",D4=""),"",IFERROR(D10/D4,"")) | E11: =IF(OR(E10="",E4=""),"",IFERROR(E10/E4,"")) | F11: =IF(OR(F10="",F4=""),"",IFERROR(F10/F4,"")) | G11: =IF(OR(G10="",G4=""),"",IFERROR(G10/G4,"")) | H11: =IF(OR(H10="",H4=""),"",IFERROR(H10/H4,"")) | I11: =IF(OR(I10="",I4=""),"",IFERROR(I10/I4,"")) | J11: =IF(OR(J10="",J4=""),"",IFERROR(J10/J4,"")) | ... AC11: =IF(OR(AC10="",AC4=""),"",IFERROR(AC10/AC4,""))
A12: YoY | G12: =IF(OR(G10="",C10=""),"",IFERROR(G10/C10-1,"")) | H12: =IF(OR(H10="",D10=""),"",IFERROR(H10/D10-1,"")) | I12: =IF(OR(I10="",E10=""),"",IFERROR(I10/E10-1,"")) | J12: =IF(OR(J10="",F10=""),"",IFERROR(J10/F10-1,"")) | K12: =IF(OR(K10="",G10=""),"",IFERROR(K10/G10-1,"")) | L12: =IF(OR(L10="",H10=""),"",IFERROR(L10/H10-1,"")) | M12: =IF(OR(M10="",I10=""),"",IFERROR(M10/I10-1,"")) | N12: =IF(OR(N10="",J10=""),"",IFERROR(N10/J10-1,"")) | P12: =IF(OR(P10="",O10=""),"",IFERROR(P10/O10-1,"")) | Q12: =IF(OR(Q10="",P10=""),"",IFERROR(Q10/P10-1,"")) | R12: =IF(OR(R10="",Q10=""),"",IFERROR(R10/Q10-1,"")) | S12: =IF(OR(S10="",R10=""),"",IFERROR(S10/R10-1,"")) | T12: =IF(OR(T10="",S10=""),"",IFERROR(T10/S10-1,"")) | U12: =IF(OR(U10="",T10=""),"",IFERROR(U10/T10-1,"")) | V12: =IF(OR(V10="",U10=""),"",IFERROR(V10/U10-1,"")) | W12: =IF(OR(W10="",V10=""),"",IFERROR(W10/V10-1,"")) | ... AC12: =IF(OR(AC10="",AB10=""),"",IFERROR(AC10/AB10-1,""))
A13: LifeStyleProductsReportableSegmentMember
A14: 비중 | C14: =IF(OR(C13="",C4=""),"",IFERROR(C13/C4,"")) | D14: =IF(OR(D13="",D4=""),"",IFERROR(D13/D4,"")) | E14: =IF(OR(E13="",E4=""),"",IFERROR(E13/E4,"")) | F14: =IF(OR(F13="",F4=""),"",IFERROR(F13/F4,"")) | G14: =IF(OR(G13="",G4=""),"",IFERROR(G13/G4,"")) | H14: =IF(OR(H13="",H4=""),"",IFERROR(H13/H4,"")) | I14: =IF(OR(I13="",I4=""),"",IFERROR(I13/I4,"")) | J14: =IF(OR(J13="",J4=""),"",IFERROR(J13/J4,"")) | ... AC14: =IF(OR(AC13="",AC4=""),"",IFERROR(AC13/AC4,""))
A15: YoY | G15: =IF(OR(G13="",C13=""),"",IFERROR(G13/C13-1,"")) | H15: =IF(OR(H13="",D13=""),"",IFERROR(H13/D13-1,"")) | I15: =IF(OR(I13="",E13=""),"",IFERROR(I13/E13-1,"")) | J15: =IF(OR(J13="",F13=""),"",IFERROR(J13/F13-1,"")) | K15: =IF(OR(K13="",G13=""),"",IFERROR(K13/G13-1,"")) | L15: =IF(OR(L13="",H13=""),"",IFERROR(L13/H13-1,"")) | M15: =IF(OR(M13="",I13=""),"",IFERROR(M13/I13-1,"")) | N15: =IF(OR(N13="",J13=""),"",IFERROR(N13/J13-1,"")) | P15: =IF(OR(P13="",O13=""),"",IFERROR(P13/O13-1,"")) | Q15: =IF(OR(Q13="",P13=""),"",IFERROR(Q13/P13-1,"")) | R15: =IF(OR(R13="",Q13=""),"",IFERROR(R13/Q13-1,"")) | S15: =IF(OR(S13="",R13=""),"",IFERROR(S13/R13-1,"")) | T15: =IF(OR(T13="",S13=""),"",IFERROR(T13/S13-1,"")) | U15: =IF(OR(U13="",T13=""),"",IFERROR(U13/T13-1,"")) | V15: =IF(OR(V13="",U13=""),"",IFERROR(V13/U13-1,"")) | W15: =IF(OR(W13="",V13=""),"",IFERROR(W13/V13-1,"")) | ... AC15: =IF(OR(AC13="",AB13=""),"",IFERROR(AC13/AB13-1,""))
A16: InteriorLifeStyleReportableSegmentsMember | E16: 3422.254 | F16: 3648.605 | V16: 14218.431 | W16: 14461.407 | X16: 14231.871
A17: 비중 | C17: =IF(OR(C16="",C4=""),"",IFERROR(C16/C4,"")) | D17: =IF(OR(D16="",D4=""),"",IFERROR(D16/D4,"")) | E17: =IF(OR(E16="",E4=""),"",IFERROR(E16/E4,"")) | F17: =IF(OR(F16="",F4=""),"",IFERROR(F16/F4,"")) | G17: =IF(OR(G16="",G4=""),"",IFERROR(G16/G4,"")) | H17: =IF(OR(H16="",H4=""),"",IFERROR(H16/H4,"")) | I17: =IF(OR(I16="",I4=""),"",IFERROR(I16/I4,"")) | J17: =IF(OR(J16="",J4=""),"",IFERROR(J16/J4,"")) | ... AC17: =IF(OR(AC16="",AC4=""),"",IFERROR(AC16/AC4,""))
A18: YoY | G18: =IF(OR(G16="",C16=""),"",IFERROR(G16/C16-1,"")) | H18: =IF(OR(H16="",D16=""),"",IFERROR(H16/D16-1,"")) | I18: =IF(OR(I16="",E16=""),"",IFERROR(I16/E16-1,"")) | J18: =IF(OR(J16="",F16=""),"",IFERROR(J16/F16-1,"")) | K18: =IF(OR(K16="",G16=""),"",IFERROR(K16/G16-1,"")) | L18: =IF(OR(L16="",H16=""),"",IFERROR(L16/H16-1,"")) | M18: =IF(OR(M16="",I16=""),"",IFERROR(M16/I16-1,"")) | N18: =IF(OR(N16="",J16=""),"",IFERROR(N16/J16-1,"")) | P18: =IF(OR(P16="",O16=""),"",IFERROR(P16/O16-1,"")) | Q18: =IF(OR(Q16="",P16=""),"",IFERROR(Q16/P16-1,"")) | R18: =IF(OR(R16="",Q16=""),"",IFERROR(R16/Q16-1,"")) | S18: =IF(OR(S16="",R16=""),"",IFERROR(S16/R16-1,"")) | T18: =IF(OR(T16="",S16=""),"",IFERROR(T16/S16-1,"")) | U18: =IF(OR(U16="",T16=""),"",IFERROR(U16/T16-1,"")) | V18: =IF(OR(V16="",U16=""),"",IFERROR(V16/U16-1,"")) | W18: =IF(OR(W16="",V16=""),"",IFERROR(W16/V16-1,"")) | ... AC18: =IF(OR(AC16="",AB16=""),"",IFERROR(AC16/AB16-1,""))
A19: EntityTotalMember | C19: 8785.176 | G19: 8251.473
A20: 비중 | C20: =IF(OR(C19="",C4=""),"",IFERROR(C19/C4,"")) | D20: =IF(OR(D19="",D4=""),"",IFERROR(D19/D4,"")) | E20: =IF(OR(E19="",E4=""),"",IFERROR(E19/E4,"")) | F20: =IF(OR(F19="",F4=""),"",IFERROR(F19/F4,"")) | G20: =IF(OR(G19="",G4=""),"",IFERROR(G19/G4,"")) | H20: =IF(OR(H19="",H4=""),"",IFERROR(H19/H4,"")) | I20: =IF(OR(I19="",I4=""),"",IFERROR(I19/I4,"")) | J20: =IF(OR(J19="",J4=""),"",IFERROR(J19/J4,"")) | ... AC20: =IF(OR(AC19="",AC4=""),"",IFERROR(AC19/AC4,""))
A21: YoY | G21: =IF(OR(G19="",C19=""),"",IFERROR(G19/C19-1,"")) | H21: =IF(OR(H19="",D19=""),"",IFERROR(H19/D19-1,"")) | I21: =IF(OR(I19="",E19=""),"",IFERROR(I19/E19-1,"")) | J21: =IF(OR(J19="",F19=""),"",IFERROR(J19/F19-1,"")) | K21: =IF(OR(K19="",G19=""),"",IFERROR(K19/G19-1,"")) | L21: =IF(OR(L19="",H19=""),"",IFERROR(L19/H19-1,"")) | M21: =IF(OR(M19="",I19=""),"",IFERROR(M19/I19-1,"")) | N21: =IF(OR(N19="",J19=""),"",IFERROR(N19/J19-1,"")) | P21: =IF(OR(P19="",O19=""),"",IFERROR(P19/O19-1,"")) | Q21: =IF(OR(Q19="",P19=""),"",IFERROR(Q19/P19-1,"")) | R21: =IF(OR(R19="",Q19=""),"",IFERROR(R19/Q19-1,"")) | S21: =IF(OR(S19="",R19=""),"",IFERROR(S19/R19-1,"")) | T21: =IF(OR(T19="",S19=""),"",IFERROR(T19/S19-1,"")) | U21: =IF(OR(U19="",T19=""),"",IFERROR(U19/T19-1,"")) | V21: =IF(OR(V19="",U19=""),"",IFERROR(V19/U19-1,"")) | W21: =IF(OR(W19="",V19=""),"",IFERROR(W19/V19-1,"")) | ... AC21: =IF(OR(AC19="",AB19=""),"",IFERROR(AC19/AB19-1,""))
A22: 매출원가
A23: 전체 매출원가 | C23: 5537.849 | D23: 5973.641 | E23: 6129.678 | F23: 7595.652 | G23: 5035.836 | H23: 5894.876 | I23: 6108.146 | J23: 7735.502 | O23: 21653.1 | P23: 21198.62 | Q23: 21146.112 | R23: 20554.178 | S23: 21880.29 | T23: 23159.303 | U23: 25203.192 | V23: 25236.82 | W23: 24774.36 | X23: 24044.543
A24: YoY | G24: =IF(OR(G23="",C23=""),"",IF(C23<=0,"",IFERROR(G23/C23-1,""))) | H24: =IF(OR(H23="",D23=""),"",IF(D23<=0,"",IFERROR(H23/D23-1,""))) | I24: =IF(OR(I23="",E23=""),"",IF(E23<=0,"",IFERROR(I23/E23-1,""))) | J24: =IF(OR(J23="",F23=""),"",IF(F23<=0,"",IFERROR(J23/F23-1,""))) | K24: =IF(OR(K23="",G23=""),"",IF(G23<=0,"",IFERROR(K23/G23-1,""))) | L24: =IF(OR(L23="",H23=""),"",IF(H23<=0,"",IFERROR(L23/H23-1,""))) | M24: =IF(OR(M23="",I23=""),"",IF(I23<=0,"",IFERROR(M23/I23-1,""))) | N24: =IF(OR(N23="",J23=""),"",IF(J23<=0,"",IFERROR(N23/J23-1,""))) | P24: =IF(OR(P23="",O23=""),"",IF(O23<=0,"",IFERROR(P23/O23-1,""))) | Q24: =IF(OR(Q23="",P23=""),"",IF(P23<=0,"",IFERROR(Q23/P23-1,""))) | R24: =IF(OR(R23="",Q23=""),"",IF(Q23<=0,"",IFERROR(R23/Q23-1,""))) | S24: =IF(OR(S23="",R23=""),"",IF(R23<=0,"",IFERROR(S23/R23-1,""))) | T24: =IF(OR(T23="",S23=""),"",IF(S23<=0,"",IFERROR(T23/S23-1,""))) | U24: =IF(OR(U23="",T23=""),"",IF(T23<=0,"",IFERROR(U23/T23-1,""))) | V24: =IF(OR(V23="",U23=""),"",IF(U23<=0,"",IFERROR(V23/U23-1,""))) | W24: =IF(OR(W23="",V23=""),"",IF(V23<=0,"",IFERROR(W23/V23-1,""))) | ... AC24: =IF(OR(AC23="",AB23=""),"",IF(AB23<=0,"",IFERROR(AC23/AB23-1,"")))
A25: 매출총이익 | C25: =IF(OR(C4="",C23=""),"",IFERROR(C4-C23,"")) | D25: =IF(OR(D4="",D23=""),"",IFERROR(D4-D23,"")) | E25: =IF(OR(E4="",E23=""),"",IFERROR(E4-E23,"")) | F25: =IF(OR(F4="",F23=""),"",IFERROR(F4-F23,"")) | G25: =IF(OR(G4="",G23=""),"",IFERROR(G4-G23,"")) | H25: =IF(OR(H4="",H23=""),"",IFERROR(H4-H23,"")) | I25: =IF(OR(I4="",I23=""),"",IFERROR(I4-I23,"")) | J25: =IF(OR(J4="",J23=""),"",IFERROR(J4-J23,"")) | ... X25: =IF(OR(X4="",X23=""),"",IFERROR(X4-X23,""))
A26: GPM | C26: =IF(OR(C25="",C4=""),"",IFERROR(C25/C4,"")) | D26: =IF(OR(D25="",D4=""),"",IFERROR(D25/D4,"")) | E26: =IF(OR(E25="",E4=""),"",IFERROR(E25/E4,"")) | F26: =IF(OR(F25="",F4=""),"",IFERROR(F25/F4,"")) | G26: =IF(OR(G25="",G4=""),"",IFERROR(G25/G4,"")) | H26: =IF(OR(H25="",H4=""),"",IFERROR(H25/H4,"")) | I26: =IF(OR(I25="",I4=""),"",IFERROR(I25/I4,"")) | J26: =IF(OR(J25="",J4=""),"",IFERROR(J25/J4,"")) | ... AC26: =IF(OR(AC25="",AC4=""),"",IFERROR(AC25/AC4,""))
A27: YoY | G27: =IF(OR(G25="",C25=""),"",IF(C25<=0,"",IFERROR(G25/C25-1,""))) | H27: =IF(OR(H25="",D25=""),"",IF(D25<=0,"",IFERROR(H25/D25-1,""))) | I27: =IF(OR(I25="",E25=""),"",IF(E25<=0,"",IFERROR(I25/E25-1,""))) | J27: =IF(OR(J25="",F25=""),"",IF(F25<=0,"",IFERROR(J25/F25-1,""))) | K27: =IF(OR(K25="",G25=""),"",IF(G25<=0,"",IFERROR(K25/G25-1,""))) | L27: =IF(OR(L25="",H25=""),"",IF(H25<=0,"",IFERROR(L25/H25-1,""))) | M27: =IF(OR(M25="",I25=""),"",IF(I25<=0,"",IFERROR(M25/I25-1,""))) | N27: =IF(OR(N25="",J25=""),"",IF(J25<=0,"",IFERROR(N25/J25-1,""))) | P27: =IF(OR(P25="",O25=""),"",IF(O25<=0,"",IFERROR(P25/O25-1,""))) | Q27: =IF(OR(Q25="",P25=""),"",IF(P25<=0,"",IFERROR(Q25/P25-1,""))) | R27: =IF(OR(R25="",Q25=""),"",IF(Q25<=0,"",IFERROR(R25/Q25-1,""))) | S27: =IF(OR(S25="",R25=""),"",IF(R25<=0,"",IFERROR(S25/R25-1,""))) | T27: =IF(OR(T25="",S25=""),"",IF(S25<=0,"",IFERROR(T25/S25-1,""))) | U27: =IF(OR(U25="",T25=""),"",IF(T25<=0,"",IFERROR(U25/T25-1,""))) | V27: =IF(OR(V25="",U25=""),"",IF(U25<=0,"",IFERROR(V25/U25-1,""))) | W27: =IF(OR(W25="",V25=""),"",IF(V25<=0,"",IFERROR(W25/V25-1,""))) | ... AC27: =IF(OR(AC25="",AB25=""),"",IF(AB25<=0,"",IFERROR(AC25/AB25-1,"")))
A28: 판매관리비
A29: 전체 판관비 | C29: 3500.086 | D29: 3489.966 | E29: 3763.823 | F29: 3804.256 | G29: 3429.424 | H29: 3408.246 | I29: 3502.363 | J29: 3987.392 | O29: 11283.751 | P29: 11676.825 | Q29: 11788.389 | R29: 11668.499 | S29: 12021.975 | T29: 12469.604 | U29: 13822.398 | V29: 14558.131 | W29: 14327.425 | X29: 13961.333
A30: YoY | G30: =IF(OR(G29="",C29=""),"",IF(C29<=0,"",IFERROR(G29/C29-1,""))) | H30: =IF(OR(H29="",D29=""),"",IF(D29<=0,"",IFERROR(H29/D29-1,""))) | I30: =IF(OR(I29="",E29=""),"",IF(E29<=0,"",IFERROR(I29/E29-1,""))) | J30: =IF(OR(J29="",F29=""),"",IF(F29<=0,"",IFERROR(J29/F29-1,""))) | K30: =IF(OR(K29="",G29=""),"",IF(G29<=0,"",IFERROR(K29/G29-1,""))) | L30: =IF(OR(L29="",H29=""),"",IF(H29<=0,"",IFERROR(L29/H29-1,""))) | M30: =IF(OR(M29="",I29=""),"",IF(I29<=0,"",IFERROR(M29/I29-1,""))) | N30: =IF(OR(N29="",J29=""),"",IF(J29<=0,"",IFERROR(N29/J29-1,""))) | P30: =IF(OR(P29="",O29=""),"",IF(O29<=0,"",IFERROR(P29/O29-1,""))) | Q30: =IF(OR(Q29="",P29=""),"",IF(P29<=0,"",IFERROR(Q29/P29-1,""))) | R30: =IF(OR(R29="",Q29=""),"",IF(Q29<=0,"",IFERROR(R29/Q29-1,""))) | S30: =IF(OR(S29="",R29=""),"",IF(R29<=0,"",IFERROR(S29/R29-1,""))) | T30: =IF(OR(T29="",S29=""),"",IF(S29<=0,"",IFERROR(T29/S29-1,""))) | U30: =IF(OR(U29="",T29=""),"",IF(T29<=0,"",IFERROR(U29/T29-1,""))) | V30: =IF(OR(V29="",U29=""),"",IF(U29<=0,"",IFERROR(V29/U29-1,""))) | W30: =IF(OR(W29="",V29=""),"",IF(V29<=0,"",IFERROR(W29/V29-1,""))) | ... AC30: =IF(OR(AC29="",AB29=""),"",IF(AB29<=0,"",IFERROR(AC29/AB29-1,"")))
A31: 영업이익 | B31: MW = 매출 × OPM | C31: -252.759 | D31: 271.273 | E31: 368.255 | F31: -628.652 | G31: -213.787 | H31: 412.634 | I31: 324.122 | J31: 14.746 | O31: 1690.969 | P31: 1912.612 | Q31: 1395.042 | R31: 1232.597 | S31: 2416.805 | T31: 1007.607 | U31: 368.308 | V31: -241.883 | W31: 537.715 | X31: 1128.91 | Y31: =IF(OR(Y4="",Y32=""),"",IFERROR(Y4*Y32,"")) | Z31: =IF(OR(Z4="",Z32=""),"",IFERROR(Z4*Z32,"")) | AA31: =IF(OR(AA4="",AA32=""),"",IFERROR(AA4*AA32,"")) | AB31: =IF(OR(AB4="",AB32=""),"",IFERROR(AB4*AB32,"")) | AC31: =IF(OR(AC4="",AC32=""),"",IFERROR(AC4*AC32,""))
A32: OPM | B32: MW 입력 | C32: =IF(OR(C31="",C4=""),"",IFERROR(C31/C4,"")) | D32: =IF(OR(D31="",D4=""),"",IFERROR(D31/D4,"")) | E32: =IF(OR(E31="",E4=""),"",IFERROR(E31/E4,"")) | F32: =IF(OR(F31="",F4=""),"",IFERROR(F31/F4,"")) | G32: =IF(OR(G31="",G4=""),"",IFERROR(G31/G4,"")) | H32: =IF(OR(H31="",H4=""),"",IFERROR(H31/H4,"")) | I32: =IF(OR(I31="",I4=""),"",IFERROR(I31/I4,"")) | J32: =IF(OR(J31="",J4=""),"",IFERROR(J31/J4,"")) | ... X32: =IF(OR(X31="",X4=""),"",IFERROR(X31/X4,""))
A33: 증가율 | G33: =IF(OR(G31="",C31=""),"",IFERROR(G31/C31-1,"")) | H33: =IF(OR(H31="",D31=""),"",IFERROR(H31/D31-1,"")) | I33: =IF(OR(I31="",E31=""),"",IFERROR(I31/E31-1,"")) | J33: =IF(OR(J31="",F31=""),"",IFERROR(J31/F31-1,"")) | K33: =IF(OR(K31="",G31=""),"",IFERROR(K31/G31-1,"")) | L33: =IF(OR(L31="",H31=""),"",IFERROR(L31/H31-1,"")) | M33: =IF(OR(M31="",I31=""),"",IFERROR(M31/I31-1,"")) | N33: =IF(OR(N31="",J31=""),"",IFERROR(N31/J31-1,"")) | P33: =IF(OR(P31="",O31=""),"",IFERROR(P31/O31-1,"")) | Q33: =IF(OR(Q31="",P31=""),"",IFERROR(Q31/P31-1,"")) | R33: =IF(OR(R31="",Q31=""),"",IFERROR(R31/Q31-1,"")) | S33: =IF(OR(S31="",R31=""),"",IFERROR(S31/R31-1,"")) | T33: =IF(OR(T31="",S31=""),"",IFERROR(T31/S31-1,"")) | U33: =IF(OR(U31="",T31=""),"",IFERROR(U31/T31-1,"")) | V33: =IF(OR(V31="",U31=""),"",IFERROR(V31/U31-1,"")) | W33: =IF(OR(W31="",V31=""),"",IFERROR(W31/V31-1,"")) | ... AC33: =IF(OR(AC31="",AB31=""),"",IFERROR(AC31/AB31-1,""))
A34: 비용의 성격별 분류 | B34: 참고 데이터
A35: 총 판관비 | O35: =IF(O29="","",O29) | P35: =IF(P29="","",P29) | Q35: =IF(Q29="","",Q29) | R35: =IF(R29="","",R29) | S35: =IF(S29="","",S29) | T35: =IF(T29="","",T29) | U35: =IF(U29="","",U29) | V35: =IF(V29="","",V29) | ... X35: =IF(X29="","",X29)
A36: 급여 | B36: 고정비
A37: % of Sales | O37: =IF(OR(O36="",O4=""),"",IFERROR(O36/O4,"")) | P37: =IF(OR(P36="",P4=""),"",IFERROR(P36/P4,"")) | Q37: =IF(OR(Q36="",Q4=""),"",IFERROR(Q36/Q4,"")) | R37: =IF(OR(R36="",R4=""),"",IFERROR(R36/R4,"")) | S37: =IF(OR(S36="",S4=""),"",IFERROR(S36/S4,"")) | T37: =IF(OR(T36="",T4=""),"",IFERROR(T36/T4,"")) | U37: =IF(OR(U36="",U4=""),"",IFERROR(U36/U4,"")) | V37: =IF(OR(V36="",V4=""),"",IFERROR(V36/V4,"")) | ... X37: =IF(OR(X36="",X4=""),"",IFERROR(X36/X4,""))
A38: 감가상각비 | B38: 고정비
A39: % of Sales | O39: =IF(OR(O38="",O4=""),"",IFERROR(O38/O4,"")) | P39: =IF(OR(P38="",P4=""),"",IFERROR(P38/P4,"")) | Q39: =IF(OR(Q38="",Q4=""),"",IFERROR(Q38/Q4,"")) | R39: =IF(OR(R38="",R4=""),"",IFERROR(R38/R4,"")) | S39: =IF(OR(S38="",S4=""),"",IFERROR(S38/S4,"")) | T39: =IF(OR(T38="",T4=""),"",IFERROR(T38/T4,"")) | U39: =IF(OR(U38="",U4=""),"",IFERROR(U38/U4,"")) | V39: =IF(OR(V38="",V4=""),"",IFERROR(V38/V4,"")) | ... X39: =IF(OR(X38="",X4=""),"",IFERROR(X38/X4,""))
A40: 지급수수료 | B40: 고정비
A41: % of Sales | O41: =IF(OR(O40="",O4=""),"",IFERROR(O40/O4,"")) | P41: =IF(OR(P40="",P4=""),"",IFERROR(P40/P4,"")) | Q41: =IF(OR(Q40="",Q4=""),"",IFERROR(Q40/Q4,"")) | R41: =IF(OR(R40="",R4=""),"",IFERROR(R40/R4,"")) | S41: =IF(OR(S40="",S4=""),"",IFERROR(S40/S4,"")) | T41: =IF(OR(T40="",T4=""),"",IFERROR(T40/T4,"")) | U41: =IF(OR(U40="",U4=""),"",IFERROR(U40/U4,"")) | V41: =IF(OR(V40="",V4=""),"",IFERROR(V40/V4,"")) | ... X41: =IF(OR(X40="",X4=""),"",IFERROR(X40/X4,""))
A42: 연구개발비 | B42: 변동비
A43: % of Sales | O43: =IF(OR(O42="",O4=""),"",IFERROR(O42/O4,"")) | P43: =IF(OR(P42="",P4=""),"",IFERROR(P42/P4,"")) | Q43: =IF(OR(Q42="",Q4=""),"",IFERROR(Q42/Q4,"")) | R43: =IF(OR(R42="",R4=""),"",IFERROR(R42/R4,"")) | S43: =IF(OR(S42="",S4=""),"",IFERROR(S42/S4,"")) | T43: =IF(OR(T42="",T4=""),"",IFERROR(T42/T4,"")) | U43: =IF(OR(U42="",U4=""),"",IFERROR(U42/U4,"")) | V43: =IF(OR(V42="",V4=""),"",IFERROR(V42/V4,"")) | ... X43: =IF(OR(X42="",X4=""),"",IFERROR(X42/X4,""))
A44: 기타비용 | B44: 변동비 | O44: =IF(OR(O35="",O36="",O38="",O40="",O42=""),"",IFERROR(O35-O36-O38-O40-O42,"")) | P44: =IF(OR(P35="",P36="",P38="",P40="",P42=""),"",IFERROR(P35-P36-P38-P40-P42,"")) | Q44: =IF(OR(Q35="",Q36="",Q38="",Q40="",Q42=""),"",IFERROR(Q35-Q36-Q38-Q40-Q42,"")) | R44: =IF(OR(R35="",R36="",R38="",R40="",R42=""),"",IFERROR(R35-R36-R38-R40-R42,"")) | S44: =IF(OR(S35="",S36="",S38="",S40="",S42=""),"",IFERROR(S35-S36-S38-S40-S42,"")) | T44: =IF(OR(T35="",T36="",T38="",T40="",T42=""),"",IFERROR(T35-T36-T38-T40-T42,"")) | U44: =IF(OR(U35="",U36="",U38="",U40="",U42=""),"",IFERROR(U35-U36-U38-U40-U42,"")) | V44: =IF(OR(V35="",V36="",V38="",V40="",V42=""),"",IFERROR(V35-V36-V38-V40-V42,"")) | ... X44: =IF(OR(X35="",X36="",X38="",X40="",X42=""),"",IFERROR(X35-X36-X38-X40-X42,""))
A45: % of Sales | O45: =IF(OR(O44="",O4=""),"",IFERROR(O44/O4,"")) | P45: =IF(OR(P44="",P4=""),"",IFERROR(P44/P4,"")) | Q45: =IF(OR(Q44="",Q4=""),"",IFERROR(Q44/Q4,"")) | R45: =IF(OR(R44="",R4=""),"",IFERROR(R44/R4,"")) | S45: =IF(OR(S44="",S4=""),"",IFERROR(S44/S4,"")) | T45: =IF(OR(T44="",T4=""),"",IFERROR(T44/T4,"")) | U45: =IF(OR(U44="",U4=""),"",IFERROR(U44/U4,"")) | V45: =IF(OR(V44="",V4=""),"",IFERROR(V44/V4,"")) | ... X45: =IF(OR(X44="",X4=""),"",IFERROR(X44/X4,""))
A46: 당기순이익 추정
A47: 특별이익 | C47: 0 | D47: 0 | E47: 0 | F47: 137.905 | J47: 101.941 | O47: 0.696 | P47: 0.982 | Q47: 0.752 | R47: 87.492 | S47: 0.453 | T47: 1.563 | U47: 180.199 | V47: 137.905 | W47: 103.157 | X47: 180.658 | Y47: =IF(OR(Y4="",Y48=""),"",IFERROR(Y4*Y48,"")) | Z47: =IF(OR(Z4="",Z48=""),"",IFERROR(Z4*Z48,"")) | AA47: =IF(OR(AA4="",AA48=""),"",IFERROR(AA4*AA48,"")) | AB47: =IF(OR(AB4="",AB48=""),"",IFERROR(AB4*AB48,"")) | AC47: =IF(OR(AC4="",AC48=""),"",IFERROR(AC4*AC48,""))
A48: % of Sales | B48: MW = 최근 3년 평균 | C48: =IF(OR(C47="",C4=""),"",IFERROR(C47/C4,"")) | D48: =IF(OR(D47="",D4=""),"",IFERROR(D47/D4,"")) | E48: =IF(OR(E47="",E4=""),"",IFERROR(E47/E4,"")) | F48: =IF(OR(F47="",F4=""),"",IFERROR(F47/F4,"")) | G48: =IF(OR(G47="",G4=""),"",IFERROR(G47/G4,"")) | H48: =IF(OR(H47="",H4=""),"",IFERROR(H47/H4,"")) | I48: =IF(OR(I47="",I4=""),"",IFERROR(I47/I4,"")) | J48: =IF(OR(J47="",J4=""),"",IFERROR(J47/J4,"")) | ... X48: =IF(OR(X47="",X4=""),"",IFERROR(X47/X4,"")) | Y48: =IFERROR(AVERAGE(V48,W48,X48),"") | Z48: =Y48 | AA48: =Z48 | AB48: =AA48 | AC48: =AB48
A49: 특별손실 | C49: 0.103 | D49: 0.016 | E49: 0.076 | F49: 225.955 | G49: 20.332 | H49: -5.539 | I49: 6.962 | J49: 97.078 | O49: 52.62 | P49: 115.311 | Q49: 82.787 | R49: 37.72 | S49: 37.168 | T49: 115.578 | U49: 0.384 | V49: 226.15 | W49: 118.833 | X49: 57.503 | Y49: =IF(OR(Y4="",Y50=""),"",IFERROR(Y4*Y50,"")) | Z49: =IF(OR(Z4="",Z50=""),"",IFERROR(Z4*Z50,"")) | AA49: =IF(OR(AA4="",AA50=""),"",IFERROR(AA4*AA50,"")) | AB49: =IF(OR(AB4="",AB50=""),"",IFERROR(AB4*AB50,"")) | AC49: =IF(OR(AC4="",AC50=""),"",IFERROR(AC4*AC50,""))
A50: % of Sales | C50: =IF(OR(C49="",C4=""),"",IFERROR(C49/C4,"")) | D50: =IF(OR(D49="",D4=""),"",IFERROR(D49/D4,"")) | E50: =IF(OR(E49="",E4=""),"",IFERROR(E49/E4,"")) | F50: =IF(OR(F49="",F4=""),"",IFERROR(F49/F4,"")) | G50: =IF(OR(G49="",G4=""),"",IFERROR(G49/G4,"")) | H50: =IF(OR(H49="",H4=""),"",IFERROR(H49/H4,"")) | I50: =IF(OR(I49="",I4=""),"",IFERROR(I49/I4,"")) | J50: =IF(OR(J49="",J4=""),"",IFERROR(J49/J4,"")) | ... X50: =IF(OR(X49="",X4=""),"",IFERROR(X49/X4,"")) | Y50: =IFERROR(AVERAGE(V50,W50,X50),"") | Z50: =Y50 | AA50: =Z50 | AB50: =AA50 | AC50: =AB50
A51: 영업외수익 | C51: 202.21 | D51: 75.209 | E51: 134.335 | F51: 52.674 | G51: 136.259 | H51: 110.789 | I51: 118.034 | J51: 48.036 | O51: 201.272 | P51: 246.952 | Q51: 303.108 | R51: 323.166 | S51: 394.536 | T51: 397.023 | U51: 365.153 | V51: 464.428 | W51: 413.118 | X51: 515.499 | Y51: =IF(OR(Y4="",Y52=""),"",IFERROR(Y4*Y52,"")) | Z51: =IF(OR(Z4="",Z52=""),"",IFERROR(Z4*Z52,"")) | AA51: =IF(OR(AA4="",AA52=""),"",IFERROR(AA4*AA52,"")) | AB51: =IF(OR(AB4="",AB52=""),"",IFERROR(AB4*AB52,"")) | AC51: =IF(OR(AC4="",AC52=""),"",IFERROR(AC4*AC52,""))
A52: % of Sales | C52: =IF(OR(C51="",C4=""),"",IFERROR(C51/C4,"")) | D52: =IF(OR(D51="",D4=""),"",IFERROR(D51/D4,"")) | E52: =IF(OR(E51="",E4=""),"",IFERROR(E51/E4,"")) | F52: =IF(OR(F51="",F4=""),"",IFERROR(F51/F4,"")) | G52: =IF(OR(G51="",G4=""),"",IFERROR(G51/G4,"")) | H52: =IF(OR(H51="",H4=""),"",IFERROR(H51/H4,"")) | I52: =IF(OR(I51="",I4=""),"",IFERROR(I51/I4,"")) | J52: =IF(OR(J51="",J4=""),"",IFERROR(J51/J4,"")) | ... X52: =IF(OR(X51="",X4=""),"",IFERROR(X51/X4,"")) | Y52: =IFERROR(AVERAGE(V52,W52,X52),"") | Z52: =Y52 | AA52: =Z52 | AB52: =AA52 | AC52: =AB52
A53: 영업외비용 | C53: 24.483 | D53: 90.466 | E53: -32.069 | F53: 9.386 | G53: 57.741 | H53: 5.35 | I53: 35.116 | J53: 16.384 | O53: 64.18 | P53: 70.498 | Q53: 61.209 | R53: 66.323 | S53: 55.89 | T53: 66.039 | U53: 96.184 | V53: 92.266 | W53: 114.591 | X53: 133.465 | Y53: =IF(OR(Y4="",Y54=""),"",IFERROR(Y4*Y54,"")) | Z53: =IF(OR(Z4="",Z54=""),"",IFERROR(Z4*Z54,"")) | AA53: =IF(OR(AA4="",AA54=""),"",IFERROR(AA4*AA54,"")) | AB53: =IF(OR(AB4="",AB54=""),"",IFERROR(AB4*AB54,"")) | AC53: =IF(OR(AC4="",AC54=""),"",IFERROR(AC4*AC54,""))
A54: % of Sales | C54: =IF(OR(C53="",C4=""),"",IFERROR(C53/C4,"")) | D54: =IF(OR(D53="",D4=""),"",IFERROR(D53/D4,"")) | E54: =IF(OR(E53="",E4=""),"",IFERROR(E53/E4,"")) | F54: =IF(OR(F53="",F4=""),"",IFERROR(F53/F4,"")) | G54: =IF(OR(G53="",G4=""),"",IFERROR(G53/G4,"")) | H54: =IF(OR(H53="",H4=""),"",IFERROR(H53/H4,"")) | I54: =IF(OR(I53="",I4=""),"",IFERROR(I53/I4,"")) | J54: =IF(OR(J53="",J4=""),"",IFERROR(J53/J4,"")) | ... X54: =IF(OR(X53="",X4=""),"",IFERROR(X53/X4,"")) | Y54: =IFERROR(AVERAGE(V54,W54,X54),"") | Z54: =Y54 | AA54: =Z54 | AB54: =AA54 | AC54: =AB54
A55: 법인세비용차감전순이익(손실) | C55: -75.135 | D55: 255.999 | E55: 534.583 | F55: -673.414 | G55: -155.602 | H55: 523.612 | I55: 401.294 | J55: 51.262 | O55: 1776.137 | P55: 1974.736 | Q55: 1554.905 | R55: 1539.213 | S55: 2718.736 | T55: 1224.577 | U55: 817.092 | V55: 42.033 | W55: 820.566 | X55: 1634.098 | Y55: =IF(OR(Y31=""),"",IFERROR(Y31+N(Y47)-N(Y49)+N(Y51)-N(Y53),"")) | Z55: =IF(OR(Z31=""),"",IFERROR(Z31+N(Z47)-N(Z49)+N(Z51)-N(Z53),"")) | AA55: =IF(OR(AA31=""),"",IFERROR(AA31+N(AA47)-N(AA49)+N(AA51)-N(AA53),"")) | AB55: =IF(OR(AB31=""),"",IFERROR(AB31+N(AB47)-N(AB49)+N(AB51)-N(AB53),"")) | AC55: =IF(OR(AC31=""),"",IFERROR(AC31+N(AC47)-N(AC49)+N(AC51)-N(AC53),""))
A56: YoY | G56: =IF(OR(G55="",C55=""),"",IF(C55<=0,"",IFERROR(G55/C55-1,""))) | H56: =IF(OR(H55="",D55=""),"",IF(D55<=0,"",IFERROR(H55/D55-1,""))) | I56: =IF(OR(I55="",E55=""),"",IF(E55<=0,"",IFERROR(I55/E55-1,""))) | J56: =IF(OR(J55="",F55=""),"",IF(F55<=0,"",IFERROR(J55/F55-1,""))) | K56: =IF(OR(K55="",G55=""),"",IF(G55<=0,"",IFERROR(K55/G55-1,""))) | L56: =IF(OR(L55="",H55=""),"",IF(H55<=0,"",IFERROR(L55/H55-1,""))) | M56: =IF(OR(M55="",I55=""),"",IF(I55<=0,"",IFERROR(M55/I55-1,""))) | N56: =IF(OR(N55="",J55=""),"",IF(J55<=0,"",IFERROR(N55/J55-1,""))) | P56: =IF(OR(P55="",O55=""),"",IF(O55<=0,"",IFERROR(P55/O55-1,""))) | Q56: =IF(OR(Q55="",P55=""),"",IF(P55<=0,"",IFERROR(Q55/P55-1,""))) | R56: =IF(OR(R55="",Q55=""),"",IF(Q55<=0,"",IFERROR(R55/Q55-1,""))) | S56: =IF(OR(S55="",R55=""),"",IF(R55<=0,"",IFERROR(S55/R55-1,""))) | T56: =IF(OR(T55="",S55=""),"",IF(S55<=0,"",IFERROR(T55/S55-1,""))) | U56: =IF(OR(U55="",T55=""),"",IF(T55<=0,"",IFERROR(U55/T55-1,""))) | V56: =IF(OR(V55="",U55=""),"",IF(U55<=0,"",IFERROR(V55/U55-1,""))) | W56: =IF(OR(W55="",V55=""),"",IF(V55<=0,"",IFERROR(W55/V55-1,""))) | ... AC56: =IF(OR(AC55="",AB55=""),"",IF(AB55<=0,"",IFERROR(AC55/AB55-1,"")))
A57: 법인세비용(수익) | C57: 142.943 | D57: 113.025 | E57: 70.758 | F57: 33.375 | G57: 143.34 | H57: 197.118 | I57: 80.107 | J57: -24.944 | O57: 552.367 | P57: 561.38 | Q57: 576.596 | R57: 457.031 | S57: 753.519 | T57: 434.584 | U57: 397.201 | V57: 360.101 | W57: 395.621 | X57: 633.655 | Y57: =IF(OR(Y55="",Y58=""),"",IFERROR(MAX(Y55,0)*Y58,"")) | Z57: =IF(OR(Z55="",Z58=""),"",IFERROR(MAX(Z55,0)*Z58,"")) | AA57: =IF(OR(AA55="",AA58=""),"",IFERROR(MAX(AA55,0)*AA58,"")) | AB57: =IF(OR(AB55="",AB58=""),"",IFERROR(MAX(AB55,0)*AB58,"")) | AC57: =IF(OR(AC55="",AC58=""),"",IFERROR(MAX(AC55,0)*AC58,""))
A58: 법인세율 | B58: MW 기본 30% | C58: =IF(OR(C57="",C55=""),"",IFERROR(C57/C55,"")) | D58: =IF(OR(D57="",D55=""),"",IFERROR(D57/D55,"")) | E58: =IF(OR(E57="",E55=""),"",IFERROR(E57/E55,"")) | F58: =IF(OR(F57="",F55=""),"",IFERROR(F57/F55,"")) | G58: =IF(OR(G57="",G55=""),"",IFERROR(G57/G55,"")) | H58: =IF(OR(H57="",H55=""),"",IFERROR(H57/H55,"")) | I58: =IF(OR(I57="",I55=""),"",IFERROR(I57/I55,"")) | J58: =IF(OR(J57="",J55=""),"",IFERROR(J57/J55,"")) | ... X58: =IF(OR(X57="",X55=""),"",IFERROR(X57/X55,"")) | Y58: 0.3 | Z58: 0.3 | AA58: 0.3 | AB58: 0.3 | AC58: 0.3
A59: 당기순이익(손실) | C59: -218.078 | D59: 142.975 | E59: 463.824 | F59: -706.789 | G59: -298.942 | H59: 326.493 | I59: 321.188 | J59: 76.205 | O59: 1223.769 | P59: 1413.355 | Q59: 978.309 | R59: 1082.181 | S59: 1965.216 | T59: 789.993 | U59: 419.891 | V59: -318.068 | W59: 424.944 | X59: 1000.443 | Y59: =IF(OR(Y55=""),"",IFERROR(Y55-Y57,"")) | Z59: =IF(OR(Z55=""),"",IFERROR(Z55-Z57,"")) | AA59: =IF(OR(AA55=""),"",IFERROR(AA55-AA57,"")) | AB59: =IF(OR(AB55=""),"",IFERROR(AB55-AB57,"")) | AC59: =IF(OR(AC55=""),"",IFERROR(AC55-AC57,""))
A60: YoY | G60: =IF(OR(G59="",C59=""),"",IF(C59<=0,"",IFERROR(G59/C59-1,""))) | H60: =IF(OR(H59="",D59=""),"",IF(D59<=0,"",IFERROR(H59/D59-1,""))) | I60: =IF(OR(I59="",E59=""),"",IF(E59<=0,"",IFERROR(I59/E59-1,""))) | J60: =IF(OR(J59="",F59=""),"",IF(F59<=0,"",IFERROR(J59/F59-1,""))) | K60: =IF(OR(K59="",G59=""),"",IF(G59<=0,"",IFERROR(K59/G59-1,""))) | L60: =IF(OR(L59="",H59=""),"",IF(H59<=0,"",IFERROR(L59/H59-1,""))) | M60: =IF(OR(M59="",I59=""),"",IF(I59<=0,"",IFERROR(M59/I59-1,""))) | N60: =IF(OR(N59="",J59=""),"",IF(J59<=0,"",IFERROR(N59/J59-1,""))) | P60: =IF(OR(P59="",O59=""),"",IF(O59<=0,"",IFERROR(P59/O59-1,""))) | Q60: =IF(OR(Q59="",P59=""),"",IF(P59<=0,"",IFERROR(Q59/P59-1,""))) | R60: =IF(OR(R59="",Q59=""),"",IF(Q59<=0,"",IFERROR(R59/Q59-1,""))) | S60: =IF(OR(S59="",R59=""),"",IF(R59<=0,"",IFERROR(S59/R59-1,""))) | T60: =IF(OR(T59="",S59=""),"",IF(S59<=0,"",IFERROR(T59/S59-1,""))) | U60: =IF(OR(U59="",T59=""),"",IF(T59<=0,"",IFERROR(U59/T59-1,""))) | V60: =IF(OR(V59="",U59=""),"",IF(U59<=0,"",IFERROR(V59/U59-1,""))) | W60: =IF(OR(W59="",V59=""),"",IF(V59<=0,"",IFERROR(W59/V59-1,""))) | ... AC60: =IF(OR(AC59="",AB59=""),"",IF(AB59<=0,"",IFERROR(AC59/AB59-1,"")))
A61: 지배주주 순이익 | C61: -218.078 | D61: 142.975 | E61: 463.824 | F61: -706.789 | G61: -298.942 | H61: 326.493 | I61: 321.188 | J61: 76.205 | O61: 1204.004 | P61: 1402.847 | Q61: 963.042 | R61: 1081.679 | S61: 1963.34 | T61: 788.782 | U61: 419.79 | V61: -318.068 | W61: 424.944 | X61: 1000.443 | Y61: =IF(OR(Y59="",Y62=""),"",IFERROR(Y59*Y62,"")) | Z61: =IF(OR(Z59="",Z62=""),"",IFERROR(Z59*Z62,"")) | AA61: =IF(OR(AA59="",AA62=""),"",IFERROR(AA59*AA62,"")) | AB61: =IF(OR(AB59="",AB62=""),"",IFERROR(AB59*AB62,"")) | AC61: =IF(OR(AC59="",AC62=""),"",IFERROR(AC59*AC62,""))
A62: 지배주주 순이익률 | B62: MW 기본 100% | C62: =IF(OR(C61="",C59=""),"",IFERROR(C61/C59,"")) | D62: =IF(OR(D61="",D59=""),"",IFERROR(D61/D59,"")) | E62: =IF(OR(E61="",E59=""),"",IFERROR(E61/E59,"")) | F62: =IF(OR(F61="",F59=""),"",IFERROR(F61/F59,"")) | G62: =IF(OR(G61="",G59=""),"",IFERROR(G61/G59,"")) | H62: =IF(OR(H61="",H59=""),"",IFERROR(H61/H59,"")) | I62: =IF(OR(I61="",I59=""),"",IFERROR(I61/I59,"")) | J62: =IF(OR(J61="",J59=""),"",IFERROR(J61/J59,"")) | ... X62: =IF(OR(X61="",X59=""),"",IFERROR(X61/X59,"")) | Y62: 1 | Z62: 1 | AA62: 1 | AB62: 1 | AC62: 1
A63: 지배주주 순이익 YoY | G63: =IF(OR(G61="",C61=""),"",IF(C61<=0,"",IFERROR(G61/C61-1,""))) | H63: =IF(OR(H61="",D61=""),"",IF(D61<=0,"",IFERROR(H61/D61-1,""))) | I63: =IF(OR(I61="",E61=""),"",IF(E61<=0,"",IFERROR(I61/E61-1,""))) | J63: =IF(OR(J61="",F61=""),"",IF(F61<=0,"",IFERROR(J61/F61-1,""))) | K63: =IF(OR(K61="",G61=""),"",IF(G61<=0,"",IFERROR(K61/G61-1,""))) | L63: =IF(OR(L61="",H61=""),"",IF(H61<=0,"",IFERROR(L61/H61-1,""))) | M63: =IF(OR(M61="",I61=""),"",IF(I61<=0,"",IFERROR(M61/I61-1,""))) | N63: =IF(OR(N61="",J61=""),"",IF(J61<=0,"",IFERROR(N61/J61-1,""))) | P63: =IF(OR(P61="",O61=""),"",IF(O61<=0,"",IFERROR(P61/O61-1,""))) | Q63: =IF(OR(Q61="",P61=""),"",IF(P61<=0,"",IFERROR(Q61/P61-1,""))) | R63: =IF(OR(R61="",Q61=""),"",IF(Q61<=0,"",IFERROR(R61/Q61-1,""))) | S63: =IF(OR(S61="",R61=""),"",IF(R61<=0,"",IFERROR(S61/R61-1,""))) | T63: =IF(OR(T61="",S61=""),"",IF(S61<=0,"",IFERROR(T61/S61-1,""))) | U63: =IF(OR(U61="",T61=""),"",IF(T61<=0,"",IFERROR(U61/T61-1,""))) | V63: =IF(OR(V61="",U61=""),"",IF(U61<=0,"",IFERROR(V61/U61-1,""))) | W63: =IF(OR(W61="",V61=""),"",IF(V61<=0,"",IFERROR(W61/V61-1,""))) | ... AC63: =IF(OR(AC61="",AB61=""),"",IF(AB61<=0,"",IFERROR(AC61/AB61-1,"")))
A64: 목표주가 산출
A65: 현재 주가 (2026.10.28) | B65: 750
A66: 발행주식수 (보통주) | B66: 31459692
A67: 시가총액 (백만엔) | B67: =IF(OR(B65="",B66=""),"",B65*B66/1000000.0)
A68: OPM | O68: =IF(O32="","",O32) | P68: =IF(P32="","",P32) | Q68: =IF(Q32="","",Q32) | R68: =IF(R32="","",R32) | S68: =IF(S32="","",S32) | T68: =IF(T32="","",T32) | U68: =IF(U32="","",U32) | V68: =IF(V32="","",V32) | ... AC68: =IF(AC32="","",AC32)
A69: 지배주주 순이익 증가율 | P69: =IF(OR(P61="",O61=""),"",IFERROR(P61/O61-1,"")) | Q69: =IF(OR(Q61="",P61=""),"",IFERROR(Q61/P61-1,"")) | R69: =IF(OR(R61="",Q61=""),"",IFERROR(R61/Q61-1,"")) | S69: =IF(OR(S61="",R61=""),"",IFERROR(S61/R61-1,"")) | T69: =IF(OR(T61="",S61=""),"",IFERROR(T61/S61-1,"")) | U69: =IF(OR(U61="",T61=""),"",IFERROR(U61/T61-1,"")) | V69: =IF(OR(V61="",U61=""),"",IFERROR(V61/U61-1,"")) | W69: =IF(OR(W61="",V61=""),"",IFERROR(W61/V61-1,"")) | ... AC69: =IF(OR(AC61="",AB61=""),"",IFERROR(AC61/AB61-1,""))
A70: P/E (현재 주가) | B70: 시총 ÷ 지배순이익 | X70: =IF(OR($B$67="",X61=""),"",IFERROR($B$67/X61,"")) | Y70: =IF(OR($B$67="",Y61=""),"",IFERROR($B$67/Y61,"")) | Z70: =IF(OR($B$67="",Z61=""),"",IFERROR($B$67/Z61,"")) | AA70: =IF(OR($B$67="",AA61=""),"",IFERROR($B$67/AA61,"")) | AB70: =IF(OR($B$67="",AB61=""),"",IFERROR($B$67/AB61,"")) | AC70: =IF(OR($B$67="",AC61=""),"",IFERROR($B$67/AC61,""))
A71: Target P/E | B71: 직접 입력
A72: EPS | B72: 지배순이익 ÷ 주식수 | O72: =IF(OR(O61="",$B$66=""),"",IFERROR(O61*1000000.0/$B$66,"")) | P72: =IF(OR(P61="",$B$66=""),"",IFERROR(P61*1000000.0/$B$66,"")) | Q72: =IF(OR(Q61="",$B$66=""),"",IFERROR(Q61*1000000.0/$B$66,"")) | R72: =IF(OR(R61="",$B$66=""),"",IFERROR(R61*1000000.0/$B$66,"")) | S72: =IF(OR(S61="",$B$66=""),"",IFERROR(S61*1000000.0/$B$66,"")) | T72: =IF(OR(T61="",$B$66=""),"",IFERROR(T61*1000000.0/$B$66,"")) | U72: =IF(OR(U61="",$B$66=""),"",IFERROR(U61*1000000.0/$B$66,"")) | V72: =IF(OR(V61="",$B$66=""),"",IFERROR(V61*1000000.0/$B$66,"")) | ... AC72: =IF(OR(AC61="",$B$66=""),"",IFERROR(AC61*1000000.0/$B$66,""))
A73: 목표주가 | Y73: =IF(OR(Y72="",Y71=""),"",IFERROR(Y72*Y71,"")) | Z73: =IF(OR(Z72="",Z71=""),"",IFERROR(Z72*Z71,"")) | AA73: =IF(OR(AA72="",AA71=""),"",IFERROR(AA72*AA71,"")) | AB73: =IF(OR(AB72="",AB71=""),"",IFERROR(AB72*AB71,"")) | AC73: =IF(OR(AC72="",AC71=""),"",IFERROR(AC72*AC71,""))
A74: 상승여력 | Y74: =IF(OR(Y73="",$B$65=""),"",IFERROR(Y73/$B$65-1,"")) | Z74: =IF(OR(Z73="",$B$65=""),"",IFERROR(Z73/$B$65-1,"")) | AA74: =IF(OR(AA73="",$B$65=""),"",IFERROR(AA73/$B$65-1,"")) | AB74: =IF(OR(AB73="",$B$65=""),"",IFERROR(AB73/$B$65-1,"")) | AC74: =IF(OR(AC73="",$B$65=""),"",IFERROR(AC73/$B$65-1,""))
A75: 자산가치 산출 | B75: 최신 분기 BS
A76: 현금및현금성자산 | X76: ='재무상태표'!G6 | Y76: ='재무상태표'!G6 | Z76: ='재무상태표'!G6 | AA76: ='재무상태표'!G6 | AB76: ='재무상태표'!G6 | AC76: ='재무상태표'!G6
A77: 단기금융상품 | X77: ='재무상태표'!G7 | Y77: ='재무상태표'!G7 | Z77: ='재무상태표'!G7 | AA77: ='재무상태표'!G7 | AB77: ='재무상태표'!G7 | AC77: ='재무상태표'!G7
A78: 투자부동산 | X78: ='재무상태표'!G14 | Y78: ='재무상태표'!G14 | Z78: ='재무상태표'!G14 | AA78: ='재무상태표'!G14 | AB78: ='재무상태표'!G14 | AC78: ='재무상태표'!G14
A79: 지배자본 | X79: ='재무상태표'!G31 | Y79: ='재무상태표'!G31 | Z79: ='재무상태표'!G31 | AA79: ='재무상태표'!G31 | AB79: ='재무상태표'!G31 | AC79: ='재무상태표'!G31
A80: 부채 | X80: ='재무상태표'!G27 | Y80: ='재무상태표'!G27 | Z80: ='재무상태표'!G27 | AA80: ='재무상태표'!G27 | AB80: ='재무상태표'!G27 | AC80: ='재무상태표'!G27
A81: 부채비율 | X81: =IF(OR(X80="",X79=""),"",IFERROR(X80/X79,"")) | Y81: =IF(OR(Y80="",Y79=""),"",IFERROR(Y80/Y79,"")) | Z81: =IF(OR(Z80="",Z79=""),"",IFERROR(Z80/Z79,"")) | AA81: =IF(OR(AA80="",AA79=""),"",IFERROR(AA80/AA79,"")) | AB81: =IF(OR(AB80="",AB79=""),"",IFERROR(AB80/AB79,"")) | AC81: =IF(OR(AC80="",AC79=""),"",IFERROR(AC80/AC79,""))
A82: 자산가치 | B82: 현금+단기금융+투자부동산 | X82: =SUM(X76,X77,X78) | Y82: =SUM(Y76,Y77,Y78) | Z82: =SUM(Z76,Z77,Z78) | AA82: =SUM(AA76,AA77,AA78) | AB82: =SUM(AB76,AB77,AB78) | AC82: =SUM(AC76,AC77,AC78)
A83: 기업가치 산출
A84: 목표 시가총액 (P/E) | B84: 지배순이익 × Target P/E | Y84: =IF(OR(Y61="",Y71=""),"",IFERROR(Y61*Y71,"")) | Z84: =IF(OR(Z61="",Z71=""),"",IFERROR(Z61*Z71,"")) | AA84: =IF(OR(AA61="",AA71=""),"",IFERROR(AA61*AA71,"")) | AB84: =IF(OR(AB61="",AB71=""),"",IFERROR(AB61*AB71,"")) | AC84: =IF(OR(AC61="",AC71=""),"",IFERROR(AC61*AC71,""))
A85: 기업가치 | B85: 목표시총 + 자산가치 | Y85: =IF(OR(Y84=""),"",IFERROR(Y84+Y82,"")) | Z85: =IF(OR(Z84=""),"",IFERROR(Z84+Z82,"")) | AA85: =IF(OR(AA84=""),"",IFERROR(AA84+AA82,"")) | AB85: =IF(OR(AB84=""),"",IFERROR(AB84+AB82,"")) | AC85: =IF(OR(AC84=""),"",IFERROR(AC84+AC82,""))
A86: 현재 시가총액 | Y86: =$B$67 | Z86: =$B$67 | AA86: =$B$67 | AB86: =$B$67 | AC86: =$B$67
A87: 상승여력 | Y87: =IF(OR(Y85="",Y86=""),"",IFERROR(Y85/Y86-1,"")) | Z87: =IF(OR(Z85="",Z86=""),"",IFERROR(Z85/Z86-1,"")) | AA87: =IF(OR(AA85="",AA86=""),"",IFERROR(AA85/AA86-1,"")) | AB87: =IF(OR(AB85="",AB86=""),"",IFERROR(AB85/AB86-1,"")) | AC87: =IF(OR(AC85="",AC86=""),"",IFERROR(AC85/AC86-1,""))
A89: 출처
A90: 결산단신 XBRL(TDnet·JPX 보관소) — 쓴 문서는 '출처' 시트
A91: 분기 = 누계에서 앞 분기를 뺀 3개월 값
A92: 주가: 야후 파이낸스 일봉 2026.10.28
A94: 손익계산서 · 전 항목 | B94: 분기 = 3개월 단독
A95: 항목 | B95: 참고 | C95: 2025.1Q | D95: 2025.2Q | E95: 2025.3Q | F95: 2025.4Q | G95: 2026.1Q | H95: 2026.2Q | I95: 2026.3Q | J95: 2026.4Q | K95: 2027.1Q | L95: 2027.2Q | M95: 2027.3Q | N95: 2027.4Q | O95: 2018 | P95: 2019 | Q95: 2020 | R95: 2021 | S95: 2022 | T95: 2023 | U95: 2024 | V95: 2025 | W95: 2026 | X95: 2027 | Y95: 2028(MW) | Z95: 2029(MW) | AA95: 2030(MW) | AB95: 2031(MW) | AC95: 2032(MW)
A96: 매출액 | C96: 8785.176 | D96: 9734.881 | E96: 10261.756 | F96: 10771.256 | G96: 8251.473 | H96: 9715.757 | I96: 9934.631 | J96: 11737.639 | S96: 9973.372 | T96: 7701.035 | U96: 10803.535 | V96: 10771.256 | W96: 11737.639
A97: YoY | B97: 전년 같은 분기·전년 대비 | G97: =IF(OR(G96="",C96=""),"",IF(C96<=0,"",IFERROR(G96/C96-1,""))) | H97: =IF(OR(H96="",D96=""),"",IF(D96<=0,"",IFERROR(H96/D96-1,""))) | I97: =IF(OR(I96="",E96=""),"",IF(E96<=0,"",IFERROR(I96/E96-1,""))) | J97: =IF(OR(J96="",F96=""),"",IF(F96<=0,"",IFERROR(J96/F96-1,""))) | S97: =IF(OR(S96="",R96=""),"",IF(R96<=0,"",IFERROR(S96/R96-1,""))) | T97: =IF(OR(T96="",S96=""),"",IF(S96<=0,"",IFERROR(T96/S96-1,""))) | U97: =IF(OR(U96="",T96=""),"",IF(T96<=0,"",IFERROR(U96/T96-1,""))) | V97: =IF(OR(V96="",U96=""),"",IF(U96<=0,"",IFERROR(V96/U96-1,""))) | W97: =IF(OR(W96="",V96=""),"",IF(V96<=0,"",IFERROR(W96/V96-1,"")))
A98: 매출원가 | C98: 5537.849 | D98: 5973.641 | E98: 6129.678 | F98: 7595.652 | G98: 5035.836 | H98: 5894.876 | I98: 6108.146 | J98: 7735.502 | S98: 5363.299 | T98: 4649.623 | U98: 7241.392 | V98: 7595.652 | W98: 7735.502
A99: YoY | B99: 전년 같은 분기·전년 대비 | G99: =IF(OR(G98="",C98=""),"",IF(G98*C98<=0,"",IFERROR(G98/C98-1,""))) | H99: =IF(OR(H98="",D98=""),"",IF(H98*D98<=0,"",IFERROR(H98/D98-1,""))) | I99: =IF(OR(I98="",E98=""),"",IF(I98*E98<=0,"",IFERROR(I98/E98-1,""))) | J99: =IF(OR(J98="",F98=""),"",IF(J98*F98<=0,"",IFERROR(J98/F98-1,""))) | S99: =IF(OR(S98="",R98=""),"",IF(S98*R98<=0,"",IFERROR(S98/R98-1,""))) | T99: =IF(OR(T98="",S98=""),"",IF(T98*S98<=0,"",IFERROR(T98/S98-1,""))) | U99: =IF(OR(U98="",T98=""),"",IF(U98*T98<=0,"",IFERROR(U98/T98-1,""))) | V99: =IF(OR(V98="",U98=""),"",IF(V98*U98<=0,"",IFERROR(V98/U98-1,""))) | W99: =IF(OR(W98="",V98=""),"",IF(W98*V98<=0,"",IFERROR(W98/V98-1,"")))
A100: 매출총이익 | C100: 3247.326 | D100: 3761.24 | E100: 4132.079 | F100: 3175.603 | G100: 3215.636 | H100: 3820.881 | I100: 3826.485 | J100: 4002.138 | S100: 4610.072 | T100: 3051.412 | U100: 3562.143 | V100: 3175.603 | W100: 4002.138
A101: YoY | B101: 전년 같은 분기·전년 대비 | G101: =IF(OR(G100="",C100=""),"",IF(C100<=0,"",IFERROR(G100/C100-1,""))) | H101: =IF(OR(H100="",D100=""),"",IF(D100<=0,"",IFERROR(H100/D100-1,""))) | I101: =IF(OR(I100="",E100=""),"",IF(E100<=0,"",IFERROR(I100/E100-1,""))) | J101: =IF(OR(J100="",F100=""),"",IF(F100<=0,"",IFERROR(J100/F100-1,""))) | S101: =IF(OR(S100="",R100=""),"",IF(R100<=0,"",IFERROR(S100/R100-1,""))) | T101: =IF(OR(T100="",S100=""),"",IF(S100<=0,"",IFERROR(T100/S100-1,""))) | U101: =IF(OR(U100="",T100=""),"",IF(T100<=0,"",IFERROR(U100/T100-1,""))) | V101: =IF(OR(V100="",U100=""),"",IF(U100<=0,"",IFERROR(V100/U100-1,""))) | W101: =IF(OR(W100="",V100=""),"",IF(V100<=0,"",IFERROR(W100/V100-1,"")))
A102: 판매비와 관리비 | C102: 3500.086 | D102: 3489.966 | E102: 3763.823 | F102: 3804.256 | G102: 3429.424 | H102: 3408.246 | I102: 3502.363 | J102: 3987.392 | S102: 2974.734 | T102: 2125.22 | U102: 2947.929 | V102: 3804.256 | W102: 3987.392
...

Sheet 재무상태표
A1: 7962 재무상태표
A2: 재무비율은 기말 잔액 기준 · 분기 손익은 최근 4분기 합산(TTM) | B2: (단위: 백만엔)
A3: 항목 | B3: 참고 | C3: 2026.1Q | D3: 2026.2Q | E3: 2026.3Q | F3: 2026.4Q | G3: 2027.1Q | H3: 2023 | I3: 2024 | J3: 2025 | K3: 2026
A4: 자산
A5: 유동자산 | C5: 24063.443 | D5: 24329.621 | E5: 25483.552 | F5: 26083.852 | G5: 24305.467 | H5: 26357.806 | I5: 26624.746 | J5: 26347.865 | K5: 26083.852
A6: 현금및현금성자산 | C6: 6831.528 | D6: 6747.841 | E6: 6984.794 | F6: 7398.912 | G6: 6832.976 | H6: 6888.375 | I6: 7103.652 | J6: 7742.985 | K6: 7398.912
A7: 단기금융상품
A8: 매출채권 | C8: 5159.478 | D8: 4140.375 | E8: 5354.194 | F8: 5232.014 | G8: 5405.64 | H8: 5285.919 | I8: 5620.898 | J8: 5192.359 | K8: 5232.014
A9: 재고자산 | C9: 11192.747 | D9: 12468.9 | E9: 12218.751 | F9: 12435.316 | G9: 10981.945 | H9: 12978.227 | I9: 13033.338 | J9: 12386.749 | K9: 12435.316
A10: 기타유동자산 | B10: 총계 − 위 항목 | C10: =IF(OR(C5=""),"",IFERROR(C5-SUM(C6,C7,C8,C9),"")) | D10: =IF(OR(D5=""),"",IFERROR(D5-SUM(D6,D7,D8,D9),"")) | E10: =IF(OR(E5=""),"",IFERROR(E5-SUM(E6,E7,E8,E9),"")) | F10: =IF(OR(F5=""),"",IFERROR(F5-SUM(F6,F7,F8,F9),"")) | G10: =IF(OR(G5=""),"",IFERROR(G5-SUM(G6,G7,G8,G9),"")) | H10: =IF(OR(H5=""),"",IFERROR(H5-SUM(H6,H7,H8,H9),"")) | I10: =IF(OR(I5=""),"",IFERROR(I5-SUM(I6,I7,I8,I9),"")) | J10: =IF(OR(J5=""),"",IFERROR(J5-SUM(J6,J7,J8,J9),"")) | K10: =IF(OR(K5=""),"",IFERROR(K5-SUM(K6,K7,K8,K9),""))
A11: 비유동자산 | C11: 11449.723 | D11: 12045.696 | E11: 12479.963 | F11: 12756.019 | G11: 13046.618 | H11: 11608.368 | I11: 11926.237 | J11: 11963.919 | K11: 12756.019
A12: 유형자산 | C12: 4111.615 | D12: 4103.731 | E12: 4170.351 | F12: 4166.872 | G12: 4189.54 | H12: 4444.374 | I12: 4304.689 | J12: 4221.397 | K12: 4166.872
A13: 무형자산 | C13: 1824.23 | D13: 1777.928 | E13: 1712.246 | F13: 1719.196 | G13: 1646.702 | H13: 2214.67 | I13: 2106.85 | J13: 2032.081 | K13: 1719.196
A14: 투자부동산
A15: 기타비유동자산 | B15: 총계 − 위 항목 | C15: =IF(OR(C11=""),"",IFERROR(C11-SUM(C12,C13,C14),"")) | D15: =IF(OR(D11=""),"",IFERROR(D11-SUM(D12,D13,D14),"")) | E15: =IF(OR(E11=""),"",IFERROR(E11-SUM(E12,E13,E14),"")) | F15: =IF(OR(F11=""),"",IFERROR(F11-SUM(F12,F13,F14),"")) | G15: =IF(OR(G11=""),"",IFERROR(G11-SUM(G12,G13,G14),"")) | H15: =IF(OR(H11=""),"",IFERROR(H11-SUM(H12,H13,H14),"")) | I15: =IF(OR(I11=""),"",IFERROR(I11-SUM(I12,I13,I14),"")) | J15: =IF(OR(J11=""),"",IFERROR(J11-SUM(J12,J13,J14),"")) | K15: =IF(OR(K11=""),"",IFERROR(K11-SUM(K12,K13,K14),""))
A16: 자산총계 | C16: 35513.167 | D16: 36375.317 | E16: 37963.515 | F16: 38839.871 | G16: 37352.086 | H16: 37966.175 | I16: 38550.983 | J16: 38311.785 | K16: 38839.871
A17: 부채
A18: 유동부채 | C18: 8210.456 | D18: 9155.888 | E18: 9664.631 | F18: 10263.576 | G18: 7676.381 | H18: 9736.854 | I18: 10168.248 | J18: 10796.674 | K18: 10263.576
A19: 매입채무 | C19: 1140.419 | D19: 1376.193 | E19: 1391.589 | F19: 1296.677 | G19: 1311.242 | H19: 1736.058 | I19: 1401.556 | J19: 1702.479 | K19: 1296.677
A20: 단기차입금 | C20: 4540 | D20: 5270 | E20: 5800 | F20: 6230 | G20: 3500 | H20: 5660 | I20: 6100 | J20: 6440 | K20: 6230
A21: 유동성장기부채 | C21: 437.806 | D21: 599.233 | E21: 437.806 | F21: 600.003 | G21: 437.806 | H21: 451.89 | I21: 650.316 | J21: 599.233 | K21: 600.003
A22: 기타유동부채 | B22: 총계 − 위 항목 | C22: =IF(OR(C18=""),"",IFERROR(C18-SUM(C19,C20,C21),"")) | D22: =IF(OR(D18=""),"",IFERROR(D18-SUM(D19,D20,D21),"")) | E22: =IF(OR(E18=""),"",IFERROR(E18-SUM(E19,E20,E21),"")) | F22: =IF(OR(F18=""),"",IFERROR(F18-SUM(F19,F20,F21),"")) | G22: =IF(OR(G18=""),"",IFERROR(G18-SUM(G19,G20,G21),"")) | H22: =IF(OR(H18=""),"",IFERROR(H18-SUM(H19,H20,H21),"")) | I22: =IF(OR(I18=""),"",IFERROR(I18-SUM(I19,I20,I21),"")) | J22: =IF(OR(J18=""),"",IFERROR(J18-SUM(J19,J20,J21),"")) | K22: =IF(OR(K18=""),"",IFERROR(K18-SUM(K19,K20,K21),""))
A23: 비유동부채 | C23: 3250.422 | D23: 3189.507 | E23: 3425.348 | F23: 3330.546 | G23: 3443.01 | H23: 3965.5 | I23: 3584.173 | J23: 3262.793 | K23: 3330.546
A24: 장기차입금 | C24: 1300.482 | D24: 1083.889 | E24: 1081.579 | F24: 864.986 | G24: 862.676 | H24: 2322.347 | I24: 1740.598 | J24: 1302.792 | K24: 864.986
A25: 사채
A26: 기타비유동부채 | B26: 총계 − 위 항목 | C26: =IF(OR(C23=""),"",IFERROR(C23-SUM(C24,C25),"")) | D26: =IF(OR(D23=""),"",IFERROR(D23-SUM(D24,D25),"")) | E26: =IF(OR(E23=""),"",IFERROR(E23-SUM(E24,E25),"")) | F26: =IF(OR(F23=""),"",IFERROR(F23-SUM(F24,F25),"")) | G26: =IF(OR(G23=""),"",IFERROR(G23-SUM(G24,G25),"")) | H26: =IF(OR(H23=""),"",IFERROR(H23-SUM(H24,H25),"")) | I26: =IF(OR(I23=""),"",IFERROR(I23-SUM(I24,I25),"")) | J26: =IF(OR(J23=""),"",IFERROR(J23-SUM(J24,J25),"")) | K26: =IF(OR(K23=""),"",IFERROR(K23-SUM(K24,K25),""))
A27: 부채총계 | C27: 11460.879 | D27: 12345.396 | E27: 13089.979 | F27: 13594.122 | G27: 11119.391 | H27: 13702.354 | I27: 13752.422 | J27: 14059.468 | K27: 13594.122
A28: 총차입금 | B28: 단기+유동성장기+장기+사채 | C28: =SUM(C20,C21,C24,C25) | D28: =SUM(D20,D21,D24,D25) | E28: =SUM(E20,E21,E24,E25) | F28: =SUM(F20,F21,F24,F25) | G28: =SUM(G20,G21,G24,G25) | H28: =SUM(H20,H21,H24,H25) | I28: =SUM(I20,I21,I24,I25) | J28: =SUM(J20,J21,J24,J25) | K28: =SUM(K20,K21,K24,K25)
A29: 순차입금 | B29: 음수 = 순현금 | C29: =C28-C6-N(C7) | D29: =D28-D6-N(D7) | E29: =E28-E6-N(E7) | F29: =F28-F6-N(F7) | G29: =G28-G6-N(G7) | H29: =H28-H6-N(H7) | I29: =I28-I6-N(I7) | J29: =J28-J6-N(J7) | K29: =K28-K6-N(K7)
A30: 자본
A31: 지배주주지분 | C31: 23965.2 | D31: 23942.833 | E31: 24786.447 | F31: 25158.661 | G31: 26145.606 | H31: 24176.732 | I31: 24711.472 | J31: 24165.229 | K31: 25158.661
A32: 자본금 | C32: 1978.69 | D32: 1978.69 | E32: 1978.69 | F32: 1978.69 | G32: 1978.69 | H32: 1978.69 | I32: 1978.69 | J32: 1978.69 | K32: 1978.69
A33: 이익잉여금 | C33: 21593.605 | D33: 21097.779 | E33: 21423.05 | F33: 21547.117 | G33: 22198.821 | H33: 21925.214 | I33: 21806.379 | J33: 21557.382 | K33: 21547.117
A34: 비지배지분 | H34: 0
A35: 자본총계 | C35: 24052.288 | D35: 24029.921 | E35: 24873.535 | F35: 25245.749 | G35: 26232.694 | H35: 24263.82 | I35: 24798.56 | J35: 24252.317 | K35: 25245.749
A36: 현금흐름 요약 | B36: 분기 = TTM (있을 때만)
A37: 영업활동현금흐름 | D37: 840.585 | F37: 1468.981 | H37: -1278.303 | I37: 166.267 | J37: 1047.192 | K37: 1468.981
A38: CAPEX (유·무형 취득) | B38: 양수로 입력 | F38: 890.696 | H38: 798.487 | I38: 636.659 | J38: 617.261 | K38: 890.696
A39: FCF | C39: =IF(OR(C37="",C38=""),"",IFERROR(C37-C38,"")) | D39: =IF(OR(D37="",D38=""),"",IFERROR(D37-D38,"")) | E39: =IF(OR(E37="",E38=""),"",IFERROR(E37-E38,"")) | F39: =IF(OR(F37="",F38=""),"",IFERROR(F37-F38,"")) | G39: =IF(OR(G37="",G38=""),"",IFERROR(G37-G38,"")) | H39: =IF(OR(H37="",H38=""),"",IFERROR(H37-H38,"")) | I39: =IF(OR(I37="",I38=""),"",IFERROR(I37-I38,"")) | J39: =IF(OR(J37="",J38=""),"",IFERROR(J37-J38,"")) | K39: =IF(OR(K37="",K38=""),"",IFERROR(K37-K38,""))
A40: 배당금 지급 | B40: 양수로 입력 | D40: 400.28 | F40: 393.948 | H40: 767.756 | I40: 626.162 | J40: 399.794 | K40: 393.948
A41: 주요 재무 비율 | B41: 기준 (빨간 글씨 = 미달)
A42: 안정성
A43: 부채비율 | B43: 100%↓ | C43: =IF(OR(C27="",C35=""),"",IFERROR(C27/C35,"")) | D43: =IF(OR(D27="",D35=""),"",IFERROR(D27/D35,"")) | E43: =IF(OR(E27="",E35=""),"",IFERROR(E27/E35,"")) | F43: =IF(OR(F27="",F35=""),"",IFERROR(F27/F35,"")) | G43: =IF(OR(G27="",G35=""),"",IFERROR(G27/G35,"")) | H43: =IF(OR(H27="",H35=""),"",IFERROR(H27/H35,"")) | I43: =IF(OR(I27="",I35=""),"",IFERROR(I27/I35,"")) | J43: =IF(OR(J27="",J35=""),"",IFERROR(J27/J35,"")) | K43: =IF(OR(K27="",K35=""),"",IFERROR(K27/K35,""))
A44: 순차입금비율 | B44: 0%↓ 순현금 | C44: =IF(OR(C29="",C35=""),"",IFERROR(C29/C35,"")) | D44: =IF(OR(D29="",D35=""),"",IFERROR(D29/D35,"")) | E44: =IF(OR(E29="",E35=""),"",IFERROR(E29/E35,"")) | F44: =IF(OR(F29="",F35=""),"",IFERROR(F29/F35,"")) | G44: =IF(OR(G29="",G35=""),"",IFERROR(G29/G35,"")) | H44: =IF(OR(H29="",H35=""),"",IFERROR(H29/H35,"")) | I44: =IF(OR(I29="",I35=""),"",IFERROR(I29/I35,"")) | J44: =IF(OR(J29="",J35=""),"",IFERROR(J29/J35,"")) | K44: =IF(OR(K29="",K35=""),"",IFERROR(K29/K35,""))
A45: 자기자본비율 | B45: 50%↑ | C45: =IF(OR(C35="",C16=""),"",IFERROR(C35/C16,"")) | D45: =IF(OR(D35="",D16=""),"",IFERROR(D35/D16,"")) | E45: =IF(OR(E35="",E16=""),"",IFERROR(E35/E16,"")) | F45: =IF(OR(F35="",F16=""),"",IFERROR(F35/F16,"")) | G45: =IF(OR(G35="",G16=""),"",IFERROR(G35/G16,"")) | H45: =IF(OR(H35="",H16=""),"",IFERROR(H35/H16,"")) | I45: =IF(OR(I35="",I16=""),"",IFERROR(I35/I16,"")) | J45: =IF(OR(J35="",J16=""),"",IFERROR(J35/J16,"")) | K45: =IF(OR(K35="",K16=""),"",IFERROR(K35/K16,""))
A46: 유동비율 | B46: 150%↑ | C46: =IF(OR(C5="",C18=""),"",IFERROR(C5/C18,"")) | D46: =IF(OR(D5="",D18=""),"",IFERROR(D5/D18,"")) | E46: =IF(OR(E5="",E18=""),"",IFERROR(E5/E18,"")) | F46: =IF(OR(F5="",F18=""),"",IFERROR(F5/F18,"")) | G46: =IF(OR(G5="",G18=""),"",IFERROR(G5/G18,"")) | H46: =IF(OR(H5="",H18=""),"",IFERROR(H5/H18,"")) | I46: =IF(OR(I5="",I18=""),"",IFERROR(I5/I18,"")) | J46: =IF(OR(J5="",J18=""),"",IFERROR(J5/J18,"")) | K46: =IF(OR(K5="",K18=""),"",IFERROR(K5/K18,""))
A47: 당좌비율 | B47: 100%↑ | C47: =IF(OR(C5="",C18=""),"",IFERROR((C5-N(C9))/C18,"")) | D47: =IF(OR(D5="",D18=""),"",IFERROR((D5-N(D9))/D18,"")) | E47: =IF(OR(E5="",E18=""),"",IFERROR((E5-N(E9))/E18,"")) | F47: =IF(OR(F5="",F18=""),"",IFERROR((F5-N(F9))/F18,"")) | G47: =IF(OR(G5="",G18=""),"",IFERROR((G5-N(G9))/G18,"")) | H47: =IF(OR(H5="",H18=""),"",IFERROR((H5-N(H9))/H18,"")) | I47: =IF(OR(I5="",I18=""),"",IFERROR((I5-N(I9))/I18,"")) | J47: =IF(OR(J5="",J18=""),"",IFERROR((J5-N(J9))/J18,"")) | K47: =IF(OR(K5="",K18=""),"",IFERROR((K5-N(K9))/K18,""))
A48: 이자보상배율 | B48: 5x↑ (금융원가 기준) | C48: =IFERROR((IF(COUNT('연간'!D31:G31)<4,"",SUM('연간'!D31:G31)))/(IF(COUNT('연간'!D53:G53)<4,"",SUM('연간'!D53:G53))),"") | D48: =IFERROR((IF(COUNT('연간'!E31:H31)<4,"",SUM('연간'!E31:H31)))/(IF(COUNT('연간'!E53:H53)<4,"",SUM('연간'!E53:H53))),"") | E48: =IFERROR((IF(COUNT('연간'!F31:I31)<4,"",SUM('연간'!F31:I31)))/(IF(COUNT('연간'!F53:I53)<4,"",SUM('연간'!F53:I53))),"") | F48: =IFERROR((IF(COUNT('연간'!G31:J31)<4,"",SUM('연간'!G31:J31)))/(IF(COUNT('연간'!G53:J53)<4,"",SUM('연간'!G53:J53))),"") | G48: =IFERROR((IF(COUNT('연간'!H31:K31)<4,"",SUM('연간'!H31:K31)))/(IF(COUNT('연간'!H53:K53)<4,"",SUM('연간'!H53:K53))),"") | H48: =IFERROR(('연간'!T31)/('연간'!T53),"") | I48: =IFERROR(('연간'!U31)/('연간'!U53),"") | J48: =IFERROR(('연간'!V31)/('연간'!V53),"") | K48: =IFERROR(('연간'!W31)/('연간'!W53),"")
A49: 차입금 상환연수 | B49: 4년↓ (버핏) | C49: =IFERROR(IF((IF(COUNT('연간'!D61:G61)<4,"",SUM('연간'!D61:G61)))<=0,"적자",C28/(IF(COUNT('연간'!D61:G61)<4,"",SUM('연간'!D61:G61)))),"") | D49: =IFERROR(IF((IF(COUNT('연간'!E61:H61)<4,"",SUM('연간'!E61:H61)))<=0,"적자",D28/(IF(COUNT('연간'!E61:H61)<4,"",SUM('연간'!E61:H61)))),"") | E49: =IFERROR(IF((IF(COUNT('연간'!F61:I61)<4,"",SUM('연간'!F61:I61)))<=0,"적자",E28/(IF(COUNT('연간'!F61:I61)<4,"",SUM('연간'!F61:I61)))),"") | F49: =IFERROR(IF((IF(COUNT('연간'!G61:J61)<4,"",SUM('연간'!G61:J61)))<=0,"적자",F28/(IF(COUNT('연간'!G61:J61)<4,"",SUM('연간'!G61:J61)))),"") | G49: =IFERROR(IF((IF(COUNT('연간'!H61:K61)<4,"",SUM('연간'!H61:K61)))<=0,"적자",G28/(IF(COUNT('연간'!H61:K61)<4,"",SUM('연간'!H61:K61)))),"") | H49: =IFERROR(IF(('연간'!T61)<=0,"적자",H28/('연간'!T61)),"") | I49: =IFERROR(IF(('연간'!U61)<=0,"적자",I28/('연간'!U61)),"") | J49: =IFERROR(IF(('연간'!V61)<=0,"적자",J28/('연간'!V61)),"") | K49: =IFERROR(IF(('연간'!W61)<=0,"적자",K28/('연간'!W61)),"")
A50: 수익성
A51: ROE | B51: 15%↑ (버핏) | C51: =IFERROR((IF(COUNT('연간'!D61:G61)<4,"",SUM('연간'!D61:G61)))/C31,"") | D51: =IFERROR((IF(COUNT('연간'!E61:H61)<4,"",SUM('연간'!E61:H61)))/D31,"") | E51: =IFERROR((IF(COUNT('연간'!F61:I61)<4,"",SUM('연간'!F61:I61)))/E31,"") | F51: =IFERROR((IF(COUNT('연간'!G61:J61)<4,"",SUM('연간'!G61:J61)))/F31,"") | G51: =IFERROR((IF(COUNT('연간'!H61:K61)<4,"",SUM('연간'!H61:K61)))/G31,"") | H51: =IFERROR(('연간'!T61)/H31,"") | I51: =IFERROR(('연간'!U61)/I31,"") | J51: =IFERROR(('연간'!V61)/J31,"") | K51: =IFERROR(('연간'!W61)/K31,"")
A52: ROA | B52: 5%↑ | C52: =IFERROR((IF(COUNT('연간'!D59:G59)<4,"",SUM('연간'!D59:G59)))/C16,"") | D52: =IFERROR((IF(COUNT('연간'!E59:H59)<4,"",SUM('연간'!E59:H59)))/D16,"") | E52: =IFERROR((IF(COUNT('연간'!F59:I59)<4,"",SUM('연간'!F59:I59)))/E16,"") | F52: =IFERROR((IF(COUNT('연간'!G59:J59)<4,"",SUM('연간'!G59:J59)))/F16,"") | G52: =IFERROR((IF(COUNT('연간'!H59:K59)<4,"",SUM('연간'!H59:K59)))/G16,"") | H52: =IFERROR(('연간'!T59)/H16,"") | I52: =IFERROR(('연간'!U59)/I16,"") | J52: =IFERROR(('연간'!V59)/J16,"") | K52: =IFERROR(('연간'!W59)/K16,"")
A53: ROIC | B53: 10%↑ (세후영업이익 기준) | C53: =IFERROR((IF(COUNT('연간'!D31:G31)<4,"",SUM('연간'!D31:G31)))*(1-0.3)/(C35+C29),"") | D53: =IFERROR((IF(COUNT('연간'!E31:H31)<4,"",SUM('연간'!E31:H31)))*(1-0.3)/(D35+D29),"") | E53: =IFERROR((IF(COUNT('연간'!F31:I31)<4,"",SUM('연간'!F31:I31)))*(1-0.3)/(E35+E29),"") | F53: =IFERROR((IF(COUNT('연간'!G31:J31)<4,"",SUM('연간'!G31:J31)))*(1-0.3)/(F35+F29),"") | G53: =IFERROR((IF(COUNT('연간'!H31:K31)<4,"",SUM('연간'!H31:K31)))*(1-0.3)/(G35+G29),"") | H53: =IFERROR(('연간'!T31)*(1-0.3)/(H35+H29),"") | I53: =IFERROR(('연간'!U31)*(1-0.3)/(I35+I29),"") | J53: =IFERROR(('연간'!V31)*(1-0.3)/(J35+J29),"") | K53: =IFERROR(('연간'!W31)*(1-0.3)/(K35+K29),"")
A54: 매출총이익률 (GPM) | B54: 40%↑ (해자 신호) | C54: =IFERROR((IF(COUNT('연간'!D25:G25)<4,"",SUM('연간'!D25:G25)))/(IF(COUNT('연간'!D4:G4)<4,"",SUM('연간'!D4:G4))),"") | D54: =IFERROR((IF(COUNT('연간'!E25:H25)<4,"",SUM('연간'!E25:H25)))/(IF(COUNT('연간'!E4:H4)<4,"",SUM('연간'!E4:H4))),"") | E54: =IFERROR((IF(COUNT('연간'!F25:I25)<4,"",SUM('연간'!F25:I25)))/(IF(COUNT('연간'!F4:I4)<4,"",SUM('연간'!F4:I4))),"") | F54: =IFERROR((IF(COUNT('연간'!G25:J25)<4,"",SUM('연간'!G25:J25)))/(IF(COUNT('연간'!G4:J4)<4,"",SUM('연간'!G4:J4))),"") | G54: =IFERROR((IF(COUNT('연간'!H25:K25)<4,"",SUM('연간'!H25:K25)))/(IF(COUNT('연간'!H4:K4)<4,"",SUM('연간'!H4:K4))),"") | H54: =IFERROR(('연간'!T25)/('연간'!T4),"") | I54: =IFERROR(('연간'!U25)/('연간'!U4),"") | J54: =IFERROR(('연간'!V25)/('연간'!V4),"") | K54: =IFERROR(('연간'!W25)/('연간'!W4),"")
A55: 영업이익률 (OPM) | B55: 15%↑ | C55: =IFERROR((IF(COUNT('연간'!D31:G31)<4,"",SUM('연간'!D31:G31)))/(IF(COUNT('연간'!D4:G4)<4,"",SUM('연간'!D4:G4))),"") | D55: =IFERROR((IF(COUNT('연간'!E31:H31)<4,"",SUM('연간'!E31:H31)))/(IF(COUNT('연간'!E4:H4)<4,"",SUM('연간'!E4:H4))),"") | E55: =IFERROR((IF(COUNT('연간'!F31:I31)<4,"",SUM('연간'!F31:I31)))/(IF(COUNT('연간'!F4:I4)<4,"",SUM('연간'!F4:I4))),"") | F55: =IFERROR((IF(COUNT('연간'!G31:J31)<4,"",SUM('연간'!G31:J31)))/(IF(COUNT('연간'!G4:J4)<4,"",SUM('연간'!G4:J4))),"") | G55: =IFERROR((IF(COUNT('연간'!H31:K31)<4,"",SUM('연간'!H31:K31)))/(IF(COUNT('연간'!H4:K4)<4,"",SUM('연간'!H4:K4))),"") | H55: =IFERROR(('연간'!T31)/('연간'!T4),"") | I55: =IFERROR(('연간'!U31)/('연간'!U4),"") | J55: =IFERROR(('연간'!V31)/('연간'!V4),"") | K55: =IFERROR(('연간'!W31)/('연간'!W4),"")
A56: 순이익률 | B56: 10%↑ | C56: =IFERROR((IF(COUNT('연간'!D59:G59)<4,"",SUM('연간'!D59:G59)))/(IF(COUNT('연간'!D4:G4)<4,"",SUM('연간'!D4:G4))),"") | D56: =IFERROR((IF(COUNT('연간'!E59:H59)<4,"",SUM('연간'!E59:H59)))/(IF(COUNT('연간'!E4:H4)<4,"",SUM('연간'!E4:H4))),"") | E56: =IFERROR((IF(COUNT('연간'!F59:I59)<4,"",SUM('연간'!F59:I59)))/(IF(COUNT('연간'!F4:I4)<4,"",SUM('연간'!F4:I4))),"") | F56: =IFERROR((IF(COUNT('연간'!G59:J59)<4,"",SUM('연간'!G59:J59)))/(IF(COUNT('연간'!G4:J4)<4,"",SUM('연간'!G4:J4))),"") | G56: =IFERROR((IF(COUNT('연간'!H59:K59)<4,"",SUM('연간'!H59:K59)))/(IF(COUNT('연간'!H4:K4)<4,"",SUM('연간'!H4:K4))),"") | H56: =IFERROR(('연간'!T59)/('연간'!T4),"") | I56: =IFERROR(('연간'!U59)/('연간'!U4),"") | J56: =IFERROR(('연간'!V59)/('연간'!V4),"") | K56: =IFERROR(('연간'!W59)/('연간'!W4),"")
A57: 효율성 (회전율)
A58: 총자산회전율 | B58: 높을수록↑ | C58: =IFERROR((IF(COUNT('연간'!D4:G4)<4,"",SUM('연간'!D4:G4)))/C16,"") | D58: =IFERROR((IF(COUNT('연간'!E4:H4)<4,"",SUM('연간'!E4:H4)))/D16,"") | E58: =IFERROR((IF(COUNT('연간'!F4:I4)<4,"",SUM('연간'!F4:I4)))/E16,"") | F58: =IFERROR((IF(COUNT('연간'!G4:J4)<4,"",SUM('연간'!G4:J4)))/F16,"") | G58: =IFERROR((IF(COUNT('연간'!H4:K4)<4,"",SUM('연간'!H4:K4)))/G16,"") | H58: =IFERROR(('연간'!T4)/H16,"") | I58: =IFERROR(('연간'!U4)/I16,"") | J58: =IFERROR(('연간'!V4)/J16,"") | K58: =IFERROR(('연간'!W4)/K16,"")
A59: 매출채권회전일수 | B59: 짧을수록↑ | C59: =IFERROR(C8/(IF(COUNT('연간'!D4:G4)<4,"",SUM('연간'!D4:G4)))*365,"") | D59: =IFERROR(D8/(IF(COUNT('연간'!E4:H4)<4,"",SUM('연간'!E4:H4)))*365,"") | E59: =IFERROR(E8/(IF(COUNT('연간'!F4:I4)<4,"",SUM('연간'!F4:I4)))*365,"") | F59: =IFERROR(F8/(IF(COUNT('연간'!G4:J4)<4,"",SUM('연간'!G4:J4)))*365,"") | G59: =IFERROR(G8/(IF(COUNT('연간'!H4:K4)<4,"",SUM('연간'!H4:K4)))*365,"") | H59: =IFERROR(H8/('연간'!T4)*365,"") | I59: =IFERROR(I8/('연간'!U4)*365,"") | J59: =IFERROR(J8/('연간'!V4)*365,"") | K59: =IFERROR(K8/('연간'!W4)*365,"")
A60: 재고자산회전일수 | B60: 짧을수록↑ | C60: =IFERROR(C9/(IF(COUNT('연간'!D23:G23)<4,"",SUM('연간'!D23:G23)))*365,"") | D60: =IFERROR(D9/(IF(COUNT('연간'!E23:H23)<4,"",SUM('연간'!E23:H23)))*365,"") | E60: =IFERROR(E9/(IF(COUNT('연간'!F23:I23)<4,"",SUM('연간'!F23:I23)))*365,"") | F60: =IFERROR(F9/(IF(COUNT('연간'!G23:J23)<4,"",SUM('연간'!G23:J23)))*365,"") | G60: =IFERROR(G9/(IF(COUNT('연간'!H23:K23)<4,"",SUM('연간'!H23:K23)))*365,"") | H60: =IFERROR(H9/('연간'!T23)*365,"") | I60: =IFERROR(I9/('연간'!U23)*365,"") | J60: =IFERROR(J9/('연간'!V23)*365,"") | K60: =IFERROR(K9/('연간'!W23)*365,"")
A61: 매입채무회전일수 | B61: 길수록 유리 | C61: =IFERROR(C19/(IF(COUNT('연간'!D23:G23)<4,"",SUM('연간'!D23:G23)))*365,"") | D61: =IFERROR(D19/(IF(COUNT('연간'!E23:H23)<4,"",SUM('연간'!E23:H23)))*365,"") | E61: =IFERROR(E19/(IF(COUNT('연간'!F23:I23)<4,"",SUM('연간'!F23:I23)))*365,"") | F61: =IFERROR(F19/(IF(COUNT('연간'!G23:J23)<4,"",SUM('연간'!G23:J23)))*365,"") | G61: =IFERROR(G19/(IF(COUNT('연간'!H23:K23)<4,"",SUM('연간'!H23:K23)))*365,"") | H61: =IFERROR(H19/('연간'!T23)*365,"") | I61: =IFERROR(I19/('연간'!U23)*365,"") | J61: =IFERROR(J19/('연간'!V23)*365,"") | K61: =IFERROR(K19/('연간'!W23)*365,"")
A62: 현금전환주기 (CCC) | B62: 짧을수록↑ | C62: =IF(OR(C59="",C60="",C61=""),"",IFERROR(C59+C60-C61,"")) | D62: =IF(OR(D59="",D60="",D61=""),"",IFERROR(D59+D60-D61,"")) | E62: =IF(OR(E59="",E60="",E61=""),"",IFERROR(E59+E60-E61,"")) | F62: =IF(OR(F59="",F60="",F61=""),"",IFERROR(F59+F60-F61,"")) | G62: =IF(OR(G59="",G60="",G61=""),"",IFERROR(G59+G60-G61,"")) | H62: =IF(OR(H59="",H60="",H61=""),"",IFERROR(H59+H60-H61,"")) | I62: =IF(OR(I59="",I60="",I61=""),"",IFERROR(I59+I60-I61,"")) | J62: =IF(OR(J59="",J60="",J61=""),"",IFERROR(J59+J60-J61,"")) | K62: =IF(OR(K59="",K60="",K61=""),"",IFERROR(K59+K60-K61,""))
A63: 현금흐름
A64: 영업현금흐름 / 순이익 | B64: 1x↑ (이익의 질) | C64: =IF(C37="","",IFERROR(C37/(IF(COUNT('연간'!D59:G59)<4,"",SUM('연간'!D59:G59))),"")) | D64: =IF(D37="","",IFERROR(D37/(IF(COUNT('연간'!E59:H59)<4,"",SUM('연간'!E59:H59))),"")) | E64: =IF(E37="","",IFERROR(E37/(IF(COUNT('연간'!F59:I59)<4,"",SUM('연간'!F59:I59))),"")) | F64: =IF(F37="","",IFERROR(F37/(IF(COUNT('연간'!G59:J59)<4,"",SUM('연간'!G59:J59))),"")) | G64: =IF(G37="","",IFERROR(G37/(IF(COUNT('연간'!H59:K59)<4,"",SUM('연간'!H59:K59))),"")) | H64: =IF(H37="","",IFERROR(H37/('연간'!T59),"")) | I64: =IF(I37="","",IFERROR(I37/('연간'!U59),"")) | J64: =IF(J37="","",IFERROR(J37/('연간'!V59),"")) | K64: =IF(K37="","",IFERROR(K37/('연간'!W59),""))
A65: FCF 마진 | B65: 5%↑ | C65: =IF(C39="","",IFERROR(C39/(IF(COUNT('연간'!D4:G4)<4,"",SUM('연간'!D4:G4))),"")) | D65: =IF(D39="","",IFERROR(D39/(IF(COUNT('연간'!E4:H4)<4,"",SUM('연간'!E4:H4))),"")) | E65: =IF(E39="","",IFERROR(E39/(IF(COUNT('연간'!F4:I4)<4,"",SUM('연간'!F4:I4))),"")) | F65: =IF(F39="","",IFERROR(F39/(IF(COUNT('연간'!G4:J4)<4,"",SUM('연간'!G4:J4))),"")) | G65: =IF(G39="","",IFERROR(G39/(IF(COUNT('연간'!H4:K4)<4,"",SUM('연간'!H4:K4))),"")) | H65: =IF(H39="","",IFERROR(H39/('연간'!T4),"")) | I65: =IF(I39="","",IFERROR(I39/('연간'!U4),"")) | J65: =IF(J39="","",IFERROR(J39/('연간'!V4),"")) | K65: =IF(K39="","",IFERROR(K39/('연간'!W4),""))
A66: CAPEX / 매출 | B66: 낮을수록↑ (자본 가벼움) | C66: =IF(C38="","",IFERROR(C38/(IF(COUNT('연간'!D4:G4)<4,"",SUM('연간'!D4:G4))),"")) | D66: =IF(D38="","",IFERROR(D38/(IF(COUNT('연간'!E4:H4)<4,"",SUM('연간'!E4:H4))),"")) | E66: =IF(E38="","",IFERROR(E38/(IF(COUNT('연간'!F4:I4)<4,"",SUM('연간'!F4:I4))),"")) | F66: =IF(F38="","",IFERROR(F38/(IF(COUNT('연간'!G4:J4)<4,"",SUM('연간'!G4:J4))),"")) | G66: =IF(G38="","",IFERROR(G38/(IF(COUNT('연간'!H4:K4)<4,"",SUM('연간'!H4:K4))),"")) | H66: =IF(H38="","",IFERROR(H38/('연간'!T4),"")) | I66: =IF(I38="","",IFERROR(I38/('연간'!U4),"")) | J66: =IF(J38="","",IFERROR(J38/('연간'!V4),"")) | K66: =IF(K38="","",IFERROR(K38/('연간'!W4),""))
A67: 배당성향 | B67: 참고 | C67: =IF(C40="","",IFERROR(C40/(IF(COUNT('연간'!D61:G61)<4,"",SUM('연간'!D61:G61))),"")) | D67: =IF(D40="","",IFERROR(D40/(IF(COUNT('연간'!E61:H61)<4,"",SUM('연간'!E61:H61))),"")) | E67: =IF(E40="","",IFERROR(E40/(IF(COUNT('연간'!F61:I61)<4,"",SUM('연간'!F61:I61))),"")) | F67: =IF(F40="","",IFERROR(F40/(IF(COUNT('연간'!G61:J61)<4,"",SUM('연간'!G61:J61))),"")) | G67: =IF(G40="","",IFERROR(G40/(IF(COUNT('연간'!H61:K61)<4,"",SUM('연간'!H61:K61))),"")) | H67: =IF(H40="","",IFERROR(H40/('연간'!T61),"")) | I67: =IF(I40="","",IFERROR(I40/('연간'!U61),"")) | J67: =IF(J40="","",IFERROR(J40/('연간'!V61),"")) | K67: =IF(K40="","",IFERROR(K40/('연간'!W61),""))
A69: 재무상태표 · 전 항목 | B69: 분기 말 잔액
A70: 항목 | B70: 참고 | C70: 2026.1Q | D70: 2026.2Q | E70: 2026.3Q | F70: 2026.4Q | G70: 2027.1Q | H70: 2023 | I70: 2024 | J70: 2025 | K70: 2026
A71: 현금 및 예금 | C71: 6831.528 | D71: 6747.841 | E71: 6984.794 | F71: 7398.912 | G71: 6832.976 | H71: 6888.375 | I71: 7103.652 | J71: 7742.985 | K71: 7398.912
A72: 받을어음 | C72: 226.669 | D72: 208.178 | E72: 191.147 | F72: 216.239 | G72: 195.956 | H72: 305.95 | I72: 196.809 | J72: 210.874 | K72: 216.239
A73: 매출채권 | C73: 5159.478 | D73: 4140.375 | E73: 5354.194 | F73: 5232.014 | G73: 5405.64 | H73: 5285.919 | I73: 5620.898 | J73: 5192.359 | K73: 5232.014
A74: 상품·제품 | C74: 9700.866 | D74: 10804.902 | E74: 10654.992 | F74: 10790.147 | G74: 9232.373 | H74: 11024.566 | I74: 11294.477 | J74: 10767.404 | K74: 10790.147
A75: 재공품 | C75: 301.213 | D75: 340.121 | E75: 343.02 | F75: 339.412 | G75: 349.684 | H75: 422.271 | I75: 355.514 | J75: 339.076 | K75: 339.412
A76: 원재료·저장품 | C76: 1190.668 | D76: 1323.877 | E76: 1220.739 | F76: 1305.757 | G76: 1399.888 | H76: 1531.39 | I76: 1383.347 | J76: 1280.269 | K76: 1305.757
A77: 기타 | C77: 653.503 | D77: 765.16 | E77: 735.54 | F77: 802.302 | G77: 890.17 | H77: 900.04 | I77: 670.486 | J77: 815.545 | K77: 802.302
A78: 대손충당금 | C78: -0.484 | D78: -0.835 | E78: -0.878 | F78: -0.934 | G78: -1.223 | H78: -0.708 | I78: -0.44 | J78: -0.65 | K78: -0.934
A79: 유동자산 합계 | C79: 24063.443 | D79: 24329.621 | E79: 25483.552 | F79: 26083.852 | G79: 24305.467 | H79: 26357.806 | I79: 26624.746 | J79: 26347.865 | K79: 26083.852
A80: 건물·구축물 | C80: 6196.545 | D80: 6211.898 | E80: 6383.8 | F80: 6442.472 | G80: 6453.964 | H80: 6162.218 | I80: 6171.625 | J80: 6204.703 | K80: 6442.472
A81: 감가상각누계액 | C81: -4306.709 | D81: -4350.422 | E81: -4416.734 | F81: -4458.457 | G81: -4504.984 | H81: -4024.616 | I81: -4147.967 | J81: -4289.35 | K81: -4458.457
A82: 건물·구축물(순액) | C82: 1889.836 | D82: 1861.476 | E82: 1967.066 | F82: 1984.014 | G82: 1948.979 | H82: 2137.601 | I82: 2023.658 | J82: 1915.352 | K82: 1984.014
... A109: 임원 상여충당금 | C109: 6.222 | D109: 1 | E109: 5.946 | F109: 10.893 | G109: 11.839 | H109: 14.218 | I109: 9.841 | J109: 6.398 | K109: 10.893
A110: 주주우대 충당금 | C110: 37.532 | D110: 37.532 | E110: 17.901 | F110: 6.064 | G110: 42.167 | K110: 6.064
A111: 자산복구부채 | C111: 0 | G111: 15
A112: 기타 | C112: 1003.193 | D112: 1035.1 | E112: 1050.659 | F112: 1175.819 | G112: 1184.228 | H112: 979.747 | I112: 1121.035 | J112: 1058.033 | K112: 1175.819
A113: 유동부채 합계 | C113: 8210.456 | D113: 9155.888 | E113: 9664.631 | F113: 10263.576 | G113: 7676.381 | H113: 9736.854 | I113: 10168.248 | J113: 10796.674 | K113: 10263.576
A114: 장기차입금 | C114: 1300.482 | D114: 1083.889 | E114: 1081.579 | F114: 864.986 | G114: 862.676 | H114: 2322.347 | I114: 1740.598 | J114: 1302.792 | K114: 864.986
A115: 이연법인세부채 | C115: 948.343 | D115: 1081.124 | E115: 1282.653 | F115: 1381.994 | G115: 1504.45 | H115: 747.229 | I115: 927.311 | J115: 986.615 | K115: 1381.994
A116: 퇴직급여부채 | C116: 515.723 | D116: 531.528 | E116: 556.409 | F116: 567.411 | G116: 549.291 | H116: 508.01 | I116: 487.234 | J116: 500.154 | K116: 567.411
A117: 자산복구부채 | C117: 41.353 | D117: 41.983 | E117: 43.724 | F117: 45.024 | G117: 49.315 | H117: 31.259 | I117: 32.007 | J117: 36.749 | K117: 45.024
A118: 기타 | C118: 444.518 | D118: 450.982 | E118: 460.981 | F118: 471.129 | G118: 477.277 | H118: 356.653 | I118: 397.022 | J118: 436.482 | K118: 471.129
A119: 비유동부채 합계 | C119: 3250.422 | D119: 3189.507 | E119: 3425.348 | F119: 3330.546 | G119: 3443.01 | H119: 3965.5 | I119: 3584.173 | J119: 3262.793 | K119: 3330.546
A120: 부채 합계 | C120: 11460.879 | D120: 12345.396 | E120: 13089.979 | F120: 13594.122 | G120: 11119.391 | H120: 13702.354 | I120: 13752.422 | J120: 14059.468 | K120: 13594.122
A121: 자본금 | C121: 1978.69 | D121: 1978.69 | E121: 1978.69 | F121: 1978.69 | G121: 1978.69 | H121: 1978.69 | I121: 1978.69 | J121: 1978.69 | K121: 1978.69
A122: 자본잉여금 | C122: 1717.975 | D122: 1717.975 | E122: 1717.704 | F122: 1717.704 | G122: 1717.704 | H122: 1718.67 | I122: 1718.919 | J122: 1717.975 | K122: 1717.704
A123: 이익잉여금 | C123: 21593.605 | D123: 21097.779 | E123: 21423.05 | F123: 21547.117 | G123: 22198.821 | H123: 21925.214 | I123: 21806.379 | J123: 21557.382 | K123: 21547.117
... A131: 신주예약권 | C131: 87.088 | D131: 87.088 | E131: 87.088 | F131: 87.088 | G131: 87.088 | H131: 87.088 | I131: 87.088 | J131: 87.088 | K131: 87.088
A132: 비지배지분 | H132: 0
A133: 순자산 합계 | C133: 24052.288 | D133: 24029.921 | E133: 24873.535 | F133: 25245.749 | G133: 26232.694 | H133: 24263.82 | I133: 24798.56 | J133: 24252.317 | K133: 25245.749
A134: 부채·순자산 합계 | C134: 35513.167 | D134: 36375.317 | E134: 37963.515 | F134: 38839.871 | G134: 37352.086 | H134: 37966.175 | I134: 38550.983 | J134: 38311.785 | K134: 38839.871

Sheet 출처
A1: 출처 · 쓴 결산단신
A3: 공시일 | B3: 문서 | C3: PDF
A4: 2026-07-30 | B4: 2026년 6월 결산기 연간 결산단신 | C4: https://www2.jpx.co.jp/disc/79620/140120260730503307.pdf
A5: 2026-04-24 | B5: 2026년 6월 결산기 ３분기 결산단신 | C5: https://www2.jpx.co.jp/disc/79620/140120260423509646.pdf
A6: 2026-01-29 | B6: 2026년 6월 결산기 ２분기 결산단신 | C6: https://www2.jpx.co.jp/disc/79620/140120260128540741.pdf
A7: 2025-10-31 | B7: 2026년 6월 결산기 １분기 결산단신 | C7: https://www2.jpx.co.jp/disc/79620/140120251030583477.pdf
A8: 2025-07-31 | B8: 2025년 6월 결산기 연간 결산단신 | C8: https://www2.jpx.co.jp/disc/79620/140120250730524541.pdf
A9: 2025-04-24 | B9: 2025년 6월 결산기 ３분기 결산단신 | C9: https://www2.jpx.co.jp/disc/79620/140120250423521388.pdf
A10: 2025-01-30 | B10: 2025년 6월 결산기 2분기 결산단신 | C10: https://www2.jpx.co.jp/disc/79620/140120250129557510.pdf
A11: 2024-11-01 | B11: 2025년 6월 결산기 1분기 결산단신 | C11: https://www2.jpx.co.jp/disc/79620/140120241031507962.pdf
A12: 2024-08-01 | B12: 2024년 6월 결산기 연간 결산단신 | C12: https://www2.jpx.co.jp/disc/79620/140120240731559327.pdf
A13: 2024-04-26 | B13: 2024년 6월 결산기 3분기 결산단신 | C13: https://www2.jpx.co.jp/disc/79620/140120240425576753.pdf
A14: 2024-02-01 | B14: 2024년 6월 결산기 2분기 결산단신 | C14: https://www2.jpx.co.jp/disc/79620/140120240131523292.pdf
... A24: 2018-08-01 | B24: 연간 결산단신 | C24: https://www2.jpx.co.jp/disc/79620/140120180731489305.pdf
