Workbook

Sheet 연간
A1: 9950 Model
A2: 모를 땐 보수적으로 | B2: (단위: 백만엔) | C2: 2월 결산 · 일본 기준 · 2027.4Q = 2027년 2월 결산기 4분기 | Y2: (추정: 파란 글씨 = 직접 입력)
A3: 항목 | B3: 참고 | C3: 2025.1Q | D3: 2025.2Q | E3: 2025.3Q | F3: 2025.4Q | G3: 2026.1Q | H3: 2026.2Q | I3: 2026.3Q | J3: 2026.4Q | K3: 2027.1Q | L3: 2027.2Q | M3: 2027.3Q | N3: 2027.4Q | O3: 2018 | P3: 2019 | Q3: 2020 | R3: 2021 | S3: 2022 | T3: 2023 | U3: 2024 | V3: 2025 | W3: 2026 | X3: 2027 | Y3: 2028(MW) | Z3: 2029(MW) | AA3: 2030(MW) | AB3: 2031(MW) | AC3: 2032(MW)
A4: 매출액 | B4: MW = 제품 합계 | C4: 1864.782 | D4: 1983.858 | E4: 1785.445 | F4: 1207.226 | G4: 1862.071 | H4: 1984.798 | I4: 1935.544 | J4: 1595.276 | K4: 2008.744 | L4: 2115.126 | O4: 6748.559 | P4: 7068.409 | Q4: 7683.199 | R4: 7650.678 | S4: 5309.975 | T4: 5400.634 | U4: 6435.409 | V4: 6841.311 | W4: 7377.689 | X4: 7730.061 | Y4: =IF(COUNT(Y7,Y10,Y13,Y16,Y19,Y22)=0,"",SUM(Y7,Y10,Y13,Y16,Y19,Y22)) | Z4: =IF(COUNT(Z7,Z10,Z13,Z16,Z19,Z22)=0,"",SUM(Z7,Z10,Z13,Z16,Z19,Z22)) | AA4: =IF(COUNT(AA7,AA10,AA13,AA16,AA19,AA22)=0,"",SUM(AA7,AA10,AA13,AA16,AA19,AA22)) | AB4: =IF(COUNT(AB7,AB10,AB13,AB16,AB19,AB22)=0,"",SUM(AB7,AB10,AB13,AB16,AB19,AB22)) | AC4: =IF(COUNT(AC7,AC10,AC13,AC16,AC19,AC22)=0,"",SUM(AC7,AC10,AC13,AC16,AC19,AC22))
A5: YoY | G5: =IF(OR(G4="",C4=""),"",IFERROR(G4/C4-1,"")) | H5: =IF(OR(H4="",D4=""),"",IFERROR(H4/D4-1,"")) | I5: =IF(OR(I4="",E4=""),"",IFERROR(I4/E4-1,"")) | J5: =IF(OR(J4="",F4=""),"",IFERROR(J4/F4-1,"")) | K5: =IF(OR(K4="",G4=""),"",IFERROR(K4/G4-1,"")) | L5: =IF(OR(L4="",H4=""),"",IFERROR(L4/H4-1,"")) | M5: =IF(OR(M4="",I4=""),"",IFERROR(M4/I4-1,"")) | N5: =IF(OR(N4="",J4=""),"",IFERROR(N4/J4-1,"")) | P5: =IF(OR(P4="",O4=""),"",IFERROR(P4/O4-1,"")) | Q5: =IF(OR(Q4="",P4=""),"",IFERROR(Q4/P4-1,"")) | R5: =IF(OR(R4="",Q4=""),"",IFERROR(R4/Q4-1,"")) | S5: =IF(OR(S4="",R4=""),"",IFERROR(S4/R4-1,"")) | T5: =IF(OR(T4="",S4=""),"",IFERROR(T4/S4-1,"")) | U5: =IF(OR(U4="",T4=""),"",IFERROR(U4/T4-1,"")) | V5: =IF(OR(V4="",U4=""),"",IFERROR(V4/U4-1,"")) | W5: =IF(OR(W4="",V4=""),"",IFERROR(W4/V4-1,"")) | ... AC5: =IF(OR(AC4="",AB4=""),"",IFERROR(AC4/AB4-1,""))
A6: 제품별 매출 분류 | B6: 사업보고서 매출실적
A7: Restaurant Business Reportable Segments | E7: 1508 | F7: 1023.631 | I7: 1624.649 | J7: 1294.115 | V7: 5822.418 | W7: 6192.966 | X7: 6528.348
A8: 비중 | C8: =IF(OR(C7="",C4=""),"",IFERROR(C7/C4,"")) | D8: =IF(OR(D7="",D4=""),"",IFERROR(D7/D4,"")) | E8: =IF(OR(E7="",E4=""),"",IFERROR(E7/E4,"")) | F8: =IF(OR(F7="",F4=""),"",IFERROR(F7/F4,"")) | G8: =IF(OR(G7="",G4=""),"",IFERROR(G7/G4,"")) | H8: =IF(OR(H7="",H4=""),"",IFERROR(H7/H4,"")) | I8: =IF(OR(I7="",I4=""),"",IFERROR(I7/I4,"")) | J8: =IF(OR(J7="",J4=""),"",IFERROR(J7/J4,"")) | ... AC8: =IF(OR(AC7="",AC4=""),"",IFERROR(AC7/AC4,""))
A9: YoY | G9: =IF(OR(G7="",C7=""),"",IFERROR(G7/C7-1,"")) | H9: =IF(OR(H7="",D7=""),"",IFERROR(H7/D7-1,"")) | I9: =IF(OR(I7="",E7=""),"",IFERROR(I7/E7-1,"")) | J9: =IF(OR(J7="",F7=""),"",IFERROR(J7/F7-1,"")) | K9: =IF(OR(K7="",G7=""),"",IFERROR(K7/G7-1,"")) | L9: =IF(OR(L7="",H7=""),"",IFERROR(L7/H7-1,"")) | M9: =IF(OR(M7="",I7=""),"",IFERROR(M7/I7-1,"")) | N9: =IF(OR(N7="",J7=""),"",IFERROR(N7/J7-1,"")) | P9: =IF(OR(P7="",O7=""),"",IFERROR(P7/O7-1,"")) | Q9: =IF(OR(Q7="",P7=""),"",IFERROR(Q7/P7-1,"")) | R9: =IF(OR(R7="",Q7=""),"",IFERROR(R7/Q7-1,"")) | S9: =IF(OR(S7="",R7=""),"",IFERROR(S7/R7-1,"")) | T9: =IF(OR(T7="",S7=""),"",IFERROR(T7/S7-1,"")) | U9: =IF(OR(U7="",T7=""),"",IFERROR(U7/T7-1,"")) | V9: =IF(OR(V7="",U7=""),"",IFERROR(V7/U7-1,"")) | W9: =IF(OR(W7="",V7=""),"",IFERROR(W7/V7-1,"")) | ... AC9: =IF(OR(AC7="",AB7=""),"",IFERROR(AC7/AB7-1,""))
A10: Wholesale Business Reportable Segments | V10: 649.629 | W10: 603.208 | X10: 576.962
A11: 비중 | C11: =IF(OR(C10="",C4=""),"",IFERROR(C10/C4,"")) | D11: =IF(OR(D10="",D4=""),"",IFERROR(D10/D4,"")) | E11: =IF(OR(E10="",E4=""),"",IFERROR(E10/E4,"")) | F11: =IF(OR(F10="",F4=""),"",IFERROR(F10/F4,"")) | G11: =IF(OR(G10="",G4=""),"",IFERROR(G10/G4,"")) | H11: =IF(OR(H10="",H4=""),"",IFERROR(H10/H4,"")) | I11: =IF(OR(I10="",I4=""),"",IFERROR(I10/I4,"")) | J11: =IF(OR(J10="",J4=""),"",IFERROR(J10/J4,"")) | ... AC11: =IF(OR(AC10="",AC4=""),"",IFERROR(AC10/AC4,""))
A12: YoY | G12: =IF(OR(G10="",C10=""),"",IFERROR(G10/C10-1,"")) | H12: =IF(OR(H10="",D10=""),"",IFERROR(H10/D10-1,"")) | I12: =IF(OR(I10="",E10=""),"",IFERROR(I10/E10-1,"")) | J12: =IF(OR(J10="",F10=""),"",IFERROR(J10/F10-1,"")) | K12: =IF(OR(K10="",G10=""),"",IFERROR(K10/G10-1,"")) | L12: =IF(OR(L10="",H10=""),"",IFERROR(L10/H10-1,"")) | M12: =IF(OR(M10="",I10=""),"",IFERROR(M10/I10-1,"")) | N12: =IF(OR(N10="",J10=""),"",IFERROR(N10/J10-1,"")) | P12: =IF(OR(P10="",O10=""),"",IFERROR(P10/O10-1,"")) | Q12: =IF(OR(Q10="",P10=""),"",IFERROR(Q10/P10-1,"")) | R12: =IF(OR(R10="",Q10=""),"",IFERROR(R10/Q10-1,"")) | S12: =IF(OR(S10="",R10=""),"",IFERROR(S10/R10-1,"")) | T12: =IF(OR(T10="",S10=""),"",IFERROR(T10/S10-1,"")) | U12: =IF(OR(U10="",T10=""),"",IFERROR(U10/T10-1,"")) | V12: =IF(OR(V10="",U10=""),"",IFERROR(V10/U10-1,"")) | W12: =IF(OR(W10="",V10=""),"",IFERROR(W10/V10-1,"")) | ... AC12: =IF(OR(AC10="",AB10=""),"",IFERROR(AC10/AB10-1,""))
A13: Retail Sales Business Reportable Segments | E13: 141.72 | I13: 143.389
A14: 비중 | C14: =IF(OR(C13="",C4=""),"",IFERROR(C13/C4,"")) | D14: =IF(OR(D13="",D4=""),"",IFERROR(D13/D4,"")) | E14: =IF(OR(E13="",E4=""),"",IFERROR(E13/E4,"")) | F14: =IF(OR(F13="",F4=""),"",IFERROR(F13/F4,"")) | G14: =IF(OR(G13="",G4=""),"",IFERROR(G13/G4,"")) | H14: =IF(OR(H13="",H4=""),"",IFERROR(H13/H4,"")) | I14: =IF(OR(I13="",I4=""),"",IFERROR(I13/I4,"")) | J14: =IF(OR(J13="",J4=""),"",IFERROR(J13/J4,"")) | ... AC14: =IF(OR(AC13="",AC4=""),"",IFERROR(AC13/AC4,""))
A15: YoY | G15: =IF(OR(G13="",C13=""),"",IFERROR(G13/C13-1,"")) | H15: =IF(OR(H13="",D13=""),"",IFERROR(H13/D13-1,"")) | I15: =IF(OR(I13="",E13=""),"",IFERROR(I13/E13-1,"")) | J15: =IF(OR(J13="",F13=""),"",IFERROR(J13/F13-1,"")) | K15: =IF(OR(K13="",G13=""),"",IFERROR(K13/G13-1,"")) | L15: =IF(OR(L13="",H13=""),"",IFERROR(L13/H13-1,"")) | M15: =IF(OR(M13="",I13=""),"",IFERROR(M13/I13-1,"")) | N15: =IF(OR(N13="",J13=""),"",IFERROR(N13/J13-1,"")) | P15: =IF(OR(P13="",O13=""),"",IFERROR(P13/O13-1,"")) | Q15: =IF(OR(Q13="",P13=""),"",IFERROR(Q13/P13-1,"")) | R15: =IF(OR(R13="",Q13=""),"",IFERROR(R13/Q13-1,"")) | S15: =IF(OR(S13="",R13=""),"",IFERROR(S13/R13-1,"")) | T15: =IF(OR(T13="",S13=""),"",IFERROR(T13/S13-1,"")) | U15: =IF(OR(U13="",T13=""),"",IFERROR(U13/T13-1,"")) | V15: =IF(OR(V13="",U13=""),"",IFERROR(V13/U13-1,"")) | W15: =IF(OR(W13="",V13=""),"",IFERROR(W13/V13-1,"")) | ... AC15: =IF(OR(AC13="",AB13=""),"",IFERROR(AC13/AB13-1,""))
A16: 해외 사업 | C16: 310.514 | D16: 348.894 | E16: 342.352 | F16: 149.984 | G16: 354.933 | H16: 358.907 | I16: 386.478 | J16: 336.956 | K16: 409.98 | L16: 372.644 | V16: 1151.744 | W16: 1437.274 | X16: 1539.202
A17: 비중 | C17: =IF(OR(C16="",C4=""),"",IFERROR(C16/C4,"")) | D17: =IF(OR(D16="",D4=""),"",IFERROR(D16/D4,"")) | E17: =IF(OR(E16="",E4=""),"",IFERROR(E16/E4,"")) | F17: =IF(OR(F16="",F4=""),"",IFERROR(F16/F4,"")) | G17: =IF(OR(G16="",G4=""),"",IFERROR(G16/G4,"")) | H17: =IF(OR(H16="",H4=""),"",IFERROR(H16/H4,"")) | I17: =IF(OR(I16="",I4=""),"",IFERROR(I16/I4,"")) | J17: =IF(OR(J16="",J4=""),"",IFERROR(J16/J4,"")) | ... AC17: =IF(OR(AC16="",AC4=""),"",IFERROR(AC16/AC4,""))
A18: YoY | G18: =IF(OR(G16="",C16=""),"",IFERROR(G16/C16-1,"")) | H18: =IF(OR(H16="",D16=""),"",IFERROR(H16/D16-1,"")) | I18: =IF(OR(I16="",E16=""),"",IFERROR(I16/E16-1,"")) | J18: =IF(OR(J16="",F16=""),"",IFERROR(J16/F16-1,"")) | K18: =IF(OR(K16="",G16=""),"",IFERROR(K16/G16-1,"")) | L18: =IF(OR(L16="",H16=""),"",IFERROR(L16/H16-1,"")) | M18: =IF(OR(M16="",I16=""),"",IFERROR(M16/I16-1,"")) | N18: =IF(OR(N16="",J16=""),"",IFERROR(N16/J16-1,"")) | P18: =IF(OR(P16="",O16=""),"",IFERROR(P16/O16-1,"")) | Q18: =IF(OR(Q16="",P16=""),"",IFERROR(Q16/P16-1,"")) | R18: =IF(OR(R16="",Q16=""),"",IFERROR(R16/Q16-1,"")) | S18: =IF(OR(S16="",R16=""),"",IFERROR(S16/R16-1,"")) | T18: =IF(OR(T16="",S16=""),"",IFERROR(T16/S16-1,"")) | U18: =IF(OR(U16="",T16=""),"",IFERROR(U16/T16-1,"")) | V18: =IF(OR(V16="",U16=""),"",IFERROR(V16/U16-1,"")) | W18: =IF(OR(W16="",V16=""),"",IFERROR(W16/V16-1,"")) | ... AC18: =IF(OR(AC16="",AB16=""),"",IFERROR(AC16/AB16-1,""))
A19: Restaurant Business Segments | C19: 1611.648 | G19: 1583.721 | K19: 1706.824
A20: 비중 | C20: =IF(OR(C19="",C4=""),"",IFERROR(C19/C4,"")) | D20: =IF(OR(D19="",D4=""),"",IFERROR(D19/D4,"")) | E20: =IF(OR(E19="",E4=""),"",IFERROR(E19/E4,"")) | F20: =IF(OR(F19="",F4=""),"",IFERROR(F19/F4,"")) | G20: =IF(OR(G19="",G4=""),"",IFERROR(G19/G4,"")) | H20: =IF(OR(H19="",H4=""),"",IFERROR(H19/H4,"")) | I20: =IF(OR(I19="",I4=""),"",IFERROR(I19/I4,"")) | J20: =IF(OR(J19="",J4=""),"",IFERROR(J19/J4,"")) | ... AC20: =IF(OR(AC19="",AC4=""),"",IFERROR(AC19/AC4,""))
A21: YoY | G21: =IF(OR(G19="",C19=""),"",IFERROR(G19/C19-1,"")) | H21: =IF(OR(H19="",D19=""),"",IFERROR(H19/D19-1,"")) | I21: =IF(OR(I19="",E19=""),"",IFERROR(I19/E19-1,"")) | J21: =IF(OR(J19="",F19=""),"",IFERROR(J19/F19-1,"")) | K21: =IF(OR(K19="",G19=""),"",IFERROR(K19/G19-1,"")) | L21: =IF(OR(L19="",H19=""),"",IFERROR(L19/H19-1,"")) | M21: =IF(OR(M19="",I19=""),"",IFERROR(M19/I19-1,"")) | N21: =IF(OR(N19="",J19=""),"",IFERROR(N19/J19-1,"")) | P21: =IF(OR(P19="",O19=""),"",IFERROR(P19/O19-1,"")) | Q21: =IF(OR(Q19="",P19=""),"",IFERROR(Q19/P19-1,"")) | R21: =IF(OR(R19="",Q19=""),"",IFERROR(R19/Q19-1,"")) | S21: =IF(OR(S19="",R19=""),"",IFERROR(S19/R19-1,"")) | T21: =IF(OR(T19="",S19=""),"",IFERROR(T19/S19-1,"")) | U21: =IF(OR(U19="",T19=""),"",IFERROR(U19/T19-1,"")) | V21: =IF(OR(V19="",U19=""),"",IFERROR(V19/U19-1,"")) | W21: =IF(OR(W19="",V19=""),"",IFERROR(W19/V19-1,"")) | ... AC21: =IF(OR(AC19="",AB19=""),"",IFERROR(AC19/AB19-1,""))
A22: Retail Sales Business Segments | C22: 163.594 | G22: 142.07 | K22: 133.743
A23: 비중 | C23: =IF(OR(C22="",C4=""),"",IFERROR(C22/C4,"")) | D23: =IF(OR(D22="",D4=""),"",IFERROR(D22/D4,"")) | E23: =IF(OR(E22="",E4=""),"",IFERROR(E22/E4,"")) | F23: =IF(OR(F22="",F4=""),"",IFERROR(F22/F4,"")) | G23: =IF(OR(G22="",G4=""),"",IFERROR(G22/G4,"")) | H23: =IF(OR(H22="",H4=""),"",IFERROR(H22/H4,"")) | I23: =IF(OR(I22="",I4=""),"",IFERROR(I22/I4,"")) | J23: =IF(OR(J22="",J4=""),"",IFERROR(J22/J4,"")) | ... AC23: =IF(OR(AC22="",AC4=""),"",IFERROR(AC22/AC4,""))
A24: YoY | G24: =IF(OR(G22="",C22=""),"",IFERROR(G22/C22-1,"")) | H24: =IF(OR(H22="",D22=""),"",IFERROR(H22/D22-1,"")) | I24: =IF(OR(I22="",E22=""),"",IFERROR(I22/E22-1,"")) | J24: =IF(OR(J22="",F22=""),"",IFERROR(J22/F22-1,"")) | K24: =IF(OR(K22="",G22=""),"",IFERROR(K22/G22-1,"")) | L24: =IF(OR(L22="",H22=""),"",IFERROR(L22/H22-1,"")) | M24: =IF(OR(M22="",I22=""),"",IFERROR(M22/I22-1,"")) | N24: =IF(OR(N22="",J22=""),"",IFERROR(N22/J22-1,"")) | P24: =IF(OR(P22="",O22=""),"",IFERROR(P22/O22-1,"")) | Q24: =IF(OR(Q22="",P22=""),"",IFERROR(Q22/P22-1,"")) | R24: =IF(OR(R22="",Q22=""),"",IFERROR(R22/Q22-1,"")) | S24: =IF(OR(S22="",R22=""),"",IFERROR(S22/R22-1,"")) | T24: =IF(OR(T22="",S22=""),"",IFERROR(T22/S22-1,"")) | U24: =IF(OR(U22="",T22=""),"",IFERROR(U22/T22-1,"")) | V24: =IF(OR(V22="",U22=""),"",IFERROR(V22/U22-1,"")) | W24: =IF(OR(W22="",V22=""),"",IFERROR(W22/V22-1,"")) | ... AC24: =IF(OR(AC22="",AB22=""),"",IFERROR(AC22/AB22-1,""))
A25: 매출원가
A26: 전체 매출원가 | C26: 1119.078 | D26: 1164.358 | E26: 1079.498 | F26: 737.004 | G26: 1149.124 | H26: 1204.381 | I26: 1174.85 | J26: 961.347 | K26: 1183.909 | L26: 1244.835 | O26: 3448.092 | P26: 3702.345 | Q26: 4049.493 | R26: 4057.732 | S26: 3197.46 | T26: 3266.112 | U26: 3729.3 | V26: 4099.938 | W26: 4489.702 | X26: 4762.017
A27: YoY | G27: =IF(OR(G26="",C26=""),"",IF(C26<=0,"",IFERROR(G26/C26-1,""))) | H27: =IF(OR(H26="",D26=""),"",IF(D26<=0,"",IFERROR(H26/D26-1,""))) | I27: =IF(OR(I26="",E26=""),"",IF(E26<=0,"",IFERROR(I26/E26-1,""))) | J27: =IF(OR(J26="",F26=""),"",IF(F26<=0,"",IFERROR(J26/F26-1,""))) | K27: =IF(OR(K26="",G26=""),"",IF(G26<=0,"",IFERROR(K26/G26-1,""))) | L27: =IF(OR(L26="",H26=""),"",IF(H26<=0,"",IFERROR(L26/H26-1,""))) | M27: =IF(OR(M26="",I26=""),"",IF(I26<=0,"",IFERROR(M26/I26-1,""))) | N27: =IF(OR(N26="",J26=""),"",IF(J26<=0,"",IFERROR(N26/J26-1,""))) | P27: =IF(OR(P26="",O26=""),"",IF(O26<=0,"",IFERROR(P26/O26-1,""))) | Q27: =IF(OR(Q26="",P26=""),"",IF(P26<=0,"",IFERROR(Q26/P26-1,""))) | R27: =IF(OR(R26="",Q26=""),"",IF(Q26<=0,"",IFERROR(R26/Q26-1,""))) | S27: =IF(OR(S26="",R26=""),"",IF(R26<=0,"",IFERROR(S26/R26-1,""))) | T27: =IF(OR(T26="",S26=""),"",IF(S26<=0,"",IFERROR(T26/S26-1,""))) | U27: =IF(OR(U26="",T26=""),"",IF(T26<=0,"",IFERROR(U26/T26-1,""))) | V27: =IF(OR(V26="",U26=""),"",IF(U26<=0,"",IFERROR(V26/U26-1,""))) | W27: =IF(OR(W26="",V26=""),"",IF(V26<=0,"",IFERROR(W26/V26-1,""))) | ... AC27: =IF(OR(AC26="",AB26=""),"",IF(AB26<=0,"",IFERROR(AC26/AB26-1,"")))
A28: 매출총이익 | C28: =IF(OR(C4="",C26=""),"",IFERROR(C4-C26,"")) | D28: =IF(OR(D4="",D26=""),"",IFERROR(D4-D26,"")) | E28: =IF(OR(E4="",E26=""),"",IFERROR(E4-E26,"")) | F28: =IF(OR(F4="",F26=""),"",IFERROR(F4-F26,"")) | G28: =IF(OR(G4="",G26=""),"",IFERROR(G4-G26,"")) | H28: =IF(OR(H4="",H26=""),"",IFERROR(H4-H26,"")) | I28: =IF(OR(I4="",I26=""),"",IFERROR(I4-I26,"")) | J28: =IF(OR(J4="",J26=""),"",IFERROR(J4-J26,"")) | ... X28: =IF(OR(X4="",X26=""),"",IFERROR(X4-X26,""))
A29: GPM | C29: =IF(OR(C28="",C4=""),"",IFERROR(C28/C4,"")) | D29: =IF(OR(D28="",D4=""),"",IFERROR(D28/D4,"")) | E29: =IF(OR(E28="",E4=""),"",IFERROR(E28/E4,"")) | F29: =IF(OR(F28="",F4=""),"",IFERROR(F28/F4,"")) | G29: =IF(OR(G28="",G4=""),"",IFERROR(G28/G4,"")) | H29: =IF(OR(H28="",H4=""),"",IFERROR(H28/H4,"")) | I29: =IF(OR(I28="",I4=""),"",IFERROR(I28/I4,"")) | J29: =IF(OR(J28="",J4=""),"",IFERROR(J28/J4,"")) | ... AC29: =IF(OR(AC28="",AC4=""),"",IFERROR(AC28/AC4,""))
A30: YoY | G30: =IF(OR(G28="",C28=""),"",IF(C28<=0,"",IFERROR(G28/C28-1,""))) | H30: =IF(OR(H28="",D28=""),"",IF(D28<=0,"",IFERROR(H28/D28-1,""))) | I30: =IF(OR(I28="",E28=""),"",IF(E28<=0,"",IFERROR(I28/E28-1,""))) | J30: =IF(OR(J28="",F28=""),"",IF(F28<=0,"",IFERROR(J28/F28-1,""))) | K30: =IF(OR(K28="",G28=""),"",IF(G28<=0,"",IFERROR(K28/G28-1,""))) | L30: =IF(OR(L28="",H28=""),"",IF(H28<=0,"",IFERROR(L28/H28-1,""))) | M30: =IF(OR(M28="",I28=""),"",IF(I28<=0,"",IFERROR(M28/I28-1,""))) | N30: =IF(OR(N28="",J28=""),"",IF(J28<=0,"",IFERROR(N28/J28-1,""))) | P30: =IF(OR(P28="",O28=""),"",IF(O28<=0,"",IFERROR(P28/O28-1,""))) | Q30: =IF(OR(Q28="",P28=""),"",IF(P28<=0,"",IFERROR(Q28/P28-1,""))) | R30: =IF(OR(R28="",Q28=""),"",IF(Q28<=0,"",IFERROR(R28/Q28-1,""))) | S30: =IF(OR(S28="",R28=""),"",IF(R28<=0,"",IFERROR(S28/R28-1,""))) | T30: =IF(OR(T28="",S28=""),"",IF(S28<=0,"",IFERROR(T28/S28-1,""))) | U30: =IF(OR(U28="",T28=""),"",IF(T28<=0,"",IFERROR(U28/T28-1,""))) | V30: =IF(OR(V28="",U28=""),"",IF(U28<=0,"",IFERROR(V28/U28-1,""))) | W30: =IF(OR(W28="",V28=""),"",IF(V28<=0,"",IFERROR(W28/V28-1,""))) | ... AC30: =IF(OR(AC28="",AB28=""),"",IF(AB28<=0,"",IFERROR(AC28/AB28-1,"")))
A31: 판매관리비
A32: 전체 판관비 | C32: 874.853 | D32: 865.874 | E32: 861.318 | F32: 686.468 | G32: 919.844 | H32: 963.136 | I32: 1010.182 | J32: 586.15 | K32: 1061.502 | L32: 1021.989 | O32: 3437.404 | P32: 3650.976 | Q32: 3956.515 | R32: 4007.669 | S32: 3247.401 | T32: 2992.36 | U32: 3209.876 | V32: 3288.513 | W32: 3479.312 | X32: 3877.842
A33: YoY | G33: =IF(OR(G32="",C32=""),"",IF(C32<=0,"",IFERROR(G32/C32-1,""))) | H33: =IF(OR(H32="",D32=""),"",IF(D32<=0,"",IFERROR(H32/D32-1,""))) | I33: =IF(OR(I32="",E32=""),"",IF(E32<=0,"",IFERROR(I32/E32-1,""))) | J33: =IF(OR(J32="",F32=""),"",IF(F32<=0,"",IFERROR(J32/F32-1,""))) | K33: =IF(OR(K32="",G32=""),"",IF(G32<=0,"",IFERROR(K32/G32-1,""))) | L33: =IF(OR(L32="",H32=""),"",IF(H32<=0,"",IFERROR(L32/H32-1,""))) | M33: =IF(OR(M32="",I32=""),"",IF(I32<=0,"",IFERROR(M32/I32-1,""))) | N33: =IF(OR(N32="",J32=""),"",IF(J32<=0,"",IFERROR(N32/J32-1,""))) | P33: =IF(OR(P32="",O32=""),"",IF(O32<=0,"",IFERROR(P32/O32-1,""))) | Q33: =IF(OR(Q32="",P32=""),"",IF(P32<=0,"",IFERROR(Q32/P32-1,""))) | R33: =IF(OR(R32="",Q32=""),"",IF(Q32<=0,"",IFERROR(R32/Q32-1,""))) | S33: =IF(OR(S32="",R32=""),"",IF(R32<=0,"",IFERROR(S32/R32-1,""))) | T33: =IF(OR(T32="",S32=""),"",IF(S32<=0,"",IFERROR(T32/S32-1,""))) | U33: =IF(OR(U32="",T32=""),"",IF(T32<=0,"",IFERROR(U32/T32-1,""))) | V33: =IF(OR(V32="",U32=""),"",IF(U32<=0,"",IFERROR(V32/U32-1,""))) | W33: =IF(OR(W32="",V32=""),"",IF(V32<=0,"",IFERROR(W32/V32-1,""))) | ... AC33: =IF(OR(AC32="",AB32=""),"",IF(AB32<=0,"",IFERROR(AC32/AB32-1,"")))
A34: 영업이익 | B34: MW = 매출 × OPM | C34: 91.825 | D34: 177.684 | E34: 51.257 | F34: -85.425 | G34: 11.757 | H34: 58.616 | I34: -30.516 | J34: 224.578 | K34: 5.136 | L34: 95.965 | O34: 427.328 | P34: 297.236 | Q34: 285.435 | R34: 202.614 | S34: -647.451 | T34: -343.402 | U34: 168.106 | V34: 235.341 | W34: 264.435 | X34: 4.653 | Y34: =IF(OR(Y4="",Y35=""),"",IFERROR(Y4*Y35,"")) | Z34: =IF(OR(Z4="",Z35=""),"",IFERROR(Z4*Z35,"")) | AA34: =IF(OR(AA4="",AA35=""),"",IFERROR(AA4*AA35,"")) | AB34: =IF(OR(AB4="",AB35=""),"",IFERROR(AB4*AB35,"")) | AC34: =IF(OR(AC4="",AC35=""),"",IFERROR(AC4*AC35,""))
A35: OPM | B35: MW 입력 | C35: =IF(OR(C34="",C4=""),"",IFERROR(C34/C4,"")) | D35: =IF(OR(D34="",D4=""),"",IFERROR(D34/D4,"")) | E35: =IF(OR(E34="",E4=""),"",IFERROR(E34/E4,"")) | F35: =IF(OR(F34="",F4=""),"",IFERROR(F34/F4,"")) | G35: =IF(OR(G34="",G4=""),"",IFERROR(G34/G4,"")) | H35: =IF(OR(H34="",H4=""),"",IFERROR(H34/H4,"")) | I35: =IF(OR(I34="",I4=""),"",IFERROR(I34/I4,"")) | J35: =IF(OR(J34="",J4=""),"",IFERROR(J34/J4,"")) | ... X35: =IF(OR(X34="",X4=""),"",IFERROR(X34/X4,""))
A36: 증가율 | G36: =IF(OR(G34="",C34=""),"",IFERROR(G34/C34-1,"")) | H36: =IF(OR(H34="",D34=""),"",IFERROR(H34/D34-1,"")) | I36: =IF(OR(I34="",E34=""),"",IFERROR(I34/E34-1,"")) | J36: =IF(OR(J34="",F34=""),"",IFERROR(J34/F34-1,"")) | K36: =IF(OR(K34="",G34=""),"",IFERROR(K34/G34-1,"")) | L36: =IF(OR(L34="",H34=""),"",IFERROR(L34/H34-1,"")) | M36: =IF(OR(M34="",I34=""),"",IFERROR(M34/I34-1,"")) | N36: =IF(OR(N34="",J34=""),"",IFERROR(N34/J34-1,"")) | P36: =IF(OR(P34="",O34=""),"",IFERROR(P34/O34-1,"")) | Q36: =IF(OR(Q34="",P34=""),"",IFERROR(Q34/P34-1,"")) | R36: =IF(OR(R34="",Q34=""),"",IFERROR(R34/Q34-1,"")) | S36: =IF(OR(S34="",R34=""),"",IFERROR(S34/R34-1,"")) | T36: =IF(OR(T34="",S34=""),"",IFERROR(T34/S34-1,"")) | U36: =IF(OR(U34="",T34=""),"",IFERROR(U34/T34-1,"")) | V36: =IF(OR(V34="",U34=""),"",IFERROR(V34/U34-1,"")) | W36: =IF(OR(W34="",V34=""),"",IFERROR(W34/V34-1,"")) | ... AC36: =IF(OR(AC34="",AB34=""),"",IFERROR(AC34/AB34-1,""))
A37: 비용의 성격별 분류 | B37: 참고 데이터
A38: 총 판관비 | O38: =IF(O32="","",O32) | P38: =IF(P32="","",P32) | Q38: =IF(Q32="","",Q32) | R38: =IF(R32="","",R32) | S38: =IF(S32="","",S32) | T38: =IF(T32="","",T32) | U38: =IF(U32="","",U32) | V38: =IF(V32="","",V32) | ... X38: =IF(X32="","",X32)
A39: 급여 | B39: 고정비 | O39: 1294.209 | P39: 1430.946 | Q39: 1512.451 | R39: 1578.299 | S39: 1264.341 | T39: 1134.829 | U39: 1238.444 | V39: 1202.665 | W39: 1315.111 | X39: 1500.55
A40: % of Sales | O40: =IF(OR(O39="",O4=""),"",IFERROR(O39/O4,"")) | P40: =IF(OR(P39="",P4=""),"",IFERROR(P39/P4,"")) | Q40: =IF(OR(Q39="",Q4=""),"",IFERROR(Q39/Q4,"")) | R40: =IF(OR(R39="",R4=""),"",IFERROR(R39/R4,"")) | S40: =IF(OR(S39="",S4=""),"",IFERROR(S39/S4,"")) | T40: =IF(OR(T39="",T4=""),"",IFERROR(T39/T4,"")) | U40: =IF(OR(U39="",U4=""),"",IFERROR(U39/U4,"")) | V40: =IF(OR(V39="",V4=""),"",IFERROR(V39/V4,"")) | ... X40: =IF(OR(X39="",X4=""),"",IFERROR(X39/X4,""))
A41: 감가상각비 | B41: 고정비 | O41: 109.043 | P41: 127.532 | Q41: 149.359 | R41: 159.782 | S41: 146.625 | T41: 120.575 | U41: 101.912 | V41: 102.209 | W41: 115.928 | X41: 152.941
A42: % of Sales | O42: =IF(OR(O41="",O4=""),"",IFERROR(O41/O4,"")) | P42: =IF(OR(P41="",P4=""),"",IFERROR(P41/P4,"")) | Q42: =IF(OR(Q41="",Q4=""),"",IFERROR(Q41/Q4,"")) | R42: =IF(OR(R41="",R4=""),"",IFERROR(R41/R4,"")) | S42: =IF(OR(S41="",S4=""),"",IFERROR(S41/S4,"")) | T42: =IF(OR(T41="",T4=""),"",IFERROR(T41/T4,"")) | U42: =IF(OR(U41="",U4=""),"",IFERROR(U41/U4,"")) | V42: =IF(OR(V41="",V4=""),"",IFERROR(V41/V4,"")) | ... X42: =IF(OR(X41="",X4=""),"",IFERROR(X41/X4,""))
A43: 지급수수료 | B43: 고정비
A44: % of Sales | O44: =IF(OR(O43="",O4=""),"",IFERROR(O43/O4,"")) | P44: =IF(OR(P43="",P4=""),"",IFERROR(P43/P4,"")) | Q44: =IF(OR(Q43="",Q4=""),"",IFERROR(Q43/Q4,"")) | R44: =IF(OR(R43="",R4=""),"",IFERROR(R43/R4,"")) | S44: =IF(OR(S43="",S4=""),"",IFERROR(S43/S4,"")) | T44: =IF(OR(T43="",T4=""),"",IFERROR(T43/T4,"")) | U44: =IF(OR(U43="",U4=""),"",IFERROR(U43/U4,"")) | V44: =IF(OR(V43="",V4=""),"",IFERROR(V43/V4,"")) | ... X44: =IF(OR(X43="",X4=""),"",IFERROR(X43/X4,""))
A45: 연구개발비 | B45: 변동비
A46: % of Sales | O46: =IF(OR(O45="",O4=""),"",IFERROR(O45/O4,"")) | P46: =IF(OR(P45="",P4=""),"",IFERROR(P45/P4,"")) | Q46: =IF(OR(Q45="",Q4=""),"",IFERROR(Q45/Q4,"")) | R46: =IF(OR(R45="",R4=""),"",IFERROR(R45/R4,"")) | S46: =IF(OR(S45="",S4=""),"",IFERROR(S45/S4,"")) | T46: =IF(OR(T45="",T4=""),"",IFERROR(T45/T4,"")) | U46: =IF(OR(U45="",U4=""),"",IFERROR(U45/U4,"")) | V46: =IF(OR(V45="",V4=""),"",IFERROR(V45/V4,"")) | ... X46: =IF(OR(X45="",X4=""),"",IFERROR(X45/X4,""))
A47: 기타비용 | B47: 변동비 | O47: =IF(OR(O38="",O39="",O41="",O43="",O45=""),"",IFERROR(O38-O39-O41-O43-O45,"")) | P47: =IF(OR(P38="",P39="",P41="",P43="",P45=""),"",IFERROR(P38-P39-P41-P43-P45,"")) | Q47: =IF(OR(Q38="",Q39="",Q41="",Q43="",Q45=""),"",IFERROR(Q38-Q39-Q41-Q43-Q45,"")) | R47: =IF(OR(R38="",R39="",R41="",R43="",R45=""),"",IFERROR(R38-R39-R41-R43-R45,"")) | S47: =IF(OR(S38="",S39="",S41="",S43="",S45=""),"",IFERROR(S38-S39-S41-S43-S45,"")) | T47: =IF(OR(T38="",T39="",T41="",T43="",T45=""),"",IFERROR(T38-T39-T41-T43-T45,"")) | U47: =IF(OR(U38="",U39="",U41="",U43="",U45=""),"",IFERROR(U38-U39-U41-U43-U45,"")) | V47: =IF(OR(V38="",V39="",V41="",V43="",V45=""),"",IFERROR(V38-V39-V41-V43-V45,"")) | ... X47: =IF(OR(X38="",X39="",X41="",X43="",X45=""),"",IFERROR(X38-X39-X41-X43-X45,""))
A48: % of Sales | O48: =IF(OR(O47="",O4=""),"",IFERROR(O47/O4,"")) | P48: =IF(OR(P47="",P4=""),"",IFERROR(P47/P4,"")) | Q48: =IF(OR(Q47="",Q4=""),"",IFERROR(Q47/Q4,"")) | R48: =IF(OR(R47="",R4=""),"",IFERROR(R47/R4,"")) | S48: =IF(OR(S47="",S4=""),"",IFERROR(S47/S4,"")) | T48: =IF(OR(T47="",T4=""),"",IFERROR(T47/T4,"")) | U48: =IF(OR(U47="",U4=""),"",IFERROR(U47/U4,"")) | V48: =IF(OR(V47="",V4=""),"",IFERROR(V47/V4,"")) | ... X48: =IF(OR(X47="",X4=""),"",IFERROR(X47/X4,""))
A49: 당기순이익 추정
A50: 특별이익 | C50: 0 | D50: 4.407 | E50: 7.423 | F50: 17.595 | I50: 0.182 | J50: 12.562 | O50: 421.199 | P50: 0 | Q50: 8.546 | R50: 1.004 | S50: 10.016 | T50: 5.701 | U50: 0.361 | V50: 29.425 | W50: 12.744 | X50: 0.756 | Y50: =IF(OR(Y4="",Y51=""),"",IFERROR(Y4*Y51,"")) | Z50: =IF(OR(Z4="",Z51=""),"",IFERROR(Z4*Z51,"")) | AA50: =IF(OR(AA4="",AA51=""),"",IFERROR(AA4*AA51,"")) | AB50: =IF(OR(AB4="",AB51=""),"",IFERROR(AB4*AB51,"")) | AC50: =IF(OR(AC4="",AC51=""),"",IFERROR(AC4*AC51,""))
A51: % of Sales | B51: MW = 최근 3년 평균 | C51: =IF(OR(C50="",C4=""),"",IFERROR(C50/C4,"")) | D51: =IF(OR(D50="",D4=""),"",IFERROR(D50/D4,"")) | E51: =IF(OR(E50="",E4=""),"",IFERROR(E50/E4,"")) | F51: =IF(OR(F50="",F4=""),"",IFERROR(F50/F4,"")) | G51: =IF(OR(G50="",G4=""),"",IFERROR(G50/G4,"")) | H51: =IF(OR(H50="",H4=""),"",IFERROR(H50/H4,"")) | I51: =IF(OR(I50="",I4=""),"",IFERROR(I50/I4,"")) | J51: =IF(OR(J50="",J4=""),"",IFERROR(J50/J4,"")) | ... X51: =IF(OR(X50="",X4=""),"",IFERROR(X50/X4,"")) | Y51: =IFERROR(AVERAGE(V51,W51,X51),"") | Z51: =Y51 | AA51: =Z51 | AB51: =AA51 | AC51: =AB51
A52: 특별손실 | C52: 4.085 | D52: 0.111 | E52: 6.595 | F52: 178.193 | G52: 0 | H52: 0.043 | I52: 0.346 | J52: 38.061 | K52: 0.018 | L52: 0.046 | O52: 53.901 | P52: 3.159 | Q52: 64.19 | R52: 81.868 | S52: 265.878 | T52: 95.472 | U52: 87.122 | V52: 188.984 | W52: 38.45 | X52: 6.398 | Y52: =IF(OR(Y4="",Y53=""),"",IFERROR(Y4*Y53,"")) | Z52: =IF(OR(Z4="",Z53=""),"",IFERROR(Z4*Z53,"")) | AA52: =IF(OR(AA4="",AA53=""),"",IFERROR(AA4*AA53,"")) | AB52: =IF(OR(AB4="",AB53=""),"",IFERROR(AB4*AB53,"")) | AC52: =IF(OR(AC4="",AC53=""),"",IFERROR(AC4*AC53,""))
A53: % of Sales | C53: =IF(OR(C52="",C4=""),"",IFERROR(C52/C4,"")) | D53: =IF(OR(D52="",D4=""),"",IFERROR(D52/D4,"")) | E53: =IF(OR(E52="",E4=""),"",IFERROR(E52/E4,"")) | F53: =IF(OR(F52="",F4=""),"",IFERROR(F52/F4,"")) | G53: =IF(OR(G52="",G4=""),"",IFERROR(G52/G4,"")) | H53: =IF(OR(H52="",H4=""),"",IFERROR(H52/H4,"")) | I53: =IF(OR(I52="",I4=""),"",IFERROR(I52/I4,"")) | J53: =IF(OR(J52="",J4=""),"",IFERROR(J52/J4,"")) | ... X53: =IF(OR(X52="",X4=""),"",IFERROR(X52/X4,"")) | Y53: =IFERROR(AVERAGE(V53,W53,X53),"") | Z53: =Y53 | AA53: =Z53 | AB53: =AA53 | AC53: =AB53
A54: 영업외수익 | C54: 154.158 | D54: 46.499 | E54: 58.883 | F54: -50.03 | G54: 157.43 | H54: 64.908 | I54: 47.817 | J54: 24.093 | K54: 160.022 | L54: 46.229 | O54: 159.217 | P54: 152.153 | Q54: 176.495 | R54: 147.282 | S54: 185.166 | T54: 346.614 | U54: 135.22 | V54: 209.51 | W54: 294.248 | X54: 297.133 | Y54: =IF(OR(Y4="",Y55=""),"",IFERROR(Y4*Y55,"")) | Z54: =IF(OR(Z4="",Z55=""),"",IFERROR(Z4*Z55,"")) | AA54: =IF(OR(AA4="",AA55=""),"",IFERROR(AA4*AA55,"")) | AB54: =IF(OR(AB4="",AB55=""),"",IFERROR(AB4*AB55,"")) | AC54: =IF(OR(AC4="",AC55=""),"",IFERROR(AC4*AC55,""))
A55: % of Sales | C55: =IF(OR(C54="",C4=""),"",IFERROR(C54/C4,"")) | D55: =IF(OR(D54="",D4=""),"",IFERROR(D54/D4,"")) | E55: =IF(OR(E54="",E4=""),"",IFERROR(E54/E4,"")) | F55: =IF(OR(F54="",F4=""),"",IFERROR(F54/F4,"")) | G55: =IF(OR(G54="",G4=""),"",IFERROR(G54/G4,"")) | H55: =IF(OR(H54="",H4=""),"",IFERROR(H54/H4,"")) | I55: =IF(OR(I54="",I4=""),"",IFERROR(I54/I4,"")) | J55: =IF(OR(J54="",J4=""),"",IFERROR(J54/J4,"")) | ... X55: =IF(OR(X54="",X4=""),"",IFERROR(X54/X4,"")) | Y55: =IFERROR(AVERAGE(V55,W55,X55),"") | Z55: =Y55 | AA55: =Z55 | AB55: =AA55 | AC55: =AB55
A56: 영업외비용 | C56: 24.221 | D56: 23.915 | E56: 23.757 | F56: 7.289 | G56: 23.801 | H56: 23.766 | I56: 23.514 | J56: 24.115 | K56: 24.622 | L56: 39.75 | O56: 40.423 | P56: 49.773 | Q56: 49.398 | R56: 59.065 | S56: 52.244 | T56: 73.135 | U56: 79.051 | V56: 79.182 | W56: 95.196 | X56: 94.244 | Y56: =IF(OR(Y4="",Y57=""),"",IFERROR(Y4*Y57,"")) | Z56: =IF(OR(Z4="",Z57=""),"",IFERROR(Z4*Z57,"")) | AA56: =IF(OR(AA4="",AA57=""),"",IFERROR(AA4*AA57,"")) | AB56: =IF(OR(AB4="",AB57=""),"",IFERROR(AB4*AB57,"")) | AC56: =IF(OR(AC4="",AC57=""),"",IFERROR(AC4*AC57,""))
A57: % of Sales | C57: =IF(OR(C56="",C4=""),"",IFERROR(C56/C4,"")) | D57: =IF(OR(D56="",D4=""),"",IFERROR(D56/D4,"")) | E57: =IF(OR(E56="",E4=""),"",IFERROR(E56/E4,"")) | F57: =IF(OR(F56="",F4=""),"",IFERROR(F56/F4,"")) | G57: =IF(OR(G56="",G4=""),"",IFERROR(G56/G4,"")) | H57: =IF(OR(H56="",H4=""),"",IFERROR(H56/H4,"")) | I57: =IF(OR(I56="",I4=""),"",IFERROR(I56/I4,"")) | J57: =IF(OR(J56="",J4=""),"",IFERROR(J56/J4,"")) | ... X57: =IF(OR(X56="",X4=""),"",IFERROR(X56/X4,"")) | Y57: =IFERROR(AVERAGE(V57,W57,X57),"") | Z57: =Y57 | AA57: =Z57 | AB57: =AA57 | AC57: =AB57
A58: 법인세비용차감전순이익(손실) | C58: 217.678 | D58: 204.563 | E58: 87.211 | F58: -303.342 | G58: 145.387 | H58: 99.714 | I58: -6.376 | J58: 199.055 | K58: 140.518 | L58: 102.398 | O58: 913.42 | P58: 396.455 | Q58: 356.889 | R58: 209.967 | S58: -770.391 | T58: -159.694 | U58: 137.514 | V58: 206.11 | W58: 437.78 | X58: 201.9 | Y58: =IF(OR(Y34=""),"",IFERROR(Y34+N(Y50)-N(Y52)+N(Y54)-N(Y56),"")) | Z58: =IF(OR(Z34=""),"",IFERROR(Z34+N(Z50)-N(Z52)+N(Z54)-N(Z56),"")) | AA58: =IF(OR(AA34=""),"",IFERROR(AA34+N(AA50)-N(AA52)+N(AA54)-N(AA56),"")) | AB58: =IF(OR(AB34=""),"",IFERROR(AB34+N(AB50)-N(AB52)+N(AB54)-N(AB56),"")) | AC58: =IF(OR(AC34=""),"",IFERROR(AC34+N(AC50)-N(AC52)+N(AC54)-N(AC56),""))
A59: YoY | G59: =IF(OR(G58="",C58=""),"",IF(C58<=0,"",IFERROR(G58/C58-1,""))) | H59: =IF(OR(H58="",D58=""),"",IF(D58<=0,"",IFERROR(H58/D58-1,""))) | I59: =IF(OR(I58="",E58=""),"",IF(E58<=0,"",IFERROR(I58/E58-1,""))) | J59: =IF(OR(J58="",F58=""),"",IF(F58<=0,"",IFERROR(J58/F58-1,""))) | K59: =IF(OR(K58="",G58=""),"",IF(G58<=0,"",IFERROR(K58/G58-1,""))) | L59: =IF(OR(L58="",H58=""),"",IF(H58<=0,"",IFERROR(L58/H58-1,""))) | M59: =IF(OR(M58="",I58=""),"",IF(I58<=0,"",IFERROR(M58/I58-1,""))) | N59: =IF(OR(N58="",J58=""),"",IF(J58<=0,"",IFERROR(N58/J58-1,""))) | P59: =IF(OR(P58="",O58=""),"",IF(O58<=0,"",IFERROR(P58/O58-1,""))) | Q59: =IF(OR(Q58="",P58=""),"",IF(P58<=0,"",IFERROR(Q58/P58-1,""))) | R59: =IF(OR(R58="",Q58=""),"",IF(Q58<=0,"",IFERROR(R58/Q58-1,""))) | S59: =IF(OR(S58="",R58=""),"",IF(R58<=0,"",IFERROR(S58/R58-1,""))) | T59: =IF(OR(T58="",S58=""),"",IF(S58<=0,"",IFERROR(T58/S58-1,""))) | U59: =IF(OR(U58="",T58=""),"",IF(T58<=0,"",IFERROR(U58/T58-1,""))) | V59: =IF(OR(V58="",U58=""),"",IF(U58<=0,"",IFERROR(V58/U58-1,""))) | W59: =IF(OR(W58="",V58=""),"",IF(V58<=0,"",IFERROR(W58/V58-1,""))) | ... AC59: =IF(OR(AC58="",AB58=""),"",IF(AB58<=0,"",IFERROR(AC58/AB58-1,"")))
A60: 법인세비용(수익) | C60: 68.745 | D60: 67.554 | E60: 38.177 | F60: -128.892 | G60: 49.83 | H60: 44.844 | I60: 9.224 | J60: 97.679 | K60: 45.43 | L60: 57.027 | O60: 341.8 | P60: 154.918 | Q60: 139.083 | R60: 95.27 | S60: -122.795 | T60: 8.948 | U60: 72.335 | V60: 45.584 | W60: 201.577 | X60: 141.759 | Y60: =IF(OR(Y58="",Y61=""),"",IFERROR(MAX(Y58,0)*Y61,"")) | Z60: =IF(OR(Z58="",Z61=""),"",IFERROR(MAX(Z58,0)*Z61,"")) | AA60: =IF(OR(AA58="",AA61=""),"",IFERROR(MAX(AA58,0)*AA61,"")) | AB60: =IF(OR(AB58="",AB61=""),"",IFERROR(MAX(AB58,0)*AB61,"")) | AC60: =IF(OR(AC58="",AC61=""),"",IFERROR(MAX(AC58,0)*AC61,""))
A61: 법인세율 | B61: MW 기본 30% | C61: =IF(OR(C60="",C58=""),"",IFERROR(C60/C58,"")) | D61: =IF(OR(D60="",D58=""),"",IFERROR(D60/D58,"")) | E61: =IF(OR(E60="",E58=""),"",IFERROR(E60/E58,"")) | F61: =IF(OR(F60="",F58=""),"",IFERROR(F60/F58,"")) | G61: =IF(OR(G60="",G58=""),"",IFERROR(G60/G58,"")) | H61: =IF(OR(H60="",H58=""),"",IFERROR(H60/H58,"")) | I61: =IF(OR(I60="",I58=""),"",IFERROR(I60/I58,"")) | J61: =IF(OR(J60="",J58=""),"",IFERROR(J60/J58,"")) | ... X61: =IF(OR(X60="",X58=""),"",IFERROR(X60/X58,"")) | Y61: 0.3 | Z61: 0.3 | AA61: 0.3 | AB61: 0.3 | AC61: 0.3
A62: 당기순이익(손실) | C62: 148.932 | D62: 137.009 | E62: 49.034 | F62: -174.45 | G62: 95.556 | H62: 54.871 | I62: -15.6 | J62: 101.376 | K62: 95.087 | L62: 45.372 | O62: 571.619 | P62: 241.537 | Q62: 217.805 | R62: 114.696 | S62: -647.596 | T62: -168.642 | U62: 65.178 | V62: 160.525 | W62: 236.203 | X62: 60.14 | Y62: =IF(OR(Y58=""),"",IFERROR(Y58-Y60,"")) | Z62: =IF(OR(Z58=""),"",IFERROR(Z58-Z60,"")) | AA62: =IF(OR(AA58=""),"",IFERROR(AA58-AA60,"")) | AB62: =IF(OR(AB58=""),"",IFERROR(AB58-AB60,"")) | AC62: =IF(OR(AC58=""),"",IFERROR(AC58-AC60,""))
A63: YoY | G63: =IF(OR(G62="",C62=""),"",IF(C62<=0,"",IFERROR(G62/C62-1,""))) | H63: =IF(OR(H62="",D62=""),"",IF(D62<=0,"",IFERROR(H62/D62-1,""))) | I63: =IF(OR(I62="",E62=""),"",IF(E62<=0,"",IFERROR(I62/E62-1,""))) | J63: =IF(OR(J62="",F62=""),"",IF(F62<=0,"",IFERROR(J62/F62-1,""))) | K63: =IF(OR(K62="",G62=""),"",IF(G62<=0,"",IFERROR(K62/G62-1,""))) | L63: =IF(OR(L62="",H62=""),"",IF(H62<=0,"",IFERROR(L62/H62-1,""))) | M63: =IF(OR(M62="",I62=""),"",IF(I62<=0,"",IFERROR(M62/I62-1,""))) | N63: =IF(OR(N62="",J62=""),"",IF(J62<=0,"",IFERROR(N62/J62-1,""))) | P63: =IF(OR(P62="",O62=""),"",IF(O62<=0,"",IFERROR(P62/O62-1,""))) | Q63: =IF(OR(Q62="",P62=""),"",IF(P62<=0,"",IFERROR(Q62/P62-1,""))) | R63: =IF(OR(R62="",Q62=""),"",IF(Q62<=0,"",IFERROR(R62/Q62-1,""))) | S63: =IF(OR(S62="",R62=""),"",IF(R62<=0,"",IFERROR(S62/R62-1,""))) | T63: =IF(OR(T62="",S62=""),"",IF(S62<=0,"",IFERROR(T62/S62-1,""))) | U63: =IF(OR(U62="",T62=""),"",IF(T62<=0,"",IFERROR(U62/T62-1,""))) | V63: =IF(OR(V62="",U62=""),"",IF(U62<=0,"",IFERROR(V62/U62-1,""))) | W63: =IF(OR(W62="",V62=""),"",IF(V62<=0,"",IFERROR(W62/V62-1,""))) | ... AC63: =IF(OR(AC62="",AB62=""),"",IF(AB62<=0,"",IFERROR(AC62/AB62-1,"")))
A64: 지배주주 순이익 | C64: 148.932 | D64: 137.009 | E64: 49.033 | F64: -174.449 | G64: 95.556 | H64: 54.871 | I64: -15.601 | J64: 101.376 | K64: 95.087 | L64: 45.371 | O64: 565.646 | P64: 237.157 | Q64: 210.377 | R64: 108.285 | S64: -647.596 | T64: -168.642 | U64: 65.178 | V64: 160.525 | W64: 236.202 | X64: 60.139 | Y64: =IF(OR(Y62="",Y65=""),"",IFERROR(Y62*Y65,"")) | Z64: =IF(OR(Z62="",Z65=""),"",IFERROR(Z62*Z65,"")) | AA64: =IF(OR(AA62="",AA65=""),"",IFERROR(AA62*AA65,"")) | AB64: =IF(OR(AB62="",AB65=""),"",IFERROR(AB62*AB65,"")) | AC64: =IF(OR(AC62="",AC65=""),"",IFERROR(AC62*AC65,""))
A65: 지배주주 순이익률 | B65: MW 기본 100% | C65: =IF(OR(C64="",C62=""),"",IFERROR(C64/C62,"")) | D65: =IF(OR(D64="",D62=""),"",IFERROR(D64/D62,"")) | E65: =IF(OR(E64="",E62=""),"",IFERROR(E64/E62,"")) | F65: =IF(OR(F64="",F62=""),"",IFERROR(F64/F62,"")) | G65: =IF(OR(G64="",G62=""),"",IFERROR(G64/G62,"")) | H65: =IF(OR(H64="",H62=""),"",IFERROR(H64/H62,"")) | I65: =IF(OR(I64="",I62=""),"",IFERROR(I64/I62,"")) | J65: =IF(OR(J64="",J62=""),"",IFERROR(J64/J62,"")) | ... X65: =IF(OR(X64="",X62=""),"",IFERROR(X64/X62,"")) | Y65: 1 | Z65: 1 | AA65: 1 | AB65: 1 | AC65: 1
A66: 지배주주 순이익 YoY | G66: =IF(OR(G64="",C64=""),"",IF(C64<=0,"",IFERROR(G64/C64-1,""))) | H66: =IF(OR(H64="",D64=""),"",IF(D64<=0,"",IFERROR(H64/D64-1,""))) | I66: =IF(OR(I64="",E64=""),"",IF(E64<=0,"",IFERROR(I64/E64-1,""))) | J66: =IF(OR(J64="",F64=""),"",IF(F64<=0,"",IFERROR(J64/F64-1,""))) | K66: =IF(OR(K64="",G64=""),"",IF(G64<=0,"",IFERROR(K64/G64-1,""))) | L66: =IF(OR(L64="",H64=""),"",IF(H64<=0,"",IFERROR(L64/H64-1,""))) | M66: =IF(OR(M64="",I64=""),"",IF(I64<=0,"",IFERROR(M64/I64-1,""))) | N66: =IF(OR(N64="",J64=""),"",IF(J64<=0,"",IFERROR(N64/J64-1,""))) | P66: =IF(OR(P64="",O64=""),"",IF(O64<=0,"",IFERROR(P64/O64-1,""))) | Q66: =IF(OR(Q64="",P64=""),"",IF(P64<=0,"",IFERROR(Q64/P64-1,""))) | R66: =IF(OR(R64="",Q64=""),"",IF(Q64<=0,"",IFERROR(R64/Q64-1,""))) | S66: =IF(OR(S64="",R64=""),"",IF(R64<=0,"",IFERROR(S64/R64-1,""))) | T66: =IF(OR(T64="",S64=""),"",IF(S64<=0,"",IFERROR(T64/S64-1,""))) | U66: =IF(OR(U64="",T64=""),"",IF(T64<=0,"",IFERROR(U64/T64-1,""))) | V66: =IF(OR(V64="",U64=""),"",IF(U64<=0,"",IFERROR(V64/U64-1,""))) | W66: =IF(OR(W64="",V64=""),"",IF(V64<=0,"",IFERROR(W64/V64-1,""))) | ... AC66: =IF(OR(AC64="",AB64=""),"",IF(AB64<=0,"",IFERROR(AC64/AB64-1,"")))
A67: 목표주가 산출
A68: 현재 주가 ()
A69: 발행주식수 (보통주)
A70: 시가총액 (백만엔) | B70: =IF(OR(B68="",B69=""),"",B68*B69/1000000.0)
A71: OPM | O71: =IF(O35="","",O35) | P71: =IF(P35="","",P35) | Q71: =IF(Q35="","",Q35) | R71: =IF(R35="","",R35) | S71: =IF(S35="","",S35) | T71: =IF(T35="","",T35) | U71: =IF(U35="","",U35) | V71: =IF(V35="","",V35) | ... AC71: =IF(AC35="","",AC35)
A72: 지배주주 순이익 증가율 | P72: =IF(OR(P64="",O64=""),"",IFERROR(P64/O64-1,"")) | Q72: =IF(OR(Q64="",P64=""),"",IFERROR(Q64/P64-1,"")) | R72: =IF(OR(R64="",Q64=""),"",IFERROR(R64/Q64-1,"")) | S72: =IF(OR(S64="",R64=""),"",IFERROR(S64/R64-1,"")) | T72: =IF(OR(T64="",S64=""),"",IFERROR(T64/S64-1,"")) | U72: =IF(OR(U64="",T64=""),"",IFERROR(U64/T64-1,"")) | V72: =IF(OR(V64="",U64=""),"",IFERROR(V64/U64-1,"")) | W72: =IF(OR(W64="",V64=""),"",IFERROR(W64/V64-1,"")) | ... AC72: =IF(OR(AC64="",AB64=""),"",IFERROR(AC64/AB64-1,""))
A73: P/E (현재 주가) | B73: 시총 ÷ 지배순이익 | X73: =IF(OR($B$70="",X64=""),"",IFERROR($B$70/X64,"")) | Y73: =IF(OR($B$70="",Y64=""),"",IFERROR($B$70/Y64,"")) | Z73: =IF(OR($B$70="",Z64=""),"",IFERROR($B$70/Z64,"")) | AA73: =IF(OR($B$70="",AA64=""),"",IFERROR($B$70/AA64,"")) | AB73: =IF(OR($B$70="",AB64=""),"",IFERROR($B$70/AB64,"")) | AC73: =IF(OR($B$70="",AC64=""),"",IFERROR($B$70/AC64,""))
A74: Target P/E | B74: 직접 입력
A75: EPS | B75: 지배순이익 ÷ 주식수 | O75: =IF(OR(O64="",$B$69=""),"",IFERROR(O64*1000000.0/$B$69,"")) | P75: =IF(OR(P64="",$B$69=""),"",IFERROR(P64*1000000.0/$B$69,"")) | Q75: =IF(OR(Q64="",$B$69=""),"",IFERROR(Q64*1000000.0/$B$69,"")) | R75: =IF(OR(R64="",$B$69=""),"",IFERROR(R64*1000000.0/$B$69,"")) | S75: =IF(OR(S64="",$B$69=""),"",IFERROR(S64*1000000.0/$B$69,"")) | T75: =IF(OR(T64="",$B$69=""),"",IFERROR(T64*1000000.0/$B$69,"")) | U75: =IF(OR(U64="",$B$69=""),"",IFERROR(U64*1000000.0/$B$69,"")) | V75: =IF(OR(V64="",$B$69=""),"",IFERROR(V64*1000000.0/$B$69,"")) | ... AC75: =IF(OR(AC64="",$B$69=""),"",IFERROR(AC64*1000000.0/$B$69,""))
A76: 목표주가 | Y76: =IF(OR(Y75="",Y74=""),"",IFERROR(Y75*Y74,"")) | Z76: =IF(OR(Z75="",Z74=""),"",IFERROR(Z75*Z74,"")) | AA76: =IF(OR(AA75="",AA74=""),"",IFERROR(AA75*AA74,"")) | AB76: =IF(OR(AB75="",AB74=""),"",IFERROR(AB75*AB74,"")) | AC76: =IF(OR(AC75="",AC74=""),"",IFERROR(AC75*AC74,""))
A77: 상승여력 | Y77: =IF(OR(Y76="",$B$68=""),"",IFERROR(Y76/$B$68-1,"")) | Z77: =IF(OR(Z76="",$B$68=""),"",IFERROR(Z76/$B$68-1,"")) | AA77: =IF(OR(AA76="",$B$68=""),"",IFERROR(AA76/$B$68-1,"")) | AB77: =IF(OR(AB76="",$B$68=""),"",IFERROR(AB76/$B$68-1,"")) | AC77: =IF(OR(AC76="",$B$68=""),"",IFERROR(AC76/$B$68-1,""))
A78: 자산가치 산출 | B78: 최신 분기 BS
A79: 현금및현금성자산 | X79: ='재무상태표'!G6 | Y79: ='재무상태표'!G6 | Z79: ='재무상태표'!G6 | AA79: ='재무상태표'!G6 | AB79: ='재무상태표'!G6 | AC79: ='재무상태표'!G6
A80: 단기금융상품 | X80: ='재무상태표'!G7 | Y80: ='재무상태표'!G7 | Z80: ='재무상태표'!G7 | AA80: ='재무상태표'!G7 | AB80: ='재무상태표'!G7 | AC80: ='재무상태표'!G7
A81: 투자부동산 | X81: ='재무상태표'!G14 | Y81: ='재무상태표'!G14 | Z81: ='재무상태표'!G14 | AA81: ='재무상태표'!G14 | AB81: ='재무상태표'!G14 | AC81: ='재무상태표'!G14
A82: 지배자본 | X82: ='재무상태표'!G31 | Y82: ='재무상태표'!G31 | Z82: ='재무상태표'!G31 | AA82: ='재무상태표'!G31 | AB82: ='재무상태표'!G31 | AC82: ='재무상태표'!G31
A83: 부채 | X83: ='재무상태표'!G27 | Y83: ='재무상태표'!G27 | Z83: ='재무상태표'!G27 | AA83: ='재무상태표'!G27 | AB83: ='재무상태표'!G27 | AC83: ='재무상태표'!G27
A84: 부채비율 | X84: =IF(OR(X83="",X82=""),"",IFERROR(X83/X82,"")) | Y84: =IF(OR(Y83="",Y82=""),"",IFERROR(Y83/Y82,"")) | Z84: =IF(OR(Z83="",Z82=""),"",IFERROR(Z83/Z82,"")) | AA84: =IF(OR(AA83="",AA82=""),"",IFERROR(AA83/AA82,"")) | AB84: =IF(OR(AB83="",AB82=""),"",IFERROR(AB83/AB82,"")) | AC84: =IF(OR(AC83="",AC82=""),"",IFERROR(AC83/AC82,""))
A85: 자산가치 | B85: 현금+단기금융+투자부동산 | X85: =SUM(X79,X80,X81) | Y85: =SUM(Y79,Y80,Y81) | Z85: =SUM(Z79,Z80,Z81) | AA85: =SUM(AA79,AA80,AA81) | AB85: =SUM(AB79,AB80,AB81) | AC85: =SUM(AC79,AC80,AC81)
A86: 기업가치 산출
A87: 목표 시가총액 (P/E) | B87: 지배순이익 × Target P/E | Y87: =IF(OR(Y64="",Y74=""),"",IFERROR(Y64*Y74,"")) | Z87: =IF(OR(Z64="",Z74=""),"",IFERROR(Z64*Z74,"")) | AA87: =IF(OR(AA64="",AA74=""),"",IFERROR(AA64*AA74,"")) | AB87: =IF(OR(AB64="",AB74=""),"",IFERROR(AB64*AB74,"")) | AC87: =IF(OR(AC64="",AC74=""),"",IFERROR(AC64*AC74,""))
A88: 기업가치 | B88: 목표시총 + 자산가치 | Y88: =IF(OR(Y87=""),"",IFERROR(Y87+Y85,"")) | Z88: =IF(OR(Z87=""),"",IFERROR(Z87+Z85,"")) | AA88: =IF(OR(AA87=""),"",IFERROR(AA87+AA85,"")) | AB88: =IF(OR(AB87=""),"",IFERROR(AB87+AB85,"")) | AC88: =IF(OR(AC87=""),"",IFERROR(AC87+AC85,""))
A89: 현재 시가총액 | Y89: =$B$70 | Z89: =$B$70 | AA89: =$B$70 | AB89: =$B$70 | AC89: =$B$70
A90: 상승여력 | Y90: =IF(OR(Y88="",Y89=""),"",IFERROR(Y88/Y89-1,"")) | Z90: =IF(OR(Z88="",Z89=""),"",IFERROR(Z88/Z89-1,"")) | AA90: =IF(OR(AA88="",AA89=""),"",IFERROR(AA88/AA89-1,"")) | AB90: =IF(OR(AB88="",AB89=""),"",IFERROR(AB88/AB89-1,"")) | AC90: =IF(OR(AC88="",AC89=""),"",IFERROR(AC88/AC89-1,""))
A92: 출처
A93: 결산단신 XBRL(TDnet·JPX 보관소) — 쓴 문서는 '출처' 시트
A94: 분기 = 누계에서 앞 분기를 뺀 3개월 값
A95: 주가: 야후 파이낸스 일봉
A97: 손익계산서 · 전 항목 | B97: 분기 = 3개월 단독
A98: 항목 | B98: 참고 | C98: 2025.1Q | D98: 2025.2Q | E98: 2025.3Q | F98: 2025.4Q | G98: 2026.1Q | H98: 2026.2Q | I98: 2026.3Q | J98: 2026.4Q | K98: 2027.1Q | L98: 2027.2Q | M98: 2027.3Q | N98: 2027.4Q | O98: 2018 | P98: 2019 | Q98: 2020 | R98: 2021 | S98: 2022 | T98: 2023 | U98: 2024 | V98: 2025 | W98: 2026 | X98: 2027 | Y98: 2028(MW) | Z98: 2029(MW) | AA98: 2030(MW) | AB98: 2031(MW) | AC98: 2032(MW)
A99: 매출액 | C99: 1864.782 | D99: 1983.858 | E99: 1785.445 | F99: 1207.226 | G99: 1862.071 | H99: 1984.798 | I99: 1935.544 | J99: 1595.276 | K99: 2008.744 | L99: 2115.126 | S99: 1220.565 | T99: 503.21 | U99: 1162.242 | V99: 1207.226 | W99: 1595.276
A100: YoY | B100: 전년 같은 분기·전년 대비 | G100: =IF(OR(G99="",C99=""),"",IF(C99<=0,"",IFERROR(G99/C99-1,""))) | H100: =IF(OR(H99="",D99=""),"",IF(D99<=0,"",IFERROR(H99/D99-1,""))) | I100: =IF(OR(I99="",E99=""),"",IF(E99<=0,"",IFERROR(I99/E99-1,""))) | J100: =IF(OR(J99="",F99=""),"",IF(F99<=0,"",IFERROR(J99/F99-1,""))) | K100: =IF(OR(K99="",G99=""),"",IF(G99<=0,"",IFERROR(K99/G99-1,""))) | L100: =IF(OR(L99="",H99=""),"",IF(H99<=0,"",IFERROR(L99/H99-1,""))) | S100: =IF(OR(S99="",R99=""),"",IF(R99<=0,"",IFERROR(S99/R99-1,""))) | T100: =IF(OR(T99="",S99=""),"",IF(S99<=0,"",IFERROR(T99/S99-1,""))) | U100: =IF(OR(U99="",T99=""),"",IF(T99<=0,"",IFERROR(U99/T99-1,""))) | V100: =IF(OR(V99="",U99=""),"",IF(U99<=0,"",IFERROR(V99/U99-1,""))) | W100: =IF(OR(W99="",V99=""),"",IF(V99<=0,"",IFERROR(W99/V99-1,"")))
A101: 매출원가 | C101: 1119.078 | D101: 1164.358 | E101: 1079.498 | F101: 737.004 | G101: 1149.124 | H101: 1204.381 | I101: 1174.85 | J101: 961.347 | K101: 1183.909 | L101: 1244.835 | S101: 753.159 | T101: 441.583 | U101: 613.037 | V101: 737.004 | W101: 961.347
A102: YoY | B102: 전년 같은 분기·전년 대비 | G102: =IF(OR(G101="",C101=""),"",IF(G101*C101<=0,"",IFERROR(G101/C101-1,""))) | H102: =IF(OR(H101="",D101=""),"",IF(H101*D101<=0,"",IFERROR(H101/D101-1,""))) | I102: =IF(OR(I101="",E101=""),"",IF(I101*E101<=0,"",IFERROR(I101/E101-1,""))) | J102: =IF(OR(J101="",F101=""),"",IF(J101*F101<=0,"",IFERROR(J101/F101-1,""))) | K102: =IF(OR(K101="",G101=""),"",IF(K101*G101<=0,"",IFERROR(K101/G101-1,""))) | L102: =IF(OR(L101="",H101=""),"",IF(L101*H101<=0,"",IFERROR(L101/H101-1,""))) | S102: =IF(OR(S101="",R101=""),"",IF(S101*R101<=0,"",IFERROR(S101/R101-1,""))) | T102: =IF(OR(T101="",S101=""),"",IF(T101*S101<=0,"",IFERROR(T101/S101-1,""))) | U102: =IF(OR(U101="",T101=""),"",IF(U101*T101<=0,"",IFERROR(U101/T101-1,""))) | V102: =IF(OR(V101="",U101=""),"",IF(V101*U101<=0,"",IFERROR(V101/U101-1,""))) | W102: =IF(OR(W101="",V101=""),"",IF(W101*V101<=0,"",IFERROR(W101/V101-1,"")))
...

Sheet 재무상태표
A1: 9950 재무상태표
A2: 재무비율은 기말 잔액 기준 · 분기 손익은 최근 4분기 합산(TTM) | B2: (단위: 백만엔)
A3: 항목 | B3: 참고 | C3: 2026.3Q | D3: 2026.4Q | E3: 2027.1Q | F3: 2027.2Q | G3: 2027.3Q | H3: 2023 | I3: 2024 | J3: 2025 | K3: 2026
A4: 자산
A5: 유동자산 | C5: 2126.837 | D5: 1914.112 | E5: 1799.529 | F5: 2200.944 | G5: 3118.64 | H5: 1959.853 | I5: 2026.813 | J5: 2162.267 | K5: 1914.112
A6: 현금및현금성자산 | C6: 883.839 | D6: 587.071 | E6: 682.082 | F6: 890.502 | G6: 1812.83 | H6: 870.986 | I6: 870.99 | J6: 913.121 | K6: 587.071
A7: 단기금융상품
A8: 매출채권 | C8: 837.08 | D8: 969.287 | E8: 795.849 | F8: 950.146 | G8: 908.975 | H8: 679.814 | I8: 720.665 | J8: 796.159 | K8: 969.287
A9: 재고자산 | C9: 216.072 | D9: 233.651 | E9: 220.091 | F9: 237.832 | G9: 261.269 | H9: 210.771 | I9: 242.75 | J9: 239.671 | K9: 233.651
A10: 기타유동자산 | B10: 총계 − 위 항목 | C10: =IF(OR(C5=""),"",IFERROR(C5-SUM(C6,C7,C8,C9),"")) | D10: =IF(OR(D5=""),"",IFERROR(D5-SUM(D6,D7,D8,D9),"")) | E10: =IF(OR(E5=""),"",IFERROR(E5-SUM(E6,E7,E8,E9),"")) | F10: =IF(OR(F5=""),"",IFERROR(F5-SUM(F6,F7,F8,F9),"")) | G10: =IF(OR(G5=""),"",IFERROR(G5-SUM(G6,G7,G8,G9),"")) | H10: =IF(OR(H5=""),"",IFERROR(H5-SUM(H6,H7,H8,H9),"")) | I10: =IF(OR(I5=""),"",IFERROR(I5-SUM(I6,I7,I8,I9),"")) | J10: =IF(OR(J5=""),"",IFERROR(J5-SUM(J6,J7,J8,J9),"")) | K10: =IF(OR(K5=""),"",IFERROR(K5-SUM(K6,K7,K8,K9),""))
A11: 비유동자산 | C11: 3561.266 | D11: 3736.07 | E11: 3809.081 | F11: 3832.592 | G11: 3920.724 | H11: 2955.748 | I11: 2857.97 | J11: 3449.38 | K11: 3736.07
A12: 유형자산 | C12: 2471.529 | D12: 2577.731 | E12: 2576.257 | F12: 2578.398 | G12: 2644.875 | H12: 2011.932 | I12: 2028.016 | J12: 2455.704 | K12: 2577.731
A13: 무형자산 | C13: 247.804 | D13: 277.574 | E13: 289.923 | F13: 293.405 | G13: 274.286 | H13: 71.482 | I13: 50.96 | J13: 210.124 | K13: 277.574
A14: 투자부동산
A15: 기타비유동자산 | B15: 총계 − 위 항목 | C15: =IF(OR(C11=""),"",IFERROR(C11-SUM(C12,C13,C14),"")) | D15: =IF(OR(D11=""),"",IFERROR(D11-SUM(D12,D13,D14),"")) | E15: =IF(OR(E11=""),"",IFERROR(E11-SUM(E12,E13,E14),"")) | F15: =IF(OR(F11=""),"",IFERROR(F11-SUM(F12,F13,F14),"")) | G15: =IF(OR(G11=""),"",IFERROR(G11-SUM(G12,G13,G14),"")) | H15: =IF(OR(H11=""),"",IFERROR(H11-SUM(H12,H13,H14),"")) | I15: =IF(OR(I11=""),"",IFERROR(I11-SUM(I12,I13,I14),"")) | J15: =IF(OR(J11=""),"",IFERROR(J11-SUM(J12,J13,J14),"")) | K15: =IF(OR(K11=""),"",IFERROR(K11-SUM(K12,K13,K14),""))
A16: 자산총계 | C16: 5688.103 | D16: 5650.182 | E16: 5608.61 | F16: 6033.536 | G16: 7039.364 | H16: 4915.602 | I16: 4884.783 | J16: 5611.648 | K16: 5650.182
A17: 부채
A18: 유동부채 | C18: 1184.975 | D18: 1169.505 | E18: 1156.746 | F18: 1543.49 | G18: 1510.935 | H18: 1127.503 | I18: 1007.068 | J18: 1141.948 | K18: 1169.505
A19: 매입채무 | C19: 420.452 | D19: 489.369 | E19: 429.872 | F19: 432.553 | G19: 461.559 | H19: 379.585 | I19: 400.595 | J19: 391.965 | K19: 489.369
A20: 단기차입금 | C20: 150.014 | D20: 149.984 | E20: 149.984 | F20: 449.984 | G20: 389.576 | H20: 210.084 | I20: 110.084 | J20: 222.551 | K20: 149.984
A21: 유동성장기부채
A22: 기타유동부채 | B22: 총계 − 위 항목 | C22: =IF(OR(C18=""),"",IFERROR(C18-SUM(C19,C20,C21),"")) | D22: =IF(OR(D18=""),"",IFERROR(D18-SUM(D19,D20,D21),"")) | E22: =IF(OR(E18=""),"",IFERROR(E18-SUM(E19,E20,E21),"")) | F22: =IF(OR(F18=""),"",IFERROR(F18-SUM(F19,F20,F21),"")) | G22: =IF(OR(G18=""),"",IFERROR(G18-SUM(G19,G20,G21),"")) | H22: =IF(OR(H18=""),"",IFERROR(H18-SUM(H19,H20,H21),"")) | I22: =IF(OR(I18=""),"",IFERROR(I18-SUM(I19,I20,I21),"")) | J22: =IF(OR(J18=""),"",IFERROR(J18-SUM(J19,J20,J21),"")) | K22: =IF(OR(K18=""),"",IFERROR(K18-SUM(K19,K20,K21),""))
A23: 비유동부채 | C23: 695.761 | D23: 667.795 | E23: 643.907 | F23: 613.529 | G23: 1522.948 | H23: 509.436 | I23: 434.206 | J23: 732.284 | K23: 667.795
A24: 장기차입금 | C24: 390.034 | D24: 352.538 | E24: 315.042 | F24: 277.546 | G24: 1200.458 | H24: 191.969 | I24: 81.885 | J24: 454.343 | K24: 352.538
A25: 사채
A26: 기타비유동부채 | B26: 총계 − 위 항목 | C26: =IF(OR(C23=""),"",IFERROR(C23-SUM(C24,C25),"")) | D26: =IF(OR(D23=""),"",IFERROR(D23-SUM(D24,D25),"")) | E26: =IF(OR(E23=""),"",IFERROR(E23-SUM(E24,E25),"")) | F26: =IF(OR(F23=""),"",IFERROR(F23-SUM(F24,F25),"")) | G26: =IF(OR(G23=""),"",IFERROR(G23-SUM(G24,G25),"")) | H26: =IF(OR(H23=""),"",IFERROR(H23-SUM(H24,H25),"")) | I26: =IF(OR(I23=""),"",IFERROR(I23-SUM(I24,I25),"")) | J26: =IF(OR(J23=""),"",IFERROR(J23-SUM(J24,J25),"")) | K26: =IF(OR(K23=""),"",IFERROR(K23-SUM(K24,K25),""))
A27: 부채총계 | C27: 1880.737 | D27: 1837.301 | E27: 1800.653 | F27: 2157.02 | G27: 3033.883 | H27: 1636.939 | I27: 1441.274 | J27: 1874.232 | K27: 1837.301
A28: 총차입금 | B28: 단기+유동성장기+장기+사채 | C28: =SUM(C20,C21,C24,C25) | D28: =SUM(D20,D21,D24,D25) | E28: =SUM(E20,E21,E24,E25) | F28: =SUM(F20,F21,F24,F25) | G28: =SUM(G20,G21,G24,G25) | H28: =SUM(H20,H21,H24,H25) | I28: =SUM(I20,I21,I24,I25) | J28: =SUM(J20,J21,J24,J25) | K28: =SUM(K20,K21,K24,K25)
A29: 순차입금 | B29: 음수 = 순현금 | C29: =C28-C6-N(C7) | D29: =D28-D6-N(D7) | E29: =E28-E6-N(E7) | F29: =F28-F6-N(F7) | G29: =G28-G6-N(G7) | H29: =H28-H6-N(H7) | I29: =I28-I6-N(I7) | J29: =J28-J6-N(J7) | K29: =K28-K6-N(K7)
A30: 자본
A31: 지배주주지분 | C31: 3807.361 | D31: 3812.876 | E31: 3807.95 | F31: 3876.511 | G31: 4005.475 | H31: 3278.659 | I31: 3443.505 | J31: 3737.412 | K31: 3812.876
A32: 자본금 | C32: 1518.454 | D32: 1518.454 | E32: 1518.454 | F32: 1518.454 | G32: 1518.454 | H32: 1518.454 | I32: 1518.454 | J32: 1518.454 | K32: 1518.454
A33: 이익잉여금 | C33: 1408.465 | D33: 1362.619 | E33: 1287.932 | F33: 1352.773 | G33: 1403.025 | H33: 1082.338 | I33: 1183.141 | J33: 1387.057 | K33: 1362.619
A34: 비지배지분 | C34: 0.005 | D34: 0.005 | E34: 0.006 | F34: 0.005 | G34: 0.005 | H34: 0.003 | I34: 0.004 | J34: 0.004 | K34: 0.005
A35: 자본총계 | C35: 3807.366 | D35: 3812.881 | E35: 3807.956 | F35: 3876.516 | G35: 4005.48 | H35: 3278.662 | I35: 3443.509 | J35: 3737.416 | K35: 3812.881
A36: 현금흐름 요약 | B36: 분기 = TTM (있을 때만)
A37: 영업활동현금흐름 | D37: 418.599 | H37: 144.588 | I37: 385.131 | J37: 499.535 | K37: 418.599
A38: CAPEX (유·무형 취득) | B38: 양수로 입력 | D38: 843.081 | H38: 74.275 | I38: 232.026 | J38: 276.158 | K38: 843.081
A39: FCF | C39: =IF(OR(C37="",C38=""),"",IFERROR(C37-C38,"")) | D39: =IF(OR(D37="",D38=""),"",IFERROR(D37-D38,"")) | E39: =IF(OR(E37="",E38=""),"",IFERROR(E37-E38,"")) | F39: =IF(OR(F37="",F38=""),"",IFERROR(F37-F38,"")) | G39: =IF(OR(G37="",G38=""),"",IFERROR(G37-G38,"")) | H39: =IF(OR(H37="",H38=""),"",IFERROR(H37-H38,"")) | I39: =IF(OR(I37="",I38=""),"",IFERROR(I37-I38,"")) | J39: =IF(OR(J37="",J38=""),"",IFERROR(J37-J38,"")) | K39: =IF(OR(K37="",K38=""),"",IFERROR(K37-K38,""))
A40: 배당금 지급 | B40: 양수로 입력 | D40: 59.628 | H40: 59.354 | I40: 59.532 | J40: 59.696 | K40: 59.628
A41: 주요 재무 비율 | B41: 기준 (빨간 글씨 = 미달)
A42: 안정성
A43: 부채비율 | B43: 100%↓ | C43: =IF(OR(C27="",C35=""),"",IFERROR(C27/C35,"")) | D43: =IF(OR(D27="",D35=""),"",IFERROR(D27/D35,"")) | E43: =IF(OR(E27="",E35=""),"",IFERROR(E27/E35,"")) | F43: =IF(OR(F27="",F35=""),"",IFERROR(F27/F35,"")) | G43: =IF(OR(G27="",G35=""),"",IFERROR(G27/G35,"")) | H43: =IF(OR(H27="",H35=""),"",IFERROR(H27/H35,"")) | I43: =IF(OR(I27="",I35=""),"",IFERROR(I27/I35,"")) | J43: =IF(OR(J27="",J35=""),"",IFERROR(J27/J35,"")) | K43: =IF(OR(K27="",K35=""),"",IFERROR(K27/K35,""))
A44: 순차입금비율 | B44: 0%↓ 순현금 | C44: =IF(OR(C29="",C35=""),"",IFERROR(C29/C35,"")) | D44: =IF(OR(D29="",D35=""),"",IFERROR(D29/D35,"")) | E44: =IF(OR(E29="",E35=""),"",IFERROR(E29/E35,"")) | F44: =IF(OR(F29="",F35=""),"",IFERROR(F29/F35,"")) | G44: =IF(OR(G29="",G35=""),"",IFERROR(G29/G35,"")) | H44: =IF(OR(H29="",H35=""),"",IFERROR(H29/H35,"")) | I44: =IF(OR(I29="",I35=""),"",IFERROR(I29/I35,"")) | J44: =IF(OR(J29="",J35=""),"",IFERROR(J29/J35,"")) | K44: =IF(OR(K29="",K35=""),"",IFERROR(K29/K35,""))
A45: 자기자본비율 | B45: 50%↑ | C45: =IF(OR(C35="",C16=""),"",IFERROR(C35/C16,"")) | D45: =IF(OR(D35="",D16=""),"",IFERROR(D35/D16,"")) | E45: =IF(OR(E35="",E16=""),"",IFERROR(E35/E16,"")) | F45: =IF(OR(F35="",F16=""),"",IFERROR(F35/F16,"")) | G45: =IF(OR(G35="",G16=""),"",IFERROR(G35/G16,"")) | H45: =IF(OR(H35="",H16=""),"",IFERROR(H35/H16,"")) | I45: =IF(OR(I35="",I16=""),"",IFERROR(I35/I16,"")) | J45: =IF(OR(J35="",J16=""),"",IFERROR(J35/J16,"")) | K45: =IF(OR(K35="",K16=""),"",IFERROR(K35/K16,""))
A46: 유동비율 | B46: 150%↑ | C46: =IF(OR(C5="",C18=""),"",IFERROR(C5/C18,"")) | D46: =IF(OR(D5="",D18=""),"",IFERROR(D5/D18,"")) | E46: =IF(OR(E5="",E18=""),"",IFERROR(E5/E18,"")) | F46: =IF(OR(F5="",F18=""),"",IFERROR(F5/F18,"")) | G46: =IF(OR(G5="",G18=""),"",IFERROR(G5/G18,"")) | H46: =IF(OR(H5="",H18=""),"",IFERROR(H5/H18,"")) | I46: =IF(OR(I5="",I18=""),"",IFERROR(I5/I18,"")) | J46: =IF(OR(J5="",J18=""),"",IFERROR(J5/J18,"")) | K46: =IF(OR(K5="",K18=""),"",IFERROR(K5/K18,""))
A47: 당좌비율 | B47: 100%↑ | C47: =IF(OR(C5="",C18=""),"",IFERROR((C5-N(C9))/C18,"")) | D47: =IF(OR(D5="",D18=""),"",IFERROR((D5-N(D9))/D18,"")) | E47: =IF(OR(E5="",E18=""),"",IFERROR((E5-N(E9))/E18,"")) | F47: =IF(OR(F5="",F18=""),"",IFERROR((F5-N(F9))/F18,"")) | G47: =IF(OR(G5="",G18=""),"",IFERROR((G5-N(G9))/G18,"")) | H47: =IF(OR(H5="",H18=""),"",IFERROR((H5-N(H9))/H18,"")) | I47: =IF(OR(I5="",I18=""),"",IFERROR((I5-N(I9))/I18,"")) | J47: =IF(OR(J5="",J18=""),"",IFERROR((J5-N(J9))/J18,"")) | K47: =IF(OR(K5="",K18=""),"",IFERROR((K5-N(K9))/K18,""))
A48: 이자보상배율 | B48: 5x↑ (금융원가 기준) | C48: =IFERROR((IF(COUNT('연간'!F34:I34)<4,"",SUM('연간'!F34:I34)))/(IF(COUNT('연간'!F56:I56)<4,"",SUM('연간'!F56:I56))),"") | D48: =IFERROR((IF(COUNT('연간'!G34:J34)<4,"",SUM('연간'!G34:J34)))/(IF(COUNT('연간'!G56:J56)<4,"",SUM('연간'!G56:J56))),"") | E48: =IFERROR((IF(COUNT('연간'!H34:K34)<4,"",SUM('연간'!H34:K34)))/(IF(COUNT('연간'!H56:K56)<4,"",SUM('연간'!H56:K56))),"") | F48: =IFERROR((IF(COUNT('연간'!I34:L34)<4,"",SUM('연간'!I34:L34)))/(IF(COUNT('연간'!I56:L56)<4,"",SUM('연간'!I56:L56))),"") | G48: =IFERROR((IF(COUNT('연간'!J34:M34)<4,"",SUM('연간'!J34:M34)))/(IF(COUNT('연간'!J56:M56)<4,"",SUM('연간'!J56:M56))),"") | H48: =IFERROR(('연간'!T34)/('연간'!T56),"") | I48: =IFERROR(('연간'!U34)/('연간'!U56),"") | J48: =IFERROR(('연간'!V34)/('연간'!V56),"") | K48: =IFERROR(('연간'!W34)/('연간'!W56),"")
A49: 차입금 상환연수 | B49: 4년↓ (버핏) | C49: =IFERROR(IF((IF(COUNT('연간'!F64:I64)<4,"",SUM('연간'!F64:I64)))<=0,"적자",C28/(IF(COUNT('연간'!F64:I64)<4,"",SUM('연간'!F64:I64)))),"") | D49: =IFERROR(IF((IF(COUNT('연간'!G64:J64)<4,"",SUM('연간'!G64:J64)))<=0,"적자",D28/(IF(COUNT('연간'!G64:J64)<4,"",SUM('연간'!G64:J64)))),"") | E49: =IFERROR(IF((IF(COUNT('연간'!H64:K64)<4,"",SUM('연간'!H64:K64)))<=0,"적자",E28/(IF(COUNT('연간'!H64:K64)<4,"",SUM('연간'!H64:K64)))),"") | F49: =IFERROR(IF((IF(COUNT('연간'!I64:L64)<4,"",SUM('연간'!I64:L64)))<=0,"적자",F28/(IF(COUNT('연간'!I64:L64)<4,"",SUM('연간'!I64:L64)))),"") | G49: =IFERROR(IF((IF(COUNT('연간'!J64:M64)<4,"",SUM('연간'!J64:M64)))<=0,"적자",G28/(IF(COUNT('연간'!J64:M64)<4,"",SUM('연간'!J64:M64)))),"") | H49: =IFERROR(IF(('연간'!T64)<=0,"적자",H28/('연간'!T64)),"") | I49: =IFERROR(IF(('연간'!U64)<=0,"적자",I28/('연간'!U64)),"") | J49: =IFERROR(IF(('연간'!V64)<=0,"적자",J28/('연간'!V64)),"") | K49: =IFERROR(IF(('연간'!W64)<=0,"적자",K28/('연간'!W64)),"")
A50: 수익성
A51: ROE | B51: 15%↑ (버핏) | C51: =IFERROR((IF(COUNT('연간'!F64:I64)<4,"",SUM('연간'!F64:I64)))/C31,"") | D51: =IFERROR((IF(COUNT('연간'!G64:J64)<4,"",SUM('연간'!G64:J64)))/D31,"") | E51: =IFERROR((IF(COUNT('연간'!H64:K64)<4,"",SUM('연간'!H64:K64)))/E31,"") | F51: =IFERROR((IF(COUNT('연간'!I64:L64)<4,"",SUM('연간'!I64:L64)))/F31,"") | G51: =IFERROR((IF(COUNT('연간'!J64:M64)<4,"",SUM('연간'!J64:M64)))/G31,"") | H51: =IFERROR(('연간'!T64)/H31,"") | I51: =IFERROR(('연간'!U64)/I31,"") | J51: =IFERROR(('연간'!V64)/J31,"") | K51: =IFERROR(('연간'!W64)/K31,"")
A52: ROA | B52: 5%↑ | C52: =IFERROR((IF(COUNT('연간'!F62:I62)<4,"",SUM('연간'!F62:I62)))/C16,"") | D52: =IFERROR((IF(COUNT('연간'!G62:J62)<4,"",SUM('연간'!G62:J62)))/D16,"") | E52: =IFERROR((IF(COUNT('연간'!H62:K62)<4,"",SUM('연간'!H62:K62)))/E16,"") | F52: =IFERROR((IF(COUNT('연간'!I62:L62)<4,"",SUM('연간'!I62:L62)))/F16,"") | G52: =IFERROR((IF(COUNT('연간'!J62:M62)<4,"",SUM('연간'!J62:M62)))/G16,"") | H52: =IFERROR(('연간'!T62)/H16,"") | I52: =IFERROR(('연간'!U62)/I16,"") | J52: =IFERROR(('연간'!V62)/J16,"") | K52: =IFERROR(('연간'!W62)/K16,"")
A53: ROIC | B53: 10%↑ (세후영업이익 기준) | C53: =IFERROR((IF(COUNT('연간'!F34:I34)<4,"",SUM('연간'!F34:I34)))*(1-0.3)/(C35+C29),"") | D53: =IFERROR((IF(COUNT('연간'!G34:J34)<4,"",SUM('연간'!G34:J34)))*(1-0.3)/(D35+D29),"") | E53: =IFERROR((IF(COUNT('연간'!H34:K34)<4,"",SUM('연간'!H34:K34)))*(1-0.3)/(E35+E29),"") | F53: =IFERROR((IF(COUNT('연간'!I34:L34)<4,"",SUM('연간'!I34:L34)))*(1-0.3)/(F35+F29),"") | G53: =IFERROR((IF(COUNT('연간'!J34:M34)<4,"",SUM('연간'!J34:M34)))*(1-0.3)/(G35+G29),"") | H53: =IFERROR(('연간'!T34)*(1-0.3)/(H35+H29),"") | I53: =IFERROR(('연간'!U34)*(1-0.3)/(I35+I29),"") | J53: =IFERROR(('연간'!V34)*(1-0.3)/(J35+J29),"") | K53: =IFERROR(('연간'!W34)*(1-0.3)/(K35+K29),"")
A54: 매출총이익률 (GPM) | B54: 40%↑ (해자 신호) | C54: =IFERROR((IF(COUNT('연간'!F28:I28)<4,"",SUM('연간'!F28:I28)))/(IF(COUNT('연간'!F4:I4)<4,"",SUM('연간'!F4:I4))),"") | D54: =IFERROR((IF(COUNT('연간'!G28:J28)<4,"",SUM('연간'!G28:J28)))/(IF(COUNT('연간'!G4:J4)<4,"",SUM('연간'!G4:J4))),"") | E54: =IFERROR((IF(COUNT('연간'!H28:K28)<4,"",SUM('연간'!H28:K28)))/(IF(COUNT('연간'!H4:K4)<4,"",SUM('연간'!H4:K4))),"") | F54: =IFERROR((IF(COUNT('연간'!I28:L28)<4,"",SUM('연간'!I28:L28)))/(IF(COUNT('연간'!I4:L4)<4,"",SUM('연간'!I4:L4))),"") | G54: =IFERROR((IF(COUNT('연간'!J28:M28)<4,"",SUM('연간'!J28:M28)))/(IF(COUNT('연간'!J4:M4)<4,"",SUM('연간'!J4:M4))),"") | H54: =IFERROR(('연간'!T28)/('연간'!T4),"") | I54: =IFERROR(('연간'!U28)/('연간'!U4),"") | J54: =IFERROR(('연간'!V28)/('연간'!V4),"") | K54: =IFERROR(('연간'!W28)/('연간'!W4),"")
A55: 영업이익률 (OPM) | B55: 15%↑ | C55: =IFERROR((IF(COUNT('연간'!F34:I34)<4,"",SUM('연간'!F34:I34)))/(IF(COUNT('연간'!F4:I4)<4,"",SUM('연간'!F4:I4))),"") | D55: =IFERROR((IF(COUNT('연간'!G34:J34)<4,"",SUM('연간'!G34:J34)))/(IF(COUNT('연간'!G4:J4)<4,"",SUM('연간'!G4:J4))),"") | E55: =IFERROR((IF(COUNT('연간'!H34:K34)<4,"",SUM('연간'!H34:K34)))/(IF(COUNT('연간'!H4:K4)<4,"",SUM('연간'!H4:K4))),"") | F55: =IFERROR((IF(COUNT('연간'!I34:L34)<4,"",SUM('연간'!I34:L34)))/(IF(COUNT('연간'!I4:L4)<4,"",SUM('연간'!I4:L4))),"") | G55: =IFERROR((IF(COUNT('연간'!J34:M34)<4,"",SUM('연간'!J34:M34)))/(IF(COUNT('연간'!J4:M4)<4,"",SUM('연간'!J4:M4))),"") | H55: =IFERROR(('연간'!T34)/('연간'!T4),"") | I55: =IFERROR(('연간'!U34)/('연간'!U4),"") | J55: =IFERROR(('연간'!V34)/('연간'!V4),"") | K55: =IFERROR(('연간'!W34)/('연간'!W4),"")
A56: 순이익률 | B56: 10%↑ | C56: =IFERROR((IF(COUNT('연간'!F62:I62)<4,"",SUM('연간'!F62:I62)))/(IF(COUNT('연간'!F4:I4)<4,"",SUM('연간'!F4:I4))),"") | D56: =IFERROR((IF(COUNT('연간'!G62:J62)<4,"",SUM('연간'!G62:J62)))/(IF(COUNT('연간'!G4:J4)<4,"",SUM('연간'!G4:J4))),"") | E56: =IFERROR((IF(COUNT('연간'!H62:K62)<4,"",SUM('연간'!H62:K62)))/(IF(COUNT('연간'!H4:K4)<4,"",SUM('연간'!H4:K4))),"") | F56: =IFERROR((IF(COUNT('연간'!I62:L62)<4,"",SUM('연간'!I62:L62)))/(IF(COUNT('연간'!I4:L4)<4,"",SUM('연간'!I4:L4))),"") | G56: =IFERROR((IF(COUNT('연간'!J62:M62)<4,"",SUM('연간'!J62:M62)))/(IF(COUNT('연간'!J4:M4)<4,"",SUM('연간'!J4:M4))),"") | H56: =IFERROR(('연간'!T62)/('연간'!T4),"") | I56: =IFERROR(('연간'!U62)/('연간'!U4),"") | J56: =IFERROR(('연간'!V62)/('연간'!V4),"") | K56: =IFERROR(('연간'!W62)/('연간'!W4),"")
A57: 효율성 (회전율)
A58: 총자산회전율 | B58: 높을수록↑ | C58: =IFERROR((IF(COUNT('연간'!F4:I4)<4,"",SUM('연간'!F4:I4)))/C16,"") | D58: =IFERROR((IF(COUNT('연간'!G4:J4)<4,"",SUM('연간'!G4:J4)))/D16,"") | E58: =IFERROR((IF(COUNT('연간'!H4:K4)<4,"",SUM('연간'!H4:K4)))/E16,"") | F58: =IFERROR((IF(COUNT('연간'!I4:L4)<4,"",SUM('연간'!I4:L4)))/F16,"") | G58: =IFERROR((IF(COUNT('연간'!J4:M4)<4,"",SUM('연간'!J4:M4)))/G16,"") | H58: =IFERROR(('연간'!T4)/H16,"") | I58: =IFERROR(('연간'!U4)/I16,"") | J58: =IFERROR(('연간'!V4)/J16,"") | K58: =IFERROR(('연간'!W4)/K16,"")
A59: 매출채권회전일수 | B59: 짧을수록↑ | C59: =IFERROR(C8/(IF(COUNT('연간'!F4:I4)<4,"",SUM('연간'!F4:I4)))*365,"") | D59: =IFERROR(D8/(IF(COUNT('연간'!G4:J4)<4,"",SUM('연간'!G4:J4)))*365,"") | E59: =IFERROR(E8/(IF(COUNT('연간'!H4:K4)<4,"",SUM('연간'!H4:K4)))*365,"") | F59: =IFERROR(F8/(IF(COUNT('연간'!I4:L4)<4,"",SUM('연간'!I4:L4)))*365,"") | G59: =IFERROR(G8/(IF(COUNT('연간'!J4:M4)<4,"",SUM('연간'!J4:M4)))*365,"") | H59: =IFERROR(H8/('연간'!T4)*365,"") | I59: =IFERROR(I8/('연간'!U4)*365,"") | J59: =IFERROR(J8/('연간'!V4)*365,"") | K59: =IFERROR(K8/('연간'!W4)*365,"")
A60: 재고자산회전일수 | B60: 짧을수록↑ | C60: =IFERROR(C9/(IF(COUNT('연간'!F26:I26)<4,"",SUM('연간'!F26:I26)))*365,"") | D60: =IFERROR(D9/(IF(COUNT('연간'!G26:J26)<4,"",SUM('연간'!G26:J26)))*365,"") | E60: =IFERROR(E9/(IF(COUNT('연간'!H26:K26)<4,"",SUM('연간'!H26:K26)))*365,"") | F60: =IFERROR(F9/(IF(COUNT('연간'!I26:L26)<4,"",SUM('연간'!I26:L26)))*365,"") | G60: =IFERROR(G9/(IF(COUNT('연간'!J26:M26)<4,"",SUM('연간'!J26:M26)))*365,"") | H60: =IFERROR(H9/('연간'!T26)*365,"") | I60: =IFERROR(I9/('연간'!U26)*365,"") | J60: =IFERROR(J9/('연간'!V26)*365,"") | K60: =IFERROR(K9/('연간'!W26)*365,"")
A61: 매입채무회전일수 | B61: 길수록 유리 | C61: =IFERROR(C19/(IF(COUNT('연간'!F26:I26)<4,"",SUM('연간'!F26:I26)))*365,"") | D61: =IFERROR(D19/(IF(COUNT('연간'!G26:J26)<4,"",SUM('연간'!G26:J26)))*365,"") | E61: =IFERROR(E19/(IF(COUNT('연간'!H26:K26)<4,"",SUM('연간'!H26:K26)))*365,"") | F61: =IFERROR(F19/(IF(COUNT('연간'!I26:L26)<4,"",SUM('연간'!I26:L26)))*365,"") | G61: =IFERROR(G19/(IF(COUNT('연간'!J26:M26)<4,"",SUM('연간'!J26:M26)))*365,"") | H61: =IFERROR(H19/('연간'!T26)*365,"") | I61: =IFERROR(I19/('연간'!U26)*365,"") | J61: =IFERROR(J19/('연간'!V26)*365,"") | K61: =IFERROR(K19/('연간'!W26)*365,"")
A62: 현금전환주기 (CCC) | B62: 짧을수록↑ | C62: =IF(OR(C59="",C60="",C61=""),"",IFERROR(C59+C60-C61,"")) | D62: =IF(OR(D59="",D60="",D61=""),"",IFERROR(D59+D60-D61,"")) | E62: =IF(OR(E59="",E60="",E61=""),"",IFERROR(E59+E60-E61,"")) | F62: =IF(OR(F59="",F60="",F61=""),"",IFERROR(F59+F60-F61,"")) | G62: =IF(OR(G59="",G60="",G61=""),"",IFERROR(G59+G60-G61,"")) | H62: =IF(OR(H59="",H60="",H61=""),"",IFERROR(H59+H60-H61,"")) | I62: =IF(OR(I59="",I60="",I61=""),"",IFERROR(I59+I60-I61,"")) | J62: =IF(OR(J59="",J60="",J61=""),"",IFERROR(J59+J60-J61,"")) | K62: =IF(OR(K59="",K60="",K61=""),"",IFERROR(K59+K60-K61,""))
A63: 현금흐름
A64: 영업현금흐름 / 순이익 | B64: 1x↑ (이익의 질) | C64: =IF(C37="","",IFERROR(C37/(IF(COUNT('연간'!F62:I62)<4,"",SUM('연간'!F62:I62))),"")) | D64: =IF(D37="","",IFERROR(D37/(IF(COUNT('연간'!G62:J62)<4,"",SUM('연간'!G62:J62))),"")) | E64: =IF(E37="","",IFERROR(E37/(IF(COUNT('연간'!H62:K62)<4,"",SUM('연간'!H62:K62))),"")) | F64: =IF(F37="","",IFERROR(F37/(IF(COUNT('연간'!I62:L62)<4,"",SUM('연간'!I62:L62))),"")) | G64: =IF(G37="","",IFERROR(G37/(IF(COUNT('연간'!J62:M62)<4,"",SUM('연간'!J62:M62))),"")) | H64: =IF(H37="","",IFERROR(H37/('연간'!T62),"")) | I64: =IF(I37="","",IFERROR(I37/('연간'!U62),"")) | J64: =IF(J37="","",IFERROR(J37/('연간'!V62),"")) | K64: =IF(K37="","",IFERROR(K37/('연간'!W62),""))
A65: FCF 마진 | B65: 5%↑ | C65: =IF(C39="","",IFERROR(C39/(IF(COUNT('연간'!F4:I4)<4,"",SUM('연간'!F4:I4))),"")) | D65: =IF(D39="","",IFERROR(D39/(IF(COUNT('연간'!G4:J4)<4,"",SUM('연간'!G4:J4))),"")) | E65: =IF(E39="","",IFERROR(E39/(IF(COUNT('연간'!H4:K4)<4,"",SUM('연간'!H4:K4))),"")) | F65: =IF(F39="","",IFERROR(F39/(IF(COUNT('연간'!I4:L4)<4,"",SUM('연간'!I4:L4))),"")) | G65: =IF(G39="","",IFERROR(G39/(IF(COUNT('연간'!J4:M4)<4,"",SUM('연간'!J4:M4))),"")) | H65: =IF(H39="","",IFERROR(H39/('연간'!T4),"")) | I65: =IF(I39="","",IFERROR(I39/('연간'!U4),"")) | J65: =IF(J39="","",IFERROR(J39/('연간'!V4),"")) | K65: =IF(K39="","",IFERROR(K39/('연간'!W4),""))
A66: CAPEX / 매출 | B66: 낮을수록↑ (자본 가벼움) | C66: =IF(C38="","",IFERROR(C38/(IF(COUNT('연간'!F4:I4)<4,"",SUM('연간'!F4:I4))),"")) | D66: =IF(D38="","",IFERROR(D38/(IF(COUNT('연간'!G4:J4)<4,"",SUM('연간'!G4:J4))),"")) | E66: =IF(E38="","",IFERROR(E38/(IF(COUNT('연간'!H4:K4)<4,"",SUM('연간'!H4:K4))),"")) | F66: =IF(F38="","",IFERROR(F38/(IF(COUNT('연간'!I4:L4)<4,"",SUM('연간'!I4:L4))),"")) | G66: =IF(G38="","",IFERROR(G38/(IF(COUNT('연간'!J4:M4)<4,"",SUM('연간'!J4:M4))),"")) | H66: =IF(H38="","",IFERROR(H38/('연간'!T4),"")) | I66: =IF(I38="","",IFERROR(I38/('연간'!U4),"")) | J66: =IF(J38="","",IFERROR(J38/('연간'!V4),"")) | K66: =IF(K38="","",IFERROR(K38/('연간'!W4),""))
A67: 배당성향 | B67: 참고 | C67: =IF(C40="","",IFERROR(C40/(IF(COUNT('연간'!F64:I64)<4,"",SUM('연간'!F64:I64))),"")) | D67: =IF(D40="","",IFERROR(D40/(IF(COUNT('연간'!G64:J64)<4,"",SUM('연간'!G64:J64))),"")) | E67: =IF(E40="","",IFERROR(E40/(IF(COUNT('연간'!H64:K64)<4,"",SUM('연간'!H64:K64))),"")) | F67: =IF(F40="","",IFERROR(F40/(IF(COUNT('연간'!I64:L64)<4,"",SUM('연간'!I64:L64))),"")) | G67: =IF(G40="","",IFERROR(G40/(IF(COUNT('연간'!J64:M64)<4,"",SUM('연간'!J64:M64))),"")) | H67: =IF(H40="","",IFERROR(H40/('연간'!T64),"")) | I67: =IF(I40="","",IFERROR(I40/('연간'!U64),"")) | J67: =IF(J40="","",IFERROR(J40/('연간'!V64),"")) | K67: =IF(K40="","",IFERROR(K40/('연간'!W64),""))
A69: 재무상태표 · 전 항목 | B69: 분기 말 잔액
A70: 항목 | B70: 참고 | C70: 2026.3Q | D70: 2026.4Q | E70: 2027.1Q | F70: 2027.2Q | G70: 2027.3Q | H70: 2023 | I70: 2024 | J70: 2025 | K70: 2026
A71: 현금 및 예금 | C71: 883.839 | D71: 587.071 | E71: 682.082 | F71: 890.502 | G71: 1812.83 | H71: 870.986 | I71: 870.99 | J71: 913.121 | K71: 587.071
A72: 매출채권 | C72: 837.08 | D72: 969.287 | E72: 795.849 | F72: 950.146 | G72: 908.975 | H72: 679.814 | I72: 720.665 | J72: 796.159 | K72: 969.287
A73: 상품·제품 | C73: 187.974 | D73: 201.293 | E73: 193.244 | F73: 206.132 | G73: 227.761 | H73: 185.168 | I73: 216.386 | J73: 209.024 | K73: 201.293
A74: 원재료·저장품 | C74: 28.098 | D74: 32.358 | E74: 26.847 | F74: 31.7 | G74: 33.508 | H74: 25.603 | I74: 26.364 | J74: 30.647 | K74: 32.358
A75: 기타 | C75: 189.844 | D75: 124.101 | E75: 101.506 | F75: 122.463 | G75: 135.564 | H75: 198.28 | I75: 192.405 | J75: 213.314 | K75: 124.101
A76: 유동자산 합계 | C76: 2126.837 | D76: 1914.112 | E76: 1799.529 | F76: 2200.944 | G76: 3118.64 | H76: 1959.853 | I76: 2026.813 | J76: 2162.267 | K76: 1914.112
A77: 건물·구축물(순액) | C77: 699.264 | D77: 796.801 | E77: 777.347 | F77: 814.881 | G77: 836.792 | H77: 601.385 | I77: 578.101 | J77: 668.18 | K77: 796.801
A78: 기계장치·운반구(순액) | C78: 199.079 | D78: 239.168 | E78: 226.593 | F78: 220.523 | G78: 277.072 | H78: 243.122 | I78: 212.174 | J78: 224.315 | K78: 239.168
A79: 공구·기구·비품(순액) | C79: 128.087 | D79: 151.381 | E79: 153.63 | F79: 166.43 | G79: 165.262 | H79: 88.896 | I79: 107.334 | J79: 127.426 | K79: 151.381
A80: 토지 | C80: 1071.028 | D80: 1071.028 | E80: 1071.028 | F80: 1071.028 | G80: 1071.028 | H80: 1071.028 | I80: 1071.028 | J80: 1071.028 | K80: 1071.028
A81: 리스자산 | C81: 336.757 | D81: 319.35 | E81: 310.256 | F81: 305.234 | G81: 293.601 | I81: 13.101 | J81: 358.108 | K81: 319.35
A82: 건설중인자산 | C82: 37.311 | D82: 0 | E82: 37.4 | F82: 0.3 | G82: 1.117 | H82: 7.5 | I82: 46.275 | J82: 6.645 | K82: 0
A83: 유형자산 합계 | C83: 2471.529 | D83: 2577.731 | E83: 2576.257 | F83: 2578.398 | G83: 2644.875 | H83: 2011.932 | I83: 2028.016 | J83: 2455.704 | K83: 2577.731
A84: 소프트웨어 | E84: 283.878 | F84: 287.382 | G84: 268.284
A85: 기타 | E85: 6.044 | F85: 6.023 | G85: 6.001
A86: 무형자산 합계 | C86: 247.804 | D86: 277.574 | E86: 289.923 | F86: 293.405 | G86: 274.286 | H86: 71.482 | I86: 50.96 | J86: 210.124 | K86: 277.574
A87: 투자유가증권 | C87: 524.297 | D87: 576.283 | E87: 641.933 | F87: 677.66 | G87: 762.143 | H87: 270.228 | I87: 329.919 | J87: 416.638 | K87: 576.283
A88: 장기대여금 | H88: 0
A89: 관계회사 출자금 | H89: 59.92 | I89: 0
A90: 보증금 | C90: 206.411 | D90: 208.487 | E90: 216.471 | F90: 215.372 | G90: 217.894 | H90: 257.867 | I90: 173.926 | J90: 208.305 | K90: 208.487
A91: 보험적립금 | C91: 20.5 | D91: 20.72 | E91: 20.94 | F91: 21.219 | G91: 16.31 | H91: 70.212 | I91: 70.982 | J91: 19.876 | K91: 20.72
A92: 이연법인세자산 | C92: 84.505 | D92: 69.314 | E92: 59.587 | F92: 41.085 | G92: 0 | H92: 209.552 | I92: 199.955 | J92: 133.847 | K92: 69.314
A93: 기타 | C93: 24.346 | D93: 24.058 | E93: 22.037 | F93: 23.256 | G93: 22.989 | H93: 22.818 | I93: 22.637 | J93: 23.138 | K93: 24.058
A94: 대손충당금 | C94: -18.128 | D94: -18.098 | E94: -18.068 | F94: -17.806 | G94: -17.776 | H94: -18.265 | I94: -18.428 | J94: -18.253 | K94: -18.098
A95: 투자 및 기타자산 합계 | C95: 841.932 | D95: 880.765 | E95: 942.901 | F95: 960.788 | G95: 1001.561 | H95: 872.333 | I95: 778.993 | J95: 783.551 | K95: 880.765
A96: 비유동자산 합계 | C96: 3561.266 | D96: 3736.07 | E96: 3809.081 | F96: 3832.592 | G96: 3920.724 | H96: 2955.748 | I96: 2857.97 | J96: 3449.38 | K96: 3736.07
A97: 자산 합계 | C97: 5688.103 | D97: 5650.182 | E97: 5608.61 | F97: 6033.536 | G97: 7039.364 | H97: 4915.602 | I97: 4884.783 | J97: 5611.648 | K97: 5650.182
A98: 매입채무 | C98: 420.452 | D98: 489.369 | E98: 429.872 | F98: 432.553 | G98: 461.559 | H98: 379.585 | I98: 400.595 | J98: 391.965 | K98: 489.369
A99: 단기차입금 | C99: 150.014 | D99: 149.984 | E99: 149.984 | F99: 449.984 | G99: 389.576 | H99: 210.084 | I99: 110.084 | J99: 222.551 | K99: 149.984
A100: 리스부채 | C100: 2.628 | D100: 2.628 | E100: 3.81 | F100: 3.81 | G100: 3.81 | I100: 4.337 | J100: 1.908 | K100: 2.628
A101: 미지급금 | C101: 25.939 | D101: 14.461 | E101: 38.275 | F101: 17.472 | G101: 97.371 | J101: 28.562 | K101: 14.461
...

Sheet 섹터 데이터
A1: 9950 섹터·사업 데이터
A2: 2단계 보고서를 만들 때 모은 자료 · 월차 · 출처는 맨 오른쪽
A4: this quarter · q alone
A5: 항목 | B5: 값 | C5: 출처
A6: 매출 | B6: 21.15 | C6: 2단계 보고서 자료(회사 설명회 자료·공시)
A7: 영업이익 | B7: 0.96
A8: ordinary | B8: 1.02
A9: 순이익 | B9: 0.45
A10: EPS | B10: 15.39
A12: this quarter · q YoY base
A13: 항목 | B13: 값 | C13: 출처
A14: 매출 | B14: 19.84 | C14: 2단계 보고서 자료(회사 설명회 자료·공시)
A15: 영업이익 | B15: 0.59
A16: ordinary | B16: 1
A17: 순이익 | B17: 0.55
A19: this quarter · 상반기
A20: 항목 | B20: 값 | C20: 출처
A21: 영업이익 매출 | B21: 46.13 | C21: 2단계 보고서 자료(회사 설명회 자료·공시)
A22: 매출 | B22: 41.24
A23: gp | B23: 16.95
A24: royalty | B24: 4.89
A25: 영업이익 gross | B25: 21.85
A26: sga | B26: 20.83
A27: 영업이익 | B27: 1.01
A28: ordinary | B28: 2.43
A29: 순이익 | B29: 1.4
A30: EPS | B30: 47.73
A32: this quarter · 상반기 직전
A33: 항목 | B33: 값 | C33: 출처
A34: 영업이익 매출 | B34: 43.07 | C34: 2단계 보고서 자료(회사 설명회 자료·공시)
A35: 매출 | B35: 38.47
A36: gp | B36: 14.93
A37: royalty | B37: 4.6
A38: 영업이익 gross | B38: 19.53
A39: sga | B39: 18.83
A40: 영업이익 | B40: 0.7
A41: ordinary | B41: 2.45
A42: 순이익 | B42: 1.5
A43: EPS | B43: 51.17
A45: market
A46: 항목 | B46: 값 | C46: 출처
A47: 가격 | B47: 3305 | C47: 주가는 결산 발표(10-30 16:00) 전 종가. 발표 뒤 반응은 아직 없음
A48: shares issued | B48: 3068111
A49: treasury | B49: 119048
A50: shares out | B50: 2949063
A51: mcap | B51: 97.5
A52: PER 가이던스 | B52: 50.7
A53: dps | B53: 20
A54: div yield | B54: 0.61
A55: PBR | B55: 2.43
A56: bps | B56: 1358
A58: 비교 기업 · fc EPS latest
A59: 항목 | B59: 값 | C59: 출처
A60: 7611 | B60: 124.99 | C60: 모두 jp_guidance history quarterly(분기 단독 계산). 히다카야·야마오카야는 개별 기준. 하치방 분기 YoY는 위 quarterly 에서.
A61: 9936 | B61: 111.54
A62: 3399 | B62: 184.3
A63: 9279 | B63: 75.32

Sheet 출처
A1: 출처 · 쓴 결산단신
A3: 공시일 | B3: 문서 | C3: PDF
A4: 2026-10-30 | B4: 2027년 3월 결산기 ２분기 결산단신 | C4: https://www2.jpx.co.jp/disc/99500/140120261030560585.pdf
A5: 2026-07-31 | B5: 2027년 3월 결산기 １분기 결산단신 | C5: https://www2.jpx.co.jp/disc/99500/140120260731505543.pdf
A6: 2026-05-01 | B6: 2026년 3월 결산기 연간 결산단신 | C6: https://www2.jpx.co.jp/disc/99500/140120260501516029.pdf
A7: 2026-01-30 | B7: 2026년 3월 결산기 ３분기 결산단신 | C7: https://www2.jpx.co.jp/disc/99500/140120260130542562.pdf
A8: 2025-10-31 | B8: 2026년 3월 결산기 ２분기 결산단신 | C8: https://www2.jpx.co.jp/disc/99500/140120251031584029.pdf
A9: 2025-07-31 | B9: 2026년 3월 결산기 １분기 결산단신 | C9: https://www2.jpx.co.jp/disc/99500/140120250731524924.pdf
A10: 2025-04-30 | B10: 2025년 3월 결산기 연간 결산단신 | C10: https://www2.jpx.co.jp/disc/99500/140120250430527253.pdf
A11: 2025-01-31 | B11: 2025년 3월 결산기 ３분기 결산단신 | C11: https://www2.jpx.co.jp/disc/99500/140120250131559802.pdf
A12: 2024-10-31 | B12: 2025년 3월 결산기 ２분기 결산단신 | C12: https://www2.jpx.co.jp/disc/99500/140120241031507229.pdf
A13: 2024-07-31 | B13: 2025년 3월 결산기 １분기 결산단신 | C13: https://www2.jpx.co.jp/disc/99500/140120240731558675.pdf
A14: 2024-05-01 | B14: 2024년 3월 결산기 연간 결산단신 | C14: https://www2.jpx.co.jp/disc/99500/140120240501580565.pdf
... A24: 2018-04-27 | B24: 연간 결산단신 | C24: https://www2.jpx.co.jp/disc/99500/140120180426422092.pdf

Sheet 재무제표 한눈에 보기
A1: 9950 재무제표 한눈에 보기 — 최근 40개 분기(달력 분기, 3Q26 = 26.7~9) · 단위 억 엔
A2: 출처: 매출·영업이익 결산단신 XBRL · 재무상태표 등 결산단신 XBRL 36건(2018-01-29~2026-10-30). 부문·지역·수주·수출은 있을 때만(출처는 줄 끝). 총 차입금 = 이자 붙는 부채 전부(단기·장기 차입금, CP, 사채·전환사채, 리스부채)
A4: 항목 | B4: 2Q17 | C4: 3Q17 | D4: 4Q17 | E4: 1Q18 | F4: 2Q18 | G4: 3Q18 | H4: 4Q18 | I4: 1Q19 | J4: 2Q19 | K4: 3Q19 | L4: 4Q19 | M4: 1Q20 | N4: 2Q20 | O4: 3Q20 | P4: 4Q20 | Q4: 1Q21 | R4: 2Q21 | S4: 3Q21 | T4: 4Q21 | U4: 1Q22 | V4: 2Q22 | W4: 3Q22 | X4: 4Q22 | Y4: 1Q23 | Z4: 2Q23 | AA4: 3Q23 | AB4: 4Q23 | AC4: 1Q24 | AD4: 2Q24 | AE4: 3Q24 | AF4: 4Q24 | AG4: 1Q25 | AH4: 2Q25 | AI4: 3Q25 | AJ4: 4Q25 | AK4: 1Q26 | AL4: 2Q26 | AM4: 3Q26 | AN4: 4Q26 | AO4: 1Q27 | AP4: 출처
A5: 매출액 | B5: 17.5 | C5: 19.6 | D5: 17.5 | E5: 12.9 | F5: 18.7 | G5: 21.1 | H5: 19.4 | I5: 11.4 | J5: 18.8 | K5: 21.5 | L5: 19.2 | M5: 17.3 | N5: 10.3 | O5: 14.4 | P5: 16 | Q5: 35.8 | R5: 12.3 | S5: 13.9 | T5: 14.7 | U5: 12.2 | V5: 15.5 | W5: 16.8 | X5: 16.7 | Y5: 5 | Z5: 17 | AA5: 18.5 | AB5: 17.2 | AC5: 11.6 | AD5: 18.6 | AE5: 19.8 | AF5: 17.9 | AG5: 12.1 | AH5: 18.6 | AI5: 19.8 | AJ5: 19.4 | AK5: 16 | AL5: 20.1 | AM5: 21.2
A6: 매출액 YoY | F6: 6.9 | G6: 7.7 | H6: 10.9 | I6: -11.6 | J6: 0.5 | K6: 1.9 | L6: -1 | M6: 51.8 | N6: -45.2 | O6: -33 | P6: -16.7 | Q6: 106.9 | R6: 19.4 | S6: -3.5 | T6: -8.1 | U6: -65.9 | V6: 26 | W6: 20.9 | X6: 13.6 | Y6: -59 | Z6: 9.7 | AA6: 10.1 | AB6: 3 | AC6: 132 | AD6: 9.4 | AE6: 7 | AF6: 4.1 | AG6: 4.3 | AH6: 0 | AI6: 0 | AJ6: 8.4 | AK6: 32.2 | AL6: 8.1 | AM6: 7.1
A7: 영업이익 | B7: 0.8 | C7: 1.4 | D7: 0.7 | E7: 1.3 | F7: 0.4 | G7: 1.7 | H7: 1 | I7: -0.1 | J7: 0.9 | K7: 1.6 | L7: 0.5 | M7: -0.1 | N7: -3.6 | O7: -1 | P7: -0.2 | Q7: 6.8 | R7: -1.5 | S7: -0.7 | T7: 0 | U7: -4.2 | V7: 0.4 | W7: 0.8 | X7: 0.5 | Y7: -5.1 | Z7: 1.1 | AA7: 1.4 | AB7: 0.6 | AC7: -1.5 | AD7: 0.9 | AE7: 1.8 | AF7: 0.5 | AG7: -0.9 | AH7: 0.1 | AI7: 0.6 | AJ7: -0.3 | AK7: 2.2 | AL7: 0.1 | AM7: 1
A8: 영업이익률 | B8: 4.6 | C8: 7.1 | D8: 4 | E8: 10.1 | F8: 2.1 | G8: 8.1 | H8: 5.2 | I8: -0.9 | J8: 4.8 | K8: 7.4 | L8: 2.6 | M8: -0.6 | N8: -35 | O8: -6.9 | P8: -1.2 | Q8: 19 | R8: -12.2 | S8: -5 | T8: 0 | U8: -34.4 | V8: 2.6 | W8: 4.8 | X8: 3 | Y8: -102 | Z8: 6.5 | AA8: 7.6 | AB8: 3.5 | AC8: -12.9 | AD8: 4.8 | AE8: 9.1 | AF8: 2.8 | AG8: -7.4 | AH8: 0.5 | AI8: 3 | AJ8: -1.5 | AK8: 13.8 | AL8: 0.5 | AM8: 4.7
A9: 영업이익 YoY | F9: -50 | G9: 21.4 | H9: 42.9 | I9: -107.7 | J9: 125 | K9: -5.9 | L9: -50 | N9: -500 | O9: -162.5 | P9: -140 | U9: -161.8 | Z9: 175 | AA9: 75 | AB9: 20 | AD9: -18.2 | AE9: 28.6 | AF9: -16.7 | AH9: -88.9 | AI9: -66.7 | AJ9: -160 | AL9: 0 | AM9: 66.7
A10: 유동자산 | B10: 14.5 | E10: 14.9 | F10: 15.2 | G10: 18.1 | H10: 17.4 | I10: 17.9 | J10: 17.1 | K10: 19.6 | L10: 20 | M10: 20.6 | N10: 17.6 | O10: 18.3 | P10: 22.6 | Q10: 22.9 | R10: 21.3 | S10: 21.5 | T10: 20.8 | U10: 22.8 | V10: 21.8 | W10: 23.4 | X10: 23.6 | Y10: 19.6 | Z10: 18.5 | AA10: 20.8 | AB10: 20.5 | AC10: 20.3 | AD10: 26.1 | AE10: 26.1 | AF10: 23.7 | AG10: 21.6 | AH10: 20.7 | AI10: 21.4 | AJ10: 21.3 | AK10: 19.1 | AL10: 18 | AM10: 22 | AN10: 31.2
A11: 유동부채 | B11: 11.3 | E11: 7.9 | F11: 7.6 | G11: 11.3 | H11: 8.9 | I11: 8.6 | J11: 8.1 | K11: 9.9 | L11: 9.6 | M11: 9.4 | N11: 8.3 | O11: 12.5 | P11: 13 | Q11: 13.5 | R11: 12.7 | S11: 13.2 | T11: 12.2 | U11: 13.9 | V11: 13.5 | W11: 14.7 | X11: 14.5 | Y11: 11.3 | Z11: 9.8 | AA11: 10.7 | AB11: 9.8 | AC11: 10.1 | AD11: 15 | AE11: 15.2 | AF11: 13.4 | AG11: 11.4 | AH11: 11.7 | AI11: 12.7 | AJ11: 11.8 | AK11: 11.7 | AL11: 11.6 | AM11: 15.4 | AN11: 15.1
A12: 부채총계 | B12: 15.4 | E12: 11.7 | F12: 11.3 | G12: 13.7 | H12: 11.4 | I12: 11 | J12: 10.5 | K12: 12.2 | L12: 12 | M12: 11.8 | N12: 10.9 | O12: 15.2 | P12: 20.2 | Q12: 20.4 | R12: 19.4 | S12: 19.7 | T12: 18.5 | U12: 20 | V12: 19.3 | W12: 20.3 | X12: 19.8 | Y12: 16.4 | Z12: 14.7 | AA12: 15.4 | AB12: 14.3 | AC12: 14.4 | AD12: 23.8 | AE12: 23.3 | AF12: 21 | AG12: 18.7 | AH12: 18.8 | AI12: 19.5 | AJ12: 18.8 | AK12: 18.4 | AL12: 18 | AM12: 21.6 | AN12: 30.3
A13: 자기자본 | B13: 34.6 | E13: 40.7 | F13: 40.5 | G13: 41.1 | H13: 42.3 | I13: 42.5 | J13: 42.1 | K13: 42.8 | L13: 43.3 | M13: 43.5 | N13: 41 | O13: 38.4 | P13: 36.9 | Q13: 36.5 | R13: 33.9 | S13: 33 | T13: 32.9 | U13: 32.5 | V13: 31.6 | W13: 32.1 | X13: 33 | Y13: 32.8 | Z13: 32.2 | AA13: 33.8 | AB13: 35 | AC13: 34.4 | AD13: 33.8 | AE13: 35.1 | AF13: 37 | AG13: 37.4 | AH13: 36.7 | AI13: 37.2 | AJ13: 38.1 | AK13: 38.1 | AL13: 38.1 | AM13: 38.8 | AN13: 40.1
A14: 유동비율 | B14: 128.3 | E14: 188.6 | F14: 200 | G14: 160.2 | H14: 195.5 | I14: 208.1 | J14: 211.1 | K14: 198 | L14: 208.3 | M14: 219.1 | N14: 212 | O14: 146.4 | P14: 173.8 | Q14: 169.6 | R14: 167.7 | S14: 162.9 | T14: 170.5 | U14: 164 | V14: 161.5 | W14: 159.2 | X14: 162.8 | Y14: 173.5 | Z14: 188.8 | AA14: 194.4 | AB14: 209.2 | AC14: 201 | AD14: 174 | AE14: 171.7 | AF14: 176.9 | AG14: 189.5 | AH14: 176.9 | AI14: 168.5 | AJ14: 180.5 | AK14: 163.2 | AL14: 155.2 | AM14: 142.9 | AN14: 206.6
A15: 부채비율 | B15: 44.5 | E15: 28.7 | F15: 27.9 | G15: 33.3 | H15: 27 | I15: 25.9 | J15: 24.9 | K15: 28.5 | L15: 27.7 | M15: 27.1 | N15: 26.6 | O15: 39.6 | P15: 54.7 | Q15: 55.9 | R15: 57.2 | S15: 59.7 | T15: 56.2 | U15: 61.5 | V15: 61.1 | W15: 63.2 | X15: 60 | Y15: 50 | Z15: 45.7 | AA15: 45.6 | AB15: 40.9 | AC15: 41.9 | AD15: 70.4 | AE15: 66.4 | AF15: 56.8 | AG15: 50 | AH15: 51.2 | AI15: 52.4 | AJ15: 49.3 | AK15: 48.3 | AL15: 47.2 | AM15: 55.7 | AN15: 75.6
A16: 순차입금/자기자본 | B16: -18.5 | E16: -14.3 | F16: -19.3 | G16: -17.8 | H16: -20.3 | I16: -20.5 | J16: -24.2 | K16: -24.1 | L16: -25.6 | M16: -26.2 | N16: -25.9 | O16: -12.8 | P16: -9.8 | Q16: -7.1 | R16: -9.4 | S16: -9.4 | T16: -8.5 | U16: -13.5 | V16: -13.9 | W16: -13.4 | X16: -13.6 | Y16: -14.3 | Z16: -17.1 | AA16: -18.3 | AB16: -22.6 | AC16: -19.5 | AD16: -21 | AE16: -10.5 | AF16: -11.9 | AG16: -6.4 | AH16: -10.9 | AI16: -6.2 | AJ16: -8.7 | AK16: -2.1 | AL16: -5.2 | AM16: -3.9 | AN16: -5.2
A17: 재고자산 | B17: 0.9 | E17: 1.1 | F17: 1 | G17: 1.3 | H17: 1.1 | I17: 1.5 | J17: 1.2 | K17: 1.5 | L17: 1.3 | M17: 1.4 | N17: 1.3 | O17: 1.6 | P17: 1.5 | Q17: 1.6 | R17: 1.7 | S17: 1.8 | T17: 1.6 | U17: 1.9 | V17: 1.7 | W17: 2 | X17: 1.7 | Y17: 2.2 | Z17: 1.9 | AA17: 2 | AB17: 1.8 | AC17: 2.5 | AD17: 1.9 | AE17: 1.9 | AF17: 2.2 | AG17: 2.4 | AH17: 2.3 | AI17: 2.2 | AJ17: 2.2 | AK17: 2.3 | AL17: 2.2 | AM17: 2.4 | AN17: 2.6
A18: 재고자산 회전일수 | B18: 9 | E18: 16 | F18: 9 | G18: 11 | H18: 10 | I18: 24 | J18: 11 | K18: 12 | L18: 12 | M18: 14 | N18: 17 | O18: 17 | P18: 15 | Q18: 9 | R18: 20 | S18: 20 | T18: 17 | U18: 23 | V18: 17 | W18: 19 | X18: 16 | Y18: 46 | Z18: 18 | AA18: 16 | AB18: 16 | AC18: 37 | AD18: 15 | AE18: 15 | AF18: 19 | AG18: 30 | AH18: 18 | AI18: 17 | AJ18: 17 | AK18: 22 | AL18: 17 | AM18: 18
A19: 매출채권 회전일수 | B19: 21 | E19: 36 | F19: 19 | G19: 23 | H19: 27 | I19: 47 | J19: 21 | K19: 24 | L19: 28 | M19: 33 | N19: 42 | O19: 32 | P19: 30 | Q19: 17 | R19: 33 | S19: 32 | T19: 32 | U19: 44 | V19: 28 | W19: 35 | X19: 40 | Y19: 124 | Z19: 35 | AA19: 34 | AB19: 37 | AC19: 56 | AD19: 30 | AE19: 40 | AF19: 39 | AG19: 60 | AH19: 34 | AI19: 39 | AJ19: 39 | AK19: 55 | AL19: 36 | AM19: 41
A20: 매입채무 회전일수 | B20: 24 | E20: 45 | F20: 23 | G20: 26 | H20: 31 | I20: 60 | J20: 27 | K20: 27 | L20: 32 | M20: 36 | N20: 35 | O20: 27 | P20: 27 | Q20: 18 | R20: 28 | S20: 26 | T20: 24 | U20: 41 | V20: 25 | W20: 29 | X20: 29 | Y20: 79 | Z20: 29 | AA20: 26 | AB20: 32 | AC20: 60 | AD20: 28 | AE20: 32 | AF20: 35 | AG20: 48 | AH20: 30 | AI20: 32 | AJ20: 33 | AK20: 46 | AL20: 33 | AM20: 32
A21: 현금전환주기(CCC) | B21: 6 | E21: 7 | F21: 5 | G21: 8 | H21: 6 | I21: 11 | J21: 5 | K21: 9 | L21: 8 | M21: 11 | N21: 24 | O21: 22 | P21: 18 | Q21: 8 | R21: 25 | S21: 26 | T21: 25 | U21: 26 | V21: 20 | W21: 25 | X21: 27 | Y21: 91 | Z21: 24 | AA21: 24 | AB21: 21 | AC21: 33 | AD21: 17 | AE21: 23 | AF21: 23 | AG21: 42 | AH21: 22 | AI21: 24 | AJ21: 23 | AK21: 31 | AL21: 20 | AM21: 27
A22: 총 차입금 | B22: 1.1 | E22: 0.5 | F22: 0.4 | G22: 0.2 | H22: 0 | I22: 0 | J22: 0 | K22: 0 | L22: 0 | M22: 0 | N22: 0 | O22: 5 | P22: 10 | Q22: 10 | R22: 9.9 | S22: 9.7 | T22: 9.4 | U22: 9.1 | V22: 8.8 | W22: 8.6 | X22: 8.3 | Y22: 4 | Z22: 2.7 | AA22: 2.5 | AB22: 2.2 | AC22: 2 | AD22: 8.7 | AE22: 8.1 | AF22: 7.5 | AG22: 6.7 | AH22: 6.1 | AI22: 5.7 | AJ22: 5.5 | AK22: 5.1 | AL22: 4.8 | AM22: 7.4 | AN22: 16
A23: 현금 | B23: 7.5 | E23: 6.3 | F23: 8.2 | G23: 7.5 | H23: 8.6 | I23: 8.7 | J23: 10.2 | K23: 10.3 | L23: 11.1 | M23: 11.4 | N23: 10.6 | O23: 9.9 | P23: 13.6 | Q23: 12.6 | R23: 13.1 | S23: 12.8 | T23: 12.2 | U23: 13.5 | V23: 13.2 | W23: 12.9 | X23: 12.8 | Y23: 8.7 | Z23: 8.2 | AA23: 8.7 | AB23: 10.1 | AC23: 8.7 | AD23: 15.8 | AE23: 11.8 | AF23: 11.9 | AG23: 9.1 | AH23: 10.1 | AI23: 8 | AJ23: 8.8 | AK23: 5.9 | AL23: 6.8 | AM23: 8.9 | AN23: 18.1
A24: 부문별 매출 · 外食事業、報告セグメント [メンバー] | AB24: 14.7 | AF24: 15.1 | AG24: 10.2 | AJ24: 16.2 | AK24: 12.9 | AP24: 결산단신 부문 정보(외부 고객 매출)
A25: 부문별 매출 · 海外事業、報告セグメント [メンバー] | AB25: 2.8 | AD25: 3.1 | AE25: 3.5 | AF25: 3.4 | AG25: 1.5 | AH25: 3.5 | AI25: 3.6 | AJ25: 3.9 | AK25: 3.4 | AL25: 4.1 | AM25: 3.7 | AP25: 결산단신 부문 정보(외부 고객 매출)
